Workbook

Sheet Calibración-UTCUTS_Osemosys
B1: Referencia | F1: Ecuador | G1: 2008 | H1: 2009 | I1: 2010 | J1: 2011 | K1: 2012 | L1: 2013 | M1: 2014 | N1: 2015 | O1: 2016 | P1: 2017 | Q1: 2018 | R1: 2019 | S1: 2020 | T1: 2021 | U1: 2022 | V1: 2023 | W1: 2024 | X1: 2025 | Y1: 2026 | Z1: 2027 | AA1: 2028 | AB1: 2029 | AC1: 2030 | AD1: 2031 | AE1: 2032 | AF1: 2033 | AG1: 2034 | AH1: 2035 | AI1: 2036 | AJ1: 2037 | AK1: 2038 | AL1: 2039 | AM1: 2040 | AN1: 2041 | AO1: 2042 | AP1: 2043 | AQ1: 2044 | AR1: 2045 | AS1: 2046 | AT1: 2047 | AU1: 2048 | AV1: 2049 | AW1: 2050
D3: DATOS PARA CALIBRAR PROYECCIONES
E6: GRÁFICO UTCUTS-1 | F6: TABLA UTCUTS - 1: Cobertura uso de suelos
F7: Uso de suelos [ha]
B8: ESPAC | F8: Montes y bosques [ha] | I8: 3504127 | J8: 3536454 | K8: 3583056 | L8: 3538424 | M8: 5758859 | N8: 5729799 | O8: 5773290 | P8: 5675402 | Q8: 5740641 | R8: 6040896 | S8: 6112324 | T8: 5900560 | U8: 5900560 | V8: 5900560 | W8: 5900560 | X8: 5900560 | Y8: 5900560 | Z8: 5900560 | AA8: 5900560 | AB8: 5900560 | AC8: 5900560 | AD8: 5900560 | AE8: 5900560 | AF8: 5900560 | AG8: 5900560 | AH8: 5900560 | AI8: 5900560 | AJ8: 5900560 | AK8: 5900560 | AL8: 5900560 | AM8: 5900560 | AN8: 5900560 | AO8: 5900560 | AP8: 5900560 | AQ8: 5900560 | AR8: 5900560 | AS8: 5900560 | AT8: 5900560 | AU8: 5900560 | AV8: 5900560 | AW8: 5900560
F9: Cultivos permanentes [ha] | I9: 1391379 | J9: 1379473 | K9: 1382918 | L9: 1469363 | M9: 1417104 | N9: 1483366 | O9: 1439117 | P9: 1430497 | Q9: 1385805 | R9: 1439504 | S9: 1442973 | T9: 1423372 | U9: 1423372 | V9: 1423372 | W9: 1423372 | X9: 1423372 | Y9: 1423372 | Z9: 1423372 | AA9: 1423372 | AB9: 1423372 | AC9: 1423372 | AD9: 1423372 | AE9: 1423372 | AF9: 1423372 | AG9: 1423372 | AH9: 1423372 | AI9: 1423372 | AJ9: 1423372 | AK9: 1423372 | AL9: 1423372 | AM9: 1423372 | AN9: 1423372 | AO9: 1423372 | AP9: 1423372 | AQ9: 1423372 | AR9: 1423372 | AS9: 1423372 | AT9: 1423372 | AU9: 1423372 | AV9: 1423372 | AW9: 1423372
F10: Cultivos transitorios y barbechos [ha] | I10: 992369 | J10: 982312 | K10: 1020870 | L10: 1003271 | M10: 876498 | N10: 950649 | O10: 849685 | P10: 904224 | Q10: 799494 | R10: 769708 | S10: 822516 | T10: 841994 | U10: 841994 | V10: 841994 | W10: 841994 | X10: 841994 | Y10: 841994 | Z10: 841994 | AA10: 841994 | AB10: 841994 | AC10: 841994 | AD10: 841994 | AE10: 841994 | AF10: 841994 | AG10: 841994 | AH10: 841994 | AI10: 841994 | AJ10: 841994 | AK10: 841994 | AL10: 841994 | AM10: 841994 | AN10: 841994 | AO10: 841994 | AP10: 841994 | AQ10: 841994 | AR10: 841994 | AS10: 841994 | AT10: 841994 | AU10: 841994 | AV10: 841994 | AW10: 841994
F11: Descanso [ha] | I11: 193957 | J11: 173442 | K11: 126982 | L11: 191159 | M11: 93574 | N11: 117390 | O11: 125946 | P11: 129268 | Q11: 168446 | R11: 219492 | S11: 215014 | T11: 163017 | U11: 163017 | V11: 163017 | W11: 163017 | X11: 163017 | Y11: 163017 | Z11: 163017 | AA11: 163017 | AB11: 163017 | AC11: 163017 | AD11: 163017 | AE11: 163017 | AF11: 163017 | AG11: 163017 | AH11: 163017 | AI11: 163017 | AJ11: 163017 | AK11: 163017 | AL11: 163017 | AM11: 163017 | AN11: 163017 | AO11: 163017 | AP11: 163017 | AQ11: 163017 | AR11: 163017 | AS11: 163017 | AT11: 163017 | AU11: 163017 | AV11: 163017 | AW11: 163017
F12: Otros usos [ha] | I12: 217058 | J12: 210584 | K12: 205657 | L12: 216225 | M12: 468180 | N12: 612090 | O12: 719109 | P12: 757791 | Q12: 796518 | R12: 662305 | S12: 681476 | T12: 712757 | U12: 712757 | V12: 712757 | W12: 712757 | X12: 712757 | Y12: 712757 | Z12: 712757 | AA12: 712757 | AB12: 712757 | AC12: 712757 | AD12: 712757 | AE12: 712757 | AF12: 712757 | AG12: 712757 | AH12: 712757 | AI12: 712757 | AJ12: 712757 | AK12: 712757 | AL12: 712757 | AM12: 712757 | AN12: 712757 | AO12: 712757 | AP12: 712757 | AQ12: 712757 | AR12: 712757 | AS12: 712757 | AT12: 712757 | AU12: 712757 | AV12: 712757 | AW12: 712757
F13: Páramos [ha] | I13: 539475 | J13: 565857 | K13: 608272 | L13: 491891 | M13: 499258 | N13: 454347 | O13: 377791 | P13: 332418 | Q13: 252612 | R13: 270986 | S13: 249139 | T13: 233074 | U13: 233074 | V13: 233074 | W13: 233074 | X13: 233074 | Y13: 233074 | Z13: 233074 | AA13: 233074 | AB13: 233074 | AC13: 233074 | AD13: 233074 | AE13: 233074 | AF13: 233074 | AG13: 233074 | AH13: 233074 | AI13: 233074 | AJ13: 233074 | AK13: 233074 | AL13: 233074 | AM13: 233074 | AN13: 233074 | AO13: 233074 | AP13: 233074 | AQ13: 233074 | AR13: 233074 | AS13: 233074 | AT13: 233074 | AU13: 233074 | AV13: 233074 | AW13: 233074
F14: Pastos cultivados [ha] | I14: 3409952 | J14: 3425412 | K14: 3553008 | L14: 3227321 | M14: 2259447 | N14: 2531442 | O14: 2300539 | P14: 2447634 | Q14: 2379042 | R14: 1985494 | S14: 2067795 | T14: 2376551 | U14: 2376551 | V14: 2376551 | W14: 2376551 | X14: 2376551 | Y14: 2376551 | Z14: 2376551 | AA14: 2376551 | AB14: 2376551 | AC14: 2376551 | AD14: 2376551 | AE14: 2376551 | AF14: 2376551 | AG14: 2376551 | AH14: 2376551 | AI14: 2376551 | AJ14: 2376551 | AK14: 2376551 | AL14: 2376551 | AM14: 2376551 | AN14: 2376551 | AO14: 2376551 | AP14: 2376551 | AQ14: 2376551 | AR14: 2376551 | AS14: 2376551 | AT14: 2376551 | AU14: 2376551 | AV14: 2376551 | AW14: 2376551
F15: Pastos permanentes [ha] | I15: 1509972 | J15: 1385547 | K15: 1423114 | L15: 1623359 | M15: 828333 | N15: 706777 | O15: 800496 | P15: 677911 | Q15: 715273 | R15: 915843 | S15: 841320 | T15: 646139 | U15: 646139 | V15: 646139 | W15: 646139 | X15: 646139 | Y15: 646139 | Z15: 646139 | AA15: 646139 | AB15: 646139 | AC15: 646139 | AD15: 646139 | AE15: 646139 | AF15: 646139 | AG15: 646139 | AH15: 646139 | AI15: 646139 | AJ15: 646139 | AK15: 646139 | AL15: 646139 | AM15: 646139 | AN15: 646139 | AO15: 646139 | AP15: 646139 | AQ15: 646139 | AR15: 646139 | AS15: 646139 | AT15: 646139 | AU15: 646139 | AV15: 646139 | AW15: 646139
F16: Uso de suelos [Mha]
B17: ESPAC | F17: Montes y bosques [Mha] | I17: =I8/1000000 -> 3.504127 | J17: =J8/1000000 -> 3.536454 | K17: =K8/1000000 -> 3.583056 | L17: =L8/1000000 -> 3.538424 | M17: =M8/1000000 -> 5.758859 | N17: =N8/1000000 -> 5.729799 | O17: =O8/1000000 -> 5.77329 | P17: =P8/1000000 -> 5.675402 | ... AW17: =AW8/1000000 -> 5.90056
F18: Cultivos permanentes [Mha] | I18: =I9/1000000 -> 1.391379 | J18: =J9/1000000 -> 1.379473 | K18: =K9/1000000 -> 1.382918 | L18: =L9/1000000 -> 1.469363 | M18: =M9/1000000 -> 1.417104 | N18: =N9/1000000 -> 1.483366 | O18: =O9/1000000 -> 1.439117 | P18: =P9/1000000 -> 1.430497 | ... AW18: =AW9/1000000 -> 1.423372
F19: Cultivos transitorios y barbechos [Mha] | I19: =I10/1000000 -> 0.992369 | J19: =J10/1000000 -> 0.982312 | K19: =K10/1000000 -> 1.02087 | L19: =L10/1000000 -> 1.003271 | M19: =M10/1000000 -> 0.876498 | N19: =N10/1000000 -> 0.950649 | O19: =O10/1000000 -> 0.849685 | P19: =P10/1000000 -> 0.904224 | ... AW19: =AW10/1000000 -> 0.841994
F20: Descanso [Mha] | I20: =I11/1000000 -> 0.193957 | J20: =J11/1000000 -> 0.173442 | K20: =K11/1000000 -> 0.126982 | L20: =L11/1000000 -> 0.191159 | M20: =M11/1000000 -> 0.093574 | N20: =N11/1000000 -> 0.11739 | O20: =O11/1000000 -> 0.125946 | P20: =P11/1000000 -> 0.129268 | ... AW20: =AW11/1000000 -> 0.163017
F21: Otros usos [Mha] | I21: =I12/1000000 -> 0.217058 | J21: =J12/1000000 -> 0.210584 | K21: =K12/1000000 -> 0.205657 | L21: =L12/1000000 -> 0.216225 | M21: =M12/1000000 -> 0.46818 | N21: =N12/1000000 -> 0.61209 | O21: =O12/1000000 -> 0.719109 | P21: =P12/1000000 -> 0.757791 | ... AW21: =AW12/1000000 -> 0.712757
F22: Páramos [Mha] | I22: =I13/1000000 -> 0.539475 | J22: =J13/1000000 -> 0.565857 | K22: =K13/1000000 -> 0.608272 | L22: =L13/1000000 -> 0.491891 | M22: =M13/1000000 -> 0.499258 | N22: =N13/1000000 -> 0.454347 | O22: =O13/1000000 -> 0.377791 | P22: =P13/1000000 -> 0.332418 | ... AW22: =AW13/1000000 -> 0.233074
F23: Pastos cultivados [Mha] | I23: =I14/1000000 -> 3.409952 | J23: =J14/1000000 -> 3.425412 | K23: =K14/1000000 -> 3.553008 | L23: =L14/1000000 -> 3.227321 | M23: =M14/1000000 -> 2.259447 | N23: =N14/1000000 -> 2.531442 | O23: =O14/1000000 -> 2.300539 | P23: =P14/1000000 -> 2.447634 | ... AW23: =AW14/1000000 -> 2.376551
F24: Pastos permanentes [Mha] | I24: =I15/1000000 -> 1.509972 | J24: =J15/1000000 -> 1.385547 | K24: =K15/1000000 -> 1.423114 | L24: =L15/1000000 -> 1.623359 | M24: =M15/1000000 -> 0.828333 | N24: =N15/1000000 -> 0.706777 | O24: =O15/1000000 -> 0.800496 | P24: =P15/1000000 -> 0.677911 | ... AW24: =AW15/1000000 -> 0.646139
F25: TOTAL COBERTURAS [Mha] | I25: =SUM(I17:I24) -> 11.758289 | J25: =SUM(J17:J24) -> 11.659081 | K25: =SUM(K17:K24) -> 11.903877 | L25: =SUM(L17:L24) -> 11.761013 | M25: =SUM(M17:M24) -> 12.201253 | N25: =SUM(N17:N24) -> 12.58586 | O25: =SUM(O17:O24) -> 12.385973 | P25: =SUM(P17:P24) -> 12.355145 | ... AW25: =SUM(AW17:AW24) -> 12.297464
D28: DATOS ÁREAS PROTEGIDAS
E31: GRÁFICO UTCUTS-1 | F31: TABLA UTCUTS - 2: Cobertura áreas protegidas
F32: Áreas protegidas [Mha]
B33: SNAP | F33: Galápagos [Mha] | I33: 0.79579217 | J33: 0.79579217 | K33: 0.79579217 | L33: 0.79579217 | M33: 0.79579217 | N33: 0.79579217 | O33: 0.79579217 | P33: 0.79579217 | Q33: 0.79579217 | R33: 0.79579217 | S33: 0.79579217 | T33: 0.79579217 | U33: 0.79579217 | V33: 0.79579217 | W33: 0.79579217 | X33: 0.79579217 | Y33: 0.79579217 | Z33: 0.79579217 | AA33: 0.79579217 | AB33: 0.79579217 | AC33: 0.79579217 | AD33: 0.79579217 | AE33: 0.79579217 | AF33: 0.79579217 | AG33: 0.79579217 | AH33: 0.79579217 | AI33: 0.79579217 | AJ33: 0.79579217 | AK33: 0.79579217 | AL33: 0.79579217 | AM33: 0.79579217 | AN33: 0.79579217 | AO33: 0.79579217 | AP33: 0.79579217 | AQ33: 0.79579217 | AR33: 0.79579217 | AS33: 0.79579217 | AT33: 0.79579217 | AU33: 0.79579217 | AV33: 0.79579217 | AW33: 0.79579217
F34: Bosques protegidos/Protected forest [Mha] | I34: 2.2633933 | J34: 2.2794224 | K34: 2.2794224 | L34: 2.2794224 | M34: 2.3725857 | N34: 2.3725857 | O34: 2.3747312 | P34: 2.3747312 | Q34: 2.4084734 | R34: 2.4088211 | S34: 2.4088211 | T34: 2.4117235 | U34: 2.4117235 | V34: 2.4117235 | W34: 2.4117235 | X34: 2.4117235 | Y34: 2.4117235 | Z34: 2.4117235 | AA34: 2.4117235 | AB34: 2.4117235 | AC34: 2.4117235 | AD34: 2.4117235 | AE34: 2.4117235 | AF34: 2.4117235 | AG34: 2.4117235 | AH34: 2.4117235 | AI34: 2.4117235 | AJ34: 2.4117235 | AK34: 2.4117235 | AL34: 2.4117235 | AM34: 2.4117235 | AN34: 2.4117235 | AO34: 2.4117235 | AP34: 2.4117235 | AQ34: 2.4117235 | AR34: 2.4117235 | AS34: 2.4117235 | AT34: 2.4117235 | AU34: 2.4117235 | AV34: 2.4117235 | AW34: 2.4117235
F35: Pradera protegida/Protected grassland [Mha] | I35: 1.8351789 | J35: 1.8351789 | K35: 1.838396 | L35: 1.838396 | M35: 1.838396 | N35: 1.838396 | O35: 1.838396 | P35: 1.8914899 | Q35: 1.8934445 | R35: 1.922489 | S35: 1.9272792 | T35: 1.95791 | U35: 1.95791 | V35: 1.95791 | W35: 1.95791 | X35: 1.95791 | Y35: 1.95791 | Z35: 1.95791 | AA35: 1.95791 | AB35: 1.95791 | AC35: 1.95791 | AD35: 1.95791 | AE35: 1.95791 | AF35: 1.95791 | AG35: 1.95791 | AH35: 1.95791 | AI35: 1.95791 | AJ35: 1.95791 | AK35: 1.95791 | AL35: 1.95791 | AM35: 1.95791 | AN35: 1.95791 | AO35: 1.95791 | AP35: 1.95791 | AQ35: 1.95791 | AR35: 1.95791 | AS35: 1.95791 | AT35: 1.95791 | AU35: 1.95791 | AV35: 1.95791 | AW35: 1.95791
F36: Manglares [Mha] | I36: 0.37320953 | J36: 0.37568766 | K36: 0.38884296 | L36: 0.38884296 | M36: 0.38884296 | N36: 0.53110941 | O36: 0.57106191 | P36: 0.57106191 | Q36: 0.57106191 | R36: 0.57106191 | S36: 0.57106191 | T36: 0.57106191 | U36: 0.57106191 | V36: 0.57106191 | W36: 0.57106191 | X36: 0.57106191 | Y36: 0.57106191 | Z36: 0.57106191 | AA36: 0.57106191 | AB36: 0.57106191 | AC36: 0.57106191 | AD36: 0.57106191 | AE36: 0.57106191 | AF36: 0.57106191 | AG36: 0.57106191 | AH36: 0.57106191 | AI36: 0.57106191 | AJ36: 0.57106191 | AK36: 0.57106191 | AL36: 0.57106191 | AM36: 0.57106191 | AN36: 0.57106191 | AO36: 0.57106191 | AP36: 0.57106191 | AQ36: 0.57106191 | AR36: 0.57106191 | AS36: 0.57106191 | AT36: 0.57106191 | AU36: 0.57106191 | AV36: 0.57106191 | AW36: 0.57106191
D39: DATOS PARA MODELO OSEMOSYS
A41: Drivers
E42: GRÁFICO UTCUTS-1 | F42: TABLA UTCUTS - 3: Coberturas generales - MAG + MAATE
F43: Coberturas generales [ha]
B44: MAG+MAATE | D44: Bosque | F44: Bosque nativo [ha] | G44: 13038367 | M44: 12753387 | O44: 12631198 | Q44: 12514340
F45: Plantación forestal [ha] | G45: 62196.93 | M45: 130072.41 | O45: 123719.94 | Q45: 121995.27
D46: Tierra agropecuaria | F46: Cultivo anual [ha] | G46: 611941.95 | M46: 1094904.6 | O46: 8933864.5 | Q46: 8999553.2
F47: Cultivo semipermanente [ha] | G47: 260389.08 | M47: 480131.91
F48: Cultivo permanente [ha] | G48: 167305.59 | M48: 917407.35
F49: Pastizal [ha] | G49: 1454890.3 | M49: 4959938.7
F50: Mosaico agropecuario [ha] | G50: 6337045.3 | M50: 1266774.3
D51: Vegetación arbustiva | F51: Vegetación arbustiva [ha] | G51: 587499.84 | M51: 810626.94 | O51: 763180.11 | Q51: 768908.61
F52: Vegetación herbácea [ha] | G52: 109528.02 | M52: 89167.14 | O52: 83035.17 | Q52: 85768.2
F53: Páramo [ha] | G53: 1465935.8 | M53: 1523970.1 | O53: 1515272.5 | Q53: 1521159.7
D54: Cuerpo de agua | F54: Cuerpo de agua natural [ha] | G54: 348472.62 | M54: 305169.39 | O54: 295476.12 | Q54: 291292.2
F55: Cuerpo de agua artificial [ha] | G55: 157677.57 | M55: 199934.1 | O55: 199287.27 | Q55: 200705.67
D56: Zona antrópica | F56: Área poblada [ha] | G56: 165538.44 | M56: 224935.38 | O56: 229182.39 | Q56: 255251.97
F57: Infraestructura [ha] | G57: 11615.85 | M57: 21206.79 | O57: 23884.2 | Q57: 30656.25
D58: Otras tierras | F58: Área sin cobertura vegetal [ha] | G58: 109686.69 | M58: 112568.04 | O58: 93841.92 | Q58: 102446.37
F59: Glaciar [ha] | G59: 9968.49 | M59: 7865.73 | O59: 6279.21 | Q59: 6144.03
F60: Sin información [ha] | G60: 0 | M60: 0 | O60: 0 | Q60: 0
F61: TOTAL COBERTURAS [ha] | G61: =SUM(G44:G60) -> 24898060 | M61: =SUM(M44:M60) -> 24898060 | O61: =SUM(O44:O60) -> 24898221 | Q61: =SUM(Q44:Q60) -> 24898221
F62: Coberturas generales [Mha]
C63: Leyendas usadas en INGEI 2018 (NIVEL I IPCC) | D63: Leyendas usadas por MAATE en los mapas interactivos y reportes de deforestacion (Nivel I IPCC) | F63: Niveles para OSEMOSYS
A64: Tasa de deforestación neta 2018 (-0.46%) | B64: MAG+MAATE | C64: Tierras forestales | D64: Bosque | F64: Bosque nativo [Mha] | G64: =G44/1000000 -> 13.038367 | M64: =M44/1000000 -> 12.753387 | O64: =O44/1000000 -> 12.631198 | Q64: =Q44/1000000 -> 12.51434 | R64: =Q64*(1-0.0046) -> 12.456774 | S64: =R64*(1-0.0046) -> 12.399472 | T64: =S64*(1-0.0046) -> 12.342435 | U64: =T64*(1-0.0046) -> 12.28566 | V64: =U64*(1-0.0046) -> 12.229146 | W64: =V64*(1-0.0046) -> 12.172892 | X64: =W64*(1-0.0046) -> 12.116896 | Y64: =X64*(1-0.0046) -> 12.061159 | ... AW64: =AV64*(1-0.0046) -> 10.797726
A65: 10% mas que el crecimiento poblacional segun la planeacion estrategica de plantaciones forestales 2012 | F65: Plantación forestal [Mha] | G65: =G45/1000000 -> 0.06219693 | M65: =M45/1000000 -> 0.13007241 | O65: =O45/1000000 -> 0.12371994 | Q65: =Q45/1000000 -> 0.12199527 | R65: =Q65*(1+(#REF!+5/100)) -> #REF! | S65: =R65*(1+(#REF!+5/100)) -> #REF! | T65: =S65*(1+(#REF!+5/100)) -> #REF! | U65: =T65*(1+(#REF!+5/100)) -> #REF! | V65: =U65*(1+(#REF!+5/100)) -> #REF! | W65: =V65*(1+(#REF!+5/100)) -> #REF! | X65: =W65*(1+(#REF!+5/100)) -> #REF! | Y65: =X65*(1+(#REF!+5/100)) -> #REF! | ... AW65: =AV65*(1+(#REF!+5/100)) -> #REF!
C66: Tierra de cultivo | D66: Tierra agropecuaria | F66: Cultivos [Mha] | G66: 7.376682 | M66: 3.7592182 | O66: 3.85228 | Q66: 3.880607
F70: Pastura [Mha] | G70: =G49/1000000 -> 1.4548903 | M70: =M49/1000000 -> 4.9599387 | O70: 5.08158 | Q70: 5.118945
C71: Pastizales (grasslands) | D71: Vegetación arbustiva y herbácea (incluye páramo) | F71: Pastizales (grasslands) [Mha] | G71: 2.1629637 | M71: 2.4237642 | O71: 2.3614878 | Q71: 2.3758365
C74: Humedal | D74: Cuerpo de agua/humedal | F74: Humedal [Mha] | G74: 0.50615019 | M74: 0.50510349 | O74: 0.49476339 | Q74: 0.49199787
C76: Asentamientos | D76: Zona antrópica | F76: Asentamientos [Mha] | G76: 0.17715429 | M76: 0.24614217 | O76: 0.25306659 | Q76: 0.28590822
C78: Otras tierras | D78: Otras tierras | F78: Otras tierras [Mha] | G78: 0.11965518 | M78: 0.12043377 | O78: 0.10012113 | Q78: 0.1085904
F81: TOTAL COBERTURAS [Mha] | G81: =SUM(G64:G80) -> 24.89806 | M81: =SUM(M64:M80) -> 24.89806 | O81: =SUM(O64:O80) -> 24.898217 | Q81: =SUM(Q64:Q80) -> 24.89822
D86: Extraccion de Madera de áreas protegidas
B87: MAATE/ INGEI | D87: Bosque nativo bajo un regimen de protección legal (PSB, SNAP, Bosques Protectores) | F87: Extracción de Madera (m3.ha-1.año-1)
D88: B. nativo | T88: 0.01959779
D89: Plantaciones forestales | T89: 15.487761
F90: TOTAL MADERA EXTRAIDA [m3.ha-1.año-1] | T90: =SUM(T88:T89) -> 15.507359
D94: Extraccion de leña de áreas protegidas
B95: Balance Energético Nacional, 2020/ INGEI | D95: Bosque nativo bajo un regimen de protección legal (PSB, SNAP, Bosques Protectores) | F95: Extracción de Leña (m3.ha-1.año-1)
D96: B. nativo | S96: 0.21000467
D97: Plantaciones forestales | S97: 0
F98: TOTAL LEÑA EXTRAIDA [m3.ha-1.año-1] | S98: =SUM(S96:S97) -> 0.21000467
D101: DATOS PARA EMISIONES INGEI
E104: GRÁFICO UTCUTS-1 | F104: TABLA UTCUTS - 4: Cambios de uso de suelos
F105: Superficie de tierras convertidas en tierras de cultivo [Mha]
B106: INGEI | D106: Bosque nativo | F106: Tierras de cultivo [Mha] | I106: 0.09472 | K106: 0.09472 | M106: 0.09472 | O106: 0.09079 | Q106: 0.07746
D107: Plantación forestal | F107: Tierras de cultivo [Mha] | I107: 0.0023 | K107: 0.0023 | M107: 0.0023 | O107: 0.01114 | Q107: 0.0086
D108: Pastizal (grassland) | F108: Tierras de cultivo [Mha] | I108: 0.02439 | K108: 0.02439 | M108: 0.02439 | O108: 0.05355 | Q108: 0.01486
D109: Humedales | F109: Tierras de cultivo [Mha] | I109: 0.00832 | K109: 0.00832 | M109: 0.00832 | O109: 0.01022 | Q109: 0.00673
D110: Asentamientos | F110: Tierras de cultivo [Mha] | I110: 0 | K110: 0 | M110: 0 | O110: 0 | Q110: 0
D111: Otras tierras | F111: Tierras de cultivo [Mha] | I111: 0.00128 | K111: 0.00128 | M111: 0.00128 | O111: 0.00923 | Q111: 0.00155
F112: TOTAL COBERTURAS [Mha] | I112: 0.13102 | K112: 0.13102 | M112: 0.13102 | O112: 0.1749 | Q112: 0.1092
E114: GRÁFICO UTCUTS-1 | F114: Superficie de tierras convertidas en pastizales [Mha]
B116: INGEI | D116: Bosque nativo | F116: Pastizal (grassland)[Mha] | I116: 0 | K116: 0 | M116: 0 | O116: 0 | Q116: 0.0018
D117: Plantación forestal | F117: Pastizal (grassland)[Mha] | I117: 0.00163 | K117: 0.00163 | M117: 0.00163 | O117: 0.00011 | Q117: 0.00437
D118: Tierras de cultivo | F118: Pastizal (grassland)[Mha] | I118: 0.06653 | K118: 0.06653 | M118: 0.06653 | O118: 0.02195 | Q118: 0.01605
D119: Humedales | F119: Pastizal (grassland)[Mha] | I119: 1e-05 | K119: 1e-05 | M119: 1e-05 | O119: 0.00274 | Q119: 0.00071
D120: Otras tierras | F120: Pastizal (grassland)[Mha] | I120: 0.00369 | K120: 0.00369 | M120: 0.00369 | O120: 0.00444 | Q120: 0.0033
F121: TOTAL COBERTURAS [Mha] | I121: 0.07186 | K121: 0.07186 | M121: 0.07186 | O121: 0.02924 | Q121: 0.02623
E123: GRÁFICO UTCUTS-1 | F123: Superficie de tierras convertidas en humedales [Mha]
B125: INGEI | D125: Bosque nativo | F125: Humedales [Mha] | I125: 0.00092 | K125: 0.00092 | M125: 0.00092 | O125: 0.00119 | Q125: 0.00111
D126: Plantación forestal | F126: Humedales [Mha] | I126: 0 | K126: 0 | M126: 0 | O126: 0.00011 | Q126: 2e-05
D127: Tierras de cultivo | F127: Humedales [Mha] | I127: 0.00774 | K127: 0.00774 | M127: 0.00774 | O127: 0.00753 | Q127: 0.00834
D128: Pastizal (grassland) | F128: Humedales [Mha] | I128: 0.00042 | K128: 0.00042 | M128: 0.00042 | O128: 0.00089 | Q128: 0.00017
D129: Otras tierras | F129: Humedales [Mha] | I129: 0.00185 | K129: 0.00185 | M129: 0.00185 | O129: 0.00364 | Q129: 0.00169
F130: TOTAL COBERTURAS [Mha] | I130: 0.01092 | K130: 0.01092 | M130: 0.01092 | O130: 0.01336 | Q130: 0.01133
E132: GRÁFICO UTCUTS-1 | F132: Superficie de tierras convertidas en asentamientos [Mha]
B134: INGEI | D134: Bosque nativo | F134: Asentamientos [Mha] | I134: 0 | K134: 0.00066 | M134: 0.00066 | O134: 0.00035 | Q134: 0.00056
D135: Plantación forestal | F135: Asentamientos [Mha] | I135: 2e-05 | K135: 2e-05 | M135: 2e-05 | O135: 7e-05 | Q135: 0.00018
D136: Tierras de cultivo | F136: Asentamientos [Mha] | I136: 0.00969 | K136: 0.00969 | M136: 0.00969 | O136: 0.00232 | Q136: 0.01422
...

Sheet Calibración-UTCUTS2
B1: Referencia | F1: Ecuador | G1: 2008 | H1: 2009 | I1: 2010 | J1: 2011 | K1: 2012 | L1: 2013 | M1: 2014 | N1: 2015 | O1: 2016 | P1: 2017 | Q1: 2018 | R1: 2019 | S1: 2020 | T1: 2021 | U1: 2022 | V1: 2023 | W1: 2024 | X1: 2025 | Y1: 2026 | Z1: 2027 | AA1: 2028 | AB1: 2029 | AC1: 2030 | AD1: 2031 | AE1: 2032 | AF1: 2033 | AG1: 2034 | AH1: 2035 | AI1: 2036 | AJ1: 2037 | AK1: 2038 | AL1: 2039 | AM1: 2040 | AN1: 2041 | AO1: 2042 | AP1: 2043 | AQ1: 2044 | AR1: 2045 | AS1: 2046 | AT1: 2047 | AU1: 2048 | AV1: 2049 | AW1: 2050
D3: DATOS PARA CALIBRAR PROYECCIONES
E6: GRÁFICO UTCUTS-1 | F6: TABLA UTCUTS - 1: Cobertura uso de suelos
F7: Uso de suelos [ha]
B8: ESPAC | F8: Montes y bosques [ha] | I8: 3504127 | J8: 3536454 | K8: 3583056 | L8: 3538424 | M8: 5758859 | N8: 5729799 | O8: 5773290 | P8: 5675402 | Q8: 5740641 | R8: 6040896 | S8: 6112324 | T8: 5900560 | U8: 5900560 | V8: 5900560 | W8: 5900560 | X8: 5900560 | Y8: 5900560 | Z8: 5900560 | AA8: 5900560 | AB8: 5900560 | AC8: 5900560 | AD8: 5900560 | AE8: 5900560 | AF8: 5900560 | AG8: 5900560 | AH8: 5900560 | AI8: 5900560 | AJ8: 5900560 | AK8: 5900560 | AL8: 5900560 | AM8: 5900560 | AN8: 5900560 | AO8: 5900560 | AP8: 5900560 | AQ8: 5900560 | AR8: 5900560 | AS8: 5900560 | AT8: 5900560 | AU8: 5900560 | AV8: 5900560 | AW8: 5900560
F9: Cultivos permanentes [ha] | I9: 1391379 | J9: 1379473 | K9: 1382918 | L9: 1469363 | M9: 1417104 | N9: 1483366 | O9: 1439117 | P9: 1430497 | Q9: 1385805 | R9: 1439504 | S9: 1442973 | T9: 1423372 | U9: 1423372 | V9: 1423372 | W9: 1423372 | X9: 1423372 | Y9: 1423372 | Z9: 1423372 | AA9: 1423372 | AB9: 1423372 | AC9: 1423372 | AD9: 1423372 | AE9: 1423372 | AF9: 1423372 | AG9: 1423372 | AH9: 1423372 | AI9: 1423372 | AJ9: 1423372 | AK9: 1423372 | AL9: 1423372 | AM9: 1423372 | AN9: 1423372 | AO9: 1423372 | AP9: 1423372 | AQ9: 1423372 | AR9: 1423372 | AS9: 1423372 | AT9: 1423372 | AU9: 1423372 | AV9: 1423372 | AW9: 1423372
F10: Cultivos transitorios y barbechos [ha] | I10: 992369 | J10: 982312 | K10: 1020870 | L10: 1003271 | M10: 876498 | N10: 950649 | O10: 849685 | P10: 904224 | Q10: 799494 | R10: 769708 | S10: 822516 | T10: 841994 | U10: 841994 | V10: 841994 | W10: 841994 | X10: 841994 | Y10: 841994 | Z10: 841994 | AA10: 841994 | AB10: 841994 | AC10: 841994 | AD10: 841994 | AE10: 841994 | AF10: 841994 | AG10: 841994 | AH10: 841994 | AI10: 841994 | AJ10: 841994 | AK10: 841994 | AL10: 841994 | AM10: 841994 | AN10: 841994 | AO10: 841994 | AP10: 841994 | AQ10: 841994 | AR10: 841994 | AS10: 841994 | AT10: 841994 | AU10: 841994 | AV10: 841994 | AW10: 841994
F11: Descanso [ha] | I11: 193957 | J11: 173442 | K11: 126982 | L11: 191159 | M11: 93574 | N11: 117390 | O11: 125946 | P11: 129268 | Q11: 168446 | R11: 219492 | S11: 215014 | T11: 163017 | U11: 163017 | V11: 163017 | W11: 163017 | X11: 163017 | Y11: 163017 | Z11: 163017 | AA11: 163017 | AB11: 163017 | AC11: 163017 | AD11: 163017 | AE11: 163017 | AF11: 163017 | AG11: 163017 | AH11: 163017 | AI11: 163017 | AJ11: 163017 | AK11: 163017 | AL11: 163017 | AM11: 163017 | AN11: 163017 | AO11: 163017 | AP11: 163017 | AQ11: 163017 | AR11: 163017 | AS11: 163017 | AT11: 163017 | AU11: 163017 | AV11: 163017 | AW11: 163017
F12: Otros usos [ha] | I12: 217058 | J12: 210584 | K12: 205657 | L12: 216225 | M12: 468180 | N12: 612090 | O12: 719109 | P12: 757791 | Q12: 796518 | R12: 662305 | S12: 681476 | T12: 712757 | U12: 712757 | V12: 712757 | W12: 712757 | X12: 712757 | Y12: 712757 | Z12: 712757 | AA12: 712757 | AB12: 712757 | AC12: 712757 | AD12: 712757 | AE12: 712757 | AF12: 712757 | AG12: 712757 | AH12: 712757 | AI12: 712757 | AJ12: 712757 | AK12: 712757 | AL12: 712757 | AM12: 712757 | AN12: 712757 | AO12: 712757 | AP12: 712757 | AQ12: 712757 | AR12: 712757 | AS12: 712757 | AT12: 712757 | AU12: 712757 | AV12: 712757 | AW12: 712757
F13: Páramos [ha] | I13: 539475 | J13: 565857 | K13: 608272 | L13: 491891 | M13: 499258 | N13: 454347 | O13: 377791 | P13: 332418 | Q13: 252612 | R13: 270986 | S13: 249139 | T13: 233074 | U13: 233074 | V13: 233074 | W13: 233074 | X13: 233074 | Y13: 233074 | Z13: 233074 | AA13: 233074 | AB13: 233074 | AC13: 233074 | AD13: 233074 | AE13: 233074 | AF13: 233074 | AG13: 233074 | AH13: 233074 | AI13: 233074 | AJ13: 233074 | AK13: 233074 | AL13: 233074 | AM13: 233074 | AN13: 233074 | AO13: 233074 | AP13: 233074 | AQ13: 233074 | AR13: 233074 | AS13: 233074 | AT13: 233074 | AU13: 233074 | AV13: 233074 | AW13: 233074
F14: Pastos cultivados [ha] | I14: 3409952 | J14: 3425412 | K14: 3553008 | L14: 3227321 | M14: 2259447 | N14: 2531442 | O14: 2300539 | P14: 2447634 | Q14: 2379042 | R14: 1985494 | S14: 2067795 | T14: 2376551 | U14: 2376551 | V14: 2376551 | W14: 2376551 | X14: 2376551 | Y14: 2376551 | Z14: 2376551 | AA14: 2376551 | AB14: 2376551 | AC14: 2376551 | AD14: 2376551 | AE14: 2376551 | AF14: 2376551 | AG14: 2376551 | AH14: 2376551 | AI14: 2376551 | AJ14: 2376551 | AK14: 2376551 | AL14: 2376551 | AM14: 2376551 | AN14: 2376551 | AO14: 2376551 | AP14: 2376551 | AQ14: 2376551 | AR14: 2376551 | AS14: 2376551 | AT14: 2376551 | AU14: 2376551 | AV14: 2376551 | AW14: 2376551
F15: Pastos permanentes [ha] | I15: 1509972 | J15: 1385547 | K15: 1423114 | L15: 1623359 | M15: 828333 | N15: 706777 | O15: 800496 | P15: 677911 | Q15: 715273 | R15: 915843 | S15: 841320 | T15: 646139 | U15: 646139 | V15: 646139 | W15: 646139 | X15: 646139 | Y15: 646139 | Z15: 646139 | AA15: 646139 | AB15: 646139 | AC15: 646139 | AD15: 646139 | AE15: 646139 | AF15: 646139 | AG15: 646139 | AH15: 646139 | AI15: 646139 | AJ15: 646139 | AK15: 646139 | AL15: 646139 | AM15: 646139 | AN15: 646139 | AO15: 646139 | AP15: 646139 | AQ15: 646139 | AR15: 646139 | AS15: 646139 | AT15: 646139 | AU15: 646139 | AV15: 646139 | AW15: 646139
F16: Uso de suelos [Mha]
B17: ESPAC | F17: Montes y bosques [Mha] | I17: =I8/1000000 -> 3.504127 | J17: =J8/1000000 -> 3.536454 | K17: =K8/1000000 -> 3.583056 | L17: =L8/1000000 -> 3.538424 | M17: =M8/1000000 -> 5.758859 | N17: =N8/1000000 -> 5.729799 | O17: =O8/1000000 -> 5.77329 | P17: =P8/1000000 -> 5.675402 | ... AW17: =AW8/1000000 -> 5.90056
F18: Cultivos permanentes [Mha] | I18: =I9/1000000 -> 1.391379 | J18: =J9/1000000 -> 1.379473 | K18: =K9/1000000 -> 1.382918 | L18: =L9/1000000 -> 1.469363 | M18: =M9/1000000 -> 1.417104 | N18: =N9/1000000 -> 1.483366 | O18: =O9/1000000 -> 1.439117 | P18: =P9/1000000 -> 1.430497 | ... AW18: =AW9/1000000 -> 1.423372
F19: Cultivos transitorios y barbechos [Mha] | I19: =I10/1000000 -> 0.992369 | J19: =J10/1000000 -> 0.982312 | K19: =K10/1000000 -> 1.02087 | L19: =L10/1000000 -> 1.003271 | M19: =M10/1000000 -> 0.876498 | N19: =N10/1000000 -> 0.950649 | O19: =O10/1000000 -> 0.849685 | P19: =P10/1000000 -> 0.904224 | ... AW19: =AW10/1000000 -> 0.841994
F20: Descanso [Mha] | I20: =I11/1000000 -> 0.193957 | J20: =J11/1000000 -> 0.173442 | K20: =K11/1000000 -> 0.126982 | L20: =L11/1000000 -> 0.191159 | M20: =M11/1000000 -> 0.093574 | N20: =N11/1000000 -> 0.11739 | O20: =O11/1000000 -> 0.125946 | P20: =P11/1000000 -> 0.129268 | ... AW20: =AW11/1000000 -> 0.163017
F21: Otros usos [Mha] | I21: =I12/1000000 -> 0.217058 | J21: =J12/1000000 -> 0.210584 | K21: =K12/1000000 -> 0.205657 | L21: =L12/1000000 -> 0.216225 | M21: =M12/1000000 -> 0.46818 | N21: =N12/1000000 -> 0.61209 | O21: =O12/1000000 -> 0.719109 | P21: =P12/1000000 -> 0.757791 | ... AW21: =AW12/1000000 -> 0.712757
F22: Páramos [Mha] | I22: =I13/1000000 -> 0.539475 | J22: =J13/1000000 -> 0.565857 | K22: =K13/1000000 -> 0.608272 | L22: =L13/1000000 -> 0.491891 | M22: =M13/1000000 -> 0.499258 | N22: =N13/1000000 -> 0.454347 | O22: =O13/1000000 -> 0.377791 | P22: =P13/1000000 -> 0.332418 | ... AW22: =AW13/1000000 -> 0.233074
F23: Pastos cultivados [Mha] | I23: =I14/1000000 -> 3.409952 | J23: =J14/1000000 -> 3.425412 | K23: =K14/1000000 -> 3.553008 | L23: =L14/1000000 -> 3.227321 | M23: =M14/1000000 -> 2.259447 | N23: =N14/1000000 -> 2.531442 | O23: =O14/1000000 -> 2.300539 | P23: =P14/1000000 -> 2.447634 | ... AW23: =AW14/1000000 -> 2.376551
F24: Pastos permanentes [Mha] | I24: =I15/1000000 -> 1.509972 | J24: =J15/1000000 -> 1.385547 | K24: =K15/1000000 -> 1.423114 | L24: =L15/1000000 -> 1.623359 | M24: =M15/1000000 -> 0.828333 | N24: =N15/1000000 -> 0.706777 | O24: =O15/1000000 -> 0.800496 | P24: =P15/1000000 -> 0.677911 | ... AW24: =AW15/1000000 -> 0.646139
F25: TOTAL COBERTURAS [Mha] | I25: =SUM(I17:I24) -> 11.758289 | J25: =SUM(J17:J24) -> 11.659081 | K25: =SUM(K17:K24) -> 11.903877 | L25: =SUM(L17:L24) -> 11.761013 | M25: =SUM(M17:M24) -> 12.201253 | N25: =SUM(N17:N24) -> 12.58586 | O25: =SUM(O17:O24) -> 12.385973 | P25: =SUM(P17:P24) -> 12.355145 | ... AW25: =SUM(AW17:AW24) -> 12.297464
D28: DATOS ÁREAS PROTEGIDAS
E31: GRÁFICO UTCUTS-2 | F31: TABLA UTCUTS - 2: Cobertura áreas protegidas
F32: Áreas protegidas [Mha]
B33: SNAP | F33: Galápagos [Mha] | I33: 0.79579217 | J33: 0.79579217 | K33: 0.79579217 | L33: 0.79579217 | M33: 0.79579217 | N33: 0.79579217 | O33: 0.79579217 | P33: 0.79579217 | Q33: 0.79579217 | R33: 0.79579217 | S33: 0.79579217 | T33: 0.79579217 | U33: 0.79579217 | V33: 0.79579217 | W33: 0.79579217 | X33: 0.79579217 | Y33: 0.79579217 | Z33: 0.79579217 | AA33: 0.79579217 | AB33: 0.79579217 | AC33: 0.79579217 | AD33: 0.79579217 | AE33: 0.79579217 | AF33: 0.79579217 | AG33: 0.79579217 | AH33: 0.79579217 | AI33: 0.79579217 | AJ33: 0.79579217 | AK33: 0.79579217 | AL33: 0.79579217 | AM33: 0.79579217 | AN33: 0.79579217 | AO33: 0.79579217 | AP33: 0.79579217 | AQ33: 0.79579217 | AR33: 0.79579217 | AS33: 0.79579217 | AT33: 0.79579217 | AU33: 0.79579217 | AV33: 0.79579217 | AW33: 0.79579217
F34: Bosques protegidos/Protected forest [Mha] | I34: 2.2633933 | J34: 2.2794224 | K34: 2.2794224 | L34: 2.2794224 | M34: 2.3725857 | N34: 2.3725857 | O34: 2.3747312 | P34: 2.3747312 | Q34: 2.4084734 | R34: 2.4088211 | S34: 2.4088211 | T34: 2.4117235 | U34: 2.4117235 | V34: 2.4117235 | W34: 2.4117235 | X34: 2.4117235 | Y34: 2.4117235 | Z34: 2.4117235 | AA34: 2.4117235 | AB34: 2.4117235 | AC34: 2.4117235 | AD34: 2.4117235 | AE34: 2.4117235 | AF34: 2.4117235 | AG34: 2.4117235 | AH34: 2.4117235 | AI34: 2.4117235 | AJ34: 2.4117235 | AK34: 2.4117235 | AL34: 2.4117235 | AM34: 2.4117235 | AN34: 2.4117235 | AO34: 2.4117235 | AP34: 2.4117235 | AQ34: 2.4117235 | AR34: 2.4117235 | AS34: 2.4117235 | AT34: 2.4117235 | AU34: 2.4117235 | AV34: 2.4117235 | AW34: 2.4117235
F35: Pradera protegida/Protected grassland [Mha] | I35: 1.8351789 | J35: 1.8351789 | K35: 1.838396 | L35: 1.838396 | M35: 1.838396 | N35: 1.838396 | O35: 1.838396 | P35: 1.8914899 | Q35: 1.8934445 | R35: 1.922489 | S35: 1.9272792 | T35: 1.95791 | U35: 1.95791 | V35: 1.95791 | W35: 1.95791 | X35: 1.95791 | Y35: 1.95791 | Z35: 1.95791 | AA35: 1.95791 | AB35: 1.95791 | AC35: 1.95791 | AD35: 1.95791 | AE35: 1.95791 | AF35: 1.95791 | AG35: 1.95791 | AH35: 1.95791 | AI35: 1.95791 | AJ35: 1.95791 | AK35: 1.95791 | AL35: 1.95791 | AM35: 1.95791 | AN35: 1.95791 | AO35: 1.95791 | AP35: 1.95791 | AQ35: 1.95791 | AR35: 1.95791 | AS35: 1.95791 | AT35: 1.95791 | AU35: 1.95791 | AV35: 1.95791 | AW35: 1.95791
F36: Manglares [Mha] | I36: 0.37320953 | J36: 0.37568766 | K36: 0.38884296 | L36: 0.38884296 | M36: 0.38884296 | N36: 0.53110941 | O36: 0.57106191 | P36: 0.57106191 | Q36: 0.57106191 | R36: 0.57106191 | S36: 0.57106191 | T36: 0.57106191 | U36: 0.57106191 | V36: 0.57106191 | W36: 0.57106191 | X36: 0.57106191 | Y36: 0.57106191 | Z36: 0.57106191 | AA36: 0.57106191 | AB36: 0.57106191 | AC36: 0.57106191 | AD36: 0.57106191 | AE36: 0.57106191 | AF36: 0.57106191 | AG36: 0.57106191 | AH36: 0.57106191 | AI36: 0.57106191 | AJ36: 0.57106191 | AK36: 0.57106191 | AL36: 0.57106191 | AM36: 0.57106191 | AN36: 0.57106191 | AO36: 0.57106191 | AP36: 0.57106191 | AQ36: 0.57106191 | AR36: 0.57106191 | AS36: 0.57106191 | AT36: 0.57106191 | AU36: 0.57106191 | AV36: 0.57106191 | AW36: 0.57106191
D39: DATOS PARA MODELO OSEMOSYS
A42: DRIVERS | E42: GRÁFICO UTCUTS-3 | F42: TABLA UTCUTS - 3: Coberturas generales - MAG + MAATE
F43: Coberturas generales [ha]
B44: MAG+MAATE | D44: Bosque | F44: Bosque nativo [ha] | G44: 13038367 | M44: 12753387 | O44: 12631198 | Q44: 12514340
F45: Plantación forestal [ha] | G45: 62196.93 | M45: 130072.41 | O45: 123719.94 | Q45: 121995.27
D46: Tierra agropecuaria | F46: Cultivo anual [ha] | G46: 611941.95 | M46: 1094904.6 | O46: 8933864.5 | Q46: 8999553.2
F47: Cultivo semipermanente [ha] | G47: 260389.08 | M47: 480131.91
F48: Cultivo permanente [ha] | G48: 167305.59 | M48: 917407.35
F49: Pastizal [ha] | G49: 1454890.3 | M49: 4959938.7
F50: Mosaico agropecuario [ha] | G50: 6337045.3 | M50: 1266774.3
D51: Vegetación arbustiva | F51: Vegetación arbustiva [ha] | G51: 587499.84 | M51: 810626.94 | O51: 763180.11 | Q51: 768908.61
F52: Vegetación herbácea [ha] | G52: 109528.02 | M52: 89167.14 | O52: 83035.17 | Q52: 85768.2
F53: Páramo [ha] | G53: 1465935.8 | M53: 1523970.1 | O53: 1515272.5 | Q53: 1521159.7
D54: Cuerpo de agua | F54: Cuerpo de agua natural [ha] | G54: 348472.62 | M54: 305169.39 | O54: 295476.12 | Q54: 291292.2
F55: Cuerpo de agua artificial [ha] | G55: 157677.57 | M55: 199934.1 | O55: 199287.27 | Q55: 200705.67
D56: Zona antrópica | F56: Área poblada [ha] | G56: 165538.44 | M56: 224935.38 | O56: 229182.39 | Q56: 255251.97
F57: Infraestructura [ha] | G57: 11615.85 | M57: 21206.79 | O57: 23884.2 | Q57: 30656.25
D58: Otras tierras | F58: Área sin cobertura vegetal [ha] | G58: 109686.69 | M58: 112568.04 | O58: 93841.92 | Q58: 102446.37
F59: Glaciar [ha] | G59: 9968.49 | M59: 7865.73 | O59: 6279.21 | Q59: 6144.03
F60: Sin información [ha] | G60: 0 | M60: 0 | O60: 0 | Q60: 0
F61: TOTAL COBERTURAS [ha] | G61: =SUM(G44:G60) -> 24898060 | M61: =SUM(M44:M60) -> 24898060 | O61: =SUM(O44:O60) -> 24898221 | Q61: =SUM(Q44:Q60) -> 24898221
F62: Coberturas generales [Mha]
C63: Leyendas usadas en INGEI 2018 (NIVEL I IPCC) | D63: Leyendas usadas por MAATE en los mapas interactivos y reportes de deforestacion (Nivel I IPCC) | F63: Niveles para OSEMOSYS
A64: Tasa de deforestación neta 2018 (-0.46%) | B64: MAG+MAATE | C64: Tierras forestales | D64: Bosque | F64: Bosque nativo [Mha] | G64: =G44/1000000 -> 13.038367 | M64: =M44/1000000 -> 12.753387 | O64: =O44/1000000 -> 12.631198 | Q64: =Q44/1000000 -> 12.51434 | R64: =Q64*(1-0.0046) -> 12.456774 | S64: =R64*(1-0.0046) -> 12.399472 | T64: =S64*(1-0.0046) -> 12.342435 | U64: =T64*(1-0.0046) -> 12.28566 | V64: =U64*(1-0.0046) -> 12.229146 | W64: =V64*(1-0.0046) -> 12.172892 | X64: =W64*(1-0.0046) -> 12.116896 | Y64: =X64*(1-0.0046) -> 12.061159 | ... AW64: =AV64*(1-0.0046) -> 10.797726
A65: El sector crece 10% mas que el crecimiento poblacional segun planeacion estrategica de plantaciones forestales 2012 | F65: Plantación forestal [Mha] | G65: =G45/1000000 -> 0.06219693 | M65: =M45/1000000 -> 0.13007241 | O65: =O45/1000000 -> 0.12371994 | Q65: =Q45/1000000 -> 0.12199527 | R65: =Q65*(1+('Drivers Económicos'!E8/100)) -> 0.1220128 | S65: =R65*(1+('Drivers Económicos'!F8/100)) -> 0.12202994 | T65: =S65*(1+('Drivers Económicos'!G8/100)) -> 0.12204671 | U65: =T65*(1+('Drivers Económicos'!H8/100)+ 0.1*('Drivers Económicos'!H8/100)) -> 0.12206476 | V65: =U65*(1+('Drivers Económicos'!I8/100)+ 0.1*('Drivers Económicos'!I8/100)) -> 0.12208242 | W65: =V65*(1+('Drivers Económicos'!J8/100)+ 0.1*('Drivers Económicos'!J8/100)) -> 0.12209969 | X65: =W65*(1+('Drivers Económicos'!K8/100)+ 0.1*('Drivers Económicos'!K8/100)) -> 0.12211659 | Y65: =X65*(1+('Drivers Económicos'!L8/100)+ 0.1*('Drivers Económicos'!L8/100)) -> 0.12213309 | Z65: =Y65*(1+('Drivers Económicos'!M8/100)+ 0.1*('Drivers Económicos'!M8/100)) -> 0.12214922 | AA65: =Z65*(1+('Drivers Económicos'!N8/100)+ 0.1*('Drivers Económicos'!N8/100)) -> 0.12216497 | AB65: =AA65*(1+('Drivers Económicos'!O8/100)+ 0.1*('Drivers Económicos'!O8/100)) -> 0.12218034 | ... AW65: =AV65*(1+('Drivers Económicos'!AJ8/100)+ 0.1*('Drivers Económicos'!AJ8/100)) -> 0.12241873
A66: Crece con la tasa de crecimiento del PIB del sector agricultura, silvicultura y pesca | C66: Tierra de cultivo | D66: Tierra agropecuaria
F67: Cultivos [Mha] | G67: 7.376682 | M67: 3.7592182 | O67: 3.85228 | Q67: 3.880607 | R67: 3.880607 | S67: 3.880607 | T67: 3.880607 | U67: =T67*(1+('Drivers Económicos'!H31/100)+0.25*(('Calibración-BAU_Agricultura '!S38-'Calibración-BAU_Agricultura '!R38)/'Calibración-BAU_Agricultura '!S38)) -> 3.8335263 | V67: =U67*(1+('Drivers Económicos'!I31/100)+0.25*(('Calibración-BAU_Agricultura '!T38-'Calibración-BAU_Agricultura '!S38)/'Calibración-BAU_Agricultura '!T38)) -> 3.829883 | W67: =V67*(1+('Drivers Económicos'!J31/100)+0.25*(('Calibración-BAU_Agricultura '!U38-'Calibración-BAU_Agricultura '!T38)/'Calibración-BAU_Agricultura '!U38)) -> 3.8860682 | X67: =W67*(1+('Drivers Económicos'!K31/100)+0.25*(('Calibración-BAU_Agricultura '!V38-'Calibración-BAU_Agricultura '!U38)/'Calibración-BAU_Agricultura '!V38)) -> 3.8886606 | Y67: =X67*(1+('Drivers Económicos'!L31/100)+0.25*(('Calibración-BAU_Agricultura '!W38-'Calibración-BAU_Agricultura '!V38)/'Calibración-BAU_Agricultura '!W38)) -> 3.9501392 | Z67: =Y67*(1+('Drivers Económicos'!M31/100)+0.25*(('Calibración-BAU_Agricultura '!X38-'Calibración-BAU_Agricultura '!W38)/'Calibración-BAU_Agricultura '!X38)) -> 3.9794395 | AA67: =Z67*(1+('Drivers Económicos'!N31/100)+0.25*(('Calibración-BAU_Agricultura '!Y38-'Calibración-BAU_Agricultura '!X38)/'Calibración-BAU_Agricultura '!Y38)) -> 4.0076574 | AB67: =AA67*(1+('Drivers Económicos'!O31/100)+0.25*(('Calibración-BAU_Agricultura '!Z38-'Calibración-BAU_Agricultura '!Y38)/'Calibración-BAU_Agricultura '!Z38)) -> 4.0332167 | ... AW67: =AV67*(1+('Drivers Económicos'!AJ31/100)+0.25*(('Calibración-BAU_Agricultura '!AU38-'Calibración-BAU_Agricultura '!AT38)/'Calibración-BAU_Agricultura '!AU38)) -> 4.326422
A70: Flexible | F70: Pastura [Mha] | G70: =G49/1000000 -> 1.4548903 | M70: =M49/1000000 -> 4.9599387 | O70: 5.08158 | Q70: 5.118945 | R70: =$Q$83-(SUM(R64:R67)+SUM(R72:R79)) -> 5.1759345 | S70: =$Q$83-(SUM(S64:S67)+SUM(S72:S79)) -> 5.2325099 | T70: =$Q$83-(SUM(T64:T67)+SUM(T72:T79)) -> 5.2888226 | U70: =$Q$83-(SUM(U64:U67)+SUM(U72:U79)) -> 5.3929646 | V70: =$Q$83-(SUM(V64:V67)+SUM(V72:V79)) -> 5.4531336 | W70: =$Q$83-(SUM(W64:W67)+SUM(W72:W79)) -> 5.4534288 | X70: =$Q$83-(SUM(X64:X67)+SUM(X72:X79)) -> 5.5066827 | Y70: =$Q$83-(SUM(Y64:Y67)+SUM(Y72:Y79)) -> 5.5008651 | ... AW70: =$Q$83-(SUM(AW64:AW67)+SUM(AW72:AW79)) -> 6.385065
A71: Decrece con tasa de crecimiento de PIB del sector agricultura, silvicultura y pesca | C71: Pastizales (grasslands) | D71: Vegetación arbustiva y herbácea (incluye páramo) | F71: Pastizales (grasslands) [Mha] | G71: 2.1629637 | M71: 2.4237642 | O71: 2.3614878
Q72: 2.3758365 | R72: 2.3758365 | S72: 2.3758365 | T72: 2.3758365 | U72: =T72*(1-'Drivers Económicos'!H31/100) -> 2.3750183 | V72: =U72*(1-'Drivers Económicos'!I31/100) -> 2.3743196 | W72: =V72*(1-'Drivers Económicos'!J31/100) -> 2.3735801 | X72: =W72*(1-'Drivers Económicos'!K31/100) -> 2.3730194 | Y72: =X72*(1-'Drivers Económicos'!L31/100) -> 2.3725566 | Z72: =Y72*(1-'Drivers Económicos'!M31/100) -> 2.3719538 | AA72: =Z72*(1-'Drivers Económicos'!N31/100) -> 2.371443 | AB72: =AA72*(1-'Drivers Económicos'!O31/100) -> 2.3711466 | ... AW72: =AV72*(1-'Drivers Económicos'!AJ31/100) -> 2.3621737
A74: Tasa de crecimiento del PIB del sector agricultura silvicultura y pesca y tasa de crecimiento del PIB del sector de la construccion | C74: Humedal | D74: Cuerpo de agua/humedal | F74: Humedal [Mha] | G74: 0.50615019 | M74: 0.50510349 | O74: 0.49476339 | Q74: 0.49199787 | R74: 0.49182843 | S74: 0.49182843 | T74: 0.49182843 | U74: =T74*(1-0.5*(('Drivers Económicos'!H31/100)+0.5*('Drivers Económicos'!H46/100))) -> 0.49163531 | V74: =U74*(1-0.5*(('Drivers Económicos'!I31/100)+0.5*('Drivers Económicos'!I46/100))) -> 0.49159881 | W74: =V74*(1-0.5*(('Drivers Económicos'!J31/100)+0.5*('Drivers Económicos'!J46/100))) -> 0.49139078 | X74: =W74*(1-0.5*(('Drivers Económicos'!K31/100)+0.5*('Drivers Económicos'!K46/100))) -> 0.49138227 | Y74: =X74*(1-0.5*(('Drivers Económicos'!L31/100)+0.5*('Drivers Económicos'!L46/100))) -> 0.49120645 | Z74: =Y74*(1-0.5*(('Drivers Económicos'!M31/100)+0.5*('Drivers Económicos'!M46/100))) -> 0.49118703 | AA74: =Z74*(1-0.5*(('Drivers Económicos'!N31/100)+0.5*('Drivers Económicos'!N46/100))) -> 0.49100445 | AB74: =AA74*(1-0.5*(('Drivers Económicos'!O31/100)+0.5*('Drivers Económicos'!O46/100))) -> 0.49102425 | ... AW74: =AV74*(1-0.5*(('Drivers Económicos'!AJ31/100)+0.5*('Drivers Económicos'!AJ46/100))) -> 0.48944669
A76: Tasa de urbanización | C76: Asentamientos | D76: Zona antrópica | F76: Asentamientos [Mha] | G76: 0.17715429 | M76: 0.24614217 | O76: 0.25306659 | Q76: 0.28590822 | R76: =Q76*(1+('Drivers Económicos'!D10/100)) -> 0.28694261 | S76: =R76*(1+('Drivers Económicos'!E10/100)) -> 0.287976 | T76: =S76*(1+('Drivers Económicos'!F10/100)) -> 0.28900794 | U76: =T76*(1+('Drivers Económicos'!G10/100)) -> 0.29003793 | V76: =U76*(1+('Drivers Económicos'!H10/100)) -> 0.29106563 | W76: =V76*(1+('Drivers Económicos'!I10/100)) -> 0.29209049 | X76: =W76*(1+('Drivers Económicos'!J10/100)) -> 0.29311188 | Y76: =X76*(1+('Drivers Económicos'!K10/100)) -> 0.29412959 | ... AW76: =AV76*(1+('Drivers Económicos'!AI10/100)) -> 0.3163118
A78: Cambio climatico causará perdida de 10% de los glaciares hasta el 2050 | C78: Otras tierras | D78: Otras tierras | F78: Otras tierras [Mha] | G78: 0.11965518
M79: 0.12043377 | O79: 0.10012113 | Q79: 0.1085904 | R79: =Q79*(1-0.003) -> 0.10826463 | S79: =R79*(1-0.003) -> 0.10793983 | T79: =S79*(1-0.003) -> 0.10761602 | U79: =T79*(1-0.003) -> 0.10729317 | V79: =U79*(1-0.003) -> 0.10697129 | W79: =V79*(1-0.003) -> 0.10665037 | X79: =W79*(1-0.003) -> 0.10633042 | Y79: =X79*(1-0.003) -> 0.10601143 | ... AW79: =AV79*(1-0.003) -> 0.098636238
F81: TOTAL COBERTURAS [Mha] | G81: =SUM(G64:G80) -> 24.89806 | M81: =SUM(M64:M80) -> 24.89806 | O81: =SUM(O64:O80) -> 24.898217 | Q81: =SUM(Q64:Q80) -> 24.89822 | R81: =SUM(R64:R80) -> 24.8982 | S81: =SUM(S64:S80) -> 24.8982 | T81: =SUM(T64:T80) -> 24.8982 | U81: =SUM(U64:U80) -> 24.8982 | V81: =SUM(V64:V80) -> 24.8982 | W81: =SUM(W64:W80) -> 24.8982 | X81: =SUM(X64:X80) -> 24.8982 | ... AW81: =SUM(AW64:AW80) -> 24.8982
Q83: =24.8982 -> 24.8982 | R83: =SUM(R64:R76) -> 24.789935 | S83: 24.771813 | T83: =SUM(T64:T76) -> 24.790584 | U83: =SUM(U64:U76) -> 24.790907 | V83: =SUM(V64:V76) -> 24.791229 | W83: =SUM(W64:W76) -> 24.79155 | X83: =SUM(X64:X76) -> 24.79187 | Y83: =SUM(Y64:Y76) -> 24.792189 | Z83: =SUM(Z64:Z76) -> 24.792507 | AA83: =SUM(AA64:AA76) -> 24.792824 | ... AW83: =SUM(AW64:AW76) -> 24.799564
D86: Extraccion de Madera de áreas protegidas
B87: MAATE/ INGEI | D87: Bosque nativo bajo un regimen de protección legal (PSB, SNAP, Bosques Protectores) | F87: Extracción de Madera (m3.ha-1.año-1)
A88: Crece con la tasa de crecimiento de las plantaciones forestales | D88: B. nativo | T88: 0.01959779 | U88: =T88*(1+((U65-T65)/U65)) -> 0.019600688 | V88: =U88*(1+((V65-U65)/V65)) -> 0.019603523 | W88: =V88*(1+((W65-V65)/W65)) -> 0.019606296 | X88: =W88*(1+((X65-W65)/X65)) -> 0.019609008 | Y88: =X88*(1+((Y65-X65)/Y65)) -> 0.019611659 | Z88: =Y88*(1+((Z65-Y65)/Z65)) -> 0.019614248 | AA88: =Z88*(1+((AA65-Z65)/AA65)) -> 0.019616776 | AB88: =AA88*(1+((AB65-AA65)/AB65)) -> 0.019619245 | ... AW88: =AV88*(1+((AW65-AV65)/AW65)) -> 0.01965752
A89: Crece con la tasa de crecimiento de las plantaciones forestales | D89: Plantaciones forestales | T89: 15.487761 | U89: =T89*(1+((U65-T65)/U65)) -> 15.490051 | V89: =U89*(1+((V65-U65)/V65)) -> 15.492292 | W89: =V89*(1+((W65-V65)/W65)) -> 15.494483 | X89: =W89*(1+((X65-W65)/X65)) -> 15.496627 | Y89: =X89*(1+((Y65-X65)/Y65)) -> 15.498721 | Z89: =Y89*(1+((Z65-Y65)/Z65)) -> 15.500768 | AA89: =Z89*(1+((AA65-Z65)/AA65)) -> 15.502766 | AB89: =AA89*(1+((AB65-AA65)/AB65)) -> 15.504717 | ... AW89: =AV89*(1+((AW65-AV65)/AW65)) -> 15.534965
F90: TOTAL MADERA EXTRAIDA [m3.ha-1.año-1] | T90: =SUM(T88:T89) -> 15.507359 | U90: =SUM(U88:U89) -> 15.509652 | V90: =SUM(V88:V89) -> 15.511895 | W90: =SUM(W88:W89) -> 15.51409 | X90: =SUM(X88:X89) -> 15.516236 | Y90: =SUM(Y88:Y89) -> 15.518333 | Z90: =SUM(Z88:Z89) -> 15.520382 | AA90: =SUM(AA88:AA89) -> 15.522382 | ... AW90: =SUM(AW88:AW89) -> 15.554623
D94: Extraccion de leña de áreas protegidas
B95: Balance Energético Nacional, 2020/ INGEI | D95: Bosque nativo bajo un regimen de protección legal (PSB, SNAP, Bosques Protectores) | F95: Extracción de Leña (m3.ha-1.año-1)
A96: Crece con la tasa de crecimiento de la poblacion | D96: B. nativo | S96: 0.21000467 | T96: =S96*(1+'Drivers Económicos'!G8/100) -> 0.21003353 | U96: =T96*(1+'Drivers Económicos'!H8/100) -> 0.21006176 | V96: =U96*(1+'Drivers Económicos'!I8/100) -> 0.21008939 | W96: =V96*(1+'Drivers Económicos'!J8/100) -> 0.21011641 | X96: =W96*(1+'Drivers Económicos'!K8/100) -> 0.21014284 | Y96: =X96*(1+'Drivers Económicos'!L8/100) -> 0.21016866 | Z96: =Y96*(1+'Drivers Económicos'!M8/100) -> 0.21019389 | AA96: =Z96*(1+'Drivers Económicos'!N8/100) -> 0.21021853 | ... AW96: =AV96*(1+'Drivers Económicos'!AJ8/100) -> 0.21061546
D97: Plantaciones forestales | S97: 0 | T97: =S97*(1+'Drivers Económicos'!G8/100) -> 0 | U97: =T97*(1+'Drivers Económicos'!H8/100) -> 0 | V97: =U97*(1+'Drivers Económicos'!I8/100) -> 0 | W97: =V97*(1+'Drivers Económicos'!J8/100) -> 0 | X97: =W97*(1+'Drivers Económicos'!K8/100) -> 0 | Y97: =X97*(1+'Drivers Económicos'!L8/100) -> 0 | Z97: =Y97*(1+'Drivers Económicos'!M8/100) -> 0 | AA97: =Z97*(1+'Drivers Económicos'!N8/100) -> 0 | ... AW97: =AV97*(1+'Drivers Económicos'!AJ8/100) -> 0
F98: TOTAL LEÑA EXTRAIDA [m3.ha-1.año-1] | S98: =SUM(S96:S97) -> 0.21000467 | T98: =SUM(T96:T97) -> 0.21003353 | U98: =SUM(U96:U97) -> 0.21006176 | V98: =SUM(V96:V97) -> 0.21008939 | W98: =SUM(W96:W97) -> 0.21011641 | X98: =SUM(X96:X97) -> 0.21014284 | Y98: =SUM(Y96:Y97) -> 0.21016866 | Z98: =SUM(Z96:Z97) -> 0.21019389 | ... AW98: =SUM(AW96:AW97) -> 0.21061546
D101: DATOS PARA EMISIONES
C103: % del Total de has que cambian de cobertura
E104: GRÁFICO UTCUTS-4 | F104: TABLA UTCUTS - 4: Cambios de uso de suelos
D105: Cobertura inicial | F105: Superficie de tierras convertidas en tierras de cultivo [Mha]
B106: Datos 2010 al 2018 INGEI | C106: 0.248 | D106: Bosque nativo | F106: Tierras de cultivo [Mha] | I106: 0.09472 | K106: 0.09472 | M106: 0.09472 | O106: 0.09079 | Q106: 0.07746 | U106: =(U64-T64)*$C$106 -> -0.01408025 | V106: =(V64-U64)*$C$106 -> -0.014015481 | W106: =(W64-V64)*$C$106 -> -0.013951009 | X106: =(X64-W64)*$C$106 -> -0.013886835 | Y106: =(Y64-X64)*$C$106 -> -0.013822955 | Z106: =(Z64-Y64)*$C$106 -> -0.01375937 | AA106: =(AA64-Z64)*$C$106 -> -0.013696077 | AB106: =(AB64-AA64)*$C$106 -> -0.013633075 | ... AW106: =(AW64-AV64)*$C$106 -> -0.012374971
C107: 0.48314607 | D107: Plantación forestal | F107: Tierras de cultivo [Mha] | I107: 0.0023 | K107: 0.0023 | M107: 0.0023 | O107: 0.01114 | Q107: 0.0086 | U107: =(U65-T65)*$C$107 -> 8.7197044e-06 | V107: =(V65-U65)*$C$107 -> 8.5319271e-06 | W107: =(W65-V65)*$C$107 -> 8.3449313e-06 | X107: =(X65-W65)*$C$107 -> 8.1620957e-06 | Y107: =(Y65-X65)*$C$107 -> 7.97572e-06 | Z107: =(Z65-Y65)*$C$107 -> 7.7919068e-06 | AA107: =(AA65-Z65)*$C$107 -> 7.6079506e-06 | AB107: =(AB65-AA65)*$C$107 -> 7.4282345e-06 | ... AW107: =(AW65-AV65)*$C$107 -> 3.8201817e-06
D108: Pastura | F108: Tierras de cultivo [Mha] | V108: =(V67-U67-V149-V159)*$C$108 -> 0 | W108: =(W67-V67-W149-W159)*$C$108 -> 0 | X108: =(X67-W67-X149-X159)*$C$108 -> 0 | Y108: =(Y67-X67-Y149-Y159)*$C$108 -> 0 | Z108: =(Z67-Y67-Z149-Z159)*$C$108 -> 0 | AA108: =(AA67-Z67-AA149-AA159)*$C$108 -> 0 | AB108: =(AB67-AA67-AB149-AB159)*$C$108 -> 0 | AC108: =(AC67-AB67-AC149-AC159)*$C$108 -> 0 | ... AW108: =(AW67-AV67-AW149-AW159)*$C$108 -> 0
C109: 0.5851 | D109: Pastizal (grassland) | F109: Tierras de cultivo [Mha] | I109: 0.02439 | K109: 0.02439 | M109: 0.02439 | O109: 0.05355 | Q109: 0.01486 | U109: =(U72-T72)*$C$109 -> -0.00047872775 | V109: =(V72-U72)*$C$109 -> -0.00040876904 | W109: =(W72-V72)*$C$109 -> -0.00043270905 | X109: =(X72-W72)*$C$109 -> -0.00032808243 | Y109: =(Y72-X72)*$C$109 -> -0.00027073907 | Z109: =(Z72-Y72)*$C$109 -> -0.00035272555 | AA109: =(AA72-Z72)*$C$109 -> -0.00029884304 | AB109: =(AB72-AA72)*$C$109 -> -0.00017342987 | ... AW109: =(AW72-AV72)*$C$109 -> -0.00030224542
C110: 0.4161 | D110: Humedales | F110: Tierras de cultivo [Mha] | I110: 0.00832 | K110: 0.00832 | M110: 0.00832 | O110: 0.01022 | Q110: 0.00673 | U110: =(U74-T74)*$C$110 -> -8.0357743e-05 | V110: =(V74-U74)*$C$110 -> -1.5188826e-05 | W110: =(W74-V74)*$C$110 -> -8.6561666e-05 | X110: =(X74-W74)*$C$110 -> -3.5422601e-06 | Y110: =(Y74-X74)*$C$110 -> -7.3157007e-05 | Z110: =(Z74-Y74)*$C$110 -> -8.0809399e-06 | AA110: =(AA74-Z74)*$C$110 -> -7.5970871e-05 | AB110: =(AB74-AA74)*$C$110 -> 8.2391959e-06 | ... AW110: =(AW74-AV74)*$C$110 -> -3.5781063e-05
D111: Asentamientos | F111: Tierras de cultivo [Mha] | I111: 0 | K111: 0 | M111: 0 | O111: 0 | Q111: 0 | V111: =(V67-U67)*$C$111 -> 0 | W111: =(W67-V67)*$C$111 -> 0 | X111: =(X67-W67)*$C$111 -> 0 | Y111: =(Y67-X67)*$C$111 -> 0 | Z111: =(Z67-Y67)*$C$111 -> 0 | AA111: =(AA67-Z67)*$C$111 -> 0 | AB111: =(AB67-AA67)*$C$111 -> 0 | AC111: =(AC67-AB67)*$C$111 -> 0 | ... AW111: =(AW67-AV67)*$C$111 -> 0
C112: 0.1573 | D112: Otras tierras | F112: Tierras de cultivo [Mha] | I112: 0.00128 | K112: 0.00128 | M112: 0.00128 | O112: 0.00923 | Q112: 0.00155 | U112: =(U79-T79)*$C$112 -> -5.0783998e-05 | V112: =(V79-U79)*$C$112 -> -5.0631646e-05 | W112: =(W79-V79)*$C$112 -> -5.0479751e-05 | X112: =(X79-W79)*$C$112 -> -5.0328311e-05 | Y112: =(Y79-X79)*$C$112 -> -5.0177327e-05 | Z112: =(Z79-Y79)*$C$112 -> -5.0026795e-05 | AA112: =(AA79-Z79)*$C$112 -> -4.9876714e-05 | AB112: =(AB79-AA79)*$C$112 -> -4.9727084e-05 | ... AW112: =(AW79-AV79)*$C$112 -> -4.66865e-05
F113: TOTAL COBERTURAS [Mha] | I113: 0.13102 | K113: 0.13102 | M113: 0.13102 | O113: 0.1749 | Q113: 0.1092 | R113: 0.1092 | S113: 0.1092 | T113: 0.1092 | U113: =SUM(U106:U112) -> -0.014681399 | V113: =SUM(V106:V112) -> -0.014481538 | W113: =SUM(W106:W112) -> -0.014512415 | X113: =SUM(X106:X112) -> -0.014260626 | Y113: =SUM(Y106:Y112) -> -0.014209053 | Z113: =SUM(Z106:Z112) -> -0.014162411 | AA113: =SUM(AA106:AA112) -> -0.014113159 | AB113: =SUM(AB106:AB112) -> -0.013840564 | ... AW113: =SUM(AW106:AW112) -> -0.012755863
D115: Cobertura inicial | F115: Superficie de tierras convertidas en Pasturas [Mha]
C116: 0.744 | D116: Bosque nativo | F116: Pasturas [Mha] | U116: =(U64-T64)*$C$116 -> -0.042240749 | V116: =(V64-U64)*$C$116 -> -0.042046442 | W116: =(W64-V64)*$C$116 -> -0.041853028 | X116: =(X64-W64)*$C$116 -> -0.041660504 | Y116: =(Y64-X64)*$C$116 -> -0.041468866 | Z116: =(Z64-Y64)*$C$116 -> -0.041278109 | AA116: =(AA64-Z64)*$C$116 -> -0.04108823 | AB116: =(AB64-AA64)*$C$116 -> -0.040899224 | ... AW116: =(AW64-AV64)*$C$116 -> -0.037124912
C117: 0.16104869 | D117: Plantación forestal | F117: Pasturas [Mha] | U117: =(U65-T65)*$C$117 -> 2.9065681e-06 | V117: =(V65-U65)*$C$117 -> 2.8439757e-06 | W117: =(W65-V65)*$C$117 -> 2.7816438e-06 | X117: =(X65-W65)*$C$117 -> 2.7206986e-06 | Y117: =(Y65-X65)*$C$117 -> 2.6585733e-06 | Z117: =(Z65-Y65)*$C$117 -> 2.5973023e-06 | AA117: =(AA65-Z65)*$C$117 -> 2.5359835e-06 | AB117: =(AB65-AA65)*$C$117 -> 2.4760782e-06 | ... AW117: =(AW65-AV65)*$C$117 -> 1.2733939e-06
D118: Tierras de cultivo | F118: Pasturas [Mha]
C119: 0.195 | D119: Pastizal (grassland) | F119: Pasturas [Mha] | U119: =(U72-T72)*$C$119 -> -0.00015954864 | V119: =(V72-U72)*$C$119 -> -0.00013623306 | W119: =(W72-V72)*$C$119 -> -0.0001442117 | X119: =(X72-W72)*$C$119 -> -0.00010934212 | Y119: =(Y72-X72)*$C$119 -> -9.0230932e-05 | Z119: =(Z72-Y72)*$C$119 -> -0.00011755509 | AA119: =(AA72-Z72)*$C$119 -> -9.9597321e-05 | AB119: =(AB72-AA72)*$C$119 -> -5.7800076e-05 | ... AW119: =(AW72-AV72)*$C$119 -> -0.00010073126
C120: 0.1387 | D120: Humedales | F120: Pasturas [Mha] | U120: =(U74-T74)*$C$120 -> -2.6785914e-05 | V120: =(V74-U74)*$C$120 -> -5.0629418e-06 | W120: =(W74-V74)*$C$120 -> -2.8853889e-05 | X120: =(X74-W74)*$C$120 -> -1.1807534e-06 | Y120: =(Y74-X74)*$C$120 -> -2.4385669e-05 | Z120: =(Z74-Y74)*$C$120 -> -2.6936466e-06 | AA120: =(AA74-Z74)*$C$120 -> -2.5323624e-05 | AB120: =(AB74-AA74)*$C$120 -> 2.7463986e-06 | ... AW120: =(AW74-AV74)*$C$120 -> -1.1927021e-05
D121: Asentamientos | F121: Pasturas [Mha]
C122: 0.05242 | D122: Otras tierras | F122: Pasturas [Mha] | U122: =(U79-T79)*$C$122 -> -1.6923695e-05 | V122: =(V79-U79)*$C$122 -> -1.6872923e-05 | W122: =(W79-V79)*$C$122 -> -1.6822305e-05 | X122: =(X79-W79)*$C$122 -> -1.6771838e-05 | Y122: =(Y79-X79)*$C$122 -> -1.6721522e-05 | Z122: =(Z79-Y79)*$C$122 -> -1.6671358e-05 | AA122: =(AA79-Z79)*$C$122 -> -1.6621344e-05 | AB122: =(AB79-AA79)*$C$122 -> -1.657148e-05 | ... AW122: =(AW79-AV79)*$C$122 -> -1.5558209e-05
F123: TOTAL COBERTURAS [Mha] | I123: 0.13102 | K123: 0.13102 | M123: 0.13102 | O123: 0.1749 | Q123: 0.1092 | R123: =SUM(U116:U122) -> -0.042441101 | S123: =SUM(S116:S122) -> 0 | T123: =SUM(T116:T122) -> 0 | U123: =SUM(U116:U122) -> -0.042441101 | V123: =SUM(V116:V122) -> -0.042201766 | W123: =SUM(W116:W122) -> -0.042040134 | X123: =SUM(X116:X122) -> -0.041785078 | Y123: =SUM(Y116:Y122) -> -0.041597545 | Z123: =SUM(Z116:Z122) -> -0.041412432 | ... AW123: =SUM(AW116:AW122) -> -0.037251855
E125: GRÁFICO UTCUTS-5 | F125: Superficie de tierras convertidas en pastizales [Mha]
D126: Cobertura inicial
B127: Datos 2010 al 2018 INGEI | D127: Bosque nativo | F127: Pastizal (grassland)[Mha] | I127: 0 | K127: 0 | M127: 0 | O127: 0 | Q127: 0.0018
C128: 0.33 | D128: Plantación forestal | F128: Pastizal (grassland)[Mha] | I128: 0.00163 | K128: 0.00163 | M128: 0.00163 | O128: 0.00011 | Q128: 0.00437 | U128: =(U65-T65)*$C$128 -> 5.9557609e-06 | V128: =(V65-U65)*$C$128 -> 5.8275047e-06 | W128: =(W65-V65)*$C$128 -> 5.6997822e-06 | X128: =(X65-W65)*$C$128 -> 5.5749012e-06 | Y128: =(Y65-X65)*$C$128 -> 5.4476022e-06 | Z128: =(Z65-Y65)*$C$128 -> 5.3220535e-06 | AA128: =(AA65-Z65)*$C$128 -> 5.1964072e-06 | AB128: =(AB65-AA65)*$C$128 -> 5.0736569e-06 | ... AW128: =(AW65-AV65)*$C$128 -> 2.6092729e-06
...

Sheet Drivers_macroeconómicos_USCUSS
C1: Ecuador | D1: 2018 | E1: 2019 | F1: 2020 | G1: 2021 | H1: 2022 | I1: 2023 | J1: 2024 | K1: 2025 | L1: 2026 | M1: 2027 | N1: 2028 | O1: 2029 | P1: 2030 | Q1: 2031 | R1: 2032 | S1: 2033 | T1: 2034 | U1: 2035 | V1: 2036 | W1: 2037 | X1: 2038 | Y1: 2039 | Z1: 2040 | AA1: 2041 | AB1: 2042 | AC1: 2043 | AD1: 2044 | AE1: 2045 | AF1: 2046 | AG1: 2047 | AH1: 2048 | AI1: 2049 | AJ1: 2050 | AK1: 2051 | AL1: 2052 | AM1: 2053 | AN1: 2054 | AO1: 2055 | AP1: 2056 | AQ1: 2057 | AR1: 2058 | AS1: 2059 | AT1: 2060 | AU1: 2061 | AV1: 2062 | AW1: 2063 | AX1: 2064 | AY1: 2065 | AZ1: 2066 | BA1: 2067 | BB1: 2068 | BC1: 2069 | BD1: 2070
C4: Drivers económicos
C6: Población
C7: Población Nacional | D7: 17023408 | E7: 17267986 | F7: 17510643 | G7: 17751277 | H7: 17989912 | I7: 18226512 | J7: 18460936 | K7: 18693140 | L7: 18922864 | M7: 19150021 | N7: 19374448 | O7: 19596113 | P7: 19814767 | Q7: 20030293 | R7: 20242540 | S7: 20451333 | T7: 20656586 | U7: 20858149 | V7: 21055934 | W7: 21249772 | X7: 21439596 | Y7: 21625281 | Z7: 21806740 | AA7: 21983950 | AB7: 22156850 | AC7: 22325333 | AD7: 22489377 | AE7: 22648875 | AF7: 22803800 | AG7: 22954177 | AH7: 23099877 | AI7: 23240939 | AJ7: 23377412 | AK7: 23509204 | AL7: 23636226 | AM7: 23758390 | AN7: 23875615 | AO7: 23987819 | AP7: 24094924 | AQ7: 24196857 | AR7: 24293546 | AS7: 24384925 | AT7: 24470928 | AU7: 24551497 | AV7: 24626572 | AW7: 24696102 | AX7: 24760036 | AY7: 24818330 | AZ7: 24870940 | BA7: 24917829 | BB7: 24958963 | BC7: 24994311 | BD7: 25023848
C8: Tasa de crecimiento Poblacional [%] | E8: 0.014367158 | F8: 0.01405242 | G8: 0.013742157 | H8: 0.013443258 | I8: 0.013151815 | J8: 0.012861704 | K8: 0.012578127 | L8: 0.012289214 | M8: 0.012004367 | N8: 0.011719413 | O8: 0.0114411 | P8: 0.011158029 | Q8: 0.010877039 | R8: 0.0105963 | S8: 0.010314565 | T8: 0.010036167 | U8: 0.009757808 | V8: 0.009482385 | W8: 0.0092058609 | X8: 0.00893299 | Y8: 0.0086608442 | Z8: 0.0083910586 | AA8: 0.0081263866 | AB8: 0.0078648287 | AC8: 0.0076041044 | AD8: 0.0073478859 | AE8: 0.0070921484 | AF8: 0.0068402956 | AG8: 0.0065943834 | AH8: 0.0063474286 | AI8: 0.0061066126 | AJ8: 0.0058720949 | AK8: 0.0056375773 | AL8: 0.0054030596 | AM8: 0.0051685419 | AN8: 0.0049340242 | AO8: 0.0046995066 | AP8: 0.0044649889 | AQ8: 0.0042304712 | AR8: 0.0039959535 | AS8: 0.0037614358 | AT8: 0.0035269182 | AU8: 0.0032924005 | AV8: 0.0030578828 | AW8: 0.0028233651 | AX8: 0.0025888475 | AY8: 0.0023543298 | AZ8: 0.0021198121 | BA8: 0.0018852944 | BB8: 0.0016507768 | BC8: 0.0014162591 | BD8: 0.0011817414
C9: Población Urbana | D9: 10864509 | E9: 11049093 | F9: 11235879 | G9: 11424900 | H9: 11615526 | I9: 11808838 | J9: 12005436 | K9: 12202757 | L9: 12402937 | M9: 12604533 | N9: 12808718 | O9: 13014434 | P9: 13223175 | Q9: 13432538 | R9: 13643430 | S9: 13856389 | T9: 14070704 | U9: 14285910 | V9: 14502306 | W9: 14719086 | X9: 14936890 | Y9: 15155932 | Z9: 15374543 | AA9: 15594304 | AB9: 15812576 | AC9: 16030860 | AD9: 16246560 | AE9: 16459880 | AF9: 16670523 | AG9: 16877776 | AH9: 17081537 | AI9: 17282572 | AJ9: 17479919 | AK9: 17675992 | AL9: 17869280 | AM9: 18059730 | AN9: 18247636 | AO9: 18432571 | AP9: 18614476 | AQ9: 18793290 | AR9: 18968832 | AS9: 19141005 | AT9: 19309699 | AU9: 19474788 | AV9: 19636165 | AW9: 19793719 | AX9: 19947339 | AY9: 20096920 | AZ9: 20242357 | BA9: 20383550 | BB9: 20520399 | BC9: 20652807 | BD9: 20780681
C10: Tasa de urbanización | D10: 0.63820999 | E10: 0.63985997 | F10: 0.64165999 | G10: 0.64361003 | H10: 0.64566886 | I10: 0.64789346 | J10: 0.65031567 | K10: 0.65279332 | L10: 0.65544714 | M10: 0.65819943 | N10: 0.66111396 | O10: 0.66413344 | P10: 0.66733941 | Q10: 0.67061116 | R10: 0.67399793 | S10: 0.67752987 | T10: 0.68117277 | U10: 0.68490785 | V10: 0.68875149 | W10: 0.6926703 | X10: 0.69669643 | Y10: 0.70084324 | Z10: 0.70503629 | AA10: 0.7093495 | AB10: 0.71366535 | AC10: 0.71805693 | AD10: 0.72241041 | AE10: 0.72674162 | AF10: 0.73104145 | AG10: 0.73528125 | AH10: 0.73946441 | AI10: 0.74362624 | AJ10: 0.74772687 | AK10: 0.7518754 | AL10: 0.7560124 | AM10: 0.76014112 | AN10: 0.76427921 | AO10: 0.76841381 | AP10: 0.77254761 | AQ10: 0.77668311 | AR10: 0.78081774 | AS10: 0.78495238 | AT10: 0.78908731 | AU10: 0.79322204 | AV10: 0.79735681 | AW10: 0.80149162 | AX10: 0.80562639 | AY10: 0.80976117 | AZ10: 0.81389596 | BA10: 0.81803074 | BB10: 0.82216552 | BC10: 0.8263003 | BD10: 0.83043508
C11: Población Rural | D11: 6158899 | E11: 6218893 | F11: 6274764 | G11: 6326377 | H11: 6374386 | I11: 6417674 | J11: 6455500 | K11: 6490383 | L11: 6519927 | M11: 6545488 | N11: 6565730 | O11: 6581679 | P11: 6591592 | Q11: 6597755 | R11: 6599110 | S11: 6594944 | T11: 6585882 | U11: 6572239 | V11: 6553628 | W11: 6530686 | X11: 6502706 | Y11: 6469349 | Z11: 6432197 | AA11: 6389646 | AB11: 6344274 | AC11: 6294473 | AD11: 6242817 | AE11: 6188995 | AF11: 6133277 | AG11: 6076401 | AH11: 6018340 | AI11: 5958367 | AJ11: 5897493 | AK11: 5833211.7 | AL11: 5766946 | AM11: 5698660.9 | AN11: 5627978.9 | AO11: 5555247.6 | AP11: 5480448 | AQ11: 5403566.9 | AR11: 5324714.4 | AS11: 5243920 | AT11: 5161229.4 | AU11: 5076708.3 | AV11: 4990407.2 | AW11: 4902383.2 | AX11: 4812697.7 | AY11: 4721410 | AZ11: 4628582.5 | BA11: 4534279 | BB11: 4438564.2 | BC11: 4341504.3 | BD11: 4243166.7
C12: Tasa de ruralización | D12: 0.36179001 | E12: 0.36014003 | F12: 0.35834001 | G12: 0.35638997 | H12: 0.35433114 | I12: 0.35210654 | J12: 0.34968433 | K12: 0.34720668 | L12: 0.34455286 | M12: 0.34180057 | N12: 0.33888604 | O12: 0.33586656 | P12: 0.33266059 | Q12: 0.32938884 | R12: 0.32600207 | S12: 0.32247013 | T12: 0.31882723 | U12: 0.31509215 | V12: 0.31124851 | W12: 0.3073297 | X12: 0.30330357 | Y12: 0.29915676 | Z12: 0.29496371 | AA12: 0.2906505 | AB12: 0.28633465 | AC12: 0.28194307 | AD12: 0.27758959 | AE12: 0.27325838 | AF12: 0.26895855 | AG12: 0.26471875 | AH12: 0.26053559 | AI12: 0.25637376 | AJ12: 0.25227313 | AK12: 0.2481246 | AL12: 0.2439876 | AM12: 0.23985888 | AN12: 0.23572079 | AO12: 0.23158619 | AP12: 0.22745239 | AQ12: 0.22331689 | AR12: 0.21918226 | AS12: 0.21504762 | AT12: 0.21091269 | AU12: 0.20677796 | AV12: 0.20264319 | AW12: 0.19850838 | AX12: 0.19437361 | AY12: 0.19023883 | AZ12: 0.18610404 | BA12: 0.18196926 | BB12: 0.17783448 | BC12: 0.1736997 | BD12: 0.16956492
C13: Población Económicamente Activa | D13: 8164671.9 | E13: 8192768.8 | F13: 8420741.7 | G13: 8582778.7 | H13: 8570550.2 | I13: 8898168 | J13: 8852383.3 | K13: 9072233.5 | L13: 9328486.5 | M13: 9424636.7 | N13: 9694170.1 | O13: 9687259.9 | P13: 9797759.8 | Q13: 10138246 | R13: 10139537 | S13: 10428883 | T13: 10452508 | U13: 10511839 | V13: 10701475 | W13: 10758750 | X13: 10892423 | Y13: 11185978 | Z13: 11302979 | AA13: 11485000 | AB13: 11676283 | AC13: 11553196 | AD13: 11744123 | AE13: 11777190 | AF13: 12098068 | AG13: 12164231 | AH13: 12237431 | AI13: 12351923 | AJ13: 12488207 | AK13: 12459201 | AL13: 12533145 | AM13: 12592775 | AN13: 12670481 | AO13: 12733611 | AP13: 12797206 | AQ13: 12848044 | AR13: 12898288 | AS13: 12947625 | AT13: 12992302 | AU13: 13030507 | AV13: 13070894 | AW13: 13108385 | AX13: 13144106 | AY13: 13175801 | AZ13: 13204201 | BA13: 13228282 | BB13: 13249780 | BC13: 13268406 | BD13: 13283873
C15: PIB Nacional Tendencial
C16: PIB Nacional [Miles USD 2021] | D16: 1.1044052e+08 | E16: 1.1045389e+08 | F16: 1.0185217e+08 | G16: 1.0616587e+08 | H16: 1.0903234e+08 | I16: 1.1241235e+08 | J16: 1.1578472e+08 | K16: 1.189109e+08 | L16: 1.2164586e+08 | M16: 1.2552006e+08 | N16: 1.2909258e+08 | O16: 1.3192742e+08 | P16: 1.3506999e+08 | Q16: 1.3934876e+08 | R16: 1.4278631e+08 | S16: 1.4691488e+08 | T16: 1.5039185e+08 | U16: 1.5394779e+08 | V16: 1.5787929e+08 | W16: 1.6146177e+08 | X16: 1.6524433e+08 | Y16: 1.694103e+08 | Z16: 1.7325839e+08 | AA16: 1.7721315e+08 | AB16: 1.8116162e+08 | AC16: 1.8433065e+08 | AD16: 1.8837051e+08 | AE16: 1.9187245e+08 | AF16: 1.962589e+08 | AG16: 1.9987601e+08 | AH16: 2.0345775e+08 | AI16: 2.0717148e+08 | AJ16: 2.1091297e+08 | AK16: 2.1516061e+08 | AL16: 2.1903011e+08 | AM16: 2.2290161e+08 | AN16: 2.2689756e+08 | AO16: 2.3093073e+08 | AP16: 2.3507519e+08 | AQ16: 2.390897e+08 | AR16: 2.4314279e+08 | AS16: 2.4723288e+08 | AT16: 2.5134133e+08 | AU16: 2.5545079e+08 | AV16: 2.5957199e+08 | AW16: 2.6370907e+08 | AX16: 2.6786265e+08 | AY16: 2.7202083e+08 | AZ16: 2.7618252e+08 | BA16: 2.8034186e+08 | BB16: 2.8450685e+08 | BC16: 2.8867414e+08 | BD16: 2.9284055e+08
C17: Tasa de crecimiento del PIB Nacional [%] | E17: 0.00012105103 | F17: -0.077876071 | G17: 0.042352512 | H17: 0.027 | I17: 0.031 | J17: 0.03 | K17: 0.027 | L17: 0.023 | M17: 0.031848226 | N17: 0.028461725 | O17: 0.021959772 | P17: 0.023820424 | Q17: 0.031678203 | R17: 0.024668623 | S17: 0.028914332 | T17: 0.02366656 | U17: 0.023644563 | V17: 0.025537867 | W17: 0.022691249 | X17: 0.023426989 | Y17: 0.025210938 | Z17: 0.022714646 | AA17: 0.022825748 | AB17: 0.022280909 | AC17: 0.017492827 | AD17: 0.021916426 | AE17: 0.018590676 | AF17: 0.022861287 | AG17: 0.018430279 | AH17: 0.017919822 | AI17: 0.018253093 | AJ17: 0.018059848 | AK17: 0.020139299 | AL17: 0.017984242 | AM17: 0.017675659 | AN17: 0.017926947 | AO17: 0.01777532 | AP17: 0.017946763 | AQ17: 0.017077545 | AR17: 0.016952187 | AS17: 0.016821774 | AT17: 0.016617719 | AU17: 0.016350119 | AV17: 0.01613305 | AW17: 0.015938076 | AX17: 0.015750621 | AY17: 0.015523529 | AZ17: 0.015299193 | BA17: 0.015060105 | BB17: 0.014856822 | BC17: 0.014647421 | BD17: 0.014432888
C19: PIB Nacional Optimista
C20: PIB Nacional [Miles USD 2021] | D20: 1.1044052e+08 | E20: 1.1045389e+08 | F20: 1.0185217e+08 | G20: 1.0616587e+08 | H20: 1.0903234e+08 | I20: 1.1241235e+08 | J20: 1.1578472e+08 | K20: 1.189109e+08 | L20: 1.2164586e+08 | M20: 1.2618356e+08 | N20: 1.3119398e+08 | O20: 1.3506116e+08 | P20: 1.3963439e+08 | Q20: 1.4542588e+08 | R20: 1.5108693e+08 | S20: 1.5842426e+08 | T20: 1.6468855e+08 | U20: 1.7163687e+08 | V20: 1.7940792e+08 | W20: 1.8675464e+08 | X20: 1.949134e+08 | Y20: 2.0401983e+08 | Z20: 2.1260645e+08 | AA20: 2.2205733e+08 | AB20: 2.3184204e+08 | AC20: 2.4086664e+08 | AD20: 2.5165093e+08 | AE20: 2.6181995e+08 | AF20: 2.7442058e+08 | AG20: 2.8555366e+08 | AH20: 2.9758914e+08 | AI20: 3.104137e+08 | AJ20: 3.2383289e+08 | AK20: 3.3783219e+08 | AL20: 3.5255474e+08 | AM20: 3.6794329e+08 | AN20: 3.838701e+08 | AO20: 4.0077811e+08 | AP20: 4.1840025e+08 | AQ20: 4.3701471e+08 | AR20: 4.562429e+08 | AS20: 4.7643646e+08 | AT20: 4.9761046e+08 | AU20: 5.197696e+08 | AV20: 5.4293709e+08 | AW20: 5.6723261e+08 | AX20: 5.9266525e+08 | AY20: 6.1931712e+08 | AZ20: 6.4721204e+08 | BA20: 6.7642284e+08 | BB20: 7.0699494e+08 | BC20: 7.3902754e+08 | BD20: 7.7257936e+08
C21: Tasa de crecimiento del PIB Nacional [%] | E21: 0.00012105103 | F21: -0.077876071 | G21: 0.042352512 | H21: 0.027 | I21: 0.031 | J21: 0.03 | K21: 0.027 | L21: 0.023 | M21: 0.037302605 | N21: 0.039707332 | O21: 0.029476823 | P21: 0.03386043 | Q21: 0.041476109 | R21: 0.038927414 | S21: 0.048563643 | T21: 0.039541205 | U21: 0.0421907 | V21: 0.045276099 | W21: 0.040949802 | X21: 0.043687049 | Y21: 0.046720382 | Z21: 0.042087215 | AA21: 0.044452419 | AB21: 0.044063914 | AC21: 0.038925655 | AD21: 0.044772853 | AE21: 0.040409229 | AF21: 0.048127088 | AG21: 0.040569398 | AH21: 0.042147864 | AI21: 0.043094874 | AJ21: 0.04323001 | AK21: 0.04323001 | AL21: 0.043579473 | AM21: 0.043648688 | AN21: 0.043286043 | AO21: 0.044046169 | AP21: 0.043969828 | AQ21: 0.04448959 | AR21: 0.043998954 | AS21: 0.044260547 | AT21: 0.04444244 | AU21: 0.044531097 | AV21: 0.044572613 | AW21: 0.04474832 | AX21: 0.044836349 | AY21: 0.044969527 | AZ21: 0.045041405 | BA21: 0.045133277 | BB21: 0.045196729 | BC21: 0.045308103 | BD21: 0.04539996
C23: PIB Nacional Escenario Negativo
C24: PIB Nacional [Miles USD 2021] | D24: 1.1044052e+08 | E24: 1.1045389e+08 | F24: 1.0185217e+08 | G24: 1.0616587e+08 | H24: 1.0903234e+08 | I24: 1.1241235e+08 | J24: 1.1578472e+08 | K24: 1.189109e+08 | L24: 1.2164586e+08 | M24: 1.2398022e+08 | N24: 1.2628167e+08 | O24: 1.2826239e+08 | P24: 1.3015186e+08 | Q24: 1.3293641e+08 | R24: 1.3547394e+08 | S24: 1.380039e+08 | T24: 1.4043897e+08 | U24: 1.4262325e+08 | V24: 1.4502121e+08 | W24: 1.4734003e+08 | X24: 1.4960131e+08 | Y24: 1.5209086e+08 | Z24: 1.5460176e+08 | AA24: 1.5694566e+08 | AB24: 1.5931023e+08 | AC24: 1.6105022e+08 | AD24: 1.6339398e+08 | AE24: 1.654843e+08 | AF24: 1.6785104e+08 | AG24: 1.7010112e+08 | AH24: 1.7204024e+08 | AI24: 1.740421e+08 | AJ24: 1.7606956e+08 | AK24: 1.7863001e+08 | AL24: 1.8073167e+08 | AM24: 1.8286392e+08 | AN24: 1.8504881e+08 | AO24: 1.8728437e+08 | AP24: 1.895735e+08 | AQ24: 1.9176363e+08 | AR24: 1.9395671e+08 | AS24: 1.9616623e+08 | AT24: 1.9838068e+08 | AU24: 2.0058591e+08 | AV24: 2.0277829e+08 | AW24: 2.0497725e+08 | AX24: 2.0717606e+08 | AY24: 2.0936996e+08 | AZ24: 2.1155518e+08 | BA24: 2.1372957e+08 | BB24: 2.1589648e+08 | BC24: 2.1805594e+08 | BD24: 2.20206e+08
C25: Tasa de crecimiento del PIB Nacional [%] | E25: 0.00012105103 | F25: -0.077876071 | G25: 0.042352512 | H25: 0.027 | I25: 0.031 | J25: 0.03 | K25: 0.027 | L25: 0.023 | M25: 0.019189799 | N25: 0.0185631 | O25: 0.015684905 | P25: 0.014731318 | Q25: 0.021394642 | R25: 0.019088298 | S25: 0.018674849 | T25: 0.017644928 | U25: 0.015553206 | V25: 0.016813279 | W25: 0.015989505 | X25: 0.01534738 | Y25: 0.016641214 | Z25: 0.01650923 | AA25: 0.015160889 | AB25: 0.015066138 | AC25: 0.010922049 | AD25: 0.014552988 | AE25: 0.012793097 | AF25: 0.014301948 | AG25: 0.013405175 | AH25: 0.011399796 | AI25: 0.011636043 | AJ25: 0.01164922 | AK25: 0.014542263 | AL25: 0.011765423 | AM25: 0.011797887 | AN25: 0.011948199 | AO25: 0.012080923 | AP25: 0.012222755 | AQ25: 0.011552933 | AR25: 0.01143636 | AS25: 0.011391832 | AT25: 0.011288604 | AU25: 0.011116163 | AV25: 0.010929889 | AW25: 0.010844183 | AX25: 0.010727066 | AY25: 0.010589524 | AZ25: 0.010437131 | BA25: 0.010278154 | BB25: 0.010138561 | BC25: 0.010002267 | BD25: 0.0098601413
C27: PIB Sectorial Tendencial
C29: Sector agricultura, silvicultura y pesca
C30: PIB Sector agricultura, silvicultura y pesca [Miles USD 2021] | D30: 10459664 | E30: 10628847 | F30: 10666853 | G30: 11028075 | H30: 11407864 | I30: 11743435 | J30: 12109217 | K30: 12395282 | L30: 12636982 | M30: 12958077 | N30: 13237105 | O30: 13402558 | P30: 13597211 | Q30: 13881504 | R30: 14068748 | S30: 14310693 | T30: 14481999 | U30: 14661880 | V30: 14879624 | W30: 15076447 | X30: 15302557 | Y30: 15584162 | Z30: 15852246 | AA30: 16154988 | AB30: 16475218 | AC30: 16750070 | AD30: 17121125 | AE30: 17465869 | AF30: 17904576 | AG30: 18290578 | AH30: 18681161 | AI30: 19094516 | AJ30: 19511992 | AK30: 19879079 | AL30: 20261015 | AM30: 20655812 | AN30: 21066381 | AO30: 21491535 | AP30: 21927658 | AQ30: 22376868 | AR30: 22837221 | AS30: 23308116 | AT30: 23794456 | AU30: 24289030 | AV30: 24794871 | AW30: 25304594 | AX30: 25823213 | AY30: 26351074 | AZ30: 26886949 | BA30: 27431155 | BB30: 27988822 | BC30: 28559780 | BD30: 29144017
C31: Tasa de crecimiento del PIB Nacional [%] | E31: 0.016174817 | F31: 0.0035757596 | G31: 0.033864024 | H31: 0.03443832 | I31: 0.029415819 | J31: 0.031147751 | K31: 0.023623758 | L31: 0.019499324 | M31: 0.025409155 | N31: 0.021533113 | O31: 0.012499168 | P31: 0.014523639 | Q31: 0.020908162 | R31: 0.013488719 | S31: 0.017197377 | T31: 0.011970435 | U31: 0.012421047 | V31: 0.014850993 | W31: 0.013227721 | X31: 0.014997548 | Y31: 0.018402462 | Z31: 0.017202389 | AA31: 0.01909772 | AB31: 0.019822354 | AC31: 0.016682758 | AD31: 0.022152455 | AE31: 0.020135555 | AF31: 0.025117958 | AG31: 0.021558839 | AH31: 0.021354363 | AI31: 0.022126832 | AJ31: 0.021863659 | AK31: 0.018813416 | AL31: 0.019212939 | AM31: 0.01948556 | AN31: 0.019876675 | AO31: 0.020181621 | AP31: 0.020292818 | AQ31: 0.02048597 | AR31: 0.020572736 | AS31: 0.020619635 | AT31: 0.020865689 | AU31: 0.020785267 | AV31: 0.020825874 | AW31: 0.020557618 | AX31: 0.020495042 | AY31: 0.020441334 | AZ31: 0.020335991 | BA31: 0.020240512 | BB31: 0.020329705 | BC31: 0.020399503 | BD31: 0.020456624
C33: Sector explotación de minas y canteras
C34: PIB Sector explotación de minas y canteras [Miles USD 2021] | D34: 10619740 | E34: 10743749 | F34: 9864685.9 | G34: 10102375 | H34: 10441573 | I34: 10665717 | J34: 11062141 | K34: 11260682 | L34: 11593335 | M34: 11868301 | N34: 12269142 | O34: 12454378 | P34: 12809347 | Q34: 13134036 | R34: 13509102 | S34: 13824040 | T34: 14194898 | U34: 14461150 | V34: 14866847 | W34: 15140781 | X34: 15525019 | Y34: 15858303 | Z34: 16241972 | AA34: 16559468 | AB34: 16946242 | AC34: 17193951 | AD34: 17583425 | AE34: 17865440 | AF34: 18281930 | AG34: 18577259 | AH34: 18914141 | AI34: 19220723 | AJ34: 19568240 | AK34: 19945901 | AL34: 20321976 | AM34: 20703861 | AN34: 21084331 | AO34: 21478999 | AP34: 21873374 | AQ34: 22279608 | AR34: 22683784 | AS34: 23099391 | AT34: 23523006 | AU34: 23958944 | AV34: 24403946 | AW34: 24855601 | AX34: 25314832 | AY34: 25781820 | AZ34: 26257587 | BA34: 26741502 | BB34: 27234502 | BC34: 27736254 | BD34: 28247961
C35: Tasa de crecimiento del PIB Nacional [%] | E35: 0.011677162 | F35: -0.081820881 | G35: 0.024094935 | H35: 0.033576057 | I35: 0.021466527 | J35: 0.037168025 | K35: 0.017947821 | L35: 0.029541062 | M35: 0.023717631 | N35: 0.033774049 | O35: 0.015097768 | P35: 0.028501562 | Q35: 0.025347811 | R35: 0.028556772 | S35: 0.023313025 | T35: 0.026827002 | U35: 0.018756882 | V35: 0.028054276 | W35: 0.018425862 | X35: 0.025377654 | Y35: 0.021467537 | Z35: 0.024193611 | AA35: 0.019547851 | AB35: 0.023356682 | AC35: 0.014617352 | AD35: 0.022651763 | AE35: 0.016038716 | AF35: 0.023312614 | AG35: 0.016154121 | AH35: 0.018134145 | AI35: 0.016209103 | AJ35: 0.018080359 | AK35: 0.019299665 | AL35: 0.018854761 | AM35: 0.018791753 | AN35: 0.018376759 | AO35: 0.018718524 | AP35: 0.018360956 | AQ35: 0.018572069 | AR35: 0.018141111 | AS35: 0.018321746 | AT35: 0.0183388 | AU35: 0.018532409 | AV35: 0.018573505 | AW35: 0.01850749 | AX35: 0.01847592 | AY35: 0.018447208 | AZ35: 0.018453613 | BA35: 0.01842953 | BB35: 0.018435764 | BC35: 0.018423372 | BD35: 0.018449033
C37: Sector D Y E - Generación, captación y distribución de energía eléctrica. Captación, depuración y distribución de agua; y saneamiento
C38: PIB Sector X [Miles USD 2021] | D38: 3138868.4 | E38: 3445471.9 | F38: 3269184.8 | G38: 3294063.3 | H38: 3555861.7 | I38: 3617250.9 | J38: 3918049.3 | K38: 3974907.3 | L38: 4258788.8 | M38: 4353139.4 | N38: 4665919.7 | O38: 4736227.4 | P38: 5031785.5 | Q38: 5167013.6 | R38: 5467260.9 | S38: 5613108.5 | T38: 5908044.9 | U38: 6048487.5 | V38: 6354658.6 | W38: 6512158.3 | X38: 6806903.1 | Y38: 7003424.9 | Z38: 7296765.4 | AA38: 7498696.7 | AB38: 7792956 | AC38: 7973698.9 | AD38: 8269153.2 | AE38: 8475254.2 | AF38: 8784740.5 | AG38: 9006042.9 | AH38: 9278775.6 | AI38: 9513418.1 | AJ38: 9793216.8 | AK38: 10096506 | AL38: 10399168 | AM38: 10713080 | AN38: 11027649 | AO38: 11357640 | AP38: 11690144 | AQ38: 12037007 | AR38: 12386672 | AS38: 12750838 | AT38: 13124687 | AU38: 13514307 | AV38: 13915830 | AW38: 14327692 | AX38: 14751249 | AY38: 15186489 | AZ38: 15634768 | BA38: 16095702 | BB38: 16570526 | BC38: 17059100 | BD38: 17562753
C39: Tasa de crecimiento del PIB Nacional [%] | E39: 0.09767964 | F39: -0.051164869 | G39: 0.0076100067 | H39: 0.079475833 | I39: 0.017264204 | J39: 0.083156649 | K39: 0.014511806 | L39: 0.071418388 | M39: 0.02215434 | N39: 0.071851658 | O39: 0.015068342 | P39: 0.062403699 | Q39: 0.026874785 | R39: 0.058108469 | S39: 0.026676535 | T39: 0.052544217 | U39: 0.023771431 | V39: 0.050619448 | W39: 0.024784905 | X39: 0.0452607 | Y39: 0.028870951 | Z39: 0.041885296 | AA39: 0.027674083 | AB39: 0.039241389 | AC39: 0.023193116 | AD39: 0.03705361 | AE39: 0.024924077 | AF39: 0.036516462 | AG39: 0.02519168 | AH39: 0.030283304 | AI39: 0.025288081 | AJ39: 0.029410954 | AK39: 0.030969277 | AL39: 0.029976912 | AM39: 0.03018626 | AN39: 0.029363067 | AO39: 0.029923971 | AP39: 0.029275822 | AQ39: 0.029671436 | AR39: 0.029049161 | AS39: 0.029399841 | AT39: 0.029319526 | AU39: 0.029686021 | AV39: 0.029711027 | AW39: 0.02959664 | AX39: 0.02956207 | AY39: 0.029505325 | AZ39: 0.029518258 | BA39: 0.029481375 | BB39: 0.029500062 | BC39: 0.029484482 | BD39: 0.029524057
C41: Sector C - Industrias Manufactureras
C42: PIB Sector Y [Miles USD 2021] | D42: 12853031 | E42: 12930007 | F42: 12191089 | G42: 12568272 | H42: 13043258 | I42: 13325429 | J42: 13855046 | K42: 14089477 | L42: 14536382 | M42: 14855781 | N42: 15395233 | O42: 15576803 | P42: 16060951 | Q42: 16425141 | R42: 16936158 | S42: 17292844 | T42: 17796821 | U42: 18096407 | V42: 18640912 | W42: 18953076 | X42: 19467026 | Y42: 19856302 | Z42: 20365186 | AA42: 20737732 | AB42: 21246519 | AC42: 21534828 | AD42: 22043312 | AE42: 22377588 | AF42: 22916652 | AG42: 23270157 | AH42: 23706471 | AI42: 24076272 | AJ42: 24523162 | AK42: 24998528 | AL42: 25468918 | AM42: 25949372 | AN42: 26425513 | AO42: 26921872 | AP42: 27415736 | AQ42: 27926585 | AR42: 28433101 | AS42: 28955814 | AT42: 29487172 | AU42: 30035657 | AV42: 30594452 | AW42: 31161473 | AX42: 31738201 | AY42: 32324574 | AZ42: 32922152 | BA42: 33529890 | BB42: 34149198 | BC42: 34779439 | BD42: 35422317
C43: Tasa de crecimiento del PIB Nacional [%] | E43: 0.0059889289 | F43: -0.057147543 | G43: 0.030939308 | H43: 0.037792405 | I43: 0.021633515 | J43: 0.039744818 | K43: 0.016920245 | L43: 0.031719063 | M43: 0.02197239 | N43: 0.03631261 | O43: 0.011793936 | P43: 0.031081357 | Q43: 0.022675461 | R43: 0.03111187 | S43: 0.021060661 | T43: 0.029143675 | U43: 0.016833639 | V43: 0.030089133 | W43: 0.016746176 | X43: 0.027116973 | Y43: 0.019996668 | Z43: 0.025628382 | AA43: 0.018293273 | AB43: 0.02453436 | AC43: 0.013569678 | AD43: 0.023612193 | AE43: 0.015164479 | AF43: 0.024089463 | AG43: 0.015425674 | AH43: 0.018749936 | AI43: 0.015599196 | AJ43: 0.018561403 | AK43: 0.019384367 | AL43: 0.018816729 | AM43: 0.018864316 | AN43: 0.018348858 | AO43: 0.018783329 | AP43: 0.018344341 | AQ43: 0.018633419 | AR43: 0.018137415 | AS43: 0.018383937 | AT43: 0.018350665 | AU43: 0.018600798 | AV43: 0.01860438 | AW43: 0.018533472 | AX43: 0.018507721 | AY43: 0.018475303 | AZ43: 0.018486798 | BA43: 0.018459841 | BB43: 0.018470341 | BC43: 0.018455516 | BD43: 0.018484434
C45: Sector F - Construcción
C46: PIB Sector Z [Miles USD 2021] | D46: 9518754.6 | E46: 9070046.9 | F46: 7251965.1 | G46: 6770880 | H46: 7367985.4 | I46: 7153337.3 | J46: 7918553.8 | K46: 7599295.2 | L46: 8390540 | M46: 8096840.6 | N46: 8952006 | O46: 8583815.8 | P46: 9375631.3 | Q46: 9128107.4 | R46: 9874161.4 | S46: 9678381.5 | T46: 10358051 | U46: 10190294 | V46: 10835160 | W46: 10730474 | X46: 11308633 | Y46: 11296105 | Z46: 11830553 | AA46: 11848398 | AB46: 12347573 | AC46: 12351038 | AD46: 12819650 | AE46: 12878791 | AF46: 13340234 | AG46: 13434923 | AH46: 13816085 | AI46: 13941345 | AJ46: 14311304 | AK46: 14624446 | AL46: 14910627 | AM46: 15226891 | AN46: 15520903 | AO46: 15847442 | AP46: 16156500 | AQ46: 16493453 | AR46: 16814981 | AS46: 17161726 | AT46: 17503531 | AU46: 17869409 | AV46: 18233783 | AW46: 18603118 | AX46: 18981095 | AY46: 19365212 | AZ46: 19758735 | BA46: 20158967 | BB46: 20568687 | BC46: 20985742 | BD46: 21412744
C47: Tasa de crecimiento del PIB Nacional [%] | E47: -0.047139324 | F47: -0.200449 | G47: -0.066338582 | H47: 0.088187259 | I47: -0.02913253 | J47: 0.10697335 | K47: -0.040317796 | L47: 0.10412083 | M47: -0.035003642 | N47: 0.10561718 | O47: -0.04112935 | P47: 0.092245165 | Q47: -0.026400779 | R47: 0.081731519 | S47: -0.019827501 | T47: 0.070225521 | U47: -0.016195822 | V47: 0.063282416 | W47: -0.0096617131 | X47: 0.053880066 | Y47: -0.0011077495 | Z47: 0.047312509 | AA47: 0.0015083936 | AB47: 0.042130216 | AC47: 0.00028056934 | AD47: 0.037941153 | AE47: 0.0046132637 | AF47: 0.03582971 | AG47: 0.0070979703 | AH47: 0.028371023 | AI47: 0.0090662243 | AJ47: 0.026536838 | AK47: 0.021880715 | AL47: 0.019568734 | AM47: 0.021210583 | AN47: 0.019308799 | AO47: 0.021038638 | AP47: 0.019502045 | AQ47: 0.020855571 | AR47: 0.019494286 | AS47: 0.020621223 | AT47: 0.019916696 | AU47: 0.020903103 | AV47: 0.020390945 | AW47: 0.020255511 | AX47: 0.020317945 | AY47: 0.020236797 | AZ47: 0.02032116 | BA47: 0.020255935 | BB47: 0.02032447 | BC47: 0.020276188 | BD47: 0.02034727
C49: Sector G - Comercio al por mayor y al por menor; reparación de los vehículos de motor y de las motocicletas
C50: PIB Sector M [Miles USD 2021] | D50: 11328940 | E50: 11241422 | F50: 10358244 | G50: 11502513 | H50: 11361983 | I50: 12043246 | J50: 11911061 | K50: 12559294 | L50: 12370057 | M50: 13056237 | N50: 12982711 | O50: 13526194 | P50: 13432690 | Q50: 14086371 | R50: 14045427 | S50: 14640450 | T50: 14625271 | U50: 15119889 | V50: 15171019 | W50: 15626829 | X50: 15682985 | Y50: 16156256 | Z50: 16234709 | AA50: 16652527 | AB50: 16754067 | AC50: 17066720 | AD50: 17188338 | AE50: 17502728 | AF50: 17663791 | AG50: 17961988 | AH50: 18056495 | AI50: 18338956 | AJ50: 18451985 | AK50: 18676629 | AL50: 18916434 | AM50: 19137141 | AN50: 19370113 | AO50: 19594498 | AP50: 19829422 | AQ50: 20055804 | AR50: 20288808 | AS50: 20514809 | AT50: 20754289 | AU50: 20989076 | AV50: 21236344 | AW50: 21485765 | AX50: 21735976 | AY50: 21989058 | AZ50: 22244027 | BA50: 22501974 | BB50: 22762109 | BC50: 23025549 | BD50: 23291946
C51: Tasa de crecimiento del PIB Nacional [%] | E51: -0.0077251159 | F51: -0.07856463 | G51: 0.11046939 | H51: -0.01221735 | I51: 0.059959875 | J51: -0.010975871 | K51: 0.054422784 | L51: -0.015067482 | M51: 0.055471049 | N51: -0.0056314741 | O51: 0.041862053 | P51: -0.0069127689 | Q51: 0.048663441 | R51: -0.0029066481 | S51: 0.042364147 | T51: -0.0010367634 | U51: 0.03381942 | V51: 0.0033815986 | W51: 0.030044803 | X51: 0.0035935501 | Y51: 0.030177377 | Z51: 0.0048558983 | AA51: 0.025736092 | AB51: 0.006097554 | AC51: 0.018661335 | AD51: 0.0071260039 | AE51: 0.018290905 | AF51: 0.0092021605 | AG51: 0.01688184 | AH51: 0.0052614865 | AI51: 0.015643168 | AJ51: 0.0061633309 | AK51: 0.012174525 | AL51: 0.012839855 | AM51: 0.011667469 | AN51: 0.012173825 | AO51: 0.011584052 | AP51: 0.011989329 | AQ51: 0.011416458 | AR51: 0.011617758 | AS51: 0.011139205 | AT51: 0.011673543 | AU51: 0.011312668 | AV51: 0.01178079 | AW51: 0.011744996 | AX51: 0.011645463 | AY51: 0.011643463 | AZ51: 0.011595248 | BA51: 0.011596266 | BB51: 0.011560533 | BC51: 0.01157363 | BD51: 0.011569619
C53: Sector H - Transporte y almacenamiento
C54: PIB Sector N [Miles USD 2021] | D54: 8027157.6 | E54: 8120225.4 | F54: 6927977.3 | G54: 7835677.5 | H54: 7699029 | I54: 8287017.9 | J54: 8193333.6 | K54: 8756320.8 | L54: 8644358.1 | M54: 9240044.1 | N54: 9207860.2 | O54: 9707414.8 | P54: 9663790.1 | Q54: 10237036 | R54: 10241450 | S54: 10773069 | T54: 10809777 | U54: 11270024 | V54: 11368570 | W54: 11804027 | X54: 11917572 | Y54: 12371564 | Z54: 12512289 | AA54: 12929805 | AB54: 13097671 | AC54: 13439198 | AD54: 13631463 | AE54: 13980623 | AF54: 14213200 | AG54: 14556718 | AH54: 14743974 | AI54: 15082226 | AJ54: 15292450 | AK54: 15590334 | AL54: 15905507 | AM54: 16208034 | AN54: 16525211 | AO54: 16838820 | AP54: 17165531 | AQ54: 17488888 | AR54: 17821836 | AS54: 18152810 | AT54: 18499349 | AU54: 18846026 | AV54: 19207425 | AW54: 19575227 | AX54: 19948173 | AY54: 20328281 | AZ54: 20714682 | BA54: 21108485 | BB54: 21509024 | BC54: 21917432 | BD54: 22333495
C55: Tasa de crecimiento del PIB Nacional [%] | E55: 0.011594115 | F55: -0.1468245 | G55: 0.13101951 | H55: -0.017439268 | I55: 0.076371821 | J55: -0.011304953 | K55: 0.068712844 | L55: -0.012786499 | M55: 0.068910382 | N55: -0.0034830935 | O55: 0.054253062 | P55: -0.0044939546 | Q55: 0.059318939 | R55: 0.0004311687 | S55: 0.051908544 | T55: 0.003407414 | U55: 0.04257696 | V55: 0.008744047 | W55: 0.038303589 | X55: 0.009619168 | Y55: 0.038094323 | Z55: 0.011374907 | AA55: 0.033368477 | AB55: 0.012982834 | AC55: 0.026075456 | AD55: 0.014306292 | AE55: 0.025614226 | AF55: 0.016635682 | AG55: 0.024168948 | AH55: 0.012863911 | AI55: 0.022941701 | AJ55: 0.013938507 | AK55: 0.019479176 | AL55: 0.020215928 | AM55: 0.019020242 | AN55: 0.019569097 | AO55: 0.01897761 | AP55: 0.019402275 | AQ55: 0.018837552 | AR55: 0.019037723 | AS55: 0.018571247 | AT55: 0.019090096 | AU55: 0.01873995 | AV55: 0.019176445 | AW55: 0.019148924 | AX55: 0.019051924 | AY55: 0.019054804 | AZ55: 0.01900805 | BA55: 0.019010817 | BB55: 0.01897523 | BC55: 0.018987747 | BD55: 0.018983203
C57: Sector Servicios
C58: PIB Sector P [Miles USD 2021] | D58: 44494361 | E58: 44274117 | F58: 41322172 | G58: 43064010 | H58: 44154791 | I58: 45576914 | J58: 46817316 | K58: 48275647 | L58: 49215414 | M58: 51091641 | N58: 52382602 | O58: 53940030 | P58: 55098581 | Q58: 57289553 | R58: 58643998 | S58: 60782290 | T58: 62216984 | U58: 64099664 | V58: 65762504 | W58: 67617979 | X58: 69233641 | Y58: 71284184 | Z58: 72924673 | AA58: 74831532 | AB58: 76501371 | AC58: 78021142 | AD58: 79714048 | AE58: 81326158 | AF58: 83153778 | AG58: 84778343 | AH58: 86260647 | AI58: 87904027 | AJ58: 89460619 | AK58: 91349186 | AL58: 92846463 | AM58: 94307419 | AN58: 95877454 | AO58: 97399927 | AP58: 99016825 | AQ58: 1.0043149e+08 | AR58: 1.0187639e+08 | AS58: 1.0328938e+08 | AT58: 1.0465484e+08 | AU58: 1.0594834e+08 | AV58: 1.0718534e+08 | AW58: 1.083956e+08 | AX58: 1.0956991e+08 | AY58: 1.1069432e+08 | AZ58: 1.1176362e+08 | BA58: 1.1277419e+08 | BB58: 1.1372398e+08 | BC58: 1.1461085e+08 | BD58: 1.1542531e+08
C59: Tasa de crecimiento del PIB Nacional [%] | E59: -0.0049499486 | F59: -0.066674272 | G59: 0.04215261 | H59: 0.025329313 | I59: 0.032207653 | J59: 0.027215597 | K59: 0.031149381 | L59: 0.019466688 | M59: 0.03812275 | N59: 0.025267558 | O59: 0.029731794 | P59: 0.021478489 | Q59: 0.03976459 | R59: 0.02364209 | S59: 0.03646224 | T59: 0.023603824 | U59: 0.030259897 | V59: 0.025941479 | W59: 0.028214796 | X59: 0.023893966 | Y59: 0.02961772 | Z59: 0.023013374 | AA59: 0.026148335 | AB59: 0.022314642 | AC59: 0.019865929 | AD59: 0.021698046 | AE59: 0.020223662 | AF59: 0.022472724 | AG59: 0.019536874 | AH59: 0.017484463 | AI59: 0.019051333 | AJ59: 0.017707856 | AK59: 0.021110593 | AL59: 0.016390699 | AM59: 0.015735185 | AN59: 0.01664805 | AO59: 0.015879366 | AP59: 0.01660061 | AQ59: 0.01428707 | AR59: 0.014386941 | AS59: 0.013869676 | AT59: 0.013219756 | AU59: 0.012359702 | AV59: 0.011675482 | AW59: 0.011291271 | AX59: 0.010833597 | AY59: 0.010261981 | AZ59: 0.0096599953 | BA59: 0.0090419655 | BB59: 0.0084221014 | BC59: 0.0077984 | BD59: 0.0071063384
S80: {=R80*(1+Drivers_macroeconómicos_USCUSS!D)} -> #NAME?

Sheet Calibración_BAU_USCUSS
B1: Referencia | F1: Ecuador | G1: 2008 | H1: 2009 | I1: 2010 | J1: 2011 | K1: 2012 | L1: 2013 | M1: 2014 | N1: 2015 | O1: 2016 | P1: 2017 | Q1: 2018 | R1: 2019 | S1: 2020 | T1: 2021 | U1: 2022 | V1: 2023 | W1: 2024 | X1: 2025 | Y1: 2026 | Z1: 2027 | AA1: 2028 | AB1: 2029 | AC1: 2030 | AD1: 2031 | AE1: 2032 | AF1: 2033 | AG1: 2034 | AH1: 2035 | AI1: 2036 | AJ1: 2037 | AK1: 2038 | AL1: 2039 | AM1: 2040 | AN1: 2041 | AO1: 2042 | AP1: 2043 | AQ1: 2044 | AR1: 2045 | AS1: 2046 | AT1: 2047 | AU1: 2048 | AV1: 2049 | AW1: 2050 | AX1: 2051 | AY1: 2052 | AZ1: 2053 | BA1: 2054 | BB1: 2055 | BC1: 2056 | BD1: 2057 | BE1: 2058 | BF1: 2059 | BG1: 2060 | BH1: 2061 | BI1: 2062 | BJ1: 2063 | BK1: 2064 | BL1: 2065 | BM1: 2066 | BN1: 2067 | BO1: 2068 | BP1: 2069 | BQ1: 2070
D3: DATOS PARA CALIBRAR PROYECCIONES
E6: GRÁFICO UTCUTS-1 | F6: TABLA UTCUTS - 1: Cobertura uso de suelos
F7: Uso de suelos [ha]
B8: ESPAC | F8: Montes y bosques [ha] | I8: 3504127 | J8: 3536454 | K8: 3583056 | L8: 3538424 | M8: 5758859 | N8: 5729799 | O8: 5773290 | P8: 5675402 | Q8: 5740641 | R8: 6040896 | S8: 6112324 | T8: 5900560 | U8: 5900560 | V8: 5900560 | W8: 5900560 | X8: 5900560 | Y8: 5900560 | Z8: 5900560 | AA8: 5900560 | AB8: 5900560 | AC8: 5900560 | AD8: 5900560 | AE8: 5900560 | AF8: 5900560 | AG8: 5900560 | AH8: 5900560 | AI8: 5900560 | AJ8: 5900560 | AK8: 5900560 | AL8: 5900560 | AM8: 5900560 | AN8: 5900560 | AO8: 5900560 | AP8: 5900560 | AQ8: 5900560 | AR8: 5900560 | AS8: 5900560 | AT8: 5900560 | AU8: 5900560 | AV8: 5900560 | AW8: 5900560
F9: Cultivos permanentes [ha] | I9: 1391379 | J9: 1379473 | K9: 1382918 | L9: 1469363 | M9: 1417104 | N9: 1483366 | O9: 1439117 | P9: 1430497 | Q9: 1385805 | R9: 1439504 | S9: 1442973 | T9: 1423372 | U9: 1423372 | V9: 1423372 | W9: 1423372 | X9: 1423372 | Y9: 1423372 | Z9: 1423372 | AA9: 1423372 | AB9: 1423372 | AC9: 1423372 | AD9: 1423372 | AE9: 1423372 | AF9: 1423372 | AG9: 1423372 | AH9: 1423372 | AI9: 1423372 | AJ9: 1423372 | AK9: 1423372 | AL9: 1423372 | AM9: 1423372 | AN9: 1423372 | AO9: 1423372 | AP9: 1423372 | AQ9: 1423372 | AR9: 1423372 | AS9: 1423372 | AT9: 1423372 | AU9: 1423372 | AV9: 1423372 | AW9: 1423372
F10: Cultivos transitorios y barbechos [ha] | I10: 992369 | J10: 982312 | K10: 1020870 | L10: 1003271 | M10: 876498 | N10: 950649 | O10: 849685 | P10: 904224 | Q10: 799494 | R10: 769708 | S10: 822516 | T10: 841994 | U10: 841994 | V10: 841994 | W10: 841994 | X10: 841994 | Y10: 841994 | Z10: 841994 | AA10: 841994 | AB10: 841994 | AC10: 841994 | AD10: 841994 | AE10: 841994 | AF10: 841994 | AG10: 841994 | AH10: 841994 | AI10: 841994 | AJ10: 841994 | AK10: 841994 | AL10: 841994 | AM10: 841994 | AN10: 841994 | AO10: 841994 | AP10: 841994 | AQ10: 841994 | AR10: 841994 | AS10: 841994 | AT10: 841994 | AU10: 841994 | AV10: 841994 | AW10: 841994
F11: Descanso [ha] | I11: 193957 | J11: 173442 | K11: 126982 | L11: 191159 | M11: 93574 | N11: 117390 | O11: 125946 | P11: 129268 | Q11: 168446 | R11: 219492 | S11: 215014 | T11: 163017 | U11: 163017 | V11: 163017 | W11: 163017 | X11: 163017 | Y11: 163017 | Z11: 163017 | AA11: 163017 | AB11: 163017 | AC11: 163017 | AD11: 163017 | AE11: 163017 | AF11: 163017 | AG11: 163017 | AH11: 163017 | AI11: 163017 | AJ11: 163017 | AK11: 163017 | AL11: 163017 | AM11: 163017 | AN11: 163017 | AO11: 163017 | AP11: 163017 | AQ11: 163017 | AR11: 163017 | AS11: 163017 | AT11: 163017 | AU11: 163017 | AV11: 163017 | AW11: 163017
F12: Otros usos [ha] | I12: 217058 | J12: 210584 | K12: 205657 | L12: 216225 | M12: 468180 | N12: 612090 | O12: 719109 | P12: 757791 | Q12: 796518 | R12: 662305 | S12: 681476 | T12: 712757 | U12: 712757 | V12: 712757 | W12: 712757 | X12: 712757 | Y12: 712757 | Z12: 712757 | AA12: 712757 | AB12: 712757 | AC12: 712757 | AD12: 712757 | AE12: 712757 | AF12: 712757 | AG12: 712757 | AH12: 712757 | AI12: 712757 | AJ12: 712757 | AK12: 712757 | AL12: 712757 | AM12: 712757 | AN12: 712757 | AO12: 712757 | AP12: 712757 | AQ12: 712757 | AR12: 712757 | AS12: 712757 | AT12: 712757 | AU12: 712757 | AV12: 712757 | AW12: 712757
F13: Páramos [ha] | I13: 539475 | J13: 565857 | K13: 608272 | L13: 491891 | M13: 499258 | N13: 454347 | O13: 377791 | P13: 332418 | Q13: 252612 | R13: 270986 | S13: 249139 | T13: 233074 | U13: 233074 | V13: 233074 | W13: 233074 | X13: 233074 | Y13: 233074 | Z13: 233074 | AA13: 233074 | AB13: 233074 | AC13: 233074 | AD13: 233074 | AE13: 233074 | AF13: 233074 | AG13: 233074 | AH13: 233074 | AI13: 233074 | AJ13: 233074 | AK13: 233074 | AL13: 233074 | AM13: 233074 | AN13: 233074 | AO13: 233074 | AP13: 233074 | AQ13: 233074 | AR13: 233074 | AS13: 233074 | AT13: 233074 | AU13: 233074 | AV13: 233074 | AW13: 233074
F14: Pastos cultivados [ha] | I14: 3409952 | J14: 3425412 | K14: 3553008 | L14: 3227321 | M14: 2259447 | N14: 2531442 | O14: 2300539 | P14: 2447634 | Q14: 2379042 | R14: 1985494 | S14: 2067795 | T14: 2376551 | U14: 2376551 | V14: 2376551 | W14: 2376551 | X14: 2376551 | Y14: 2376551 | Z14: 2376551 | AA14: 2376551 | AB14: 2376551 | AC14: 2376551 | AD14: 2376551 | AE14: 2376551 | AF14: 2376551 | AG14: 2376551 | AH14: 2376551 | AI14: 2376551 | AJ14: 2376551 | AK14: 2376551 | AL14: 2376551 | AM14: 2376551 | AN14: 2376551 | AO14: 2376551 | AP14: 2376551 | AQ14: 2376551 | AR14: 2376551 | AS14: 2376551 | AT14: 2376551 | AU14: 2376551 | AV14: 2376551 | AW14: 2376551
F15: Pastos permanentes [ha] | I15: 1509972 | J15: 1385547 | K15: 1423114 | L15: 1623359 | M15: 828333 | N15: 706777 | O15: 800496 | P15: 677911 | Q15: 715273 | R15: 915843 | S15: 841320 | T15: 646139 | U15: 646139 | V15: 646139 | W15: 646139 | X15: 646139 | Y15: 646139 | Z15: 646139 | AA15: 646139 | AB15: 646139 | AC15: 646139 | AD15: 646139 | AE15: 646139 | AF15: 646139 | AG15: 646139 | AH15: 646139 | AI15: 646139 | AJ15: 646139 | AK15: 646139 | AL15: 646139 | AM15: 646139 | AN15: 646139 | AO15: 646139 | AP15: 646139 | AQ15: 646139 | AR15: 646139 | AS15: 646139 | AT15: 646139 | AU15: 646139 | AV15: 646139 | AW15: 646139
F16: Uso de suelos [Mha]
B17: ESPAC | F17: Montes y bosques [Mha] | I17: =I8/1000000 -> 3.504127 | J17: =J8/1000000 -> 3.536454 | K17: =K8/1000000 -> 3.583056 | L17: =L8/1000000 -> 3.538424 | M17: =M8/1000000 -> 5.758859 | N17: =N8/1000000 -> 5.729799 | O17: =O8/1000000 -> 5.77329 | P17: =P8/1000000 -> 5.675402 | ... AW17: =AW8/1000000 -> 5.90056
F18: Cultivos permanentes [Mha] | I18: =I9/1000000 -> 1.391379 | J18: =J9/1000000 -> 1.379473 | K18: =K9/1000000 -> 1.382918 | L18: =L9/1000000 -> 1.469363 | M18: =M9/1000000 -> 1.417104 | N18: =N9/1000000 -> 1.483366 | O18: =O9/1000000 -> 1.439117 | P18: =P9/1000000 -> 1.430497 | ... AW18: =AW9/1000000 -> 1.423372
F19: Cultivos transitorios y barbechos [Mha] | I19: =I10/1000000 -> 0.992369 | J19: =J10/1000000 -> 0.982312 | K19: =K10/1000000 -> 1.02087 | L19: =L10/1000000 -> 1.003271 | M19: =M10/1000000 -> 0.876498 | N19: =N10/1000000 -> 0.950649 | O19: =O10/1000000 -> 0.849685 | P19: =P10/1000000 -> 0.904224 | ... AW19: =AW10/1000000 -> 0.841994
F20: Descanso [Mha] | I20: =I11/1000000 -> 0.193957 | J20: =J11/1000000 -> 0.173442 | K20: =K11/1000000 -> 0.126982 | L20: =L11/1000000 -> 0.191159 | M20: =M11/1000000 -> 0.093574 | N20: =N11/1000000 -> 0.11739 | O20: =O11/1000000 -> 0.125946 | P20: =P11/1000000 -> 0.129268 | ... AW20: =AW11/1000000 -> 0.163017
F21: Otros usos [Mha] | I21: =I12/1000000 -> 0.217058 | J21: =J12/1000000 -> 0.210584 | K21: =K12/1000000 -> 0.205657 | L21: =L12/1000000 -> 0.216225 | M21: =M12/1000000 -> 0.46818 | N21: =N12/1000000 -> 0.61209 | O21: =O12/1000000 -> 0.719109 | P21: =P12/1000000 -> 0.757791 | ... AW21: =AW12/1000000 -> 0.712757
F22: Páramos [Mha] | I22: =I13/1000000 -> 0.539475 | J22: =J13/1000000 -> 0.565857 | K22: =K13/1000000 -> 0.608272 | L22: =L13/1000000 -> 0.491891 | M22: =M13/1000000 -> 0.499258 | N22: =N13/1000000 -> 0.454347 | O22: =O13/1000000 -> 0.377791 | P22: =P13/1000000 -> 0.332418 | ... AW22: =AW13/1000000 -> 0.233074
F23: Pastos cultivados [Mha] | I23: =I14/1000000 -> 3.409952 | J23: =J14/1000000 -> 3.425412 | K23: =K14/1000000 -> 3.553008 | L23: =L14/1000000 -> 3.227321 | M23: =M14/1000000 -> 2.259447 | N23: =N14/1000000 -> 2.531442 | O23: =O14/1000000 -> 2.300539 | P23: =P14/1000000 -> 2.447634 | ... AW23: =AW14/1000000 -> 2.376551
F24: Pastos permanentes [Mha] | I24: =I15/1000000 -> 1.509972 | J24: =J15/1000000 -> 1.385547 | K24: =K15/1000000 -> 1.423114 | L24: =L15/1000000 -> 1.623359 | M24: =M15/1000000 -> 0.828333 | N24: =N15/1000000 -> 0.706777 | O24: =O15/1000000 -> 0.800496 | P24: =P15/1000000 -> 0.677911 | ... AW24: =AW15/1000000 -> 0.646139
F25: TOTAL COBERTURAS [Mha] | I25: =SUM(I17:I24) -> 11.758289 | J25: =SUM(J17:J24) -> 11.659081 | K25: =SUM(K17:K24) -> 11.903877 | L25: =SUM(L17:L24) -> 11.761013 | M25: =SUM(M17:M24) -> 12.201253 | N25: =SUM(N17:N24) -> 12.58586 | O25: =SUM(O17:O24) -> 12.385973 | P25: =SUM(P17:P24) -> 12.355145 | ... AW25: =SUM(AW17:AW24) -> 12.297464
D28: DATOS ÁREAS PROTEGIDAS
E31: GRÁFICO UTCUTS-2 | F31: TABLA UTCUTS - 2: Cobertura áreas protegidas
F32: Áreas protegidas [Mha]
B33: SNAP | F33: Galápagos [Mha] | I33: 0.79579217 | J33: 0.79579217 | K33: 0.79579217 | L33: 0.79579217 | M33: 0.79579217 | N33: 0.79579217 | O33: 0.79579217 | P33: 0.79579217 | Q33: 0.79579217 | R33: 0.79579217 | S33: 0.79579217 | T33: 0.79579217 | U33: 0.79579217 | V33: 0.79579217 | W33: 0.79579217 | X33: 0.79579217 | Y33: 0.79579217 | Z33: 0.79579217 | AA33: 0.79579217 | AB33: 0.79579217 | AC33: 0.79579217 | AD33: 0.79579217 | AE33: 0.79579217 | AF33: 0.79579217 | AG33: 0.79579217 | AH33: 0.79579217 | AI33: 0.79579217 | AJ33: 0.79579217 | AK33: 0.79579217 | AL33: 0.79579217 | AM33: 0.79579217 | AN33: 0.79579217 | AO33: 0.79579217 | AP33: 0.79579217 | AQ33: 0.79579217 | AR33: 0.79579217 | AS33: 0.79579217 | AT33: 0.79579217 | AU33: 0.79579217 | AV33: 0.79579217 | AW33: 0.79579217
F34: Bosques protegidos/Protected forest [Mha] | I34: 2.2633933 | J34: 2.2794224 | K34: 2.2794224 | L34: 2.2794224 | M34: 2.3725857 | N34: 2.3725857 | O34: 2.3747312 | P34: 2.3747312 | Q34: 2.4084734 | R34: 2.4088211 | S34: 2.4088211 | T34: 2.4117235 | U34: 2.4117235 | V34: 2.4117235 | W34: 2.4117235 | X34: 2.4117235 | Y34: 2.4117235 | Z34: 2.4117235 | AA34: 2.4117235 | AB34: 2.4117235 | AC34: 2.4117235 | AD34: 2.4117235 | AE34: 2.4117235 | AF34: 2.4117235 | AG34: 2.4117235 | AH34: 2.4117235 | AI34: 2.4117235 | AJ34: 2.4117235 | AK34: 2.4117235 | AL34: 2.4117235 | AM34: 2.4117235 | AN34: 2.4117235 | AO34: 2.4117235 | AP34: 2.4117235 | AQ34: 2.4117235 | AR34: 2.4117235 | AS34: 2.4117235 | AT34: 2.4117235 | AU34: 2.4117235 | AV34: 2.4117235 | AW34: 2.4117235
F35: Pradera protegida/Protected grassland [Mha] | I35: 1.8351789 | J35: 1.8351789 | K35: 1.838396 | L35: 1.838396 | M35: 1.838396 | N35: 1.838396 | O35: 1.838396 | P35: 1.8914899 | Q35: 1.8934445 | R35: 1.922489 | S35: 1.9272792 | T35: 1.95791 | U35: 1.95791 | V35: 1.95791 | W35: 1.95791 | X35: 1.95791 | Y35: 1.95791 | Z35: 1.95791 | AA35: 1.95791 | AB35: 1.95791 | AC35: 1.95791 | AD35: 1.95791 | AE35: 1.95791 | AF35: 1.95791 | AG35: 1.95791 | AH35: 1.95791 | AI35: 1.95791 | AJ35: 1.95791 | AK35: 1.95791 | AL35: 1.95791 | AM35: 1.95791 | AN35: 1.95791 | AO35: 1.95791 | AP35: 1.95791 | AQ35: 1.95791 | AR35: 1.95791 | AS35: 1.95791 | AT35: 1.95791 | AU35: 1.95791 | AV35: 1.95791 | AW35: 1.95791
F36: Manglares [Mha] | I36: 0.37320953 | J36: 0.37568766 | K36: 0.38884296 | L36: 0.38884296 | M36: 0.38884296 | N36: 0.53110941 | O36: 0.57106191 | P36: 0.57106191 | Q36: 0.57106191 | R36: 0.57106191 | S36: 0.57106191 | T36: 0.57106191 | U36: 0.57106191 | V36: 0.57106191 | W36: 0.57106191 | X36: 0.57106191 | Y36: 0.57106191 | Z36: 0.57106191 | AA36: 0.57106191 | AB36: 0.57106191 | AC36: 0.57106191 | AD36: 0.57106191 | AE36: 0.57106191 | AF36: 0.57106191 | AG36: 0.57106191 | AH36: 0.57106191 | AI36: 0.57106191 | AJ36: 0.57106191 | AK36: 0.57106191 | AL36: 0.57106191 | AM36: 0.57106191 | AN36: 0.57106191 | AO36: 0.57106191 | AP36: 0.57106191 | AQ36: 0.57106191 | AR36: 0.57106191 | AS36: 0.57106191 | AT36: 0.57106191 | AU36: 0.57106191 | AV36: 0.57106191 | AW36: 0.57106191
AZ38: =U79-AW79 -> 0.018558031
D39: DATOS PARA MODELO OSEMOSYS
U40: =(T64-U64)/T64 -> 0.0076 | V40: =(U64-V64)/U64 -> 0.0076 | W40: =(V64-W64)/V64 -> 0.0076 | X40: =(W64-X64)/W64 -> 0.0076 | Y40: =(X64-Y64)/X64 -> 0.0076 | Z40: =(Y64-Z64)/Y64 -> 0.0076 | AA40: =(Z64-AA64)/Z64 -> 0.0076 | AB40: =(AA64-AB64)/AA64 -> 0.0076 | ... AD40: =(AC64-AD64)/AC64 -> 0.0076 | AU40: =1-AU64/AT64 -> 0.0076 | AV40: =1-AV64/AU64 -> 0.0076 | AW40: =1-AW64/AV64 -> 0.0076
A42: DRIVERS | E42: GRÁFICO UTCUTS-3 | F42: TABLA UTCUTS - 3: Coberturas generales - MAG + MAATE
F43: Coberturas generales [ha]
B44: MAG+MAATE | D44: Bosque | F44: Bosque nativo [ha] | G44: 13038367 | M44: 12753387 | O44: 12631198 | Q44: 12514340
F45: Plantación forestal [ha] | G45: 62196.93 | M45: 130072.41 | O45: 123719.94 | Q45: 121995.27
D46: Tierra agropecuaria | F46: Cultivo anual [ha] | G46: 611941.95 | M46: 1094904.6 | O46: 8933864.5 | Q46: 8999553.2
F47: Cultivo semipermanente [ha] | G47: 260389.08 | M47: 480131.91
F48: Cultivo permanente [ha] | G48: 167305.59 | M48: 917407.35
F49: Pastizal [ha] | G49: 1454890.3 | M49: 4959938.7
F50: Mosaico agropecuario [ha] | G50: 6337045.3 | M50: 1266774.3
D51: Vegetación arbustiva | F51: Vegetación arbustiva [ha] | G51: 587499.84 | M51: 810626.94 | O51: 763180.11 | Q51: 768908.61
F52: Vegetación herbácea [ha] | G52: 109528.02 | M52: 89167.14 | O52: 83035.17 | Q52: 85768.2
F53: Páramo [ha] | G53: 1465935.8 | M53: 1523970.1 | O53: 1515272.5 | Q53: 1521159.7
D54: Cuerpo de agua | F54: Cuerpo de agua natural [ha] | G54: 348472.62 | M54: 305169.39 | O54: 295476.12 | Q54: 291292.2
F55: Cuerpo de agua artificial [ha] | G55: 157677.57 | M55: 199934.1 | O55: 199287.27 | Q55: 200705.67
D56: Zona antrópica | F56: Área poblada [ha] | G56: 165538.44 | M56: 224935.38 | O56: 229182.39 | Q56: 255251.97
F57: Infraestructura [ha] | G57: 11615.85 | M57: 21206.79 | O57: 23884.2 | Q57: 30656.25
D58: Otras tierras | F58: Área sin cobertura vegetal [ha] | G58: 109686.69 | M58: 112568.04 | O58: 93841.92 | Q58: 102446.37
F59: Glaciar [ha] | G59: 9968.49 | M59: 7865.73 | O59: 6279.21 | Q59: 6144.03
F60: Sin información [ha] | G60: 0 | M60: 0 | O60: 0 | Q60: 0
F61: TOTAL COBERTURAS [ha] | G61: =SUM(G44:G60) -> 24898060 | M61: =SUM(M44:M60) -> 24898060 | O61: =SUM(O44:O60) -> 24898221 | Q61: =SUM(Q44:Q60) -> 24898221
F62: Coberturas generales [Mha]
C63: Leyendas usadas en INGEI 2018 (NIVEL I IPCC) | D63: Leyendas usadas por MAATE en los mapas interactivos y reportes de deforestacion (Nivel I IPCC) | F63: Niveles para OSEMOSYS
A64: Tasa de deforestación neta 2018 y 2019 con (-0.46%) a partir de 2020 con tasa de def. neta de -0.76% | B64: MAG+MAATE | C64: Tierras forestales | D64: Bosque | F64: Bosque nativo con deforestacion neta [Mha] | G64: =G44/1000000 -> 13.038367 | M64: =M44/1000000 -> 12.753387 | O64: =O44/1000000 -> 12.631198 | Q64: =Q44/1000000 -> 12.51434 | R64: =Q64*(1-0.0046) -> 12.456774 | S64: =R64*(1-0.0076) -> 12.362102 | T64: =S64*(1-0.0076) -> 12.26815 | U64: =T64*(1-0.0076) -> 12.174912 | V64: =U64*(1-0.0076) -> 12.082383 | W64: =V64*(1-0.0076) -> 11.990557 | X64: =W64*(1-0.0076) -> 11.899428 | Y64: =X64*(1-0.0076) -> 11.808993 | Z64: =Y64*(1-0.0076) -> 11.719244 | ... BQ64: =BP64*(1-0.0076) -> 8.4417037
A65: Se usa una tasa de deforestacion bruta de -0.75% para 2019 y a partir de 2020 se usa -0.78% | F65: Bosque proyectado con def. bruta [Mha] | Q65: 12.49024 | R65: =Q64*(1-0.0075) -> 12.420482 | S65: =R64*(1-0.0078) -> 12.359611 | T65: =S64*(1-0.0078) -> 12.265678 | U65: =T64*(1-0.0078) -> 12.172459 | V65: =U64*(1-0.0078) -> 12.079948 | W65: =V64*(1-0.0078) -> 11.98814 | X65: =W64*(1-0.0078) -> 11.89703 | Y65: =X64*(1-0.0078) -> 11.806613 | Z65: =Y64*(1-0.0078) -> 11.716883 | ... BQ65: =BP64*(1-0.0078) -> 8.4400025
F66: Def. bruta anual [Mha] | Q66: 0.082529 | R66: =Q64-R65 -> 0.093857546 | S66: =R64-S65 -> 0.097162834 | T66: =S64-T65 -> 0.096424396 | U66: =T64-U65 -> 0.095691571 | V66: =U64-V65 -> 0.094964315 | W66: =V64-W65 -> 0.094242586 | X66: =W64-X65 -> 0.093526342 | Y66: =X64-Y65 -> 0.092815542 | ... BQ66: =BP64-BQ65 -> 0.066349546
F67: Bosque regenerado [Mha] | Q67: =Q64-Q65 -> 0.02409957 | R67: =R64-R65 -> 0.036291585 | S67: =S64-S65 -> 0.0024913547 | T67: =T64-T65 -> 0.0024724204 | U67: =U64-U65 -> 0.00245363 | V67: =V64-V65 -> 0.0024349824 | W67: =W64-W65 -> 0.0024164766 | X67: =X64-X65 -> 0.0023981113 | ... BQ67: =BQ64-BQ65 -> 0.0017012704
F68: Bosque nativo no protegido [Mha] | S68: =S64-S69 -> 6.4022095 | T68: =T64-T69 -> 6.3082575 | U68: =U64-U69 -> 6.2150196 | V68: =V64-V69 -> 6.1224902 | W68: =W64-W69 -> 6.0306641 | X68: =X64-X69 -> 5.9395359 | Y68: =Y64-Y69 -> 5.8491002 | Z68: =Z64-Z69 -> 5.7593519 | ... BQ68: =BQ64-BQ69 -> 2.4818111
F69: Bosque nativo bajo régimen de proteccion legal [Mha] | Q69: 5.9598926 | R69: 5.9598926 | S69: 5.9598926 | T69: 5.9598926 | U69: 5.9598926 | V69: 5.9598926 | W69: 5.9598926 | X69: 5.9598926 | Y69: 5.9598926 | Z69: 5.9598926 | AA69: 5.9598926 | AB69: 5.9598926 | AC69: 5.9598926 | AD69: 5.9598926 | AE69: 5.9598926 | AF69: 5.9598926 | AG69: 5.9598926 | AH69: 5.9598926 | AI69: 5.9598926 | AJ69: 5.9598926 | AK69: 5.9598926 | AL69: 5.9598926 | AM69: 5.9598926 | AN69: 5.9598926 | AO69: 5.9598926 | AP69: 5.9598926 | AQ69: 5.9598926 | AR69: 5.9598926 | AS69: 5.9598926 | AT69: 5.9598926 | AU69: 5.9598926 | AV69: 5.9598926 | AW69: 5.9598926 | AX69: 5.9598926 | AY69: 5.9598926 | AZ69: 5.9598926 | BA69: 5.9598926 | BB69: 5.9598926 | BC69: 5.9598926 | BD69: 5.9598926 | BE69: 5.9598926 | BF69: 5.9598926 | BG69: 5.9598926 | BH69: 5.9598926 | BI69: 5.9598926 | BJ69: 5.9598926 | BK69: 5.9598926 | BL69: 5.9598926 | BM69: 5.9598926 | BN69: 5.9598926 | BO69: 5.9598926 | BP69: 5.9598926 | BQ69: 5.9598926
A70: El sector silvicultura aporta en 1 % al PIB Nacional, entonces se proyecta que el sector crezca a un 1% del crecimiento del PIB | F70: Plantación forestal [Mha] | G70: =G45/1000000 -> 0.06219693 | M70: =M45/1000000 -> 0.13007241 | O70: =O45/1000000 -> 0.12371994 | Q70: =Q45/1000000 -> 0.12199527 | R70: =Q70*(1+ 0.01*Drivers_macroeconómicos_USCUSS!E17) -> 0.12199542 | S70: =R70*(1+ 0.01*Drivers_macroeconómicos_USCUSS!F17) -> 0.12190041 | T70: =S70*(1+ 0.01*Drivers_macroeconómicos_USCUSS!G17) -> 0.12195204 | U70: =T70*(1+ 0.01*Drivers_macroeconómicos_USCUSS!H17) -> 0.12198497 | V70: =U70*(1+ 0.01*Drivers_macroeconómicos_USCUSS!I17) -> 0.12202278 | W70: =V70*(1+ 0.01*Drivers_macroeconómicos_USCUSS!J17) -> 0.12205939 | X70: =W70*(1+ 0.01*Drivers_macroeconómicos_USCUSS!K17) -> 0.12209235 | Y70: =X70*(1+ 0.01*Drivers_macroeconómicos_USCUSS!L17) -> 0.12212043 | ... BQ70: =BP70*(1+ 0.01*Drivers_macroeconómicos_USCUSS!BD17) -> 0.1232093
A71: Driver: la superficie destinada a cultivos crece con el PIB sectorial, se estima que el PIB Agricultura, silvicultura y pesca incide en un 34% en la expansion de suelo agricola | C71: Tierra de cultivo | D71: Tierra agropecuaria
F72: Cultivos [Mha] | G72: 7.376682 | M72: 3.7592182 | O72: 3.85228 | Q72: 3.880607 | R72: =Q72*(1+0.34*Drivers_macroeconómicos_USCUSS!E31) -> 3.9019482 | S72: =R72*(1+0.34*Drivers_macroeconómicos_USCUSS!F31) -> 3.906692 | T72: =S72*(1+0.34*Drivers_macroeconómicos_USCUSS!G31) -> 3.9516727 | U72: =T72*(1+0.34*Drivers_macroeconómicos_USCUSS!H31) -> 3.997943 | V72: =U72*(1+0.34*Drivers_macroeconómicos_USCUSS!I31) -> 4.0379279 | W72: =V72*(1+0.34*Drivers_macroeconómicos_USCUSS!J31) -> 4.0806905 | X72: =W72*(1+0.34*Drivers_macroeconómicos_USCUSS!K31) -> 4.1134669 | Y72: =X72*(1+0.34*Drivers_macroeconómicos_USCUSS!L31) -> 4.1407383 | ... BQ72: =BP72*(1+0.34*Drivers_macroeconómicos_USCUSS!BD31) -> 5.5113889
A75: Flexible | F75: Pastura [Mha] | G75: =G49/1000000 -> 1.4548903 | M75: =M49/1000000 -> 4.9599387 | O75: 5.08158 | Q75: 5.118945 | R75: =$Q$88-R64-R70-R72-R77-R79-R81-R84 -> 5.1571372 | S75: =$Q$88-S64-S70-S72-S77-S79-S81-S84 -> 5.2494749 | T75: =$Q$86-T64-T70-T72-T77-T79-T81-T84 -> 5.300745 | U75: =$Q$86-U64-U70-U72-U77-U79-U81-U84 -> 5.3500272 | V75: =$Q$86-V64-V70-V72-V77-V79-V81-V84 -> 5.4048968 | W75: =$Q$86-W64-W70-W72-W77-W79-W81-W84 -> 5.4563043 | X75: =$Q$86-X64-X70-X72-X77-X79-X81-X84 -> 5.5170221 | Y75: =$Q$86-Y64-Y70-Y72-Y77-Y79-Y81-Y84 -> 5.5825796 | Z75: =$Q$86-Z64-Z70-Z72-Z77-Z79-Z81-Z84 -> 5.6389616 | AA75: =$Q$86-AA64-AA70-AA72-AA77-AA79-AA81-AA84 -> 5.6998868 | ... BQ75: =$Q$86-BQ64-BQ70-BQ72-BQ77-BQ79-BQ81-BQ84 -> 7.7288738
A76: Decrece con la tasa de crecimiento de cultivos y ganaderia | C76: Pastizales (grasslands) | D76: Vegetación arbustiva y herbácea (incluye páramo)
F77: Pastizales (grasslands) [Mha] | G77: 2.1629637 | M77: 2.4237642 | O77: 2.3614878 | Q77: 2.3758365 | R77: 2.369059 | S77: 2.361968 | T77: 2.354877 | U77: 2.347786 | V77: 2.340695 | W77: 2.333604 | X77: 2.326513 | Y77: 2.319422 | Z77: 2.312331 | AA77: 2.30524 | AB77: 2.298149 | AC77: 2.291058 | AD77: 2.283967 | AE77: 2.276876 | AF77: 2.269785 | AG77: 2.262694 | AH77: 2.255603 | AI77: 2.248512 | AJ77: 2.241421 | AK77: 2.23433 | AL77: 2.227239 | AM77: 2.220148 | AN77: 2.213057 | AO77: 2.205966 | AP77: 2.198875 | AQ77: 2.191784 | AR77: 2.184693 | AS77: 2.177602 | AT77: 2.170511 | AU77: 2.16342 | AV77: 2.156329 | AW77: 2.149238 | AX77: 2.142147 | AY77: 2.135056 | AZ77: 2.127965 | BA77: 2.120874 | BB77: 2.113783 | BC77: 2.106692 | BD77: 2.099601 | BE77: 2.09251 | BF77: 2.085419 | BG77: 2.078328 | BH77: 2.071237 | BI77: 2.064146 | BJ77: 2.057055 | BK77: 2.049964 | BL77: 2.042873 | BM77: 2.035782 | BN77: 2.028691 | BO77: 2.0216 | BP77: 2.014509 | BQ77: 2.007418
A79: se mantiene con la tasa 2016-2018 | C79: Humedal | D79: Cuerpo de agua/humedal | F79: Humedal [Mha] | G79: 0.50615019 | M79: 0.50510349 | O79: 0.49476339 | Q79: 0.49199787 | R79: =Q79*(1-0.00138) -> 0.49131891 | S79: =R79*(1-0.00138) -> 0.49064089 | T79: =S79*(1-0.00138) -> 0.48996381 | U79: =T79*(1-0.00138) -> 0.48928766 | V79: =U79*(1-0.00138) -> 0.48861244 | W79: =V79*(1-0.00138) -> 0.48793816 | X79: =W79*(1-0.00138) -> 0.4872648 | Y79: =X79*(1-0.00138) -> 0.48659238 | ... BQ79: =BP79*(1-0.00138) -> 0.45790641
A81: Tasa de crecimiento poblacional | C81: Asentamientos | D81: Zona antrópica | F81: Asentamientos [Mha] | G81: 0.17715429 | M81: 0.24614217 | O81: 0.25306659 | Q81: 0.28590822 | R81: =Q81*(1+Drivers_macroeconómicos_USCUSS!E8) -> 0.29001591 | S81: =R81*(1+Drivers_macroeconómicos_USCUSS!F8) -> 0.29409133 | T81: =S81*(1+Drivers_macroeconómicos_USCUSS!G8) -> 0.29813278 | U81: =T81*(1+Drivers_macroeconómicos_USCUSS!H8) -> 0.30214066 | V81: =U81*(1+Drivers_macroeconómicos_USCUSS!I8) -> 0.30611436 | W81: =V81*(1+Drivers_macroeconómicos_USCUSS!J8) -> 0.31005151 | X81: =W81*(1+Drivers_macroeconómicos_USCUSS!K8) -> 0.31395138 | Y81: =X81*(1+Drivers_macroeconómicos_USCUSS!L8) -> 0.31780959 | ... BQ81: =BP81*(1+Drivers_macroeconómicos_USCUSS!BD8) -> 0.42027565
A83: Glaciares representan el 6% de la cobertura otras tierras y se estima que se reducen en 1 % anual hasta el 2050. El otro 94% de tierra sin cobertura vegetal se estima que aumentara debido a procesos erosivos en una tasa del 1.4% anual hasta 2050 | C83: Otras tierras | D83: Otras tierras | F83: Otras tierras [Mha] | G83: 0.11965518
M84: 0.12043377 | O84: 0.10012113 | Q84: 0.1085904 | R84: =Q84*(1+0.0669*((-0.0119))+ 0.933087*(0.01429)) -> 0.10995187 | S84: =R84*(1+0.0669*((-0.0119))+ 0.933087*(0.01429)) -> 0.11133042 | T84: =S84*(1+0.0669*((-0.0119))+ 0.933087*(0.01429)) -> 0.11272625 | U84: =T84*(0.0669*(1-0.0119)+ 0.933087*(1+0.01429)) -> 0.11413811 | V84: =U84*(0.0669*(1-0.0119)+ 0.933087*(1+0.01429)) -> 0.11556765 | W84: =V84*(0.0669*(1-0.0119)+ 0.933087*(1+0.01429)) -> 0.11701511 | X84: =W84*(0.0669*(1-0.0119)+ 0.933087*(1+0.01429)) -> 0.11848068 | Y84: =X84*(0.0669*(1-0.0119)+ 0.933087*(1+0.01429)) -> 0.11996462 | Z84: =Y84*(0.0669*(1-0.0119)+ 0.933087*(1+0.01429)) -> 0.12146714 | AA84: =Z84*(0.0669*(1-0.0119)+ 0.933087*(1+0.01429)) -> 0.12298848 | AB84: =AA84*(0.0669*(1-0.0119)+ 0.933087*(1+0.01429)) -> 0.12452888 | ... BQ84: =BP84*(0.0669*(1-0.0119)+ 0.933087*(1+0.01429)) -> 0.20744397
F86: TOTAL COBERTURAS [Mha] | G86: =SUM(G64:G85) -> 24.89806 | M86: =SUM(M64:M85) -> 24.89806 | O86: =SUM(O64:O85) -> 24.898217 | Q86: =Q64+Q70+Q72+Q75+Q77+Q79+Q81+Q84 -> 24.89822 | R86: =R64+R70+R72+R75+R77+R79+R81+R84 -> 24.8982 | S86: =S64+S70+S72+S75+S77+S79+S81+S84 -> 24.8982 | T86: =T64+T70+T72+T75+T77+T79+T81+T84 -> 24.89822 | U86: =U64+U70+U72+U75+U77+U79+U81+U84 -> 24.89822 | V86: =V64+V70+V72+V75+V77+V79+V81+V84 -> 24.89822 | W86: =W64+W70+W72+W75+W77+W79+W81+W84 -> 24.89822 | X86: =X64+X70+X72+X75+X77+X79+X81+X84 -> 24.89822 | ... BQ86: =BQ64+BQ70+BQ72+BQ75+BQ77+BQ79+BQ81+BQ84 -> 24.89822
Q88: =24.8982 -> 24.8982
D91: Extraccion de Madera de áreas protegidas
B92: MAATE/ INGEI | D92: Bosque nativo bajo un regimen de protección legal (PSB, SNAP, Bosques Protectores) | F92: Extracción de Madera (m3.ha-1.año-1)
A93: Crece con la tasa de crecimiento de las plantaciones forestales | D93: B. nativo | T93: 0.01959779 | U93: =T93*(1+((U70-T70)/U70)) -> 0.01960308 | V93: =U93*(1+((V70-U70)/V70)) -> 0.019609155 | W93: =V93*(1+((W70-V70)/W70)) -> 0.019615036 | X93: =W93*(1+((X70-W70)/X70)) -> 0.019620331 | Y93: =X93*(1+((Y70-X70)/Y70)) -> 0.019624842 | Z93: =Y93*(1+((Z70-Y70)/Z70)) -> 0.01963109 | AA93: =Z93*(1+((AA70-Z70)/AA70)) -> 0.019636676 | AB93: =AA93*(1+((AB70-AA70)/AB70)) -> 0.019640987 | ... AW93: =AV93*(1+((AW70-AV70)/AW70)) -> 0.019734394
A94: Crece con la tasa de crecimiento de las plantaciones forestales | D94: Plantaciones forestales | T94: 15.487761 | U94: =T94*(1+((U70-T70)/U70)) -> 15.491942 | V94: =U94*(1+((V70-U70)/V70)) -> 15.496743 | W94: =V94*(1+((W70-V70)/W70)) -> 15.50139 | X94: =W94*(1+((X70-W70)/X70)) -> 15.505575 | Y94: =X94*(1+((Y70-X70)/Y70)) -> 15.50914 | Z94: =Y94*(1+((Z70-Y70)/Z70)) -> 15.514078 | AA94: =Z94*(1+((AA70-Z70)/AA70)) -> 15.518492 | AB94: =AA94*(1+((AB70-AA70)/AB70)) -> 15.521899 | ... AW94: =AV94*(1+((AW70-AV70)/AW70)) -> 15.595717
F95: TOTAL MADERA EXTRAIDA [m3.ha-1.año-1] | T95: =SUM(T93:T94) -> 15.507359 | U95: =SUM(U93:U94) -> 15.511545 | V95: =SUM(V93:V94) -> 15.516352 | W95: =SUM(W93:W94) -> 15.521006 | X95: =SUM(X93:X94) -> 15.525195 | Y95: =SUM(Y93:Y94) -> 15.528765 | Z95: =SUM(Z93:Z94) -> 15.533709 | AA95: =SUM(AA93:AA94) -> 15.538129 | ... AW95: =SUM(AW93:AW94) -> 15.615451
D99: Extraccion de leña de áreas protegidas
B100: Balance Energético Nacional, 2020/ INGEI | D100: Bosque nativo bajo un regimen de protección legal (PSB, SNAP, Bosques Protectores) | F100: Extracción de Leña (m3.ha-1.año-1)
A101: Crece con la tasa de crecimiento de la poblacion | D101: B. nativo | S101: 0.21000467 | T101: =S101*(1+ Drivers_macroeconómicos_USCUSS!G8) -> 0.21289058 | U101: =T101*(1+ Drivers_macroeconómicos_USCUSS!H8) -> 0.21575253 | V101: =U101*(1+ Drivers_macroeconómicos_USCUSS!I8) -> 0.21859006 | W101: =V101*(1+ Drivers_macroeconómicos_USCUSS!J8) -> 0.2214015 | X101: =W101*(1+ Drivers_macroeconómicos_USCUSS!K8) -> 0.22418632 | Y101: =X101*(1+ Drivers_macroeconómicos_USCUSS!L8) -> 0.22694139 | Z101: =Y101*(1+ Drivers_macroeconómicos_USCUSS!M8) -> 0.22966568 | AA101: =Z101*(1+ Drivers_macroeconómicos_USCUSS!N8) -> 0.23235723 | ... AW101: =AV101*(1+ Drivers_macroeconómicos_USCUSS!AJ8) -> 0.28036467
D102: Plantaciones forestales | S102: 0 | T102: 0 | U102: 0 | V102: 0 | W102: 0 | X102: 0 | Y102: 0 | Z102: 0 | AA102: 0 | AB102: 0 | AC102: 0 | AD102: 0 | AE102: 0 | AF102: 0 | AG102: 0 | AH102: 0 | AI102: 0 | AJ102: 0 | AK102: 0 | AL102: 0 | AM102: 0 | AN102: 0 | AO102: 0 | AP102: 0 | AQ102: 0 | AR102: 0 | AS102: 0 | AT102: 0 | AU102: 0 | AV102: 0 | AW102: 0
F103: TOTAL LEÑA EXTRAIDA [m3.ha-1.año-1] | S103: =SUM(S101:S102) -> 0.21000467 | T103: =SUM(T101:T102) -> 0.21289058 | U103: =SUM(U101:U102) -> 0.21575253 | V103: =SUM(V101:V102) -> 0.21859006 | W103: =SUM(W101:W102) -> 0.2214015 | X103: =SUM(X101:X102) -> 0.22418632 | Y103: =SUM(Y101:Y102) -> 0.22694139 | Z103: =SUM(Z101:Z102) -> 0.22966568 | ... AW103: =SUM(AW101:AW102) -> 0.28036467
D106: DATOS PARA EMISIONES
C108: % del total de has que cambian de cobertura
E109: GRÁFICO UTCUTS-4 | F109: TABLA UTCUTS - 4: Cambios de uso de suelos
F110: Superficie de tierras convertidas en tierras de cultivo [Mha]
B111: Datos 2010 al 2018 INGEI | C111: 0.2345 | D111: Bosque nativo | F111: Tierras de cultivo [Mha] | I111: 0.09472 | K111: 0.09472 | M111: 0.09472 | O111: 0.09079 | Q111: 0.07746 | R111: =R66*$C$111 -> 0.022009595 | S111: =S66*$C$111 -> 0.022784685 | T111: =T66*$C$111 -> 0.022611521 | U111: =U66*$C$111 -> 0.022439673 | V111: =V66*$C$111 -> 0.022269132 | W111: =W66*$C$111 -> 0.022099886 | X111: =X66*$C$111 -> 0.021931927 | Y111: =Y66*$C$111 -> 0.021765245 | ... BQ111: =BQ66*$C$111 -> 0.015558968
C112: 0.48314607 | D112: Plantación forestal | F112: Tierras de cultivo [Mha] | I112: 0.0023 | K112: 0.0023 | M112: 0.0023 | O112: 0.01114 | Q112: 0.0086 | R112: =(R70-Q70)*$C$112 -> 7.1349334e-08 | S112: =(S70-R70)*$C$112 -> -4.5901407e-05 | T112: =(T70-S70)*$C$112 -> 2.4943811e-05 | U112: =(U70-T70)*$C$112 -> 1.5908575e-05 | V112: =(V70-U70)*$C$112 -> 1.8270333e-05 | W112: =(W70-V70)*$C$112 -> 1.7686448e-05 | X112: =(X70-W70)*$C$112 -> 1.5922579e-05 | Y112: =(Y70-X70)*$C$112 -> 1.356734e-05 | ... BQ112: =(BQ70-BP70)*$C$112 -> 8.5903831e-06
C113: 0.4 | D113: Pastura | F113: Tierras de cultivo [Mha] | R113: =(R75-Q75)*$C$113 -> 0.015276865 | S113: =(S75-R75)*$C$113 -> 0.036935084 | T113: =(T75-S75)*$C$113 -> 0.020508068 | U113: =(U75-T75)*$C$113 -> 0.01971287 | V113: =(V75-U75)*$C$113 -> 0.02194782 | W113: =(W75-V75)*$C$113 -> 0.020563031 | X113: =(X75-W75)*$C$113 -> 0.024287104 | Y113: =(Y75-X75)*$C$113 -> 0.026223004 | ... BQ113: =(BQ75-BP75)*$C$113 -> 0.012489539
C114: 0.5851 | D114: Pastizal (grassland) | F114: Tierras de cultivo [Mha] | I114: 0.02439 | K114: 0.02439 | M114: 0.02439 | O114: 0.05355 | Q114: 0.01486 | R114: =(R77-Q77)*$C$114 -> -0.0039654977 | S114: =(S77-R77)*$C$114 -> -0.0041489441 | T114: =(T77-S77)*$C$114 -> -0.0041489441 | U114: =(U77-T77)*$C$114 -> -0.0041489441 | V114: =(V77-U77)*$C$114 -> -0.0041489441 | W114: =(W77-V77)*$C$114 -> -0.0041489441 | X114: =(X77-W77)*$C$114 -> -0.0041489441 | Y114: =(Y77-X77)*$C$114 -> -0.0041489441 | ... BQ114: =(BQ77-BP77)*$C$114 -> -0.0041489441
C115: 0.4161 | D115: Humedales | F115: Tierras de cultivo [Mha] | I115: 0.00832 | K115: 0.00832 | M115: 0.00832 | O115: 0.01022 | Q115: 0.00673 | R115: =(R79-Q79)*$C$115 -> -0.00028251403 | S115: =(S79-R79)*$C$115 -> -0.00028212416 | T115: =(T79-S79)*$C$115 -> -0.00028173483 | U115: =(U79-T79)*$C$115 -> -0.00028134604 | V115: =(V79-U79)*$C$115 -> -0.00028095778 | W115: =(W79-V79)*$C$115 -> -0.00028057006 | X115: =(X79-W79)*$C$115 -> -0.00028018287 | Y115: =(Y79-X79)*$C$115 -> -0.00027979622 | ... BQ115: =(BQ79-BP79)*$C$115 -> -0.00026330146
D116: Asentamientos | F116: Tierras de cultivo [Mha] | I116: 0 | K116: 0 | M116: 0 | O116: 0 | Q116: 0 | W116: =(W72-V72)*$C$116 -> 0 | X116: =(X72-W72)*$C$116 -> 0 | Y116: =(Y72-X72)*$C$116 -> 0 | Z116: =(Z72-Y72)*$C$116 -> 0 | AA116: =(AA72-Z72)*$C$116 -> 0 | AB116: =(AB72-AA72)*$C$116 -> 0 | AC116: =(AC72-AB72)*$C$116 -> 0 | AD116: =(AD72-AC72)*$C$116 -> 0 | ... AW116: =(AW72-AV72)*$C$116 -> 0
C117: 0.1573 | D117: Otras tierras | F117: Tierras de cultivo [Mha] | I117: 0.00128 | K117: 0.00128 | M117: 0.00128 | O117: 0.00923 | Q117: 0.00155 | R117: =(R84-Q84)*$C$117 -> 0.00021415989 | S117: =(S84-R84)*$C$117 -> 0.00021684497 | T117: =(T84-S84)*$C$117 -> 0.0002195637 | U117: =(U84-T84)*$C$117 -> 0.00022208601 | V117: =(V84-U84)*$C$117 -> 0.00022486758 | W117: =(W84-V84)*$C$117 -> 0.00022768398 | X117: =(X84-W84)*$C$117 -> 0.00023053565 | Y117: =(Y84-X84)*$C$117 -> 0.00023342304 | ... BQ117: =(BQ84-BP84)*$C$117 -> 0.00040363735
F118: TOTAL COBERTURAS [Mha] | I118: 0.13102 | K118: 0.13102 | M118: 0.13102 | O118: 0.1749 | Q118: 0.1092 | R118: 0.1092 | S118: 0.1092 | T118: 0.1092 | U118: =SUM(U111:U117) -> 0.037960248 | V118: =SUM(V111:V117) -> 0.040030188 | W118: =SUM(W111:W117) -> 0.038478774 | X118: =SUM(X111:X117) -> 0.042036362 | Y118: =SUM(Y111:Y117) -> 0.043806499 | Z118: =SUM(Z111:Z117) -> 0.039979421 | AA118: =SUM(AA111:AA117) -> 0.041633868 | AB118: =SUM(AB111:AB117) -> 0.046292834 | ... BQ118: =SUM(BQ111:BQ117) -> 0.02404849
F120: Superficie de tierras convertidas en Pasturas [Mha]
C121: 0.7035 | D121: Bosque nativo | F121: Pasturas [Mha] | Q121: =(Q66)*$C$121 -> 0.058059152 | R121: =(R66)*$C$121 -> 0.066028784 | S121: =(S66)*$C$121 -> 0.068354054 | T121: =(T66)*$C$121 -> 0.067834563 | U121: =(U66)*$C$121 -> 0.06731902 | V121: =(V66)*$C$121 -> 0.066807396 | W121: =(W66)*$C$121 -> 0.066299659 | X121: =(X66)*$C$121 -> 0.065795782 | ... BQ121: =(BQ66)*$C$121 -> 0.046676905
C122: 0.16104869 | D122: Plantación forestal | F122: Pasturas [Mha] | Q122: =(Q70-P70)*$C$122 -> 0.019647178 | R122: =(R70-Q70)*$C$122 -> 2.3783111e-08 | S122: =(S70-R70)*$C$122 -> -1.5300469e-05 | T122: =(T70-S70)*$C$122 -> 8.3146036e-06 | U122: =(U70-T70)*$C$122 -> 5.3028584e-06 | V122: =(V70-U70)*$C$122 -> 6.0901109e-06 | W122: =(W70-V70)*$C$122 -> 5.8954828e-06 | X122: =(X70-W70)*$C$122 -> 5.3075263e-06 | ... BQ122: =(BQ70-BP70)*$C$122 -> 2.863461e-06
C123: 0.09 | D123: Tierras de cultivo | F123: Pasturas [Mha] | Q123: =(Q72-P72)*$C$123 -> 0.34925463 | R123: =(R72-Q72)*$C$123 -> 0.0019207041 | S123: =(S72-R72)*$C$123 -> 0.00042694432 | T123: =(T72-S72)*$C$123 -> 0.0040482671 | U123: =(U72-T72)*$C$123 -> 0.0041643225 | V123: =(V72-U72)*$C$123 -> 0.0035986446 | W123: =(W72-V72)*$C$123 -> 0.0038486346 | X123: =(X72-W72)*$C$123 -> 0.0029498781 | ... BQ123: =(BQ72-BP72)*$C$123 -> 0.0034261493
C124: 0.195 | D124: Pastizal (grassland) | F124: Pasturas [Mha] | Q124: =((R77-Q77)*$C$124)*-1 -> 0.0013216066 | R124: =(R77-Q77)*$C$124 -> -0.0013216066 | S124: =(S77-R77)*$C$124 -> -0.001382745 | T124: =(T77-S77)*$C$124 -> -0.001382745 | U124: =(U77-T77)*$C$124 -> -0.001382745 | V124: =(V77-U77)*$C$124 -> -0.001382745 | W124: =(W77-V77)*$C$124 -> -0.001382745 | X124: =(X77-W77)*$C$124 -> -0.001382745 | Y124: =(Y77-X77)*$C$124 -> -0.001382745 | ... BQ124: =(BQ77-BP77)*$C$124 -> -0.001382745
C125: 0.1387 | D125: Humedales | F125: Pasturas [Mha] | Q125: =(Q79-P79)*$C$125 -> 0.068240105 | R125: =(R79-Q79)*$C$125 -> -9.4171344e-05 | S125: =(S79-R79)*$C$125 -> -9.4041388e-05 | T125: =(T79-S79)*$C$125 -> -9.3911611e-05 | U125: =(U79-T79)*$C$125 -> -9.3782013e-05 | V125: =(V79-U79)*$C$125 -> -9.3652594e-05 | W125: =(W79-V79)*$C$125 -> -9.3523353e-05 | X125: =(X79-W79)*$C$125 -> -9.3394291e-05 | ... BQ125: =(BQ79-BP79)*$C$125 -> -8.7767154e-05
...

Sheet Emisiones_USCUSS
A1: Referencias | D1: Emisiones | E1: 2010 | F1: 2011 | G1: 2012 | H1: 2013 | I1: 2014 | J1: 2015 | K1: 2016 | L1: 2017 | M1: 2018 | N1: 2019 | O1: 2020 | P1: 2021 | Q1: 2022 | R1: 2023 | S1: 2024 | T1: 2025 | U1: 2026 | V1: 2027 | W1: 2028 | X1: 2029 | Y1: 2030 | Z1: 2031 | AA1: 2032 | AB1: 2033 | AC1: 2034 | AD1: 2035 | AE1: 2036 | AF1: 2037 | AG1: 2038 | AH1: 2039 | AI1: 2040 | AJ1: 2041 | AK1: 2042 | AL1: 2043 | AM1: 2044 | AN1: 2045 | AO1: 2046 | AP1: 2047 | AQ1: 2048 | AR1: 2049 | AS1: 2050 | AT1: 2051 | AU1: 2052 | AV1: 2053 | AW1: 2054 | AX1: 2055 | AY1: 2056 | AZ1: 2057 | BA1: 2058 | BB1: 2059 | BC1: 2060 | BD1: 2061 | BE1: 2062 | BF1: 2063 | BG1: 2064 | BH1: 2065 | BI1: 2066 | BJ1: 2067 | BK1: 2068 | BL1: 2069 | BM1: 2070
D4: Incendios
A5: 1 | D5: Biomasa quemada [Mton] | E5: 0.09247036 | F5: 0.29849617 | G5: 0.50611284 | H5: 0.17253752 | I5: 0.10759797 | J5: 0.24254432 | K5: 0.49494541 | L5: 0.092155155 | M5: 0.18826599 | N5: 0.44935907
D6: Superficie quemada [Mha] | E6: 0.007543961 | F6: 0.04158632 | G6: 0.044365131 | H6: 0.023935645 | I6: 0.010834785 | J6: 0.022673817 | K6: 0.063577337 | L6: 0.012437746 | M6: 0.019896414 | N6: 0.05035058
D7: Emisiones (CH4) [mton] | E7: 0.2128 | F7: 0.6866 | G7: 1.164 | H7: 0.3969 | I7: 0.2475 | J7: 0.5579 | K7: 1.1383 | L7: 0.2119 | M7: 0.4331 | N7: 1.0335
D8: Emisiones (N2O) [mton] | E8: 0.0194 | F8: 0.0627 | G8: 0.1063 | H8: 0.0362 | I8: 0.0225 | J8: 0.0509 | K8: 0.1039 | L8: 0.0192 | M8: 0.0396 | N8: 0.0943
D13: Bosque
D14: Remociones
A15: 2,4,5 | D15: Deforestación [Mha] | E15: 0.097918 | F15: 0.097918 | G15: 0.097918 | H15: 0.097918 | I15: 0.097918 | J15: 0.094353 | K15: 0.094353 | L15: 0.122793 | M15: 0.122793
A16: 3,4,5 | D16: Regeneración [Mha] | E16: 0.050421 | F16: 0.050421 | G16: 0.050421 | H16: 0.050421 | I16: 0.050421 | J16: 0.033241 | K16: 0.033241 | L16: 0.037765 | M16: 0.037765
D17: Deforestación bruta [Mton C] | E17: 10.523577 | F17: 10.523577 | G17: 10.523577 | H17: 10.523577 | I17: 10.523577
D18: Bosque protegido [Mton CO2e] | E18: 38.586447 | F18: 38.586447 | G18: 38.586447 | H18: 38.586447 | I18: 38.586447
A19: 6 | D19: Absorciones de CO2 [ton CO2eq.ha] Bosques nativos | I19: 5.4966589 | K19: 5.5093519 | M19: 5.5139349
A20: 6 | D20: Absorciones de CO2 [tonCO2eq.ha] Plantaciones forestales | I20: 20.279497 | K20: 20.279497 | M20: 20.279497
E25: Tierras convertidas en Cultivos
E26: Factor de emisión neto (t CO2 equivalent/Ha)
A27: 6 | C27: Bosque nativo | G27: 388.13985 | I27: 388.13985 | K27: 397.07534 | M27: 406.02577
C28: Plantación forestal | G28: 307.8185 | I28: 307.8185 | K28: 307.8185 | M28: 307.8185
C29: Pasturas
C30: Pastizales (grasslands) | G30: 128.33333 | I30: 128.33333 | K30: 128.33333 | M30: 128.33333
C31: Humedales | G31: -9.5333333 | I31: -9.5333333 | K31: -9.53333 | M31: -9.53333
C32: Asentamientos
C33: Otras tierras | G33: -9.5333333 | I33: -9.5333333 | K33: -9.53333 | M33: -9.53333
E34: Tierras convertidas en Pasturas
E35: Factor de emisión neto (t CO2 equivalent/Ha)
A36: 6 | C36: Bosque nativo | G36: 388.13985 | I36: 388.13985 | K36: 397.07534 | M36: 406.02577
C37: Plantación forestal | G37: 307.8185 | I37: 307.8185 | K37: 307.8185 | M37: 307.8185
C38: Cultivos
C39: Pastizales (grasslands) | G39: 128.33333 | I39: 128.33333 | K39: 128.33333 | M39: 128.33333
C40: Humedales | G40: -9.5333333 | I40: -9.5333333 | K40: -9.53333 | M40: -9.53333
C41: Asentamientos
C42: Otras tierras | G42: -9.5333333 | I42: -9.5333333 | K42: -9.53333 | M42: -9.53333
E43: Tierras convertidas en Pastizales (grasslands)
E44: Factor de emisión neto (t CO2 equivalent/Ha)
A45: 6 | C45: Bosque nativo | M45: 272.77726
C46: Plantación forestal | G46: 289.59 | I46: 289.59 | K46: 289.39861 | M46: 289.39861
C47: Cultivos | G47: -27.75 | I47: -27.75 | K47: -27.7467 | M47: -27.74708
C48: Pasturas | G48: -27.75 | I48: -27.75 | K48: -27.7467 | M48: -27.74708
C49: Humedales | G49: -29.57 | I49: -29.57 | K49: -27.75397 | M49: -27.77787
C50: Asentamientos
C51: Otras tierras | G51: -27.75 | I51: -27.75 | K51: -27.75079 | M51: -27.75256
E52: Tierras convertidas en humedales
E53: Factor de emisión neto(t CO2 equivalent/Ha)
A54: 6 | C54: Bosque nativo | G54: 280.94 | I54: 280.94 | K54: 287.28393 | M54: 306.30677
C55: Plantación forestal | K55: 317.35183 | M55: 317.35183
C56: Cultivos | G56: 77 | I56: 77 | K56: 77 | M56: 77
C57: Pasturas | G57: 77 | I57: 77 | K57: 77 | M57: 77
C58: Pastizales (grasslands) | G58: 137.87 | I58: 137.87 | K58: 137.86667 | M58: 137.86667
C59: Asentamientos
C60: Otras tierras | G60: 0 | K60: 0 | M60: 0
E63: Tierras convertidas en asentamientos
E64: Factor de emisión neto (t CO2 equivalent/Ha)
A65: 6 | C65: Bosque nativo | G65: 275.05 | I65: 283.62 | K65: 368.09804 | M65: 441.43195
C66: Plantación forestal | G66: 317.35 | I66: 317.35 | K66: 279.26961 | M66: 317.35183
C67: Cultivos | G67: 77 | I67: 77 | K67: 77 | M67: 77
C68: Pasturas | G68: 77 | I68: 77 | K68: 77 | M68: 77
C69: Pastizales (grasslands) | G69: 137.87 | I69: 137.87 | K69: 137.86667 | M69: 137.86667
C70: Humedales | G70: 0 | I70: 0 | K70: 0 | M70: 0
C71: Otras tierras | G71: 0 | I71: 0 | K71: 0 | M71: 0
E73: Tierras convertidas en otras tierras
E74: Factor de emisión neto (t CO2 equivalent/Ha)
A75: 6 | C75: Bosque nativo | G75: 247.12 | I75: 247.12 | K75: 393.17335 | M75: 454.93998
C76: Plantación forestal | G76: 317.35 | I76: 317.35 | K76: 332.33848 | M76: 317.35183
C77: Cultivos | G77: 77 | I77: 77 | K77: 77 | M77: 77
C78: Pasturas | G78: 77 | I78: 77 | K78: 77 | M78: 77
C79: Pastizales (grasslands) | G79: 137.87 | I79: 137.87 | K79: 137.86667 | M79: 137.86667
C80: Humedales | G80: 0 | I80: 0 | K80: 0 | M80: 0
C81: Otras tierras
E84: Tierras forestales que se mantienen o tierras convertidas a plantaciones forestales
E85: Factor de emisión neto (t CO2 equivalent/Ha)
A86: 6 | C86: Bosque nativo que se mantiene como Bosque nativo | G86: -3.91 | I86: -4.05 | K86: -4.23 | M86: -4.3621204
C87: Plantación forestal que se mantiene como Plantacion forestal | G87: 21.35 | I87: 50.53 | K87: 20.24 | M87: 16.50729
C88: Cultivos convertidos en plantaciones forestales | G88: -20.28 | I88: -26.79 | K88: -20.279497 | M88: -20.279497
C89: Pasturas convertidas en plantaciones forestales | G89: -20.28 | I89: -26.79 | K89: -20.279497 | M89: -20.279497
C90: Pastizales (grasslands) convertidas en plantaciones forestales | G90: -20.28 | I90: -20.279497 | K90: -20.279497 | M90: -20.279497
C91: Humedales convertidas en plantaciones forestales | G91: -20.28 | I91: -20.279497 | K91: -20.279497 | M91: -20.279497
C92: Asentamientos convertidos en plantaciones forestales
C93: Otras tierras convertidas en plantaciones forestales | G93: -20.28 | I93: -20.279497 | K93: -20.279497 | M93: -20.279497
C94: Bosque que se regeneró | M94: -18.46
E96: Quema de biomasa
E97: Factor de emisión (t CO2 equivalent/Ha)
A98: 6 | C98: Quema de biomasa de bosques (t CO2 equivalent/Ha) | G98: 9.9606179 | I98: 9.9606179 | K98: 9.96062 | M98: 9.96062
D101: Referencias Bibliográficas
B102: 1 | D102: FAOSTAT - Residuos agrícolas - Ecuador - Emisiones directas (N2O) - Fecha consulta: 13SEP2022 - Documento: Plantilla inicial USCUSS 7- 13SEP2022
B103: 2 | D103: Primer informe bienal de Actualización del Ecuador, Septiembre 2016
B104: 3 | D104: Análisis de la deforestación en el Ecuador Continental 1990-2014
B105: 4 | D105: Deforestación del Ecuador Contiental periodo 2014-2016
B106: 5 | D106: La deforestación en el Ecuador 1990-2018
B107: 6 | D107: INGEI 2016, INGEI 2018
C110: EMISIONES
C111: Emisiones de tierras convertidas en tierras de cultivo [MtonCO2 eq]
C112: Bosque nativo | M112: =IF(Calibración_BAU_USCUSS!Q111<0,Calibración_BAU_USCUSS!Q111*-1, Calibración_BAU_USCUSS!Q111)*Emisiones_USCUSS!$M$27 -> 31.450756 | N112: =IF(Calibración_BAU_USCUSS!R111<0,Calibración_BAU_USCUSS!R111*-1, Calibración_BAU_USCUSS!R111)*Emisiones_USCUSS!$M$27 -> 8.9364626 | O112: =IF(Calibración_BAU_USCUSS!S111<0,Calibración_BAU_USCUSS!S111*-1, Calibración_BAU_USCUSS!S111)*Emisiones_USCUSS!$M$27 -> 9.2511691 | P112: =IF(Calibración_BAU_USCUSS!T111<0,Calibración_BAU_USCUSS!T111*-1, Calibración_BAU_USCUSS!T111)*Emisiones_USCUSS!$M$27 -> 9.1808602 | Q112: =IF(Calibración_BAU_USCUSS!U111<0,Calibración_BAU_USCUSS!U111*-1, Calibración_BAU_USCUSS!U111)*Emisiones_USCUSS!$M$27 -> 9.1110857 | R112: =IF(Calibración_BAU_USCUSS!V111<0,Calibración_BAU_USCUSS!V111*-1, Calibración_BAU_USCUSS!V111)*Emisiones_USCUSS!$M$27 -> 9.0418414 | S112: =IF(Calibración_BAU_USCUSS!W111<0,Calibración_BAU_USCUSS!W111*-1, Calibración_BAU_USCUSS!W111)*Emisiones_USCUSS!$M$27 -> 8.9731234 | T112: =IF(Calibración_BAU_USCUSS!X111<0,Calibración_BAU_USCUSS!X111*-1, Calibración_BAU_USCUSS!X111)*Emisiones_USCUSS!$M$27 -> 8.9049277 | ... BM112: =IF(Calibración_BAU_USCUSS!BQ111<0,Calibración_BAU_USCUSS!BQ111*-1, Calibración_BAU_USCUSS!BQ111)*Emisiones_USCUSS!$M$27 -> 6.3173421
C113: Plantación forestal | M113: =IF(Calibración_BAU_USCUSS!Q112 <0,Calibración_BAU_USCUSS!Q112 *-1, Calibración_BAU_USCUSS!Q112 )*Emisiones_USCUSS!$M$28 -> 2.6472391 | N113: =IF(Calibración_BAU_USCUSS!R112 <0,Calibración_BAU_USCUSS!R112 *-1, Calibración_BAU_USCUSS!R112 )*Emisiones_USCUSS!$M$28 -> 2.1962645e-05 | O113: =IF(Calibración_BAU_USCUSS!S112 <0,Calibración_BAU_USCUSS!S112 *-1, Calibración_BAU_USCUSS!S112 )*Emisiones_USCUSS!$M$28 -> 0.014129302 | P113: =IF(Calibración_BAU_USCUSS!T112 <0,Calibración_BAU_USCUSS!T112 *-1, Calibración_BAU_USCUSS!T112 )*Emisiones_USCUSS!$M$28 -> 0.0076781664 | Q113: =IF(Calibración_BAU_USCUSS!U112 <0,Calibración_BAU_USCUSS!U112 *-1, Calibración_BAU_USCUSS!U112 )*Emisiones_USCUSS!$M$28 -> 0.0048969537 | R113: =IF(Calibración_BAU_USCUSS!V112 <0,Calibración_BAU_USCUSS!V112 *-1, Calibración_BAU_USCUSS!V112 )*Emisiones_USCUSS!$M$28 -> 0.0056239464 | S113: =IF(Calibración_BAU_USCUSS!W112 <0,Calibración_BAU_USCUSS!W112 *-1, Calibración_BAU_USCUSS!W112 )*Emisiones_USCUSS!$M$28 -> 0.005444216 | T113: =IF(Calibración_BAU_USCUSS!X112 <0,Calibración_BAU_USCUSS!X112 *-1, Calibración_BAU_USCUSS!X112 )*Emisiones_USCUSS!$M$28 -> 0.0049012643 | ... BM113: =IF(Calibración_BAU_USCUSS!BQ112 <0,Calibración_BAU_USCUSS!BQ112 *-1, Calibración_BAU_USCUSS!BQ112 )*Emisiones_USCUSS!$M$28 -> 0.0026442788
C114: Pastura
C115: Pastizal (grassland) | M115: =IF(Calibración_BAU_USCUSS!Q114<0,Calibración_BAU_USCUSS!Q114*-1, Calibración_BAU_USCUSS!Q114)*Emisiones_USCUSS!$M$30 -> 1.9070333 | N115: =IF(Calibración_BAU_USCUSS!R114<0,Calibración_BAU_USCUSS!R114*-1, Calibración_BAU_USCUSS!R114)*Emisiones_USCUSS!$M$30 -> 0.50890552 | O115: =IF(Calibración_BAU_USCUSS!S114<0,Calibración_BAU_USCUSS!S114*-1, Calibración_BAU_USCUSS!S114)*Emisiones_USCUSS!$M$30 -> 0.53244781 | P115: =IF(Calibración_BAU_USCUSS!T114<0,Calibración_BAU_USCUSS!T114*-1, Calibración_BAU_USCUSS!T114)*Emisiones_USCUSS!$M$30 -> 0.53244781 | Q115: =IF(Calibración_BAU_USCUSS!U114<0,Calibración_BAU_USCUSS!U114*-1, Calibración_BAU_USCUSS!U114)*Emisiones_USCUSS!$M$30 -> 0.53244781 | R115: =IF(Calibración_BAU_USCUSS!V114<0,Calibración_BAU_USCUSS!V114*-1, Calibración_BAU_USCUSS!V114)*Emisiones_USCUSS!$M$30 -> 0.53244781 | S115: =IF(Calibración_BAU_USCUSS!W114<0,Calibración_BAU_USCUSS!W114*-1, Calibración_BAU_USCUSS!W114)*Emisiones_USCUSS!$M$30 -> 0.53244781 | T115: =IF(Calibración_BAU_USCUSS!X114<0,Calibración_BAU_USCUSS!X114*-1, Calibración_BAU_USCUSS!X114)*Emisiones_USCUSS!$M$30 -> 0.53244781 | ... BM115: =IF(Calibración_BAU_USCUSS!BQ114<0,Calibración_BAU_USCUSS!BQ114*-1, Calibración_BAU_USCUSS!BQ114)*Emisiones_USCUSS!$M$30 -> 0.53244781
C116: Humedales | M116: =IF(Calibración_BAU_USCUSS!Q115<0,Calibración_BAU_USCUSS!Q115 *-1, Calibración_BAU_USCUSS!Q115)*Emisiones_USCUSS!$M$31 -> -0.064159311 | N116: =IF(Calibración_BAU_USCUSS!R115<0,Calibración_BAU_USCUSS!R115 *-1, Calibración_BAU_USCUSS!R115)*Emisiones_USCUSS!$M$31 -> -0.0026932995 | O116: =IF(Calibración_BAU_USCUSS!S115<0,Calibración_BAU_USCUSS!S115 *-1, Calibración_BAU_USCUSS!S115)*Emisiones_USCUSS!$M$31 -> -0.0026895828 | P116: =IF(Calibración_BAU_USCUSS!T115<0,Calibración_BAU_USCUSS!T115 *-1, Calibración_BAU_USCUSS!T115)*Emisiones_USCUSS!$M$31 -> -0.0026858711 | Q116: =IF(Calibración_BAU_USCUSS!U115<0,Calibración_BAU_USCUSS!U115 *-1, Calibración_BAU_USCUSS!U115)*Emisiones_USCUSS!$M$31 -> -0.0026821646 | R116: =IF(Calibración_BAU_USCUSS!V115<0,Calibración_BAU_USCUSS!V115 *-1, Calibración_BAU_USCUSS!V115)*Emisiones_USCUSS!$M$31 -> -0.0026784632 | S116: =IF(Calibración_BAU_USCUSS!W115<0,Calibración_BAU_USCUSS!W115 *-1, Calibración_BAU_USCUSS!W115)*Emisiones_USCUSS!$M$31 -> -0.002674767 | T116: =IF(Calibración_BAU_USCUSS!X115<0,Calibración_BAU_USCUSS!X115 *-1, Calibración_BAU_USCUSS!X115)*Emisiones_USCUSS!$M$31 -> -0.0026710758 | ... BM116: =IF(Calibración_BAU_USCUSS!BQ115<0,Calibración_BAU_USCUSS!BQ115 *-1, Calibración_BAU_USCUSS!BQ115)*Emisiones_USCUSS!$M$31 -> -0.0025101397
C117: Asentamientos
C118: Otras tierras | M118: =IF(Calibración_BAU_USCUSS!Q117 <0,Calibración_BAU_USCUSS!Q117 *-1, Calibración_BAU_USCUSS!Q117)*Emisiones_USCUSS!$M$33 -> -0.014776661 | N118: =IF(Calibración_BAU_USCUSS!R117 <0,Calibración_BAU_USCUSS!R117 *-1, Calibración_BAU_USCUSS!R117)*Emisiones_USCUSS!$M$33 -> -0.0020416569 | O118: =IF(Calibración_BAU_USCUSS!S117 <0,Calibración_BAU_USCUSS!S117 *-1, Calibración_BAU_USCUSS!S117)*Emisiones_USCUSS!$M$33 -> -0.0020672546 | P118: =IF(Calibración_BAU_USCUSS!T117 <0,Calibración_BAU_USCUSS!T117 *-1, Calibración_BAU_USCUSS!T117)*Emisiones_USCUSS!$M$33 -> -0.0020931732 | Q118: =IF(Calibración_BAU_USCUSS!U117 <0,Calibración_BAU_USCUSS!U117 *-1, Calibración_BAU_USCUSS!U117)*Emisiones_USCUSS!$M$33 -> -0.0021172193 | R118: =IF(Calibración_BAU_USCUSS!V117 <0,Calibración_BAU_USCUSS!V117 *-1, Calibración_BAU_USCUSS!V117)*Emisiones_USCUSS!$M$33 -> -0.0021437368 | S118: =IF(Calibración_BAU_USCUSS!W117 <0,Calibración_BAU_USCUSS!W117 *-1, Calibración_BAU_USCUSS!W117)*Emisiones_USCUSS!$M$33 -> -0.0021705865 | T118: =IF(Calibración_BAU_USCUSS!X117 <0,Calibración_BAU_USCUSS!X117 *-1, Calibración_BAU_USCUSS!X117)*Emisiones_USCUSS!$M$33 -> -0.0021977724 | ... BM118: =IF(Calibración_BAU_USCUSS!BQ117 <0,Calibración_BAU_USCUSS!BQ117 *-1, Calibración_BAU_USCUSS!BQ117)*Emisiones_USCUSS!$M$33 -> -0.003848008
M119: =SUM(M112:M118) -> 35.926093 | N119: =SUM(N112:N118) -> 9.4406551 | O119: =SUM(O112:O118) -> 9.7929894 | P119: =SUM(P112:P118) -> 9.7162071 | Q119: =SUM(Q112:Q118) -> 9.643631 | R119: =SUM(R112:R118) -> 9.575091 | S119: =SUM(S112:S118) -> 9.5061701 | T119: =SUM(T112:T118) -> 9.4374079 | ... BM119: =SUM(BM112:BM118) -> 6.8460761
C120: Emisiones de tierras convertidas en Pasturas [MtonCO2 eq]
...

Sheet Costos_USCUSS
B1: Costos considerados para USCUSS
B3: 1. COSTOS RESTAURACIÓN (Reforestación)
A4: Fuente
B5: Restauración Año 1 | C5: Unidades | E5: Costo
A6: Programa Nacional de Restauración del Paisaje (Ministerio del Ambiente, 2019) | B6: Mano de obra | C6: USD/ha | E6: 383.1629
B7: Insumos | C7: USD/ha | E7: 469.8005
B8: Cercado | C8: USD/ha | E8: 601.8953
B9: Mantenimiento | C9: USD/ha | E9: 0
B10: Gastos administrativos | C10: USD/ha | E10: 30.85
A11: Sistema Nacional de Monitoreo de Bosques | B11: Gastos monitoreo | C11: USD/ha | E11: 0.081766149
B12: Total | C12: USD/ha | E12: =SUM(D6:E11) -> 1485.7905
B14: Restauración Año 2 | C14: Unidades | E14: Costo
A15: Programa Nacional de Restauración del Paisaje (Ministerio del Ambiente, 2019) | B15: Mano de obra | C15: USD/ha | E15: 70.63258
B16: Insumos | C16: USD/ha | E16: 88.72681
B17: Cercado | C17: USD/ha | E17: 93.96509
B18: Mantenimiento | C18: USD/ha | E18: 77.93017
B19: Gastos administrativos | C19: USD/ha | E19: 30.85
A20: Sistema Nacional de Monitoreo de Bosques | B20: Gastos monitoreo | C20: USD/ha | E20: 0.081766149
B21: Total | C21: USD/ha | E21: =SUM(D15:E20) -> 362.18642
B23: Restauración Año 3 | C23: Unidades | E23: Costo
A24: Programa Nacional de Restauración del Paisaje (Ministerio del Ambiente, 2019) | B24: Mano de obra | C24: USD/ha | E24: 35.31629
B25: Insumos | C25: USD/ha | E25: 44.3634
B26: Cercado | C26: USD/ha | E26: 0
B27: Mantenimiento | C27: USD/ha | E27: 77.93017
B28: Gastos administrativos | C28: USD/ha | E28: 30.85
A29: Sistema Nacional de Monitoreo de Bosques | B29: Gastos monitoreo | C29: USD/ha | E29: 0.081766149
B30: Total | C30: USD/ha | E30: =SUM(D24:E29) -> 188.54163
B32: Restauración Año 4 | C32: Unidades | E32: Costo
A33: Programa Nacional de Restauración del Paisaje (Ministerio del Ambiente, 2019) | B33: Mano de obra | C33: USD/ha | E33: 17.65815
B34: Insumos | C34: USD/ha | E34: 22.1817
B35: Cercado | C35: USD/ha | E35: 0
B36: Mantenimiento | C36: USD/ha | E36: 77.93017
B37: Gastos administrativos | C37: USD/ha | E37: 30.85
A38: Sistema Nacional de Monitoreo de Bosques | B38: Gastos monitoreo | C38: USD/ha | E38: 0.081766149
B39: Total | C39: USD/ha | E39: =SUM(D33:E38) -> 148.70179
B41: Restauración Año 5 | C41: Unidades | E41: Costo
A42: Programa Nacional de Restauración del Paisaje (Ministerio del Ambiente, 2019) | B42: Mano de obra | C42: USD/ha | E42: 8.829073
B43: Insumos | C43: USD/ha | E43: 11.09085
B44: Cercado | C44: USD/ha | E44: 0
B45: Mantenimiento | C45: USD/ha | E45: 77.93017
B46: Gastos administrativos | C46: USD/ha | E46: 30.85
A47: Sistema Nacional de Monitoreo de Bosques | B47: Gastos monitoreo | C47: USD/ha | E47: 0.081766149
B48: Total | C48: USD/ha | E48: =SUM(D42:E47) -> 128.78186
A50: Programa Nacional de Restauración del Paisaje (Ministerio del Ambiente, 2019) | B50: Restauración Año 6 | C50: Unidades | E50: Costo
B51: Mano de obra | C51: USD/ha | E51: 4.414536
B52: Insumos | C52: USD/ha | E52: 5.545425
B53: Cercado | C53: USD/ha | E53: 0
B54: Mantenimiento | C54: USD/ha | E54: 77.93017
B55: Gastos administrativos | C55: USD/ha | E55: 30.85
A56: Sistema Nacional de Monitoreo de Bosques | B56: Gastos monitoreo | C56: USD/ha | E56: 0.081766149
B57: Total | C57: USD/ha | E57: =SUM(D51:E56) -> 118.8219
B59: Restauración Año 7 | C59: Unidades | E59: Costo
A60: Programa Nacional de Restauración del Paisaje (Ministerio del Ambiente, 2019) | B60: Mano de obra | C60: USD/ha | E60: 2.207268
B61: Insumos | C61: USD/ha | E61: 2.772713
B62: Cercado | C62: USD/ha | E62: 0
B63: Mantenimiento | C63: USD/ha | E63: 77.93017
B64: Gastos administrativos | C64: USD/ha | E64: 30.85
A65: Sistema Nacional de Monitoreo de Bosques | B65: Gastos monitoreo | C65: USD/ha | E65: 0.081766149
B66: Total | C66: USD/ha | E66: =SUM(E60:E65) -> 113.84192
B68: 2. COSTOS CONSERVACIÓN
A70: Programa Socio Bosque II (MAATE, 2021) | B70: Conservación de bosques con incentivos económicos NETO CERO 2050 | C70: Unidades | E70: 2023 | F70: 2024 | G70: 2025 | H70: 2026 | I70: 2027 | J70: 2028 | K70: 2029 | L70: 2030 | M70: 2031 | N70: 2032 | O70: 2033 | P70: 2034 | Q70: 2035 | R70: 2036 | S70: 2037 | T70: 2038 | U70: 2039 | V70: 2040 | W70: 2041 | X70: 2042 | Y70: 2043 | Z70: 2044 | AA70: 2045 | AB70: 2046 | AC70: 2047 | AD70: 2048 | AE70: 2049 | AF70: 2050 | AG70: 2051 | AH70: 2052 | AI70: 2053 | AJ70: 2054 | AK70: 2055 | AL70: 2056 | AM70: 2057 | AN70: 2058 | AO70: 2059 | AP70: 2060 | AQ70: 2061 | AR70: 2062 | AS70: 2063 | AT70: 2064 | AU70: 2065 | AV70: 2066 | AW70: 2067 | AX70: 2068 | AY70: 2069 | AZ70: 2070
B71: Pago por conservación de bosques (promedio ponderado Socio Bosque) | C71: USD/ha | E71: 13.45 | F71: =(F70*10.057)-20333 -> 22.368 | G71: =(G70*10.057)-20333 -> 32.425 | H71: =(H70*10.057)-20333 -> 42.482 | I71: =(I70*10.057)-20333 -> 52.539 | J71: =(J70*10.057)-20333 -> 62.596 | K71: =(K70*10.057)-20333 -> 72.653 | L71: =(L70*10.057)-20333 -> 82.71 | M71: =(M70*10.057)-20333 -> 92.767 | ... AF71: =(AF70*10.057)-20333 -> 283.85 | AG71: 285 | AH71: 285 | AI71: 285 | AJ71: 285 | AK71: 285 | AL71: 285 | AM71: 285 | AN71: 285 | AO71: 285 | AP71: 285 | AQ71: 285 | AR71: 285 | AS71: 285 | AT71: 285 | AU71: 285 | AV71: 285 | AW71: 285 | AX71: 285 | AY71: 285 | AZ71: 285
A72: Dato sugerido en el taller | B72: Gastos administrativos | C72: USD/ha | E72: =0.02*E71 -> 0.269 | F72: =0.02*F71 -> 0.44736 | G72: =0.02*G71 -> 0.6485 | H72: =0.02*H71 -> 0.84964 | I72: =0.02*I71 -> 1.05078 | J72: =0.02*J71 -> 1.25192 | K72: =0.02*K71 -> 1.45306 | L72: =0.02*L71 -> 1.6542 | ... AZ72: =0.02*AZ71 -> 5.7
B73: Total | C73: USD/ha | E73: =SUM(E71:E72) -> 13.719 | F73: =SUM(F71:F72) -> 22.81536 | G73: =SUM(G71:G72) -> 33.0735 | H73: =SUM(H71:H72) -> 43.33164 | I73: =SUM(I71:I72) -> 53.58978 | J73: =SUM(J71:J72) -> 63.84792 | K73: =SUM(K71:K72) -> 74.10606 | L73: =SUM(L71:L72) -> 84.3642 | ... AZ73: =SUM(AZ71:AZ72) -> 290.7
B75: Conservación de bosques con incentivos económicos NETO CERO 2070 | C75: Unidades | E75: 2023 | F75: 2024 | G75: 2025 | H75: 2026 | I75: 2027 | J75: 2028 | K75: 2029 | L75: 2030 | M75: 2031 | N75: 2032 | O75: 2033 | P75: 2034 | Q75: 2035 | R75: 2036 | S75: 2037 | T75: 2038 | U75: 2039 | V75: 2040 | W75: 2041 | X75: 2042 | Y75: 2043 | Z75: 2044 | AA75: 2045 | AB75: 2046 | AC75: 2047 | AD75: 2048 | AE75: 2049 | AF75: 2050 | AG75: 2051 | AH75: 2052 | AI75: 2053 | AJ75: 2054 | AK75: 2055 | AL75: 2056 | AM75: 2057 | AN75: 2058 | AO75: 2059 | AP75: 2060 | AQ75: 2061 | AR75: 2062 | AS75: 2063 | AT75: 2064 | AU75: 2065 | AV75: 2066 | AW75: 2067 | AX75: 2068 | AY75: 2069 | AZ75: 2070
B76: Pago por conservación de bosques (promedio ponderado Socio Bosque) | C76: USD/ha | E76: 13.45 | F76: =(F75*5.7777 )+(-11675) -> 19.0648 | G76: =(G75*5.7777 )+(-11675) -> 24.8425 | H76: =(H75*5.7777 )+(-11675) -> 30.6202 | I76: =(I75*5.7777 )+(-11675) -> 36.3979 | J76: =(J75*5.7777 )+(-11675) -> 42.1756 | K76: =(K75*5.7777 )+(-11675) -> 47.9533 | L76: =(L75*5.7777 )+(-11675) -> 53.731 | M76: =(M75*5.7777 )+(-11675) -> 59.5087 | ... AZ76: =(AZ75*5.7777 )+(-11675) -> 284.839
B77: Gastos administrativos | C77: USD/ha | E77: =0.02*E76 -> 0.269 | F77: =0.02*F76 -> 0.381296 | G77: =0.02*G76 -> 0.49685 | H77: =0.02*H76 -> 0.612404 | I77: =0.02*I76 -> 0.727958 | J77: =0.02*J76 -> 0.843512 | K77: =0.02*K76 -> 0.959066 | L77: =0.02*L76 -> 1.07462 | ... AZ77: =0.02*AZ76 -> 5.69678
B78: Total | C78: USD/ha | E78: =SUM(E76:E77) -> 13.719 | F78: =SUM(F76:F77) -> 19.446096 | G78: =SUM(G76:G77) -> 25.33935 | H78: =SUM(H76:H77) -> 31.232604 | I78: =SUM(I76:I77) -> 37.125858 | J78: =SUM(J76:J77) -> 43.019112 | K78: =SUM(K76:K77) -> 48.912366 | L78: =SUM(L76:L77) -> 54.80562 | ... AZ78: =SUM(AZ76:AZ77) -> 290.53578
B81: 3. COSTOS PLANTACIONES FORESTALES
A83: PROYECTO DE INVERSIÓN: “DINAMIZACIÓN DEL SECTOR FORESTAL PRODUCTIVO SOSTENIBLE” (MAG, 2021) | B83: Plantaciones forestales comerciales y sistemas sostenibles año 1 | C83: Unidades | E83: Costo
B84: Establecimiento de plantaciones forestales, sistemas silvopastoriles y agroforestales comerciales, bajo diferentes esquemas de manejo | C84: USD/ha | E84: 1200
B85: Total | C85: USD/ha | E85: =SUM(E84) -> 1200
B87: Plantaciones forestales comerciales y sistemas sostenibles año 2 hasta año 11 | C87: Unidades | E87: Costo
A88: Direccion de Produccion Forestal (no hay documento solo entrevista) | B88: Mantenimiento de plantaciones forestales | C88: USD/ha | E88: 400
B89: Total | C89: USD/ha | E89: =SUM(E88) -> 400
B94: Referencias:
B95: •MAATE. (2021). Proyecto Socio Bosque II (pp. 1–94). MAATE.
B96: •MAATE. (2022). Proyecto Nacional de Restauración del Paisaje 2022-2025.
B97: •MAG. (2021). Dinamización del Sector Forestal Productivo Sostenible. MAG.
B98: •Ministerio del Ambiente. (2019). Plan Nacional de Restauración Forestal 2019-2030 (pp. 1–55). Ministerio del Ambiente.

Sheet Beneficios_USCUSS
B1: Beneficios del sector USCUSS aplicados a bosques bajo régimen de protección legal. Ya sea sistema nacional de áreas protegidas SNAP o bosques que ingresan al programa de conservación por incentivos economicos (Socio Bosque)
B2: 1. Belleza escénica
A4: Proyecto Nacional de Restauración de Paisaje (MAATE, 2022) para el rango alto. Rango base se consideró 1/3 del valor indicado en el PNRP para ser conservadores. | B4: Descripción del servicio | C4: Unidades | D4: Costo base (conservador) | E4: Costo rango alto
B5: Beneficio que genera las áreas naturales a nivel de paisaje | C5: USD/ha.año | D5: =E5*(1/3) -> 54.306667 | E5: 162.92
B6: Total | C6: USD/ha.año | D6: =SUM(D5) -> 54.306667 | E6: =SUM(E5) -> 162.92
B8: 2. Regulación hídrica y disminución de sedimento
A10: Basado en TEEB (EPN y PNUMA, 2018) para rango bajo. Rango alto basado en Plan Nacional de Restauración del Paisaje (MAATE, 2022) | B10: Descripción del servicio | C10: Unidades | D10: Costo base (conservador) | E10: Costo rango alto
B11: Provisión de servicio hídrico, restitución del recurso para consumo humano, caudales ecológicos y prevención de inundaciones | C11: USD/ha.año | D11: 20.06 | E11: 47.5
B12: Total | C12: USD/ha.año | D12: =SUM(D11) -> 20.06 | E12: =SUM(E11) -> 47.5
B14: 3. Turismo y recreación
A16: Basado en TEEB, USAID para rango bajo. Rango alto basado en Plan Nacional de Restauración del Paisaje (MAATE, 2022) | B16: Descripción del servicio | C16: Unidades | D16: Costo base (conservador) | E16: Costo rango alto
B17: Beneficio de la recreación en áreas naturales | C17: USD/ha.año | D17: 16.98 | E17: 151.9
B18: Total | C18: USD/ha.año | D18: =SUM(D17) -> 16.98 | E18: =SUM(E17) -> 151.9
H19: Para el análisis de incerteza considerar el comentario que Miguel C. dejo en el documento de word
B20: 4. Secuestro y almacenamiento de carbono
A22: (EPA 2016),rango bajo para el caso conservador. (Ricke et al., 2018) indica un costo social global de 417 usd/tCO2e, asumimos que este valor sería alcanzado en 2050 en el rango alto de costo. Siguiendo una metodología aproximada a la de Ricke, el valor en 2020 sería 210,7 usd/tco2, y se alcanzaría 417 usd/tCO2 en 2050. Otra referencia es 5 USD/ton CO2 según el Plan Nacional de Restauración del Paisaje (MAATE, 2022) | B22: Descripción del servicio | C22: Año | D22: Costo base (conservador) | E22: Costo rango alto | H22: Valor bajo: (Basado en la estimación de EPA, 2016): Para el año presente sería de 14 $/tCO2 en el escenario con 5% de tasa de descuento recomendado por EPA. Pero lo interesante es que este no es un valor constante sino que crece en el tiempo reflejando la creciente concentración de CO2 y como cada tonelada adicional implica mayor riesgo y daños globales. Este valor es del daño global, no separa por países como el de Ricke pero distribuye los daños crecientes en el tiempo por lo que deberíamos usar los de la siguiente tabla con diferentes valores para cada año. Valor alto: recomendado usar el valor medio de Ricke et al 2018 de 417 $/tCO2 total que sería alcanzado en 2050
B23: Mitigación al cambio climático (el carbono fijado no se emite a la atmosfera) | D23: USD/tonCO2 | E23: USD/tonCO2
C25: 2020 | D25: 14 | E25: 210.7
C26: =C25+5 -> 2025 | D26: 18 | E26: 270.5
C27: =C26+5 -> 2030 | D27: 21 | E27: 297.4
C28: =C27+5 -> 2035 | D28: 24 | E28: 328.8
C29: =C28+5 -> 2040 | D29: 28 | E29: 358.7
C30: =C29+5 -> 2045 | D30: 30 | E30: 387.1
C31: =C30+5 -> 2050 | D31: 34 | E31: 417
B33: 5. Otros beneficios ecosistémicos
B35: Descripción del servicio | C35: Unidades | D35: Costo base (conservador) | E35: Costo rango alto
A36: Informe Técnico Programa Socio Bosque II Tablas 17 a 21 | B36: Recursos genéticos | C36: USD/ha.año | D36: 0.1510512
B37: Recursos medicinales | C37: USD/ha.año | D37: 0.0286909
B38: Regulación de la calidad del aire | C38: USD/ha.año | D38: 3.3825202
B39: Moderación de eventos extremos | C39: USD/ha.año | D39: 1.0213386
B40: Control biológico | C40: USD/ha.año | D40: 0.1321698
B41: Mantenimiento de ciclo migratorio de especies | C41: USD/ha.año | D41: 0.1793733
B43: Tasas de descuento sugeridas por Miguel C.
A45: Castillo et al 2021 | B45: Años | C45: %
B46: 0 a 5 | C46: 10.57
B47: 5 a 20 | C47: 3.88
B48: 20 a 50 | C48: 2.77 | D48: Usemos esto de 2,77%
B49: 50 a 100 | C49: 1.99
B52: References
B53: MAATE. (2022). Proyecto Nacional de Restauración del Paisaje 2022-2025.
B54: Ricke, K., Drouet, L., Caldeira, K., & Tavoni, M. (2018). Country-level social cost of carbon. Nature Climate Change, 8(10), Article 10. https://doi.org/10.1038/s41558-018-0282-y

Sheet Driver_macroeconómicos_Agricult
C1: Ecuador | D1: 2018 | E1: 2019 | F1: 2020 | G1: 2021 | H1: 2022 | I1: 2023 | J1: 2024 | K1: 2025 | L1: 2026 | M1: 2027 | N1: 2028 | O1: 2029 | P1: 2030 | Q1: 2031 | R1: 2032 | S1: 2033 | T1: 2034 | U1: 2035 | V1: 2036 | W1: 2037 | X1: 2038 | Y1: 2039 | Z1: 2040 | AA1: 2041 | AB1: 2042 | AC1: 2043 | AD1: 2044 | AE1: 2045 | AF1: 2046 | AG1: 2047 | AH1: 2048 | AI1: 2049 | AJ1: 2050 | AK1: 2051 | AL1: 2052 | AM1: 2053 | AN1: 2054 | AO1: 2055 | AP1: 2056 | AQ1: 2057 | AR1: 2058 | AS1: 2059 | AT1: 2060 | AU1: 2061 | AV1: 2062 | AW1: 2063 | AX1: 2064 | AY1: 2065 | AZ1: 2066 | BA1: 2067 | BB1: 2068 | BC1: 2069 | BD1: 2070
C4: Drivers económicos
C6: Población
C7: Población Nacional | D7: 17023408 | E7: 17267986 | F7: 17510643 | G7: 17751277 | H7: 17989912 | I7: 18226512 | J7: 18460936 | K7: 18693140 | L7: 18922864 | M7: 19150021 | N7: 19374448 | O7: 19596113 | P7: 19814767 | Q7: 20030293 | R7: 20242540 | S7: 20451333 | T7: 20656586 | U7: 20858149 | V7: 21055934 | W7: 21249772 | X7: 21439596 | Y7: 21625281 | Z7: 21806740 | AA7: 21983950 | AB7: 22156850 | AC7: 22325333 | AD7: 22489377 | AE7: 22648875 | AF7: 22803800 | AG7: 22954177 | AH7: 23099877 | AI7: 23240939 | AJ7: 23377412 | AK7: 23509204 | AL7: 23636226 | AM7: 23758390 | AN7: 23875615 | AO7: 23987819 | AP7: 24094924 | AQ7: 24196857 | AR7: 24293546 | AS7: 24384925 | AT7: 24470928 | AU7: 24551497 | AV7: 24626572 | AW7: 24696102 | AX7: 24760036 | AY7: 24818330 | AZ7: 24870940 | BA7: 24917829 | BB7: 24958963 | BC7: 24994311 | BD7: 25023848
C8: Tasa de crecimiento Poblacional [%] | E8: 0.014367158 | F8: 0.01405242 | G8: 0.013742157 | H8: 0.013443258 | I8: 0.013151815 | J8: 0.012861704 | K8: 0.012578127 | L8: 0.012289214 | M8: 0.012004367 | N8: 0.011719413 | O8: 0.0114411 | P8: 0.011158029 | Q8: 0.010877039 | R8: 0.0105963 | S8: 0.010314565 | T8: 0.010036167 | U8: 0.009757808 | V8: 0.009482385 | W8: 0.0092058609 | X8: 0.00893299 | Y8: 0.0086608442 | Z8: 0.0083910586 | AA8: 0.0081263866 | AB8: 0.0078648287 | AC8: 0.0076041044 | AD8: 0.0073478859 | AE8: 0.0070921484 | AF8: 0.0068402956 | AG8: 0.0065943834 | AH8: 0.0063474286 | AI8: 0.0061066126 | AJ8: 0.0058720949 | AK8: 0.0056375773 | AL8: 0.0054030596 | AM8: 0.0051685419 | AN8: 0.0049340242 | AO8: 0.0046995066 | AP8: 0.0044649889 | AQ8: 0.0042304712 | AR8: 0.0039959535 | AS8: 0.0037614358 | AT8: 0.0035269182 | AU8: 0.0032924005 | AV8: 0.0030578828 | AW8: 0.0028233651 | AX8: 0.0025888475 | AY8: 0.0023543298 | AZ8: 0.0021198121 | BA8: 0.0018852944 | BB8: 0.0016507768 | BC8: 0.0014162591 | BD8: 0.0011817414
C10: PIB Nacional Tendencial
C11: PIB Nacional [Miles USD 2021] | D11: 1.1044052e+08 | E11: 1.1045389e+08 | F11: 1.0185217e+08 | G11: 1.0616587e+08 | H11: 1.0903234e+08 | I11: 1.1241235e+08 | J11: 1.1578472e+08 | K11: 1.189109e+08 | L11: 1.2164586e+08 | M11: 1.2552006e+08 | N11: 1.2909258e+08 | O11: 1.3192742e+08 | P11: 1.3506999e+08 | Q11: 1.3934876e+08 | R11: 1.4278631e+08 | S11: 1.4691488e+08 | T11: 1.5039185e+08 | U11: 1.5394779e+08 | V11: 1.5787929e+08 | W11: 1.6146177e+08 | X11: 1.6524433e+08 | Y11: 1.694103e+08 | Z11: 1.7325839e+08 | AA11: 1.7721315e+08 | AB11: 1.8116162e+08 | AC11: 1.8433065e+08 | AD11: 1.8837051e+08 | AE11: 1.9187245e+08 | AF11: 1.962589e+08 | AG11: 1.9987601e+08 | AH11: 2.0345775e+08 | AI11: 2.0717148e+08 | AJ11: 2.1091297e+08 | AK11: 2.1516061e+08 | AL11: 2.1903011e+08 | AM11: 2.2290161e+08 | AN11: 2.2689756e+08 | AO11: 2.3093073e+08 | AP11: 2.3507519e+08 | AQ11: 2.390897e+08 | AR11: 2.4314279e+08 | AS11: 2.4723288e+08 | AT11: 2.5134133e+08 | AU11: 2.5545079e+08 | AV11: 2.5957199e+08 | AW11: 2.6370907e+08 | AX11: 2.6786265e+08 | AY11: 2.7202083e+08 | AZ11: 2.7618252e+08 | BA11: 2.8034186e+08 | BB11: 2.8450685e+08 | BC11: 2.8867414e+08 | BD11: 2.9284055e+08
C12: Tasa de crecimiento del PIB Nacional [%] | E12: 0.00012105103 | F12: -0.077876071 | G12: 0.042352512 | H12: 0.027 | I12: 0.031 | J12: 0.03 | K12: 0.027 | L12: 0.023 | M12: 0.031848226 | N12: 0.028461725 | O12: 0.021959772 | P12: 0.023820424 | Q12: 0.031678203 | R12: 0.024668623 | S12: 0.028914332 | T12: 0.02366656 | U12: 0.023644563 | V12: 0.025537867 | W12: 0.022691249 | X12: 0.023426989 | Y12: 0.025210938 | Z12: 0.022714646 | AA12: 0.022825748 | AB12: 0.022280909 | AC12: 0.017492827 | AD12: 0.021916426 | AE12: 0.018590676 | AF12: 0.022861287 | AG12: 0.018430279 | AH12: 0.017919822 | AI12: 0.018253093 | AJ12: 0.018059848 | AK12: 0.020139299 | AL12: 0.017984242 | AM12: 0.017675659 | AN12: 0.017926947 | AO12: 0.01777532 | AP12: 0.017946763 | AQ12: 0.017077545 | AR12: 0.016952187 | AS12: 0.016821774 | AT12: 0.016617719 | AU12: 0.016350119 | AV12: 0.01613305 | AW12: 0.015938076 | AX12: 0.015750621 | AY12: 0.015523529 | AZ12: 0.015299193 | BA12: 0.015060105 | BB12: 0.014856822 | BC12: 0.014647421 | BD12: 0.014432888
C14: PIB Nacional Optimista
C15: PIB Nacional [Miles USD 2021] | D15: 1.1044052e+08 | E15: 1.1045389e+08 | F15: 1.0185217e+08 | G15: 1.0616587e+08 | H15: 1.0903234e+08 | I15: 1.1241235e+08 | J15: 1.1578472e+08 | K15: 1.189109e+08 | L15: 1.2164586e+08 | M15: 1.2618356e+08 | N15: 1.3119398e+08 | O15: 1.3506116e+08 | P15: 1.3963439e+08 | Q15: 1.4542588e+08 | R15: 1.5108693e+08 | S15: 1.5842426e+08 | T15: 1.6468855e+08 | U15: 1.7163687e+08 | V15: 1.7940792e+08 | W15: 1.8675464e+08 | X15: 1.949134e+08 | Y15: 2.0401983e+08 | Z15: 2.1260645e+08 | AA15: 2.2205733e+08 | AB15: 2.3184204e+08 | AC15: 2.4086664e+08 | AD15: 2.5165093e+08 | AE15: 2.6181995e+08 | AF15: 2.7442058e+08 | AG15: 2.8555366e+08 | AH15: 2.9758914e+08 | AI15: 3.104137e+08 | AJ15: 3.2383289e+08 | AK15: 3.3783219e+08 | AL15: 3.5255474e+08 | AM15: 3.6794329e+08 | AN15: 3.838701e+08 | AO15: 4.0077811e+08 | AP15: 4.1840025e+08 | AQ15: 4.3701471e+08 | AR15: 4.562429e+08 | AS15: 4.7643646e+08 | AT15: 4.9761046e+08 | AU15: 5.197696e+08 | AV15: 5.4293709e+08 | AW15: 5.6723261e+08 | AX15: 5.9266525e+08 | AY15: 6.1931712e+08 | AZ15: 6.4721204e+08 | BA15: 6.7642284e+08 | BB15: 7.0699494e+08 | BC15: 7.3902754e+08 | BD15: 7.7257936e+08
C16: Tasa de crecimiento del PIB Nacional [%] | E16: 0.00012105103 | F16: -0.077876071 | G16: 0.042352512 | H16: 0.027 | I16: 0.031 | J16: 0.03 | K16: 0.027 | L16: 0.023 | M16: 0.037302605 | N16: 0.039707332 | O16: 0.029476823 | P16: 0.03386043 | Q16: 0.041476109 | R16: 0.038927414 | S16: 0.048563643 | T16: 0.039541205 | U16: 0.0421907 | V16: 0.045276099 | W16: 0.040949802 | X16: 0.043687049 | Y16: 0.046720382 | Z16: 0.042087215 | AA16: 0.044452419 | AB16: 0.044063914 | AC16: 0.038925655 | AD16: 0.044772853 | AE16: 0.040409229 | AF16: 0.048127088 | AG16: 0.040569398 | AH16: 0.042147864 | AI16: 0.043094874 | AJ16: 0.04323001 | AK16: 0.04323001 | AL16: 0.043579473 | AM16: 0.043648688 | AN16: 0.043286043 | AO16: 0.044046169 | AP16: 0.043969828 | AQ16: 0.04448959 | AR16: 0.043998954 | AS16: 0.044260547 | AT16: 0.04444244 | AU16: 0.044531097 | AV16: 0.044572613 | AW16: 0.04474832 | AX16: 0.044836349 | AY16: 0.044969527 | AZ16: 0.045041405 | BA16: 0.045133277 | BB16: 0.045196729 | BC16: 0.045308103 | BD16: 0.04539996
C18: PIB Nacional Escenario Negativo
C19: PIB Nacional [Miles USD 2021] | D19: 1.1044052e+08 | E19: 1.1045389e+08 | F19: 1.0185217e+08 | G19: 1.0616587e+08 | H19: 1.0903234e+08 | I19: 1.1241235e+08 | J19: 1.1578472e+08 | K19: 1.189109e+08 | L19: 1.2164586e+08 | M19: 1.2398022e+08 | N19: 1.2628167e+08 | O19: 1.2826239e+08 | P19: 1.3015186e+08 | Q19: 1.3293641e+08 | R19: 1.3547394e+08 | S19: 1.380039e+08 | T19: 1.4043897e+08 | U19: 1.4262325e+08 | V19: 1.4502121e+08 | W19: 1.4734003e+08 | X19: 1.4960131e+08 | Y19: 1.5209086e+08 | Z19: 1.5460176e+08 | AA19: 1.5694566e+08 | AB19: 1.5931023e+08 | AC19: 1.6105022e+08 | AD19: 1.6339398e+08 | AE19: 1.654843e+08 | AF19: 1.6785104e+08 | AG19: 1.7010112e+08 | AH19: 1.7204024e+08 | AI19: 1.740421e+08 | AJ19: 1.7606956e+08 | AK19: 1.7863001e+08 | AL19: 1.8073167e+08 | AM19: 1.8286392e+08 | AN19: 1.8504881e+08 | AO19: 1.8728437e+08 | AP19: 1.895735e+08 | AQ19: 1.9176363e+08 | AR19: 1.9395671e+08 | AS19: 1.9616623e+08 | AT19: 1.9838068e+08 | AU19: 2.0058591e+08 | AV19: 2.0277829e+08 | AW19: 2.0497725e+08 | AX19: 2.0717606e+08 | AY19: 2.0936996e+08 | AZ19: 2.1155518e+08 | BA19: 2.1372957e+08 | BB19: 2.1589648e+08 | BC19: 2.1805594e+08 | BD19: 2.20206e+08
C20: Tasa de crecimiento del PIB Nacional [%] | E20: 0.00012105103 | F20: -0.077876071 | G20: 0.042352512 | H20: 0.027 | I20: 0.031 | J20: 0.03 | K20: 0.027 | L20: 0.023 | M20: 0.019189799 | N20: 0.0185631 | O20: 0.015684905 | P20: 0.014731318 | Q20: 0.021394642 | R20: 0.019088298 | S20: 0.018674849 | T20: 0.017644928 | U20: 0.015553206 | V20: 0.016813279 | W20: 0.015989505 | X20: 0.01534738 | Y20: 0.016641214 | Z20: 0.01650923 | AA20: 0.015160889 | AB20: 0.015066138 | AC20: 0.010922049 | AD20: 0.014552988 | AE20: 0.012793097 | AF20: 0.014301948 | AG20: 0.013405175 | AH20: 0.011399796 | AI20: 0.011636043 | AJ20: 0.01164922 | AK20: 0.014542263 | AL20: 0.011765423 | AM20: 0.011797887 | AN20: 0.011948199 | AO20: 0.012080923 | AP20: 0.012222755 | AQ20: 0.011552933 | AR20: 0.01143636 | AS20: 0.011391832 | AT20: 0.011288604 | AU20: 0.011116163 | AV20: 0.010929889 | AW20: 0.010844183 | AX20: 0.010727066 | AY20: 0.010589524 | AZ20: 0.010437131 | BA20: 0.010278154 | BB20: 0.010138561 | BC20: 0.010002267 | BD20: 0.0098601413
C22: PIB Sectorial Tendencial
C23: Sector agricultura, silvicultura y pesca
C24: PIB Sector agricultura, silvicultura y pesca [Miles USD 2021] | D24: 10459664 | E24: 10628847 | F24: 10666853 | G24: 11028075 | H24: 11407864 | I24: 11743435 | J24: 12109217 | K24: 12395282 | L24: 12636982 | M24: 12958077 | N24: 13237105 | O24: 13402558 | P24: 13597211 | Q24: 13881504 | R24: 14068748 | S24: 14310693 | T24: 14481999 | U24: 14661880 | V24: 14879624 | W24: 15076447 | X24: 15302557 | Y24: 15584162 | Z24: 15852246 | AA24: 16154988 | AB24: 16475218 | AC24: 16750070 | AD24: 17121125 | AE24: 17465869 | AF24: 17904576 | AG24: 18290578 | AH24: 18681161 | AI24: 19094516 | AJ24: 19511992 | AK24: 19879079 | AL24: 20261015 | AM24: 20655812 | AN24: 21066381 | AO24: 21491535 | AP24: 21927658 | AQ24: 22376868 | AR24: 22837221 | AS24: 23308116 | AT24: 23794456 | AU24: 24289030 | AV24: 24794871 | AW24: 25304594 | AX24: 25823213 | AY24: 26351074 | AZ24: 26886949 | BA24: 27431155 | BB24: 27988822 | BC24: 28559780 | BD24: 29144017
C25: Tasa de crecimiento del PIB Nacional [%] | E25: 0.016174817 | F25: 0.0035757596 | G25: 0.033864024 | H25: 0.03443832 | I25: 0.029415819 | J25: 0.031147751 | K25: 0.023623758 | L25: 0.019499324 | M25: 0.025409155 | N25: 0.021533113 | O25: 0.012499168 | P25: 0.014523639 | Q25: 0.020908162 | R25: 0.013488719 | S25: 0.017197377 | T25: 0.011970435 | U25: 0.012421047 | V25: 0.014850993 | W25: 0.013227721 | X25: 0.014997548 | Y25: 0.018402462 | Z25: 0.017202389 | AA25: 0.01909772 | AB25: 0.019822354 | AC25: 0.016682758 | AD25: 0.022152455 | AE25: 0.020135555 | AF25: 0.025117958 | AG25: 0.021558839 | AH25: 0.021354363 | AI25: 0.022126832 | AJ25: 0.021863659 | AK25: 0.018813416 | AL25: 0.019212939 | AM25: 0.01948556 | AN25: 0.019876675 | AO25: 0.020181621 | AP25: 0.020292818 | AQ25: 0.02048597 | AR25: 0.020572736 | AS25: 0.020619635 | AT25: 0.020865689 | AU25: 0.020785267 | AV25: 0.020825874 | AW25: 0.020557618 | AX25: 0.020495042 | AY25: 0.020441334 | AZ25: 0.020335991 | BA25: 0.020240512 | BB25: 0.020329705 | BC25: 0.020399503 | BD25: 0.020456624
C27: PIB Sectorial Optimista
C28: Sector agricultura, silvicultura y pesca
C29: PIB Sector agricultura, silvicultura y pesca [Miles USD 2021] | D29: 10459664 | E29: 10628847 | F29: 10666853 | G29: 11028075 | H29: 11407864 | I29: 11743435 | J29: 12109217 | K29: 12395282 | L29: 12636982 | M29: 13026574 | N29: 13452581 | O29: 13720915 | P29: 14056700 | Q29: 14486888 | R29: 14886609 | S29: 15431800 | T29: 15858701 | U29: 16346576 | V29: 16908629 | W29: 17438162 | X29: 18050080 | Y29: 18767914 | Z29: 19452390 | AA29: 20243044 | AB29: 21084202 | AC29: 21887479 | AD29: 22872726 | AE29: 23833088 | AF29: 25035217 | AG29: 26130907 | AH29: 27324153 | AI29: 28610113 | AJ29: 29958446 | AK29: 31173924 | AL29: 32457827 | AM29: 33808405 | AN29: 35236930 | AO29: 36741591 | AP29: 38317235 | AQ29: 39975811 | AR29: 41712774 | AS29: 43530155 | AT29: 45441600 | AU29: 47433846 | AV29: 49518933 | AW29: 51675616 | AX29: 53925539 | AY29: 56266262 | AZ29: 58695728 | BA29: 61215604 | BB29: 63852687 | BC29: 66610928 | BD29: 69494922
C30: Tasa de crecimiento del PIB Nacional [%] | E30: 0.016174817 | F30: 0.0035757596 | G30: 0.033864024 | H30: 0.03443832 | I30: 0.029415819 | J30: 0.031147751 | K30: 0.023623758 | L30: 0.019499324 | M30: 0.030829498 | N30: 0.03270296 | O30: 0.019946631 | P30: 0.024472476 | Q30: 0.030603785 | R30: 0.027591936 | S30: 0.036622927 | T30: 0.027663701 | U30: 0.030763839 | V30: 0.034383537 | W30: 0.031317319 | X30: 0.035090736 | Y30: 0.039769061 | Z30: 0.036470543 | AA30: 0.040645565 | AB30: 0.041552972 | AC30: 0.038098523 | AD30: 0.045014162 | AE30: 0.0419872 | AF30: 0.050439501 | AG30: 0.043765968 | AH30: 0.045664152 | AI30: 0.047063119 | AJ30: 0.047127865 | AK30: 0.040572129 | AL30: 0.041185147 | AM30: 0.041610248 | AN30: 0.042253556 | AO30: 0.042701232 | AP30: 0.042884492 | AQ30: 0.043285364 | AR30: 0.043450352 | AS30: 0.043568938 | AT30: 0.043910839 | AU30: 0.043841881 | AV30: 0.043957799 | AW30: 0.043552693 | AX30: 0.043539363 | AY30: 0.043406564 | AZ30: 0.043178029 | BA30: 0.042931164 | BB30: 0.043078604 | BC30: 0.043196945 | BD30: 0.043296113
C32: PIB Sectorial Negativo
C33: Sector agricultura, silvicultura y pesca
C34: PIB Sector agricultura, silvicultura y pesca [Miles USD 2021] | D34: 10459664 | E34: 10628847 | F34: 10666853 | G34: 11028075 | H34: 11407864 | I34: 11743435 | J34: 12109217 | K34: 12395282 | L34: 12636982 | M34: 12799111 | N34: 12948876 | O34: 13030225 | P34: 13102114 | Q34: 13242725 | R34: 13348260 | S34: 13442693 | T34: 13523585 | U34: 13583338 | V34: 13667790 | W34: 13757833 | X34: 13853925 | Y34: 13990935 | Z34: 14145261 | AA34: 14307377 | AB34: 14488007 | AC34: 14634585 | AD34: 14850991 | AE34: 15063794 | AF34: 15312945 | AG34: 15565889 | AH34: 15796456 | AI34: 16041058 | AJ34: 16288557 | AK34: 16479165 | AL34: 16679506 | AM34: 16888474 | AN34: 17106331 | AO34: 17333322 | AP34: 17566987 | AQ34: 17806492 | AR34: 18051681 | AS34: 18301537 | AT34: 18559111 | AU34: 18819483 | AV34: 19083155 | AW34: 19347505 | AX34: 19612293 | AY34: 19879324 | AZ34: 20147669 | BA34: 20417205 | BB34: 20692486 | BC34: 20973193 | BD34: 21259067
C35: Tasa de crecimiento del PIB Nacional [%] | E35: 0.016174817 | F35: 0.0035757596 | G35: 0.033864024 | H35: 0.03443832 | I35: 0.029415819 | J35: 0.031147751 | K35: 0.023623758 | L35: 0.019499324 | M35: 0.012829721 | N35: 0.011701174 | O35: 0.0062823889 | P35: 0.0055170661 | Q35: 0.010731955 | R35: 0.0079692793 | S35: 0.0070744971 | T35: 0.0060176045 | U35: 0.004418406 | V35: 0.0062173214 | W35: 0.006587993 | X35: 0.0069844858 | Y35: 0.0098896497 | Z35: 0.011030418 | AA35: 0.011460798 | AB35: 0.012624934 | AC35: 0.010117211 | AD35: 0.014787316 | AE35: 0.014329183 | AF35: 0.016539735 | AG35: 0.016518297 | AH35: 0.014812339 | AI35: 0.01548461 | AJ35: 0.015429079 | AK35: 0.011701986 | AL35: 0.01215721 | AM35: 0.012528453 | AN35: 0.012899732 | AO35: 0.013269434 | AP35: 0.013480671 | AQ35: 0.013633812 | AR35: 0.013769625 | AS35: 0.013841168 | AT35: 0.014073916 | AU35: 0.014029328 | AV35: 0.014010587 | AW35: 0.013852515 | AX35: 0.013685904 | AY35: 0.013615502 | AZ35: 0.013498683 | BA35: 0.013378033 | BB35: 0.013482786 | BC35: 0.013565634 | BD35: 0.013630458
C37: Exportaciones Tendencial
C38: Agrícolas
C39: Valores reales totales [Miles USD 2021] | D39: 5883128.5 | E39: 6149980.1 | F39: 7356140.6 | G39: 5691562.9 | H39: 5663629.7 | I39: 5384523.8 | J39: 6346366.2 | K39: 6188711.7 | L39: 7283331.3 | M39: 7693726.3 | N39: 8145637.2 | O39: 8535947.1 | P39: 9044256.3 | Q39: 8416378 | R39: 8737945.2 | S39: 9182657 | T39: 9456483.5 | U39: 9714917.9 | V39: 9963153.4 | W39: 10152423 | X39: 10293913 | Y39: 10599346 | Z39: 10874020 | AA39: 11128775 | AB39: 11374659 | AC39: 11565263 | AD39: 11808931 | AE39: 12023306 | AF39: 12308490 | AG39: 12539606 | AH39: 12763589 | AI39: 12994627 | AJ39: 13227399 | AK39: 13492960 | AL39: 13736284 | AM39: 13980710 | AN39: 14231532 | AO39: 14484019 | AP39: 14743517 | AQ39: 14995105 | AR39: 15249393 | AS39: 15506153 | AT39: 15763998 | AU39: 16021669 | AV39: 16280034 | AW39: 16539452 | AX39: 16799969 | AY39: 17060806 | AZ39: 17321858 | BA39: 17582730 | BB39: 17843929 | BC39: 18105281 | BD39: 18366592
C40: Tasa de crecimiento real [%] | E40: 0.045358785 | F40: 0.1961243 | G40: -0.22628411 | H40: -0.0049078206 | I40: -0.04928039 | J40: 0.17863091 | K40: -0.024841707 | L40: 0.17687359 | M40: 0.056347159 | N40: 0.058737578 | O40: 0.047916438 | P40: 0.059549238 | Q40: -0.069422878 | R40: 0.038207313 | S40: 0.050894331 | T40: 0.029819963 | U40: 0.0273288 | V40: 0.025551991 | W40: 0.018997005 | X40: 0.013936509 | Y40: 0.02967126 | Z40: 0.025914204 | AA40: 0.023427838 | AB40: 0.022094505 | AC40: 0.016756833 | AD40: 0.021068999 | AE40: 0.018153663 | AF40: 0.02371922 | AG40: 0.018776978 | AH40: 0.017862017 | AI40: 0.018101337 | AJ40: 0.017912971 | AK40: 0.020076609 | AL40: 0.018033399 | AM40: 0.017794168 | AN40: 0.017940547 | AO40: 0.017741369 | AP40: 0.017916214 | AQ40: 0.01706432 | AR40: 0.016958037 | AS40: 0.016837385 | AT40: 0.016628544 | AU40: 0.01634558 | AV40: 0.016125924 | AW40: 0.015934775 | AX40: 0.015751205 | AY40: 0.015526082 | AZ40: 0.015301276 | BA40: 0.015060259 | BB40: 0.014855454 | BC40: 0.014646505 | BD40: 0.014432858
C42: Silvícolas, Pecuarias y Piscícolas
C43: Valores reales totales [Miles USD 2021] | D43: 4414281.6 | E43: 5379687.9 | F43: 6091101.2 | G43: 6105759 | H43: 5339914.7 | I43: 5732252.3 | J43: 6159486.2 | K43: 6432632.9 | L43: 6441734.1 | M43: 6532500.8 | N43: 6797637.4 | O43: 6990817.2 | P43: 7151725.8 | Q43: 7346286.8 | R43: 7520766.9 | S43: 7756677.5 | T43: 7944462.8 | U43: 8127232.6 | V43: 8329853.8 | W43: 8520231.1 | X43: 8723068.4 | Y43: 8942708.1 | Z43: 9144528.2 | AA43: 9352818.6 | AB43: 9561799.4 | AC43: 9729473.5 | AD43: 9942475.7 | AE43: 10127091 | AF43: 10358633 | AG43: 10549675 | AH43: 10738748 | AI43: 10934701 | AJ43: 11132156 | AK43: 11356370 | AL43: 11560625 | AM43: 11764962 | AN43: 11975860 | AO43: 12188735 | AP43: 12407488 | AQ43: 12619379 | AR43: 12833303 | AS43: 13049181 | AT43: 13266029 | AU43: 13482931 | AV43: 13700452 | AW43: 13918810 | AX43: 14138040 | AY43: 14357513 | AZ43: 14577171 | BA43: 14796705 | BB43: 15016537 | BC43: 15236490 | BD43: 15456397
C44: Tasa de crecimiento real [%] | E44: 0.21870065 | F44: 0.13224062 | G44: 0.0024064306 | H44: -0.12542982 | I44: 0.073472624 | J44: 0.074531596 | K44: 0.044345696 | L44: 0.0014148586 | M44: 0.014090401 | N44: 0.040587314 | O44: 0.02841866 | P44: 0.023017149 | Q44: 0.027204751 | R44: 0.023750792 | S44: 0.031367897 | T44: 0.024209495 | U44: 0.023005935 | V44: 0.024931144 | W44: 0.022854818 | X44: 0.02380655 | Y44: 0.025179177 | Z44: 0.022568118 | AA44: 0.022777604 | AB44: 0.022344157 | AC44: 0.017535829 | AD44: 0.021892469 | AE44: 0.018568334 | AF44: 0.022863677 | AG44: 0.018442722 | AH44: 0.01792215 | AI44: 0.018247281 | AJ44: 0.018057648 | AK44: 0.020141129 | AL44: 0.017985959 | AM44: 0.017675231 | AN44: 0.017925968 | AO44: 0.017775308 | AP44: 0.017947188 | AQ44: 0.01707769 | AR44: 0.016952017 | AS44: 0.016821656 | AT44: 0.016617773 | AU44: 0.016350186 | AV44: 0.016133045 | AW44: 0.015938042 | AX44: 0.015750614 | AY44: 0.015523544 | AZ44: 0.0152992 | BA44: 0.0150601 | BB44: 0.014856817 | BC44: 0.014647422 | BD44: 0.014432891
C46: Industria alimenticia
C47: Valores reales totales [Miles USD 2021] | D47: 26748.703 | E47: 25197.883 | F47: 27706.871 | G47: 24418.158 | H47: 26016.959 | I47: 27635.577 | J47: 29034.711 | K47: 29856.626 | L47: 30678.241 | M47: 31218.924 | N47: 31644.483 | O47: 32109.304 | P47: 32539.717 | Q47: 32914.282 | R47: 33458.747 | S47: 34103.279 | T47: 34562.174 | U47: 35006.872 | V47: 35348.557 | W47: 35798.362 | X47: 36304.699 | Y47: 36788.813 | Z47: 37273.684 | AA47: 37766.895 | AB47: 38121.602 | AC47: 38578.297 | AD47: 38936.819 | AE47: 39331.72 | AF47: 39823.216 | AG47: 40300.155 | AH47: 40773.188 | AI47: 41114.577 | AJ47: 41564.579 | AK47: 42026.181 | AL47: 42481.222 | AM47: 42931.428 | AN47: 43376.618 | AO47: 43843.748 | AP47: 44314.367 | AQ47: 44786.743 | AR47: 45262.65 | AS47: 45743.871 | AT47: 46232.604 | AU47: 46725.772 | AV47: 47223.577 | AW47: 47726.629 | AX47: 48235.292 | AY47: 48749.629 | AZ47: 49269.245 | BA47: 49794.318 | BB47: 50325.022 | BC47: 50861.436 | BD47: 51403.579
C48: Tasa de crecimiento real [%] | E48: -0.057977402 | F48: 0.099571393 | G48: -0.11869665 | H48: 0.065475896 | I48: 0.06221395 | J48: 0.050628002 | K48: 0.028308028 | L48: 0.027518678 | M48: 0.017624308 | N48: 0.013631462 | O48: 0.01468884 | P48: 0.013404614 | Q48: 0.011511017 | R48: 0.016541913 | S48: 0.019263472 | T48: 0.013456047 | U48: 0.012866601 | V48: 0.009760505 | W48: 0.012724862 | X48: 0.014144134 | Y48: 0.013334732 | Z48: 0.013179853 | AA48: 0.013232152 | AB48: 0.0093920047 | AC48: 0.011979946 | AD48: 0.0092933727 | AE48: 0.010142095 | AF48: 0.012496181 | AG48: 0.011976397 | AH48: 0.011737743 | AI48: 0.0083728974 | AJ48: 0.010945063 | AK48: 0.011105656 | AL48: 0.010827551 | AM48: 0.010597782 | AN48: 0.01036979 | AO48: 0.010769168 | AP48: 0.01073399 | AQ48: 0.010659656 | AR48: 0.010626077 | AS48: 0.010631736 | AT48: 0.010684126 | AU48: 0.010667117 | AV48: 0.010653742 | AW48: 0.01065256 | AX48: 0.010657856 | AY48: 0.01066308 | AZ48: 0.010658871 | BA48: 0.010657222 | BB48: 0.010657918 | BC48: 0.010658989 | BD48: 0.010659216
C50: Exportaciones Optimista
C51: Agrícolas
C52: Valores reales totales [Miles USD 2021] | D52: 5883128.5 | E52: 6149980.1 | F52: 7356140.6 | G52: 5691562.9 | H52: 5663629.7 | I52: 5384523.8 | J52: 6346366.2 | K52: 6188711.7 | L52: 7283331.3 | M52: 7734395.6 | N52: 8278233.7 | O52: 8738705.6 | P52: 9349887.3 | Q52: 8783423.1 | R52: 9245909.9 | S52: 9902031.1 | T52: 10355445 | U52: 10831192 | V52: 11321742 | W52: 11742793 | X52: 12142150 | Y52: 12764730 | Z52: 13343577 | AA52: 13944936 | AB52: 14556749 | AC52: 15112441 | AD52: 15775975 | AE52: 16406428 | AF52: 17210445 | AG52: 17914759 | AH52: 18668767 | AI52: 19470393 | AJ52: 20309168 | AK52: 21185832 | AL52: 22110167 | AM52: 23077933 | AN52: 24077208 | AO52: 25136878 | AP52: 26241354 | AQ52: 27408465 | AR52: 28614573 | AS52: 29881529 | AT52: 31209869 | AU52: 32599533 | AV52: 34052341 | AW52: 35576010 | AX52: 37171130 | AY52: 38842796 | AZ52: 40592413 | BA52: 42424489 | BB52: 44341877 | BC52: 46350881 | BD52: 48455208
C53: Tasa de crecimiento real [%] | E53: 0.045358785 | F53: 0.1961243 | G53: -0.22628411 | H53: -0.0049078206 | I53: -0.04928039 | J53: 0.17863091 | K53: -0.024841707 | L53: 0.17687359 | M53: 0.061931041 | N53: 0.070314234 | O53: 0.055624414 | P53: 0.069939615 | Q53: -0.060585134 | R53: 0.052654502 | S53: 0.070963397 | T53: 0.045790032 | U53: 0.045941686 | V53: 0.045290494 | W53: 0.037189604 | X53: 0.034008693 | Y53: 0.051274284 | Z53: 0.04534738 | AA53: 0.04506724 | AB53: 0.043873538 | AC53: 0.038174158 | AD53: 0.043906473 | AE53: 0.039962854 | AF53: 0.049006213 | AG53: 0.040923633 | AH53: 0.042088683 | AI53: 0.042939416 | AJ53: 0.043079502 | AK53: 0.043165902 | AL53: 0.043629865 | AM53: 0.043770222 | AN53: 0.043299982 | AO53: 0.044011341 | AP53: 0.043938498 | AQ53: 0.044476009 | AR53: 0.044004959 | AS53: 0.044276579 | AT53: 0.044453561 | AU53: 0.044526432 | AV53: 0.044565288 | AW53: 0.044744926 | AX53: 0.044836949 | AY53: 0.044972154 | AZ53: 0.045043549 | BA53: 0.045133435 | BB53: 0.04519532 | BC53: 0.045307159 | BD53: 0.045399929
C55: Silvícolas, Pecuarias y Piscícolas
C56: Valores reales totales [Miles USD 2021] | D56: 4414281.6 | E56: 5379687.9 | F56: 6091101.2 | G56: 6105759 | H56: 5339914.7 | I56: 5732252.3 | J56: 6159486.2 | K56: 6432632.9 | L56: 6441734.1 | M56: 6567031.7 | N56: 6908290.9 | O56: 7156873.4 | P56: 7393402.9 | Q56: 7666664.4 | R56: 7957973.2 | S56: 8364339.6 | T56: 8699687.4 | U56: 9061076.8 | V56: 9465723.6 | W56: 9854919.1 | X56: 10289266 | Y56: 10769651 | Z56: 11221307 | AA56: 11719570 | AB56: 12236737 | AC56: 12713597 | AD56: 13282510 | AE56: 13818943 | AF56: 14484042 | AG56: 15071835 | AH56: 15707117 | AI56: 16383920 | AJ56: 17092160 | AK56: 17831086 | AL56: 18608187 | AM56: 19420401 | AN56: 20261014 | AO56: 21153434 | AP56: 22083556 | AQ56: 23066048 | AR56: 24080926 | AS56: 25146758 | AT56: 26264343 | AU56: 27433924 | AV56: 28656726 | AW56: 29939065 | AX56: 31281423 | AY56: 32688135 | AZ56: 34160454 | BA56: 35702227 | BB56: 37315851 | BC56: 39006562 | BD56: 40777458
C57: Tasa de crecimiento real [%] | E57: 0.21870065 | F57: 0.13224062 | G57: 0.0024064306 | H57: -0.12542982 | I57: 0.073472624 | J57: 0.074531596 | K57: 0.044345696 | L57: 0.0014148586 | M57: 0.019450912 | N57: 0.051965507 | O57: 0.03598322 | P57: 0.033049277 | Q57: 0.036960173 | R57: 0.037996811 | S57: 0.051064064 | T57: 0.04009256 | U57: 0.041540501 | V57: 0.044657698 | W57: 0.041116292 | X57: 0.044074124 | Y57: 0.046687955 | Z57: 0.041937911 | AA57: 0.044403256 | AB57: 0.04412851 | AC57: 0.038969563 | AD57: 0.044748361 | AE57: 0.040386408 | AF57: 0.048129537 | AG57: 0.040582111 | AH57: 0.042150248 | AI57: 0.04308892 | AJ57: 0.043227757 | AK57: 0.043231882 | AL57: 0.043581232 | AM57: 0.04364825 | AN57: 0.04328504 | AO57: 0.044046156 | AP57: 0.043970264 | AQ57: 0.044489738 | AR57: 0.04399878 | AS57: 0.044260426 | AT57: 0.044442495 | AU57: 0.044531166 | AV57: 0.044572609 | AW57: 0.044748285 | AX57: 0.044836341 | AY57: 0.044969543 | AZ57: 0.045041413 | BA57: 0.045133272 | BB57: 0.045196724 | BC57: 0.045308104 | BD57: 0.045399962
C59: Industria alimenticia
C60: Valores reales totales [Miles USD 2021] | D60: 26748.703 | E60: 25197.883 | F60: 27706.871 | G60: 24418.158 | H60: 26016.959 | I60: 27635.577 | J60: 29034.711 | K60: 29856.626 | L60: 30678.241 | M60: 31581.888 | N60: 31957.127 | O60: 32590.242 | P60: 33463.411 | Q60: 34195.151 | R60: 34668.565 | S60: 35375.815 | T60: 36404.849 | U60: 37505.169 | V60: 38419.325 | W60: 39379.83 | X60: 40376.572 | Y60: 41448.817 | Z60: 42679.39 | AA60: 43880.272 | AB60: 45117.784 | AC60: 46241.865 | AD60: 47428.296 | AE60: 48524.514 | AF60: 49698.804 | AG60: 51031.78 | AH60: 52577.666 | AI60: 53946.898 | AJ60: 55326.838 | AK60: 56797.816 | AL60: 58335.02 | AM60: 59916.667 | AN60: 61503.097 | AO60: 63136.885 | AP60: 64826.508 | AQ60: 66563.606 | AR60: 68343.678 | AS60: 70166.286 | AT60: 72040.181 | AU60: 73966.169 | AV60: 75943.258 | AW60: 77972.184 | AX60: 80054.909 | AY60: 82193.952 | AZ60: 84390.368 | BA60: 86645.264 | BB60: 88960.241 | BC60: 91337.097 | BD60: 93777.586
C61: Tasa de crecimiento real [%] | E61: -0.057977402 | F61: 0.099571393 | G61: -0.11869665 | H61: 0.065475896 | I61: 0.06221395 | J61: 0.050628002 | K61: 0.028308028 | L61: 0.027518678 | M61: 0.029455624 | N61: 0.011881468 | O61: 0.019811376 | P61: 0.026792342 | Q61: 0.021866878 | R61: 0.01384448 | S61: 0.020400333 | T61: 0.029088635 | U61: 0.030224543 | V61: 0.024374125 | W61: 0.025000554 | X61: 0.025310994 | Y61: 0.026556119 | Z61: 0.029688975 | AA61: 0.028137276 | AB61: 0.02820202 | AC61: 0.02491437 | AD61: 0.025657074 | AE61: 0.023113167 | AF61: 0.024199919 | AG61: 0.026821099 | AH61: 0.030292604 | AI61: 0.026042096 | AJ61: 0.025579588 | AK61: 0.026587061 | AL61: 0.02706449 | AM61: 0.027113168 | AN61: 0.026477281 | AO61: 0.026564318 | AP61: 0.026761264 | AQ61: 0.026796104 | AR61: 0.026742427 | AS61: 0.026668279 | AT61: 0.026706478 | AU61: 0.02673491 | AV61: 0.026729639 | AW61: 0.026716347 | AX61: 0.026711131 | AY61: 0.026719701 | AZ61: 0.026722346 | BA61: 0.026719833 | BB61: 0.026717871 | BC61: 0.026718176 | BD61: 0.026719585
C63: Exportaciones Negativo
C64: Agrícolas
C65: Valores reales totales [Miles USD 2021] | D65: 5883128.5 | E65: 6149980.1 | F65: 7356140.6 | G65: 5691562.9 | H65: 5663629.7 | I65: 5384523.8 | J65: 6346366.2 | K65: 6188711.7 | L65: 7283331.3 | M65: 7599341.8 | N65: 7968271.3 | O65: 8298812.7 | P65: 8714939.6 | Q65: 8029085.4 | R65: 8290458.2 | S65: 8625692.1 | T65: 8830657 | U65: 9000279 | V65: 9151729.3 | W65: 9264473.7 | X65: 9319429 | Y65: 9515735.8 | Z65: 9703094.7 | AA65: 9856000.6 | AB65: 10002668 | AC65: 10104603 | AD65: 10243154 | AE65: 10369745 | AF65: 10526875 | AG65: 10671621 | AH65: 10792662 | AI65: 10916619 | AJ65: 11042196 | AK65: 11202086 | AL65: 11334431 | AM65: 11469488 | AN65: 11606683 | AO65: 11746511 | AP65: 11889729 | AQ65: 12026934 | AR65: 12164548 | AS65: 12303313 | AT65: 12442333 | AU65: 12580588 | AV65: 12718003 | AW65: 12855878 | AX65: 12993791 | AY65: 13131422 | AZ65: 13268504 | BA65: 13404881 | BB65: 13540769 | BC65: 13676195 | BD65: 13811044
C66: Tasa de crecimiento real [%] | E66: 0.045358785 | F66: 0.1961243 | G66: -0.22628411 | H66: -0.0049078206 | I66: -0.04928039 | J66: 0.17863091 | K66: -0.024841707 | L66: 0.17687359 | M66: 0.043388186 | N66: 0.048547558 | O66: 0.041482196 | P66: 0.050142944 | Q66: -0.078698683 | R66: 0.032553257 | S66: 0.040436108 | T66: 0.023762134 | U66: 0.019208321 | V66: 0.016827283 | W66: 0.01231947 | X66: 0.0059318235 | Y66: 0.021064252 | Z66: 0.019689374 | AA66: 0.015758467 | AB66: 0.014881049 | AC66: 0.010190808 | AD66: 0.013711667 | AE66: 0.012358571 | AF66: 0.015152702 | AG66: 0.013750163 | AH66: 0.011342362 | AI66: 0.011485274 | AJ66: 0.011503268 | AK66: 0.014479918 | AL66: 0.011814279 | AM66: 0.011915712 | AN66: 0.011961719 | AO66: 0.012047162 | AP66: 0.012192378 | AQ66: 0.01153978 | AR66: 0.011442178 | AS66: 0.011407359 | AT66: 0.011299371 | AU66: 0.011111648 | AV66: 0.0109228 | AW66: 0.010840899 | AX66: 0.010727647 | AY66: 0.010592064 | AZ66: 0.010439204 | BA66: 0.010278307 | BB66: 0.0101372 | BC66: 0.010001356 | BD66: 0.0098601113
C68: Silvícolas, Pecuarias y Piscícolas
C69: Valores reales totales [Miles USD 2021] | D69: 4414281.6 | E69: 5379687.9 | F69: 6091101.2 | G69: 6105759 | H69: 5339914.7 | I69: 5732252.3 | J69: 6159486.2 | K69: 6432632.9 | L69: 6441734.1 | M69: 6452361.8 | N69: 6649623.4 | O69: 6796607.5 | P69: 6891319.4 | Q69: 7008236.1 | R69: 7135614 | S69: 7286204 | T69: 7418701.2 | U69: 7529385.4 | V69: 7651449.7 | W69: 7775035.9 | X69: 7897290.2 | Y69: 8028461.9 | Z69: 8159836.4 | AA69: 8283156.9 | AB69: 8408472.2 | AC69: 8500669.2 | AD69: 8624177.2 | AE69: 8734315.5 | AF69: 8859254 | AG69: 8978123.5 | AH69: 9080493.1 | AI69: 9186101.6 | AJ69: 9293092.5 | AK69: 9428252 | AL69: 9539195.4 | AM69: 9651733.7 | AN69: 9767045.2 | AO69: 9885040 | AP69: 10005867 | AQ69: 10121465 | AR69: 10237216 | AS69: 10353836 | AT69: 10470716 | AU69: 10587111 | AV69: 10702827 | AW69: 10818890 | AX69: 10934945 | AY69: 11050741 | AZ69: 11166079 | BA69: 11280846 | BB69: 11395217 | BC69: 11509195 | BD69: 11622678
C70: Tasa de crecimiento real [%] | E70: 0.21870065 | F70: 0.13224062 | G70: 0.0024064306 | H70: -0.12542982 | I70: 0.073472624 | J70: 0.074531596 | K70: 0.044345696 | L70: 0.0014148586 | M70: 0.0016498219 | N70: 0.030571984 | O70: 0.022104135 | P70: 0.013935174 | Q70: 0.016965781 | R70: 0.018175465 | S70: 0.021103996 | T70: 0.018184669 | U70: 0.014919626 | V70: 0.016211717 | W70: 0.016152003 | X70: 0.015723944 | Y70: 0.016609718 | Z70: 0.016363591 | AA70: 0.015113105 | AB70: 0.01512894 | AC70: 0.010964773 | AD70: 0.014529204 | AE70: 0.012770882 | AF70: 0.014304318 | AG70: 0.013417556 | AH70: 0.01140211 | AI70: 0.011630269 | AJ70: 0.011647035 | AK70: 0.014544084 | AL70: 0.011767129 | AM70: 0.011797462 | AN70: 0.011947226 | AO70: 0.012080911 | AP70: 0.012223178 | AQ70: 0.011553077 | AR70: 0.011436191 | AS70: 0.011391715 | AT70: 0.011288657 | AU70: 0.01111623 | AV70: 0.010929885 | AW70: 0.010844149 | AX70: 0.010727059 | AY70: 0.010589539 | AZ70: 0.010437138 | BA70: 0.010278149 | BB70: 0.010138556 | BC70: 0.010002268 | BD70: 0.0098601439
C72: Industria alimenticia
C73: Valores reales totales [Miles USD 2021] | D73: 26748.703 | E73: 25197.883 | F73: 27706.871 | G73: 24418.158 | H73: 26016.959 | I73: 27635.577 | J73: 29034.711 | K73: 29856.626 | L73: 30678.241 | M73: 31288.023 | N73: 31646.437 | O73: 31953.219 | P73: 32242.335 | Q73: 32533.358 | R73: 32822.051 | S73: 33171.604 | T73: 33646.209 | U73: 33942.906 | V73: 34229.448 | W73: 34463.98 | X73: 34750.243 | Y73: 35073.604 | Z73: 35412.302 | AA73: 35721.207 | AB73: 36039.681 | AC73: 36250.087 | AD73: 36537.446 | AE73: 36770.17 | AF73: 37002.714 | AG73: 37337.712 | AH73: 37621.054 | AI73: 37901.481 | AJ73: 38105.403 | AK73: 38378.241 | AL73: 38659.449 | AM73: 38929.372 | AN73: 39196.456 | AO73: 39460.723 | AP73: 39737.518 | AQ73: 40015.098 | AR73: 40291.88 | AS73: 40570.052 | AT73: 40850.494 | AU73: 41134.267 | AV73: 41419.454 | AW73: 41706.186 | AX73: 41994.949 | AY73: 42285.879 | AZ73: 42578.952 | BA73: 42873.921 | BB73: 43170.887 | BC73: 43469.944 | BD73: 43771.102
C74: Tasa de crecimiento real [%] | E74: -0.057977402 | F74: 0.099571393 | G74: -0.11869665 | H74: 0.065475896 | I74: 0.06221395 | J74: 0.050628002 | K74: 0.028308028 | L74: 0.027518678 | M74: 0.019876703 | N74: 0.01145531 | O74: 0.009694029 | P74: 0.0090480946 | Q74: 0.0090261425 | R74: 0.008873734 | S74: 0.010649947 | T74: 0.014307567 | U74: 0.0088181308 | V74: 0.0084419005 | W74: 0.0068517665 | X74: 0.0083061432 | Y74: 0.0093052749 | Z74: 0.0096567953 | AA74: 0.008723085 | AB74: 0.0089155461 | AC74: 0.0058381667 | AD74: 0.0079271484 | AE74: 0.0063694411 | AF74: 0.0063242779 | AG74: 0.0090533157 | AH74: 0.0075886438 | AI74: 0.007453995 | AJ74: 0.0053802992 | AK74: 0.0071601063 | AL74: 0.007327272 | AM74: 0.0069820633 | AN74: 0.0068607471 | AO74: 0.0067420976 | AP74: 0.0070144573 | AQ74: 0.0069853274 | AR74: 0.0069169385 | AS74: 0.0069039136 | AT74: 0.0069125469 | AU74: 0.0069466367 | AV74: 0.0069330726 | AW74: 0.0069226217 | AX74: 0.0069237583 | AY74: 0.0069277273 | AZ74: 0.0069307633 | BA74: 0.0069275886 | BB74: 0.0069264918 | BC74: 0.0069272659 | BD74: 0.0069279674
C76: Importaciones Tendencial
C77: Alimentos, bebidas y tabacos
C78: Valores reales totales [Miles USD 2021] | D78: 790705.76 | E78: 889438.4 | F78: 987993.3 | G78: 941721.56 | H78: 1093434.6 | I78: 1098322.8 | J78: 1146286.6 | K78: 1324043 | L78: 1457120.1 | M78: 1678994.9 | N78: 1897921.2 | O78: 2111850 | P78: 2343327.2 | Q78: 2046012 | R78: 2173711.4 | S78: 2290839.7 | T78: 2371854.5 | U78: 2420654.3 | V78: 2431158 | W78: 2509450.8 | X78: 2578767.3 | Y78: 2644214.5 | Z78: 2698634.9 | AA78: 2754984.8 | AB78: 2821706.3 | AC78: 2872303 | AD78: 2934370.4 | AE78: 2987744.5 | AF78: 3055880.7 | AG78: 3113180.7 | AH78: 3168965.4 | AI78: 3226527.3 | AJ78: 3284651.7 | AK78: 3350887.4 | AL78: 3411292 | AM78: 3471543.2 | AN78: 3533722.2 | AO78: 3596530.6 | AP78: 3661103.7 | AQ78: 3723640.3 | AR78: 3786749.8 | AS78: 3850442.3 | AT78: 3914431.1 | AU78: 3978437.5 | AV78: 4042621.9 | AW78: 4107050.6 | AX78: 4171738.7 | AY78: 4236499.9 | AZ78: 4301315.6 | BA78: 4366093.5 | BB78: 4430959.3 | BC78: 4495861.5 | BD78: 4560750
C79: Tasa de crecimiento real [%] | E79: 0.12486647 | F79: 0.11080576 | G79: -0.046834059 | H79: 0.16110175 | I79: 0.0044705632 | J79: 0.043670023 | K79: 0.15507153 | L79: 0.10050811 | M79: 0.15226941 | N79: 0.13039127 | O79: 0.11271745 | P79: 0.10960872 | Q79: -0.12687739 | R79: 0.062413845 | S79: 0.053884007 | T79: 0.035364686 | U79: 0.020574495 | V79: 0.0043392275 | W79: 0.032203921 | X79: 0.027622156 | Y79: 0.025379249 | Z79: 0.020580947 | AA79: 0.020880896 | AB79: 0.024218457 | AC79: 0.017931237 | AD79: 0.021608948 | AE79: 0.018189288 | AF79: 0.022805222 | AG79: 0.018750715 | AH79: 0.017918903 | AI79: 0.018164242 | AJ79: 0.018014533 | AK79: 0.020165228 | AL79: 0.018026449 | AM79: 0.017662266 | AN79: 0.017911055 | AO79: 0.017774016 | AP79: 0.017954259 | AQ79: 0.017081363 | AR79: 0.016948336 | AS79: 0.01681983 | AT79: 0.016618561 | AU79: 0.016351389 | AV79: 0.016133076 | AW79: 0.015937345 | AX79: 0.015750514 | AY79: 0.015523789 | AZ79: 0.015299337 | BA79: 0.015060024 | BB79: 0.014856719 | BC79: 0.014647443 | BD79: 0.014432937
C81: Materia prima agrícola
C82: Valores reales totales [Miles USD 2021] | D82: 1498460.7 | E82: 1487939.6 | F82: 1630352.9 | G82: 1851563.2 | H82: 2113300.7 | I82: 2263283 | J82: 2478648.5 | K82: 2868643.6 | L82: 2639155.2 | M82: 2553054.1 | N82: 2684920.6 | O82: 2795622.4 | P82: 2926119.6 | Q82: 3055474.3 | R82: 3050542.6 | S82: 3141996.6 | T82: 3171445.1 | U82: 3184012.8 | V82: 3223634.8 | W82: 3205274.8 | X82: 3221109.1 | Y82: 3273976.2 | Z82: 3270881.8 | AA82: 3283564.8 | AB82: 3287341.7 | AC82: 3237716.4 | AD82: 3273393.9 | AE82: 3268449.4 | AF82: 3325358.9 | AG82: 3325733 | AH82: 3318784.7 | AI82: 3342859.1 | AJ82: 3356042.9 | AK82: 3373919.1 | AL82: 3383735.6 | AM82: 3395473.6 | AN82: 3411026.9 | AO82: 3424827.5 | AP82: 3438753.9 | AQ82: 3451870.2 | AR82: 3465661.1 | AS82: 3479871.9 | AT82: 3493806.7 | AU82: 3507768.4 | AV82: 3521736.7 | AW82: 3535878.8 | AX82: 3550092.1 | AY82: 3564305.3 | AZ82: 3578574.8 | BA82: 3592906.6 | BB82: 3607312.3 | BC82: 3621771.3 | BD82: 3636279.8
C83: Tasa de crecimiento real [%] | E83: -0.0070212934 | F83: 0.095711736 | G83: 0.13568252 | H83: 0.14136025 | I83: 0.070970649 | J83: 0.095156235 | K83: 0.15734183 | L83: -0.079998916 | M83: -0.032624507 | N83: 0.051650486 | O83: 0.041230949 | P83: 0.046679133 | Q83: 0.044206903 | R83: -0.0016140473 | S83: 0.029979576 | T83: 0.0093725527 | U83: 0.0039627761 | V83: 0.012444031 | W83: -0.005695423 | X83: 0.0049400648 | Y83: 0.016412689 | Z83: -0.00094514749 | AA83: 0.003877554 | AB83: 0.001150259 | AC83: -0.015095888 | AD83: 0.011019354 | AE83: -0.0015105304 | AF83: 0.017411784 | AG83: 0.0001124915 | AH83: -0.0020892624 | AI83: 0.0072539977 | AJ83: 0.0039438638 | AK83: 0.005326575 | AL83: 0.0029095331 | AM83: 0.0034689414 | AN83: 0.0045805822 | AO83: 0.0040458991 | AP83: 0.0040663062 | AQ83: 0.0038142524 | AR83: 0.0039951963 | AS83: 0.0041004472 | AT83: 0.0040044202 | AU83: 0.0039961245 | AV83: 0.0039820881 | AW83: 0.0040156553 | AX83: 0.0040197471 | AY83: 0.004003607 | AZ83: 0.0040034444 | BA83: 0.0040049084 | BB83: 0.0040094724 | BC83: 0.0040082359 | BD83: 0.0040059336
C85: Importaciones Optimista
C86: Alimentos, bebidas y tabacos
C87: Valores reales totales [Miles USD 2021] | D87: 790705.76 | E87: 889438.4 | F87: 987993.3 | G87: 941721.56 | H87: 1093434.6 | I87: 1098322.8 | J87: 1146286.6 | K87: 1324043 | L87: 1457120.1 | M87: 1692181.6 | N87: 1920507.2 | O87: 2142857.6 | P87: 2387433.8 | Q87: 2135240.2 | R87: 2300076.2 | S87: 2470305.3 | T87: 2597330.2 | U87: 2698794.9 | V87: 2762673.9 | W87: 2902554.5 | X87: 3041776.3 | Y87: 3184411.9 | Z87: 3311511.7 | AA87: 3452139.8 | AB87: 3611085.8 | AC87: 3753266.2 | AD87: 3920130.8 | AE87: 4076933 | AF87: 4272909.7 | AG87: 4447658.1 | AH87: 4635113.2 | AI87: 4834440.9 | AJ87: 5043209.3 | AK87: 5261361.1 | AL87: 5490876 | AM87: 5730470.2 | AN87: 5978426.2 | AO87: 6241745 | AP87: 6516241.4 | AQ87: 6806171.9 | AR87: 7105609.4 | AS87: 7420093.4 | AT87: 7749866.9 | AU87: 8094987 | AV87: 8455802 | AW87: 8834178.6 | AX87: 9230269.9 | AY87: 9645353.3 | AZ87: 10079795 | BA87: 10534728 | BB87: 11010862 | BC87: 11509744 | BD87: 12032286
C88: Tasa de crecimiento real [%] | E88: 0.12486647 | F88: 0.11080576 | G88: -0.046834059 | H88: 0.16110175 | I88: 0.0044705632 | J88: 0.043670023 | K88: 0.15507153 | L88: 0.10050811 | M88: 0.16131926 | N88: 0.13492971 | O88: 0.11577693 | P88: 0.11413555 | Q88: -0.10563376 | R88: 0.07719788 | S88: 0.074010167 | T88: 0.051420741 | U88: 0.039065009 | V88: 0.023669455 | W88: 0.050632309 | X88: 0.047965265 | Y88: 0.046892224 | Z88: 0.039913098 | AA88: 0.042466444 | AB88: 0.046042748 | AC88: 0.039373301 | AD88: 0.044458499 | AE88: 0.039999243 | AF88: 0.048069638 | AG88: 0.0408968 | AH88: 0.042146923 | AI88: 0.043003855 | AJ88: 0.043183575 | AK88: 0.043256527 | AL88: 0.043622741 | AM88: 0.043634953 | AN88: 0.043269755 | AO88: 0.044044831 | AP88: 0.043977517 | AQ88: 0.044493511 | AR88: 0.043995001 | AS88: 0.04425855 | AT88: 0.044443305 | AU88: 0.044532402 | AV88: 0.044572641 | AW88: 0.044747569 | AX88: 0.044836238 | AY88: 0.044969794 | AZ88: 0.045041553 | BA88: 0.045133193 | BB88: 0.045196623 | BC88: 0.045308126 | BD88: 0.045400009
C90: Materia prima agrícola
C91: Valores reales totales [Miles USD 2021] | D91: 1498460.7 | E91: 1487939.6 | F91: 1630352.9 | G91: 1851563.2 | H91: 2113300.7 | I91: 2263283 | J91: 2478648.5 | K91: 2868643.6 | L91: 2639155.2 | M91: 2688268.2 | N91: 2978214.3 | O91: 3196846.9 | P91: 3512316.6 | Q91: 3844073.5 | R91: 4073914.4 | S91: 4604245.5 | T91: 4967646.4 | U91: 5421170.4 | V91: 6021906.8 | W91: 6488767.1 | X91: 7151090.1 | Y91: 8011202.4 | Z91: 7477401.8 | AA91: 7969007.3 | AB91: 8427807.2 | AC91: 8833261.8 | AD91: 9227961 | AE91: 9464861.4 | AF91: 9974170.3 | AG91: 10405038 | AH91: 10848743 | AI91: 11302771 | AJ91: 11774698 | AK91: 12297918 | AL91: 12837814 | AM91: 13396369 | AN91: 13972663 | AO91: 14587103 | AP91: 15231553 | AQ91: 15909358 | AR91: 16608527 | AS91: 17343061 | AT91: 18114045 | AU91: 18921213 | AV91: 19764452 | AW91: 20648676 | AX91: 21574448 | AY91: 22544738 | AZ91: 23560252 | BA91: 24623550 | BB91: 25736419 | BC91: 26902497 | BD91: 28123893
C92: Tasa de crecimiento real [%] | E92: -0.0070212934 | F92: 0.095711736 | G92: 0.13568252 | H92: 0.14136025 | I92: 0.070970649 | J92: 0.095156235 | K92: 0.15734183 | L92: -0.079998916 | M92: 0.018609366 | N92: 0.10785607 | O92: 0.073410659 | P92: 0.098681519 | Q92: 0.094455296 | R92: 0.05979096 | S92: 0.13017729 | T92: 0.078927344 | U92: 0.091295539 | V92: 0.11081306 | W92: 0.077526985 | X92: 0.10207223 | Y92: 0.1202771 | Z92: -0.066631773 | AA92: 0.065745491 | AB92: 0.057573038 | AC92: 0.048109138 | AD92: 0.044683289 | AE92: 0.025672028 | AF92: 0.053810498 | AG92: 0.043198306 | AH92: 0.042643287 | AI92: 0.04185083 | AJ92: 0.041753196 | AK92: 0.04443589 | AL92: 0.043901432 | AM92: 0.043508584 | AN92: 0.043018682 | AO92: 0.043974438 | AP92: 0.044179446 | AQ92: 0.044500029 | AR92: 0.043947061 | AS92: 0.044226303 | AT92: 0.04445488 | AU92: 0.044560378 | AV92: 0.04456581 | AW92: 0.044738067 | AX92: 0.044834431 | AY92: 0.044974079 | AZ92: 0.045044379 | BA92: 0.045130985 | BB92: 0.045195341 | BC92: 0.045308488 | BD92: 0.045400806
C94: Importaciones Negativo
C95: Alimentos, bebidas y tabacos
C96: Valores reales totales [Miles USD 2021] | D96: 790705.76 | E96: 889438.4 | F96: 987993.3 | G96: 941721.56 | H96: 1093434.6 | I96: 1098322.8 | J96: 1146286.6 | K96: 1324043 | L96: 1457120.1 | M96: 1617379.9 | N96: 1754454 | O96: 1895089.6 | P96: 2023040.8 | Q96: 1951861.6 | R96: 2062391.5 | S96: 2151891.1 | T96: 2214886.1 | U96: 2242588.6 | V96: 2233158.4 | W96: 2289969.6 | X96: 2334645.6 | Y96: 2373886.6 | Z96: 2408043.2 | AA96: 2439903.1 | AB96: 2481357.1 | AC96: 2509539.4 | AD96: 2545294.7 | AE96: 2576841 | AF96: 2613551.6 | AG96: 2649420.1 | AH96: 2679620.5 | AI96: 2710564.2 | AJ96: 2742018.1 | AK96: 2781963.9 | AL96: 2814811.6 | AM96: 2847983 | AN96: 2881966.2 | AO96: 2916779.3 | AP96: 2952452.1 | AQ96: 2986572.8 | AR96: 3020716.9 | AS96: 3055122.6 | AT96: 3089613.2 | AU96: 3123961.7 | AV96: 3158106.4 | AW96: 3192351.2 | AX96: 3226595.4 | AY96: 3260764.3 | AZ96: 3294797.8 | BA96: 3328662 | BB96: 3362409.5 | BC96: 3396041.3 | BD96: 3429526.9
C97: Tasa de crecimiento real [%] | E97: 0.12486647 | F97: 0.11080576 | G97: -0.046834059 | H97: 0.16110175 | I97: 0.0044705632 | J97: 0.043670023 | K97: 0.15507153 | L97: 0.10050811 | M97: 0.10998398 | N97: 0.084750698 | O97: 0.080159142 | P97: 0.067517251 | Q97: -0.035184276 | R97: 0.05662796 | S97: 0.043396032 | T97: 0.02927424 | U97: 0.012507405 | V97: -0.0042050168 | W97: 0.025439841 | X97: 0.019509427 | Y97: 0.016808118 | Z97: 0.014388477 | AA97: 0.013230611 | AB97: 0.016990011 | AC97: 0.011357628 | AD97: 0.014247726 | AE97: 0.012393994 | AF97: 0.014246352 | AG97: 0.01372403 | AH97: 0.011398883 | AI97: 0.011547769 | AJ97: 0.011604191 | AK97: 0.014568051 | AL97: 0.011807372 | AM97: 0.011784572 | AN97: 0.011932401 | AO97: 0.012079626 | AP97: 0.01223021 | AQ97: 0.01155673 | AR97: 0.01143253 | AS97: 0.011389898 | AT97: 0.01128944 | AU97: 0.011117426 | AV97: 0.010929916 | AW97: 0.010843456 | AX97: 0.010726959 | AY97: 0.010589782 | AZ97: 0.010437273 | BA97: 0.010278073 | BB97: 0.010138459 | BC97: 0.010002289 | BD97: 0.0098601891
C99: Materia prima agrícola
C100: Valores reales totales [Miles USD 2021] | D100: 1498460.7 | E100: 1487939.6 | F100: 1630352.9 | G100: 1851563.2 | H100: 2113300.7 | I100: 2263283 | J100: 2478648.5 | K100: 2868643.6 | L100: 2639155.2 | M100: 2529143.7 | N100: 2614050.5 | O100: 2690698.2 | P100: 2768065.5 | Q100: 2850463.1 | R100: 2844808.2 | S100: 2899716.8 | T100: 2919902.5 | U100: 2927485.3 | V100: 2951387.2 | W100: 2929568.4 | X100: 2939015.1 | Y100: 2970749.8 | Z100: 2967167.6 | AA100: 2974782.4 | AB100: 2977087.9 | AC100: 2915140.6 | AD100: 2936396.4 | AE100: 2930565.4 | AF100: 2962383.8 | AG100: 2962625.2 | AH100: 2954167.8 | AI100: 2967776.5 | AJ100: 2975297.7 | AK100: 2984357.5 | AL100: 2988781.9 | AM100: 2994050.4 | AN100: 3002093.1 | AO100: 3009004.5 | AP100: 3015792 | AQ100: 3022118.8 | AR100: 3028830.8 | AS100: 3035835.2 | AT100: 3042629 | AU100: 3049398.9 | AV100: 3056165.1 | AW100: 3063020.3 | AX100: 3069904.4 | AY100: 3076763.9 | AZ100: 3083636.7 | BA100: 3090530.3 | BB100: 3097449.5 | BC100: 3104381.7 | BD100: 3111323.5
C101: Tasa de crecimiento real [%] | E101: -0.0070212934 | F101: 0.095711736 | G101: 0.13568252 | H101: 0.14136025 | I101: 0.070970649 | J101: 0.095156235 | K101: 0.15734183 | L101: -0.079998916 | M101: -0.041684377 | N101: 0.033571378 | O101: 0.029321435 | P101: 0.028753612 | Q101: 0.029767198 | R101: -0.0019838408 | S101: 0.019301328 | T101: 0.0069612799 | U101: 0.00259692 | V101: 0.0081646483 | W101: -0.0073927221 | X101: 0.0032246232 | Y101: 0.010797733 | Z101: -0.0012058346 | AA101: 0.0025663589 | AB101: 0.00077502034 | AC101: -0.020808017 | AD101: 0.0072915229 | AE101: -0.0019857817 | AF101: 0.010857418 | AG101: 8.1498581e-05 | AH101: -0.0028546986 | AI101: 0.0046066151 | AJ101: 0.0025342681 | AK101: 0.0030450202 | AL101: 0.0014825407 | AM101: 0.0017627491 | AN101: 0.0026862386 | AO101: 0.0023021633 | AP101: 0.0022557424 | AQ101: 0.0020978868 | AR101: 0.002220956 | AS101: 0.0023125974 | AT101: 0.0022378692 | AU101: 0.0022250104 | AV101: 0.002218864 | AW101: 0.0022430594 | AX101: 0.0022474801 | AY101: 0.0022344566 | AZ101: 0.0022337741 | BA101: 0.0022355268 | BB101: 0.0022388594 | BC101: 0.0022380194 | BD101: 0.0022361273

Sheet Calibración-BAU_Agricultura 
A1: Referencia | F1: Ecuador | G1: 2010 | H1: 2011 | I1: 2012 | J1: 2013 | K1: 2014 | L1: 2015 | M1: 2016 | N1: 2017 | O1: 2018 | P1: 2019 | Q1: 2020 | R1: 2021 | S1: 2022 | T1: 2023 | U1: 2024 | V1: 2025 | W1: 2026 | X1: 2027 | Y1: 2028 | Z1: 2029 | AA1: 2030 | AB1: 2031 | AC1: 2032 | AD1: 2033 | AE1: 2034 | AF1: 2035 | AG1: 2036 | AH1: 2037 | AI1: 2038 | AJ1: 2039 | AK1: 2040 | AL1: 2041 | AM1: 2042 | AN1: 2043 | AO1: 2044 | AP1: 2045 | AQ1: 2046 | AR1: 2047 | AS1: 2048 | AT1: 2049 | AU1: 2050 | AV1: 2051 | AW1: 2052 | AX1: 2053 | AY1: 2054 | AZ1: 2055 | BA1: 2056 | BB1: 2057 | BC1: 2058 | BD1: 2059 | BE1: 2060 | BF1: 2061 | BG1: 2062 | BH1: 2063 | BI1: 2064 | BJ1: 2065 | BK1: 2066 | BL1: 2067 | BM1: 2068 | BN1: 2069 | BO1: 2070
F3: COBERTURA DE CULTIVOS ESPAC
F6: TABLA AGR - 1: Cobertura de cultivos SEMBRADOS
F7: Cultivos en hectáreas [ha]
A8: ESPAC | F8: Banano [ha] | G8: 235773 | H8: 200110 | I8: 221775 | J8: 217874 | K8: 196673 | L8: 195533 | M8: 186222 | N8: 166972 | O8: 173706 | P8: 190381 | Q8: 165080 | R8: 167893 | S8: 172653 | T8: =T24*1000000 -> 171797.76 | U8: =U24*1000000 -> 182266.22 | V8: =V24*1000000 -> 182580.88 | W8: =W24*1000000 -> 193539.14 | X8: =X24*1000000 -> 198351.25 | Y8: =Y24*1000000 -> 199343.01 | Z8: =Z24*1000000 -> 200339.73 | AA8: =AA24*1000000 -> 201341.42 | ... BO8: =BO24*1000000 -> 245796.45
F9: Cacao - Almendra seca [ha] | G9: 470054 | H9: 521091 | I9: 507721 | J9: 508885 | K9: 487316 | L9: 537410 | M9: 559617 | N9: 573516 | O9: 573833 | P9: 601954 | Q9: 590579 | R9: 626962 | S9: 591556.81 | T9: =T25*1000000 -> 588626.52 | U9: =U25*1000000 -> 624494.34 | V9: =V25*1000000 -> 625572.45 | W9: =W25*1000000 -> 676380.86 | X9: =X25*1000000 -> 707062.2 | Y9: =Y25*1000000 -> 739489.33 | Z9: =Z25*1000000 -> 770887.55 | AA9: =AA25*1000000 -> 806113.49 | ... BO9: =BO25*1000000 -> 1292098.7
F10: Café - Grano Oro [ha] | G10: 191080 | H10: 122856 | I10: 113029 | J10: 97684 | K10: 70269 | L10: 79744 | M10: 55898 | N10: 52714 | O10: 45852 | P10: 48097 | Q10: 34789 | R10: 34931 | S10: 36397.649 | T10: =T26*1000000 -> 36217.353 | U10: =U26*1000000 -> 38424.249 | V10: =V26*1000000 -> 38490.583 | W10: =W26*1000000 -> 40800.738 | X10: =X26*1000000 -> 41815.198 | Y10: =Y26*1000000 -> 42875.409 | Z10: =Z26*1000000 -> 43819.48 | AA10: =AA26*1000000 -> 44923.358 | ... BO10: =BO26*1000000 -> 65218.505
F11: Caña de azucar [ha] | G11: 156530 | H11: 137829 | I11: 150448 | J11: 163476 | K11: 139467 | L11: 104557.78 | M11: 125587 | N11: 134950 | O11: 132771 | P11: 144116 | Q11: 157986 | R11: 151764 | S11: 141031 | T11: =T27*1000000 -> 140332.4 | U11: =U27*1000000 -> 148883.52 | V11: =V27*1000000 -> 149140.55 | W11: =W27*1000000 -> 158091.77 | X11: =X27*1000000 -> 158091.77 | Y11: =Y27*1000000 -> 158091.77 | Z11: =Z27*1000000 -> 158091.77 | AA11: =AA27*1000000 -> 158091.77 | ... BO11: =BO27*1000000 -> 158091.77
F12: Maíz [ha] | G12: 476148 | H12: 650105 | I12: 532003 | J12: 530612 | K12: 518393 | L12: 572123 | M12: 425737 | N12: 482482 | O12: 461547 | P12: 405259 | Q12: 444681 | R12: 453718 | S12: 433216 | T12: =T28*1000000 -> 431070.05 | U12: =U28*1000000 -> 457337.21 | V12: =V28*1000000 -> 458126.75 | W12: =W28*1000000 -> 485622.91 | X12: =X28*1000000 -> 497697.33 | Y12: =Y28*1000000 -> 510316.29 | Z12: =Z28*1000000 -> 521552.91 | AA12: =AA28*1000000 -> 534691.6 | ... BO12: =BO28*1000000 -> 776250.68
F13: Palma africana [ha] | G13: 248199 | H13: 244574 | I13: 240333 | J13: 288199 | K13: 387799 | L13: 369406 | M13: 319602 | N13: 313882 | O13: 267760 | P13: 246574 | Q13: 256854 | R13: 225575 | S13: 196082.3 | T13: =T29*1000000 -> 195111 | U13: =U29*1000000 -> 207000.04 | V13: =V29*1000000 -> 207357.4 | W13: =W29*1000000 -> 219802.72 | X13: =X29*1000000 -> 225267.85 | Y13: =Y29*1000000 -> 230979.44 | Z13: =Z29*1000000 -> 236065.37 | AA13: =AA29*1000000 -> 242012.2 | ... BO13: =BO29*1000000 -> 351346.71
D14: ! | F14: Soya - Grano seco [ha] | G14: 0 | H14: 0 | I14: 0 | J14: 0 | K14: 28290.798 | L14: 23277.033 | M14: 27322.836 | N14: 28542.581 | O14: 23358.381 | P14: 27960.008 | Q14: 20921.873 | R14: 18807.755 | S14: 22163.449 | T14: =T30*1000000 -> 22053.661 | U14: =U30*1000000 -> 23397.496 | V14: =V30*1000000 -> 23437.889 | W14: =W30*1000000 -> 24844.6 | X14: =X30*1000000 -> 25462.331 | Y14: =Y30*1000000 -> 26107.92 | Z14: =Z30*1000000 -> 26682.789 | AA14: =AA30*1000000 -> 27354.968 | ... BO14: =BO30*1000000 -> 39713.196
F15: Palmito [ha] | G15: 0 | H15: 0 | I15: 0 | J15: 0 | K15: 0 | L15: 11011.083 | M15: 6858.9587 | N15: 7691.3356 | O15: 6376.2151 | P15: 5242.5295 | Q15: 7438.9026 | R15: 4332.7007 | S15: 3957.5664 | T15: =T31*1000000 -> 3937.9625 | U15: =U31*1000000 -> 4177.9213 | V15: =V31*1000000 -> 4185.134 | W15: =W31*1000000 -> 4436.3202 | X15: =X31*1000000 -> 4546.6239 | Y15: =Y31*1000000 -> 4661.9021 | Z15: =Z31*1000000 -> 4764.5522 | AA15: =AA31*1000000 -> 4884.5784 | ... BO15: =BO31*1000000 -> 7091.2976
F16: Legumbres (Pulses) [ha] | G16: 118954 | H16: 153977 | I16: 113577 | J16: 94706 | K16: 81821 | L16: 79090 | M16: 62613 | N16: 73792 | O16: 45638 | P16: 47367 | Q16: 41949 | R16: 59410 | S16: 50866.618 | T16: =T32*1000000 -> 50614.649 | U16: =U32*1000000 -> 53698.841 | V16: =V32*1000000 -> 53791.545 | W16: =W32*1000000 -> 57020.043 | X16: =X32*1000000 -> 58437.776 | Y16: =Y32*1000000 -> 59919.447 | Z16: =Z32*1000000 -> 61238.811 | AA16: =AA32*1000000 -> 62781.507 | ... BO16: =BO32*1000000 -> 91144.479
F17: Cereales y pseudocereales[ha] | G17: 37898 | H17: 38441 | I17: 30415 | J17: 35697 | K17: 23299 | L17: 22364 | M17: 26372 | N17: 18065 | O17: 15675 | P17: 15810 | Q17: 23879 | R17: 19669 | S17: 13838.983 | T17: =T33*1000000 -> 13770.431 | U17: =U33*1000000 -> 14609.53 | V17: =V33*1000000 -> 14634.751 | W17: =W33*1000000 -> 15513.11 | X17: =X33*1000000 -> 15898.824 | Y17: =Y33*1000000 -> 16301.934 | Z17: =Z33*1000000 -> 16660.885 | AA17: =AA33*1000000 -> 17080.597 | ... BO17: =BO33*1000000 -> 24797.145
