Workbook
Name empty: #REF!
Name gwp.ch4: #REF!
Name gwp.n2o: #REF!

Sheet Detalles
B2: Laplantillaesunaguíapararecopilardatosnecesariosparalamodelación,nosedetallannecesariamentetodaslastecnologías.Incorporamosalgunasdeellasyescuestióndeagregarmáslíneasparacaracterizarcadatecnología.
B6: Puedendejarcomentariosenlasplantillasconformelasvanllenando,vamosaentrarperiódicamentearevisarycontestarcualquierinquitud.Tambiénpodemosagendarreunionesvirtualescuandosehayanacumuladovariaspreguntas.
B10: Enunaprimeraetapavamosamodelarhastalademandafinaldelossectores:residencial,comercial,industrial,agricultura,construcciónyotros.Altenerfuncionalelmodeloañadimosespecificidadacadasectoreincluimosusosfinales.
B14: Sialgunatecnologíanoseutilizaenelpaíspuedeneliminarlafila
B18: Sifaltaalgúntipodeinformaciónquecreanqueesimportantenosavisan.NosotrosvamosairtrabajandoenelRRSyconformeloarmemospuedenhabersolicitudesdeotrosdatos.
B23: ComentarioEquipoUSFQ:Cadaplantilla(excepto"CostosEnergía")poseeunacopialocalizadaalfinaldeldocumento.Lacopiaseutilizóparacolocar:(i)losvaloresenlasunidadesoficialesdelosreporteseinformes,(ii)comentariosrelevantes,y(iii)fuentesbibliográficas.Mientrasquelasplantillasoriginalesseutilizaronparatransformarlosvaloresalasunidadessolicitadasinicialmente.

Sheet Bitácora
A1: Persona que realizó el cambio | B1: Fecha | C1: Hoja del Cambio | D1: Descripción del Cambio
A2: Lissete Dávila | B2: 45075 | C2: Copia de Emisiones Energía | D2: Cambio de unidades de la celda C12 cambió de "Gg de contaminante/10^3 m3" a "Gg de contaminante/Mm^3"
C3: Emisiones Energía V2 | D3: Modificación de la celda D137 para tener un factor de conversión GgCO2/Mm^3 a MtonCO2/PJ. Esta modificación afectó las siguientes celdas:

Sheet Mejoras pendientes al modelo
A1: # | B1: Sector
A2: 1 | B2: Energía | C2: Mejorar la cadena de gas natural, desde importaciones hasta consumo. Considerando la componente de regasificación.

Sheet Combustibles
C1: Ecuador
D4: Combustibles fósiles
D5: Reservas probadas (puedeserunvalorparatodoelperiodo) | E5: 2018 | F5: 2019 | G5: 2020 | H5: 2021
A6: 1 | D6: Petróleo[PJ] | E6: ='Copia de Combustibles'!D6*$E$299*$E$305 -> 9490.5128 | F6: ='Copia de Combustibles'!E6*$E$299*$E$305 -> 7577.2906 | G6: ='Copia de Combustibles'!F6*$E$299*$E$305 -> 7780.8249 | H6: ='Copia de Combustibles'!G6*$E$299*$E$305 -> 7966.9133
A7: 1.2 | D7: Gas Natural [PJ] | E7: ='Copia de Combustibles'!D7*$E$302*$E$305 -> 162.95573 | F7: ='Copia de Combustibles'!E7*$E$302*$E$305 -> 151.75636 | G7: ='Copia de Combustibles'!F7*$E$302*$E$305 -> 137.36406 | H7: ='Copia de Combustibles'!G7*$E$302*$E$305 -> 146.63016
D8: Carbón [PJ]
D10: Total [PJ] | E10: =SUM(E6:E8) -> 9653.4686 | F10: =SUM(F6:F8) -> 7729.0469 | G10: =SUM(G6:G8) -> 7918.1889 | H10: =SUM(H6:H7) -> 8113.5435
D12: Potencial Hidrocarburifero (Petróleo) | E12: 2018 | F12: 2019 | G12: 2020 | H12: 2021
A13: 1 | D13: Reservas totales (3P) [PJ] | E13: ='Copia de Combustibles'!D13*$E$299*$E$305 -> 15672.14 | F13: ='Copia de Combustibles'!E13*$E$299*$E$305 -> 13020.379 | G13: ='Copia de Combustibles'!F13*$E$299*$E$305 -> 13125.054 | H13: ='Copia de Combustibles'!G13*$E$299*$E$305 -> 11985.262
A14: 1 | D14: Recursos contingentes (3C) [PJ] | E14: ='Copia de Combustibles'!D14*$E$299*$E$305 -> 8594.962 | F14: ='Copia de Combustibles'!E14*$E$299*$E$305 -> 9891.7661 | G14: ='Copia de Combustibles'!F14*$E$299*$E$305 -> 10258.128 | H14: ='Copia de Combustibles'!G14*$E$299*$E$305 -> 7100.4388
A15: 1 | D15: Recursos prospectivos [PJ] | E15: ='Copia de Combustibles'!D15*$E$299*$E$305 -> 4425.4168 | F15: ='Copia de Combustibles'!E15*$E$299*$E$305 -> 4483.5695 | G15: ='Copia de Combustibles'!F15*$E$299*$E$305 -> 4425.4168 | H15: ='Copia de Combustibles'!G15*$E$299*$E$305 -> 4855.7465
D17: Potencial Hidrocarburifero (Gas Natural) | E17: 2018 | F17: 2019 | G17: 2020 | H17: 2021
A18: 1,2 | D18: Reservas totales (3P) [PJ] | E18: ='Copia de Combustibles'!D18*$E$302*$E$305 -> 448.87338 | F18: ='Copia de Combustibles'!E18*$E$302*$E$305 -> 424.24835 | G18: ='Copia de Combustibles'!F18*$E$302*$E$305 -> 409.43911 | H18: ='Copia de Combustibles'!G18*$E$302*$E$305 -> 418.70423
A19: 1,2 | D19: Recursos contingentes (3C) [PJ] | E19: ='Copia de Combustibles'!D19*$E$302*$E$305 -> 0 | F19: ='Copia de Combustibles'!E19*$E$302*$E$305 -> 0 | G19: ='Copia de Combustibles'!F19*$E$302*$E$305 -> 0 | H19: ='Copia de Combustibles'!G19*$E$302*$E$305 -> 0
A20: 1,2 | D20: Recursos prospectivos [PJ] | E20: ='Copia de Combustibles'!D20*$E$302*$E$305 -> 0 | F20: ='Copia de Combustibles'!E20*$E$302*$E$305 -> 0 | G20: ='Copia de Combustibles'!F20*$E$302*$E$305 -> 0 | H20: ='Copia de Combustibles'!G20*$E$302*$E$305 -> 0
D22: Extracción anual | E22: 2018 | F22: 2019 | G22: 2020 | H22: 2021
A23: 1 | D23: Petróleo [PJ] | E23: ='Copia de Combustibles'!D23*$E$305 -> 1097.8784 | F23: ='Copia de Combustibles'!E23*$E$305 -> 1127.0919 | G23: ='Copia de Combustibles'!F23*$E$305 -> 1020.2949 | H23: ='Copia de Combustibles'!G23*$E$305 -> 1003.7065
A24: 1 | D24: Gas Natural [PJ] | E24: ='Copia de Combustibles'!D24*$E$305 -> 52.855462 | F24: ='Copia de Combustibles'!E24*$E$305 -> 50.385083 | G24: ='Copia de Combustibles'!F24*$E$305 -> 44.910759 | H24: ='Copia de Combustibles'!G24*$E$305 -> 45.345474
A25: 1 | D25: Carbón [PJ]
D27: Total [PJ] | E27: =SUM(E23:E24) -> 1150.7339 | F27: =SUM(F23:F24) -> 1177.477 | G27: =SUM(G23:G24) -> 1065.2056 | H27: =SUM(H23:H24) -> 1049.052
D29: **Pérdidas por extracción anual | E29: 2018 | F29: 2019 | G29: 2020 | H29: 2021
D30: Petróleo [PJ] Extrae + Importa - Entradas de refinación - Exportaciones | E30: =E23+E44+E57+E60+E65+E68-E145 -> -14.297741 | F30: =F23+F44+F57+F60+F65+F68-F145 -> 4.3826104 | G30: =G23+G44+G57+G60+G65+G68-G145 -> 17.123449 | H30: =H23+H44+H57+H60+H65+H68-H145 -> -9.9901907
D31: Gas Natural [PJ] | E31: =E24+E61+E69+E124+E125-E255 -> 20.964402 | F31: =F24+F61+F69+F124+F125-F255 -> 21.180982 | G31: =G24+G61+G69+G124+G125-G255 -> 18.895591 | H31: =H24+H61+H69+H124+H125-H255 -> 18.46924
D32: Carbón [PJ] | E32: =E61+E69+E124+E125 -> -12.015221
D34: Total [PJ] | E34: =SUM(E30:E31) -> 6.6666616 | F34: =SUM(F30:F31) -> 25.563592 | G34: =SUM(G30:G31) -> 36.01904 | H34: =SUM(H30:H31) -> 8.4790493
D36: InputActivityRatio Extracción | E36: 2018 | F36: 2019 | G36: 2020 | H36: 2021 | I36: 2022-2070
D37: Petróleo [PJ] | E37: =(E23-E30)/E23 -> 1.0130231 | F37: =(F23-F30)/F23 -> 0.99611158 | G37: =(G23-G30)/G23 -> 0.98321716 | H37: =(H23-H30)/H23 -> 1.0099533 | I37: =AVERAGE(E37:H37) -> 1.0005763
D38: Gas Natural [PJ] | E38: =(E24)/(E24-E31) -> 1.6573755 | F38: =(F24)/(F24-F31) -> 1.7252742 | G38: =(G24)/(G24-G31) -> 1.7263298 | H38: =(H24)/(H24-H31) -> 1.687196 | I38: =AVERAGE(E38:H38) -> 1.6990439
D40: No aprovechado | E40: 2018 | F40: 2019 | G40: 2020 | H40: 2021
A41: 1 | D41: Gas Natural [PJ] | E41: ='Copia de Combustibles'!D39*$E$305 -> 25.245742 | F41: ='Copia de Combustibles'!E39*$E$305 -> 25.73117 | G41: ='Copia de Combustibles'!F39*$E$305 -> 23.967719 | H41: ='Copia de Combustibles'!G39*$E$305 -> 23.255254
I42: * Esto no se introduce directamente al modelo, se usa para corroborar el comportamiento
D43: Importación | E43: 2018 | F43: 2019 | G43: 2020 | H43: 2021 | I43: 2022 | J43: 2023 | K43: 2024 | L43: 2025 | M43: 2026 | N43: 2027 | O43: 2028 | P43: 2029 | Q43: 2030 | R43: 2031 | S43: 2032 | T43: 2033 | U43: 2034 | V43: 2035 | W43: 2036 | X43: 2037 | Y43: 2038 | Z43: 2039 | AA43: 2040 | AB43: 2041 | AC43: 2042 | AD43: 2043 | AE43: 2044 | AF43: 2045 | AG43: 2046 | AH43: 2047 | AI43: 2048 | AJ43: 2049 | AK43: 2050 | AL43: 2051 | AM43: 2052 | AN43: 2053 | AO43: 2054 | AP43: 2055 | AQ43: 2056 | AR43: 2057 | AS43: 2058 | AT43: 2059 | AU43: 2060 | AV43: 2061 | AW43: 2062 | AX43: 2063 | AY43: 2064 | AZ43: 2065 | BA43: 2066 | BB43: 2067 | BC43: 2068 | BD43: 2069 | BE43: 2070
D44: Petróleo crudo [PJ] | I44: 0 | J44: 0 | K44: 0 | L44: 0 | M44: 0 | N44: 0 | O44: 0 | P44: 0 | Q44: 107.34 | R44: 152.09 | S44: 188.59 | T44: 232.28 | U44: 273.43 | V44: 345.84 | W44: 379.09 | X44: 379.09 | Y44: 379.11 | Z44: 379.11 | AA44: 379.11 | AB44: 379.11 | AC44: 379.11 | AD44: 379.11 | AE44: 379.11 | AF44: 379.11 | AG44: 379.11 | AH44: 379.11 | AI44: 379.11 | AJ44: 379.11 | AK44: 379.11 | AL44: 379.11 | AM44: 379.11 | AN44: 379.11 | AO44: 379.11 | AP44: 379.11 | AQ44: 379.11 | AR44: 379.11 | AS44: 379.11 | AT44: 379.11 | AU44: 379.11 | AV44: 379.11 | AW44: 379.11 | AX44: 379.11 | AY44: 379.11 | AZ44: 379.11 | BA44: 379.11 | BB44: 379.11 | BC44: 379.11 | BD44: 379.11 | BE44: 379.11
A45: 1 | D45: Diésel oil [PJ] | E45: ='Copia de Combustibles'!D43*$E$305 -> 117.76053 | F45: ='Copia de Combustibles'!E43*$E$305 -> 124.42923 | G45: ='Copia de Combustibles'!F43*$E$305 -> 108.25918 | H45: ='Copia de Combustibles'!G43*$E$305 -> 136.77356 | I45: 134.39 | J45: 144.65 | K45: 143.02 | L45: 152.84 | M45: 150.89 | N45: 161.29 | O45: 160.73 | P45: 169.45 | Q45: 168.68 | R45: 178.69 | S45: 178.77 | T45: 188.05 | U45: 188.69 | V45: 196.72 | W45: 198.44 | X45: 206.04 | Y45: 208.02 | Z45: 215.95 | AA45: 218.4 | AB45: 225.69 | AC45: 228.62 | AD45: 234.58 | AE45: 237.94 | AF45: 244.03 | AG45: 248.09 | AH45: 254.09 | AI45: 257.36 | AJ45: 263.26 | AK45: 266.93 | AL45: 272.14 | AM45: 277.64 | AN45: 282.91 | AO45: 288.46 | AP45: 293.94 | AQ45: 299.64 | AR45: 305.27 | AS45: 311.07 | AT45: 316.86 | AU45: 322.91 | AV45: 328.95 | AW45: 335.26 | AX45: 341.67 | AY45: 348.19 | AZ45: 354.84 | BA45: 361.59 | BB45: 368.46 | BC45: 375.46 | BD45: 382.59 | BE45: 389.86
A46: 1 | D46: Gasolina [PJ] | E46: ='Copia de Combustibles'!D44*$E$305 -> 91.607975 | F46: ='Copia de Combustibles'!E44*$E$305 -> 105.93169 | G46: ='Copia de Combustibles'!F44*$E$305 -> 78.997084 | H46: ='Copia de Combustibles'!G44*$E$305 -> 93.045175 | I46: 90.01 | J46: 114.02 | K46: 78.1 | L46: 99.44 | M46: 88.86 | N46: 121.88 | O46: 77.83 | P46: 104.83 | Q46: 88.46 | R46: 129.11 | S46: 77.87 | T46: 110.28 | U46: 88.76 | V46: 134.61 | W46: 78.55 | X46: 114.5 | Y46: 89.62 | Z46: 139.73 | AA46: 79.44 | AB46: 118.32 | AC46: 90.78 | AD46: 143.38 | AE46: 80.58 | AF46: 121.35 | AG46: 92.29 | AH46: 146.84 | AI46: 81.61 | AJ46: 124.13 | AK46: 93.58 | AL46: 149.71 | AM46: 83.26 | AN46: 126.49 | AO46: 95.41 | AP46: 152.55 | AQ46: 84.88 | AR46: 128.87 | AS46: 97.22 | AT46: 155.39 | AU46: 86.5 | AV46: 131.28 | AW46: 99.09 | AX46: 158.36 | AY46: 88.15 | AZ46: 133.79 | BA46: 100.97 | BB46: 161.36 | BC46: 89.82 | BD46: 136.33 | BE46: 102.89
A47: 1 | D47: GLP [PJ] | E47: ='Copia de Combustibles'!D45*$E$305 -> 43.389807 | F47: ='Copia de Combustibles'!E45*$E$305 -> 47.274512 | G47: ='Copia de Combustibles'!F45*$E$305 -> 48.313115 | H47: ='Copia de Combustibles'!G45*$E$305 -> 49.878195 | I47: 50.85 | J47: 51.85 | K47: 52.88 | L47: 53.86 | M47: 54.75 | N47: 55.89 | O47: 56.91 | P47: 57.87 | Q47: 58.81 | R47: 60.03 | S47: 61.02 | T47: 62.2 | U47: 63.19 | V47: 64.24 | W47: 65.3 | X47: 66.33 | Y47: 67.34 | Z47: 68.42 | AA47: 69.41 | AB47: 70.42 | AC47: 71.4 | AD47: 72.25 | AE47: 73.21 | AF47: 74.07 | AG47: 75.05 | AH47: 75.91 | AI47: 76.74 | AJ47: 77.58 | AK47: 78.41 | AL47: 79.32 | AM47: 80.12 | AN47: 80.89 | AO47: 81.68 | AP47: 82.46 | AQ47: 83.24 | AR47: 83.96 | AS47: 84.68 | AT47: 85.38 | AU47: 86.05 | AV47: 86.7 | AW47: 87.33 | AX47: 87.93 | AY47: 88.52 | AZ47: 89.08 | BA47: 89.62 | BB47: 90.13 | BC47: 90.61 | BD47: 91.07 | BE47: 91.49
A48: 1 | D48: Fuel oil [PJ] | E48: ='Copia de Combustibles'!D46*$E$305 -> 24.078346 | F48: ='Copia de Combustibles'!E46*$E$305 -> 25.523332 | G48: ='Copia de Combustibles'!F46*$E$305 -> 17.832535 | H48: ='Copia de Combustibles'!G46*$E$305 -> 13.861503 | I48: 14.39 | J48: 14.7 | K48: 15.28 | L48: 15.54 | M48: 16.03 | N48: 16.38 | O48: 16.98 | P48: 17.18 | Q48: 17.71 | R48: 18.12 | S48: 18.68 | T48: 19.07 | U48: 19.63 | V48: 19.96 | W48: 20.56 | X48: 20.9 | Y48: 21.47 | Z48: 21.9 | AA48: 22.46 | AB48: 22.87 | AC48: 23.43 | AD48: 23.75 | AE48: 24.31 | AF48: 24.68 | AG48: 25.27 | AH48: 25.66 | AI48: 26.15 | AJ48: 26.55 | AK48: 27.05 | AL48: 27.57 | AM48: 28.09 | AN48: 28.62 | AO48: 29.14 | AP48: 29.69 | AQ48: 30.24 | AR48: 30.8 | AS48: 31.36 | AT48: 31.93 | AU48: 32.52 | AV48: 33.12 | AW48: 33.74 | AX48: 34.36 | AY48: 35 | AZ48: 35.65 | BA48: 36.31 | BB48: 36.98 | BC48: 37.66 | BD48: 38.36 | BE48: 39.07
A49: 1 | D49: Jet Fuel [PJ] | G49: ='Copia de Combustibles'!F47*$E$305 -> 0.93795161 | I49: 1 | J49: 1.04 | K49: 1.07 | L49: 1.1 | M49: 1.12 | N49: 1.16 | O49: 1.19 | P49: 1.21 | Q49: 1.24 | R49: 1.28 | S49: 1.31 | T49: 1.35 | U49: 1.38 | V49: 1.42 | W49: 1.45 | X49: 1.49 | Y49: 1.52 | Z49: 1.56 | AA49: 1.6 | AB49: 1.63 | AC49: 1.67 | AD49: 1.7 | AE49: 1.73 | AF49: 1.77 | AG49: 1.81 | AH49: 1.84 | AI49: 1.87 | AJ49: 1.91 | AK49: 1.94 | AL49: 1.98 | AM49: 2.02 | AN49: 2.05 | AO49: 2.09 | AP49: 2.13 | AQ49: 2.16 | AR49: 2.2 | AS49: 2.24 | AT49: 2.28 | AU49: 2.31 | AV49: 2.35 | AW49: 2.39 | AX49: 2.43 | AY49: 2.47 | AZ49: 2.51 | BA49: 2.54 | BB49: 2.58 | BC49: 2.62 | BD49: 2.66 | BE49: 2.7
A50: 1 | D50: Coque de Petróleo [PJ] | E50: ='Copia de Combustibles'!D48*$E$305 -> 5.5666818 | F50: ='Copia de Combustibles'!E48*$E$305 -> 4.4513001 | G50: ='Copia de Combustibles'!F48*$E$305 -> 5.1349055 | H50: ='Copia de Combustibles'!G48*$E$305 -> 5.6722964 | I50: 6.17 | J50: 5.99 | K50: 6.63 | L50: 6.37 | M50: 7.03 | N50: 6.78 | O50: 7.5 | P50: 7.19 | Q50: 7.85 | R50: 7.65 | S50: 8.27 | T50: 8.11 | U50: 8.68 | V50: 8.54 | W50: 9.08 | X50: 8.99 | Y50: 9.47 | Z50: 9.46 | AA50: 9.91 | AB50: 9.93 | AC50: 10.34 | AD50: 10.35 | AE50: 10.74 | AF50: 10.79 | AG50: 11.18 | AH50: 11.26 | AI50: 11.57 | AJ50: 11.68 | AK50: 11.99 | AL50: 12.25 | AM50: 12.49 | AN50: 12.76 | AO50: 13 | AP50: 13.28 | AQ50: 13.53 | AR50: 13.82 | AS50: 14.09 | AT50: 14.38 | AU50: 14.66 | AV50: 14.97 | AW50: 15.28 | AX50: 15.59 | AY50: 15.9 | AZ50: 16.22 | BA50: 16.55 | BB50: 16.89 | BC50: 17.23 | BD50: 17.58 | BE50: 17.94
D52: Total [PJ] | E52: =SUM(E44:E50) -> 282.40334 | F52: =SUM(F44:F50) -> 307.61006 | G52: =SUM(G44:G50) -> 259.47477 | H52: =SUM(H44:H50) -> 299.23073 | I52: =SUM(I44:I50) -> 296.81 | J52: =SUM(J44:J50) -> 332.25 | K52: =SUM(K44:K50) -> 296.98 | L52: =SUM(L44:L50) -> 329.15 | ... BE52: =SUM(BE44:BE50) -> 1023.06
D54: Refinación anual (Entradas) | E54: 2018 | F54: 2019 | G54: 2020 | H54: 2021
D56: REFINERÍA ESMERALDAS
A57: 1 | D57: Petróleo [PJ] | E57: ='Copia de Combustibles'!D55*$E$305 -> -205.8151 | F57: ='Copia de Combustibles'!E55*$E$305 -> -186.99043 | G57: ='Copia de Combustibles'!F55*$E$305 -> -152.82313 | H57: ='Copia de Combustibles'!G55*$E$305 -> -191.32602
D59: REFINERÍA LA LIBERTAD
A60: 1 | D60: Petróleo [PJ] | E60: ='Copia de Combustibles'!D58*$E$305 -> -90.48273 | F60: ='Copia de Combustibles'!E58*$E$305 -> -78.871773 | G60: ='Copia de Combustibles'!F58*$E$305 -> -60.866776 | H60: ='Copia de Combustibles'!G58*$E$305 -> -78.600637
A61: 1 | D61: Líquidos de gas natural [PJ] | E61: ='Copia de Combustibles'!D59*$E$305 -> -0.0098878395 | F61: ='Copia de Combustibles'!E59*$E$305 -> -0.0095444979 | G61: ='Copia de Combustibles'!F59*$E$305 -> 0 | H61: ='Copia de Combustibles'!G59*$E$305 -> -0.015734418
D62: Total | E62: =SUM(E60:E61) -> -90.492617 | F62: =SUM(F60:F61) -> -78.881318 | G62: =SUM(G60:G61) -> -60.866776 | H62: =SUM(H60:H61) -> -78.616371
D64: REFINERÍA SHUSHUFINDI
A65: 1 | D65: Petróleo [PJ] | E65: ='Copia de Combustibles'!D62*$E$305 -> -41.73416 | F65: ='Copia de Combustibles'!E62*$E$305 -> -39.021069 | G65: ='Copia de Combustibles'!F62*$E$305 -> -34.962444 | H65: ='Copia de Combustibles'!G62*$E$305 -> -41.014581
D67: OTRAS REFINERÍAS
A68: 1 | D68: Petróleo [PJ] | E68: ='Copia de Combustibles'!D65*$E$305 -> -20.224117 | F68: ='Copia de Combustibles'!E65*$E$305 -> -20.856188 | G68: ='Copia de Combustibles'!F65*$E$305 -> -19.223275 | H68: ='Copia de Combustibles'!G65*$E$305 -> -19.772461
A69: 1 | D69: Líquidos de gas natural [PJ] | E69: ='Copia de Combustibles'!D66*$E$305 -> -0.65793673 | F69: ='Copia de Combustibles'!E66*$E$305 -> -0.7015951 | G69: ='Copia de Combustibles'!F66*$E$305 -> -0.61250611 | H69: ='Copia de Combustibles'!G66*$E$305 -> -0.5844326
D70: Total | E70: =SUM(E68:E69) -> -20.882054 | F70: =SUM(F68:F69) -> -21.557784 | G70: =SUM(G68:G69) -> -19.835781 | H70: =SUM(H68:H69) -> -20.356893
D72: TOTAL ENTRADAS A REFINACIÓN | E72: =SUM(E57,E62,E65,E70) -> -358.92393 | F72: =SUM(F57,F62,F65,F70) -> -326.4506 | G72: =SUM(G57,G62,G65,G70) -> -268.48813 | H72: =SUM(H57,H62,H65,H70) -> -331.31387
D74: Refinación anual (Producción)
D76: REFINERÍA ESMERALDAS | E76: 2018 | F76: 2019 | G76: 2020 | H76: 2021
A77: 1 | D77: Diésel oil [PJ] | E77: ='Copia de Combustibles'!D71*$E$305 -> 46.266364 | F77: ='Copia de Combustibles'!E71*$E$305 -> 45.714525 | G77: ='Copia de Combustibles'!F71*$E$305 -> 30.879314 | H77: ='Copia de Combustibles'!G71*$E$305 -> 40.823367
A78: 1 | D78: Gasolina [PJ] | E78: ='Copia de Combustibles'!D72*$E$305 -> 47.548201 | F78: ='Copia de Combustibles'!E72*$E$305 -> 44.109717 | G78: ='Copia de Combustibles'!F72*$E$305 -> 33.169012 | H78: ='Copia de Combustibles'!G72*$E$305 -> 37.888687
A79: 1 | D79: GLP [PJ] | E79: ='Copia de Combustibles'!D73*$E$305 -> 5.7008131 | F79: ='Copia de Combustibles'!E73*$E$305 -> 3.2676672 | G79: ='Copia de Combustibles'!F73*$E$305 -> 3.8438972 | H79: ='Copia de Combustibles'!G73*$E$305 -> 3.9998097
A80: 1 | D80: Fuel oil [PJ] | E80: ='Copia de Combustibles'!D74*$E$305 -> 79.093466 | F80: ='Copia de Combustibles'!E74*$E$305 -> 55.548866 | G80: ='Copia de Combustibles'!F74*$E$305 -> 59.806509 | H80: ='Copia de Combustibles'!G74*$E$305 -> 77.999642
A81: 1 | D81: Jet Fuel [PJ] | E81: ='Copia de Combustibles'!D75*$E$305 -> 13.142442 | F81: ='Copia de Combustibles'!E75*$E$305 -> 12.939706 | G81: ='Copia de Combustibles'!F75*$E$305 -> 7.772674 | H81: ='Copia de Combustibles'!G75*$E$305 -> 11.317184
A82: 1 | D82: Gases de refinería [PJ] | E82: ='Copia de Combustibles'!D76*$E$305 -> 2.3406026 | F82: ='Copia de Combustibles'!E76*$E$305 -> 2.2529304 | G82: ='Copia de Combustibles'!F76*$E$305 -> 1.8116965 | H82: ='Copia de Combustibles'!G76*$E$305 -> 2.0050209
A83: 1 | D83: No energético [PJ] | E83: ='Copia de Combustibles'!D77*$E$305 -> 7.9542969 | F83: ='Copia de Combustibles'!E77*$E$305 -> 7.6952091 | G83: ='Copia de Combustibles'!F77*$E$305 -> 5.7891404 | H83: ='Copia de Combustibles'!G77*$E$305 -> 6.9855604
D84: Total | E84: =SUM(E77:E83) -> 202.04619 | F84: =SUM(F77:F83) -> 171.52862 | G84: =SUM(G77:G83) -> 143.07224 | H84: =SUM(H77:H83) -> 181.01927
D86: REFINERÍA LA LIBERTAD | E86: 2018 | F86: 2019 | G86: 2020 | H86: 2021
A87: 1 | D87: Diésel oil [PJ] | E87: ='Copia de Combustibles'!D80*$E$305 -> 16.283951 | F87: ='Copia de Combustibles'!E80*$E$305 -> 13.587256 | G87: ='Copia de Combustibles'!F80*$E$305 -> 11.561992 | H87: ='Copia de Combustibles'!G80*$E$305 -> 14.675241
A88: 1 | D88: Gasolina [PJ] | E88: ='Copia de Combustibles'!D81*$E$305 -> 11.706538 | F88: ='Copia de Combustibles'!E81*$E$305 -> 10.172931 | G88: ='Copia de Combustibles'!F81*$E$305 -> 7.274616 | H88: ='Copia de Combustibles'!G81*$E$305 -> 9.6491394
A89: 1 | D89: GLP [PJ] | E89: ='Copia de Combustibles'!D82*$E$305 -> 0.10132428 | F89: ='Copia de Combustibles'!E82*$E$305 -> 0.081076044 | G89: ='Copia de Combustibles'!F82*$E$305 -> 0.020339165 | H89: ='Copia de Combustibles'!G82*$E$305 -> 0.010252869
A90: 1 | D90: Fuel oil [PJ] | E90: ='Copia de Combustibles'!D83*$E$305 -> 56.454918 | F90: ='Copia de Combustibles'!E83*$E$305 -> 49.836777 | G90: ='Copia de Combustibles'!F83*$E$305 -> 39.399964 | H90: ='Copia de Combustibles'!G83*$E$305 -> 50.68529
A91: 1 | D91: Jet Fuel [PJ] | E91: ='Copia de Combustibles'!D84*$E$305 -> 3.2373557 | F91: ='Copia de Combustibles'!E84*$E$305 -> 3.1136653 | G91: ='Copia de Combustibles'!F84*$E$305 -> 0.78196823 | H91: ='Copia de Combustibles'!G84*$E$305 -> 1.0520081
A92: 1 | D92: No energético [PJ] | E92: ='Copia de Combustibles'!D85*$E$305 -> 1.0072327 | F92: ='Copia de Combustibles'!E85*$E$305 -> 0.87958748 | G92: ='Copia de Combustibles'!F85*$E$305 -> 0.83409918 | H92: ='Copia de Combustibles'!G85*$E$305 -> 0.98419035
D93: Total | E93: =SUM(E87:E92) -> 88.791321 | F93: =SUM(F87:F92) -> 77.671293 | G93: =SUM(G87:G92) -> 59.872978 | H93: =SUM(H87:H92) -> 77.056122
D95: REFINERÍA SHUSHUFINDI | E95: 2018 | F95: 2019 | G95: 2020 | H95: 2021
A96: 1 | D96: Diésel oil [PJ] | E96: ='Copia de Combustibles'!D88*$E$305 -> 12.229114 | F96: ='Copia de Combustibles'!E88*$E$305 -> 11.932752 | G96: ='Copia de Combustibles'!F88*$E$305 -> 10.411496 | H96: ='Copia de Combustibles'!G88*$E$305 -> 13.295669
A97: 1 | D97: Gasolina [PJ] | E97: ='Copia de Combustibles'!D89*$E$305 -> 6.086923 | F97: ='Copia de Combustibles'!E89*$E$305 -> 5.8355775 | G97: ='Copia de Combustibles'!F89*$E$305 -> 5.5567405 | H97: ='Copia de Combustibles'!G89*$E$305 -> 5.4551051
A98: 1 | D98: GLP [PJ]
A99: 1 | D99: Fuel oil [PJ] | E99: ='Copia de Combustibles'!D91*$E$305 -> 2.1804689 | F99: ='Copia de Combustibles'!E91*$E$305 -> 1.4047431 | G99: ='Copia de Combustibles'!F91*$E$305 -> 1.3323435 | H99: ='Copia de Combustibles'!G91*$E$305 -> 1.6630184
A100: 1 | D100: Jet Fuel [PJ] | F100: ='Copia de Combustibles'!E92*$E$305 -> 0.085135657
A101: 1 | D101: Crudo reducido [PJ] | E101: ='Copia de Combustibles'!D93*$E$305 -> 20.381725 | F101: ='Copia de Combustibles'!E93*$E$305 -> 18.849829 | G101: ='Copia de Combustibles'!F93*$E$305 -> 17.056602 | H101: ='Copia de Combustibles'!G93*$E$305 -> 19.738008
D102: Total | E102: =SUM(E96:E101) -> 40.87823 | F102: =SUM(F96:F101) -> 38.108038 | G102: =SUM(G96:G101) -> 34.357182 | H102: =SUM(H96:H101) -> 40.151801
D104: OTRAS REFINERÍAS | E104: 2018 | F104: 2019 | G104: 2020 | H104: 2021
A105: 1 | D105: Diésel oil [PJ] | E105: ='Copia de Combustibles'!D96*$E$305 -> 4.4931343 | F105: ='Copia de Combustibles'!E96*$E$305 -> 4.600433 | G105: ='Copia de Combustibles'!F96*$E$305 -> 4.2077092 | H105: ='Copia de Combustibles'!G96*$E$305 -> 4.3458946
A106: 1 | D106: Gasolina [PJ] | E106: ='Copia de Combustibles'!D97*$E$305 -> 0.66375276 | F106: ='Copia de Combustibles'!E97*$E$305 -> 0.69664853 | G106: ='Copia de Combustibles'!F97*$E$305 -> 0.62576886 | H106: ='Copia de Combustibles'!G97*$E$305 -> 0.85512479
A107: 1 | D107: GLP [PJ] | E107: ='Copia de Combustibles'!D98*$E$305 -> 0.77798109 | F107: ='Copia de Combustibles'!E98*$E$305 -> 0.63579094 | G107: ='Copia de Combustibles'!F98*$E$305 -> 0.66004166 | H107: ='Copia de Combustibles'!G98*$E$305 -> 0.62190974
A108: 1 | D108: Fuel oil [PJ]
A109: 1 | D109: Jet Fuel [PJ] | E109: ='Copia de Combustibles'!D100*$E$305 -> 0.12442048 | F109: ='Copia de Combustibles'!E100*$E$305 -> 0.14258381 | G109: ='Copia de Combustibles'!F100*$E$305 -> 0.129701 | H109: ='Copia de Combustibles'!G100*$E$305 -> 0.14019567
A110: 1 | D110: Crudo reducido [PJ] | E110: ='Copia de Combustibles'!D101*$E$305 -> 14.60424 | F110: ='Copia de Combustibles'!E101*$E$305 -> 15.154857 | G110: ='Copia de Combustibles'!F101*$E$305 -> 14.178259 | H110: ='Copia de Combustibles'!G101*$E$305 -> 14.464054
A111: 1 | D111: Gases de refinería [PJ] | E111: ='Copia de Combustibles'!D102*$E$305 -> 0.056913783 | F111: ='Copia de Combustibles'!E102*$E$305 -> 0.054948154 | G111: ='Copia de Combustibles'!F102*$E$305 -> 0.038947488 | H111: ='Copia de Combustibles'!G102*$E$305 -> 0.041105793
D112: Total | E112: =SUM(E105:E111) -> 20.720443 | F112: =SUM(F105:F111) -> 21.285261 | G112: =SUM(G105:G111) -> 19.840427 | H112: =SUM(H105:H111) -> 20.468285
D116: InputActivityRatio | E116: 2018 | F116: 2019 | G116: 2020 | H116: 2021 | I116: 2022-2070
D117: Esmeraldas | E117: =ABS(E57/E84) -> 1.0186537 | F117: =ABS(F57/F84) -> 1.0901413 | G117: =ABS(G57/G84) -> 1.0681536 | H117: =ABS(H57/H84) -> 1.0569373 | I117: =AVERAGE(E117:H117) -> 1.0584715
D118: La Libertad | E118: =ABS(E62/E93) -> 1.0191606 | F118: =ABS(F62/F93) -> 1.0155788 | G118: =ABS(G62/G93) -> 1.0165984 | H118: =ABS(H62/H93) -> 1.0202482 | I118: =AVERAGE(E118:H118) -> 1.0178965
D119: Shushufindi | E119: =ABS(E65/E102) -> 1.0209385 | F119: =ABS(F65/F102) -> 1.023959 | G119: =ABS(G65/G102) -> 1.0176168 | H119: =ABS(H65/H102) -> 1.021488 | I119: =AVERAGE(E119:H119) -> 1.0210006
D120: Otras refinerías | E120: =ABS(E70/E112) -> 1.0077996 | F120: =ABS(F70/F112) -> 1.0128033 | G120: =ABS(G70/G112) -> 0.99976583 | H120: =ABS(H70/H112) -> 0.99455784 | I120: =AVERAGE(E120:H120) -> 1.0037316
D121: Promedio | E121: =ROUND(AVERAGE(E117:E119),4) -> 1.0196 | F121: =ROUND(AVERAGE(F117:F119),4) -> 1.0432 | G121: =ROUND(AVERAGE(G117:G119),4) -> 1.0341 | H121: =ROUND(AVERAGE(H117:H119),4) -> 1.0329 | I121: =AVERAGE(E121:H121) -> 1.03245
D123: Centros de gas (Entradas) | E123: 2018 | F123: 2019 | G123: 2020 | H123: 2021
A124: 1 | D124: Líquidos de gas natural [PJ] | E124: ='Copia de Combustibles'!D117*$E$305 -> -5.6001653 | F124: ='Copia de Combustibles'!E117*$E$305 -> -5.4410257 | G124: ='Copia de Combustibles'!F117*$E$305 -> -5.4222713 | H124: ='Copia de Combustibles'!G117*$E$305 -> -5.8635981
A125: 1 | D125: Gas natural [PJ] | E125: ='Copia de Combustibles'!D118*$E$305 -> -5.7472313 | F125: ='Copia de Combustibles'!E118*$E$305 -> -5.2896828 | G125: ='Copia de Combustibles'!F118*$E$305 -> -4.6394715 | H125: ='Copia de Combustibles'!G118*$E$305 -> -5.1296152
D127: Total [PJ] | E127: =SUM(E124:E125) -> -11.347397 | F127: =SUM(F124:F125) -> -10.730708 | G127: =SUM(G124:G125) -> -10.061743 | H127: =SUM(H124:H125) -> -10.993213
D129: Centros de gas (Salidas) | E129: 2018 | F129: 2019 | G129: 2020 | H129: 2021
...

Sheet Electricidad
B1: Ecuador
D4: Generación eléctrica
D5: Capacidad instalada (SNI) [GW] | E5: 2018 | F5: 2019 | G5: 2020 | H5: 2021
D6: Biomasa | E6: ='Copia de Electricidad'!D7/1000 -> 0.1443 | F6: ='Copia de Electricidad'!E7/1000 -> 0.1443 | G6: ='Copia de Electricidad'!F7/1000 -> 0.1443 | H6: ='Copia de Electricidad'!G7/1000 -> 0.1443
D7: Turbovapor
C8: PP_SUG | D8: Bagazo de caña | E8: ='Copia de Electricidad'!D9/1000 -> 0.1443 | F8: ='Copia de Electricidad'!E9/1000 -> 0.1443 | G8: ='Copia de Electricidad'!F9/1000 -> 0.1443 | H8: ='Copia de Electricidad'!G9/1000 -> 0.1443
C9: PP_WND_US | D9: Eólica | E9: ='Copia de Electricidad'!D10/1000 -> 0.0165 | F9: ='Copia de Electricidad'!E10/1000 -> 0.0165 | G9: ='Copia de Electricidad'!F10/1000 -> 0.0165 | H9: ='Copia de Electricidad'!G10/1000 -> 0.0165
D10: Hidraúlica | E10: ='Copia de Electricidad'!D11/1000 -> 5.060344 | F10: ='Copia de Electricidad'!E11/1000 -> 5.070344 | G10: ='Copia de Electricidad'!F11/1000 -> 5.092686 | H10: ='Copia de Electricidad'!G11/1000 -> 5.100786
D11: Embalse | E11: ='Copia de Electricidad'!D12/1000 -> 1.7332 | F11: ='Copia de Electricidad'!E12/1000 -> 1.7332 | G11: ='Copia de Electricidad'!F12/1000 -> 1.7332 | H11: ='Copia de Electricidad'!G12/1000 -> 1.7332
D12: Amazonas | E12: ='Copia de Electricidad'!D13/1000 -> 1.478 | F12: ='Copia de Electricidad'!E13/1000 -> 1.478 | G12: ='Copia de Electricidad'!F13/1000 -> 1.478 | H12: ='Copia de Electricidad'!G13/1000 -> 1.478
D13: Pacífico | E13: ='Copia de Electricidad'!D14/1000 -> 0.2552 | F13: ='Copia de Electricidad'!E14/1000 -> 0.2552 | G13: ='Copia de Electricidad'!F14/1000 -> 0.2552 | H13: ='Copia de Electricidad'!G14/1000 -> 0.2552
D14: Pasada | E14: ='Copia de Electricidad'!D15/1000 -> 3.327144 | F14: ='Copia de Electricidad'!E15/1000 -> 3.337144 | G14: ='Copia de Electricidad'!F15/1000 -> 3.359486 | H14: ='Copia de Electricidad'!G15/1000 -> 3.367586
D15: Amazonas | E15: ='Copia de Electricidad'!D16/1000 -> 2.93939 | F15: ='Copia de Electricidad'!E16/1000 -> 2.94939 | G15: ='Copia de Electricidad'!F16/1000 -> 2.961586 | H15: ='Copia de Electricidad'!G16/1000 -> 2.969686
D16: Pacífico | E16: ='Copia de Electricidad'!D17/1000 -> 0.387754 | F16: ='Copia de Electricidad'!E17/1000 -> 0.387754 | G16: ='Copia de Electricidad'!F17/1000 -> 0.3979 | H16: ='Copia de Electricidad'!G17/1000 -> 0.3979
C17: PP_SPV_US | D17: Solar | E17: ='Copia de Electricidad'!D18/1000 -> 0.02446082 | F17: ='Copia de Electricidad'!E18/1000 -> 0.02446082 | G17: ='Copia de Electricidad'!F18/1000 -> 0.02446082 | H17: ='Copia de Electricidad'!G18/1000 -> 0.02446082
D18: Térmica | E18: ='Copia de Electricidad'!D19/1000 -> 2.1026506 | F18: ='Copia de Electricidad'!E19/1000 -> 2.0550506 | G18: ='Copia de Electricidad'!F19/1000 -> 2.0550506 | H18: ='Copia de Electricidad'!G19/1000 -> 2.0634706
D19: MCI | E19: ='Copia de Electricidad'!D20/1000 -> 0.8360556 | F19: ='Copia de Electricidad'!E20/1000 -> 0.7884556 | G19: ='Copia de Electricidad'!F20/1000 -> 0.7884556 | H19: ='Copia de Electricidad'!G20/1000 -> 0.7976756
C20: PP_DSLICE | D20: Diesel MCI | E20: ='Copia de Electricidad'!D21/1000 -> 0.3099856 | F20: ='Copia de Electricidad'!E21/1000 -> 0.2623856 | G20: ='Copia de Electricidad'!F21/1000 -> 0.2623856 | H20: ='Copia de Electricidad'!G21/1000 -> 0.2623856
C21: PP_FOIICE | D21: Fuel Oil MCI | E21: ='Copia de Electricidad'!D22/1000 -> 0.43722 | F21: ='Copia de Electricidad'!E22/1000 -> 0.43722 | G21: ='Copia de Electricidad'!F22/1000 -> 0.43722 | H21: ='Copia de Electricidad'!G22/1000 -> 0.44644
D22: Otro MCI | E22: ='Copia de Electricidad'!D23/1000 -> 0.00225 | F22: ='Copia de Electricidad'!E23/1000 -> 0.00225 | G22: ='Copia de Electricidad'!F23/1000 -> 0.00225 | H22: ='Copia de Electricidad'!G23/1000 -> 0.00225
C23: PP_WASICE | D23: Residuo MCI | E23: ='Copia de Electricidad'!D24/1000 -> 0.0866 | F23: ='Copia de Electricidad'!E24/1000 -> 0.0866 | G23: ='Copia de Electricidad'!F24/1000 -> 0.0866 | H23: ='Copia de Electricidad'!G24/1000 -> 0.0866
D24: Turbogas | E24: ='Copia de Electricidad'!D25/1000 -> 0.820595 | F24: ='Copia de Electricidad'!E25/1000 -> 0.820595 | G24: ='Copia de Electricidad'!F25/1000 -> 0.820595 | H24: ='Copia de Electricidad'!G25/1000 -> 0.819795
C25: PP_DSLTGS | D25: Diesel | E25: ='Copia de Electricidad'!D26/1000 -> 0.545235 | F25: ='Copia de Electricidad'!E26/1000 -> 0.545235 | G25: ='Copia de Electricidad'!F26/1000 -> 0.545235 | H25: ='Copia de Electricidad'!G26/1000 -> 0.544435
C26: PP_NGSTGS | D26: OC Gas Natural | E26: ='Copia de Electricidad'!D27/1000 -> 0.27536 | F26: ='Copia de Electricidad'!E27/1000 -> 0.27536 | G26: ='Copia de Electricidad'!F27/1000 -> 0.27536 | H26: ='Copia de Electricidad'!G27/1000 -> 0.27536
D27: Turbovapor | E27: ='Copia de Electricidad'!D28/1000 -> 0.446 | F27: ='Copia de Electricidad'!E28/1000 -> 0.446 | G27: ='Copia de Electricidad'!F28/1000 -> 0.446 | H27: ='Copia de Electricidad'!G28/1000 -> 0.446
C28: PP_FOITST | D28: Fuel Oil | E28: ='Copia de Electricidad'!D29/1000 -> 0.446 | F28: ='Copia de Electricidad'!E29/1000 -> 0.446 | G28: ='Copia de Electricidad'!F29/1000 -> 0.446 | H28: ='Copia de Electricidad'!G29/1000 -> 0.446
D29: Biogás | E29: ='Copia de Electricidad'!D30/1000 -> 0.00726 | F29: ='Copia de Electricidad'!E30/1000 -> 0.00726 | G29: ='Copia de Electricidad'!F30/1000 -> 0.00726 | H29: ='Copia de Electricidad'!G30/1000 -> 0.00832
D30: MCI
C31: PP_BGSICE | D31: Biogás | E31: ='Copia de Electricidad'!D32/1000 -> 0.00726 | F31: ='Copia de Electricidad'!E32/1000 -> 0.00726 | G31: ='Copia de Electricidad'!F32/1000 -> 0.00726 | H31: ='Copia de Electricidad'!G32/1000 -> 0.00832
D32: Hidroeléctrico represa [GW]
C33: PP_HYDPACDAMSMA | D33: Pacífico (pequeñas) | E33: ='Copia de Electricidad'!D34/1000 -> 0.0422 | F33: ='Copia de Electricidad'!E34/1000 -> 0.0422 | G33: ='Copia de Electricidad'!F34/1000 -> 0.0422 | H33: ='Copia de Electricidad'!G34/1000 -> 0.0422
C34: PP_HYDPACDAMMED | D34: Pacífico (medianas) | E34: ='Copia de Electricidad'!D35/1000 -> 0.213 | F34: ='Copia de Electricidad'!E35/1000 -> 0.213 | G34: ='Copia de Electricidad'!F35/1000 -> 0.213 | H34: ='Copia de Electricidad'!G35/1000 -> 0.213
C35: PP_HYDPACDAMLAR | D35: Pacífico (grandes)
C36: PP_HYDAMADAMSMA | D36: Amazonas (pequeñas)
C37: PP_HYDAMADAMMED | D37: Amazonas (medianas) | E37: ='Copia de Electricidad'!D38/1000 -> 0.403 | F37: ='Copia de Electricidad'!E38/1000 -> 0.403 | G37: ='Copia de Electricidad'!F38/1000 -> 0.403 | H37: ='Copia de Electricidad'!G38/1000 -> 0.403
C38: PP_HYDAMADAMLAR | D38: Amazonas (grandes) | E38: ='Copia de Electricidad'!D39/1000 -> 1.075 | F38: ='Copia de Electricidad'!E39/1000 -> 1.075 | G38: ='Copia de Electricidad'!F39/1000 -> 1.075 | H38: ='Copia de Electricidad'!G39/1000 -> 1.075
D39: Hidroeléctrico filo de agua [GW]
C40: PP_HYDPACRORSMA | D40: Pacífico (pequeñas) | E40: ='Copia de Electricidad'!D41/1000 -> 0.054394 | F40: ='Copia de Electricidad'!E41/1000 -> 0.054394 | G40: ='Copia de Electricidad'!F41/1000 -> 0.06454 | H40: ='Copia de Electricidad'!G41/1000 -> 0.06454
C41: PP_HYDPACRORMED | D41: Pacífico (medianas) | E41: ='Copia de Electricidad'!D42/1000 -> 0.33336 | F41: ='Copia de Electricidad'!E42/1000 -> 0.33336 | G41: ='Copia de Electricidad'!F42/1000 -> 0.33336 | H41: ='Copia de Electricidad'!G42/1000 -> 0.33336
C42: PP_HYDPACRORLAR | D42: Pacífico (grandes)
C43: PP_HYDAMARORSMA | D43: Amazonas (pequeñas) | E43: ='Copia de Electricidad'!D44/1000 -> 0.54239 | F43: ='Copia de Electricidad'!E44/1000 -> 0.55239 | G43: ='Copia de Electricidad'!F44/1000 -> 0.500282 | H43: ='Copia de Electricidad'!G44/1000 -> 0.508382
C44: PP_HYDAMARORMED | D44: Amazonas (medianas) | E44: ='Copia de Electricidad'!D45/1000 -> 0.41 | F44: ='Copia de Electricidad'!E45/1000 -> 0.41 | G44: ='Copia de Electricidad'!F45/1000 -> 0.474304 | H44: ='Copia de Electricidad'!G45/1000 -> 0.474304
C45: PP_HYDAMARORLAR | D45: Amazonas (grandes) | E45: ='Copia de Electricidad'!D46/1000 -> 1.987 | F45: ='Copia de Electricidad'!E46/1000 -> 1.987 | G45: ='Copia de Electricidad'!F46/1000 -> 1.987 | H45: ='Copia de Electricidad'!G46/1000 -> 1.987
D46: Total | E46: =E6+E9+E10+E17+E18+E29 -> 7.3555154 | F46: =F6+F9+F10+F17+F18+F29 -> 7.3179154 | G46: =G6+G9+G10+G17+G18+G29 -> 7.3402574 | H46: =H6+H9+H10+H17+H18+H29 -> 7.3578374
D48: Capacidad instalada (Sistemas Aislados) | E48: 2018 | F48: 2019 | G48: 2020 | H48: 2021 | I48: 2022 | J48: 2023 | K48: 2024 | L48: 2025 | M48: 2026 | N48: 2027 | O48: 2028 | P48: 2029 | Q48: 2030 | R48: 2031 | S48: 2032 | T48: 2033 | U48: 2034 | V48: 2035 | W48: 2036 | X48: 2037 | Y48: 2038 | Z48: 2039 | AA48: 2040 | AB48: 2041 | AC48: 2042 | AD48: 2043 | AE48: 2044 | AF48: 2045 | AG48: 2046 | AH48: 2047 | AI48: 2048 | AJ48: 2049 | AK48: 2050 | AL48: 2051 | AM48: 2052 | AN48: 2053 | AO48: 2054 | AP48: 2055 | AQ48: 2056 | AR48: 2057 | AS48: 2058 | AT48: 2059 | AU48: 2060 | AV48: 2061 | AW48: 2062 | AX48: 2063 | AY48: 2064 | AZ48: 2065 | BA48: 2066 | BB48: 2067 | BC48: 2068 | BD48: 2069 | BE48: 2070
D49: Biomasa [GW] | E49: - | F49: - | G49: - | H49: -
D50: Eólica | E50: ='Copia de Electricidad'!D51/1000 -> 0.00465 | F50: ='Copia de Electricidad'!E51/1000 -> 0.00465 | G50: ='Copia de Electricidad'!F51/1000 -> 0.00465 | H50: ='Copia de Electricidad'!G51/1000 -> 0.00465
C51: PPIWNDGAL | D51: Galápagos | E51: ='Copia de Electricidad'!D52/1000 -> 0.00465 | F51: ='Copia de Electricidad'!E52/1000 -> 0.00465 | G51: ='Copia de Electricidad'!F52/1000 -> 0.00465 | H51: ='Copia de Electricidad'!G52/1000 -> 0.00465 | I51: 0.00499476 | J51: 0.00512 | K51: 0.00524 | L51: 0.00537 | M51: 0.00549 | N51: 0.00562 | O51: 0.00574 | P51: 0.00587 | Q51: 0.00599 | R51: 0.00604 | S51: 0.00608 | T51: 0.00613 | U51: 0.00618 | V51: 0.00623 | W51: 0.00627 | X51: 0.00632 | Y51: 0.00637 | Z51: 0.00642 | AA51: 0.00646 | AB51: 0.00647 | AC51: 0.00648 | AD51: 0.00648 | AE51: 0.00649 | AF51: 0.0065 | AG51: 0.0065 | AH51: 0.00651 | AI51: 0.00651 | AJ51: 0.00652 | AK51: 0.00653 | AL51: 0.00653 | AM51: 0.00653 | AN51: 0.00653 | AO51: 0.00653 | AP51: 0.00653 | AQ51: 0.00653 | AR51: 0.00653 | AS51: 0.00653 | AT51: 0.00653 | AU51: 0.00653 | AV51: 0.00653 | AW51: 0.00653 | AX51: 0.00653 | AY51: 0.00653 | AZ51: 0.00653 | BA51: 0.00653 | BB51: 0.00653 | BC51: 0.00653 | BD51: 0.00653 | BE51: 0.00653
D52: Hidraúlica | E52: ='Copia de Electricidad'!D53/1000 -> 0.00606 | F52: ='Copia de Electricidad'!E53/1000 -> 0.00606 | G52: ='Copia de Electricidad'!F53/1000 -> 0.00606 | H52: ='Copia de Electricidad'!G53/1000 -> 0.00606
D53: Pasada | E53: ='Copia de Electricidad'!D54/1000 -> 0.00606 | F53: ='Copia de Electricidad'!E54/1000 -> 0.00606 | G53: ='Copia de Electricidad'!F54/1000 -> 0.00606 | H53: ='Copia de Electricidad'!G54/1000 -> 0.00606
D54: Electrificación Rural
C55: PPIHYDAMAELR | D55: Amazonas | E55: ='Copia de Electricidad'!D56/1000 -> 0.00116 | F55: ='Copia de Electricidad'!E56/1000 -> 0.00116 | G55: ='Copia de Electricidad'!F56/1000 -> 0.00116 | H55: ='Copia de Electricidad'!G56/1000 -> 0.00116 | I55: 0.0014 | J55: 0.00142 | K55: 0.00144 | L55: 0.00147 | M55: 0.00149 | N55: 0.00151 | O55: 0.00154 | P55: 0.00156 | Q55: 0.00159 | R55: 0.00161 | S55: 0.00164 | T55: 0.00166 | U55: 0.00169 | V55: 0.00172 | W55: 0.00174 | X55: 0.00177 | Y55: 0.00179 | Z55: 0.00182 | AA55: 0.00185 | AB55: 0.00187 | AC55: 0.0019 | AD55: 0.00193 | AE55: 0.00195 | AF55: 0.00198 | AG55: 0.002 | AH55: 0.00203 | AI55: 0.00205 | AJ55: 0.00208 | AK55: 0.0021 | AL55: 0.0007 | AM55: 0.00069 | AN55: 0.00068 | AO55: 0.00068 | AP55: 0.00067 | AQ55: 0.00066 | AR55: 0.00065 | AS55: 0.00064 | AT55: 0.00063 | AU55: 0.00062 | AV55: 0.00061 | AW55: 0.0006 | AX55: 0.00059 | AY55: 0.00058 | AZ55: 0.00057 | BA55: 0.00056 | BB55: 0.00054 | BC55: 0.00053 | BD55: 0.00052 | BE55: 0.00051
C56: PPIHYDPACELR | D56: Pacífico | E56: ='Copia de Electricidad'!D57/1000 -> 0.0029 | F56: ='Copia de Electricidad'!E57/1000 -> 0.0029 | G56: ='Copia de Electricidad'!F57/1000 -> 0.0029 | H56: ='Copia de Electricidad'!G57/1000 -> 0.0029 | I56: 0.00407 | J56: 0.00414 | K56: 0.00421 | L56: 0.00428 | M56: 0.00435 | N56: 0.00442 | O56: 0.00449 | P56: 0.00456 | Q56: 0.00463 | R56: 0.00471 | S56: 0.00478 | T56: 0.00485 | U56: 0.00493 | V56: 0.00501 | W56: 0.00508 | X56: 0.00516 | Y56: 0.00523 | Z56: 0.00531 | AA56: 0.00539 | AB56: 0.00546 | AC56: 0.00554 | AD56: 0.00562 | AE56: 0.00569 | AF56: 0.00577 | AG56: 0.00584 | AH56: 0.00591 | AI56: 0.00598 | AJ56: 0.00606 | AK56: 0.00612 | AL56: 0.00204 | AM56: 0.00202 | AN56: 0.002 | AO56: 0.00197 | AP56: 0.00195 | AQ56: 0.00192 | AR56: 0.00189 | AS56: 0.00187 | AT56: 0.00184 | AU56: 0.00181 | AV56: 0.00178 | AW56: 0.00175 | AX56: 0.00172 | AY56: 0.00169 | AZ56: 0.00165 | BA56: 0.00162 | BB56: 0.00159 | BC56: 0.00156 | BD56: 0.00152 | BE56: 0.00149
D57: Cementera
C58: PPIHYDAMACEM | D58: Amazonas | E58: ='Copia de Electricidad'!D59/1000 -> 0.002 | F58: ='Copia de Electricidad'!E59/1000 -> 0.002 | G58: ='Copia de Electricidad'!F59/1000 -> 0.002 | H58: ='Copia de Electricidad'!G59/1000 -> 0.002
C59: PPIHYDPACCEM | D59: Pacífico | E59: ='Copia de Electricidad'!D60/1000 -> 0 | F59: ='Copia de Electricidad'!E60/1000 -> 0 | G59: ='Copia de Electricidad'!F60/1000 -> 0 | H59: ='Copia de Electricidad'!G60/1000 -> 0
D60: Solar | E60: ='Copia de Electricidad'!D61/1000 -> 0.00316902 | F60: ='Copia de Electricidad'!E61/1000 -> 0.00316902 | G60: ='Copia de Electricidad'!F61/1000 -> 0.00316902 | H60: ='Copia de Electricidad'!G61/1000 -> 0.00319236
C61: PPISPVGAL | D61: Galápagos | E61: ='Copia de Electricidad'!D62/1000 -> 0.00259642 | F61: ='Copia de Electricidad'!E62/1000 -> 0.00259642 | G61: ='Copia de Electricidad'!F62/1000 -> 0.00259642 | H61: ='Copia de Electricidad'!G62/1000 -> 0.00261976 | I61: 0.00326 | J61: 0.00334 | K61: 0.00342 | L61: 0.0035 | M61: 0.00358 | N61: 0.00366 | O61: 0.00374 | P61: 0.00382 | Q61: 0.00391 | R61: 0.00394 | S61: 0.00397 | T61: 0.004 | U61: 0.00403 | V61: 0.00406 | W61: 0.00409 | X61: 0.00412 | Y61: 0.00415 | Z61: 0.00418 | AA61: 0.00421 | AB61: 0.00422 | AC61: 0.00422 | AD61: 0.00423 | AE61: 0.00423 | AF61: 0.00423 | AG61: 0.00424 | AH61: 0.00424 | AI61: 0.00425 | AJ61: 0.00425 | AK61: 0.00426 | AL61: 0.00426 | AM61: 0.00426 | AN61: 0.00426 | AO61: 0.00426 | AP61: 0.00426 | AQ61: 0.00426 | AR61: 0.00426 | AS61: 0.00426 | AT61: 0.00426 | AU61: 0.00426 | AV61: 0.00426 | AW61: 0.00426 | AX61: 0.00426 | AY61: 0.00426 | AZ61: 0.00426 | BA61: 0.00426 | BB61: 0.00426 | BC61: 0.00426 | BD61: 0.00426 | BE61: 0.00426
C62: PPISPVELR | D62: Electrificación Rural | E62: ='Copia de Electricidad'!D63/1000 -> 0.0005726 | F62: ='Copia de Electricidad'!E63/1000 -> 0.0005726 | G62: ='Copia de Electricidad'!F63/1000 -> 0.0005726 | H62: ='Copia de Electricidad'!G63/1000 -> 0.0005726 | I62: 0.0007 | J62: 0.00071 | K62: 0.00072 | L62: 0.00074 | M62: 0.00075 | N62: 0.00076 | O62: 0.00077 | P62: 0.00079 | Q62: 0.0008 | R62: 0.00081 | S62: 0.00082 | T62: 0.00084 | U62: 0.00085 | V62: 0.00086 | W62: 0.00088 | X62: 0.00089 | Y62: 0.0009 | Z62: 0.00091 | AA62: 0.00093 | AB62: 0.00094 | AC62: 0.00095 | AD62: 0.00097 | AE62: 0.00098 | AF62: 0.00099 | AG62: 0.00101 | AH62: 0.00102 | AI62: 0.00103 | AJ62: 0.00104 | AK62: 0.00105 | AL62: 0.00035 | AM62: 0.00035 | AN62: 0.00034 | AO62: 0.00034 | AP62: 0.00034 | AQ62: 0.00033 | AR62: 0.00033 | AS62: 0.00032 | AT62: 0.00032 | AU62: 0.00031 | AV62: 0.00031 | AW62: 0.0003 | AX62: 0.0003 | AY62: 0.00029 | AZ62: 0.00028 | BA62: 0.00028 | BB62: 0.00027 | BC62: 0.00027 | BD62: 0.00026 | BE62: 0.00026
D63: Térmica | E63: ='Copia de Electricidad'!D64/1000 -> 1.2925078 | F63: ='Copia de Electricidad'!E64/1000 -> 1.3532198 | G63: ='Copia de Electricidad'!F64/1000 -> 1.3581608 | H63: ='Copia de Electricidad'!G64/1000 -> 1.3626708
D64: MCI | E64: ='Copia de Electricidad'!D65/1000 -> 1.1753888 | F64: ='Copia de Electricidad'!E65/1000 -> 1.2363408 | G64: ='Copia de Electricidad'!F65/1000 -> 1.2412818 | H64: ='Copia de Electricidad'!G65/1000 -> 1.2229918
D65: Electrificación Rural
C66: PPIDSLELRICE | D66: Diesel | E66: ='Copia de Electricidad'!D67/1000 -> 0.0328 | F66: ='Copia de Electricidad'!E67/1000 -> 0.03225 | G66: ='Copia de Electricidad'!F67/1000 -> 0.03365 | H66: ='Copia de Electricidad'!G67/1000 -> 0.01325 | I66: 0.03206 | J66: 0.0326 | K66: 0.03314 | L66: 0.03368 | M66: 0.03424 | N66: 0.03479 | O66: 0.03536 | P66: 0.03592 | Q66: 0.0365 | R66: 0.03708 | S66: 0.03766 | T66: 0.03825 | U66: 0.03884 | V66: 0.03943 | W66: 0.04003 | X66: 0.04063 | Y66: 0.04123 | Z66: 0.04184 | AA66: 0.04244 | AB66: 0.04305 | AC66: 0.04365 | AD66: 0.04425 | AE66: 0.04485 | AF66: 0.04543 | AG66: 0.04602 | AH66: 0.04659 | AI66: 0.04715 | AJ66: 0.04771 | AK66: 0.04825 | AL66: 0.0161 | AM66: 0.01592 | AN66: 0.01573 | AO66: 0.01554 | AP66: 0.01533 | AQ66: 0.01513 | AR66: 0.01492 | AS66: 0.0147 | AT66: 0.01448 | AU66: 0.01425 | AV66: 0.01401 | AW66: 0.01378 | AX66: 0.01353 | AY66: 0.01328 | AZ66: 0.01303 | BA66: 0.01278 | BB66: 0.01252 | BC66: 0.01225 | BD66: 0.01198 | BE66: 0.01171
D67: Galápagos
C68: PPIDSLGALICE | D68: Diesel | E68: ='Copia de Electricidad'!D69/1000 -> 0.027582 | F68: ='Copia de Electricidad'!E69/1000 -> 0.024147 | G68: ='Copia de Electricidad'!F69/1000 -> 0.024285 | H68: ='Copia de Electricidad'!G69/1000 -> 0.024285 | I68: 0.03011 | J68: 0.03086 | K68: 0.03161 | L68: 0.03236 | M68: 0.03311 | N68: 0.03386 | O68: 0.03461 | P68: 0.03536 | Q68: 0.03611 | R68: 0.0364 | S68: 0.03668 | T68: 0.03697 | U68: 0.03725 | V68: 0.03754 | W68: 0.03782 | X68: 0.03811 | Y68: 0.03839 | Z68: 0.03868 | AA68: 0.03897 | AB68: 0.039 | AC68: 0.03904 | AD68: 0.03908 | AE68: 0.03912 | AF68: 0.03916 | AG68: 0.0392 | AH68: 0.03924 | AI68: 0.03928 | AJ68: 0.03932 | AK68: 0.03935 | AL68: 0.03935 | AM68: 0.03935 | AN68: 0.03935 | AO68: 0.03935 | AP68: 0.03935 | AQ68: 0.03935 | AR68: 0.03935 | AS68: 0.03935 | AT68: 0.03935 | AU68: 0.03935 | AV68: 0.03935 | AW68: 0.03935 | AX68: 0.03935 | AY68: 0.03935 | AZ68: 0.03935 | BA68: 0.03935 | BB68: 0.03935 | BC68: 0.03935 | BD68: 0.03935 | BE68: 0.03935
D69: Petrolero
C70: PPICRUPETICE | D70: Crudo | E70: ='Copia de Electricidad'!D71/1000 -> 0.378587 | F70: ='Copia de Electricidad'!E71/1000 -> 0.378587 | G70: ='Copia de Electricidad'!F71/1000 -> 0.378537 | H70: ='Copia de Electricidad'!G71/1000 -> 0.432292
C71: PPIDSLPETICE | D71: Diesel | E71: ='Copia de Electricidad'!D72/1000 -> 0.53094778 | F71: ='Copia de Electricidad'!E72/1000 -> 0.59061478 | G71: ='Copia de Electricidad'!F72/1000 -> 0.59251978 | H71: ='Copia de Electricidad'!G72/1000 -> 0.54150778
C72: PPIFOIPETICE | D72: Fuel Oil | E72: ='Copia de Electricidad'!D73/1000 -> 0.0144 | F72: ='Copia de Electricidad'!E73/1000 -> 0.0144 | G72: ='Copia de Electricidad'!F73/1000 -> 0.0144 | H72: ='Copia de Electricidad'!G73/1000 -> 0.0144
C73: PPINGSPETICE | D73: Gas Natural | E73: ='Copia de Electricidad'!D74/1000 -> 0.191072 | F73: ='Copia de Electricidad'!E74/1000 -> 0.196342 | G73: ='Copia de Electricidad'!F74/1000 -> 0.19789 | H73: ='Copia de Electricidad'!G74/1000 -> 0.197257
D74: Turbogas | E74: ='Copia de Electricidad'!D75/1000 -> 0.101254 | F74: ='Copia de Electricidad'!E75/1000 -> 0.101254 | G74: ='Copia de Electricidad'!F75/1000 -> 0.101254 | H74: ='Copia de Electricidad'!G75/1000 -> 0.124054
D75: Petrolero
C76: PPIDSLPETTGS | D76: Diesel | E76: ='Copia de Electricidad'!D77/1000 -> 0.0504 | F76: ='Copia de Electricidad'!E77/1000 -> 0.0504 | G76: ='Copia de Electricidad'!F77/1000 -> 0.0504 | H76: ='Copia de Electricidad'!G77/1000 -> 0.0504
C77: PPINGSPETTGS | D77: OC Gas Natural | E77: ='Copia de Electricidad'!D78/1000 -> 0.04585 | F77: ='Copia de Electricidad'!E78/1000 -> 0.04585 | G77: ='Copia de Electricidad'!F78/1000 -> 0.04585 | H77: ='Copia de Electricidad'!G78/1000 -> 0.06865
C78: PPICRUPETTST | D78: Crudo | E78: ='Copia de Electricidad'!D79/1000 -> 0.005004 | F78: ='Copia de Electricidad'!E79/1000 -> 0.005004 | G78: ='Copia de Electricidad'!F79/1000 -> 0.005004 | H78: ='Copia de Electricidad'!G79/1000 -> 0.005004
D79: Turbovapor | E79: ='Copia de Electricidad'!D80/1000 -> 0.015865 | F79: ='Copia de Electricidad'!E80/1000 -> 0.015625 | G79: ='Copia de Electricidad'!F80/1000 -> 0.015625 | H79: ='Copia de Electricidad'!G80/1000 -> 0.015625
D80: Electrificación Rural
C81: PPIDSLELRTST | D81: Diesel | E81: ='Copia de Electricidad'!D82/1000 -> 0.00024 | F81: ='Copia de Electricidad'!E82/1000 -> 0 | G81: ='Copia de Electricidad'!F82/1000 -> 0 | H81: ='Copia de Electricidad'!G82/1000 -> 0
D82: Cementera
C83: PPIDSLCEMTST | D83: Diesel | E83: ='Copia de Electricidad'!D84/1000 -> 0.003625 | F83: ='Copia de Electricidad'!E84/1000 -> 0.003625 | G83: ='Copia de Electricidad'!F84/1000 -> 0.003625 | H83: ='Copia de Electricidad'!G84/1000 -> 0.003625
D84: Petrolero
C85: PPINGSPETTST | D85: Gas Natural | E85: ='Copia de Electricidad'!D86/1000 -> 0.012 | F85: ='Copia de Electricidad'!E86/1000 -> 0.012 | G85: ='Copia de Electricidad'!F86/1000 -> 0.012 | H85: ='Copia de Electricidad'!G86/1000 -> 0.012
D86: Biogás [GW]
D87: Total | E87: =SUM(E50+E52+E60+E63) -> 1.3063868 | F87: =SUM(F50+F52+F60+F63) -> 1.3670988 | G87: =SUM(G50+G52+G60+G63) -> 1.3720398 | H87: =SUM(H50+H52+H60+H63) -> 1.3765731
D89: Capacidad instalada (Total) | E89: 2018 | F89: 2019 | G89: 2020 | H89: 2021
D90: Biomasa [GW] | E90: ='Copia de Electricidad'!D91/1000 -> 0.1443 | F90: ='Copia de Electricidad'!E91/1000 -> 0.1443 | G90: ='Copia de Electricidad'!F91/1000 -> 0.1443 | H90: ='Copia de Electricidad'!G91/1000 -> 0.1443
D91: Eólica [GW] | E91: ='Copia de Electricidad'!D92/1000 -> 0.02115 | F91: ='Copia de Electricidad'!E92/1000 -> 0.02115 | G91: ='Copia de Electricidad'!F92/1000 -> 0.02115 | H91: ='Copia de Electricidad'!G92/1000 -> 0.02115
D92: Hidraúlica [GW] | E92: ='Copia de Electricidad'!D93/1000 -> 5.066404 | F92: ='Copia de Electricidad'!E93/1000 -> 5.076404 | G92: ='Copia de Electricidad'!F93/1000 -> 5.098746 | H92: ='Copia de Electricidad'!G93/1000 -> 5.106846
D93: Embalse | E93: ='Copia de Electricidad'!D94/1000 -> 1.7332 | F93: ='Copia de Electricidad'!E94/1000 -> 1.7332 | G93: ='Copia de Electricidad'!F94/1000 -> 1.7332 | H93: ='Copia de Electricidad'!G94/1000 -> 1.7332
D94: Pasada | E94: ='Copia de Electricidad'!D95/1000 -> 3.333204 | F94: ='Copia de Electricidad'!E95/1000 -> 3.343204 | G94: ='Copia de Electricidad'!F95/1000 -> 3.365546 | H94: ='Copia de Electricidad'!G95/1000 -> 3.373646
D95: Solar [GW] | E95: ='Copia de Electricidad'!D96/1000 -> 0.02762984 | F95: ='Copia de Electricidad'!E96/1000 -> 0.02762984 | G95: ='Copia de Electricidad'!F96/1000 -> 0.02762984 | H95: ='Copia de Electricidad'!G96/1000 -> 0.02765318
D96: Térmica [GW] | E96: ='Copia de Electricidad'!D97/1000 -> 3.3951584 | F96: ='Copia de Electricidad'!E97/1000 -> 3.4082704 | G96: ='Copia de Electricidad'!F97/1000 -> 3.4132114 | H96: ='Copia de Electricidad'!G97/1000 -> 3.4261414
D97: MCI | E97: ='Copia de Electricidad'!D98/1000 -> 2.0114444 | F97: ='Copia de Electricidad'!E98/1000 -> 2.0247964 | G97: ='Copia de Electricidad'!F98/1000 -> 2.0297374 | H97: ='Copia de Electricidad'!G98/1000 -> 2.0206674
D98: Turbogas | E98: ='Copia de Electricidad'!D99/1000 -> 0.921849 | F98: ='Copia de Electricidad'!E99/1000 -> 0.921849 | G98: ='Copia de Electricidad'!F99/1000 -> 0.921849 | H98: ='Copia de Electricidad'!G99/1000 -> 0.943849
D99: Turbovapor | E99: ='Copia de Electricidad'!D100/1000 -> 0.461865 | F99: ='Copia de Electricidad'!E100/1000 -> 0.461625 | G99: ='Copia de Electricidad'!F100/1000 -> 0.461625 | H99: ='Copia de Electricidad'!G100/1000 -> 0.461625
D100: Biogás [GW] | E100: ='Copia de Electricidad'!D101/1000 -> 0.00726 | F100: ='Copia de Electricidad'!E101/1000 -> 0.00726 | G100: ='Copia de Electricidad'!F101/1000 -> 0.00726 | H100: ='Copia de Electricidad'!G101/1000 -> 0.00832
D101: Total | E101: =E90+E91+E92+E95+E96+E100 -> 8.6619022 | F101: =F90+F91+F92+F95+F96+F100 -> 8.6850142 | G101: =G90+G91+G92+G95+G96+G100 -> 8.7122972 | H101: =H90+H91+H92+H95+H96+H100 -> 8.7344105
D103: Nueva capacidad proyectada en los actuales planes de expansión | E103: Por favor categorizar la nueva capacidad igual que la capacidad instalada
E104: 2018 | F104: 2019 | G104: 2020 | H104: 2021 | I104: 2022 | J104: 2023 | K104: 2024 | L104: 2025 | M104: 2026 | N104: 2027 | O104: 2028 | P104: 2029 | Q104: 2030 | R104: 2031 | S104: 2032 | T104: 2033 | U104: 2034 | V104: 2035 | W104: 2036 | X104: 2037 | Y104: 2038 | Z104: 2039 | AA104: 2040 | AB104: 2041 | AC104: 2042 | AD104: 2043 | AE104: 2044 | AF104: 2045 | AG104: 2046 | AH104: 2047 | AI104: 2048 | AJ104: 2049 | AK104: 2050 | AL104: 2051 | AM104: 2052 | AN104: 2053 | AO104: 2054 | AP104: 2055 | AQ104: 2056 | AR104: 2057 | AS104: 2058 | AT104: 2059 | AU104: 2060 | AV104: 2061 | AW104: 2062 | AX104: 2063 | AY104: 2064 | AZ104: 2065 | BA104: 2066 | BB104: 2067 | BC104: 2068 | BD104: 2069 | BE104: 2070
D105: Biomasa [GW] | N105: ='Copia de Electricidad'!M105/1000 -> 0.1
...

Sheet Hidrógeno
D1: Ecuador | E1: 2018 | F1: 2019 | G1: 2020 | H1: 2021 | I1: 2022 | J1: 2023 | K1: 2024 | L1: 2025 | M1: 2026 | N1: 2027 | O1: 2028 | P1: 2029 | Q1: 2030 | R1: 2031 | S1: 2032 | T1: 2033 | U1: 2034 | V1: 2035 | W1: 2036 | X1: 2037 | Y1: 2038 | Z1: 2039 | AA1: 2040 | AB1: 2041 | AC1: 2042 | AD1: 2043 | AE1: 2044 | AF1: 2045 | AG1: 2046 | AH1: 2047 | AI1: 2048 | AJ1: 2049 | AK1: 2050 | AL1: 2051 | AM1: 2052 | AN1: 2053 | AO1: 2054 | AP1: 2055 | AQ1: 2056 | AR1: 2057 | AS1: 2058 | AT1: 2059 | AU1: 2060 | AV1: 2061 | AW1: 2062 | AX1: 2063 | AY1: 2064 | AZ1: 2065 | BA1: 2066 | BB1: 2067 | BC1: 2068 | BD1: 2069 | BE1: 2070
D3: [PJ]
C4: Electrolyzer | D4: Efficiency electricidad (PJ) para producir un PJ de hidrógeno | E4: 0.7 | F4: 0.7 | G4: 0.7 | H4: 0.7 | I4: 0.7 | J4: 0.7 | K4: 0.7 | L4: 0.7 | M4: 0.7 | N4: 0.7 | O4: 0.7 | P4: 0.7 | Q4: 0.7 | R4: 0.7 | S4: 0.7 | T4: 0.7 | U4: 0.7 | V4: 0.7 | W4: 0.7 | X4: 0.7 | Y4: 0.7 | Z4: 0.7 | AA4: 0.7 | AB4: 0.7 | AC4: 0.7 | AD4: 0.7 | AE4: 0.7 | AF4: 0.7 | AG4: 0.7 | AH4: 0.7 | AI4: 0.7 | AJ4: 0.7 | AK4: 0.7 | AL4: 0.7 | AM4: 0.7 | AN4: 0.7 | AO4: 0.7 | AP4: 0.7 | AQ4: 0.7 | AR4: 0.7 | AS4: 0.7 | AT4: 0.7 | AU4: 0.7 | AV4: 0.7 | AW4: 0.7 | AX4: 0.7 | AY4: 0.7 | AZ4: 0.7 | BA4: 0.7 | BB4: 0.7 | BC4: 0.7 | BD4: 0.7 | BE4: 0.7
D5: Lifetime | E5: 30 | F5: 30 | G5: 30 | H5: 30 | I5: 30 | J5: 30 | K5: 30 | L5: 30 | M5: 30 | N5: 30 | O5: 30 | P5: 30 | Q5: 30 | R5: 30 | S5: 30 | T5: 30 | U5: 30 | V5: 30 | W5: 30 | X5: 30 | Y5: 30 | Z5: 30 | AA5: 30 | AB5: 30 | AC5: 30 | AD5: 30 | AE5: 30 | AF5: 30 | AG5: 30 | AH5: 30 | AI5: 30 | AJ5: 30 | AK5: 30 | AL5: 30 | AM5: 30 | AN5: 30 | AO5: 30 | AP5: 30 | AQ5: 30 | AR5: 30 | AS5: 30 | AT5: 30 | AU5: 30 | AV5: 30 | AW5: 30 | AX5: 30 | AY5: 30 | AZ5: 30 | BA5: 30 | BB5: 30 | BC5: 30 | BD5: 30 | BE5: 30
C8: Parameter_Category | D8: Parameter | E8: Set | F8: Source | G8: Info_Type | H8: Value_Type | I8: Units | J8: Projection Mode | K8: Value
C9: Transport | D9: Levelized cost of transport | E9: Pipeline Cost at 1000 km | F9: IRENA 2022 - Part 2 | G9: Numerical | H9: Min | I9: $/kg | J9: Flat | K9: 0.1
C10: Transport | D10: Levelized cost of transport | E10: Pipeline Cost at 1000 km | F10: IRENA 2022 - Part 2 | G10: Numerical | H10: Max | I10: $/kg | J10: Flat | K10: 2
C11: General | D11: Specific energy | E11: Hydrogeno | F11: Ammonia for power (Science Direct) | G11: Numerical | H11: LHV | I11: MJ/kg | J11: Flat | K11: 120
I13: M$/PJ | J13: Flat | K13: =K9/120*1000 -> 0.83333333 | L13: M$/PJ | M13: =AVERAGE(K13:K14) -> 8.75
I14: M$/PJ | J14: Flat | K14: =K10/120*1000 -> 16.666667

Sheet Calculos electricidad
D1: Ecuador | E1: 2018 | F1: 2019 | G1: 2020 | H1: 2021 | I1: 2022 | J1: 2023 | K1: 2024 | L1: 2025 | M1: 2026 | N1: 2027 | O1: 2028 | P1: 2029 | Q1: 2030 | R1: 2031 | S1: 2032 | T1: 2033 | U1: 2034 | V1: 2035 | W1: 2036 | X1: 2037 | Y1: 2038 | Z1: 2039 | AA1: 2040 | AB1: 2041 | AC1: 2042 | AD1: 2043 | AE1: 2044 | AF1: 2045 | AG1: 2046 | AH1: 2047 | AI1: 2048 | AJ1: 2049 | AK1: 2050 | AL1: 2051 | AM1: 2052 | AN1: 2053 | AO1: 2054 | AP1: 2055 | AQ1: 2056 | AR1: 2057 | AS1: 2058 | AT1: 2059 | AU1: 2060 | AV1: 2061 | AW1: 2062 | AX1: 2063 | AY1: 2064 | AZ1: 2065 | BA1: 2066 | BB1: 2067 | BC1: 2068 | BD1: 2069 | BE1: 2070
D4: Generación eléctrica
D6: Capacidad instalada (SNI)
D7: Biomasa [GW] | E7: =Electricidad!E6 -> 0.1443 | F7: =Electricidad!F6 -> 0.1443 | G7: =Electricidad!G6 -> 0.1443 | H7: =Electricidad!H6 -> 0.1443
D8: Eólica [GW] | E8: =Electricidad!E9 -> 0.0165 | F8: =Electricidad!F9 -> 0.0165 | G8: =Electricidad!G9 -> 0.0165 | H8: =Electricidad!H9 -> 0.0165
D9: Hidroeléctrico represa [GW] | E9: =SUM(E10:E15) -> 1.7332 | F9: =SUM(F10:F15) -> 1.7332 | G9: =SUM(G10:G15) -> 1.7332 | H9: =SUM(H10:H15) -> 1.7332
D10: Pacífico (pequeñas) | E10: =Electricidad!E33 -> 0.0422 | F10: =Electricidad!F33 -> 0.0422 | G10: =Electricidad!G33 -> 0.0422 | H10: =Electricidad!H33 -> 0.0422
D11: Pacífico (medianas) | E11: =Electricidad!E34 -> 0.213 | F11: =Electricidad!F34 -> 0.213 | G11: =Electricidad!G34 -> 0.213 | H11: =Electricidad!H34 -> 0.213
D12: Pacífico (grandes) | E12: =Electricidad!E35 -> 0 | F12: =Electricidad!F35 -> 0 | G12: =Electricidad!G35 -> 0 | H12: =Electricidad!H35 -> 0
D13: Amazonas (pequeñas) | E13: =Electricidad!E36 -> 0 | F13: =Electricidad!F36 -> 0 | G13: =Electricidad!G36 -> 0 | H13: =Electricidad!H36 -> 0
D14: Amazonas (medianas) | E14: =Electricidad!E37 -> 0.403 | F14: =Electricidad!F37 -> 0.403 | G14: =Electricidad!G37 -> 0.403 | H14: =Electricidad!H37 -> 0.403
D15: Amazonas (grandes) | E15: =Electricidad!E38 -> 1.075 | F15: =Electricidad!F38 -> 1.075 | G15: =Electricidad!G38 -> 1.075 | H15: =Electricidad!H38 -> 1.075
D16: Hidroeléctrico filo de agua [GW] | E16: =SUM(E17:E22) -> 3.327144 | F16: =SUM(F17:F22) -> 3.337144 | G16: =SUM(G17:G22) -> 3.359486 | H16: =SUM(H17:H22) -> 3.367586
D17: Pacífico (pequeñas) | E17: =Electricidad!E40 -> 0.054394 | F17: =Electricidad!F40 -> 0.054394 | G17: =Electricidad!G40 -> 0.06454 | H17: =Electricidad!H40 -> 0.06454
D18: Pacífico (medianas) | E18: =Electricidad!E41 -> 0.33336 | F18: =Electricidad!F41 -> 0.33336 | G18: =Electricidad!G41 -> 0.33336 | H18: =Electricidad!H41 -> 0.33336
D19: Pacífico (grandes) | E19: =Electricidad!E42 -> 0 | F19: =Electricidad!F42 -> 0 | G19: =Electricidad!G42 -> 0 | H19: =Electricidad!H42 -> 0
D20: Amazonas (pequeñas) | E20: =Electricidad!E43 -> 0.54239 | F20: =Electricidad!F43 -> 0.55239 | G20: =Electricidad!G43 -> 0.500282 | H20: =Electricidad!H43 -> 0.508382
D21: Amazonas (medianas) | E21: =Electricidad!E44 -> 0.41 | F21: =Electricidad!F44 -> 0.41 | G21: =Electricidad!G44 -> 0.474304 | H21: =Electricidad!H44 -> 0.474304
D22: Amazonas (grandes) | E22: =Electricidad!E45 -> 1.987 | F22: =Electricidad!F45 -> 1.987 | G22: =Electricidad!G45 -> 1.987 | H22: =Electricidad!H45 -> 1.987
D23: Solar [GW] | E23: 0.02446082 | F23: 0.02446082 | G23: 0.02446082 | H23: 0.02446082
D24: Otro
D25: MCI
D26: Diesel | E26: =Electricidad!E20 -> 0.3099856 | F26: =Electricidad!F20 -> 0.2623856 | G26: =Electricidad!G20 -> 0.2623856 | H26: =Electricidad!H20 -> 0.2623856
D27: Fuel Oil | E27: =Electricidad!E21 -> 0.43722 | F27: =Electricidad!F21 -> 0.43722 | G27: =Electricidad!G21 -> 0.43722 | H27: =Electricidad!H21 -> 0.44644
D28: Otro | E28: =Electricidad!E22 -> 0.00225 | F28: =Electricidad!F22 -> 0.00225 | G28: =Electricidad!G22 -> 0.00225 | H28: =Electricidad!H22 -> 0.00225
D29: Residuo | E29: =Electricidad!E23 -> 0.0866 | F29: =Electricidad!F23 -> 0.0866 | G29: =Electricidad!G23 -> 0.0866 | H29: =Electricidad!H23 -> 0.0866
D30: Turbogas
D31: Diesel | E31: =Electricidad!E25 -> 0.545235 | F31: =Electricidad!F25 -> 0.545235 | G31: =Electricidad!G25 -> 0.545235 | H31: =Electricidad!H25 -> 0.544435
D32: Gas Natural | E32: =Electricidad!E26 -> 0.27536 | F32: =Electricidad!F26 -> 0.27536 | G32: =Electricidad!G26 -> 0.27536 | H32: =Electricidad!H26 -> 0.27536
D33: Turbovapor
D34: Fuel Oil | E34: =Electricidad!E28 -> 0.446 | F34: =Electricidad!F28 -> 0.446 | G34: =Electricidad!G28 -> 0.446 | H34: =Electricidad!H28 -> 0.446
D35: Biogás [GW] | E35: =Electricidad!E29 -> 0.00726 | F35: =Electricidad!F29 -> 0.00726 | G35: =Electricidad!G29 -> 0.00726 | H35: =Electricidad!H29 -> 0.00832
D36: Total | E36: =SUM(E7:E35)-E9-E16 -> 7.3555154 | F36: =SUM(F7:F35)-F9-F16 -> 7.3179154 | G36: =SUM(G7:G35)-G9-G16 -> 7.3402574 | H36: =SUM(H7:H35)-H9-H16 -> 7.3578374
D38: Capacidad instalada (Aislados) Reordenado
D39: GALÁPAGOS
D40: Eólica | E40: =Electricidad!E51 -> 0.00465 | F40: =Electricidad!F51 -> 0.00465 | G40: =Electricidad!G51 -> 0.00465 | H40: =Electricidad!H51 -> 0.00465
D41: Diesel MCI | E41: =Electricidad!E68 -> 0.027582 | F41: =Electricidad!F68 -> 0.024147 | G41: =Electricidad!G68 -> 0.024285 | H41: =Electricidad!H68 -> 0.024285
D42: Solar | E42: =Electricidad!E61 -> 0.00259642 | F42: =Electricidad!F61 -> 0.00259642 | G42: =Electricidad!G61 -> 0.00259642 | H42: =Electricidad!H61 -> 0.00261976
D44: ELÉCTRIFICACIÓN RURAL
D45: Hidro Amazonas | E45: =Electricidad!E55 -> 0.00116 | F45: =Electricidad!F55 -> 0.00116 | G45: =Electricidad!G55 -> 0.00116 | H45: =Electricidad!H55 -> 0.00116
D46: Hidro Pacífico | E46: =Electricidad!E56 -> 0.0029 | F46: =Electricidad!F56 -> 0.0029 | G46: =Electricidad!G56 -> 0.0029 | H46: =Electricidad!H56 -> 0.0029
D47: Solar | E47: =Electricidad!E62 -> 0.0005726 | F47: =Electricidad!F62 -> 0.0005726 | G47: =Electricidad!G62 -> 0.0005726 | H47: =Electricidad!H62 -> 0.0005726
D48: Diesel | E48: =SUM(E49:E50) -> 0.03304 | F48: =SUM(F49:F50) -> 0.03225 | G48: =SUM(G49:G50) -> 0.03365 | H48: =SUM(H49:H50) -> 0.01325
D49: Diesel MCI | E49: =Electricidad!E66 -> 0.0328 | F49: =Electricidad!F66 -> 0.03225 | G49: =Electricidad!G66 -> 0.03365 | H49: =Electricidad!H66 -> 0.01325
D50: Diesel Turbovapor | E50: =Electricidad!E81 -> 0.00024 | F50: =Electricidad!F81 -> 0 | G50: =Electricidad!G81 -> 0 | H50: =Electricidad!H81 -> 0
D52: CEMENTERA
D53: Hidro Amazonas | E53: =Electricidad!E58 -> 0.002 | F53: =Electricidad!F58 -> 0.002 | G53: =Electricidad!G58 -> 0.002 | H53: =Electricidad!H58 -> 0.002
D54: Hidro Pacífico | E54: =Electricidad!E59 -> 0 | F54: =Electricidad!F59 -> 0 | G54: =Electricidad!G59 -> 0 | H54: =Electricidad!H59 -> 0
D55: Diesel Turbovapor | E55: =Electricidad!E83 -> 0.003625 | F55: =Electricidad!F83 -> 0.003625 | G55: =Electricidad!G83 -> 0.003625 | H55: =Electricidad!H83 -> 0.003625
D57: PETROLERO
D58: Crudo | E58: =SUM(E59:E60) -> 0.383591 | F58: =SUM(F59:F60) -> 0.383591 | G58: =SUM(G59:G60) -> 0.383541 | H58: =SUM(H59:H60) -> 0.437296
D59: Crudo MCI | E59: =Electricidad!E70 -> 0.378587 | F59: =Electricidad!F70 -> 0.378587 | G59: =Electricidad!G70 -> 0.378537 | H59: =Electricidad!H70 -> 0.432292
D60: Crudo Turbogas | E60: =Electricidad!E78 -> 0.005004 | F60: =Electricidad!F78 -> 0.005004 | G60: =Electricidad!G78 -> 0.005004 | H60: =Electricidad!H78 -> 0.005004
D61: Fuel Oil MCI | E61: =Electricidad!E72 -> 0.0144 | F61: =Electricidad!F72 -> 0.0144 | G61: =Electricidad!G72 -> 0.0144 | H61: =Electricidad!H72 -> 0.0144
D62: Diesel | E62: =SUM(E63:E64) -> 0.58134778 | F62: =SUM(F63:F64) -> 0.64101478 | G62: =SUM(G63:G64) -> 0.64291978 | H62: =SUM(H63:H64) -> 0.59190778
D63: Diesel Turbogas | E63: =Electricidad!E76 -> 0.0504 | F63: =Electricidad!F76 -> 0.0504 | G63: =Electricidad!G76 -> 0.0504 | H63: =Electricidad!H76 -> 0.0504
D64: Diesel MCI | E64: =Electricidad!E71 -> 0.53094778 | F64: =Electricidad!F71 -> 0.59061478 | G64: =Electricidad!G71 -> 0.59251978 | H64: =Electricidad!H71 -> 0.54150778
D65: Gas Natural | E65: =SUM(E66:E68) -> 0.248922 | F65: =SUM(F66:F68) -> 0.254192 | G65: =SUM(G66:G68) -> 0.25574 | H65: =SUM(H66:H68) -> 0.277907
D66: Gas Natural Turbovapor | E66: =Electricidad!E85 -> 0.012 | F66: =Electricidad!F85 -> 0.012 | G66: =Electricidad!G85 -> 0.012 | H66: =Electricidad!H85 -> 0.012
D67: Gas Natural MCI | E67: =Electricidad!E73 -> 0.191072 | F67: =Electricidad!F73 -> 0.196342 | G67: =Electricidad!G73 -> 0.19789 | H67: =Electricidad!H73 -> 0.197257
D68: Gas Natural Turbogas | E68: =Electricidad!E77 -> 0.04585 | F68: =Electricidad!F77 -> 0.04585 | G68: =Electricidad!G77 -> 0.04585 | H68: =Electricidad!H77 -> 0.06865
E70: =SUM(E40+E41+E42+E45+E46+E47+E48+E53+E54+E55+E58+E61+E62+E65) -> 1.3063868 | F70: =SUM(F40+F41+F42+F45+F46+F47+F48+F53+F54+F55+F58+F61+F62+F65) -> 1.3670988 | G70: =SUM(G40+G41+G42+G45+G46+G47+G48+G53+G54+G55+G58+G61+G62+G65) -> 1.3720398 | H70: =SUM(H40+H41+H42+H45+H46+H47+H48+H53+H54+H55+H58+H61+H62+H65) -> 1.3765731
D73: Nueva capacidad proyectada en los actuales planes de expansión
D74: Biomasa [GW] | N74: 0.1
D75: Fuel oil [GW]
D76: Geotérmico [GW] | O76: 0.05
D77: Hidroeléctrico represa [GW]
D78: Pacífico (pequeñas) | I78: 0.049
D79: Pacífico (medianas) | J79: 0.2054
D80: Pacífico (grandes)
D81: Amazonas (pequeñas) | K81: 0.0072 | L81: 0.0146
D82: Amazonas (medianas)
D83: Amazonas (grandes) | Q83: 0.5956 | S83: 2.4
D84: Hidroeléctrico filo de agua [GW]
D85: Pacífico (pequeñas) | J85: 0.009 | K85: 0.05 | M85: -
D86: Pacífico (medianas) | O86: 0.194
D87: Pacífico (grandes)
D88: Amazonas (pequeñas) | I88: 0.03 | K88: 0.004 | L88: 0.01458
D89: Amazonas (medianas) | L89: 0.05
D90: Amazonas (grandes)
D91: Diesel [GW]
D92: Fotovoltaico [GW] | K92: 0.2
D93: Eólico [GW] | J93: 0.05 | K93: 0.11
D94: Carbón [GW]
D95: Distribuida solar [GW]
D96: Distribuida eólica [GW]
D97: Termoeléctrico (Ciclo Combinado gas natural) [GW] | K97: 0.187 | M97: 0.4
D98: ERNC [GW] | N98: 0.12 | O98: 0.32
D99: Hidroeléctricas de pasada | K99: 0.15
D100: Eólicos | K100: 0.2 | M100: 0.13
D101: Solares fotovoltaicos | K101: 0.12 | M101: 0.27
D102: Biomasa, biogás, y biogás de residuos urbanos | K102: 0.03
D103: Total [GW] | E103: =SUM(E74:E102)-E77-E84 -> 0 | F103: =SUM(F74:F102)-F77-F84 -> 0 | G103: =SUM(G74:G102)-G77-G84 -> 0 | H103: =SUM(H74:H102)-H77-H84 -> 0 | I103: =SUM(I74:I102)-I77-I84 -> 0.079 | J103: =SUM(J74:J102)-J77-J84 -> 0.2644 | K103: =SUM(K74:K102)-K77-K84 -> 1.0582 | L103: =SUM(L74:L102)-L77-L84 -> 0.07918 | ... R103: =SUM(R74:R102)-R77-R84 -> 0
D105: TotalAnnualMinCapacityInvestment
D106: Biomasa [GW] | E106: =E74+E102*0.5 -> 0 | F106: =F74+F102*0.5 -> 0 | G106: =G74+G102*0.5 -> 0 | H106: =H74+H102*0.5 -> 0 | I106: =I74+I102*0.5 -> 0 | J106: =J74+J102*0.5 -> 0 | K106: =K74+K102*0.5 -> 0.015 | L106: =L74+L102*0.5 -> 0 | ... BE106: =BE74+BE102*0.5 -> 0
D107: Eólica [GW] | E107: =E93+E100+E98*0.5 -> 0 | F107: =F93+F100+F98*0.5 -> 0 | G107: =G93+G100+G98*0.5 -> 0 | H107: =H93+H100+H98*0.5 -> 0 | I107: =I93+I100+I98*0.5 -> 0 | J107: =J93+J100+J98*0.5 -> 0.05 | K107: =K93+K100+K98*0.5 -> 0.31 | L107: =L93+L100+L98*0.5 -> 0 | ... BE107: =BE93+BE100+BE98*0.5 -> 0
D108: Hidroeléctrico represa [GW]
D109: Pacífico (pequeñas) | E109: =E78 -> 0 | F109: =F78 -> 0 | G109: =G78 -> 0 | H109: =H78 -> 0 | I109: =I78 -> 0.049 | J109: =J78 -> 0 | K109: =K78 -> 0 | L109: =L78 -> 0 | ... BE109: =BE78 -> 0
D110: Pacífico (medianas) | E110: =E79+0.5*E99 -> 0 | F110: =F79+0.5*F99 -> 0 | G110: =G79+0.5*G99 -> 0 | H110: =H79+0.5*H99 -> 0 | I110: =I79+0.5*I99 -> 0 | J110: =J79+0.5*J99 -> 0.2054 | K110: =K79+0.5*K99 -> 0.075 | L110: =L79+0.5*L99 -> 0 | ... BE110: =BE79+0.5*BE99 -> 0
D111: Pacífico (grandes) | E111: =E80 -> 0 | F111: =F80 -> 0 | G111: =G80 -> 0 | H111: =H80 -> 0 | I111: =I80 -> 0 | J111: =J80 -> 0 | K111: =K80 -> 0 | L111: =L80 -> 0 | ... BE111: =BE80 -> 0
...

Sheet Demanda_energia
D1: Ecuador | E1: 2018 | F1: 2019 | G1: 2020 | H1: 2021 | I1: 2022 | J1: 2023 | K1: 2024 | L1: 2025 | M1: 2026 | N1: 2027 | O1: 2028 | P1: 2029 | Q1: 2030 | R1: 2031 | S1: 2032 | T1: 2033 | U1: 2034 | V1: 2035 | W1: 2036 | X1: 2037 | Y1: 2038 | Z1: 2039 | AA1: 2040 | AB1: 2041 | AC1: 2042 | AD1: 2043 | AE1: 2044 | AF1: 2045 | AG1: 2046 | AH1: 2047 | AI1: 2048 | AJ1: 2049 | AK1: 2050 | AL1: 2051 | AM1: 2052 | AN1: 2053 | AO1: 2054 | AP1: 2055 | AQ1: 2056 | AR1: 2057 | AS1: 2058 | AT1: 2059 | AU1: 2060 | AV1: 2061 | AW1: 2062 | AX1: 2063 | AY1: 2064 | AZ1: 2065 | BA1: 2066 | BB1: 2067 | BC1: 2068 | BD1: 2069 | BE1: 2070
D4: Demandas de combustibles
D5: Demandas de Gasolina
A6: 1 | D6: Demanda residencial [PJ] | E6: - | F6: - | G6: - | H6: - | I6: - | J6: - | K6: - | L6: - | M6: - | N6: - | O6: - | P6: - | Q6: - | R6: - | S6: - | T6: - | U6: - | V6: - | W6: - | X6: - | Y6: - | Z6: - | AA6: - | AB6: - | AC6: - | AD6: - | AE6: - | AF6: - | AG6: - | AH6: - | AI6: - | AJ6: - | AK6: - | AL6: - | AM6: - | AN6: - | AO6: - | AP6: - | AQ6: - | AR6: - | AS6: - | AT6: - | AU6: - | AV6: - | AW6: - | AX6: - | AY6: - | AZ6: - | BA6: - | BB6: - | BC6: - | BD6: - | BE6: -
A7: 1 | C7: E5_COMPURGSL | D7: Demanda comercial y servicios públicos [PJ] | E7: ='Copia de Demandas de energía '!D7*$E$89 -> 0.099128536 | F7: ='Copia de Demandas de energía '!E7*$E$89 -> 0.12304462 | G7: ='Copia de Demandas de energía '!F7*$E$89 -> 0.034599036 | H7: ='Copia de Demandas de energía '!G7*$E$89 -> 0.23700358 | I7: 0 | J7: 0.25 | K7: 0.25 | L7: 0.26 | M7: 0.26 | N7: 0.28 | O7: 0.28 | P7: 0.29 | Q7: 0.29 | R7: 0.3 | S7: 0.31 | T7: 0.32 | U7: 0.32 | V7: 0.33 | W7: 0.34 | X7: 0.35 | Y7: 0.35 | Z7: 0.36 | AA7: 0.37 | AB7: 0.38 | AC7: 0.38 | AD7: 0.39 | AE7: 0.39 | AF7: 0.4 | AG7: 0.41 | AH7: 0.42 | AI7: 0.42 | AJ7: 0.43 | AK7: 0.43 | AL7: 0.44 | AM7: 0.45 | AN7: 0.45 | AO7: 0.46 | AP7: 0.47 | AQ7: 0.47 | AR7: 0.48 | AS7: 0.48 | AT7: 0.49 | AU7: 0.5 | AV7: 0.5 | AW7: 0.51 | AX7: 0.51 | AY7: 0.52 | AZ7: 0.53 | BA7: 0.53 | BB7: 0.54 | BC7: 0.54 | BD7: 0.55 | BE7: 0.55
A8: 1,2 | C8: E5_INDPURGSL | D8: Demanda Industrial [PJ] | E8: ='Copia de Demandas de energía '!D8*$E$89 -> 0.61379802 | F8: ='Copia de Demandas de energía '!E8*$E$89 -> 0.85415239 | G8: ='Copia de Demandas de energía '!F8*$E$89 -> 0.7482621 | H8: ='Copia de Demandas de energía '!G8*$E$89 -> 1.0382512 | I8: 0.90639122 | J8: 1.1 | K8: 1.14 | L8: 1.16 | M8: 1.2 | N8: 1.23 | O8: 1.27 | P8: 1.29 | Q8: 1.33 | R8: 1.36 | S8: 1.4 | T8: 1.43 | U8: 1.47 | V8: 1.49 | W8: 1.54 | X8: 1.57 | Y8: 1.61 | Z8: 1.64 | AA8: 1.68 | AB8: 1.71 | AC8: 1.76 | AD8: 1.78 | AE8: 1.82 | AF8: 1.85 | AG8: 1.89 | AH8: 1.92 | AI8: 1.96 | AJ8: 1.99 | AK8: 2.03 | AL8: 2.07 | AM8: 2.1 | AN8: 2.14 | AO8: 2.18 | AP8: 2.22 | AQ8: 2.26 | AR8: 2.31 | AS8: 2.35 | AT8: 2.39 | AU8: 2.44 | AV8: 2.48 | AW8: 2.53 | AX8: 2.57 | AY8: 2.62 | AZ8: 2.67 | BA8: 2.72 | BB8: 2.77 | BC8: 2.82 | BD8: 2.87 | BE8: 2.93
A9: 1 | C9: E5_CONPURGSL | D9: Demanda construcción y otros [PJ] | E9: ='Copia de Demandas de energía '!D9*$E$89 -> 34.952289 | F9: ='Copia de Demandas de energía '!E9*$E$89 -> 32.606013 | G9: ='Copia de Demandas de energía '!F9*$E$89 -> 25.107181 | H9: ='Copia de Demandas de energía '!G9*$E$89 -> 20.302985 | I9: 17.793157 | J9: 22.1825 | K9: 22.93 | L9: 23.62 | M9: 24.3475 | N9: 25.14 | O9: 25.925 | P9: 26.6075 | Q9: 27.3325 | R9: 28.115 | S9: 28.9025 | T9: 29.6775 | U9: 30.425 | V9: 31.1675 | W9: 31.93 | X9: 32.69 | Y9: 33.4675 | Z9: 34.28 | AA9: 35.085 | AB9: 35.89 | AC9: 36.6575 | AD9: 37.3875 | AE9: 38.135 | AF9: 38.92 | AG9: 39.7275 | AH9: 40.5025 | AI9: 41.2375 | AJ9: 41.985 | AK9: 42.8675 | AL9: 43.83 | AM9: 44.7325 | AN9: 45.6425 | AO9: 46.565 | AP9: 47.5075 | AQ9: 48.47 | AR9: 49.4475 | AS9: 50.44 | AT9: 51.4575 | AU9: 52.505 | AV9: 53.5825 | AW9: 54.6825 | AX9: 55.795 | AY9: 56.925 | AZ9: 58.0775 | BA9: 59.255 | BB9: 60.4575 | BC9: 61.685 | BD9: 62.9375 | BE9: 64.21
A10: 1 | C10: E5_AGRPURGSL | D10: Demanda Agro, pesca y minería [PJ] | E10: ='Copia de Demandas de energía '!D10*$E$89 -> 4.7630758 | F10: ='Copia de Demandas de energía '!E10*$E$89 -> 5.2140193 | G10: ='Copia de Demandas de energía '!F10*$E$89 -> 4.8432446 | H10: ='Copia de Demandas de energía '!G10*$E$89 -> 5.4102096 | I10: 5.3645578 | J10: 5.76 | K10: 5.94 | L10: 6.08 | M10: 6.2 | N10: 6.36 | O10: 6.49 | P10: 6.58 | Q10: 6.67 | R10: 6.81 | S10: 6.9 | T10: 7.02 | U10: 7.1 | V10: 7.19 | W10: 7.3 | X10: 7.4 | Y10: 7.51 | Z10: 7.65 | AA10: 7.78 | AB10: 7.93 | AC10: 8.08 | AD10: 8.22 | AE10: 8.4 | AF10: 8.57 | AG10: 8.78 | AH10: 8.97 | AI10: 9.16 | AJ10: 9.37 | AK10: 9.57 | AL10: 9.75 | AM10: 9.94 | AN10: 10.13 | AO10: 10.33 | AP10: 10.54 | AQ10: 10.76 | AR10: 10.98 | AS10: 11.2 | AT10: 11.44 | AU10: 11.67 | AV10: 11.92 | AW10: 12.16 | AX10: 12.42 | AY10: 12.67 | AZ10: 12.93 | BA10: 13.19 | BB10: 13.46 | BC10: 13.73 | BD10: 14.01 | BE10: 14.3
A11: 1 | D11: Demanda transporte [PJ]
A12: 1 | D12: Terrestre carga | E12: ='Copia de Demandas de energía '!D12*$E$89 -> 62.130723 | F12: ='Copia de Demandas de energía '!E12*$E$89 -> 63.134677 | G12: ='Copia de Demandas de energía '!F12*$E$89 -> 49.270364 | H12: ='Copia de Demandas de energía '!G12*$E$89 -> 64.154308 | I12: 63.04 | J12: 67.85 | K12: 67.08 | L12: 71.69 | M12: 70.78 | N12: 75.65 | O12: 75.39 | P12: 79.48 | Q12: 79.12 | R12: 83.82 | S12: 83.85 | T12: 88.2 | U12: 88.5 | V12: 92.27 | W12: 93.08 | X12: 96.65 | Y12: 97.57 | Z12: 101.29 | AA12: 102.44 | AB12: 105.86 | AC12: 107.24 | AD12: 110.03 | AE12: 111.61 | AF12: 114.47 | AG12: 116.37 | AH12: 119.18 | AI12: 120.72 | AJ12: 123.49 | AK12: 125.21 | AL12: 127.65 | AM12: 130.23 | AN12: 132.7 | AO12: 135.3 | AP12: 137.87 | AQ12: 140.55 | AR12: 143.19 | AS12: 145.91 | AT12: 148.62 | AU12: 151.46 | AV12: 154.29 | AW12: 157.26 | AX12: 160.26 | AY12: 163.32 | AZ12: 166.44 | BA12: 169.6 | BB12: 172.83 | BC12: 176.11 | BD12: 179.46 | BE12: 182.87
A13: 1,2 | D13: Terrestre pasajeros | E13: ='Copia de Demandas de energía '!D13*$E$89 -> 58.736211 | F13: ='Copia de Demandas de energía '!E13*$E$89 -> 59.685002 | G13: ='Copia de Demandas de energía '!F13*$E$89 -> 46.916968 | H13: ='Copia de Demandas de energía '!G13*$E$89 -> 61.090189 | I13: 61.91 | J13: 62.73 | K13: 63.53 | L13: 64.33 | M13: 65.12 | N13: 65.9 | O13: 66.68 | P13: 67.44 | Q13: 68.19 | R13: 68.93 | S13: 69.66 | T13: 70.38 | U13: 71.09 | V13: 71.78 | W13: 72.46 | X13: 73.13 | Y13: 73.78 | Z13: 74.42 | AA13: 75.05 | AB13: 75.66 | AC13: 76.25 | AD13: 76.83 | AE13: 77.4 | AF13: 77.95 | AG13: 78.48 | AH13: 79 | AI13: 79.5 | AJ13: 79.98 | AK13: 80.45 | AL13: 80.91 | AM13: 81.34 | AN13: 81.76 | AO13: 82.17 | AP13: 82.55 | AQ13: 82.92 | AR13: 83.27 | AS13: 83.61 | AT13: 83.92 | AU13: 84.22 | AV13: 84.49 | AW13: 84.75 | AX13: 84.99 | AY13: 85.21 | AZ13: 85.41 | BA13: 85.59 | BB13: 85.75 | BC13: 85.9 | BD13: 86.02 | BE13: 86.12
A14: 1 | C14: E5_SHITRNPURGSL | D14: Marítimo | E14: ='Copia de Demandas de energía '!D14*$E$89 -> 0.030774744 | F14: ='Copia de Demandas de energía '!E14*$E$89 -> 0.0034839332 | G14: ='Copia de Demandas de energía '!F14*$E$89 -> 0.0098711442 | H14: ='Copia de Demandas de energía '!G14*$E$89 -> 0.019742288 | I14: 0.02 | J14: 0.02 | K14: 0.02 | L14: 0.02 | M14: 0.02 | N14: 0.02 | O14: 0.02 | P14: 0.02 | Q14: 0.03 | R14: 0.03 | S14: 0.03 | T14: 0.03 | U14: 0.03 | V14: 0.03 | W14: 0.03 | X14: 0.03 | Y14: 0.03 | Z14: 0.03 | AA14: 0.03 | AB14: 0.03 | AC14: 0.03 | AD14: 0.03 | AE14: 0.04 | AF14: 0.04 | AG14: 0.04 | AH14: 0.04 | AI14: 0.04 | AJ14: 0.04 | AK14: 0.04 | AL14: 0.04 | AM14: 0.04 | AN14: 0.04 | AO14: 0.04 | AP14: 0.04 | AQ14: 0.04 | AR14: 0.04 | AS14: 0.05 | AT14: 0.05 | AU14: 0.05 | AV14: 0.05 | AW14: 0.05 | AX14: 0.05 | AY14: 0.05 | AZ14: 0.05 | BA14: 0.05 | BB14: 0.05 | BC14: 0.05 | BD14: 0.05 | BE14: 0.05
A15: 1 | C15: E5_AERTRNPURGSL | D15: Aéreo | E15: 4.7630758 | F15: 5.2140193 | G15: 4.8432446 | H15: 5.4102096 | I15: 5.3645578 | J15: 5.76 | K15: 5.94 | L15: 6.08 | M15: 6.2 | N15: 6.36 | O15: 6.49 | P15: 6.58 | Q15: 6.67 | R15: 6.81 | S15: 6.9 | T15: 7.02 | U15: 7.1 | V15: 7.19 | W15: 7.3 | X15: 7.4 | Y15: 7.51 | Z15: 7.65 | AA15: 7.78 | AB15: 7.93 | AC15: 8.08 | AD15: 8.22 | AE15: 8.4 | AF15: 8.57 | AG15: 8.78 | AH15: 8.97 | AI15: 9.16 | AJ15: 9.37 | AK15: 9.57 | AL15: 9.75 | AM15: 9.94 | AN15: 10.13 | AO15: 10.33 | AP15: 10.54 | AQ15: 10.76 | AR15: 10.98 | AS15: 11.2 | AT15: 11.44 | AU15: 11.67 | AV15: 11.92 | AW15: 12.16 | AX15: 12.42 | AY15: 12.67 | AZ15: 12.93 | BA15: 13.19 | BB15: 13.46 | BC15: 13.73 | BD15: 14.01 | BE15: 14.3
D16: Total [PJ] | E16: =SUM(E6:E15) -> 166.08908 | F16: =SUM(F6:F15) -> 166.83441 | G16: =SUM(G6:G15) -> 131.77373 | H16: =SUM(H6:H15) -> 157.6629 | I16: =SUM(I6:I15) -> 154.39866 | J16: =SUM(J6:J15) -> 165.6525 | K16: =SUM(K6:K15) -> 166.83 | L16: =SUM(L6:L15) -> 173.24 | ... BE16: =SUM(BE6:BE15) -> 365.33
D18: Demandas de Diesel
D19: Demanda residencial [PJ] | E19: - | F19: - | G19: - | H19: -
C20: E5_COMPURDSL | D20: Demanda comercial y servicios públicos [PJ] | E20: ='Copia de Demandas de energía '!D20*$E$89 -> 5.736839 | F20: ='Copia de Demandas de energía '!E20*$E$89 -> 4.7138773 | G20: ='Copia de Demandas de energía '!F20*$E$89 -> 4.5998941 | H20: ='Copia de Demandas de energía '!G20*$E$89 -> 4.3899412 | I20: 6.0873467 | J20: 4.58 | K20: 4.7 | L20: 4.8125 | M20: 4.925 | N20: 5.055 | O20: 5.1825 | P20: 5.295 | Q20: 5.42 | R20: 5.565 | S20: 5.71 | T20: 5.8525 | U20: 5.99 | V20: 6.125 | W20: 6.2625 | X20: 6.3975 | Y20: 6.535 | Z20: 6.6775 | AA20: 6.8175 | AB20: 6.9525 | AC20: 7.08 | AD20: 7.2 | AE20: 7.32 | AF20: 7.445 | AG20: 7.575 | AH20: 7.695 | AI20: 7.805 | AJ20: 7.9175 | AK20: 8.0325 | AL20: 8.155 | AM20: 8.2775 | AN20: 8.3925 | AO20: 8.51 | AP20: 8.63 | AQ20: 8.7475 | AR20: 8.8625 | AS20: 8.9775 | AT20: 9.0925 | AU20: 9.205 | AV20: 9.3125 | AW20: 9.42 | AX20: 9.53 | AY20: 9.6375 | AZ20: 9.7425 | BA20: 9.8475 | BB20: 9.95 | BC20: 10.05 | BD20: 10.1475 | BE20: 10.24
A21: 2 | C21: E5_INDPURDSL | D21: Demanda Industrial [PJ] | E21: ='Copia de Demandas de energía '!D21*$E$89 -> 25.584823 | F21: ='Copia de Demandas de energía '!E21*$E$89 -> 22.023941 | G21: ='Copia de Demandas de energía '!F21*$E$89 -> 21.491394 | H21: ='Copia de Demandas de energía '!G21*$E$89 -> 20.510462 | I21: 28.440349 | J21: 21.75 | K21: 22.61 | L21: 22.99 | M21: 23.72 | N21: 24.24 | O21: 25.12 | P21: 25.42 | Q21: 26.21 | R21: 26.8 | S21: 27.64 | T21: 28.22 | U21: 29.04 | V21: 29.53 | W21: 30.42 | X21: 30.93 | Y21: 31.77 | Z21: 32.4 | AA21: 33.23 | AB21: 33.84 | AC21: 34.67 | AD21: 35.14 | AE21: 35.97 | AF21: 36.52 | AG21: 37.4 | AH21: 37.98 | AI21: 38.69 | AJ21: 39.29 | AK21: 40.02 | AL21: 40.8 | AM21: 41.56 | AN21: 42.35 | AO21: 43.12 | AP21: 43.93 | AQ21: 44.74 | AR21: 45.57 | AS21: 46.4 | AT21: 47.25 | AU21: 48.12 | AV21: 49.01 | AW21: 49.93 | AX21: 50.85 | AY21: 51.79 | AZ21: 52.75 | BA21: 53.72 | BB21: 54.72 | BC21: 55.73 | BD21: 56.76 | BE21: 57.81
A22: 2 | C22: E5_CONPURDSL | D22: Demanda construcción y otros [PJ] | E22: ='Copia de Demandas de energía '!D22*$E$89 -> 2.5489151 | F22: ='Copia de Demandas de energía '!E22*$E$89 -> 2.9144162 | G22: ='Copia de Demandas de energía '!F22*$E$89 -> 0.67387279 | H22: ='Copia de Demandas de energía '!G22*$E$89 -> 3.1559712 | I22: 5.8671401 | J22: 3.445 | K22: 3.5625 | L22: 3.67 | M22: 3.7825 | N22: 3.905 | O22: 4.0275 | P22: 4.135 | Q22: 4.2475 | R22: 4.3675 | S22: 4.49 | T22: 4.6125 | U22: 4.73 | V22: 4.845 | W22: 4.9625 | X22: 5.08 | Y22: 5.2025 | Z22: 5.33 | AA22: 5.4525 | AB22: 5.5775 | AC22: 5.7 | AD22: 5.815 | AE22: 5.93 | AF22: 6.05 | AG22: 6.175 | AH22: 6.295 | AI22: 6.41 | AJ22: 6.5275 | AK22: 6.665 | AL22: 6.815 | AM22: 6.955 | AN22: 7.095 | AO22: 7.2375 | AP22: 7.385 | AQ22: 7.535 | AR22: 7.6875 | AS22: 7.8425 | AT22: 8 | AU22: 8.1625 | AV22: 8.33 | AW22: 8.5 | AX22: 8.6725 | AY22: 8.85 | AZ22: 9.03 | BA22: 9.2125 | BB22: 9.4 | BC22: 9.59 | BD22: 9.7825 | BE22: 9.98
A23: 2 | D23: Demanda Agro, pesca y minería [PJ] | E23: - | F23: - | G23: - | H23: -
D24: Demanda transporte [PJ]
A25: 2 | D25: Terrestre carga | E25: ='Copia de Demandas de energía '!D25*$E$89 -> 119.77472 | F25: ='Copia de Demandas de energía '!E25*$E$89 -> 121.70947 | G25: ='Copia de Demandas de energía '!F25*$E$89 -> 103.25101 | H25: ='Copia de Demandas de energía '!G25*$E$89 -> 116.77854 | I25: 114.74 | J25: 123.51 | K25: 122.11 | L25: 130.5 | M25: 128.83 | N25: 137.71 | O25: 137.23 | P25: 144.67 | Q25: 144.02 | R25: 152.57 | S25: 152.63 | T25: 160.56 | U25: 161.1 | V25: 167.96 | W25: 169.43 | X25: 175.92 | Y25: 177.61 | Z25: 184.38 | AA25: 186.48 | AB25: 192.7 | AC25: 195.2 | AD25: 200.29 | AE25: 203.16 | AF25: 208.36 | AG25: 211.83 | AH25: 216.95 | AI25: 219.74 | AJ25: 224.78 | AK25: 227.91 | AL25: 232.35 | AM25: 237.05 | AN25: 241.55 | AO25: 246.29 | AP25: 250.97 | AQ25: 255.83 | AR25: 260.64 | AS25: 265.6 | AT25: 270.54 | AU25: 275.7 | AV25: 280.86 | AW25: 286.25 | AX25: 291.72 | AY25: 297.29 | AZ25: 302.97 | BA25: 308.73 | BB25: 314.59 | BC25: 320.57 | BD25: 326.66 | BE25: 332.87
A26: 2 | D26: Terrestre pasajeros | E26: ='Copia de Demandas de energía '!D26*$E$89 -> 8.5942826 | F26: ='Copia de Demandas de energía '!E26*$E$89 -> 8.7330593 | G26: ='Copia de Demandas de energía '!F26*$E$89 -> 7.408584 | H26: ='Copia de Demandas de energía '!G26*$E$89 -> 8.3794401 | I26: 8.49 | J26: 8.6 | K26: 8.71 | L26: 8.82 | M26: 8.93 | N26: 9.04 | O26: 9.15 | P26: 9.25 | Q26: 9.35 | R26: 9.46 | S26: 9.56 | T26: 9.65 | U26: 9.75 | V26: 9.85 | W26: 9.94 | X26: 10.03 | Y26: 10.12 | Z26: 10.21 | AA26: 10.29 | AB26: 10.38 | AC26: 10.46 | AD26: 10.54 | AE26: 10.62 | AF26: 10.69 | AG26: 10.76 | AH26: 10.84 | AI26: 10.9 | AJ26: 10.97 | AK26: 11.04 | AL26: 11.1 | AM26: 11.16 | AN26: 11.22 | AO26: 11.27 | AP26: 11.32 | AQ26: 11.37 | AR26: 11.42 | AS26: 11.47 | AT26: 11.51 | AU26: 11.55 | AV26: 11.59 | AW26: 11.62 | AX26: 11.66 | AY26: 11.69 | AZ26: 11.72 | BA26: 11.74 | BB26: 11.76 | BC26: 11.78 | BD26: 11.8 | BE26: 11.81
C27: E5_SHITRNPURDSL | D27: Marítimo | E27: ='Copia de Demandas de energía '!D27*$E$89 -> 11.47956 | F27: ='Copia de Demandas de energía '!E27*$E$89 -> 11.546335 | G27: ='Copia de Demandas de energía '!F27*$E$89 -> 9.8560471 | H27: ='Copia de Demandas de energía '!G27*$E$89 -> 11.926665 | I27: 12.25 | J27: 12.63 | K27: 13.01 | L27: 13.36 | M27: 13.67 | N27: 14.1 | O27: 14.5 | P27: 14.82 | Q27: 15.17 | R27: 15.65 | S27: 16.04 | T27: 16.5 | U27: 16.9 | V27: 17.29 | W27: 17.74 | X27: 18.14 | Y27: 18.56 | Z27: 19.03 | AA27: 19.46 | AB27: 19.91 | AC27: 20.35 | AD27: 20.71 | AE27: 21.16 | AF27: 21.55 | AG27: 22.05 | AH27: 22.45 | AI27: 22.86 | AJ27: 23.27 | AK27: 23.69 | AL27: 24.17 | AM27: 24.61 | AN27: 25.04 | AO27: 25.49 | AP27: 25.94 | AQ27: 26.41 | AR27: 26.86 | AS27: 27.31 | AT27: 27.77 | AU27: 28.24 | AV27: 28.7 | AW27: 29.16 | AX27: 29.63 | AY27: 30.09 | AZ27: 30.56 | BA27: 31.03 | BB27: 31.49 | BC27: 31.96 | BD27: 32.43 | BE27: 32.9
D28: Aéreo | E28: - | F28: - | G28: - | H28: - | I28: - | J28: - | K28: - | L28: - | M28: - | N28: - | O28: - | P28: - | Q28: - | R28: - | S28: - | T28: - | U28: - | V28: - | W28: - | X28: - | Y28: - | Z28: - | AA28: - | AB28: - | AC28: - | AD28: - | AE28: - | AF28: - | AG28: - | AH28: - | AI28: - | AJ28: - | AK28: - | AL28: - | AM28: - | AN28: - | AO28: - | AP28: - | AQ28: - | AR28: - | AS28: - | AT28: - | AU28: - | AV28: - | AW28: - | AX28: - | AY28: - | AZ28: - | BA28: - | BB28: - | BC28: - | BD28: - | BE28: -
D29: Total [PJ] | E29: =SUM(E19:E28) -> 173.71914 | F29: =SUM(F19:F28) -> 171.64109 | G29: =SUM(G19:G28) -> 147.2808 | H29: =SUM(H19:H28) -> 165.14102 | I29: =SUM(I19:I28) -> 175.87484 | J29: =SUM(J19:J28) -> 174.515 | K29: =SUM(K19:K28) -> 174.7025 | L29: =SUM(L19:L28) -> 184.1525 | ... BE29: =SUM(BE19:BE28) -> 455.61
D31: Demandas de GLP
A32: 2 | C32: E5_RESLPG | D32: Demanda residencial [PJ] | E32: ='Copia de Demandas de energía '!D32*$E$89 -> 37.188178 | F32: ='Copia de Demandas de energía '!E32*$E$89 -> 38.367604 | G32: ='Copia de Demandas de energía '!F32*$E$89 -> 39.136215 | H32: ='Copia de Demandas de energía '!G32*$E$89 -> 39.917656 | I32: 41.30297 | J32: 40.99 | K32: 41.51 | L32: 42.04 | M32: 42.55 | N32: 43.06 | O32: 43.57 | P32: 44.07 | Q32: 44.56 | R32: 45.04 | S32: 45.52 | T32: 45.99 | U32: 46.45 | V32: 46.9 | W32: 47.35 | X32: 47.78 | Y32: 48.21 | Z32: 48.63 | AA32: 49.04 | AB32: 49.44 | AC32: 49.82 | AD32: 50.2 | AE32: 50.57 | AF32: 50.93 | AG32: 51.28 | AH32: 51.62 | AI32: 51.95 | AJ32: 52.26 | AK32: 52.57 | AL32: 52.87 | AM32: 53.15 | AN32: 53.43 | AO32: 53.69 | AP32: 53.94 | AQ32: 54.18 | AR32: 54.41 | AS32: 54.63 | AT32: 54.83 | AU32: 55.03 | AV32: 55.21 | AW32: 55.38 | AX32: 55.53 | AY32: 55.68 | AZ32: 55.81 | BA32: 55.93 | BB32: 56.03 | BC32: 56.13 | BD32: 56.21 | BE32: 56.27
C33: E5_COMLPG | D33: Demanda comercial y servicios públicos [PJ] | E33: ='Copia de Demandas de energía '!D33*$E$89 -> 2.3911178 | F33: ='Copia de Demandas de energía '!E33*$E$89 -> 2.3977572 | G33: ='Copia de Demandas de energía '!F33*$E$89 -> 2.2406901 | H33: ='Copia de Demandas de energía '!G33*$E$89 -> 2.3810968 | I33: 2.6552615 | J33: 2.4875 | K33: 2.5525 | L33: 2.6125 | M33: 2.6725 | N33: 2.7425 | O33: 2.81 | P33: 2.87 | Q33: 2.9375 | R33: 3.015 | S33: 3.0925 | T33: 3.17 | U33: 3.245 | V33: 3.3175 | W33: 3.3925 | X33: 3.4675 | Y33: 3.545 | Z33: 3.625 | AA33: 3.7 | AB33: 3.7725 | AC33: 3.8425 | AD33: 3.9075 | AE33: 3.9725 | AF33: 4.04 | AG33: 4.11 | AH33: 4.175 | AI33: 4.235 | AJ33: 4.295 | AK33: 4.3575 | AL33: 4.425 | AM33: 4.49 | AN33: 4.5525 | AO33: 4.6175 | AP33: 4.6825 | AQ33: 4.7475 | AR33: 4.81 | AS33: 4.87 | AT33: 4.93 | AU33: 4.99 | AV33: 5.05 | AW33: 5.11 | AX33: 5.17 | AY33: 5.23 | AZ33: 5.2875 | BA33: 5.3425 | BB33: 5.3975 | BC33: 5.45 | BD33: 5.5025 | BE33: 5.56
A34: 2 | C34: E5_INDLPG | D34: Demanda Industrial [PJ] | E34: ='Copia de Demandas de energía '!D34*$E$89 -> 3.9680445 | F34: ='Copia de Demandas de energía '!E34*$E$89 -> 4.1453384 | G34: ='Copia de Demandas de energía '!F34*$E$89 -> 3.6902606 | H34: ='Copia de Demandas de energía '!G34*$E$89 -> 4.1259798 | I34: 4.2501614 | J34: 4.37 | K34: 4.55 | L34: 4.63 | M34: 4.77 | N34: 4.88 | O34: 5.05 | P34: 5.11 | Q34: 5.27 | R34: 5.39 | S34: 5.56 | T34: 5.68 | U34: 5.84 | V34: 5.94 | W34: 6.12 | X34: 6.22 | Y34: 6.39 | Z34: 6.52 | AA34: 6.69 | AB34: 6.81 | AC34: 6.97 | AD34: 7.07 | AE34: 7.24 | AF34: 7.35 | AG34: 7.52 | AH34: 7.64 | AI34: 7.78 | AJ34: 7.9 | AK34: 8.05 | AL34: 8.21 | AM34: 8.36 | AN34: 8.52 | AO34: 8.67 | AP34: 8.84 | AQ34: 9 | AR34: 9.17 | AS34: 9.33 | AT34: 9.5 | AU34: 9.68 | AV34: 9.86 | AW34: 10.04 | AX34: 10.23 | AY34: 10.42 | AZ34: 10.61 | BA34: 10.81 | BB34: 11.01 | BC34: 11.21 | BD34: 11.42 | BE34: 11.63
C35: E5_CONLPG | D35: Demanda construcción y otros [PJ] | E35: ='Copia de Demandas de energía '!D35*$E$89 -> 5.77117 | F35: ='Copia de Demandas de energía '!E35*$E$89 -> 7.8918634 | G35: ='Copia de Demandas de energía '!F35*$E$89 -> 8.4675547 | H35: ='Copia de Demandas de energía '!G35*$E$89 -> 8.6230478 | I35: 9.8256294 | J35: 9.42 | K35: 9.7375 | L35: 10.0325 | M35: 10.3425 | N35: 10.6775 | O35: 11.01 | P35: 11.3 | Q35: 11.61 | R35: 11.945 | S35: 12.28 | T35: 12.6075 | U35: 12.9225 | V35: 13.2375 | W35: 13.5625 | X35: 13.885 | Y35: 14.215 | Z35: 14.5625 | AA35: 14.905 | AB35: 15.245 | AC35: 15.57 | AD35: 15.88 | AE35: 16.1975 | AF35: 16.53 | AG35: 16.8725 | AH35: 17.2025 | AI35: 17.515 | AJ35: 17.8325 | AK35: 18.21 | AL35: 18.62 | AM35: 19 | AN35: 19.385 | AO35: 19.7775 | AP35: 20.1775 | AQ35: 20.5875 | AR35: 21.005 | AS35: 21.4275 | AT35: 21.8575 | AU35: 22.3 | AV35: 22.7575 | AW35: 23.2225 | AX35: 23.6925 | AY35: 24.1725 | AZ35: 24.6625 | BA35: 25.1625 | BB35: 25.675 | BC35: 26.2 | BD35: 26.7325 | BE35: 27.27
A36: 2 | C36: E5_AGRLPG | D36: Demanda Agro, pesca y minería [PJ] | E36: ='Copia de Demandas de energía '!D36*$E$89 -> 1.0525426 | F36: ='Copia de Demandas de energía '!E36*$E$89 -> 1.1384701 | G36: ='Copia de Demandas de energía '!F36*$E$89 -> 0.9331363 | H36: ='Copia de Demandas de energía '!G36*$E$89 -> 1.0966181 | I36: 1.0278244 | J36: 1.17 | K36: 1.2 | L36: 1.23 | M36: 1.26 | N36: 1.29 | O36: 1.32 | P36: 1.33 | Q36: 1.35 | R36: 1.38 | S36: 1.4 | T36: 1.42 | U36: 1.44 | V36: 1.46 | W36: 1.48 | X36: 1.5 | Y36: 1.52 | Z36: 1.55 | AA36: 1.58 | AB36: 1.61 | AC36: 1.64 | AD36: 1.67 | AE36: 1.7 | AF36: 1.74 | AG36: 1.78 | AH36: 1.82 | AI36: 1.86 | AJ36: 1.9 | AK36: 1.94 | AL36: 1.98 | AM36: 2.01 | AN36: 2.05 | AO36: 2.09 | AP36: 2.14 | AQ36: 2.18 | AR36: 2.23 | AS36: 2.27 | AT36: 2.32 | AU36: 2.37 | AV36: 2.42 | AW36: 2.47 | AX36: 2.52 | AY36: 2.57 | AZ36: 2.62 | BA36: 2.67 | BB36: 2.73 | BC36: 2.78 | BD36: 2.84 | BE36: 2.9
D37: Demanda transporte (terrestre pasajeros) [PJ]
D38: Terrestre carga | E38: - | F38: - | G38: - | H38: - | I38: - | J38: - | K38: - | L38: - | M38: - | N38: - | O38: - | P38: - | Q38: - | R38: - | S38: - | T38: - | U38: - | V38: - | W38: - | X38: - | Y38: - | Z38: - | AA38: - | AB38: - | AC38: - | AD38: - | AE38: - | AF38: - | AG38: - | AH38: - | AI38: - | AJ38: - | AK38: - | AL38: - | AM38: - | AN38: - | AO38: - | AP38: - | AQ38: - | AR38: - | AS38: - | AT38: - | AU38: - | AV38: - | AW38: - | AX38: - | AY38: - | AZ38: - | BA38: - | BB38: - | BC38: - | BD38: - | BE38: -
A39: 2 | D39: Terrestre pasajeros | E39: ='Copia de Demandas de energía '!D39*$E$89 -> 0.25392067 | F39: ='Copia de Demandas de energía '!E39*$E$89 -> 0.28806321 | G39: ='Copia de Demandas de energía '!F39*$E$89 -> 0.3147153 | H39: ='Copia de Demandas de energía '!G39*$E$89 -> 0.55202922 | I39: 0.56 | J39: 0.57 | K39: 0.57 | L39: 0.58 | M39: 0.59 | N39: 0.6 | O39: 0.6 | P39: 0.61 | Q39: 0.62 | R39: 0.62 | S39: 0.63 | T39: 0.64 | U39: 0.64 | V39: 0.65 | W39: 0.65 | X39: 0.66 | Y39: 0.67 | Z39: 0.67 | AA39: 0.68 | AB39: 0.68 | AC39: 0.69 | AD39: 0.69 | AE39: 0.7 | AF39: 0.7 | AG39: 0.71 | AH39: 0.71 | AI39: 0.72 | AJ39: 0.72 | AK39: 0.73 | AL39: 0.73 | AM39: 0.74 | AN39: 0.74 | AO39: 0.74 | AP39: 0.75 | AQ39: 0.75 | AR39: 0.75 | AS39: 0.76 | AT39: 0.76 | AU39: 0.76 | AV39: 0.76 | AW39: 0.77 | AX39: 0.77 | AY39: 0.77 | AZ39: 0.77 | BA39: 0.77 | BB39: 0.77 | BC39: 0.78 | BD39: 0.78 | BE39: 0.78
D40: Marítimo | E40: - | F40: - | G40: - | H40: -
D41: Aéreo | E41: - | F41: - | G41: - | H41: -
D42: Total [PJ] | E42: =SUM(E32:E41) -> 50.624973 | F42: =SUM(F32:F41) -> 54.229097 | G42: =SUM(G32:G41) -> 54.782572 | H42: =SUM(H32:H41) -> 56.696428 | I42: =SUM(I32:I41) -> 59.621846 | J42: =SUM(J32:J41) -> 59.0075 | K42: =SUM(K32:K41) -> 60.12 | L42: =SUM(L32:L41) -> 61.125 | ... BE42: =SUM(BE32:BE41) -> 104.41
D44: Demandas de Kerosene/Jet Fuel
D45: Demanda residencial [PJ] | E45: - | F45: - | G45: - | H45: - | I45: - | J45: - | K45: - | L45: - | M45: - | N45: - | O45: - | P45: - | Q45: - | R45: - | S45: - | T45: - | U45: - | V45: - | W45: - | X45: - | Y45: - | Z45: - | AA45: - | AB45: - | AC45: - | AD45: - | AE45: - | AF45: - | AG45: - | AH45: - | AI45: - | AJ45: - | AK45: -
D46: Demanda comercial y servicios públicos [PJ] | E46: - | F46: - | G46: - | H46: - | I46: - | J46: - | K46: - | L46: - | M46: - | N46: - | O46: - | P46: - | Q46: - | R46: - | S46: - | T46: - | U46: - | V46: - | W46: - | X46: - | Y46: - | Z46: - | AA46: - | AB46: - | AC46: - | AD46: - | AE46: - | AF46: - | AG46: - | AH46: - | AI46: - | AJ46: - | AK46: -
A47: 2 | D47: Demanda Industrial [PJ] | E47: - | F47: - | G47: - | H47: - | I47: - | J47: - | K47: - | L47: - | M47: - | N47: - | O47: - | P47: - | Q47: - | R47: - | S47: - | T47: - | U47: - | V47: - | W47: - | X47: - | Y47: - | Z47: - | AA47: - | AB47: - | AC47: - | AD47: - | AE47: - | AF47: - | AG47: - | AH47: - | AI47: - | AJ47: - | AK47: -
C48: E5_CONKJF | D48: Demanda construcción y otros [PJ] | E48: ='Copia de Demandas de energía '!D48*$E$89 -> 1.3684501 | F48: ='Copia de Demandas de energía '!E48*$E$89 -> 1.0504393 | G48: ='Copia de Demandas de energía '!F48*$E$89 -> 1.599827 | H48: ='Copia de Demandas de energía '!G48*$E$89 -> 1.8325867 | I48: 2.4914138 | J48: 2.0025 | K48: 2.07 | L48: 2.1325 | M48: 2.1975 | N48: 2.2675 | O48: 2.3375 | P48: 2.4 | Q48: 2.4675 | R48: 2.5375 | S48: 2.6075 | T48: 2.6775 | U48: 2.745 | V48: 2.8125 | W48: 2.88 | X48: 2.9475 | Y48: 3.02 | Z48: 3.095 | AA48: 3.1675 | AB48: 3.24 | AC48: 3.3075 | AD48: 3.3725 | AE48: 3.4425 | AF48: 3.515 | AG48: 3.5875 | AH48: 3.6575 | AI48: 3.7225 | AJ48: 3.7875 | AK48: 3.8675 | AL48: 3.9575 | AM48: 4.04 | AN48: 4.12 | AO48: 4.2025 | AP48: 4.2875 | AQ48: 4.3725 | AR48: 4.46 | AS48: 4.5525 | AT48: 4.6475 | AU48: 4.7425 | AV48: 4.84 | AW48: 4.94 | AX48: 5.04 | AY48: 5.14 | AZ48: 5.2425 | BA48: 5.35 | BB48: 5.46 | BC48: 5.57 | BD48: 5.6825 | BE48: 5.8
D49: Demanda Agro, pesca y minería [PJ] | E49: - | F49: - | G49: - | H49: -
A50: 2 | D50: Demanda transporte [PJ]
D51: Terrestre carga | E51: - | F51: - | G51: - | H51: - | I51: - | J51: - | K51: - | L51: - | M51: - | N51: - | O51: - | P51: - | Q51: - | R51: - | S51: - | T51: - | U51: - | V51: - | W51: - | X51: - | Y51: - | Z51: - | AA51: - | AB51: - | AC51: - | AD51: - | AE51: - | AF51: - | AG51: - | AH51: - | AI51: - | AJ51: - | AK51: - | AL51: - | AM51: - | AN51: - | AO51: - | AP51: - | AQ51: - | AR51: - | AS51: - | AT51: - | AU51: - | AV51: - | AW51: - | AX51: - | AY51: - | AZ51: - | BA51: - | BB51: - | BC51: - | BD51: - | BE51: -
D52: Terrestre pasajeros | E52: - | F52: - | G52: - | H52: - | I52: - | J52: - | K52: - | L52: - | M52: - | N52: - | O52: - | P52: - | Q52: - | R52: - | S52: - | T52: - | U52: - | V52: - | W52: - | X52: - | Y52: - | Z52: - | AA52: - | AB52: - | AC52: - | AD52: - | AE52: - | AF52: - | AG52: - | AH52: - | AI52: - | AJ52: - | AK52: - | AL52: - | AM52: - | AN52: - | AO52: - | AP52: - | AQ52: - | AR52: - | AS52: - | AT52: - | AU52: - | AV52: - | AW52: - | AX52: - | AY52: - | AZ52: - | BA52: - | BB52: - | BC52: - | BD52: - | BE52: -
D53: Marítimo | E53: - | F53: - | G53: - | H53: -
A54: 2 | C54: E5_AERTRNKJF | D54: Aéreo | E54: ='Copia de Demandas de energía '!D54*$E$89 -> 3.8285523 | F54: ='Copia de Demandas de energía '!E54*$E$89 -> 3.8492817 | G54: ='Copia de Demandas de energía '!F54*$E$89 -> 1.741444 | H54: ='Copia de Demandas de energía '!G54*$E$89 -> 2.3650681 | I54: 4.3396385 | J54: 3.46 | K54: 3.65 | L54: 3.72 | M54: 3.78 | N54: 3.87 | O54: 3.94 | P54: 4.01 | Q54: 4.08 | R54: 4.17 | S54: 4.24 | T54: 4.32 | U54: 4.4 | V54: 4.47 | W54: 4.55 | X54: 4.62 | Y54: 4.7 | Z54: 4.77 | AA54: 4.85 | AB54: 4.92 | AC54: 5 | AD54: 5.06 | AE54: 5.14 | AF54: 5.2 | AG54: 5.28 | AH54: 5.34 | AI54: 5.41 | AJ54: 5.48 | AK54: 5.54 | AL54: 5.6123238 | AM54: 5.6701828 | AN54: 5.7425065 | AO54: 5.8003655 | AP54: 5.8726893 | AQ54: 5.9305483 | AR54: 6.0028721 | AS54: 6.0607311 | AT54: 6.1185901 | AU54: 6.1909138 | AV54: 6.2487728 | AW54: 6.3066318 | AX54: 6.3644909 | AY54: 6.4223499 | AZ54: 6.4802089 | BA54: 6.5380679 | BB54: 6.5959269 | BC54: 6.6537859 | BD54: 6.6971801 | BE54: 6.7550392
D55: Total [PJ] | E55: =SUM(E45:E54) -> 5.1970024 | F55: =SUM(F45:F54) -> 4.899721 | G55: =SUM(G45:G54) -> 3.341271 | H55: =SUM(H45:H54) -> 4.1976548 | I55: =SUM(I45:I54) -> 6.8310523 | J55: =SUM(J45:J54) -> 5.4625 | K55: =SUM(K45:K54) -> 5.72 | L55: =SUM(L45:L54) -> 5.8525 | ... BE55: =SUM(BE45:BE54) -> 12.555039
D57: Demandas de Fuel Oil
D58: Demanda residencial [PJ] | E58: - | F58: - | G58: - | H58: -
C59: E5_COMFOI | D59: Demanda comercial y servicios públicos [PJ] | E59: ='Copia de Demandas de energía '!D59*$E$89 -> 0.27453469 | F59: ='Copia de Demandas de energía '!E59*$E$89 -> 0.28255512 | G59: ='Copia de Demandas de energía '!F59*$E$89 -> 0.26980483 | H59: ='Copia de Demandas de energía '!G59*$E$89 -> 0.31491248 | I59: 0.31723693 | J59: 0.33 | K59: 0.33 | L59: 0.35 | M59: 0.35 | N59: 0.37 | O59: 0.37 | P59: 0.38 | Q59: 0.39 | R59: 0.4 | S59: 0.41 | T59: 0.42 | U59: 0.43 | V59: 0.44 | W59: 0.45 | X59: 0.46 | Y59: 0.47 | Z59: 0.48 | AA59: 0.49 | AB59: 0.5 | AC59: 0.51 | AD59: 0.52 | AE59: 0.52 | AF59: 0.53 | AG59: 0.54 | AH59: 0.55 | AI59: 0.56 | AJ59: 0.57 | AK59: 0.58 | AL59: 0.59 | AM59: 0.59 | AN59: 0.6 | AO59: 0.61 | AP59: 0.62 | AQ59: 0.63 | AR59: 0.64 | AS59: 0.64 | AT59: 0.65 | AU59: 0.66 | AV59: 0.67 | AW59: 0.68 | AX59: 0.68 | AY59: 0.69 | AZ59: 0.7 | BA59: 0.71 | BB59: 0.71 | BC59: 0.72 | BD59: 0.73 | BE59: 0.73
C60: E5_INDFOI | D60: Demanda Industrial [PJ] | E60: ='Copia de Demandas de energía '!D60*$E$89 -> 9.4607379 | F60: ='Copia de Demandas de energía '!E60*$E$89 -> 9.73713 | G60: ='Copia de Demandas de energía '!F60*$E$89 -> 9.2977423 | H60: ='Copia de Demandas de energía '!G60*$E$89 -> 10.852197 | I60: 10.928405 | J60: 11.51 | K60: 11.96 | L60: 12.17 | M60: 12.55 | N60: 12.83 | O60: 13.29 | P60: 13.45 | Q60: 13.87 | R60: 14.18 | S60: 14.62 | T60: 14.93 | U60: 15.37 | V60: 15.63 | W60: 16.1 | X60: 16.37 | Y60: 16.81 | Z60: 17.15 | AA60: 17.58 | AB60: 17.91 | AC60: 18.35 | AD60: 18.59 | AE60: 19.03 | AF60: 19.32 | AG60: 19.79 | AH60: 20.09 | AI60: 20.47 | AJ60: 20.79 | AK60: 21.17 | AL60: 21.59 | AM60: 21.99 | AN60: 22.41 | AO60: 22.82 | AP60: 23.25 | AQ60: 23.67 | AR60: 24.11 | AS60: 24.55 | AT60: 25 | AU60: 25.46 | AV60: 25.93 | AW60: 26.42 | AX60: 26.9 | AY60: 27.4 | AZ60: 27.91 | BA60: 28.43 | BB60: 28.95 | BC60: 29.49 | BD60: 30.03 | BE60: 30.59
D61: Demanda construcción y otros [PJ] | E61: - | F61: - | G61: - | H61: -
D62: Demanda Agro, pesca y minería [PJ] | E62: - | F62: - | G62: - | H62: -
D63: Demanda transporte [PJ]
D64: Terrestre carga | E64: - | F64: - | G64: - | H64: - | I64: - | J64: - | K64: - | L64: - | M64: - | N64: - | O64: - | P64: - | Q64: - | R64: - | S64: - | T64: - | U64: - | V64: - | W64: - | X64: - | Y64: - | Z64: - | AA64: - | AB64: - | AC64: - | AD64: - | AE64: - | AF64: - | AG64: - | AH64: - | AI64: - | AJ64: - | AK64: - | AL64: - | AM64: - | AN64: - | AO64: - | AP64: - | AQ64: - | AR64: - | AS64: - | AT64: - | AU64: - | AV64: - | AW64: - | AX64: - | AY64: - | AZ64: - | BA64: - | BB64: - | BC64: - | BD64: - | BE64: -
D65: Terrestre pasajeros | E65: - | F65: - | G65: - | H65: - | I65: - | J65: - | K65: - | L65: - | M65: - | N65: - | O65: - | P65: - | Q65: - | R65: - | S65: - | T65: - | U65: - | V65: - | W65: - | X65: - | Y65: - | Z65: - | AA65: - | AB65: - | AC65: - | AD65: - | AE65: - | AF65: - | AG65: - | AH65: - | AI65: - | AJ65: - | AK65: - | AL65: - | AM65: - | AN65: - | AO65: - | AP65: - | AQ65: - | AR65: - | AS65: - | AT65: - | AU65: - | AV65: - | AW65: - | AX65: - | AY65: - | AZ65: - | BA65: - | BB65: - | BC65: - | BD65: - | BE65: -
C66: E5_SHITRNFOI | D66: Marítimo | E66: ='Copia de Demandas de energía '!D66*$E$89 -> 0.37022597 | F66: ='Copia de Demandas de energía '!E66*$E$89 -> 0.36906466 | G66: ='Copia de Demandas de energía '!F66*$E$89 -> 0.18720335 | H66: 0.18720335 | I66: 0.36 | J66: 0.38 | K66: 0.39 | L66: 0.4 | M66: 0.41 | N66: 0.42 | O66: 0.43 | P66: 0.44 | Q66: 0.45 | R66: 0.47 | S66: 0.48 | T66: 0.49 | U66: 0.5 | V66: 0.51 | W66: 0.53 | X66: 0.54 | Y66: 0.55 | Z66: 0.57 | AA66: 0.58 | AB66: 0.59 | AC66: 0.61 | AD66: 0.62 | AE66: 0.63 | AF66: 0.64 | AG66: 0.66 | AH66: 0.67 | AI66: 0.68 | AJ66: 0.69 | AK66: 0.7 | AL66: 0.72 | AM66: 0.73 | AN66: 0.74 | AO66: 0.76 | AP66: 0.77 | AQ66: 0.79 | AR66: 0.8 | AS66: 0.81 | AT66: 0.83 | AU66: 0.84 | AV66: 0.85 | AW66: 0.87 | AX66: 0.88 | AY66: 0.9 | AZ66: 0.91 | BA66: 0.92 | BB66: 0.94 | BC66: 0.95 | BD66: 0.96 | BE66: 0.98
D67: Aéreo | E67: - | F67: - | G67: - | H67: -
D68: Total [PJ] | E68: =SUM(E58:E67) -> 10.105499 | F68: =SUM(F58:F67) -> 10.38875 | G68: =SUM(G58:G67) -> 9.7547505 | H68: =SUM(H58:H67) -> 11.354313 | I68: =SUM(I58:I67) -> 11.605642 | J68: =SUM(J58:J67) -> 12.22 | K68: =SUM(K58:K67) -> 12.68 | L68: =SUM(L58:L67) -> 12.92 | ... BE68: =SUM(BE58:BE67) -> 32.3
D70: Demandas de gas natural
C71: E5_INDNGS | D71: Demanda Industrial [PJ] | E71: ='Copia de Demandas de energía '!D71*$E$89 -> 1.9633783 | F71: ='Copia de Demandas de energía '!E71*$E$89 -> 1.5793631 | G71: ='Copia de Demandas de energía '!F71*$E$89 -> 0.94433599 | H71: ='Copia de Demandas de energía '!G71*$E$89 -> 1.6548595 | I71: 1.74306 | J71: 1.75 | K71: 1.82 | L71: 1.86 | M71: 1.91 | N71: 1.96 | O71: 2.03 | P71: 2.05 | Q71: 2.11 | R71: 2.16 | S71: 2.23 | T71: 2.28 | U71: 2.34 | V71: 2.38 | W71: 2.45 | X71: 2.5 | Y71: 2.56 | Z71: 2.61 | AA71: 2.68 | AB71: 2.73 | AC71: 2.8 | AD71: 2.84 | AE71: 2.9 | AF71: 2.95 | AG71: 3.02 | AH71: 3.06 | AI71: 3.12 | AJ71: 3.17 | AK71: 3.23 | AL71: 3.29 | AM71: 3.35 | AN71: 3.42 | AO71: 3.48 | AP71: 3.54 | AQ71: 3.61 | AR71: 3.68 | AS71: 3.74 | AT71: 3.81 | AU71: 3.88 | AV71: 3.95 | AW71: 4.03 | AX71: 4.1 | AY71: 4.18 | AZ71: 4.26 | BA71: 4.33 | BB71: 4.41 | BC71: 4.5 | BD71: 4.58 | BE71: 4.66
C72: E5_RESNGS | D72: Demanda residencial [PJ] | E72: ='Copia de Demandas de energía '!D72*$E$89 -> 0.021965065 | F72: ='Copia de Demandas de energía '!E72*$E$89 -> 0.020567029 | G72: ='Copia de Demandas de energía '!F72*$E$89 -> 0.019008263 | H72: ='Copia de Demandas de energía '!G72*$E$89 -> 0.023492364 | I72: 0.02 | J72: 0.02 | K72: 0.02 | L72: 0.02 | M72: 0.03 | N72: 0.03 | O72: 0.03 | P72: 0.03 | Q72: 0.03 | R72: 0.03 | S72: 0.03 | T72: 0.03 | U72: 0.03 | V72: 0.03 | W72: 0.03 | X72: 0.03 | Y72: 0.03 | Z72: 0.03 | AA72: 0.03 | AB72: 0.03 | AC72: 0.03 | AD72: 0.03 | AE72: 0.03 | AF72: 0.03 | AG72: 0.03 | AH72: 0.03 | AI72: 0.03 | AJ72: 0.03 | AK72: 0.03 | AL72: 0.03 | AM72: 0.03 | AN72: 0.03 | AO72: 0.03 | AP72: 0.03 | AQ72: 0.03 | AR72: 0.03 | AS72: 0.03 | AT72: 0.03 | AU72: 0.03 | AV72: 0.03 | AW72: 0.03 | AX72: 0.03 | AY72: 0.03 | AZ72: 0.03 | BA72: 0.03 | BB72: 0.03 | BC72: 0.03 | BD72: 0.03 | BE72: 0.03
D73: Total [PJ] | E73: =SUM(E71:E72) -> 1.9853433 | F73: =SUM(F71:F72) -> 1.5999301 | G73: =SUM(G71:G72) -> 0.96334426 | H73: =SUM(H71:H72) -> 1.6783519 | I73: =SUM(I71:I72) -> 1.76306 | J73: =SUM(J71:J72) -> 1.77 | K73: =SUM(K71:K72) -> 1.84 | L73: =SUM(L71:L72) -> 1.88 | ... BE73: =SUM(BE71:BE72) -> 4.69
D75: Demandas de Leña
C76: E5_INDFIR | D76: Demanda industrial [PJ] | E76: ='Copia de Demandas de energía '!D76*$E$89 -> 2.0379768 | F76: ='Copia de Demandas de energía '!E76*$E$89 -> 2.0787364 | G76: ='Copia de Demandas de energía '!F76*$E$89 -> 2.1203111 | H76: ='Copia de Demandas de energía '!G76*$E$89 -> 2.1627173 | I76: 2.207295 | J76: 2.29 | K76: 2.38 | L76: 2.42 | M76: 2.5 | N76: 2.56 | O76: 2.65 | P76: 2.68 | Q76: 2.76 | R76: 2.83 | S76: 2.91 | T76: 2.98 | U76: 3.06 | V76: 3.11 | W76: 3.21 | X76: 3.26 | Y76: 3.35 | Z76: 3.42 | AA76: 3.5 | AB76: 3.57 | AC76: 3.66 | AD76: 3.71 | AE76: 3.79 | AF76: 3.85 | AG76: 3.94 | AH76: 4 | AI76: 4.08 | AJ76: 4.14 | AK76: 4.22 | AL76: 4.3 | AM76: 4.38 | AN76: 4.47 | AO76: 4.55 | AP76: 4.63 | AQ76: 4.72 | AR76: 4.81 | AS76: 4.89 | AT76: 4.98 | AU76: 5.07 | AV76: 5.17 | AW76: 5.26 | AX76: 5.36 | AY76: 5.46 | AZ76: 5.56 | BA76: 5.66 | BB76: 5.77 | BC76: 5.88 | BD76: 5.99 | BE76: 6.1
C77: E5_RESFIR | D77: Demanda residencial [PJ] | E77: 8.082685 | F77: 7.728487 | G77: 7.33945 | H77: 7.116082 | I77: 6.5004519 | J77: 6.6693 | K77: 6.445981 | L77: 6.222614 | M77: 6.062908 | N77: 5.903202 | O77: 5.743496 | P77: 5.583789 | Q77: 5.424083 | R77: 5.310735 | S77: 5.197388 | T77: 5.08404 | U77: 4.970692 | V77: 4.857344 | W77: 4.779001 | X77: 4.700658 | Y77: 4.622315 | Z77: 4.543972 | AA77: 4.465628 | AB77: 4.414897 | AC77: 4.364165 | AD77: 4.313433 | AE77: 4.262701 | AF77: 4.21197 | AG77: 4.184204 | AH77: 4.156438 | AI77: 4.128672 | AJ77: 4.100906 | AK77: 4.07314 | AL77: 4.046289 | AM77: 4.019438 | AN77: 3.992587 | AO77: 3.965736 | AP77: 3.938885 | AQ77: 3.91292 | AR77: 3.886954 | AS77: 3.860988 | AT77: 3.835022 | AU77: 3.809056 | AV77: 3.783946 | AW77: 3.758836 | AX77: 3.733726 | AY77: 3.708616 | AZ77: 3.683507 | BA77: 3.659224 | BB77: 3.634942 | BC77: 3.61066 | BD77: 3.586377 | BE77: 3.562095
D78: Total [PJ] | E78: =SUM(E76:E77) -> 10.120662 | F78: =SUM(F76:F77) -> 9.8072234 | G78: =SUM(G76:G77) -> 9.4597611 | H78: =SUM(H76:H77) -> 9.2787993 | I78: =SUM(I76:I77) -> 8.7077469 | J78: =SUM(J76:J77) -> 8.9593 | K78: =SUM(K76:K77) -> 8.825981 | L78: =SUM(L76:L77) -> 8.642614 | ... BE78: =SUM(BE76:BE77) -> 9.662095
D80: Demandas de productos de caña
C81: E5_INDSUG | D81: Demanda industrial [PJ] | E81: ='Copia de Demandas de energía '!D81*$E$89 -> 8.2146779 | F81: ='Copia de Demandas de energía '!E81*$E$89 -> 8.957836 | G81: ='Copia de Demandas de energía '!F81*$E$89 -> 9.0914696 | H81: ='Copia de Demandas de energía '!G81*$E$89 -> 7.6698878 | I81: 5.5353777 | J81: 7.67 | K81: 7.67 | L81: 7.67 | M81: 7.67 | N81: 7.67 | O81: 7.67 | P81: 7.67 | Q81: 7.67 | R81: 7.67 | S81: 7.67 | T81: 7.67 | U81: 7.67 | V81: 7.67 | W81: 7.67 | X81: 7.67 | Y81: 7.67 | Z81: 7.67 | AA81: 7.67 | AB81: 7.67 | AC81: 7.67 | AD81: 7.67 | AE81: 7.67 | AF81: 7.67 | AG81: 7.67 | AH81: 7.67 | AI81: 7.67 | AJ81: 7.67 | AK81: 7.67 | AL81: 7.67 | AM81: 7.67 | AN81: 7.67 | AO81: 7.67 | AP81: 7.67 | AQ81: 7.67 | AR81: 7.67 | AS81: 7.67 | AT81: 7.67 | AU81: 7.67 | AV81: 7.67 | AW81: 7.67 | AX81: 7.67 | AY81: 7.67 | AZ81: 7.67 | BA81: 7.67 | BB81: 7.67 | BC81: 7.67 | BD81: 7.67 | BE81: 7.67
D83: Demandas de Biomasa
D84: Demanda industrial [PJ]
C86: 1 | D86: 2 | E86: 3 | F86: 4 | G86: 5 | H86: 6 | I86: 7 | J86: 8 | K86: 9 | L86: 10 | M86: 11 | N86: 12 | O86: 13 | P86: 14 | Q86: 15 | R86: 16 | S86: 17 | T86: 18 | U86: 19 | V86: 20 | W86: 21 | X86: 22 | Y86: 23 | Z86: 24 | AA86: 25 | AB86: 26 | AC86: 27 | AD86: 28 | AE86: 29 | AF86: 30 | AG86: 31 | AH86: 32 | AI86: 33 | AJ86: 34 | AK86: 35 | AL86: 36 | AM86: 37 | AN86: 38 | AO86: 39 | AP86: 40 | AQ86: 41 | AR86: 42 | AS86: 43 | AT86: 44 | AU86: 45 | AV86: 46 | AW86: 47 | AX86: 48 | AY86: 49 | AZ86: 50 | BA86: 51 | BB86: 52 | BC86: 53 | BD86: 54 | BE86: 55
D87: Factores de conversión utilizados
D89: 1 kBEP = | E89: =(G89*I89*K89*M89*O89)/(I90*K90*M90*O90) -> 0.0058065554 | F89: PJ | G89: 1 | H89: kBEP | I89: 1000 | J89: BEP | K89: 1 | L89: TOE | M89: 41.84 | N89: TJ | O89: 1 | P89: PJ
I90: 1 | J90: kBEP | K90: 7.205649 | L90: BEP | M90: 1000 | N90: TOE | O90: 1000 | P90: TJ
D92: Demanda electrica en Galápagos [PJ] | E92: 0.1978992 | F92: 0.2033721 | G92: 0.208845 | H92: 0.2143179 | I92: 0.2197908 | J92: 0.2252637 | K92: 0.2307366 | L92: 0.2362095 | M92: 0.2416824 | N92: 0.2471553 | O92: 0.2526282 | P92: 0.2581011 | Q92: 0.263574 | R92: 0.26565624 | S92: 0.26773848 | T92: 0.26982072 | U92: 0.27190296 | V92: 0.2739852 | W92: 0.27606744 | X92: 0.27814968 | Y92: 0.28023192 | Z92: 0.28231416 | AA92: 0.2843964 | AB92: 0.2846808 | AC92: 0.2849652 | AD92: 0.2852496 | AE92: 0.285534 | AF92: 0.2858184 | AG92: 0.2861028 | AH92: 0.2863872 | AI92: 0.2866716 | AJ92: 0.286956 | AK92: 0.2872404 | AL92: 0.287 | AM92: 0.287 | AN92: 0.287 | AO92: 0.287 | AP92: 0.287 | AQ92: 0.287 | AR92: 0.287 | AS92: 0.287 | AT92: 0.287 | AU92: 0.287 | AV92: 0.287 | AW92: 0.287 | AX92: 0.287 | AY92: 0.287 | AZ92: 0.287 | BA92: 0.287 | BB92: 0.287 | BC92: 0.287 | BD92: 0.287 | BE92: 0.287
D93: Galapagos Wind | E93: 0.02411042 | F93: 0.024777193 | G93: 0.025443967 | H93: 0.02611074 | I93: 0.026777513 | J93: 0.027444287 | K93: 0.02811106 | L93: 0.028777833 | M93: 0.029444607 | N93: 0.03011138 | O93: 0.030778153 | P93: 0.031444927 | Q93: 0.0321117 | R93: 0.032365383 | S93: 0.032619066 | T93: 0.032872749 | U93: 0.033126433 | V93: 0.033380116 | W93: 0.033633799 | X93: 0.033887482 | Y93: 0.034141165 | Z93: 0.034394848 | AA93: 0.034648531 | AB93: 0.03468318 | AC93: 0.034717829 | AD93: 0.034752478 | AE93: 0.034787127 | AF93: 0.034821776 | AG93: 0.034856425 | AH93: 0.034891074 | AI93: 0.034925723 | AJ93: 0.034960372 | AK93: 0.034995021 | AL93: 0.035 | AM93: 0.035 | AN93: 0.035 | AO93: 0.035 | AP93: 0.035 | AQ93: 0.035 | AR93: 0.035 | AS93: 0.035 | AT93: 0.035 | AU93: 0.035 | AV93: 0.035 | AW93: 0.035 | AX93: 0.035 | AY93: 0.035 | AZ93: 0.035 | BA93: 0.035 | BB93: 0.035 | BC93: 0.035 | BD93: 0.035 | BE93: 0.035
D94: Galápagos PV | E94: 0.0027741153 | F94: 0.0028508334 | G94: 0.0029275516 | H94: 0.0030042697 | I94: 0.0030809878 | J94: 0.0031577059 | K94: 0.0032344241 | L94: 0.0033111422 | M94: 0.0033878603 | N94: 0.0034645784 | O94: 0.0035412966 | P94: 0.0036180147 | Q94: 0.0036947328 | R94: 0.0037239213 | S94: 0.0037531097 | T94: 0.0037822982 | U94: 0.0038114867 | V94: 0.0038406751 | W94: 0.0038698636 | X94: 0.0038990521 | Y94: 0.0039282405 | Z94: 0.003957429 | AA94: 0.0039866175 | AB94: 0.0039906041 | AC94: 0.0039945908 | AD94: 0.0039985775 | AE94: 0.0040025641 | AF94: 0.0040065508 | AG94: 0.0040105375 | AH94: 0.0040145241 | AI94: 0.0040185108 | AJ94: 0.0040224975 | AK94: 0.0040264841 | AL94: 0.004 | AM94: 0.004 | AN94: 0.004 | AO94: 0.004 | AP94: 0.004 | AQ94: 0.004 | AR94: 0.004 | AS94: 0.004 | AT94: 0.004 | AU94: 0.004 | AV94: 0.004 | AW94: 0.004 | AX94: 0.004 | AY94: 0.004 | AZ94: 0.004 | BA94: 0.004 | BB94: 0.004 | BC94: 0.004 | BD94: 0.004 | BE94: 0.004
D95: Galapagos diesel | E95: 0.17101466 | F95: 0.17574407 | G95: 0.18047348 | H95: 0.18520289 | I95: 0.1899323 | J95: 0.19466171 | K95: 0.19939112 | L95: 0.20412052 | M95: 0.20884993 | N95: 0.21357934 | O95: 0.21830875 | P95: 0.22303816 | Q95: 0.22776757 | R95: 0.22956694 | S95: 0.2313663 | T95: 0.23316567 | U95: 0.23496504 | V95: 0.23676441 | W95: 0.23856378 | X95: 0.24036315 | Y95: 0.24216251 | Z95: 0.24396188 | AA95: 0.24576125 | AB95: 0.24600702 | AC95: 0.24625278 | AD95: 0.24649854 | AE95: 0.24674431 | AF95: 0.24699007 | AG95: 0.24723584 | AH95: 0.2474816 | AI95: 0.24772737 | AJ95: 0.24797313 | AK95: 0.2482189 | AL95: 0.248 | AM95: 0.248 | AN95: 0.248 | AO95: 0.248 | AP95: 0.248 | AQ95: 0.248 | AR95: 0.248 | AS95: 0.248 | AT95: 0.248 | AU95: 0.248 | AV95: 0.248 | AW95: 0.248 | AX95: 0.248 | AY95: 0.248 | AZ95: 0.248 | BA95: 0.248 | BB95: 0.248 | BC95: 0.248 | BD95: 0.248 | BE95: 0.248
D96: Demanda eléctrica rural PJ | E96: 0.496 | F96: 0.4662 | G96: 0.5149 | H96: 0.52356215 | I96: 0.53229786 | J96: 0.54115665 | K96: 0.55016603 | L96: 0.55920855 | M96: 0.56838208 | N96: 0.5776205 | O96: 0.58697757 | P96: 0.59640479 | Q96: 0.60597064 | R96: 0.615565 | S96: 0.62522942 | T96: 0.63498857 | U96: 0.64480985 | V96: 0.65467197 | W96: 0.66458862 | X96: 0.67452287 | Y96: 0.68450405 | Z96: 0.69454196 | AA96: 0.70456011 | AB96: 0.71463097 | AC96: 0.72463359 | AD96: 0.73463677 | AE96: 0.74452152 | AF96: 0.75429721 | AG96: 0.76395023 | AH96: 0.77344789 | AI96: 0.78278552 | AJ96: 0.79199823 | AK96: 0.80104194 | AL96: 0.267 | AM96: 0.264 | AN96: 0.261 | AO96: 0.258 | AP96: 0.255 | AQ96: 0.251 | AR96: 0.248 | AS96: 0.244 | AT96: 0.24 | AU96: 0.237 | AV96: 0.233 | AW96: 0.229 | AX96: 0.225 | AY96: 0.221 | AZ96: 0.216 | BA96: 0.212 | BB96: 0.208 | BC96: 0.203 | BD96: 0.199 | BE96: 0.194
D97: Electrificación rural hidro | E97: 0.070316709 | F97: 0.066092036 | G97: 0.072996116 | H97: 0.074224129 | I97: 0.075462568 | J97: 0.076718458 | K97: 0.077995696 | L97: 0.079277631 | M97: 0.08057814 | N97: 0.081887848 | O97: 0.083214377 | P97: 0.084550851 | Q97: 0.085906979 | R97: 0.087267147 | S97: 0.088637249 | T97: 0.090020779 | U97: 0.091413119 | V97: 0.092811247 | W97: 0.094217107 | X97: 0.095625461 | Y97: 0.097040468 | Z97: 0.098463518 | AA97: 0.099883768 | AB97: 0.10131149 | AC97: 0.10272954 | AD97: 0.10414766 | AE97: 0.105549 | AF97: 0.10693487 | AG97: 0.10830336 | AH97: 0.10964982 | AI97: 0.11097359 | AJ97: 0.11227966 | AK97: 0.11356176 | AL97: 0.038 | AM97: 0.037 | AN97: 0.037 | AO97: 0.037 | AP97: 0.036 | AQ97: 0.036 | AR97: 0.035 | AS97: 0.035 | AT97: 0.034 | AU97: 0.034 | AV97: 0.033 | AW97: 0.032 | AX97: 0.032 | AY97: 0.031 | AZ97: 0.031 | BA97: 0.03 | BB97: 0.029 | BC97: 0.029 | BD97: 0.028 | BE97: 0.028
D98: Electrificación rural solar | E98: 0.01112264 | F98: 0.010454385 | G98: 0.011546467 | H98: 0.011740713 | I98: 0.011936608 | J98: 0.012135264 | K98: 0.012337296 | L98: 0.012540072 | M98: 0.012745785 | N98: 0.012952954 | O98: 0.013162783 | P98: 0.013374186 | Q98: 0.013588697 | R98: 0.013803847 | S98: 0.014020569 | T98: 0.014239414 | U98: 0.014459653 | V98: 0.014680808 | W98: 0.014903186 | X98: 0.015125958 | Y98: 0.015349783 | Z98: 0.01557488 | AA98: 0.015799534 | AB98: 0.01602537 | AC98: 0.016249675 | AD98: 0.016473993 | AE98: 0.016695656 | AF98: 0.016914872 | AG98: 0.017131338 | AH98: 0.01734432 | AI98: 0.017553713 | AJ98: 0.017760306 | AK98: 0.017963108 | AL98: 0.006 | AM98: 0.006 | AN98: 0.006 | AO98: 0.006 | AP98: 0.006 | AQ98: 0.006 | AR98: 0.006 | AS98: 0.005 | AT98: 0.005 | AU98: 0.005 | AV98: 0.005 | AW98: 0.005 | AX98: 0.005 | AY98: 0.005 | AZ98: 0.005 | BA98: 0.005 | BB98: 0.005 | BC98: 0.005 | BD98: 0.004 | BE98: 0.004
D99: Electrificación rural diesel | E99: 0.41456065 | F99: 0.38965358 | G99: 0.43035742 | H99: 0.43759731 | I99: 0.44489868 | J99: 0.45230293 | K99: 0.45983304 | L99: 0.46739085 | M99: 0.47505815 | N99: 0.4827797 | O99: 0.49060041 | P99: 0.49847975 | Q99: 0.50647497 | R99: 0.514494 | S99: 0.5225716 | T99: 0.53072837 | U99: 0.53893708 | V99: 0.54717992 | W99: 0.55546833 | X99: 0.56377145 | Y99: 0.5721138 | Z99: 0.58050356 | AA99: 0.58887681 | AB99: 0.59729411 | AC99: 0.60565438 | AD99: 0.61401511 | AE99: 0.62227687 | AF99: 0.63044747 | AG99: 0.63851553 | AH99: 0.64645375 | AI99: 0.65425822 | AJ99: 0.66195827 | AK99: 0.66951707 | AL99: 0.223 | AM99: 0.221 | AN99: 0.218 | AO99: 0.216 | AP99: 0.213 | AQ99: 0.21 | AR99: 0.207 | AS99: 0.204 | AT99: 0.201 | AU99: 0.198 | AV99: 0.194 | AW99: 0.191 | AX99: 0.188 | AY99: 0.184 | AZ99: 0.181 | BA99: 0.177 | BB99: 0.174 | BC99: 0.17 | BD99: 0.166 | BE99: 0.163
E109: 3.83 | F109: 3.85 | G109: 1.74 | H109: 2.37 | I109: 3.1 | J109: 3.46 | K109: 3.65 | L109: 3.72 | M109: 3.78 | N109: 3.87 | O109: 3.94 | P109: 4.01 | Q109: 4.08 | R109: 4.17 | S109: 4.24 | T109: 4.32 | U109: 4.4 | V109: 4.47 | W109: 4.55 | X109: 4.62 | Y109: 4.7 | Z109: 4.77 | AA109: 4.85 | AB109: 4.92 | AC109: 5 | AD109: 5.06 | AE109: 5.14 | AF109: 5.2 | AG109: 5.28 | AH109: 5.34 | AI109: 5.41 | AJ109: 5.48 | AK109: 5.54

Sheet Emisiones Energía V2
C1: Ecuador | D1: 2018 | E1: 2019 | F1: 2020 | G1: 2021 | H1: 2022 | I1: 2023 | J1: 2024 | K1: 2025 | L1: 2026 | M1: 2027 | N1: 2028 | O1: 2029 | P1: 2030 | Q1: 2031 | R1: 2032 | S1: 2033 | T1: 2034 | U1: 2035 | V1: 2036 | W1: 2037 | X1: 2038 | Y1: 2039 | Z1: 2040 | AA1: 2041 | AB1: 2042 | AC1: 2043 | AD1: 2044 | AE1: 2045 | AF1: 2046 | AG1: 2047 | AH1: 2048 | AI1: 2049 | AJ1: 2050
C4: Combustibles
C5: Factores de emisión para emisiones fugitivas
A6: 1 | C6: Petróleo | D6: [Mton CO2 / PJ] | E6: [Mton CH4 / PJ] | F6: [Mton N2O / PJ] | G6: [Mton CO2eq / PJ]
C7: Venteo | D7: ='Copia de Emisiones Energía'!D7*'Emisiones Energía V2'!$D$131 -> 2.6011668e-06 | E7: ='Copia de Emisiones Energía'!E7*'Emisiones Energía V2'!$D$131 -> 1.9714106e-05 | F7: - | G7: =(D7*$D$144)+(E7*$D$145) -> 0.00049545382 | H7: Se incluyen agrupadas | I7: =G7+G8+G10+G11 -> 0.0016451372
C8: Quema en antorcha | D8: ='Copia de Emisiones Energía'!D8*'Emisiones Energía V2'!$D$131 -> 0.0011226088 | E8: ='Copia de Emisiones Energía'!E8*'Emisiones Energía V2'!$D$131 -> 6.8451757e-07 | F8: ='Copia de Emisiones Energía'!F8*'Emisiones Energía V2'!$D$131 -> 1.752365e-08 | G8: =(D8*$D$144)+(E8*$D$145)+(F8*$D$146) -> 0.0011449438
C9: Exploración | D9: ='Copia de Emisiones Energía'!D9*'Emisiones Energía V2'!$D$131 -> 2.7380703e-06 | E9: ='Copia de Emisiones Energía'!E9*'Emisiones Energía V2'!$D$131 -> 9.0356319e-07 | F9: - | G9: =(D9*$D$144)+(E9*$D$145) -> 2.532715e-05
C10: Producción y Refinación | D10: ='Copia de Emisiones Energía'!D10*'Emisiones Energía V2'!$D$131 -> 3.0118773e-09 | E10: ='Copia de Emisiones Energía'!E10*'Emisiones Energía V2'!$D$131 -> 4.1071054e-08 | F10: - | G10: =(D10*$D$144)+(E10*$D$145) -> 1.0297882e-06
C11: Transporte por tuberías | D11: ='Copia de Emisiones Energía'!D11*'Emisiones Energía V2'!$D$131 -> 1.3416544e-08 | E11: ='Copia de Emisiones Energía'!E11*'Emisiones Energía V2'!$D$131 -> 1.478558e-07 | F11: - | G11: =(D11*$D$144)+(E11*$D$145) -> 3.7098114e-06
A12: 2 | C12: Gas Natural | D12: [Mton CO2 / PJ] | E12: [Mton CH4 / PJ] | F12: [Mton N2O / PJ] | G12: [Mton CO2eq / PJ]
C13: Quema en antorcha | D13: ='Copia de Emisiones Energía'!D13*'Emisiones Energía V2'!$D$137 -> 3.4555559e-17 | E13: ='Copia de Emisiones Energía'!E13*'Emisiones Energía V2'!$D$137 -> 2.1885187e-20 | F13: ='Copia de Emisiones Energía'!F13*'Emisiones Energía V2'!$D$137 -> 6.0472227e-22 | G13: =(D13*$D$144)+(E13*$D$145)+(F13*$D$146) -> 3.5282895e-17 | H13: =G13+G15+G16+G17 -> 4.6512179e-16
C14: Exploración | D14: ='Copia de Emisiones Energía'!D14*'Emisiones Energía V2'!$D$137 -> 2.8796299e-18 | E14: ='Copia de Emisiones Energía'!E14*'Emisiones Energía V2'!$D$137 -> 9.5027786e-19 | F14: - | G14: =(D14*$D$144)+(E14*$D$145) -> 2.6636576e-17
C15: Producción | D15: ='Copia de Emisiones Energía'!D15*'Emisiones Energía V2'!$D$137 -> 4.0314818e-19 | E15: ='Copia de Emisiones Energía'!E15*'Emisiones Energía V2'!$D$137 -> 1.0942594e-17 | F15: - | G15: =(D15*$D$144)+(E15*$D$145) -> 2.7396799e-16
C16: Procesamiento | D16: ='Copia de Emisiones Energía'!D16*'Emisiones Energía V2'!$D$137 -> 3.4555559e-19 | E16: ='Copia de Emisiones Energía'!E16*'Emisiones Energía V2'!$D$137 -> 4.3194448e-18 | F16: - | G16: =(D16*$D$144)+(E16*$D$145) -> 1.0833168e-16
C17: Transmisión y almacenamiento | D17: ='Copia de Emisiones Energía'!D17*'Emisiones Energía V2'!$D$137 -> 2.5340743e-20 | E17: ='Copia de Emisiones Energía'!E17*'Emisiones Energía V2'!$D$137 -> 1.9005557e-18 | F17: - | G17: =(D17*$D$144)+(E17*$D$145) -> 4.7539234e-17 | H17: =SUM(G17:G18) -> 8.4090606e-16
C18: Distribución | D18: ='Copia de Emisiones Energía'!D18*'Emisiones Energía V2'!$D$137 -> 1.4686112e-18 | E18: ='Copia de Emisiones Energía'!E18*'Emisiones Energía V2'!$D$137 -> 3.1675929e-17 | F18: - | G18: =(D18*$D$144)+(E18*$D$145) -> 7.9336683e-16
A21: 3 | C21: Factores de emisión por quema de combustible
C23: 1A1a Producción de electricidad y calor como actividad principal
C24: Factores de emisión [Mton CO2/PJ] | D24: [Mton CO2 / PJ] | E24: [Mton CH4 / PJ] | F24: [Mton N2O / PJ] | G24: [Mton CO2eq / PJ]
C25: Gas/Diesel Oil | D25: ='Copia de Emisiones Energía'!D25*'Emisiones Energía V2'!$D$140 -> 0.0741 | E25: ='Copia de Emisiones Energía'!E25*'Emisiones Energía V2'!$D$140 -> 3e-06 | F25: ='Copia de Emisiones Energía'!F25*'Emisiones Energía V2'!$D$140 -> 6e-07 | G25: =(D25*$D$144)+(E25*$D$145)+(F25*$D$146) -> 0.0743538
C26: Fuel oil residual | D26: ='Copia de Emisiones Energía'!D26*'Emisiones Energía V2'!$D$140 -> 0.0774 | E26: ='Copia de Emisiones Energía'!E26*'Emisiones Energía V2'!$D$140 -> 3e-06 | F26: ='Copia de Emisiones Energía'!F26*'Emisiones Energía V2'!$D$140 -> 6e-07 | G26: =(D26*$D$144)+(E26*$D$145) -> 0.077475
C27: Gas Natural (seco) | D27: ='Copia de Emisiones Energía'!D27*'Emisiones Energía V2'!$D$140 -> 0.0561 | E27: ='Copia de Emisiones Energía'!E27*'Emisiones Energía V2'!$D$140 -> 1e-06 | F27: ='Copia de Emisiones Energía'!F27*'Emisiones Energía V2'!$D$140 -> 1e-07 | G27: =(D27*$D$144)+(E27*$D$145) -> 0.056125
C28: Desechos municipales | D28: ='Copia de Emisiones Energía'!D28*'Emisiones Energía V2'!$D$140 -> 0.1 | E28: ='Copia de Emisiones Energía'!E28*'Emisiones Energía V2'!$D$140 -> 3e-05 | F28: ='Copia de Emisiones Energía'!F28*'Emisiones Energía V2'!$D$140 -> 4e-06 | G28: =(D28*$D$144)+(E28*$D$145) -> 0.10075
C30: 1A1b Refinación del Petróleo
C31: Factores de emisión [Mton CO2/PJ] | D31: [Mton CO2 / PJ] | E31: [Mton CH4 / PJ] | F31: [Mton N2O / PJ] | G31: [Mton CO2eq / PJ]
A32: 65.4 | C32: Gasolina | D32: ='Copia de Emisiones Energía'!D32*'Emisiones Energía V2'!$D$140 -> 0.0693 | E32: ='Copia de Emisiones Energía'!E32*'Emisiones Energía V2'!$D$140 -> 3e-06 | F32: ='Copia de Emisiones Energía'!F32*'Emisiones Energía V2'!$D$140 -> 6e-07 | G32: =(D32*$D$144)+(E32*$D$145)+(F32*$D$146) -> 0.0695538
A33: 5.3 | C33: Queroseno | D33: ='Copia de Emisiones Energía'!D33*'Emisiones Energía V2'!$D$140 -> 0.0715 | E33: ='Copia de Emisiones Energía'!E33*'Emisiones Energía V2'!$D$140 -> 3e-06 | F33: ='Copia de Emisiones Energía'!F33*'Emisiones Energía V2'!$D$140 -> 6e-07 | G33: =(D33*$D$144)+(E33*$D$145) -> 0.071575
A34: 79.7 | C34: Gas/Diesel Oil | D34: ='Copia de Emisiones Energía'!D34*'Emisiones Energía V2'!$D$140 -> 0.0741 | E34: ='Copia de Emisiones Energía'!E34*'Emisiones Energía V2'!$D$140 -> 3e-06 | F34: ='Copia de Emisiones Energía'!F34*'Emisiones Energía V2'!$D$140 -> 6e-07 | G34: =(D34*$D$144)+(E34*$D$145) -> 0.074175
A35: 134 | C35: Fuel oil residual | D35: ='Copia de Emisiones Energía'!D35*'Emisiones Energía V2'!$D$140 -> 0.0774 | E35: ='Copia de Emisiones Energía'!E35*'Emisiones Energía V2'!$D$140 -> 3e-06 | F35: ='Copia de Emisiones Energía'!F35*'Emisiones Energía V2'!$D$140 -> 6e-07 | G35: =(D35*$D$144)+(E35*$D$145) -> 0.077475
A36: 2.85 | C36: Gas licuado de petróleo | D36: ='Copia de Emisiones Energía'!D36*'Emisiones Energía V2'!$D$140 -> 0.0631 | E36: ='Copia de Emisiones Energía'!E36*'Emisiones Energía V2'!$D$140 -> 1e-06 | F36: ='Copia de Emisiones Energía'!F36*'Emisiones Energía V2'!$D$140 -> 1e-07 | G36: =(D36*$D$144)+(E36*$D$145) -> 0.063125
C37: Gas de refinería | D37: ='Copia de Emisiones Energía'!D37*'Emisiones Energía V2'!$D$140 -> 0.0576 | E37: ='Copia de Emisiones Energía'!E37*'Emisiones Energía V2'!$D$140 -> 1e-06 | F37: ='Copia de Emisiones Energía'!F37*'Emisiones Energía V2'!$D$140 -> 1e-07 | G37: =(D37*$D$144)+(E37*$D$145) -> 0.057625
C39: 1A4a Consumo
C40: Factores de emisión [Mton CO2/PJ] | D40: [Mton CO2 / PJ] | E40: [Mton CH4 / PJ] | F40: [Mton N2O / PJ] | G40: [Mton CO2eq / PJ]
C41: Gas natural | D41: ='Copia de Emisiones Energía'!D41*'Emisiones Energía V2'!$D$140 -> 0.0561 | E41: ='Copia de Emisiones Energía'!E41*'Emisiones Energía V2'!$D$140 -> 5e-06 | F41: ='Copia de Emisiones Energía'!F41*'Emisiones Energía V2'!$D$140 -> 1e-07 | G41: =(D41*$D$144)+(E41*$D$145) -> 0.056225
C42: Leña | D42: ='Copia de Emisiones Energía'!D42*'Emisiones Energía V2'!$D$140 -> 0.112 | E42: ='Copia de Emisiones Energía'!E42*'Emisiones Energía V2'!$D$140 -> 0.0003 | F42: ='Copia de Emisiones Energía'!F42*'Emisiones Energía V2'!$D$140 -> 4e-06 | G42: =(D42*$D$144)+(E42*$D$145) -> 0.1195
C43: Gas licuado de petróleo | D43: ='Copia de Emisiones Energía'!D43*'Emisiones Energía V2'!$D$140 -> 0.0631 | E43: ='Copia de Emisiones Energía'!E43*'Emisiones Energía V2'!$D$140 -> 5e-06 | F43: ='Copia de Emisiones Energía'!F43*'Emisiones Energía V2'!$D$140 -> 1e-07 | G43: =(D43*$D$144)+(E43*$D$145) -> 0.063225
C44: Gasolina para motores | D44: ='Copia de Emisiones Energía'!D44*'Emisiones Energía V2'!$D$140 -> 0.0693 | E44: ='Copia de Emisiones Energía'!E44*'Emisiones Energía V2'!$D$140 -> 1e-05 | F44: ='Copia de Emisiones Energía'!F44*'Emisiones Energía V2'!$D$140 -> 6e-07 | G44: =(D44*$D$144)+(E44*$D$145) -> 0.06955
C45: Gasolina para aviación | D45: ='Copia de Emisiones Energía'!D45*'Emisiones Energía V2'!$D$140 -> 0.07 | E45: ='Copia de Emisiones Energía'!E45*'Emisiones Energía V2'!$D$140 -> 1e-05 | F45: ='Copia de Emisiones Energía'!F45*'Emisiones Energía V2'!$D$140 -> 6e-07 | G45: =(D45*$D$144)+(E45*$D$145) -> 0.07025
C46: Queroseno | D46: ='Copia de Emisiones Energía'!D46*'Emisiones Energía V2'!$D$140 -> 0.0715 | E46: ='Copia de Emisiones Energía'!E46*'Emisiones Energía V2'!$D$140 -> 1e-05 | F46: ='Copia de Emisiones Energía'!F46*'Emisiones Energía V2'!$D$140 -> 6e-07 | G46: =(D46*$D$144)+(E46*$D$145) -> 0.07175
C47: Gas/Diesel Oil | D47: ='Copia de Emisiones Energía'!D47*'Emisiones Energía V2'!$D$140 -> 0.0741 | E47: ='Copia de Emisiones Energía'!E47*'Emisiones Energía V2'!$D$140 -> 1e-05 | F47: ='Copia de Emisiones Energía'!F47*'Emisiones Energía V2'!$D$140 -> 6e-07 | G47: =(D47*$D$144)+(E47*$D$145) -> 0.07435
C48: Fuel oil residual | D48: ='Copia de Emisiones Energía'!D48*'Emisiones Energía V2'!$D$140 -> 0.0774 | E48: ='Copia de Emisiones Energía'!E48*'Emisiones Energía V2'!$D$140 -> 1e-05 | F48: ='Copia de Emisiones Energía'!F48*'Emisiones Energía V2'!$D$140 -> 6e-07 | G48: =(D48*$D$144)+(E48*$D$145) -> 0.07765
C49: Coque de petróleo | D49: ='Copia de Emisiones Energía'!D49*'Emisiones Energía V2'!$D$140 -> 0.0975 | E49: ='Copia de Emisiones Energía'!E49*'Emisiones Energía V2'!$D$140 -> 1e-05 | F49: ='Copia de Emisiones Energía'!F49*'Emisiones Energía V2'!$D$140 -> 6e-07 | G49: =(D49*$D$144)+(E49*$D$145) -> 0.09775
C51: Emisiones asociadas a la producción
C52: Petróleo [Mton CO2 eq] | D52: ='Copia de Emisiones Energía'!D52*0.001 -> 0.1522 | E52: ='Copia de Emisiones Energía'!E52*0.001 -> 0.1641 | F52: ='Copia de Emisiones Energía'!F52*0.001 -> 0.1486 | G52: ='Copia de Emisiones Energía'!G52*0.001 -> 0.1461
C53: Líquidos de gas natural [Mton CO2 eq] | D53: ='Copia de Emisiones Energía'!D53*0.001 -> 0.004 | E53: ='Copia de Emisiones Energía'!E53*0.001 -> 0.0044 | F53: ='Copia de Emisiones Energía'!F53*0.001 -> 0.0039 | G53: ='Copia de Emisiones Energía'!G53*0.001 -> 0.0046
C54: Gas natural [Mton CO2 eq] | D54: ='Copia de Emisiones Energía'!D54*0.001 -> 0.0376 | E54: ='Copia de Emisiones Energía'!E54*0.001 -> 0.0362 | F54: ='Copia de Emisiones Energía'!F54*0.001 -> 0.0323 | G54: ='Copia de Emisiones Energía'!G54*0.001 -> 0.0326
C56: Total [Mton CO2 eq] | D56: =SUM(D52:D54) -> 0.1938 | E56: =SUM(E52:E54) -> 0.2047 | F56: =SUM(F52:F54) -> 0.1848 | G56: =SUM(G52:G54) -> 0.1833
C60: Electricidad
C61: Emisiones asociadas a la generación de electricidad en centrales electricas
C62: Petróleo [Mton CO2 eq] | D62: - | E62: - | F62: - | G62: ='Copia de Emisiones Energía'!G62*0.001 -> 0.014
C63: Gas natural [Mton CO2 eq] | D63: ='Copia de Emisiones Energía'!D63*0.001 -> 0.5695 | E63: ='Copia de Emisiones Energía'!E63*0.001 -> 0.5184 | F63: ='Copia de Emisiones Energía'!F63*0.001 -> 0.4431 | G63: ='Copia de Emisiones Energía'!G63*0.001 -> 0.392
C64: Productos de caña [Mton CO2 eq] | D64: - | E64: - | F64: - | G64: ='Copia de Emisiones Energía'!G64*0.001 -> 0.0381
C65: Diesel oil [Mton CO2 eq] | D65: ='Copia de Emisiones Energía'!D65*0.001 -> 0.2185 | E65: ='Copia de Emisiones Energía'!E65*0.001 -> 0.2682 | F65: ='Copia de Emisiones Energía'!F65*0.001 -> 0.2355 | G65: ='Copia de Emisiones Energía'!G65*0.001 -> 0.0986
C66: Fuel oil [Mton CO2 eq] | D66: ='Copia de Emisiones Energía'!D66*0.001 -> 1.9875 | E66: ='Copia de Emisiones Energía'!E66*0.001 -> 1.1076 | F66: ='Copia de Emisiones Energía'!F66*0.001 -> 1.0869 | G66: ='Copia de Emisiones Energía'!G66*0.001 -> 0.9628
C67: Otros productos de petróleo y gas [Mton CO2 eq] | D67: ='Copia de Emisiones Energía'!D67*0.001 -> 0.0005 | E67: ='Copia de Emisiones Energía'!E67*0.001 -> 0.0002 | F67: - | G67: -
C68: Total [Mton CO2 eq] | D68: =SUM(D62:D67) -> 2.776 | E68: =SUM(E62:E67) -> 1.8944 | F68: =SUM(F62:F67) -> 1.7655 | G68: =SUM(G62:G67) -> 1.5055
C70: Emisiones asociadas a la generación de electricidad en autoproductores
C71: Petróleo [Mton CO2 eq] | D71: ='Copia de Emisiones Energía'!D71*0.001 -> 1.1393 | E71: ='Copia de Emisiones Energía'!E71*0.001 -> 1.2007 | F71: ='Copia de Emisiones Energía'!F71*0.001 -> 1.2099 | G71: ='Copia de Emisiones Energía'!G71*0.001 -> 1.1555
C72: Gas natural [Mton CO2 eq] | D72: ='Copia de Emisiones Energía'!D72*0.001 -> 0.5466 | E72: ='Copia de Emisiones Energía'!E72*0.001 -> 0.4791 | F72: ='Copia de Emisiones Energía'!F72*0.001 -> 0.4183 | G72: ='Copia de Emisiones Energía'!G72*0.001 -> 0.4662
C73: Productos de caña [Mton CO2 eq] | D73: ='Copia de Emisiones Energía'!D73*0.001 -> 0.2779 | E73: ='Copia de Emisiones Energía'!E73*0.001 -> 0.3006 | F73: ='Copia de Emisiones Energía'!F73*0.001 -> 0.3101 | G73: ='Copia de Emisiones Energía'!G73*0.001 -> 0.2329
C74: GLP [Mton CO2 eq] | D74: ='Copia de Emisiones Energía'!D74*0.001 -> 0.0462 | E74: ='Copia de Emisiones Energía'!E74*0.001 -> 0.0369 | F74: ='Copia de Emisiones Energía'!F74*0.001 -> 0.0389 | G74: ='Copia de Emisiones Energía'!G74*0.001 -> 0.0363
C75: Diesel oil [Mton CO2 eq] | D75: ='Copia de Emisiones Energía'!D75*0.001 -> 0.9583 | E75: ='Copia de Emisiones Energía'!E75*0.001 -> 1.0486 | F75: ='Copia de Emisiones Energía'!F75*0.001 -> 1.0057 | G75: ='Copia de Emisiones Energía'!G75*0.001 -> 1.1934
C76: Fuel oil [Mton CO2 eq] | D76: ='Copia de Emisiones Energía'!D76*0.001 -> 0.07 | E76: ='Copia de Emisiones Energía'!E76*0.001 -> 0.0672 | F76: ='Copia de Emisiones Energía'!F76*0.001 -> 0.0672 | G76: ='Copia de Emisiones Energía'!G76*0.001 -> 0.0704
C77: Otros productos de petróleo y gas [Mton CO2 eq] | D77: ='Copia de Emisiones Energía'!D77*0.001 -> 0.0003 | E77: ='Copia de Emisiones Energía'!E77*0.001 -> 0.0002 | F77: ='Copia de Emisiones Energía'!F77*0.001 -> 0.0002 | G77: ='Copia de Emisiones Energía'!G77*0.001 -> 0.0002
C78: Total [Mton CO2 eq] | D78: =SUM(D71:D77) -> 3.0386 | E78: =SUM(E71:E77) -> 3.1333 | F78: =SUM(F71:F77) -> 3.0503 | G78: =SUM(G71:G77) -> 3.1549
C82: Demandas de combustibles
C83: Emisiones asociadas al consumo de combustibles
C84: Gas natural [Mton CO2 eq] | D84: ='Copia de Emisiones Energía'!D84*0.001 -> 0.1115 | E84: ='Copia de Emisiones Energía'!E84*0.001 -> 0.0898 | F84: ='Copia de Emisiones Energía'!F84*0.001 -> 0.0541 | G84: ='Copia de Emisiones Energía'!G84*0.001 -> 0.0942
C85: Leña [Mton CO2 eq] | D85: ='Copia de Emisiones Energía'!D85*0.001 -> 1.1983 | E85: ='Copia de Emisiones Energía'!E85*0.001 -> 1.1757 | F85: ='Copia de Emisiones Energía'!F85*0.001 -> 1.1331 | G85: ='Copia de Emisiones Energía'!G85*0.001 -> 1.0877
C86: Productos de caña [Mton CO2 eq] | D86: ='Copia de Emisiones Energía'!D86*0.001 -> 0.8368 | E86: ='Copia de Emisiones Energía'!E86*0.001 -> 0.9128 | F86: ='Copia de Emisiones Energía'!F86*0.001 -> 0.9264 | G86: ='Copia de Emisiones Energía'!G86*0.001 -> 0.7816
C87: GLP [Mton CO2 eq] | D87: ='Copia de Emisiones Energía'!D87*0.001 -> 3.2013 | E87: ='Copia de Emisiones Energía'!E87*0.001 -> 3.4309 | F87: ='Copia de Emisiones Energía'!F87*0.001 -> 3.466 | G87: ='Copia de Emisiones Energía'!G87*0.001 -> 3.5874
C88: Gasolina [Mton CO2 eq] | D88: ='Copia de Emisiones Energía'!D88*0.001 -> 11.3289 | E88: ='Copia de Emisiones Energía'!E88*0.001 -> 11.3761 | F88: ='Copia de Emisiones Energía'!F88*0.001 -> 8.9349 | G88: ='Copia de Emisiones Energía'!G88*0.001 -> 10.7243
C89: Kerosene/Jet Fuel [Mton CO2 eq] | D89: ='Copia de Emisiones Energía'!D89*0.001 -> 0.3754 | E89: ='Copia de Emisiones Energía'!E89*0.001 -> 0.3537 | F89: ='Copia de Emisiones Energía'!F89*0.001 -> 0.2411 | G89: ='Copia de Emisiones Energía'!G89*0.001 -> 0.3029
C90: Diesel oil [Mton CO2 eq] | D90: ='Copia de Emisiones Energía'!D90*0.001 -> 12.9334 | E90: ='Copia de Emisiones Energía'!E90*0.001 -> 12.778 | F90: ='Copia de Emisiones Energía'!F90*0.001 -> 10.964 | G90: ='Copia de Emisiones Energía'!G90*0.001 -> 12.2939
C91: Fuel oil [Mton CO2 eq] | D91: ='Copia de Emisiones Energía'!D91*0.001 -> 0.7844 | E91: ='Copia de Emisiones Energía'!E91*0.001 -> 0.8063 | F91: ='Copia de Emisiones Energía'!F91*0.001 -> 0.7573 | G91: ='Copia de Emisiones Energía'!G91*0.001 -> 0.867
C92: Coque [Mton CO2 eq] | D92: - | E92: - | F92: - | G92: ='Copia de Emisiones Energía'!G92*0.001 -> 0.5544
C93: No energéticos [Mton CO2 eq] | D93: ='Copia de Emisiones Energía'!D93*0.001 -> 0.6591 | E93: ='Copia de Emisiones Energía'!E93*0.001 -> 0.6306 | F93: ='Copia de Emisiones Energía'!F93*0.001 -> 0.4871 | G93: ='Copia de Emisiones Energía'!G93*0.001 -> 0.5861
C95: Total [Mton CO2 eq] | D95: =SUM(D84:D93) -> 31.4291 | E95: =SUM(E84:E93) -> 31.5539 | F95: =SUM(F84:F93) -> 26.964 | G95: =SUM(G84:G93) -> 30.8795
C99: Emisiones asociadas a centros de gas
C100: Líquidos de gas natural [Mton CO2 eq] | D100: ='Copia de Emisiones Energía'!D100*0.001 -> 0.3128 | E100: ='Copia de Emisiones Energía'!E100*0.001 -> 0.3449 | F100: ='Copia de Emisiones Energía'!F100*0.001 -> 0.3045 | G100: ='Copia de Emisiones Energía'!G100*0.001 -> 0.3293
C101: Gas natural [Mton CO2 eq] | D101: ='Copia de Emisiones Energía'!D101*0.001 -> 0.3227 | E101: ='Copia de Emisiones Energía'!E101*0.001 -> 0.297 | F101: ='Copia de Emisiones Energía'!F101*0.001 -> 0.2605 | G101: ='Copia de Emisiones Energía'!G101*0.001 -> 0.2881
C102: Total [Mton CO2 eq] | D102: =SUM(D100:D101) -> 0.6355 | E102: =SUM(E100:E101) -> 0.6419 | F102: =SUM(F100:F101) -> 0.565 | G102: =SUM(G100:G101) -> 0.6174
C104: Emisiones asociadas a consumo propio
C105: Petróleo [Mton CO2 eq] | D105: ='Copia de Emisiones Energía'!D105*0.001 -> 0.449 | E105: ='Copia de Emisiones Energía'!E105*0.001 -> 0.4854 | F105: ='Copia de Emisiones Energía'!F105*0.001 -> 0.4546 | G105: ='Copia de Emisiones Energía'!G105*0.001 -> 0.4375
C106: GLP [Mton CO2 eq] | D106: ='Copia de Emisiones Energía'!D106*0.001 -> 0.0494 | E106: ='Copia de Emisiones Energía'!E106*0.001 -> 0.0407 | F106: ='Copia de Emisiones Energía'!F106*0.001 -> 0.0417 | G106: ='Copia de Emisiones Energía'!G106*0.001 -> 0.0397
C107: Gasolina [Mton CO2 eq] | D107: ='Copia de Emisiones Energía'!D107*0.001 -> 0.0463 | E107: ='Copia de Emisiones Energía'!E107*0.001 -> 0.0514 | F107: ='Copia de Emisiones Energía'!F107*0.001 -> 0.0437 | G107: ='Copia de Emisiones Energía'!G107*0.001 -> 0.0491
C108: Kerosene/Jet Fuel [Mton CO2 eq] | D108: ='Copia de Emisiones Energía'!D108*0.001 -> 0.0089 | E108: ='Copia de Emisiones Energía'!E108*0.001 -> 0.0102 | F108: ='Copia de Emisiones Energía'!F108*0.001 -> 0.0093 | G108: ='Copia de Emisiones Energía'!G108*0.001 -> 0.0101
C109: Diesel oil [Mton CO2 eq] | D109: ='Copia de Emisiones Energía'!D109*0.001 -> 0.354 | E109: ='Copia de Emisiones Energía'!E109*0.001 -> 0.3625 | F109: ='Copia de Emisiones Energía'!F109*0.001 -> 0.3129 | G109: ='Copia de Emisiones Energía'!G109*0.001 -> 0.3274
C110: Fuel oil [Mton CO2 eq] | D110: ='Copia de Emisiones Energía'!D110*0.001 -> 0.6431 | E110: ='Copia de Emisiones Energía'!E110*0.001 -> 0.5855 | F110: ='Copia de Emisiones Energía'!F110*0.001 -> 0.4918 | G110: ='Copia de Emisiones Energía'!G110*0.001 -> 0.5839
C111: Gas de refinería [Mton CO2 eq] | D111: ='Copia de Emisiones Energía'!D111*0.001 -> 0.0965 | E111: ='Copia de Emisiones Energía'!E111*0.001 -> 0.0935 | F111: ='Copia de Emisiones Energía'!F111*0.001 -> 0.192 | G111: ='Copia de Emisiones Energía'!G111*0.001 -> 0.2049
C112: Total [Mton CO2 eq] | D112: =SUM(D105:D111) -> 1.6472 | E112: =SUM(E105:E111) -> 1.6292 | F112: =SUM(F105:F111) -> 1.546 | G112: =SUM(G105:G111) -> 1.6526
C115: Total emisiones de gases de efecto invernadero | D115: =SUM(D112,D102,D95,D78,D68,D56) -> 39.7202 | E115: =SUM(E112,E102,E95,E78,E68,E56) -> 39.0574 | F115: =SUM(F112,F102,F95,F78,F68,F56) -> 34.0756 | G115: =SUM(G112,G102,G95,G78,G68,G56) -> 37.9932
C118: Datos faltantes
C119: Petróleo quemado en autoproductoras eléctricas [PJ] | D119: ='Copia de Emisiones Energía'!D120*$D$134 -> 15.490148 | E119: ='Copia de Emisiones Energía'!E120*$D$134 -> 16.326872 | F119: ='Copia de Emisiones Energía'!F120*$D$134 -> 16.451713 | G119: ='Copia de Emisiones Energía'!G120*$D$134 -> 15.711378
C121: Factores de emisión de gen. eléctrica en autoproductores térmicos que queman petróleo [MtonCO2eq/PJ] | D121: =D71/D119 -> 0.073549976 | E121: =E71/E119 -> 0.073541335 | F121: =F71/F119 -> 0.073542492 | G121: =G71/G119 -> 0.073545429 | H121: * Se utiliza este factor de emisión para todas las PPI
C123: Factor de emisión de Refinerías por quema de petróleo [Mton CO2/PJ] | D123: ='Copia de Emisiones Energía'!D122*$D$140 -> 0.0733
C124: Petróleo utilizado para consumo en sistema de bombeo de oleoductos SOTE y OCP según BEN [PJ] | D124: ='Copia de Emisiones Energía'!D125/1000 -> 6.0819 | E124: ='Copia de Emisiones Energía'!E125/1000 -> 6.6057 | F124: ='Copia de Emisiones Energía'!F125/1000 -> 6.18666 | G124: ='Copia de Emisiones Energía'!G125/1000 -> 5.95386 | H124: =AVERAGE(D124:G124) -> 6.20703
D125: 7.5185926 | E125: 7.974793 | F125: 7.4680847 | G125: 7.2829706
C126: Emisiones totales del sistema de bombeo en tuberias de petróleo [MtonCO2eq] | D126: ='Copia de Emisiones Energía'!D128*0.001 -> 0.44580327 | E126: ='Copia de Emisiones Energía'!E128*0.001 -> 0.48419781 | F126: ='Copia de Emisiones Energía'!F128*0.001 -> 0.45348218 | G126: ='Copia de Emisiones Energía'!G128*0.001 -> 0.43641794
C129: Factores de conversión utilizados
...

Sheet Emisiones Energía
C1: Ecuador | D1: 2018 | E1: 2019 | F1: 2020 | G1: 2021 | H1: 2022 | I1: 2023 | J1: 2024 | K1: 2025 | L1: 2026 | M1: 2027 | N1: 2028 | O1: 2029 | P1: 2030 | Q1: 2031 | R1: 2032 | S1: 2033 | T1: 2034 | U1: 2035 | V1: 2036 | W1: 2037 | X1: 2038 | Y1: 2039 | Z1: 2040 | AA1: 2041 | AB1: 2042 | AC1: 2043 | AD1: 2044 | AE1: 2045 | AF1: 2046 | AG1: 2047 | AH1: 2048 | AI1: 2049 | AJ1: 2050
C4: Combustibles
C5: Factores de emisión para emisiones fugitivas | D5: -
A6: 1 | C6: Petróleo [Mton CO2/PJ] | D6: [Mton CO2/PJ] | E6: [Mton CH4CO2eq/PJ] | F6: [Mton NH4CO2eq/PJ] | I6: kbbl | J6: PJ | K6: Mton CO2 | L6: CH4CO2eq | M6: N2OCO2eq | N6: Technology in OSeMOSYS | O6: [Mton CO2/PJ] | P6: [Mton CH4CO2eq/PJ] | Q6: [Mton NH4CO2eq/PJ]
C7: Venteo | D7: ='Copia de Emisiones Energía'!D7*$D$132 -> 2.6011668e-06 | E7: =L7/J7 -> 0.00049255869 | G7: 1B2ai | H7: Venteo | I7: 188792.49 | J7: =I7*5.81/1000 -> 1096.8844 | K7: =J7*D7 -> 0.0028531792 | L7: 0.54027993 | M7: 0 | N7: PROCRU | O7: =D7+D8+D10+D11 -> 0.0011252264 | P7: =E7+E8+E10+E11 -> 0.00051438178 | Q7: =F7+F8+F10+F11 -> 5.2114728e-06
C8: Quema en antorcha | D8: ='Copia de Emisiones Energía'!D8*$D$132 -> 0.0011226088 | E8: =L8/J8 -> 1.7102732e-05 | F8: =M8/J8 -> 5.2114728e-06 | G8: 1B2aii | H8: Quema en antorcha | I8: 188792.49 | J8: =I8*5.81/1000 -> 1096.8844 | K8: =J8*D8 -> 1.2313721 | L8: 0.01875972 | M8: 0.005716383 | N8: PROCRU
C9: Exploración | D9: ='Copia de Emisiones Energía'!D9*$D$132 -> 2.7380703e-06 | E9: =L9/J9 -> 2.2575607e-05 | G9: 1B2aiii1 | H9: Exploración | I9: 188792.49 | J9: =I9*5.81/1000 -> 1096.8844 | K9: =J9*D9 -> 0.0030033465 | L9: 0.02476283 | M9: 0 | N9: RSVCRU | O9: =D9 -> 2.7380703e-06 | P9: =E9 -> 2.2575607e-05 | Q9: =F9 -> 0
C10: Producción y Refinación | D10: ='Copia de Emisiones Energía'!D10*$D$132 -> 3.0118773e-09 | E10: =L10/J10 -> 1.0261639e-06 | G10: 1B2aiii2 | H10: Producción y refinación | I10: 188792.49 | J10: =I10*5.81/1000 -> 1096.8844 | K10: =J10*D10 -> 3.3036811e-06 | L10: 0.0011255832 | M10: 0 | N10: PROCRU
C11: Transporte por tuberías | D11: ='Copia de Emisiones Energía'!D11*$D$132 -> 1.3416544e-08 | E11: =L11/J11 -> 3.6941902e-06 | G11: 1B2aiii3 | H11: Transporte | I11: 186735.23 | J11: =I11*5.81/1000 -> 1084.9317 | K11: =J11*D11 -> 1.4556034e-05 | L11: 0.0040079439 | M11: 0 | N11: PROCRU
C12: Refinación | E12: =L12/J12 -> 0 | G12: 1B2aiii4 | H12: Refinación | I12: 60569.318 | J12: =I12*5.81/1000 -> 351.90774 | K12: =J12*D12 -> 0 | N12: REFCRU | O12: =D12 -> 0 | P12: =E12 -> 0 | Q12: =F12 -> 0
A13: 2 | C13: Gas Natural [Mton CO2/PJ] | D13: -
C14: Quema en antorcha | D14: ='Copia de Emisiones Energía'!D13*$D$138 -> 0.034555559
C15: Exploración | D15: ='Copia de Emisiones Energía'!D14*$D$138 -> 0.0028796299
C16: Producción | D16: ='Copia de Emisiones Energía'!D15*$D$138 -> 0.00040314818
C17: Procesamiento | D17: ='Copia de Emisiones Energía'!D16*$D$138 -> 0.00034555559
C18: Transmisión y almacenamiento | D18: ='Copia de Emisiones Energía'!D17*$D$138 -> 2.5340743e-05
C19: Distribución | D19: ='Copia de Emisiones Energía'!D18*$D$138 -> 0.0014686112
C20: Carbón [Mton CO2/PJ] | D20: -
A22: 3 | C22: Factores de emisión por quema de combustible
G23: Gases de refinería [PJ] | H23: 2.3406026 | I23: 2.2529304 | J23: 1.8116965 | K23: 2.0050209
C24: 1A1a Producción de electricidad y calor como actividad principal | G24: Gases de refinería [PJ] | H24: 0.056913783 | I24: 0.054948154 | J24: 0.038947488 | K24: 0.041105793
C25: Factores de emisión [Mton CO2/PJ] | H25: =H23*#REF!*1000 -> #REF!
C26: Gas/Diesel Oil | D26: ='Copia de Emisiones Energía'!D25*$D$141 -> 0.0741
C27: Fuel oil residual | D27: ='Copia de Emisiones Energía'!D26*$D$141 -> 0.0774
C28: Gas Natural (seco) | D28: ='Copia de Emisiones Energía'!D27*$D$141 -> 0.0561
C29: Desechos municipales | D29: ='Copia de Emisiones Energía'!D28*$D$141 -> 0.1
C31: 1A1b Refinación del Petróleo | E31: Se usa el consumo propio total en PJ y las emisiones del INGEI
C32: Factores de emisión [Mton CO2/PJ] | F32: =Combustibles!E211 -> 373.48693 | G32: PJ
A33: 65.4 | C33: Gasolina | D33: ='Copia de Emisiones Energía'!D32*$D$141 -> 0.0693 | F33: 1195.47 | G33: Gg CO2eq
A34: 5.3 | C34: Queroseno | D34: ='Copia de Emisiones Energía'!D33*$D$141 -> 0.0715 | F34: =SUM(Combustibles!E217:E227) -> 0.0406 | G34: IAR Consumo propio
A35: 79.7 | C35: Gas/Diesel Oil | D35: ='Copia de Emisiones Energía'!D34*$D$141 -> 0.0741 | F35: =F34*F32 -> 15.163569 | G35: PJ Consumo Propio
A36: 134 | C36: Fuel oil residual | D36: ='Copia de Emisiones Energía'!D35*$D$141 -> 0.0774 | F36: =F33/F35/1000 -> 0.078838297 | G36: Mton CO2eq/PJ
A37: 2.85 | C37: Gas licuado de petróleo | D37: ='Copia de Emisiones Energía'!D36*$D$141 -> 0.0631 | F37: =F33/F35/1000 -> 0.078838297
C38: Gas de refinería | D38: ='Copia de Emisiones Energía'!D37*$D$141 -> 0.0576 | F38: =F34*F37*F32 -> 1.19547
C40: 1A4a Consumo
C41: Factores de emisión [Mton CO2/PJ]
C42: Gas natural | D42: ='Copia de Emisiones Energía'!D41*$D$141 -> 0.0561
C43: Leña | D43: ='Copia de Emisiones Energía'!D42*$D$141 -> 0.112 | E43: 1713 | F43: 1629
C44: Gas licuado de petróleo | D44: ='Copia de Emisiones Energía'!D43*$D$141 -> 0.0631 | E44: =E43-F43 -> 84
C45: Gasolina para motores | D45: ='Copia de Emisiones Energía'!D44*$D$141 -> 0.0693 | E45: =E44*F36*1000 -> 6622.417
C46: Gasolina para aviación | D46: ='Copia de Emisiones Energía'!D45*$D$141 -> 0.07 | E46: 3054 | F46: =E46-E45 -> -3568.417
C47: Queroseno | D47: ='Copia de Emisiones Energía'!D46*$D$141 -> 0.0715
C48: Gas/Diesel Oil | D48: ='Copia de Emisiones Energía'!D47*$D$141 -> 0.0741
C49: Fuel oil residual | D49: ='Copia de Emisiones Energía'!D48*$D$141 -> 0.0774
C50: Coque de petróleo | D50: ='Copia de Emisiones Energía'!D49*$D$141 -> 0.0975
C52: Emisiones asociadas a la producción
C53: Petróleo [Mton CO2 eq] | D53: ='Copia de Emisiones Energía'!D52*0.001 -> 0.1522 | E53: ='Copia de Emisiones Energía'!E52*0.001 -> 0.1641 | F53: ='Copia de Emisiones Energía'!F52*0.001 -> 0.1486 | G53: ='Copia de Emisiones Energía'!G52*0.001 -> 0.1461
C54: Líquidos de gas natural [Mton CO2 eq] | D54: ='Copia de Emisiones Energía'!D53*0.001 -> 0.004 | E54: ='Copia de Emisiones Energía'!E53*0.001 -> 0.0044 | F54: ='Copia de Emisiones Energía'!F53*0.001 -> 0.0039 | G54: ='Copia de Emisiones Energía'!G53*0.001 -> 0.0046
C55: Gas natural [Mton CO2 eq] | D55: ='Copia de Emisiones Energía'!D54*0.001 -> 0.0376 | E55: ='Copia de Emisiones Energía'!E54*0.001 -> 0.0362 | F55: ='Copia de Emisiones Energía'!F54*0.001 -> 0.0323 | G55: ='Copia de Emisiones Energía'!G54*0.001 -> 0.0326
C57: Total [Mton CO2 eq] | D57: =SUM(D53:D55) -> 0.1938 | E57: =SUM(E53:E55) -> 0.2047 | F57: =SUM(F53:F55) -> 0.1848 | G57: =SUM(G53:G55) -> 0.1833
C61: Electricidad
C62: Emisiones asociadas a la generación de electricidad en centrales electricas
C63: Petróleo [Mton CO2 eq] | D63: - | E63: - | F63: - | G63: ='Copia de Emisiones Energía'!G62*0.001 -> 0.014
C64: Gas natural [Mton CO2 eq] | D64: ='Copia de Emisiones Energía'!D63*0.001 -> 0.5695 | E64: ='Copia de Emisiones Energía'!E63*0.001 -> 0.5184 | F64: ='Copia de Emisiones Energía'!F63*0.001 -> 0.4431 | G64: ='Copia de Emisiones Energía'!G63*0.001 -> 0.392
C65: Productos de caña [Mton CO2 eq] | D65: - | E65: - | F65: - | G65: ='Copia de Emisiones Energía'!G64*0.001 -> 0.0381
C66: Diesel oil [Mton CO2 eq] | D66: ='Copia de Emisiones Energía'!D65*0.001 -> 0.2185 | E66: ='Copia de Emisiones Energía'!E65*0.001 -> 0.2682 | F66: ='Copia de Emisiones Energía'!F65*0.001 -> 0.2355 | G66: ='Copia de Emisiones Energía'!G65*0.001 -> 0.0986
C67: Fuel oil [Mton CO2 eq] | D67: ='Copia de Emisiones Energía'!D66*0.001 -> 1.9875 | E67: ='Copia de Emisiones Energía'!E66*0.001 -> 1.1076 | F67: ='Copia de Emisiones Energía'!F66*0.001 -> 1.0869 | G67: ='Copia de Emisiones Energía'!G66*0.001 -> 0.9628
C68: Otros productos de petróleo y gas [Mton CO2 eq] | D68: ='Copia de Emisiones Energía'!D67*0.001 -> 0.0005 | E68: ='Copia de Emisiones Energía'!E67*0.001 -> 0.0002 | F68: - | G68: -
C69: Total [Mton CO2 eq] | D69: =SUM(D63:D68) -> 2.776 | E69: =SUM(E63:E68) -> 1.8944 | F69: =SUM(F63:F68) -> 1.7655 | G69: =SUM(G63:G68) -> 1.5055
C71: Emisiones asociadas a la generación de electricidad en autoproductores
C72: Petróleo [Mton CO2 eq] | D72: ='Copia de Emisiones Energía'!D71*0.001 -> 1.1393 | E72: ='Copia de Emisiones Energía'!E71*0.001 -> 1.2007 | F72: ='Copia de Emisiones Energía'!F71*0.001 -> 1.2099 | G72: ='Copia de Emisiones Energía'!G71*0.001 -> 1.1555
C73: Gas natural [Mton CO2 eq] | D73: ='Copia de Emisiones Energía'!D72*0.001 -> 0.5466 | E73: ='Copia de Emisiones Energía'!E72*0.001 -> 0.4791 | F73: ='Copia de Emisiones Energía'!F72*0.001 -> 0.4183 | G73: ='Copia de Emisiones Energía'!G72*0.001 -> 0.4662
C74: Productos de caña [Mton CO2 eq] | D74: ='Copia de Emisiones Energía'!D73*0.001 -> 0.2779 | E74: ='Copia de Emisiones Energía'!E73*0.001 -> 0.3006 | F74: ='Copia de Emisiones Energía'!F73*0.001 -> 0.3101 | G74: ='Copia de Emisiones Energía'!G73*0.001 -> 0.2329
C75: GLP [Mton CO2 eq] | D75: ='Copia de Emisiones Energía'!D74*0.001 -> 0.0462 | E75: ='Copia de Emisiones Energía'!E74*0.001 -> 0.0369 | F75: ='Copia de Emisiones Energía'!F74*0.001 -> 0.0389 | G75: ='Copia de Emisiones Energía'!G74*0.001 -> 0.0363
C76: Diesel oil [Mton CO2 eq] | D76: ='Copia de Emisiones Energía'!D75*0.001 -> 0.9583 | E76: ='Copia de Emisiones Energía'!E75*0.001 -> 1.0486 | F76: ='Copia de Emisiones Energía'!F75*0.001 -> 1.0057 | G76: ='Copia de Emisiones Energía'!G75*0.001 -> 1.1934
C77: Fuel oil [Mton CO2 eq] | D77: ='Copia de Emisiones Energía'!D76*0.001 -> 0.07 | E77: ='Copia de Emisiones Energía'!E76*0.001 -> 0.0672 | F77: ='Copia de Emisiones Energía'!F76*0.001 -> 0.0672 | G77: ='Copia de Emisiones Energía'!G76*0.001 -> 0.0704
C78: Otros productos de petróleo y gas [Mton CO2 eq] | D78: ='Copia de Emisiones Energía'!D77*0.001 -> 0.0003 | E78: ='Copia de Emisiones Energía'!E77*0.001 -> 0.0002 | F78: ='Copia de Emisiones Energía'!F77*0.001 -> 0.0002 | G78: ='Copia de Emisiones Energía'!G77*0.001 -> 0.0002
C79: Total [Mton CO2 eq] | D79: =SUM(D72:D78) -> 3.0386 | E79: =SUM(E72:E78) -> 3.1333 | F79: =SUM(F72:F78) -> 3.0503 | G79: =SUM(G72:G78) -> 3.1549
C83: Demandas de combustibles
C84: Emisiones asociadas al consumo de combustibles
C85: Gas natural [Mton CO2 eq] | D85: ='Copia de Emisiones Energía'!D84*0.001 -> 0.1115 | E85: ='Copia de Emisiones Energía'!E84*0.001 -> 0.0898 | F85: ='Copia de Emisiones Energía'!F84*0.001 -> 0.0541 | G85: ='Copia de Emisiones Energía'!G84*0.001 -> 0.0942
C86: Leña [Mton CO2 eq] | D86: ='Copia de Emisiones Energía'!D85*0.001 -> 1.1983 | E86: ='Copia de Emisiones Energía'!E85*0.001 -> 1.1757 | F86: ='Copia de Emisiones Energía'!F85*0.001 -> 1.1331 | G86: ='Copia de Emisiones Energía'!G85*0.001 -> 1.0877
C87: Productos de caña [Mton CO2 eq] | D87: ='Copia de Emisiones Energía'!D86*0.001 -> 0.8368 | E87: ='Copia de Emisiones Energía'!E86*0.001 -> 0.9128 | F87: ='Copia de Emisiones Energía'!F86*0.001 -> 0.9264 | G87: ='Copia de Emisiones Energía'!G86*0.001 -> 0.7816
C88: GLP [Mton CO2 eq] | D88: ='Copia de Emisiones Energía'!D87*0.001 -> 3.2013 | E88: ='Copia de Emisiones Energía'!E87*0.001 -> 3.4309 | F88: ='Copia de Emisiones Energía'!F87*0.001 -> 3.466 | G88: ='Copia de Emisiones Energía'!G87*0.001 -> 3.5874
C89: Gasolina [Mton CO2 eq] | D89: ='Copia de Emisiones Energía'!D88*0.001 -> 11.3289 | E89: ='Copia de Emisiones Energía'!E88*0.001 -> 11.3761 | F89: ='Copia de Emisiones Energía'!F88*0.001 -> 8.9349 | G89: ='Copia de Emisiones Energía'!G88*0.001 -> 10.7243
C90: Kerosene/Jet Fuel [Mton CO2 eq] | D90: ='Copia de Emisiones Energía'!D89*0.001 -> 0.3754 | E90: ='Copia de Emisiones Energía'!E89*0.001 -> 0.3537 | F90: ='Copia de Emisiones Energía'!F89*0.001 -> 0.2411 | G90: ='Copia de Emisiones Energía'!G89*0.001 -> 0.3029
C91: Diesel oil [Mton CO2 eq] | D91: ='Copia de Emisiones Energía'!D90*0.001 -> 12.9334 | E91: ='Copia de Emisiones Energía'!E90*0.001 -> 12.778 | F91: ='Copia de Emisiones Energía'!F90*0.001 -> 10.964 | G91: ='Copia de Emisiones Energía'!G90*0.001 -> 12.2939
C92: Fuel oil [Mton CO2 eq] | D92: ='Copia de Emisiones Energía'!D91*0.001 -> 0.7844 | E92: ='Copia de Emisiones Energía'!E91*0.001 -> 0.8063 | F92: ='Copia de Emisiones Energía'!F91*0.001 -> 0.7573 | G92: ='Copia de Emisiones Energía'!G91*0.001 -> 0.867
C93: Coque [Mton CO2 eq] | D93: - | E93: - | F93: - | G93: ='Copia de Emisiones Energía'!G92*0.001 -> 0.5544
C94: No energéticos [Mton CO2 eq] | D94: ='Copia de Emisiones Energía'!D93*0.001 -> 0.6591 | E94: ='Copia de Emisiones Energía'!E93*0.001 -> 0.6306 | F94: ='Copia de Emisiones Energía'!F93*0.001 -> 0.4871 | G94: ='Copia de Emisiones Energía'!G93*0.001 -> 0.5861
C96: Total [Mton CO2 eq] | D96: =SUM(D85:D94) -> 31.4291 | E96: =SUM(E85:E94) -> 31.5539 | F96: =SUM(F85:F94) -> 26.964 | G96: =SUM(G85:G94) -> 30.8795
C100: Emisiones asociadas a centros de gas
C101: Líquidos de gas natural [Mton CO2 eq] | D101: ='Copia de Emisiones Energía'!D100*0.001 -> 0.3128 | E101: ='Copia de Emisiones Energía'!E100*0.001 -> 0.3449 | F101: ='Copia de Emisiones Energía'!F100*0.001 -> 0.3045 | G101: ='Copia de Emisiones Energía'!G100*0.001 -> 0.3293
C102: Gas natural [Mton CO2 eq] | D102: ='Copia de Emisiones Energía'!D101*0.001 -> 0.3227 | E102: ='Copia de Emisiones Energía'!E101*0.001 -> 0.297 | F102: ='Copia de Emisiones Energía'!F101*0.001 -> 0.2605 | G102: ='Copia de Emisiones Energía'!G101*0.001 -> 0.2881
C103: Total [Mton CO2 eq] | D103: =SUM(D101:D102) -> 0.6355 | E103: =SUM(E101:E102) -> 0.6419 | F103: =SUM(F101:F102) -> 0.565 | G103: =SUM(G101:G102) -> 0.6174
C105: Emisiones asociadas a consumo propio
C106: Petróleo [Mton CO2 eq] | D106: ='Copia de Emisiones Energía'!D105*0.001 -> 0.449 | E106: ='Copia de Emisiones Energía'!E105*0.001 -> 0.4854 | F106: ='Copia de Emisiones Energía'!F105*0.001 -> 0.4546 | G106: ='Copia de Emisiones Energía'!G105*0.001 -> 0.4375
C107: GLP [Mton CO2 eq] | D107: ='Copia de Emisiones Energía'!D106*0.001 -> 0.0494 | E107: ='Copia de Emisiones Energía'!E106*0.001 -> 0.0407 | F107: ='Copia de Emisiones Energía'!F106*0.001 -> 0.0417 | G107: ='Copia de Emisiones Energía'!G106*0.001 -> 0.0397
C108: Gasolina [Mton CO2 eq] | D108: ='Copia de Emisiones Energía'!D107*0.001 -> 0.0463 | E108: ='Copia de Emisiones Energía'!E107*0.001 -> 0.0514 | F108: ='Copia de Emisiones Energía'!F107*0.001 -> 0.0437 | G108: ='Copia de Emisiones Energía'!G107*0.001 -> 0.0491
C109: Kerosene/Jet Fuel [Mton CO2 eq] | D109: ='Copia de Emisiones Energía'!D108*0.001 -> 0.0089 | E109: ='Copia de Emisiones Energía'!E108*0.001 -> 0.0102 | F109: ='Copia de Emisiones Energía'!F108*0.001 -> 0.0093 | G109: ='Copia de Emisiones Energía'!G108*0.001 -> 0.0101
C110: Diesel oil [Mton CO2 eq] | D110: ='Copia de Emisiones Energía'!D109*0.001 -> 0.354 | E110: ='Copia de Emisiones Energía'!E109*0.001 -> 0.3625 | F110: ='Copia de Emisiones Energía'!F109*0.001 -> 0.3129 | G110: ='Copia de Emisiones Energía'!G109*0.001 -> 0.3274
C111: Fuel oil [Mton CO2 eq] | D111: ='Copia de Emisiones Energía'!D110*0.001 -> 0.6431 | E111: ='Copia de Emisiones Energía'!E110*0.001 -> 0.5855 | F111: ='Copia de Emisiones Energía'!F110*0.001 -> 0.4918 | G111: ='Copia de Emisiones Energía'!G110*0.001 -> 0.5839
C112: Gas de refinería [Mton CO2 eq] | D112: ='Copia de Emisiones Energía'!D111*0.001 -> 0.0965 | E112: ='Copia de Emisiones Energía'!E111*0.001 -> 0.0935 | F112: ='Copia de Emisiones Energía'!F111*0.001 -> 0.192 | G112: ='Copia de Emisiones Energía'!G111*0.001 -> 0.2049
C113: Total [Mton CO2 eq] | D113: =SUM(D106:D112) -> 1.6472 | E113: =SUM(E106:E112) -> 1.6292 | F113: =SUM(F106:F112) -> 1.546 | G113: =SUM(G106:G112) -> 1.6526
C116: Total emisiones de gases de efecto invernadero | D116: =SUM(D113,D103,D96,D79,D69,D57) -> 39.7202 | E116: =SUM(E113,E103,E96,E79,E69,E57) -> 39.0574 | F116: =SUM(F113,F103,F96,F79,F69,F57) -> 34.0756 | G116: =SUM(G113,G103,G96,G79,G69,G57) -> 37.9932
C119: Datos faltantes
C120: Petróleo quemado en autoproductoras eléctricas [PJ] | D120: ='Copia de Emisiones Energía'!D120*$D$135 -> 15.490148 | E120: ='Copia de Emisiones Energía'!E120*$D$135 -> 16.326872 | F120: ='Copia de Emisiones Energía'!F120*$D$135 -> 16.451713 | G120: ='Copia de Emisiones Energía'!G120*$D$135 -> 15.711378
C122: Factores de emisión de gen. eléctrica en autoproductores térmicos que queman petróleo [MtonCO2eq/PJ] | D122: =D72/D120 -> 0.073549976 | E122: =E72/E120 -> 0.073541335 | F122: =F72/F120 -> 0.073542492 | G122: =G72/G120 -> 0.073545429 | H122: * Se utiliza este factor de emisión para todas las PPI
C124: Factor de emisión de Refinerías por quema de petróleo [Mton CO2/PJ] | D124: ='Copia de Emisiones Energía'!D122*$D$141 -> 0.0733
C125: Petróleo utilizado para consumo en sistema de bombeo de oleoductos SOTE y OCP según BEN [PJ] | D125: ='Copia de Emisiones Energía'!D125/1000 -> 6.0819 | E125: ='Copia de Emisiones Energía'!E125/1000 -> 6.6057 | F125: ='Copia de Emisiones Energía'!F125/1000 -> 6.18666 | G125: ='Copia de Emisiones Energía'!G125/1000 -> 5.95386 | H125: =AVERAGE(D125:G125) -> 6.20703
...

Sheet Costos Energía
C1: Ecuador | D1: 2018 | E1: 2019 | F1: 2020 | G1: 2021 | H1: 2022 | I1: 2023 | J1: 2024 | K1: 2025 | L1: 2026 | M1: 2027 | N1: 2028 | O1: 2029 | P1: 2030 | Q1: 2031 | R1: 2032 | S1: 2033 | T1: 2034 | U1: 2035 | V1: 2036 | W1: 2037 | X1: 2038 | Y1: 2039 | Z1: 2040 | AA1: 2041 | AB1: 2042 | AC1: 2043 | AD1: 2044 | AE1: 2045 | AF1: 2046 | AG1: 2047 | AH1: 2048 | AI1: 2049 | AJ1: 2050
C4: Combustibles fósiles
C5: Costos variables de producción
A6: 1 | C6: Diésel oil [Millones de US$/PJ] | D6: 12.063902 | E6: 13.0199 | F6: 10.093 | G6: =AVERAGE(D6:F6) -> 11.725601 | H6: =AVERAGE(E6:G6) -> 11.612834 | I6: =AVERAGE(F6:H6) -> 11.143811 | J6: =AVERAGE(G6:I6) -> 11.494082 | K6: =AVERAGE(H6:J6) -> 11.416909 | L6: =AVERAGE(I6:K6) -> 11.351601 | M6: =AVERAGE(J6:L6) -> 11.420864 | N6: =AVERAGE(K6:M6) -> 11.396458 | ... AJ6: =AVERAGE(AG6:AI6) -> 11.397117
C7: Gasolina [Millones de US$/PJ] | D7: 10.984012 | E7: 13.8933 | F7: 13.0825 | G7: =AVERAGE(D7:F7) -> 12.653271 | H7: =AVERAGE(E7:G7) -> 13.20969 | I7: =AVERAGE(F7:H7) -> 12.98182 | J7: =AVERAGE(G7:I7) -> 12.94826 | K7: =AVERAGE(H7:J7) -> 13.04659 | L7: =AVERAGE(I7:K7) -> 12.992224 | M7: =AVERAGE(J7:L7) -> 12.995691 | N7: =AVERAGE(K7:M7) -> 13.011502 | ... AJ7: =AVERAGE(AG7:AI7) -> 13.003019
C8: GLP [Millones de US$/PJ] | D8: 3.4628884 | E8: 3.39569 | F8: 3.0584 | G8: =AVERAGE(D8:F8) -> 3.3056595 | H8: =AVERAGE(E8:G8) -> 3.2532498 | I8: =AVERAGE(F8:H8) -> 3.2057698 | J8: =AVERAGE(G8:I8) -> 3.254893 | K8: =AVERAGE(H8:J8) -> 3.2379709 | L8: =AVERAGE(I8:K8) -> 3.2328779 | M8: =AVERAGE(J8:L8) -> 3.2419139 | N8: =AVERAGE(K8:M8) -> 3.2375876 | ... AJ8: =AVERAGE(AG8:AI8) -> 3.2382448
C9: Fuel Oil [Millones de US$/PJ] | D9: 0.80418051 | E9: 0.78913 | F9: 0.55557 | G9: =AVERAGE(D9:F9) -> 0.7162935 | H9: =AVERAGE(E9:G9) -> 0.68699784 | I9: =AVERAGE(F9:H9) -> 0.65295378 | J9: =AVERAGE(G9:I9) -> 0.68541504 | K9: =AVERAGE(H9:J9) -> 0.67512222 | L9: =AVERAGE(I9:K9) -> 0.67116368 | M9: =AVERAGE(J9:L9) -> 0.67723365 | N9: =AVERAGE(K9:M9) -> 0.67450651 | ... AJ9: =AVERAGE(AG9:AI9) -> 0.67485843
C10: Jet Fuel [Millones de US$/PJ] | D10: 16.109516 | E10: 16.0865 | F10: 12.6517 | G10: =AVERAGE(D10:F10) -> 14.949239 | H10: =AVERAGE(E10:G10) -> 14.56248 | I10: =AVERAGE(F10:H10) -> 14.054473 | J10: =AVERAGE(G10:I10) -> 14.522064 | K10: =AVERAGE(H10:J10) -> 14.379672 | L10: =AVERAGE(I10:K10) -> 14.318736 | M10: =AVERAGE(J10:L10) -> 14.406824 | N10: =AVERAGE(K10:M10) -> 14.368411 | ... AJ10: =AVERAGE(AG10:AI10) -> 14.372936
C11: Gas Natural Fuel [Millones de US$/PJ]
C12: ...
C13: Total [Millones de US$/PJ] | D13: =SUM(D6:D10) -> 43.424499 | E13: =SUM(E6:E10) -> 47.18452 | F13: =SUM(F6:F10) -> 39.44117 | G13: =SUM(G6:G10) -> 43.350063 | H13: =SUM(H6:H10) -> 43.325251 | I13: =SUM(I6:I10) -> 42.038828 | J13: =SUM(J6:J10) -> 42.904714 | K13: =SUM(K6:K10) -> 42.756264 | ... AJ13: =SUM(AJ6:AJ10) -> 42.686175
C15: Costos fijos de producción
C16: Diésel oil [Millones de US$/PJ]
C17: Gasolina [Millones de US$/PJ]
C18: GLP [Millones de US$/PJ]
C19: Fuel Oil [Millones de US$/PJ]
C20: Jet Fuel [Millones de US$/PJ]
C21: Gas Natural Fuel [Millones de US$/PJ]
C22: ...
C23: Total [Millones de US$/PJ] | D23: =SUM(D16:D20) -> 0 | E23: =SUM(E16:E20) -> 0 | F23: =SUM(F16:F20) -> 0 | G23: =SUM(G16:G20) -> 0 | H23: =SUM(H16:H20) -> 0 | I23: =SUM(I16:I20) -> 0 | J23: =SUM(J16:J20) -> 0 | K23: =SUM(K16:K20) -> 0 | ... AJ23: =SUM(AJ16:AJ20) -> 0
C25: Costos capitales de producción
C26: Diésel oil [Millones de US$/PJ]
C27: Gasolina [Millones de US$/PJ]
C28: GLP [Millones de US$/PJ]
C29: Fuel Oil [Millones de US$/PJ]
C30: Jet Fuel [Millones de US$/PJ]
C31: Gas Natural Fuel [Millones de US$/PJ]
C32: ...
C33: Total [Millones de US$/PJ] | D33: =SUM(D26:D30) -> 0 | E33: =SUM(E26:E30) -> 0 | F33: =SUM(F26:F30) -> 0 | G33: =SUM(G26:G30) -> 0 | H33: =SUM(H26:H30) -> 0 | I33: =SUM(I26:I30) -> 0 | J33: =SUM(J26:J30) -> 0 | K33: =SUM(K26:K30) -> 0 | ... AJ33: =SUM(AJ26:AJ30) -> 0
C37: Otros combustibles
C38: Costos variables de los combustibles
C39: Leña [Millones de US$/PJ]
C40: Productos de caña [Millones de US$/PJ]
C41: Aceite de piñón [Millones de US$/PJ]
C42: Hidrógeno [Millones de US$/PJ]
C43: ...
C44: Total [Millones de US$/PJ] | D44: =SUM(D39:D41) -> 0 | E44: =SUM(E39:E41) -> 0 | F44: =SUM(F39:F41) -> 0 | G44: =SUM(G39:G41) -> 0 | H44: =SUM(H39:H41) -> 0 | I44: =SUM(I39:I41) -> 0 | J44: =SUM(J39:J41) -> 0 | K44: =SUM(K39:K41) -> 0 | ... AJ44: =SUM(AJ39:AJ41) -> 0
C46: Costos fijos de producción
C47: Leña [Millones de US$/PJ]
C48: Productos de caña [Millones de US$/PJ]
C49: Aceite de piñón [Millones de US$/PJ]
C50: Hidrógeno [Millones de US$/PJ]
C51: ...
C52: Total [Millones de US$/PJ] | D52: =SUM(D47:D49) -> 0 | E52: =SUM(E47:E49) -> 0 | F52: =SUM(F47:F49) -> 0 | G52: =SUM(G47:G49) -> 0 | H52: =SUM(H47:H49) -> 0 | I52: =SUM(I47:I49) -> 0 | J52: =SUM(J47:J49) -> 0 | K52: =SUM(K47:K49) -> 0 | ... AJ52: =SUM(AJ47:AJ49) -> 0
C54: Costos capitales de producción
C55: Leña [Millones de US$/PJ]
C56: Productos de caña [Millones de US$/PJ]
C57: Aceite de piñón [Millones de US$/PJ]
C58: Hidrógeno [Millones de US$/PJ]
C59: ...
C60: Total [Millones de US$/PJ] | D60: =SUM(D55:D57) -> 0 | E60: =SUM(E55:E57) -> 0 | F60: =SUM(F55:F57) -> 0 | G60: =SUM(G55:G57) -> 0 | H60: =SUM(H55:H57) -> 0 | I60: =SUM(I55:I57) -> 0 | J60: =SUM(J55:J57) -> 0 | K60: =SUM(K55:K57) -> 0 | ... AJ60: =SUM(AJ55:AJ57) -> 0
C64: Plantas de Generación
C65: Costos Capitales
C66: Biomasa [Millones de US$/GW]
A67: 2 | C67: Bagasse Sub-critical | D67: 1500 | E67: 1500 | F67: 1500 | G67: 1500 | H67: 1500 | I67: 1500 | J67: 1500 | K67: 1500 | L67: 1500 | M67: 1500 | N67: 1500 | O67: 1500 | P67: 1500 | Q67: 1500 | R67: 1500 | S67: 1500 | T67: 1500 | U67: 1500 | V67: 1500 | W67: 1500 | X67: 1500 | Y67: 1500 | Z67: 1500 | AA67: 1500 | AB67: 1500 | AC67: 1500 | AD67: 1500 | AE67: 1500 | AF67: 1500 | AG67: 1500 | AH67: 1500 | AI67: 1500 | AJ67: 1500
C68: Bagasse Sub-critical CCS | D68: 2785 | E68: 2785 | F68: 2785 | G68: 2785 | H68: 2785 | I68: 2785 | J68: 2785 | K68: 2785 | L68: 2785 | M68: 2785 | N68: 2785 | O68: 2785 | P68: 2785 | Q68: 2785 | R68: 2785 | S68: 2785 | T68: 2785 | U68: 2785 | V68: 2785 | W68: 2785 | X68: 2785 | Y68: 2785 | Z68: 2785 | AA68: 2785 | AB68: 2785 | AC68: 2785 | AD68: 2785 | AE68: 2785 | AF68: 2785 | AG68: 2785 | AH68: 2785 | AI68: 2785 | AJ68: 2785
C69: Existing Bagasse | D69: 2712 | E69: 2712 | F69: 2712 | G69: 2712 | H69: 2712 | I69: 2712 | J69: 2712 | K69: 2712 | L69: 2712 | M69: 2712 | N69: 2712 | O69: 2712 | P69: 2712 | Q69: 2712 | R69: 2712 | S69: 2712 | T69: 2712 | U69: 2712 | V69: 2712 | W69: 2712 | X69: 2712 | Y69: 2712 | Z69: 2712 | AA69: 2712 | AB69: 2712 | AC69: 2712 | AD69: 2712 | AE69: 2712 | AF69: 2712 | AG69: 2712 | AH69: 2712 | AI69: 2712 | AJ69: 2712
C70: New Bagasse | D70: 2712 | E70: 2712 | F70: 2712 | G70: 2712 | H70: 2712 | I70: 2712 | J70: 2712 | K70: 2606 | L70: 2606 | M70: 2606 | N70: 2606 | O70: 2606 | P70: 2500 | Q70: 2500 | R70: 2500 | S70: 2500 | T70: 2500 | U70: 2473 | V70: 2473 | W70: 2473 | X70: 2473 | Y70: 2473 | Z70: 2446 | AA70: 2446 | AB70: 2446 | AC70: 2446 | AD70: 2446 | AE70: 2419 | AF70: 2419 | AG70: 2419 | AH70: 2419 | AI70: 2419 | AJ70: 2392
C71: Integrated coal gasification combined cycle (IGCC) | D71: 2500 | E71: 2500 | F71: 2500 | G71: 2500 | H71: 2500 | I71: 2500 | J71: 2500 | K71: 2500 | L71: 2500 | M71: 2500 | N71: 2500 | O71: 2500 | P71: 2500 | Q71: 2500 | R71: 2500 | S71: 2500 | T71: 2500 | U71: 2500 | V71: 2500 | W71: 2500 | X71: 2500 | Y71: 2500 | Z71: 2500 | AA71: 2500 | AB71: 2500 | AC71: 2500 | AD71: 2500 | AE71: 2500 | AF71: 2500 | AG71: 2500 | AH71: 2500 | AI71: 2500 | AJ71: 2500
C72: Integrated coal gasification combined cycle (IGCC) with CCS | D72: 3300 | E72: 3300 | F72: 3300 | G72: 3300 | H72: 3300 | I72: 3300 | J72: 3300 | K72: 3300 | L72: 3300 | M72: 3300 | N72: 3300 | O72: 3300 | P72: 3300 | Q72: 3300 | R72: 3300 | S72: 3300 | T72: 3300 | U72: 3300 | V72: 3300 | W72: 3300 | X72: 3300 | Y72: 3300 | Z72: 3300 | AA72: 3300 | AB72: 3300 | AC72: 3300 | AD72: 3300 | AE72: 3300 | AF72: 3300 | AG72: 3300 | AH72: 3300 | AI72: 3300 | AJ72: 3300
C73: Solid waste [Millones de U+C88:C107S$/GW] | D73: 2350 | E73: 2350 | F73: 2350 | G73: 2350 | H73: 2350 | I73: 2350 | J73: 2350 | K73: 2325 | L73: 2325 | M73: 2325 | N73: 2325 | O73: 2325 | P73: 2300 | Q73: 2300 | R73: 2300 | S73: 2300 | T73: 2300 | U73: 2288 | V73: 2288 | W73: 2288 | X73: 2288 | Y73: 2288 | Z73: 2275 | AA73: 2275 | AB73: 2275 | AC73: 2275 | AD73: 2275 | AE73: 2263 | AF73: 2263 | AG73: 2263 | AH73: 2263 | AI73: 2263 | AJ73: 2250
C74: Geotérmico [Millones de US$/GW] | D74: 5855 | E74: 5085 | F74: 5085 | G74: 5085 | H74: 5085 | I74: 5085 | J74: 5085 | K74: 4755 | L74: 4755 | M74: 4755 | N74: 4755 | O74: 4755 | P74: 4424 | Q74: 4424 | R74: 4424 | S74: 4424 | T74: 4424 | U74: 4424 | V74: 4424 | W74: 4424 | X74: 4424 | Y74: 4424 | Z74: 4424 | AA74: 4424 | AB74: 4424 | AC74: 4424 | AD74: 4424 | AE74: 4424 | AF74: 4424 | AG74: 4424 | AH74: 4424 | AI74: 4424 | AJ74: 4424
C75: Hidroeléctrico represa [Millones de US$/GW]
C76: Pequeña (<50MW)
C77: Mediana (50MW-450MW) | D77: 5065 | E77: 5065 | F77: 5065 | G77: 5065 | H77: 5065 | I77: 5065 | J77: 5065 | K77: 5065 | L77: 5065 | M77: 5065 | N77: 5065 | O77: 5065 | P77: 5065 | Q77: 5065 | R77: 5065 | S77: 5065 | T77: 5065 | U77: 5065 | V77: 5065 | W77: 5065 | X77: 5065 | Y77: 5065 | Z77: 5065 | AA77: 5065 | AB77: 5065 | AC77: 5065 | AD77: 5065 | AE77: 5065 | AF77: 5065 | AG77: 5065 | AH77: 5065 | AI77: 5065 | AJ77: 5065
C78: Grande >450MW | D78: 3360 | E78: 3360 | F78: 3360 | G78: 3360 | H78: 3360 | I78: 3360 | J78: 3360 | K78: 3360 | L78: 3360 | M78: 3360 | N78: 3360 | O78: 3360 | P78: 3360 | Q78: 3360 | R78: 3360 | S78: 3360 | T78: 3360 | U78: 3360 | V78: 3360 | W78: 3360 | X78: 3360 | Y78: 3360 | Z78: 3360 | AA78: 3360 | AB78: 3360 | AC78: 3360 | AD78: 3360 | AE78: 3360 | AF78: 3360 | AG78: 3360 | AH78: 3360 | AI78: 3360 | AJ78: 3360
C79: Hidroeléctrico filo de agua [Millones de US$/GW]
C80: Pequeña (<50MW) | D80: 5275 | E80: 5275 | F80: 5275 | G80: 5275 | H80: 5275 | I80: 5275 | J80: 5275 | K80: 5275 | L80: 5275 | M80: 5275 | N80: 5275 | O80: 5275 | P80: 5275 | Q80: 5275 | R80: 5275 | S80: 5275 | T80: 5275 | U80: 5275 | V80: 5275 | W80: 5275 | X80: 5275 | Y80: 5275 | Z80: 5275 | AA80: 5275 | AB80: 5275 | AC80: 5275 | AD80: 5275 | AE80: 5275 | AF80: 5275 | AG80: 5275 | AH80: 5275 | AI80: 5275 | AJ80: 5275
C81: Mediana (50MW-450MW) | D81: 3518 | E81: 3518 | F81: 3518 | G81: 3518 | H81: 3518 | I81: 3518 | J81: 3518 | K81: 3518 | L81: 3518 | M81: 3518 | N81: 3518 | O81: 3518 | P81: 3518 | Q81: 3518 | R81: 3518 | S81: 3518 | T81: 3518 | U81: 3518 | V81: 3518 | W81: 3518 | X81: 3518 | Y81: 3518 | Z81: 3518 | AA81: 3518 | AB81: 3518 | AC81: 3518 | AD81: 3518 | AE81: 3518 | AF81: 3518 | AG81: 3518 | AH81: 3518 | AI81: 3518 | AJ81: 3518
C82: Grande >450MW | D82: 3465 | E82: 3465 | F82: 3465 | G82: 3465 | H82: 3465 | I82: 3465 | J82: 3465 | K82: 3465 | L82: 3465 | M82: 3465 | N82: 3465 | O82: 3465 | P82: 3465 | Q82: 3465 | R82: 3465 | S82: 3465 | T82: 3465 | U82: 3465 | V82: 3465 | W82: 3465 | X82: 3465 | Y82: 3465 | Z82: 3465 | AA82: 3465 | AB82: 3465 | AC82: 3465 | AD82: 3465 | AE82: 3465 | AF82: 3465 | AG82: 3465 | AH82: 3465 | AI82: 3465 | AJ82: 3465
C83: Natural Gas [Millones de US$/GW]
C84: Existentes | D84: 869 | E84: 869 | F84: 869 | G84: 869 | H84: 869 | I84: 869 | J84: 869 | K84: 869 | L84: 869 | M84: 869 | N84: 869 | O84: 869 | P84: 869 | Q84: 869 | R84: 869 | S84: 869 | T84: 869 | U84: 869 | V84: 869 | W84: 869 | X84: 869 | Y84: 869 | Z84: 869 | AA84: 869 | AB84: 869 | AC84: 869 | AD84: 869 | AE84: 869 | AF84: 869 | AG84: 869 | AH84: 869 | AI84: 869 | AJ84: 869
C85: Open Cycle | D85: 869 | E85: 845 | F85: 845 | G85: 845 | H85: 845 | I85: 845 | J85: 845 | K85: 825 | L85: 825 | M85: 825 | N85: 825 | O85: 825 | P85: 805 | Q85: 805 | R85: 805 | S85: 805 | T85: 805 | U85: 790 | V85: 790 | W85: 790 | X85: 790 | Y85: 790 | Z85: 775 | AA85: 775 | AB85: 775 | AC85: 775 | AD85: 775 | AE85: 759 | AF85: 759 | AG85: 759 | AH85: 759 | AI85: 759 | AJ85: 744
C86: Close Cycle | D86: 1190 | E86: 1000 | F86: 1000 | G86: 1000 | H86: 1000 | I86: 1000 | J86: 1000 | K86: 991.5 | L86: 991.5 | M86: 991.5 | N86: 991.5 | O86: 991.5 | P86: 983 | Q86: 983 | R86: 983 | S86: 983 | T86: 983 | U86: 965.5 | V86: 965.5 | W86: 965.5 | X86: 965.5 | Y86: 965.5 | Z86: 948 | AA86: 948 | AB86: 948 | AC86: 948 | AD86: 948 | AE86: 930.5 | AF86: 930.5 | AG86: 930.5 | AH86: 930.5 | AI86: 930.5 | AJ86: 913
C87: Close Cycle with CCS | D87: 2450 | E87: 2450 | F87: 2450 | G87: 2450 | H87: 2450 | I87: 2450 | J87: 2450 | K87: 2325 | L87: 2325 | M87: 2325 | N87: 2325 | O87: 2325 | P87: 2200 | Q87: 2200 | R87: 2200 | S87: 2200 | T87: 2200 | U87: 2175 | V87: 2175 | W87: 2175 | X87: 2175 | Y87: 2175 | Z87: 2150 | AA87: 2150 | AB87: 2150 | AC87: 2150 | AD87: 2150 | AE87: 2125 | AF87: 2125 | AG87: 2125 | AH87: 2125 | AI87: 2125 | AJ87: 2100
C88: Diesel [Millones de US$/GW]
C89: Existing Steam
C90: Existing Internal combustion engine
C91: Heavy oil [Millones de US$/GW]
C92: Existing Steam
C93: Existing Internal combustion engine
C94: Ranking Cycle | D94: 1770 | E94: 1770 | F94: 1770 | G94: 1770 | H94: 1770 | I94: 1770 | J94: 1770 | K94: 1770 | L94: 1770 | M94: 1770 | N94: 1770 | O94: 1770 | P94: 1770 | Q94: 1770 | R94: 1770 | S94: 1770 | T94: 1770 | U94: 1770 | V94: 1770 | W94: 1770 | X94: 1770 | Y94: 1770 | Z94: 1770 | AA94: 1770 | AB94: 1770 | AC94: 1770 | AD94: 1770 | AE94: 1770 | AF94: 1770 | AG94: 1770 | AH94: 1770 | AI94: 1770 | AJ94: 1770
C95: Ranking Cycle with CCS | D95: 4500 | E95: 4500 | F95: 4500 | G95: 4500 | H95: 4500 | I95: 4500 | J95: 4500 | K95: 4500 | L95: 4500 | M95: 4500 | N95: 4500 | O95: 4500 | P95: 4500 | Q95: 4500 | R95: 4500 | S95: 4500 | T95: 4500 | U95: 4400 | V95: 4400 | W95: 4400 | X95: 4400 | Y95: 4400 | Z95: 4300 | AA95: 4300 | AB95: 4300 | AC95: 4300 | AD95: 4300 | AE95: 4200 | AF95: 4200 | AG95: 4200 | AH95: 4200 | AI95: 4200 | AJ95: 4100
C96: Carbón [Millones de US$/GW]
C97: Sin CCS | D97: 2500 | E97: 2500 | F97: 2500 | G97: 2500 | H97: 2500 | I97: 2500 | J97: 2500 | K97: 2500 | L97: 2500 | M97: 2500 | N97: 2500 | O97: 2500 | P97: 2500 | Q97: 2500 | R97: 2500 | S97: 2500 | T97: 2500 | U97: 2250 | V97: 2250 | W97: 2250 | X97: 2250 | Y97: 2250 | Z97: 1875 | AA97: 1875 | AB97: 1875 | AC97: 1875 | AD97: 1875 | AE97: 1875 | AF97: 1875 | AG97: 1875 | AH97: 1875 | AI97: 1875 | AJ97: 1875
C98: Con CCS | D98: 4275 | E98: 4275 | F98: 4275 | G98: 4275 | H98: 4275 | I98: 4275 | J98: 4275 | K98: 4275 | L98: 4275 | M98: 4275 | N98: 4275 | O98: 4275 | P98: 4275 | Q98: 4275 | R98: 4275 | S98: 4275 | T98: 4275 | U98: 4275 | V98: 4275 | W98: 4275 | X98: 4275 | Y98: 4275 | Z98: 3563 | AA98: 3563 | AB98: 3563 | AC98: 3563 | AD98: 3563 | AE98: 3563 | AF98: 3563 | AG98: 3563 | AH98: 3563 | AI98: 3563 | AJ98: 3563
C99: Solar [Millones de US$/GW]
C100: Existente FV | D100: 1980
C101: Nuevo FV | D101: 1980 | E101: 1360 | F101: 1360 | G101: 1360 | H101: 1360 | I101: 1360 | J101: 1360 | K101: 1220 | L101: 1220 | M101: 1220 | N101: 1220 | O101: 1220 | P101: 1080 | Q101: 1080 | R101: 1080 | S101: 1080 | T101: 1080 | U101: 1050 | V101: 1050 | W101: 1050 | X101: 1050 | Y101: 1050 | Z101: 1020 | AA101: 1020 | AB101: 1020 | AC101: 1020 | AD101: 1020 | AE101: 990 | AF101: 990 | AG101: 990 | AH101: 990 | AI101: 990 | AJ101: 960
C102: FV generación distribuida | D102: 1980 | E102: 1360 | F102: 1360 | G102: 1360 | H102: 1360 | I102: 1360 | J102: 1360 | K102: 1220 | L102: 1220 | M102: 1220 | N102: 1220 | O102: 1220 | P102: 1080 | Q102: 1080 | R102: 1080 | S102: 1080 | T102: 1080 | U102: 1050 | V102: 1050 | W102: 1050 | X102: 1050 | Y102: 1050 | Z102: 1020 | AA102: 1020 | AB102: 1020 | AC102: 1020 | AD102: 1020 | AE102: 990 | AF102: 990 | AG102: 990 | AH102: 990 | AI102: 990 | AJ102: 960
C103: Solar CSP | D103: 7254 | E103: 6849 | F103: 6849 | G103: 6849 | H103: 6849 | I103: 6849 | J103: 6849 | K103: 6445 | L103: 6445 | M103: 6445 | N103: 6445 | O103: 6445 | P103: 6040 | Q103: 6040 | R103: 6040 | S103: 6040 | T103: 6040 | U103: 5636 | V103: 5636 | W103: 5636 | X103: 5636 | Y103: 5636 | Z103: 5231 | AA103: 5231 | AB103: 5231 | AC103: 5231 | AD103: 5231 | AE103: 4827 | AF103: 4827 | AG103: 4827 | AH103: 4827 | AI103: 4827 | AJ103: 4422
C104: …
C106: Total [Millones de US$/kW]
C108: Costos Fijos
C109: Biomasa [Millones de US$/GW-año]
C110: Bagasse Sub-critical | D110: 96 | E110: 96 | F110: 96 | G110: 96 | H110: 96 | I110: 96 | J110: 96 | K110: 96 | L110: 96 | M110: 96 | N110: 96 | O110: 96 | P110: 96 | Q110: 96 | R110: 96 | S110: 96 | T110: 96 | U110: 96 | V110: 96 | W110: 96 | X110: 96 | Y110: 96 | Z110: 96 | AA110: 96 | AB110: 96 | AC110: 96 | AD110: 96 | AE110: 96 | AF110: 96 | AG110: 96 | AH110: 96 | AI110: 96 | AJ110: 96
C111: Bagasse Sub-critical CCS | D111: 150 | E111: 150 | F111: 150 | G111: 150 | H111: 150 | I111: 150 | J111: 150 | K111: 150 | L111: 150 | M111: 150 | N111: 150 | O111: 150 | P111: 150 | Q111: 150 | R111: 150 | S111: 150 | T111: 150 | U111: 150 | V111: 150 | W111: 150 | X111: 150 | Y111: 150 | Z111: 150 | AA111: 150 | AB111: 150 | AC111: 150 | AD111: 150 | AE111: 150 | AF111: 150 | AG111: 150 | AH111: 150 | AI111: 150 | AJ111: 150
C112: Existing Bagasse | D112: 90 | E112: 90 | F112: 90 | G112: 90 | H112: 90 | I112: 90 | J112: 90 | K112: 90 | L112: 90 | M112: 90 | N112: 90 | O112: 90 | P112: 90 | Q112: 90 | R112: 90 | S112: 90 | T112: 90 | U112: 90 | V112: 90 | W112: 90 | X112: 90 | Y112: 90 | Z112: 90 | AA112: 90 | AB112: 90 | AC112: 90 | AD112: 90 | AE112: 90 | AF112: 90 | AG112: 90 | AH112: 90 | AI112: 90 | AJ112: 90
C113: New Bagasse | D113: 95 | E113: 95 | F113: 95 | G113: 95 | H113: 95 | I113: 95 | J113: 95 | K113: 91 | L113: 91 | M113: 91 | N113: 91 | O113: 91 | P113: 88 | Q113: 88 | R113: 88 | S113: 88 | T113: 88 | U113: 87 | V113: 87 | W113: 87 | X113: 87 | Y113: 87 | Z113: 86 | AA113: 86 | AB113: 86 | AC113: 86 | AD113: 86 | AE113: 85 | AF113: 85 | AG113: 85 | AH113: 85 | AI113: 85 | AJ113: 84
C114: Integrated coal gasification combined cycle (IGCC) | D114: 160 | E114: 160 | F114: 160 | G114: 160 | H114: 160 | I114: 160 | J114: 160 | K114: 160 | L114: 160 | M114: 160 | N114: 160 | O114: 160 | P114: 160 | Q114: 160 | R114: 160 | S114: 160 | T114: 160 | U114: 160 | V114: 160 | W114: 160 | X114: 160 | Y114: 160 | Z114: 160 | AA114: 160 | AB114: 160 | AC114: 160 | AD114: 160 | AE114: 160 | AF114: 160 | AG114: 160 | AH114: 160 | AI114: 160 | AJ114: 160
...

Sheet Costos Energía (2)
C1: Ecuador | D1: 2018 | E1: 2019 | F1: 2020 | G1: 2021 | H1: 2022 | I1: 2023 | J1: 2024 | K1: 2025 | L1: 2026 | M1: 2027 | N1: 2028 | O1: 2029 | P1: 2030 | Q1: 2031 | R1: 2032 | S1: 2033 | T1: 2034 | U1: 2035 | V1: 2036 | W1: 2037 | X1: 2038 | Y1: 2039 | Z1: 2040 | AA1: 2041 | AB1: 2042 | AC1: 2043 | AD1: 2044 | AE1: 2045 | AF1: 2046 | AG1: 2047 | AH1: 2048 | AI1: 2049 | AJ1: 2050
C4: Combustibles fósiles
C5: Costos variables de producción
A6: 1 | C6: Diésel oil [Millones de US$/PJ] | D6: 12.063902 | E6: 13.0199 | F6: 10.093 | G6: =AVERAGE(D6:F6) -> 11.725601 | H6: =AVERAGE(E6:G6) -> 11.612834 | I6: =AVERAGE(F6:H6) -> 11.143811 | J6: =AVERAGE(G6:I6) -> 11.494082 | K6: =AVERAGE(H6:J6) -> 11.416909 | L6: =AVERAGE(I6:K6) -> 11.351601 | M6: =AVERAGE(J6:L6) -> 11.420864 | N6: =AVERAGE(K6:M6) -> 11.396458 | ... AJ6: =AVERAGE(AG6:AI6) -> 11.397117
C7: Gasolina [Millones de US$/PJ] | D7: 10.984012 | E7: 13.8933 | F7: 13.0825 | G7: =AVERAGE(D7:F7) -> 12.653271 | H7: =AVERAGE(E7:G7) -> 13.20969 | I7: =AVERAGE(F7:H7) -> 12.98182 | J7: =AVERAGE(G7:I7) -> 12.94826 | K7: =AVERAGE(H7:J7) -> 13.04659 | L7: =AVERAGE(I7:K7) -> 12.992224 | M7: =AVERAGE(J7:L7) -> 12.995691 | N7: =AVERAGE(K7:M7) -> 13.011502 | ... AJ7: =AVERAGE(AG7:AI7) -> 13.003019
C8: GLP [Millones de US$/PJ] | D8: 3.4628884 | E8: 3.39569 | F8: 3.0584 | G8: =AVERAGE(D8:F8) -> 3.3056595 | H8: =AVERAGE(E8:G8) -> 3.2532498 | I8: =AVERAGE(F8:H8) -> 3.2057698 | J8: =AVERAGE(G8:I8) -> 3.254893 | K8: =AVERAGE(H8:J8) -> 3.2379709 | L8: =AVERAGE(I8:K8) -> 3.2328779 | M8: =AVERAGE(J8:L8) -> 3.2419139 | N8: =AVERAGE(K8:M8) -> 3.2375876 | ... AJ8: =AVERAGE(AG8:AI8) -> 3.2382448
C9: Fuel Oil [Millones de US$/PJ] | D9: 0.80418051 | E9: 0.78913 | F9: 0.55557 | G9: =AVERAGE(D9:F9) -> 0.7162935 | H9: =AVERAGE(E9:G9) -> 0.68699784 | I9: =AVERAGE(F9:H9) -> 0.65295378 | J9: =AVERAGE(G9:I9) -> 0.68541504 | K9: =AVERAGE(H9:J9) -> 0.67512222 | L9: =AVERAGE(I9:K9) -> 0.67116368 | M9: =AVERAGE(J9:L9) -> 0.67723365 | N9: =AVERAGE(K9:M9) -> 0.67450651 | ... AJ9: =AVERAGE(AG9:AI9) -> 0.67485843
C10: Jet Fuel [Millones de US$/PJ] | D10: 16.109516 | E10: 16.0865 | F10: 12.6517 | G10: =AVERAGE(D10:F10) -> 14.949239 | H10: =AVERAGE(E10:G10) -> 14.56248 | I10: =AVERAGE(F10:H10) -> 14.054473 | J10: =AVERAGE(G10:I10) -> 14.522064 | K10: =AVERAGE(H10:J10) -> 14.379672 | L10: =AVERAGE(I10:K10) -> 14.318736 | M10: =AVERAGE(J10:L10) -> 14.406824 | N10: =AVERAGE(K10:M10) -> 14.368411 | ... AJ10: =AVERAGE(AG10:AI10) -> 14.372936
C11: Gas Natural Fuel [Millones de US$/PJ]
C12: ...
C13: Total [Millones de US$/PJ] | D13: =SUM(D6:D10) -> 43.424499 | E13: =SUM(E6:E10) -> 47.18452 | F13: =SUM(F6:F10) -> 39.44117 | G13: =SUM(G6:G10) -> 43.350063 | H13: =SUM(H6:H10) -> 43.325251 | I13: =SUM(I6:I10) -> 42.038828 | J13: =SUM(J6:J10) -> 42.904714 | K13: =SUM(K6:K10) -> 42.756264 | ... AJ13: =SUM(AJ6:AJ10) -> 42.686175
A15: 2 | C15: Costos fijos de producción
C16: Diésel oil [Millones de US$/PJ] | D16: 0.2008
C17: Gasolina [Millones de US$/PJ] | D17: 0.2097
C18: GLP [Millones de US$/PJ] | D18: 0.0139
C19: Fuel Oil [Millones de US$/PJ] | D19: 0.441
C20: Kerosene [Millones de US$/PJ] | D20: 0.0489
C21: Petroleum gases [Millones de US$/PJ] | D21: 0.0005
C22: ...
C23: Total [Millones de US$/PJ] | D23: =SUM(D16:D21) -> 0.9148 | E23: =SUM(E16:E21) -> 0 | F23: =SUM(F16:F21) -> 0 | G23: =SUM(G16:G21) -> 0 | H23: =SUM(H16:H21) -> 0 | I23: =SUM(I16:I21) -> 0 | J23: =SUM(J16:J21) -> 0 | K23: =SUM(K16:K21) -> 0 | ... AJ23: =SUM(AJ16:AJ21) -> 0
A25: 2 | C25: Costos capitales de producción
C26: Diésel oil [Millones de US$/PJ] | D26: 2.68
C27: Gasolina [Millones de US$/PJ] | D27: 2.8
C28: GLP [Millones de US$/PJ] | D28: 0.19
C29: Fuel Oil [Millones de US$/PJ] | D29: 5.88
C30: Kerosene [Millones de US$/PJ] | D30: 0.65
C31: Petroleum gases [Millones de US$/PJ] | D31: 0.01
C32: ...
C33: Total [Millones de US$/PJ] | D33: =SUM(D26:D30) -> 12.2 | E33: =SUM(E26:E30) -> 0 | F33: =SUM(F26:F30) -> 0 | G33: =SUM(G26:G30) -> 0 | H33: =SUM(H26:H30) -> 0 | I33: =SUM(I26:I30) -> 0 | J33: =SUM(J26:J30) -> 0 | K33: =SUM(K26:K30) -> 0 | ... AJ33: =SUM(AJ26:AJ30) -> 0
A35: 3 | C35: Costos de importación
C36: Gasolina [US$/BEP] | D36: 87.9 | E36: 79.6 | F36: 58.1 | G36: 88.6
C37: Diésel oil [US$/BEP] | D37: 90 | E37: 84.1 | F37: 57.1 | G37: 84.6
C38: GLP [US$/BEP] | D38: 47.5 | E38: 32.1 | F38: 28.5 | G38: 54.7
C39: Electricidad Colombia [MUS$/PJ] | D39: 12.13 | E39: 13.34 | F39: 14.03 | G39: 7.09
C40: Electricidad Perú [MUS$/PJ] | D40: Entre 2017 y 2021 no se reporta importación de electricidad desde Perú. En el período 2014-2016 se importó energía desde perú a un valor promedio de 14.71[MUS$/PJ]
C44: Otros combustibles
C45: Costos variables de los combustibles
C46: Leña [Millones de US$/PJ]
C47: Productos de caña [Millones de US$/PJ]
C48: Aceite de piñón [Millones de US$/PJ]
A49: 4 | C49: Hidrógeno [Millones de US$/PJ] | D49: 1.27 | E49: 1.27 | F49: 1.27 | G49: 1.27 | H49: 1.27 | I49: 1.27 | J49: 1.27 | K49: 1.27 | L49: 1.27 | M49: 1.27 | N49: 1.27 | O49: 1.27 | P49: 1.27 | Q49: 1.27 | R49: 1.27 | S49: 1.27 | T49: 1.27 | U49: 1.27 | V49: 1.27 | W49: 1.27 | X49: 1.27 | Y49: 1.27 | Z49: 1.27 | AA49: 1.27 | AB49: 1.27 | AC49: 1.27 | AD49: 1.27 | AE49: 1.27 | AF49: 1.27 | AG49: 1.27 | AH49: 1.27 | AI49: 1.27 | AJ49: 1.27
C50: ...
C51: Total [Millones de US$/PJ] | D51: =SUM(D46:D48) -> 0 | E51: =SUM(E46:E48) -> 0 | F51: =SUM(F46:F48) -> 0 | G51: =SUM(G46:G48) -> 0 | H51: =SUM(H46:H48) -> 0 | I51: =SUM(I46:I48) -> 0 | J51: =SUM(J46:J48) -> 0 | K51: =SUM(K46:K48) -> 0 | ... AJ51: =SUM(AJ46:AJ48) -> 0
C53: Costos fijos de producción
C54: Leña [Millones de US$/PJ]
C55: Productos de caña [Millones de US$/PJ]
C56: Aceite de piñón [Millones de US$/PJ]
C57: Hidrógeno [Millones de US$/PJ]
C58: ...
C59: Total [Millones de US$/PJ] | D59: =SUM(D54:D56) -> 0 | E59: =SUM(E54:E56) -> 0 | F59: =SUM(F54:F56) -> 0 | G59: =SUM(G54:G56) -> 0 | H59: =SUM(H54:H56) -> 0 | I59: =SUM(I54:I56) -> 0 | J59: =SUM(J54:J56) -> 0 | K59: =SUM(K54:K56) -> 0 | ... AJ59: =SUM(AJ54:AJ56) -> 0
C61: Costos capitales de producción
C62: Leña [Millones de US$/PJ]
C63: Productos de caña [Millones de US$/PJ]
C64: Aceite de piñón [Millones de US$/PJ]
A65: 4 | C65: Hidrógeno [Millones de US$/PJ]
C66: Electrolyzer (Alkaline Electrolyzer Type) | D66: 35.32 | E66: 35.32 | F66: 34.34 | G66: 34.34 | H66: 34.34 | I66: 34.34 | J66: 34.34 | K66: 33.77 | L66: 33.77 | M66: 33.77 | N66: 33.77 | O66: 33.77 | P66: 23.37 | Q66: 23.37 | R66: 23.37 | S66: 23.37 | T66: 23.37 | U66: 23.37 | V66: 23.37 | W66: 23.37 | X66: 23.37 | Y66: 23.37 | Z66: 23.37 | AA66: 23.37 | AB66: 23.37 | AC66: 23.37 | AD66: 23.37 | AE66: 23.37 | AF66: 23.37 | AG66: 23.37 | AH66: 23.37 | AI66: 23.37 | AJ66: 23.37
C67: Electrolyzer (Proton Exchange Membrane Type) | D67: 35.32 | E67: 35.32 | F67: 35.32 | G67: 35.32 | H67: 35.32 | I67: 35.32 | J67: 35.32 | K67: 33.77 | L67: 33.77 | M67: 33.77 | N67: 33.77 | O67: 33.77 | P67: 23.37 | Q67: 23.37 | R67: 23.37 | S67: 23.37 | T67: 23.37 | U67: 23.37 | V67: 23.37 | W67: 23.37 | X67: 23.37 | Y67: 23.37 | Z67: 23.37 | AA67: 23.37 | AB67: 23.37 | AC67: 23.37 | AD67: 23.37 | AE67: 23.37 | AF67: 23.37 | AG67: 23.37 | AH67: 23.37 | AI67: 23.37 | AJ67: 23.37
C68: Electrolyzer (Solid Oxide Electrolyzer Cell Type) | D68: 73.09 | E68: 73.09 | F68: 34.09 | G68: 34.09 | H68: 34.09 | I68: 34.09 | J68: 34.09 | K68: 33.52 | L68: 33.52 | M68: 33.52 | N68: 33.52 | O68: 33.52 | P68: 23.37 | Q68: 23.37 | R68: 23.37 | S68: 23.37 | T68: 23.37 | U68: 23.37 | V68: 23.37 | W68: 23.37 | X68: 23.37 | Y68: 23.37 | Z68: 23.37 | AA68: 23.37 | AB68: 23.37 | AC68: 23.37 | AD68: 23.37 | AE68: 23.37 | AF68: 23.37 | AG68: 23.37 | AH68: 23.37 | AI68: 23.37 | AJ68: 23.37
C69: ...
C70: Total [Millones de US$/PJ] | D70: =SUM(D62:D64) -> 0 | E70: =SUM(E62:E64) -> 0 | F70: =SUM(F62:F64) -> 0 | G70: =SUM(G62:G64) -> 0 | H70: =SUM(H62:H64) -> 0 | I70: =SUM(I62:I64) -> 0 | J70: =SUM(J62:J64) -> 0 | K70: =SUM(K62:K64) -> 0 | ... AJ70: =SUM(AJ62:AJ64) -> 0
A74: 2 | C74: Plantas de Generación
C76: Costos Capitales [Millones de US$/GW]
C78: Biomasa
C79: Tipo de biomasa:
C80: Bagazo de caña (Existing) | D80: 2712 | E80: 2712 | F80: 2712 | G80: 2712 | H80: 2712 | I80: 2712 | J80: 2712 | K80: 2712 | L80: 2712 | M80: 2712 | N80: 2712 | O80: 2712 | P80: 2712 | Q80: 2712 | R80: 2712 | S80: 2712 | T80: 2712 | U80: 2712 | V80: 2712 | W80: 2712 | X80: 2712 | Y80: 2712 | Z80: 2712 | AA80: 2712 | AB80: 2712 | AC80: 2712 | AD80: 2712 | AE80: 2712 | AF80: 2712 | AG80: 2712 | AH80: 2712 | AI80: 2712 | AJ80: 2712
C81: Bagazo de caña (Nuevo) | D81: 2712 | E81: 2712 | F81: 2712 | G81: 2712 | H81: 2712 | I81: 2712 | J81: 2712 | K81: 2606 | L81: 2606 | M81: 2606 | N81: 2606 | O81: 2606 | P81: 2500 | Q81: 2500 | R81: 2500 | S81: 2500 | T81: 2500 | U81: 2473 | V81: 2473 | W81: 2473 | X81: 2473 | Y81: 2473 | Z81: 2446 | AA81: 2446 | AB81: 2446 | AC81: 2446 | AD81: 2446 | AE81: 2419 | AF81: 2419 | AG81: 2419 | AH81: 2419 | AI81: 2419 | AJ81: 2392
C82: Tecnología:
C83: Turbovapor-Integrated coal gasification combined cycle (IGCC) | D83: 2500 | E83: 2500 | F83: 2500 | G83: 2500 | H83: 2500 | I83: 2500 | J83: 2500 | K83: 2500 | L83: 2500 | M83: 2500 | N83: 2500 | O83: 2500 | P83: 2500 | Q83: 2500 | R83: 2500 | S83: 2500 | T83: 2500 | U83: 2500 | V83: 2500 | W83: 2500 | X83: 2500 | Y83: 2500 | Z83: 2500 | AA83: 2500 | AB83: 2500 | AC83: 2500 | AD83: 2500 | AE83: 2500 | AF83: 2500 | AG83: 2500 | AH83: 2500 | AI83: 2500 | AJ83: 2500
C84: Turbovapor-Integrated coal gasification combined cycle (IGCC) with CCS | D84: 3300 | E84: 3300 | F84: 3300 | G84: 3300 | H84: 3300 | I84: 3300 | J84: 3300 | K84: 3300 | L84: 3300 | M84: 3300 | N84: 3300 | O84: 3300 | P84: 3300 | Q84: 3300 | R84: 3300 | S84: 3300 | T84: 3300 | U84: 3300 | V84: 3300 | W84: 3300 | X84: 3300 | Y84: 3300 | Z84: 3300 | AA84: 3300 | AB84: 3300 | AC84: 3300 | AD84: 3300 | AE84: 3300 | AF84: 3300 | AG84: 3300 | AH84: 3300 | AI84: 3300 | AJ84: 3300
C85: Eólica
C86: Tipo de eólica:
C87: Eólica (Existing) | D87: 2530 | E87: 2530 | F87: 2530 | G87: 2530 | H87: 2530 | I87: 2530 | J87: 2530 | K87: 2530 | L87: 2530 | M87: 2530 | N87: 2530 | O87: 2530 | P87: 2533 | Q87: 2533 | R87: 2533 | S87: 2533 | T87: 2533 | U87: 2533 | V87: 2533 | W87: 2533 | X87: 2533 | Y87: 2533 | Z87: 2533 | AA87: 2533 | AB87: 2533 | AC87: 2533 | AD87: 2533 | AE87: 2533 | AF87: 2533 | AG87: 2533 | AH87: 2533 | AI87: 2533 | AJ87: 2537
C88: Eólica (Nuevo) | D88: 2286 | E88: 2286 | F88: 2286 | G88: 2286 | H88: 2286 | I88: 2286 | J88: 2286 | K88: 2286 | L88: 2286 | M88: 2286 | N88: 2286 | O88: 2286 | P88: 1639.5 | Q88: 1639.5 | R88: 1639.5 | S88: 1639.5 | T88: 1639.5 | U88: 1639.5 | V88: 1639.5 | W88: 1639.5 | X88: 1639.5 | Y88: 1639.5 | Z88: 1639.5 | AA88: 1639.5 | AB88: 1639.5 | AC88: 1639.5 | AD88: 1639.5 | AE88: 1639.5 | AF88: 1639.5 | AG88: 1639.5 | AH88: 1639.5 | AI88: 1639.5 | AJ88: 1158
C89: Hidraúlica
C90: Tipos de centrales:
C91: Embalse
C92: Vertiente-Tamaño:
C93: Amazonas-Pequeñas | D93: - | E93: - | F93: - | G93: - | H93: - | I93: - | J93: - | K93: - | L93: - | M93: - | N93: - | O93: - | P93: - | Q93: - | R93: - | S93: - | T93: - | U93: - | V93: - | W93: - | X93: - | Y93: - | Z93: - | AA93: - | AB93: - | AC93: - | AD93: - | AE93: - | AF93: - | AG93: - | AH93: - | AI93: - | AJ93: -
C94: Amazonas-Medianas | D94: 5065 | E94: 5065 | F94: 5065 | G94: 5065 | H94: 5065 | I94: 5065 | J94: 5065 | K94: 5065 | L94: 5065 | M94: 5065 | N94: 5065 | O94: 5065 | P94: 5065 | Q94: 5065 | R94: 5065 | S94: 5065 | T94: 5065 | U94: 5065 | V94: 5065 | W94: 5065 | X94: 5065 | Y94: 5065 | Z94: 5065 | AA94: 5065 | AB94: 5065 | AC94: 5065 | AD94: 5065 | AE94: 5065 | AF94: 5065 | AG94: 5065 | AH94: 5065 | AI94: 5065 | AJ94: 5065
C95: Amazonas-Grandes | D95: 3360 | E95: 3360 | F95: 3360 | G95: 3360 | H95: 3360 | I95: 3360 | J95: 3360 | K95: 3360 | L95: 3360 | M95: 3360 | N95: 3360 | O95: 3360 | P95: 3360 | Q95: 3360 | R95: 3360 | S95: 3360 | T95: 3360 | U95: 3360 | V95: 3360 | W95: 3360 | X95: 3360 | Y95: 3360 | Z95: 3360 | AA95: 3360 | AB95: 3360 | AC95: 3360 | AD95: 3360 | AE95: 3360 | AF95: 3360 | AG95: 3360 | AH95: 3360 | AI95: 3360 | AJ95: 3360
C96: Pacífico-Pequeñas | D96: - | E96: - | F96: - | G96: - | H96: - | I96: - | J96: - | K96: - | L96: - | M96: - | N96: - | O96: - | P96: - | Q96: - | R96: - | S96: - | T96: - | U96: - | V96: - | W96: - | X96: - | Y96: - | Z96: - | AA96: - | AB96: - | AC96: - | AD96: - | AE96: - | AF96: - | AG96: - | AH96: - | AI96: - | AJ96: -
C97: Pacífico-Medianas | D97: 5065 | E97: 5065 | F97: 5065 | G97: 5065 | H97: 5065 | I97: 5065 | J97: 5065 | K97: 5065 | L97: 5065 | M97: 5065 | N97: 5065 | O97: 5065 | P97: 5065 | Q97: 5065 | R97: 5065 | S97: 5065 | T97: 5065 | U97: 5065 | V97: 5065 | W97: 5065 | X97: 5065 | Y97: 5065 | Z97: 5065 | AA97: 5065 | AB97: 5065 | AC97: 5065 | AD97: 5065 | AE97: 5065 | AF97: 5065 | AG97: 5065 | AH97: 5065 | AI97: 5065 | AJ97: 5065
C98: Pacífico-Grandes | D98: 3360 | E98: 3360 | F98: 3360 | G98: 3360 | H98: 3360 | I98: 3360 | J98: 3360 | K98: 3360 | L98: 3360 | M98: 3360 | N98: 3360 | O98: 3360 | P98: 3360 | Q98: 3360 | R98: 3360 | S98: 3360 | T98: 3360 | U98: 3360 | V98: 3360 | W98: 3360 | X98: 3360 | Y98: 3360 | Z98: 3360 | AA98: 3360 | AB98: 3360 | AC98: 3360 | AD98: 3360 | AE98: 3360 | AF98: 3360 | AG98: 3360 | AH98: 3360 | AI98: 3360 | AJ98: 3360
C99: Pasada
C100: Vertiente-Tamaño:
C101: Amazonas-Pequeñas | D101: 5275 | E101: 5275 | F101: 5275 | G101: 5275 | H101: 5275 | I101: 5275 | J101: 5275 | K101: 5275 | L101: 5275 | M101: 5275 | N101: 5275 | O101: 5275 | P101: 5275 | Q101: 5275 | R101: 5275 | S101: 5275 | T101: 5275 | U101: 5275 | V101: 5275 | W101: 5275 | X101: 5275 | Y101: 5275 | Z101: 5275 | AA101: 5275 | AB101: 5275 | AC101: 5275 | AD101: 5275 | AE101: 5275 | AF101: 5275 | AG101: 5275 | AH101: 5275 | AI101: 5275 | AJ101: 5275
C102: Amazonas-Medianas | D102: 3518 | E102: 3518 | F102: 3518 | G102: 3518 | H102: 3518 | I102: 3518 | J102: 3518 | K102: 3518 | L102: 3518 | M102: 3518 | N102: 3518 | O102: 3518 | P102: 3518 | Q102: 3518 | R102: 3518 | S102: 3518 | T102: 3518 | U102: 3518 | V102: 3518 | W102: 3518 | X102: 3518 | Y102: 3518 | Z102: 3518 | AA102: 3518 | AB102: 3518 | AC102: 3518 | AD102: 3518 | AE102: 3518 | AF102: 3518 | AG102: 3518 | AH102: 3518 | AI102: 3518 | AJ102: 3518
C103: Amazonas-Grandes | D103: 3465 | E103: 3465 | F103: 3465 | G103: 3465 | H103: 3465 | I103: 3465 | J103: 3465 | K103: 3465 | L103: 3465 | M103: 3465 | N103: 3465 | O103: 3465 | P103: 3465 | Q103: 3465 | R103: 3465 | S103: 3465 | T103: 3465 | U103: 3465 | V103: 3465 | W103: 3465 | X103: 3465 | Y103: 3465 | Z103: 3465 | AA103: 3465 | AB103: 3465 | AC103: 3465 | AD103: 3465 | AE103: 3465 | AF103: 3465 | AG103: 3465 | AH103: 3465 | AI103: 3465 | AJ103: 3465
C104: Pacífico-Pequeñas | D104: 5275 | E104: 5275 | F104: 5275 | G104: 5275 | H104: 5275 | I104: 5275 | J104: 5275 | K104: 5275 | L104: 5275 | M104: 5275 | N104: 5275 | O104: 5275 | P104: 5275 | Q104: 5275 | R104: 5275 | S104: 5275 | T104: 5275 | U104: 5275 | V104: 5275 | W104: 5275 | X104: 5275 | Y104: 5275 | Z104: 5275 | AA104: 5275 | AB104: 5275 | AC104: 5275 | AD104: 5275 | AE104: 5275 | AF104: 5275 | AG104: 5275 | AH104: 5275 | AI104: 5275 | AJ104: 5275
C105: Pacífico-Medianas | D105: 3518 | E105: 3518 | F105: 3518 | G105: 3518 | H105: 3518 | I105: 3518 | J105: 3518 | K105: 3518 | L105: 3518 | M105: 3518 | N105: 3518 | O105: 3518 | P105: 3518 | Q105: 3518 | R105: 3518 | S105: 3518 | T105: 3518 | U105: 3518 | V105: 3518 | W105: 3518 | X105: 3518 | Y105: 3518 | Z105: 3518 | AA105: 3518 | AB105: 3518 | AC105: 3518 | AD105: 3518 | AE105: 3518 | AF105: 3518 | AG105: 3518 | AH105: 3518 | AI105: 3518 | AJ105: 3518
C106: Pacífico-Grandes | D106: 3465 | E106: 3465 | F106: 3465 | G106: 3465 | H106: 3465 | I106: 3465 | J106: 3465 | K106: 3465 | L106: 3465 | M106: 3465 | N106: 3465 | O106: 3465 | P106: 3465 | Q106: 3465 | R106: 3465 | S106: 3465 | T106: 3465 | U106: 3465 | V106: 3465 | W106: 3465 | X106: 3465 | Y106: 3465 | Z106: 3465 | AA106: 3465 | AB106: 3465 | AC106: 3465 | AD106: 3465 | AE106: 3465 | AF106: 3465 | AG106: 3465 | AH106: 3465 | AI106: 3465 | AJ106: 3465
C107: Solar
C108: Tipo de solar:
C109: Existente FV | D109: 1980
C110: Nuevo FV | D110: 1980 | E110: 1360 | F110: 1360 | G110: 1360 | H110: 1360 | I110: 1360 | J110: 1360 | K110: 1220 | L110: 1220 | M110: 1220 | N110: 1220 | O110: 1220 | P110: 1080 | Q110: 1080 | R110: 1080 | S110: 1080 | T110: 1080 | U110: 1050 | V110: 1050 | W110: 1050 | X110: 1050 | Y110: 1050 | Z110: 1020 | AA110: 1020 | AB110: 1020 | AC110: 1020 | AD110: 1020 | AE110: 990 | AF110: 990 | AG110: 990 | AH110: 990 | AI110: 990 | AJ110: 960
C111: Tecnología:
C112: FV generación distribuida | D112: 1980 | E112: 1360 | F112: 1360 | G112: 1360 | H112: 1360 | I112: 1360 | J112: 1360 | K112: 1220 | L112: 1220 | M112: 1220 | N112: 1220 | O112: 1220 | P112: 1080 | Q112: 1080 | R112: 1080 | S112: 1080 | T112: 1080 | U112: 1050 | V112: 1050 | W112: 1050 | X112: 1050 | Y112: 1050 | Z112: 1020 | AA112: 1020 | AB112: 1020 | AC112: 1020 | AD112: 1020 | AE112: 990 | AF112: 990 | AG112: 990 | AH112: 990 | AI112: 990 | AJ112: 960
C113: Solar CSP | D113: 7254 | E113: 6849 | F113: 6849 | G113: 6849 | H113: 6849 | I113: 6849 | J113: 6849 | K113: 6445 | L113: 6445 | M113: 6445 | N113: 6445 | O113: 6445 | P113: 6040 | Q113: 6040 | R113: 6040 | S113: 6040 | T113: 6040 | U113: 5636 | V113: 5636 | W113: 5636 | X113: 5636 | Y113: 5636 | Z113: 5231 | AA113: 5231 | AB113: 5231 | AC113: 5231 | AD113: 5231 | AE113: 4827 | AF113: 4827 | AG113: 4827 | AH113: 4827 | AI113: 4827 | AJ113: 4422
C114: Térmica
C115: Tecnología:
...

Sheet Costos Residencial
C3: Precios Sector Residencial
A5: 1 | C5: Electrodomésticos
C7: Artefacto | D7: Especificación de la referencia | E7: Modelos Eficientes Precio 2018 | F7: Modelos Ineficientes Precio 2018
C9: Cocina a GN - con horno | D9: 4 hornillas, horno 48 lt, grill | E9: 319.9834 | F9: 218.1705
C10: Cocina a GLP - con horno | D10: 4 hornillas, horno 48 lt, grill | E10: 319.9834 | F10: 218.1705
C11: Cocina eléctrica de inducción (encimera) | D11: 4 hornillas, sin horno (solo la "encimera"), potencia total 7,2 kW | E11: 1163.576 | F11: 538.1539
C12: Cocina eléctrica de inducción-con horno | D12: 4 hornillas (potencia total 7,2 kW), horno 52 lt | E12: 1599.917 | F12: 872.682
C13: Horno microondas/ microondas | D13: 25lt, 800 W | E13: 116.3576 | F13: 72.7235
C14: Refrigerador o freezer | D14: No frost, 340 lts, 2 puertas (nevera 269 lts y freezer 92lts), 250 W, consumo de aprox. 40 kWh/mes | E14: 654.5115 | F14: 552.6986
C15: Aire acondicionado | D15: Split pared, capacidad de refrigeración de 18.000 BTU/h, potencia de 1811 W | E15: 648.69362 | F15: 557.49835
C16: Computadora (laptop) | D16: Laptop, 14 inch, Core i3, 8GB en RAM, 256 GB SSD, potencia 200 W | E16: 1018.129 | F16: 683.6009
C17: Radio | D17: Equipo de sonido 720W de potencia RMS, 3 parlantes | E17: 504.70109 | F17: 381.07114
C18: Televisor | D18: 43 pulg, LED, smart TV, potencia 65 W | E18: 509.0645 | F18: 407.2516
C19: Lavadora de ropa | D19: Lavadora y secadora, carga frontal, 12 kg. Potencia Lavado 2100W. Potencia secado 1500W | E19: 1018.129 | F19: 799.9585
C24: Referencias Bibliográficas
B25: 1 | C25: https://www.dismac.com.bo/
C26: https://www.tibo.bo/tiendasbolivia/
C27: https://www.creditoseconomicos.com/

Sheet Gráficos Combustibles
C1: Ecuador
C4: Combustibles fósiles
C120: Otros combustibles
C143: Consumo de combustibles para electricidad
C166: Energía generada por combustible
C189: Input Activity Ratio
C227: Annual Activity Lower Limit

Sheet Gráficos Electricidad
C1: Ecuador
C4: Capacidad Instalada
C163: Capacidad Proyectada en los actuales planes de expansión
C190: Vida útil (años)
C205: Potencial eléctrico de las fuentes renovables
C262: Energía generada
C441: Energía transmitida y distribuida Teórica
C484: Energía importada y exportada
C504: Consumos de electricidad
C523: Technology Annual Activity Lower Limit

Sheet Graficos Demanda Energia
D1: Ecuador
D4: Demandas de combustibles

Sheet Gráfico Emisiones Energía
C1: Ecuador
C4: Combustibles
C5: Factores de emisión para emisiones fugitivas
C21: Factores de emisión por quema de combustibles
C54: Emisiones asociadas a la producción
C91: Electricidad
C113: Demandas de combustibles
C156: Datos faltantes
C157: Petróleo quemado en autoproductoras eléctricas [PJ] | D157: =#REF!*#REF! -> #REF! | E157: =#REF!*#REF! -> #REF! | F157: =#REF!*#REF! -> #REF! | G157: =#REF!*#REF! -> #REF!
C159: Factores de emisión de gen. eléctrica en autoproductores térmicos que queman petróleo [MtonCO2eq/PJ] | D159: =D102/D157 -> #REF! | E159: =E102/E157 -> #REF! | F159: =F102/F157 -> #REF! | G159: =G102/G157 -> #REF!
C161: Petróleo quemado en refinerías [PJ] | D161: =#REF!/1000 -> #REF!
C162: Emisiones emitidas por refinación de petróleo [MtonCO2eq] | D162: =#REF!/1000 -> #REF!
C164: Factor de emisión de Refinerías por quema de petróleo [GgtonCO2eq/TJ] | D164: =D162/D161 -> #REF!

Sheet Driver PIB
C1: Ecuador | D1: 2018 | E1: 2019 | F1: 2020 | G1: 2021 | H1: 2022 | I1: 2023 | J1: 2024 | K1: 2025 | L1: 2026 | M1: 2027 | N1: 2028 | O1: 2029 | P1: 2030 | Q1: 2031 | R1: 2032 | S1: 2033 | T1: 2034 | U1: 2035 | V1: 2036 | W1: 2037 | X1: 2038 | Y1: 2039 | Z1: 2040 | AA1: 2041 | AB1: 2042 | AC1: 2043 | AD1: 2044 | AE1: 2045 | AF1: 2046 | AG1: 2047 | AH1: 2048 | AI1: 2049 | AJ1: 2050
C2: PIB | H2: 0.030425139 | I2: 0.025876257 | J2: 0.028673474 | K2: 0.029836119 | L2: 0.030666571 | M2: 0.026567681 | N2: 0.028559838 | O2: 0.022055657 | P2: 0.023915088 | Q2: 0.031772923 | R2: 0.02476136 | S2: 0.029006504 | T2: 0.02375684 | U2: 0.023733451 | V2: 0.025625718 | W2: 0.022777432 | X2: 0.02351191 | Y2: 0.025294853 | Z2: 0.02279702 | AA2: 0.022906838 | AB2: 0.022360652 | AC2: 0.017570573 | AD2: 0.021993282 | AE2: 0.018665848 | AF2: 0.022935697 | AG2: 0.018503 | AH2: 0.017991157 | AI2: 0.018323179 | AJ2: 0.01812868

Sheet Demandas Cálculos Driver PIB
C1: Ecuador | D1: 2018 | E1: 2019 | F1: 2020 | G1: 2021 | H1: 2022 | I1: 2023 | J1: 2024 | K1: 2025 | L1: 2026 | M1: 2027 | N1: 2028 | O1: 2029 | P1: 2030 | Q1: 2031 | R1: 2032 | S1: 2033 | T1: 2034 | U1: 2035 | V1: 2036 | W1: 2037 | X1: 2038 | Y1: 2039 | Z1: 2040 | AA1: 2041 | AB1: 2042 | AC1: 2043 | AD1: 2044 | AE1: 2045 | AF1: 2046 | AG1: 2047 | AH1: 2048 | AI1: 2049 | AJ1: 2050
C4: Demandas de combustibles
C5: Demandas de Gasolina
A6: 1 | C6: Demanda residencial [PJ] | H6: =G6*(1+'Driver PIB'!H$2) -> 0 | I6: =H6*(1+'Driver PIB'!I$2) -> 0 | J6: =I6*(1+'Driver PIB'!J$2) -> 0 | K6: =J6*(1+'Driver PIB'!K$2) -> 0 | L6: =K6*(1+'Driver PIB'!L$2) -> 0 | M6: =L6*(1+'Driver PIB'!M$2) -> 0 | N6: =M6*(1+'Driver PIB'!N$2) -> 0 | O6: =N6*(1+'Driver PIB'!O$2) -> 0 | ... AJ6: =AI6*(1+'Driver PIB'!AJ$2) -> 0
A7: 1 | C7: Demanda comercial y servicios públicos [PJ] | D7: ='Copia de Demandas de energía '!D7*1000*($E$110) -> 0.10753598 | E7: ='Copia de Demandas de energía '!E7*1000*($E$110) -> 0.13348048 | F7: ='Copia de Demandas de energía '!F7*1000*($E$110) -> 0.037533503 | G7: ='Copia de Demandas de energía '!G7*1000*($E$110) -> 0.25710469 | H7: =G7*(1+'Driver PIB'!H$2) -> 0.26492714 | I7: =H7*(1+'Driver PIB'!I$2) -> 0.27178246 | J7: =I7*(1+'Driver PIB'!J$2) -> 0.27957541 | K7: =J7*(1+'Driver PIB'!K$2) -> 0.28791685 | L7: =K7*(1+'Driver PIB'!L$2) -> 0.29674628 | M7: =L7*(1+'Driver PIB'!M$2) -> 0.30463014 | N7: =M7*(1+'Driver PIB'!N$2) -> 0.31333032 | O7: =N7*(1+'Driver PIB'!O$2) -> 0.32024103 | ... AJ7: =AI7*(1+'Driver PIB'!AJ$2) -> 0.51283573
A8: 1,2 | C8: Demanda Industrial [PJ] | D8: ='Copia de Demandas de energía '!D8*1000*($E$110) -> 0.66585641 | E8: ='Copia de Demandas de energía '!E8*1000*($E$110) -> 0.92659609 | F8: ='Copia de Demandas de energía '!F8*1000*($E$110) -> 0.81172487 | G8: ='Copia de Demandas de energía '!G8*1000*($E$110) -> 1.126309 | H8: =G8*(1+'Driver PIB'!H$2) -> 1.1605771 | I8: =H8*(1+'Driver PIB'!I$2) -> 1.1906085 | J8: =I8*(1+'Driver PIB'!J$2) -> 1.2247474 | K8: =J8*(1+'Driver PIB'!K$2) -> 1.2612891 | L8: =K8*(1+'Driver PIB'!L$2) -> 1.2999685 | M8: =L8*(1+'Driver PIB'!M$2) -> 1.3345056 | N8: =M8*(1+'Driver PIB'!N$2) -> 1.3726189 | O8: =N8*(1+'Driver PIB'!O$2) -> 1.4028929 | ... AJ8: =AI8*(1+'Driver PIB'!AJ$2) -> 2.2466003
A9: 1 | C9: Demanda construcción y otros [PJ] | D9: ='Copia de Demandas de energía '!D9*1000*($E$110) -> 37.916717 | E9: ='Copia de Demandas de energía '!E9*1000*($E$110) -> 35.371445 | F9: ='Copia de Demandas de energía '!F9*1000*($E$110) -> 27.23661 | G9: ='Copia de Demandas de energía '!G9*1000*($E$110) -> 22.024953 | H9: =G9*(1+'Driver PIB'!H$2) -> 22.695066 | I9: =H9*(1+'Driver PIB'!I$2) -> 23.282329 | J9: =I9*(1+'Driver PIB'!J$2) -> 23.949914 | K9: =J9*(1+'Driver PIB'!K$2) -> 24.664487 | L9: =K9*(1+'Driver PIB'!L$2) -> 25.420862 | M9: =L9*(1+'Driver PIB'!M$2) -> 26.096235 | N9: =M9*(1+'Driver PIB'!N$2) -> 26.841539 | O9: =N9*(1+'Driver PIB'!O$2) -> 27.433547 | ... AJ9: =AI9*(1+'Driver PIB'!AJ$2) -> 43.932232
A10: 1 | C10: Demanda Agro, pesca y minería [PJ] | D10: ='Copia de Demandas de energía '!D10*1000*($E$110) -> 5.1670492 | E10: ='Copia de Demandas de energía '!E10*1000*($E$110) -> 5.6562388 | F10: ='Copia de Demandas de energía '!F10*1000*($E$110) -> 5.2540174 | G10: ='Copia de Demandas de energía '!G10*1000*($E$110) -> 5.8690687 | H10: =G10*(1+'Driver PIB'!H$2) -> 6.0476359 | I10: =H10*(1+'Driver PIB'!I$2) -> 6.2041261 | J10: =I10*(1+'Driver PIB'!J$2) -> 6.38202 | K10: =J10*(1+'Driver PIB'!K$2) -> 6.5724347 | L10: =K10*(1+'Driver PIB'!L$2) -> 6.7739887 | M10: =L10*(1+'Driver PIB'!M$2) -> 6.9539579 | N10: =M10*(1+'Driver PIB'!N$2) -> 7.1525618 | O10: =N10*(1+'Driver PIB'!O$2) -> 7.3103162 | ... AJ10: =AI10*(1+'Driver PIB'!AJ$2) -> 11.70678
A11: 1 | C11: Demanda transporte [PJ] | H11: =G11*(1+'Driver PIB'!H$2) -> 0 | I11: =H11*(1+'Driver PIB'!I$2) -> 0 | J11: =I11*(1+'Driver PIB'!J$2) -> 0 | K11: =J11*(1+'Driver PIB'!K$2) -> 0 | L11: =K11*(1+'Driver PIB'!L$2) -> 0 | M11: =L11*(1+'Driver PIB'!M$2) -> 0 | N11: =M11*(1+'Driver PIB'!N$2) -> 0 | O11: =N11*(1+'Driver PIB'!O$2) -> 0 | ... AJ11: =AI11*(1+'Driver PIB'!AJ$2) -> 0
A12: 1 | C12: Terrestre carga | D12: ='Copia de Demandas de energía '!D12*1000*($E$110) -> 67.400251 | E12: ='Copia de Demandas de energía '!E12*1000*($E$110) -> 68.489353 | F12: ='Copia de Demandas de energía '!F12*1000*($E$110) -> 53.449159 | G12: ='Copia de Demandas de energía '!G12*1000*($E$110) -> 69.595463 | H12: =G12*(1+'Driver PIB'!H$2) -> 71.712915 | I12: =H12*(1+'Driver PIB'!I$2) -> 73.568576 | J12: =I12*(1+'Driver PIB'!J$2) -> 75.678043 | K12: =J12*(1+'Driver PIB'!K$2) -> 77.935982 | L12: =K12*(1+'Driver PIB'!L$2) -> 80.326011 | M12: =L12*(1+'Driver PIB'!M$2) -> 82.460087 | N12: =M12*(1+'Driver PIB'!N$2) -> 84.815134 | O12: =N12*(1+'Driver PIB'!O$2) -> 86.685788 | ... AJ12: =AI12*(1+'Driver PIB'!AJ$2) -> 138.81909
A13: 1,2 | C13: Terrestre pasajeros | D13: ='Copia de Demandas de energía '!D13*1000*($E$110) -> 63.717838 | E13: ='Copia de Demandas de energía '!E13*1000*($E$110) -> 64.747099 | F13: ='Copia de Demandas de energía '!F13*1000*($E$110) -> 50.896162 | G13: ='Copia de Demandas de energía '!G13*1000*($E$110) -> 66.271465 | H13: =G13*(1+'Driver PIB'!H$2) -> 68.287783 | I13: =H13*(1+'Driver PIB'!I$2) -> 70.054816 | J13: =I13*(1+'Driver PIB'!J$2) -> 72.06353 | K13: =J13*(1+'Driver PIB'!K$2) -> 74.213627 | L13: =K13*(1+'Driver PIB'!L$2) -> 76.489504 | M13: =L13*(1+'Driver PIB'!M$2) -> 78.521653 | N13: =M13*(1+'Driver PIB'!N$2) -> 80.764218 | O13: =N13*(1+'Driver PIB'!O$2) -> 82.545526 | ... AJ13: =AI13*(1+'Driver PIB'!AJ$2) -> 132.18885
A14: 1 | C14: Marítimo | D14: ='Copia de Demandas de energía '!D14*1000*($E$110) -> 0.033384859 | E14: ='Copia de Demandas de energía '!E14*1000*($E$110) -> 0.003779418 | F14: ='Copia de Demandas de energía '!F14*1000*($E$110) -> 0.010708351 | G14: ='Copia de Demandas de energía '!G14*1000*($E$110) -> 0.021416702 | H14: =G14*(1+'Driver PIB'!H$2) -> 0.022068308 | I14: =H14*(1+'Driver PIB'!I$2) -> 0.022639353 | J14: =I14*(1+'Driver PIB'!J$2) -> 0.023288502 | K14: =J14*(1+'Driver PIB'!K$2) -> 0.023983341 | L14: =K14*(1+'Driver PIB'!L$2) -> 0.024718828 | M14: =L14*(1+'Driver PIB'!M$2) -> 0.02537555 | N14: =M14*(1+'Driver PIB'!N$2) -> 0.026100271 | O14: =N14*(1+'Driver PIB'!O$2) -> 0.02667593 | ... AJ14: =AI14*(1+'Driver PIB'!AJ$2) -> 0.042718979
A15: 1 | C15: Aéreo | D15: ='Copia de Demandas de energía '!D15*1000*($E$110) -> 0.20597828 | E15: ='Copia de Demandas de energía '!E15*1000*($E$110) -> 0.21920624 | F15: ='Copia de Demandas de energía '!F15*1000*($E$110) -> 0.18267187 | G15: ='Copia de Demandas de energía '!G15*1000*($E$110) -> 0.21416702 | H15: =G15*(1+'Driver PIB'!H$2) -> 0.22068308 | I15: =H15*(1+'Driver PIB'!I$2) -> 0.22639353 | J15: =I15*(1+'Driver PIB'!J$2) -> 0.23288502 | K15: =J15*(1+'Driver PIB'!K$2) -> 0.23983341 | L15: =K15*(1+'Driver PIB'!L$2) -> 0.24718828 | M15: =L15*(1+'Driver PIB'!M$2) -> 0.2537555 | N15: =M15*(1+'Driver PIB'!N$2) -> 0.26100271 | O15: =N15*(1+'Driver PIB'!O$2) -> 0.2667593 | ... AJ15: =AI15*(1+'Driver PIB'!AJ$2) -> 0.42718979
C16: Total [PJ] | D16: =SUM(D6:D15) -> 175.21461 | E16: =SUM(E6:E15) -> 175.5472 | F16: =SUM(F6:F15) -> 137.87859 | G16: =SUM(G6:G15) -> 165.37995 | H16: =SUM(H6:H15) -> 170.41165 | I16: =SUM(I6:I15) -> 174.82127 | J16: =SUM(J6:J15) -> 179.834 | K16: =SUM(K6:K15) -> 185.19955 | ... AJ16: =SUM(AJ6:AJ15) -> 329.8763
C18: Demandas de Diesel
C19: Demanda residencial [PJ] | H19: =G19*(1+'Driver PIB'!H$2) -> 0 | I19: =H19*(1+'Driver PIB'!I$2) -> 0 | J19: =I19*(1+'Driver PIB'!J$2) -> 0 | K19: =J19*(1+'Driver PIB'!K$2) -> 0 | L19: =K19*(1+'Driver PIB'!L$2) -> 0 | M19: =L19*(1+'Driver PIB'!M$2) -> 0 | N19: =M19*(1+'Driver PIB'!N$2) -> 0 | O19: =N19*(1+'Driver PIB'!O$2) -> 0 | ... AJ19: =AI19*(1+'Driver PIB'!AJ$2) -> 0
C20: Demanda comercial y servicios públicos [PJ] | D20: ='Copia de Demandas de energía '!D20*1000*($E$110) -> 6.2234008 | E20: ='Copia de Demandas de energía '!E20*1000*($E$110) -> 5.113678 | F20: ='Copia de Demandas de energía '!F20*1000*($E$110) -> 4.9900274 | G20: ='Copia de Demandas de energía '!G20*1000*($E$110) -> 4.7622677 | H20: =G20*(1+'Driver PIB'!H$2) -> 4.9071603 | I20: =H20*(1+'Driver PIB'!I$2) -> 5.0341393 | J20: =I20*(1+'Driver PIB'!J$2) -> 5.1784856 | K20: =J20*(1+'Driver PIB'!K$2) -> 5.3329915 | L20: =K20*(1+'Driver PIB'!L$2) -> 5.496536 | M20: =L20*(1+'Driver PIB'!M$2) -> 5.6425662 | N20: =M20*(1+'Driver PIB'!N$2) -> 5.803717 | O20: =N20*(1+'Driver PIB'!O$2) -> 5.9317218 | ... AJ20: =AI20*(1+'Driver PIB'!AJ$2) -> 9.4990916
A21: 2 | C21: Demanda Industrial [PJ] | D21: ='Copia de Demandas de energía '!D21*1000*($E$110) -> 27.754763 | E21: ='Copia de Demandas de energía '!E21*1000*($E$110) -> 23.891869 | F21: ='Copia de Demandas de energía '!F21*1000*($E$110) -> 23.314155 | G21: ='Copia de Demandas de energía '!G21*1000*($E$110) -> 22.250028 | H21: =G21*(1+'Driver PIB'!H$2) -> 22.926988 | I21: =H21*(1+'Driver PIB'!I$2) -> 23.520253 | J21: =I21*(1+'Driver PIB'!J$2) -> 24.19466 | K21: =J21*(1+'Driver PIB'!K$2) -> 24.916535 | L21: =K21*(1+'Driver PIB'!L$2) -> 25.680639 | M21: =L21*(1+'Driver PIB'!M$2) -> 26.362914 | N21: =M21*(1+'Driver PIB'!N$2) -> 27.115835 | O21: =N21*(1+'Driver PIB'!O$2) -> 27.713893 | ... AJ21: =AI21*(1+'Driver PIB'!AJ$2) -> 44.381178
