Workbook
Name ____W.O.R.K.B.O.O.K..C.O.N.T.E.N.T.S____: #REF!
Name ____W.O.R.K.B.O.O.K..C.O.N.T.E.N.T.S____: #REF!
Name CRF_4_KP_I_A.1.1_Doc: #REF!
Name CRF_4_KP_I_A.1.1_Doc: #REF!
Name CRF_4_KP_I_A.2.1_Doc: #REF!
Name CRF_4_KP_I_A.2.1_Doc: #REF!
Name CRF_4_KP_I_A.2_Doc: #REF!
Name CRF_4_KP_I_A.2_Doc: #REF!
Name CRF_4_KP_I_B.1.1_Doc: #REF!
Name CRF_4_KP_I_B.1.1_Doc: #REF!
Name CRF_4_KP_I_B.1.3_Doc: #REF!
Name CRF_4_KP_I_B.1.3_Doc: #REF!
Name CRF_Address: #REF!
Name CRF_Address: #REF!
Name CRF_Address1: #REF!
Name CRF_Address1: #REF!
Name CRF_Comment: #REF!
Name CRF_Comment: #REF!
Name CRF_ContactName: #REF!
Name CRF_ContactName: #REF!
Name CRF_CountryName: [1]Sheet1!$C$4
Name CRF_Email: #REF!
Name CRF_Email: #REF!
Name CRF_Fax: #REF!
Name CRF_Fax: #REF!
Name CRF_InventoryYear: [1]Sheet1!$C$6
Name CRF_Organisation: #REF!
Name CRF_Organisation: #REF!
Name CRF_Phone: #REF!
Name CRF_Phone: #REF!
Name CRF_Sheet1_Main: #REF!
Name CRF_Sheet1_Main: #REF!
Name CRF_Status: #REF!
Name CRF_Status: #REF!
Name CRF_Submission: [1]Sheet1!$C$8
Name CRF_Summary1_A_Main: #REF!
Name CRF_Summary1_A_Main: #REF!
Name CRF_Summary1_A_Range1: #REF!
Name CRF_Summary1_A_Range1: #REF!
Name CRF_Summary2_Main: #REF!
Name CRF_Summary2_Main: #REF!
Name CRF_Summary2_Range1: #REF!
Name CRF_Summary2_Range1: #REF!
Name CRF_Table10s1_Dyn10: [1]Table10!#REF!
Name CRF_Table10s1_Dyn10: [1]Table10!#REF!
Name CRF_Table10s1_Dyn11: [1]Table10!#REF!
Name CRF_Table10s1_Dyn12: [1]Table10!#REF!
Name CRF_Table10s1_Dyn13: [1]Table10!#REF!
Name CRF_Table10s1_Dyn14: [1]Table10!#REF!
Name CRF_Table10s1_Dyn15: [1]Table10!#REF!
Name CRF_Table10s1_Dyn16: [1]Table10!#REF!
Name CRF_Table10s1_Dyn17: [1]Table10!#REF!
Name CRF_Table10s1_Dyn18: [1]Table10!#REF!
Name CRF_Table10s1_Dyn19: [1]Table10!#REF!
Name CRF_Table10s1_Dyn20: [1]Table10!#REF!
Name CRF_Table10s1_Dyn21: [1]Table10!#REF!
Name CRF_Table10s1_Dyn22: [1]Table10!#REF!
Name CRF_Table2_II__Doc: #REF!
Name CRF_Table2_II__Doc: #REF!
Name CRF_Table2_II__Main: #REF!

Sheet INDICE
C3: INVENTARIO NACIONAL DE GASES DE EFECTO INVERNADERO 2018 -- LIBRO DE CÁLCULOS
C4: SECTOR AGRICULTURA
C6: INDICE DE CATEGORÍAS
C8: Datos de Actividad | D8: Tabla Compilatoria de los Datos de Actividad
B9: 3A1 | C9: Fermentación Entérica | D9: Tabla de Cálculos para Fermentación Entérica
B10: 3A2 | C10: Gestión de Estiércol CH4 | D10: Tabla de Cálculos para Gestión de Estércol CH4
B11: 3A2 | C11: Gestión de Estércol N2O Directo | D11: Tabla de Cálculos para Gestión de Estércol N2O - Directo
B12: 3C6 | C12: Gestión de Estércol N2O Indirecto | D12: Tabla de Cálculos para Gestión de Estércol N2O - Indirecto
B13: 3C7 | C13: Cultivo de Arroz CH4 | D13: Tabla de Cálculos para Cultivo de arroz CH4
B14: 3C4 | C14: Suelos Agricolas N2O Directo | D14: Tabla de Cálculos para Suelos Agricolas N2O - Directo
C15: Anexo 3C4 | D15: Tabla de Cálculos complementarios para Suelos Agricolas N2O - Directo
B16: 3C5 | C16: Suelos Agricolas N2O Indirecto | D16: Tabla de Cálculos para Suelos Agricolas N2O - Indirecto
B17: 3C2 | C17: Emisiones CO2 por Encalado | D17: Tabla de Cálculos para CO2 por Encalado
B18: 3C3 | C18: Emisiones CO2 por Aplicación de Urea | D18: Tabla de Cálculos para CO2 por Aplicación de Urea
B19: 3C1 | C19: Quema de Biomasa | D19: Tabla de Cálculos para N2O, CH4 por quema de biomasa
C20: RESULTADOS | D20: Tabla compilatoria de resultados finales CO2 Eq por categoria
B22: (*) | C22: Las tablas CTR comunes del inventario se integran al final
C23: Categorías Principales Desagregado | D23: Tabla de cálculo de las categorías Principales sectorial
C25: Especialista Sector Agricultura: Roberto Lucero

Sheet Presentación
B2: ÚLTIMA ACTUALIZACIÓN DE LA HERRAMIENTA
B5: Fecha de la última actualización: | C5: 43508
B7: Nombre: | C7: Roberto Daniel Lucero Romero
B9: Unidad del MAE: | C9: Técnico sector Agricultura
B11: Tel Institucional: | C11: 5933987600 etx. 1314
B13: e-mail: | C13: roberto.lucero@ambiente.gob.ec
A17: Proveedores de Información /Datos de Contacto
A21: No | B21: Organización | D21: Contacto | G21: Información Contacto
B22: Nombre de la organización | C22: Tipo | D22: Rol | E22: Cargo | F22: Nombres | G22: Telefono 1 | H22: Ext.1 | I22: mail
A23: 1 | B23: Instituto Nacional de Estadística y Censos (INEC) | C23: Nacional | D23: Punto focal NDC directivo Agricultura y USCUSS | E23: JEFE DE ESTADÍSTICAS AGROPECUARIAS | F23: ARMANDO DAVID SALAZAR MÉNDEZ | G23: 02-2544326 | H23: 1405 | I23: armando_salazar@inec.gob.ec
A24: 3 | B24: Instituto Nacional de Estadística y Censos (INEC) | C24: Nacional | D24: Punto focal NDC directivo Agricultura y USCUSS | E24: ANALISTA DE ESTADISTICAS AGROPECUARIAS Y AMBIENTALES 3 | F24: ARGUELLO RUIZ JENNY ELIZABETH | G24: 02-2544326 - 2238489 - 2555703 | I24: jenny_arguello@inec.gob.ec
A25: 4 | B25: Instituto Nacional de Estadística y Censos (INEC) | C25: Nacional | D25: Punto focal NDC directivo Agricultura y USCUSS | E25: DIRECTORA DE ESTADISTICAS AGROPECUARIAS Y AMBIENTALES | F25: MURGUEITIO TAMAYO MARIA JOSE | G25: 02-2544326 - 2238489 - 2555701 | H25: 1217 | I25: MariaJose_Murgueitio@inec.gob.ec
A26: 5 | B26: Instituto Nacional de Estadística y Censos (INEC) | C26: Nacional | D26: Punto focal NDC directivo Agricultura y USCUSS | E26: ANALISTA DE ESTADISTICAS AGROPECUARIAS Y AMBIENTALES 3 | F26: PILATAXI GUAIRACAJA CARLOS PATRICIO | G26: 02-2544326 - 2238489 - 2555701 | H26: 1405 | I26: carlos_pilataxi@inec.gob.ec
A27: 6 | B27: Agricultura y Ganadería (MAG) | C27: Nacional | D27: Punto focal NDC directivo Agricultura y USCUSS | E27: TÉCNICO, UNIDAD DE PROCESAMIENTO DE LA INFORMACIÓN | F27: RAÚL GAETHE | G27: 02-3960100 | H27: 3257 | I27: rgaethe@magap.gob.ec
A28: 7 | B28: Universidad de Cuenca | C28: Nacional | D28: Punto focal NDC directivo Agricultura y USCUSS | E28: DECANO DE LA FACULTAD DE CIENCIAS AGROPECAUARIAS | F28: DR. GUILLERMO SERPA GARCÍA | I28: guillermo.serpa@ucuenca.edu.ec c
A29: 8 | B29: Instituto Nacional de Investigaciones Agropecuarias INIAP | C29: Nacional | D29: Punto focal NDC directivo Agricultura y USCUSS | E29: INVESTIGADOR PRINCIPAL 4 | F29: DR. VÍCTOR HUGO BARRERA MOSQUERA | G29: 022567645 Ext: 215 | I29: victor.barrera@iniap.gob.ec
A30: 10 | B30: Instituto Nacional de Investigación Agropecuaria (INIAP) | C30: Nacional | D30: Punto focal NDC directivo Agricultura y USCUSS | E30: DIRECTOR DE INVESTIGACIONES , ENCARGADO | F30: DR. JOSÉ LUIS ZAMBRANO | G30: (593 2) 2567645 (MAG) (593 2) 3076004 | 3076002 (Estación Santa Catalina) | I30: jose.zambrano@iniap.gob.ec
A31: 11 | B31: Instituto Nacional de Investigación Agropecuaria (INIAP) | C31: Nacional | D31: Punto focal NDC técnico Agricultura y USCUSS | E31: DIRECTOR DE INVESTIGADORES, ENCARGADO | F31: DR. VÍCTOR HUGO BARRERA | G31: (02)2567645 (Ext) 201 Quito | I31: Victor.barrera@iniap.gob.ec
A32: 12 | B32: Instituto Nacional de Investigación Agropecuaria (INIAP) | C32: Nacional | D32: Punto focal NDC técnico (alterno) Agricultura y USCUSS | E32: INVESTIGAR AGROPECUARIO | F32: ING. LUIS ESCUDERO | G32: (593 2) 2567645 (MAG) (593 2) 3076004 | 3076002 (Estación Santa Catalina) | I32: Luis.escudero@iniap.gob.ec
A33: 13 | B33: Agricultura y Ganadería (MAG) | C33: Nacional | D33: Agricultura y Uso de suelo Cambio de Uso del Suelo y Silvicultura (USCUSS) | E33: GERENTE DEL PROYECTO DE INVERSIÓN DE INCENTIVOS FORESTALES | F33: JAIME MEDINA | G33: 959250781 | I33: jmedina@mag.gob.ec
A34: 14 | B34: Agricultura y Ganadería (MAG) | C34: Nacional | D34: Agricultura y Uso de suelo Cambio de Uso del Suelo y Silvicultura (USCUSS) | E34: TÉCNICO DEL PROYECTO DE INVERSIÓN DE INCENTIVOS FORESTALES | F34: JULIO VEGA | G34: 593-2 396-0100 | I34: jvegal@mag.gob.ec
A35: 15 | B35: Agricultura y Ganadería (MAG) | C35: Nacional | D35: Agricultura y Uso de suelo Cambio de Uso del Suelo y Silvicultura (USCUSS) | E35: DIRECTORA DE PRE INVERSIÓN Y COOPERACIÓN NACIONAL E INTERNACIONAL, ENCARGADA | F35: DENISSE SÁNCHEZ | G35: 593-2 396-0100 | I35: dsanchezt@mag.gob.ec
A36: 16 | B36: Agricultura y Ganadería (MAG) | C36: Nacional | D36: Agricultura y Uso de suelo Cambio de Uso del Suelo y Silvicultura (USCUSS) | E36: ESPECIALISTA EN DESARROLLO FORESTAL | F36: FELIPE ESPINOZA | G36: Telf.: (593 4) 2 599330 ext. 5663 (0999610360) | I36: fespinozaj@mag.gob.ec

Sheet Datos de Actividad
B1: Tabla para recopilación de información sector agricultura
C2: Datos de actividad usados para la construcci[on de inventarios nacionales de gases de efecto invernadero serie 1994-2021 5CN/1BTR, directrices ipcc 2006 refinamiento 2019 | H2: INDICE
G7: GANADO DOMÉSTICO | L7: GANADO DOMÉSTICO | Q7: GANADO DOMÉSTICO | V7: GANADO DOMÉSTICO
C11: Fuentes y Categorías | E11: Número de Animales (Total nacional por año de inventario)
C12: Fermentación Entérica / Gestión del estiércol | E12: 1994 | G12: 2000 | I12: 2006 | K12: 2010 | M12: 2012 | O12: 2014 | Q12: 2016 | S12: 2018 | U12: 2020 | W12: 2021 | Y12: 2022
E13: Fuente | F13: Cabezas | G13: Fuente | H13: Cabezas | I13: Fuente | J13: Cabezas | K13: Fuente | L13: Cabezas | M13: Fuente | N13: Cabezas | O13: Fuente | P13: Cabezas | Q13: Fuente | R13: Cabezas | S13: Fuente | T13: Cabezas | U13: Fuente | V13: Cabezas | W13: Fuente | X13: Cabezas | Y13: Fuente | Z13: Cabezas
B14: GANADO BOVINO | C14: Ganado Lechero | D14: Sierra | E14: ESPAC 1995, Desagregación por región estimada en base a las proporciones de años posteriores | F14: 574414.58 | G14: CNA 2000, tabla 6_00, Desagregación por región estimada en función de datos ESPAC años posteriores | H14: 626104.05 | I14: ESPAC 2006, tabla 51_6 | J14: 594479 | K14: ESPAC 2010, tabla 51_10 | L14: 702076 | M14: ESPAC 2012, tabla 51 | N14: 674076.85 | O14: ESPAC 2014 (version II corregida), tabla 54 | P14: 630175.66 | Q14: ESPAC 2016, tabla 63 | R14: 570270.14 | S14: ESPAC 2018 , tabla 66 | T14: 522643.97 | U14: ESPAC 2020 , tabla 67 | V14: 616168.02 | W14: ESPAC 2021 , tabla 67 | X14: 564165.51 | Y14: ESPAC 2022 , tabla 67 | Z14: 545149.32
D15: Costa | E15: ESPAC 1995, Desagregación por región estimada en base a las proporciones de años posteriores | F15: 263584.92 | G15: CNA 2000, tabla 6_00, Desagregación por región estimada en función de datos ESPAC años posteriores | H15: 241691.92 | I15: ESPAC 2006, tabla 51_7 | J15: 272792 | K15: ESPAC 2010, tabla 51_11 | L15: 271019 | M15: ESPAC 2012, tabla 52 | N15: 280034.87 | O15: ESPAC 2014 (version II corregida), tabla 54 | P15: 280963.69 | Q15: ESPAC 2016, tabla 63 | R15: 271362.48 | S15: ESPAC 2018 , tabla 66 | T15: 262262.61 | U15: ESPAC 2020 , tabla 67 | V15: 291374.79 | W15: ESPAC 2021 , tabla 67 | X15: 236336.44 | Y15: ESPAC 2022 , tabla 67 | Z15: 226251.1
D16: Amazonia | E16: ESPAC 1995, Desagregación por región estimada en base a las proporciones de años posteriores | F16: 119692.13 | G16: CNA 2000, tabla 6_00, Desagregación por región estimada en función de datos ESPAC años posteriores | H16: 103239.8 | I16: ESPAC 2006, tabla 51_8 | J16: 123873 | K16: ESPAC 2010, tabla 51_12 | L16: 115767 | M16: ESPAC 2012, tabla 53 | N16: 99199.328 | O16: ESPAC 2014 (version II corregida), tabla 54 | P16: 68708.593 | Q16: ESPAC 2016, tabla 63 | R16: 54537.495 | S16: ESPAC 2018 , tabla 66 | T16: 47621.019 | U16: ESPAC 2020 , tabla 67 | V16: 54977.432 | W16: ESPAC 2021 , tabla 67 | X16: 46212.781 | Y16: ESPAC 2022 , tabla 67 | Z16: 43664.111
C17: No Lechero Toros | D17: Sierra | E17: ESPAC 1995, Desagregación por región estimada en base a las proporciones de años posteriores | F17: 334787.01 | G17: CNA Provincial 2000, tabla 35, Desagregación por región estimada en función de datos ESPAC años posteriores | H17: 254082.67 | I17: ESPAC 2006, tabla 38_6 | J17: 215034 | K17: ESPAC 2010, tabla 38_10 | L17: 199819 | M17: ESPAC 2012, tabla 38 | N17: 176888.93 | O17: ESPAC 2014 (version II corregida), tabla 41 | P17: 179616.91 | Q17: ESPAC 2016, tabla 50 | R17: 149944.77 | S17: ESPAC 2018, tabla 50 | T17: 153765.65 | U17: ESPAC 2020, tabla 50 | V17: 179622.35 | W17: ESPAC 2021, tabla 50 | X17: 159223 | Y17: ESPAC 2022, tabla 50 | Z17: 157756.54
D18: Costa | E18: ESPAC 1995, Desagregación por región estimada en base a las proporciones de años posteriores | F18: 111373.03 | G18: CNA Provincial 2000, tabla 35, Desagregación por región estimada en función de datos ESPAC años posteriores | H18: 109983.94 | I18: ESPAC 2006, tabla 38_7 | J18: 71535 | K18: ESPAC 2010, tabla 38_11 | L18: 86495 | M18: ESPAC 2012, tabla 39 | N18: 73963.106 | O18: ESPAC 2014 (version II corregida), tabla 41 | P18: 85070.54 | Q18: ESPAC 2016, tabla 50 | R18: 68066.762 | S18: ESPAC 2018, tabla 50 | T18: 73566.158 | U18: ESPAC 2020, tabla 50 | V18: 106116.23 | W18: ESPAC 2021, tabla 50 | X18: 74162.62 | Y18: ESPAC 2022, tabla 50 | Z18: 71653.442
D19: Amazonia | E19: ESPAC 1995, Desagregación por región estimada en base a las proporciones de años posteriores | F19: 98924.039 | G19: CNA Provincial 2000, tabla 35, Desagregación por región estimada en función de datos ESPAC años posteriores | H19: 67666.285 | I19: ESPAC 2006, tabla 38_8 | J19: 63539 | K19: ESPAC 2010, tabla 38_12 | L19: 53215 | M19: ESPAC 2012, tabla 40 | N19: 49692.794 | O19: ESPAC 2014 (version II corregida), tabla 41 | P19: 38932.57 | Q19: ESPAC 2016, tabla 50 | R19: 25916.702 | S19: ESPAC 2018, tabla 50 | T19: 28493.155 | U19: ESPAC 2020, tabla 50 | V19: 39109.133 | W19: ESPAC 2021, tabla 50 | X19: 29865.823 | Y19: ESPAC 2022, tabla 50 | Z19: 27896.897
C20: No Lechero Vacas | D20: Sierra | E20: ESPAC 1995, Desagregación por región estimada en base a las proporciones de años posteriores | F20: 333821.6 | G20: CNA Provincial 2000, tabla 35 | H20: 311611.06 | I20: ESPAC 2006, tabla 38_06 | J20: 376913 | K20: ESPAC 2010, tabla 38_10 | L20: 326517 | M20: ESPAC 2012, tabla 38 | N20: 374957.18 | O20: ESPAC 2014 (version II corregida), tabla 41-54 | P20: 323096.43 | Q20: ESPAC 2016, tabla 50 | R20: 253038.23 | S20: ESPAC 2018, tabla 50 | T20: 250720.67 | U20: ESPAC 2020, tabla 50 | V20: 258773.78 | W20: ESPAC 2021, tabla 50 | X20: 277351.12 | Y20: ESPAC 2022, tabla 50 | Z20: 273816.95
D21: Costa | E21: ESPAC 1995, Desagregación por región estimada en base a las proporciones de años posteriores | F21: 410142.68 | G21: CNA Provincial 2000, tabla 35, Desagregación por región estimada en función de datos ESPAC años posteriores | H21: 468269.3 | I21: ESPAC 2006, tabla 38_07 | J21: 463086 | K21: ESPAC 2010, tabla 38_11 | L21: 490669 | M21: ESPAC 2012, tabla 39 | N21: 417290.71 | O21: ESPAC 2014 (version II corregida), tabla 41-54 | P21: 392883.31 | Q21: ESPAC 2016, tabla 50 | R21: 374969.32 | S21: ESPAC 2018, tabla 50 | T21: 401964.14 | U21: ESPAC 2020, tabla 50 | V21: 426123.25 | W21: ESPAC 2021, tabla 50 | X21: 382587.31 | Y21: ESPAC 2022, tabla 50 | Z21: 353200.41
D22: Amazonia | E22: ESPAC 1995, Desagregación por región estimada en base a las proporciones de años posteriores | F22: 100534.49 | G22: CNA Provincial 2000, tabla 36 | H22: 115162.21 | I22: ESPAC 2006, tabla 38_08 | J22: 113512 | K22: ESPAC 2010, tabla 38_12 | L22: 120671 | M22: ESPAC 2012, tabla 40 | N22: 150135.02 | O22: ESPAC 2014 (version II corregida), tabla 41-54 | P22: 70590.986 | Q22: ESPAC 2016, tabla 50 | R22: 70415.123 | S22: ESPAC 2018, tabla 50 | T22: 74474.301 | U22: ESPAC 2020, tabla 50 | V22: 94501.381 | W22: ESPAC 2021, tabla 50 | X22: 79622.394 | Y22: ESPAC 2022, tabla 50 | Z22: 74308.968
C23: No Lechero En crecimiento | D23: Sierra | E23: ESPAC 1995, Desagregación por región estimada en base a las proporciones de años posteriores | F23: 1177840.2 | G23: CNA Provincial 2000, tabla 35, Desagregación por región estimada en función de datos ESPAC años posteriores | H23: 1218489.8 | I23: ESPAC 2006, tabla 38_06 | J23: 1304372 | K23: ESPAC 2010, tabla 38_10 | L23: 1408615 | M23: ESPAC 2012, tabla 38 | N23: 1425251.8 | O23: ESPAC 2014 (version II corregida), tabla 41 | P23: 1212212.1 | Q23: ESPAC 2016, tabla 50 | R23: 1068890.5 | S23: ESPAC 2018, tabla 50 | T23: 1036600.5 | U23: ESPAC 2020, tabla 50 | V23: 1074848.8 | W23: ESPAC 2021, tabla 50 | X23: 1110233.4 | Y23: ESPAC 2022, tabla 50 | Z23: 1068249.5
D24: Costa | E24: ESPAC 1995, Desagregación por región estimada en base a las proporciones de años posteriores | F24: 975655.33 | G24: CNA Provincial 2000, tabla 37 | H24: 957121.05 | I24: ESPAC 2006, tabla 38_07 | J24: 1080467 | K24: ESPAC 2010, tabla 38_11 | L24: 1106464 | M24: ESPAC 2012, tabla 39 | N24: 1129032.6 | O24: ESPAC 2014 (version II corregida), tabla 41 | P24: 1019540.9 | Q24: ESPAC 2016, tabla 50 | R24: 1019540.9 | S24: ESPAC 2018, tabla 50 | T24: 984149.28 | U24: ESPAC 2020, tabla 50 | V24: 964542.04 | W24: ESPAC 2021, tabla 50 | X24: 898303.47 | Y24: ESPAC 2022, tabla 50 | Z24: 837169.03
D25: Amazonia | E25: ESPAC 1995, Desagregación por región estimada en base a las proporciones de años posteriores | F25: 320608.06 | G25: CNA Provincial 2000, tabla 35, Desagregación por región estimada en función de datos ESPAC años posteriores | H25: 321970.77 | I25: ESPAC 2006, tabla 38_08 | J25: 355050 | K25: ESPAC 2010, tabla 38_12 | L25: 372209 | M25: ESPAC 2012, tabla 40 | N25: 385026.56 | O25: ESPAC 2014 (version II corregida), tabla 41 | P25: 240620.69 | Q25: ESPAC 2016, tabla 50 | R25: 200358.89 | S25: ESPAC 2018, tabla 50 | T25: 220534.27 | U25: ESPAC 2020, tabla 50 | V25: 229766.59 | W25: ESPAC 2021, tabla 50 | X25: 208865.91 | Y25: ESPAC 2022, tabla 50 | Z25: 181377.18
B26: OTROS TIPOS DE GANADO | C26: Búfalo | E26: Retroproyección del dato considerando tasas de crecimiento del registro de agrocalidad - fiebre aftosa periodo 2016-2021 y la tasa de crecimiento el conjunto de bovinos mismo periodo | F26: 989.43 | G26: Retroproyección del dato considerando tasas de crecimiento del registro de agrocalidad - fiebre aftosa periodo 2016-2021 y la tasa de crecimiento el conjunto de bovinos mismo periodo | H26: 1406 | I26: Retroproyección del dato considerando tasas de crecimiento del registro de agrocalidad - fiebre aftosa periodo 2016-2021 y la tasa de crecimiento el conjunto de bovinos mismo periodo | J26: 2051 | K26: Retroproyección del dato considerando tasas de crecimiento del registro de agrocalidad - fiebre aftosa periodo 2016-2021 y la tasa de crecimiento el conjunto de bovinos mismo periodo | L26: 2606 | M26: Retroproyección del dato considerando tasas de crecimiento del registro de agrocalidad - fiebre aftosa periodo 2016-2021 y la tasa de crecimiento el conjunto de bovinos mismo periodo | N26: 2891 | O26: Retroproyección del dato considerando tasas de crecimiento del registro de agrocalidad - fiebre aftosa periodo 2016-2021 y la tasa de crecimiento el conjunto de bovinos mismo periodo | P26: 3049 | Q26: Datos de registro de vacunación por fiebre aftosa de Agrocalidad | R26: 3254 | S26: Datos de registro de vacunación por fiebre aftosa de Agrocalidad | T26: 3839 | U26: Datos de registro de vacunación por fiebre aftosa de Agrocalidad | V26: 4496 | W26: Datos de registro de vacunación por fiebre aftosa de Agrocalidad | X26: 5237 | Y26: Datos de registro de vacunación por fiebre aftosa de Agrocalidad | Z26: 5807
C27: Ovejas | E27: ESPAC 1995 | F27: 1692000 | G27: CNA 2000, tabla 6_00 | H27: 1127407 | I27: ESPAC 2006, tabla 10_06 | J27: 973223 | K27: ESPAC 2010, tabla 10_10 | L27: 792497 | M27: ESPAC 2012, tabla 10 | N27: 767729.5 | O27: ESPAC 2014 (version II corregida), tabla 48 | P27: 696732.28 | Q27: ESPAC 2016 , tabla 57 | R27: 589698.24 | S27: ESPAC 2018 , tabla 59 | T27: 498952.01 | U27: ESPAC 2020 , tabla 60 | V27: 496535.04 | W27: ESPAC 2021 , tabla 60 | X27: 528827.56 | Y27: ESPAC 2022 , tabla 60 | Z27: 551960.11
C28: Cabras | E28: ESPAC 1995 | F28: 317000 | G28: CNA 2000, tabla 6_00 | H28: 178105 | I28: ESPAC 2006, tabla 10_06 | J28: 156422 | K28: ESPAC 2010, tabla 10_10 | L28: 134824 | M28: ESPAC 2012, tabla 10 | N28: 108714.06 | O28: ESPAC 2014 (version II corregida), tabla 49 | P28: 20792.771 | Q28: ESPAC 2016 , tabla 56 | R28: 35761.086 | S28: ESPAC 2018 , tabla 60 | T28: 21745.307 | U28: ESPAC 2020 , tabla 61 | V28: 14092.397 | W28: ESPAC 2021 , tabla 61 | X28: 57849.051 | Y28: ESPAC 2022 , tabla 61 | Z28: 23789.38
C29: Camélidos sudamericanos | E29: Estimación según datos MAG Chimborazo | F29: 23177 | G29: Estimación según datos MAG Chimborazo | H29: 23177 | I29: FAO 2005, Situación de los camélidos sudamericanos en Ecuador | J29: 20043 | K29: MAGAP_Subsecretaría de Ganadería_2013 | L29: 16851.506 | M29: MAGAP_Subsecretaría de Ganadería_2013 | N29: 16851.506 | O29: Ministerio de Agricultura, Regional Chimborazo | P29: 16851.506 | Q29: Ministerio de Agricultura, Agrocalidad, Regional Chimborazo | R29: 17757.383 | S29: Ministerio de Agricultura, Agrocalidad, Regional Chimborazo | T29: 20949.783 | U29: Ministerio de Agricultura, Agrocalidad, Regional Chimborazo | V29: 20782.017 | W29: Ministerio de Agricultura, Agrocalidad, Regional Chimborazo | X29: 20698.806 | Y29: Ministerio de Agricultura, Agrocalidad, Regional Chimborazo | Z29: 20615.928
C30: Caballos | E30: ESPAC 1995 | F30: 524000 | G30: CNA 2000, tabla 6_00 | H30: 371480 | I30: ESPAC 2006, tabla 10_06 | J30: 403144 | K30: ESPAC 2010, tabla 10_10 | L30: 367248 | M30: ESPAC 2012, tabla 10 | N30: 351931.4 | O30: ESPAC 2014 (version II corregida), tabla 49 | P30: 327645.95 | Q30: ESPAC 2016 , tabla 58 | R30: 297860.72 | S30: ESPAC 2018 , tabla 60 | T30: 260479.02 | U30: ESPAC 2020 , tabla 61 | V30: 172574.11 | W30: ESPAC 2021 , tabla 61 | X30: 192187.21 | Y30: ESPAC 2022 , tabla 61 | Z30: 155407.36
C31: Mulas y Asnos | E31: ESPAC 1995 | F31: 405000 | G31: CNA 2000, tabla 6_00 | H31: 301995 | I31: ESPAC 2006, tabla 10_06 | J31: 303509 | K31: ESPAC 2010, tabla 10_10 | L31: 264405 | M31: ESPAC 2012, tabla 10 | N31: 246857.82 | O31: ESPAC 2014 (version II corregida), tabla 49 | P31: 222684.05 | Q31: ESPAC 2016 , tabla 59 | R31: 175261.66 | S31: ESPAC 2018 , tabla 60 | T31: 147168.66 | U31: ESPAC 2020 , tabla 61 | V31: 98938.513 | W31: ESPAC 2021 , tabla 61 | X31: 116082.94 | Y31: ESPAC 2022 , tabla 61 | Z31: 95081.034
C32: Cerdos | E32: ESPAC 1995 | F32: 2670000 | G32: CNA 2000, tabla 6_00 | H32: 1515276 | I32: ESPAC 2006, tabla 10_06 | J32: 1912048 | K32: ESPAC 2010, tabla 10_10 | L32: 1489761 | M32: ESPAC 2012, tabla 10 | N32: 1387203.2 | O32: ESPAC 2014 (version II corregida), tabla 47 | P32: 1672627.1 | Q32: ESPAC 2016 , tabla 60 | R32: 1428161.3 | S32: ESPAC 2018 , tabla 57 | T32: 1682662 | U32: ESPAC 2020 , tabla 57 | V32: 1059841.8 | W32: ESPAC 2021 , tabla 57 | X32: 1053923.1 | Y32: ESPAC 2022 , tabla 57 | Z32: 943249.42
C33: Aves de engorde | E33: Estimación según datos de CONAVE | F33: 17481848 | G33: Estimación según datos de CONAVE | H33: 19990113 | I33: Estimación según datos de CONAVE | J33: 22858259 | K33: Estimación según datos de CONAVE | L33: 24944905 | M33: Estimación según datos de CONAVE | N33: 26033770 | O33: Estimación según datos de CONAVE | P33: 27170165 | Q33: Datos de CONAVE | R33: 28356164 | S33: Datos de CONAVE | T33: 30205479 | U33: Datos de CONAVE | V33: 32424658 | W33: Datos de CONAVE | X33: 31438356 | Y33: Datos de CONAVE | Z33: 32424658
C34: Ponedoras | E34: Estimación según datos de CONAVE | F34: 9486896.5 | G34: Estimación según datos de CONAVE | H34: 10284930 | I34: Estimación según datos de CONAVE | J34: 11150093 | K34: Estimación según datos de CONAVE | L34: 11758331 | M34: Estimación según datos de CONAVE | N34: 12070525 | O34: Estimación según datos de CONAVE | P34: 12391008 | Q34: Datos de CONAVE | R34: 12720000 | S34: Datos de CONAVE | T34: 13510000 | U34: Datos de CONAVE | V34: 12690000 | W34: Datos de CONAVE | X34: 12840000 | Y34: Datos de CONAVE | Z34: 13790000
C35: Patos | E35: ESPAC 1995 | F35: 308162.78 | G35: CNA 2000, tabla 7_00 | H35: 400030 | I35: ESPAC 2006, tabla 47 y 48 | J35: 513644 | K35: ESPAC 2010, tabla 47 y 48 | L35: 553006 | M35: ESPAC 2012, tabla 47 y 48 | N35: 576346.26 | O35: ESPAC 2014 (version II corregida), tabla 50-51 | P35: 105674.95 | Q35: ESPAC 2016 , tabla 63 | R35: 524518.27 | S35: ESPAC 2018 , tabla 61,62 | T35: 70291.656 | U35: ESPAC 2020 , tabla 62,63 | V35: 458275.89 | W35: ESPAC 2021 , tabla 62,63 | X35: 554094.02 | Y35: ESPAC 2022 , tabla 62,63 | Z35: 376745.77
C36: Pavos | E36: ESPAC 1995 | F36: 266839.26 | G36: CNA 2000, tabla 7_00 | H36: 117040 | I36: ESPAC 2006, tabla 48 | J36: 196165 | K36: ESPAC 2010, tabla 48 | L36: 287080 | M36: ESPAC 2012, tabla 48 | N36: 78857.795 | O36: ESPAC 2014 (version II corregida), tabla 50-51 | P36: 446358.94 | Q36: ESPAC 2016 , tabla 64 | R36: 280845.58 | S36: ESPAC 2018 , tabla 61,62 | T36: 198716.81 | U36: ESPAC 2020 , tabla 62,63 | V36: 179336.36 | W36: ESPAC 2021 , tabla 62,63 | X36: 311843.7 | Y36: ESPAC 2022 , tabla 62,63 | Z36: 455071.32
C37: Otros (Especificar)
C38: TOTALES | F38: =SUM(F14:F37) -> 37997291 | H38: =SUM(H14:H37) -> 39106351 | J38: =SUM(J14:J37) -> 43523253 | L38: =SUM(L14:L37) -> 45865051 | N38: =SUM(N14:N37) -> 46877228 | P38: =SUM(P14:P37) -> 47616002 | R38: =SUM(R14:R37) -> 48556594 | T38: =SUM(T14:T37) -> 50677079 | V38: =SUM(V14:V37) -> 51955453 | X38: =SUM(X14:X37) -> 51186029 | Z38: =SUM(Z14:Z37) -> 52702878
B40: CULTIVO DEL ARROZ | G40: CULTIVO DEL ARROZ | L40: CULTIVO DEL ARROZ | Q40: CULTIVO DEL ARROZ | V40: CULTIVO DEL ARROZ | AA40: CULTIVO DEL ARROZ | AF40: CULTIVO DEL ARROZ | AK40: CULTIVO DEL ARROZ | AP40: CULTIVO DEL ARROZ
C43: Fuentes y Categorías | E43: Superficie sembrada Cultivo Arroz
C44: Cultivo del arroz | E44: 1994 | H44: 2000 | K44: 2006 | N44: 2010 | Q44: 2012 | T44: 2014 | W44: 2016 | Z44: 2018 | AC44: 2020 | AF44: 2021 | AI44: 2022
E45: Fuente | F45: Total /(has) | G45: % | H45: Fuente | I45: Total /(has) | J45: Total (miles has) | K45: Fuente | L45: Total /(has) | M45: Total (miles has) | N45: Fuente | O45: Total /(has) | P45: Total (miles has) | Q45: Fuente | R45: Total /(has) | S45: Total (miles has) | T45: Fuente | U45: Total /(has) | V45: % | W45: Fuente | X45: Total /(has) | Y45: % | Z45: Fuente | AA45: Total /(has) | AB45: % | AC45: Fuente | AD45: Total /(has) | AE45: % | AF45: Fuente | AG45: Total /(has) | AH45: % | AI45: Fuente | AJ45: Total /(has) | AK45: %
C46: Total de superficie sembrada | E46: ESPAC 1995 | F46: 400350 | H46: CNA 2000, tabla 20_00 | I46: 349726 | K46: ESPAC 2006, tabla 6_06 | L46: 357558 | N46: ESPAC 2010, tabla 6_10 | O46: 393137 | Q46: ESPAC 2012, tabla 6 | R46: 371170 | T46: ESPAC 2014, tabla 23 | U46: 354136 | W46: ESPAC 2016, tabla 28 | X46: 385039.49 | Z46: ESPAC 2018 | AA46: 301853 | AC46: ESPAC 2020 | AD46: 315023.04 | AF46: ESPAC 2021 | AG46: 342967.08 | AI46: ESPAC 2022 | AJ46: 343061.41
B47: a | C47: Upland /tierras altas | F47: =F$46*G47 -> 0 | G47: 0 | I47: =I$46*J47 -> 0 | J47: 0 | L47: =L$46*M47 -> 0 | M47: 0 | O47: =O$46*P47 -> 0 | P47: 0 | R47: =R$46*S47 -> 0 | S47: 0 | U47: =U$46*V47 -> 0 | V47: 0 | X47: =X$46*Y47 -> 0 | Y47: 0 | AA47: =AA$46*AB47 -> 0 | AB47: 0 | AD47: =AD$46*AE47 -> 0 | AE47: 0 | AG47: =AG$46*AH47 -> 0 | AH47: 0 | AJ47: =AJ$46*AK47 -> 0 | AK47: 0
B48: b | C48: Irrigadas | D48: Inundadas permanentemente | F48: =F$46*G48 -> 0 | G48: 0 | I48: =I$46*J48 -> 0 | J48: 0 | L48: =L$46*M48 -> 0 | M48: 0 | O48: =O$46*P48 -> 0 | P48: 0 | R48: =R$46*S48 -> 0 | S48: 0 | U48: =U$46*V48 -> 0 | V48: 0 | X48: =X$46*Y48 -> 0 | Y48: 0 | AA48: =AA$46*AB48 -> 0 | AB48: 0 | AD48: =AD$46*AE48 -> 0 | AE48: 0 | AG48: =AG$46*AH48 -> 0 | AH48: 0 | AJ48: =AJ$46*AK48 -> 0 | AK48: 0
B49: c | D49: Inundados intermitentemente – aireación simple | F49: =F$46*G49 -> 0 | G49: 0 | I49: =I$46*J49 -> 0 | J49: 0 | L49: =L$46*M49 -> 0 | M49: 0 | O49: =O$46*P49 -> 0 | P49: 0 | R49: =R$46*S49 -> 0 | S49: 0 | U49: =U$46*V49 -> 0 | V49: 0 | X49: =X$46*Y49 -> 0 | Y49: 0 | AA49: =AA$46*AB49 -> 0 | AB49: 0 | AD49: =AD$46*AE49 -> 0 | AE49: 0 | AG49: =AG$46*AH49 -> 0 | AH49: 0 | AJ49: =AJ$46*AK49 -> 0 | AK49: 0
B50: d | D50: Inundados intermitentemente – aireación multiple | F50: =F$46*G50 -> 88077 | G50: 0.22 | I50: =I$46*J50 -> 76939.72 | J50: 0.22 | L50: =L$46*M50 -> 78662.76 | M50: 0.22 | O50: =O$46*P50 -> 86490.14 | P50: 0.22 | R50: =R$46*S50 -> 81657.4 | S50: 0.22 | U50: =U$46*V50 -> 77909.92 | V50: 0.22 | X50: =X$46*Y50 -> 77007.899 | Y50: 0.2 | AA50: =AA$46*AB50 -> 84518.84 | AB50: 0.28 | AD50: =AD$46*AE50 -> 69305.068 | AE50: 0.22 | AG50: =AG$46*AH50 -> 65163.746 | AH50: 0.19 | AJ50: =AJ$46*AK50 -> 68612.282 | AK50: 0.2
B51: e | C51: Secano y aguas profundas | D51: Alimentacion regular por lluvia | F51: =F$46*G51 -> 192168 | G51: 0.48 | I51: =I$46*J51 -> 167868.48 | J51: 0.48 | L51: =L$46*M51 -> 171627.84 | M51: 0.48 | O51: =O$46*P51 -> 188705.76 | P51: 0.48 | R51: =R$46*S51 -> 178161.6 | S51: 0.48 | U51: =U$46*V51 -> 169985.28 | V51: 0.48 | X51: =X$46*Y51 -> 157866.19 | Y51: 0.41 | AA51: =AA$46*AB51 -> 135833.85 | AB51: 0.45 | AD51: =AD$46*AE51 -> 160661.75 | AE51: 0.51 | AG51: =AG$46*AH51 -> 185202.23 | AH51: 0.54 | AJ51: =AJ$46*AK51 -> 174961.32 | AK51: 0.51
B52: f | D52: Con tendencia a la sequia | F52: =F$46*G52 -> 0 | G52: 0 | I52: =I$46*J52 -> 0 | J52: 0 | L52: =L$46*M52 -> 0 | M52: 0 | O52: =O$46*P52 -> 0 | P52: 0 | R52: =R$46*S52 -> 0 | S52: 0 | U52: =U$46*V52 -> 0 | V52: 0 | X52: =X$46*Y52 -> 0 | Y52: 0 | AA52: =AA$46*AB52 -> 0 | AB52: 0 | AD52: =AD$46*AE52 -> 0 | AE52: 0 | AG52: =AG$46*AH52 -> 0 | AH52: 0 | AJ52: =AJ$46*AK52 -> 0 | AK52: 0
B53: g | D53: Aguas profundas | F53: =F$46*G53 -> 120105 | G53: 0.3 | I53: =I$46*J53 -> 104917.8 | J53: 0.3 | L53: =L$46*M53 -> 107267.4 | M53: 0.3 | O53: =O$46*P53 -> 117941.1 | P53: 0.3 | R53: =R$46*S53 -> 111351 | S53: 0.3 | U53: =U$46*V53 -> 106240.8 | V53: 0.3 | X53: =X$46*Y53 -> 146315.01 | Y53: 0.38 | AA53: =AA$46*AB53 -> 81500.31 | AB53: 0.27 | AD53: =AD$46*AE53 -> 85056.22 | AE53: 0.27 | AG53: =AG$46*AH53 -> 96030.784 | AH53: 0.28 | AJ53: =AJ$46*AK53 -> 99487.809 | AK53: 0.29
Z54: https://fliphtml5.com/ijia/seet/basic
B56: SUELOS AGRÍCOLAS | G56: SUELOS AGRÍCOLAS | L56: SUELOS AGRÍCOLAS | Q56: SUELOS AGRÍCOLAS | V56: SUELOS AGRÍCOLAS | AA56: SUELOS AGRÍCOLAS | AF56: SUELOS AGRÍCOLAS | AK56: SUELOS AGRÍCOLAS | AP56: SUELOS AGRÍCOLAS
C61: Fuentes y Categorías | E61: Cultivos no Fijadores de Nitrógeno (Total nacional por año de inventario)
C62: Suelos Agrícolas | D62: Fracción materia seca (%) | E62: 1994 | H62: 2000 | K62: 2006 | N62: 2010 | Q62: 2012 | T62: 2014 | W62: 2016 | Z62: 2018 | AC62: 2020 | AF62: 2021 | AI62: 2022
E63: Fuente | F63: Producción (t) | G63: Producción Kg. Materia Seca (C*E*1000) | H63: Fuente | I63: Producción (t) | J63: Producción Kg. Materia Seca (C*E*1000) | K63: Fuente | L63: Producción (t) | M63: Producción Kg. Materia Seca (C*E*1000) | N63: Fuente | O63: Producción (t) | P63: Producción Kg. Materia Seca (C*E*1000) | Q63: Fuente | R63: Producción (t) | S63: Producción Kg. Materia Seca (C*E*1000) | T63: Fuente | U63: Producción (t) | V63: Producción Kg. Materia Seca (C*E*1000) | W63: Fuente | X63: Producción (t) | Y63: Producción Kg. Materia Seca (C*E*1000) | Z63: Fuente | AA63: Producción (t) | AB63: Producción Kg. Materia Seca (C*E*1000) | AC63: Fuente | AD63: Producción (t) | AE63: Producción Kg. Materia Seca (C*E*1000) | AF63: Fuente | AG63: Producción (t) | AH63: Producción Kg. Materia Seca (C*E*1000) | AI63: Fuente | AJ63: Producción (t) | AK63: Producción Kg. Materia Seca (C*E*1000)
C64: Arroz Seco Solo | D64: 0.83 | E64: ESPAC 1995 | F64: 1290518.3 | G64: =D64*F64*1000 -> 1.0711302e+09 | H64: CNA 2000, tabla 20_00 | I64: 1239269 | J64: =D64*I64*1000 -> 1.0285933e+09 | K64: ESPAC 2006, tabla 6_06 | L64: 1501238 | M64: =D64*L64*1000 -> 1246027540 | N64: ESPAC 2010, tabla 6_10 | O64: 1706193 | P64: =D64*O64*1000 -> 1416140190 | Q64: ESPAC 2012, tabla 6 | R64: 1565535.3 | S64: =D64*R64*1000 -> 1.2993943e+09 | T64: ESPAC 2014, tabla 6 | U64: 1379953.6 | V64: =D64*U64*1000 -> 1.1453615e+09 | W64: ESPAC 2016, tabla 6 | X64: 1534537.1 | Y64: =D64*X64*1000 -> 1.2736658e+09 | Z64: ESPAC 2018, tabla 6 | AA64: 1350092.7 | AB64: =D64*AA64*1000 -> 1.1205769e+09 | AC64: ESPAC 2020, tabla 6 | AD64: 1336501.8 | AE64: =D64*AD64*1000 -> 1.1092965e+09 | AF64: ESPAC 2021, tabla 6 | AG64: 1503526.6 | AH64: =D64*AG64*1000 -> 1.2479271e+09 | AI64: ESPAC 2022, tabla 6 | AJ64: 1561211.4 | AK64: =D64*AJ64*1000 -> 1.2958055e+09
C65: Arroz Seco Asociado | D65: 0.83 | G65: =D65*F65*1000 -> 0 | H65: CNA 2000, tabla 20_00 | I65: 7365 | J65: =D65*I65*1000 -> 6112950 | K65: ESPAC 2006, tabla 6_06 | L65: 0 | M65: =D65*L65*1000 -> 0 | N65: ESPAC 2010, tabla 6_10 | O65: 0 | P65: =D65*O65*1000 -> 0 | Q65: ESPAC 2012, tabla 6 | S65: =D65*R65*1000 -> 0 | T65: ESPAC 2014, tabla 6 | V65: =D65*U65*1000 -> 0 | W65: ESPAC 2016, tabla 6 | Y65: =D65*X65*1000 -> 0 | Z65: ESPAC 2018, tabla 6 | AB65: =D65*AA65*1000 -> 0 | AC65: ESPAC 2020, tabla 6 | AE65: =D65*AD65*1000 -> 0 | AF65: ESPAC 2021, tabla 6 | AG65: 687.04946 | AH65: =D65*AG65*1000 -> 570251.05 | AI65: ESPAC 2022, tabla 6 | AJ65: 59.916354 | AK65: =D65*AJ65*1000 -> 49730.574
C66: Cebada Grano Seco Solo | D66: 0.83 | E66: ESPAC 1995 | F66: 31683.48 | G66: =D66*F66*1000 -> 26297288 | H66: CNA 2000, tabla 20_00 | I66: 24897 | J66: =D66*I66*1000 -> 20664510 | K66: ESPAC 2006, tabla 6_06 | L66: 23438 | M66: =D66*L66*1000 -> 19453540 | N66: ESPAC 2010, tabla 6_10 | O66: 18733 | P66: =D66*O66*1000 -> 15548390 | Q66: ESPAC 2012, tabla 6 | R66: 10961.922 | S66: =D66*R66*1000 -> 9098395.1 | T66: ESPAC 2014, tabla 6 | U66: 14489.938 | V66: =D66*U66*1000 -> 12026649 | W66: ESPAC 2016, tabla 6 | X66: 25414.102 | Y66: =D66*X66*1000 -> 21093704 | Z66: ESPAC 2018, tabla 6 | AA66: 13673.517 | AB66: =D66*AA66*1000 -> 11349019 | AC66: ESPAC 2020, tabla 6 | AD66: 14107.492 | AE66: =D66*AD66*1000 -> 11709218 | AF66: ESPAC 2021, tabla 6 | AG66: 14680.863 | AH66: =D66*AG66*1000 -> 12185116 | AI66: ESPAC 2022, tabla 6 | AJ66: 11155.095 | AK66: =D66*AJ66*1000 -> 9258728.6
C67: Cebada Grano Seco Asociado | D67: 0.83 | G67: =D67*F67*1000 -> 0 | H67: CNA 2000, tabla 20_00 | I67: 224 | J67: =D67*I67*1000 -> 185920 | K67: ESPAC 2006, tabla 6_06 | L67: 0 | M67: =D67*L67*1000 -> 0 | N67: ESPAC 2010, tabla 6_10 | O67: 0 | P67: =D67*O67*1000 -> 0 | Q67: ESPAC 2012, tabla 6 | S67: =D67*R67*1000 -> 0 | T67: ESPAC 2014, tabla 6 | V67: =D67*U67*1000 -> 0 | W67: ESPAC 2016, tabla 6 | Y67: =D67*X67*1000 -> 0 | Z67: ESPAC 2018, tabla 6 | AB67: =D67*AA67*1000 -> 0 | AC67: ESPAC 2020, tabla 6 | AE67: =D67*AD67*1000 -> 0 | AF67: ESPAC 2021, tabla 6 | AH67: =D67*AG67*1000 -> 0 | AI67: ESPAC 2022, tabla 6 | AK67: =D67*AJ67*1000 -> 0
C68: Maíz Duro Seco Solo | D68: 0.87 | E68: ESPAC 1995 | F68: 489692.26 | G68: =D68*F68*1000 -> 4.2603227e+08 | H68: CNA 2000, tabla 20_00 | I68: 487825 | J68: =D68*I68*1000 -> 424407750 | K68: ESPAC 2006, tabla 6_06 | L68: 647184 | M68: =D68*L68*1000 -> 563050080 | N68: ESPAC 2010, tabla 6_10 | O68: 412021 | P68: =D68*O68*1000 -> 358458270 | Q68: ESPAC 2012, tabla 6 | R68: 1130552.5 | S68: =D68*R68*1000 -> 9.8358071e+08 | T68: ESPAC 2014, tabla 6 | U68: 1468801.7 | V68: =D68*U68*1000 -> 1.2778575e+09 | W68: ESPAC 2016, tabla 6 | X68: 1028521.6 | Y68: =D68*X68*1000 -> 8.9481378e+08 | Z68: ESPAC 2018, tabla 6 | AA68: 1306660.7 | AB68: =D68*AA68*1000 -> 1.1367948e+09 | AC68: ESPAC 2020, tabla 6 | AD68: 1286416.5 | AE68: =D68*AD68*1000 -> 1.1191824e+09 | AF68: ESPAC 2021, tabla 6 | AG68: 1657355.4 | AH68: =D68*AG68*1000 -> 1.4418992e+09 | AI68: ESPAC 2022, tabla 6 | AJ68: 1613368.7 | AK68: =D68*AJ68*1000 -> 1.4036308e+09
C69: Maíz Duro Seco Asociado | D69: 0.87 | G69: =D69*F69*1000 -> 0 | H69: CNA 2000, tabla 20_00 | I69: 27478 | J69: =D69*I69*1000 -> 23905860 | K69: ESPAC 2006, tabla 6_06 | L69: 35854 | M69: =D69*L69*1000 -> 31192980 | N69: ESPAC 2010, tabla 6_10 | O69: 456006 | P69: =D69*O69*1000 -> 396725220 | Q69: ESPAC 2012, tabla 6 | R69: 84640.052 | S69: =D69*R69*1000 -> 73636845 | T69: ESPAC 2014, tabla 6 | U69: 64417.014 | V69: =D69*U69*1000 -> 56042802 | W69: ESPAC 2016, tabla 6 | X69: 62586.483 | Y69: =D69*X69*1000 -> 54450241 | Z69: ESPAC 2018, tabla 6 | AA69: 17486.237 | AB69: =D69*AA69*1000 -> 15213026 | AC69: ESPAC 2020, tabla 6 | AD69: 18467.853 | AE69: =D69*AD69*1000 -> 16067032 | AF69: ESPAC 2021, tabla 6 | AG69: 42014.183 | AH69: =D69*AG69*1000 -> 36552339 | AI69: ESPAC 2022, tabla 6 | AJ69: 27762.535 | AK69: =D69*AJ69*1000 -> 24153406
C70: Maíz Suave Seco solo | D70: 0.4 | G70: =D70*F70*1000 -> 0 | H70: CNA 2000, tabla 20_00 | I70: 4603 | J70: =D70*I70*1000 -> 1841200 | K70: ESPAC 2006, tabla 6_06 | L70: 30738 | M70: =D70*L70*1000 -> 12295200 | N70: ESPAC 2010, tabla 6_10 | O70: 11420 | P70: =D70*O70*1000 -> 4568000 | Q70: ESPAC 2012, tabla 6 | R70: 8773.585 | S70: =D70*R70*1000 -> 3509434 | T70: ESPAC 2014, tabla 6 | U70: 22780.467 | V70: =D70*U70*1000 -> 9112186.9 | W70: ESPAC 2016, tabla 6 | X70: 22699.186 | Y70: =D70*X70*1000 -> 9079674.4 | Z70: ESPAC 2018, tabla 6 | AA70: 42296.134 | AB70: =D70*AA70*1000 -> 16918454 | AC70: ESPAC 2020, tabla 6 | AD70: 83119.531 | AE70: =D70*AD70*1000 -> 33247812 | AF70: ESPAC 2021, tabla 6 | AG70: 35898.189 | AH70: =D70*AG70*1000 -> 14359275 | AI70: ESPAC 2022, tabla 6 | AJ70: 33832.959 | AK70: =D70*AJ70*1000 -> 13533184
C71: Maíz Suave Seco Asociado | D71: 0.4 | G71: =D71*F71*1000 -> 0 | H71: CNA 2000, tabla 20_00 | I71: 687 | J71: =D71*I71*1000 -> 274800 | K71: ESPAC 2006, tabla 6_06 | L71: 3898 | M71: =D71*L71*1000 -> 1559200 | N71: ESPAC 2010, tabla 6_10 | O71: 13377 | P71: =D71*O71*1000 -> 5350800 | Q71: ESPAC 2012, tabla 6 | R71: 19362.06 | S71: =D71*R71*1000 -> 7744824.2 | T71: ESPAC 2014, tabla 6 | U71: 13937.691 | V71: =D71*U71*1000 -> 5575076.5 | W71: ESPAC 2016, tabla 6 | X71: 7551.3165 | Y71: =D71*X71*1000 -> 3020526.6 | Z71: ESPAC 2018, tabla 6 | AA71: 7556.4412 | AB71: =D71*AA71*1000 -> 3022576.5 | AC71: ESPAC 2020, tabla 6 | AD71: 5474.6167 | AE71: =D71*AD71*1000 -> 2189846.7 | AF71: ESPAC 2021, tabla 6 | AG71: 6915.117 | AH71: =D71*AG71*1000 -> 2766046.8 | AI71: ESPAC 2022, tabla 6 | AJ71: 5618.7013 | AK71: =D71*AJ71*1000 -> 2247480.5
C72: Maíz Duro Choclo solo | D72: 0.87 | E72: ESPAC 1995 | F72: 67696.15 | G72: =D72*F72*1000 -> 58895650 | H72: CNA 2000, tabla 20_00 | I72: 46068 | J72: =D72*I72*1000 -> 40079160 | K72: ESPAC 2006, tabla 6_06 | L72: 34839 | M72: =D72*L72*1000 -> 30309930 | N72: ESPAC 2010, tabla 6_10 | O72: 17125 | P72: =D72*O72*1000 -> 14898750 | Q72: ESPAC 2012, tabla 6 | R72: 8682.6684 | S72: =D72*R72*1000 -> 7553921.5 | T72: ESPAC 2014, tabla 6 | U72: 17057.903 | V72: =D72*U72*1000 -> 14840376 | W72: ESPAC 2016, tabla 6 | X72: 7912.0672 | Y72: =D72*X72*1000 -> 6883498.5 | Z72: ESPAC 2018, tabla 6 | AA72: 7355.1166 | AB72: =D72*AA72*1000 -> 6398951.5 | AC72: ESPAC 2020, tabla 6 | AD72: 15911.221 | AE72: =D72*AD72*1000 -> 13842763 | AF72: ESPAC 2021, tabla 6 | AG72: 22034.519 | AH72: =D72*AG72*1000 -> 19170032 | AI72: ESPAC 2022, tabla 6 | AJ72: 10290.954 | AK72: =D72*AJ72*1000 -> 8953129.9
C73: Maíz Duro Choclo asociado | D73: 0.87 | G73: =D73*F73*1000 -> 0 | H73: CNA 2000, tabla 20_00 | I73: 26145 | J73: =D73*I73*1000 -> 22746150 | K73: ESPAC 2006, tabla 6_06 | L73: 15750 | M73: =D73*L73*1000 -> 13702500 | N73: ESPAC 2010, tabla 6_10 | O73: 20422 | P73: =D73*O73*1000 -> 17767140 | Q73: ESPAC 2012, tabla 6 | R73: 4896.7511 | S73: =D73*R73*1000 -> 4260173.4 | T73: ESPAC 2014, tabla 6 | U73: 5649.9836 | V73: =D73*U73*1000 -> 4915485.7 | W73: ESPAC 2016, tabla 6 | X73: 797.86347 | Y73: =D73*X73*1000 -> 694141.22 | Z73: ESPAC 2018, tabla 6 | AA73: 122.76859 | AB73: =D73*AA73*1000 -> 106808.67 | AC73: ESPAC 2020, tabla 6 | AD73: 147.71108 | AE73: =D73*AD73*1000 -> 128508.64 | AF73: ESPAC 2021, tabla 6 | AG73: 369.62463 | AH73: =D73*AG73*1000 -> 321573.43 | AI73: ESPAC 2022, tabla 6 | AJ73: 1123.1756 | AK73: =D73*AJ73*1000 -> 977162.79
C74: Maíz Suave Choclo Solo | D74: 0.4 | E74: ESPAC 1995 | F74: 55514.74 | G74: =D74*F74*1000 -> 22205896 | H74: CNA 2000, tabla 20_00 | I74: 32543 | J74: =D74*I74*1000 -> 13017200 | K74: ESPAC 2006, tabla 6_06 | L74: 50320 | M74: =D74*L74*1000 -> 20128000 | N74: ESPAC 2010, tabla 6_10 | O74: 34557 | P74: =D74*O74*1000 -> 13822800 | Q74: ESPAC 2012, tabla 6 | R74: 50270.321 | S74: =D74*R74*1000 -> 20108128 | T74: ESPAC 2014, tabla 6 | U74: 55358.328 | V74: =D74*U74*1000 -> 22143331 | W74: ESPAC 2016, tabla 6 | X74: 61955.656 | Y74: =D74*X74*1000 -> 24782262 | Z74: ESPAC 2018, tabla 6 | AA74: 65948.036 | AB74: =D74*AA74*1000 -> 26379214 | AC74: ESPAC 2020, tabla 6 | AD74: 52169.961 | AE74: =D74*AD74*1000 -> 20867984 | AF74: ESPAC 2021, tabla 6 | AG74: 81666.918 | AH74: =D74*AG74*1000 -> 32666767 | AI74: ESPAC 2022, tabla 6 | AJ74: 40052.848 | AK74: =D74*AJ74*1000 -> 16021139
C75: Maíz Suave Choclo Asociado | D75: 0.4 | G75: =D75*F75*1000 -> 0 | H75: CNA 2000, tabla 20_00 | I75: 10626 | J75: =D75*I75*1000 -> 4250400 | K75: ESPAC 2006, tabla 6_06 | L75: 16458 | M75: =D75*L75*1000 -> 6583200 | N75: ESPAC 2010, tabla 6_10 | O75: 19168 | P75: =D75*O75*1000 -> 7667200 | Q75: ESPAC 2012, tabla 6 | R75: 22354.113 | S75: =D75*R75*1000 -> 8941645 | T75: ESPAC 2014, tabla 6 | U75: 19700.831 | V75: =D75*U75*1000 -> 7880332.3 | W75: ESPAC 2016, tabla 6 | X75: 7050.7049 | Y75: =D75*X75*1000 -> 2820282 | Z75: ESPAC 2018, tabla 6 | AA75: 1840.4696 | AB75: =D75*AA75*1000 -> 736187.85 | AC75: ESPAC 2020, tabla 6 | AD75: 1571.4791 | AE75: =D75*AD75*1000 -> 628591.63 | AF75: ESPAC 2021, tabla 6 | AG75: 3151.1677 | AH75: =D75*AG75*1000 -> 1260467.1 | AI75: ESPAC 2022, tabla 6 | AJ75: 4347.1244 | AK75: =D75*AJ75*1000 -> 1738849.8
C76: Papa Tierno Solo | D76: 0.45 | E76: ESPAC 1995 | F76: 473204.54 | G76: =D76*F76*1000 -> 212942043 | H76: CNA 2000, tabla 20_00 | I76: 237066 | J76: =D76*I76*1000 -> 106679700 | K76: ESPAC 2006, tabla 6_06 | L76: 358300 | M76: =D76*L76*1000 -> 161235000 | N76: ESPAC 2010, tabla 6_10 | O76: 384235 | P76: =D76*O76*1000 -> 172905750 | Q76: ESPAC 2012, tabla 6 | R76: 284629.09 | S76: =D76*R76*1000 -> 1.2808309e+08 | T76: ESPAC 2014, tabla 6 | U76: 417178.14 | V76: =D76*U76*1000 -> 1.8773016e+08 | W76: ESPAC 2016, tabla 6 | X76: 418547.13 | Y76: =D76*X76*1000 -> 1.8834621e+08 | Z76: ESPAC 2018, tabla 6 | AA76: 267743.2 | AB76: =D76*AA76*1000 -> 1.2048444e+08 | AC76: ESPAC 2020, tabla 6 | AD76: 407514.3 | AE76: =D76*AD76*1000 -> 1.8338143e+08 | AF76: ESPAC 2021, tabla 6 | AG76: 243328.75 | AH76: =D76*AG76*1000 -> 1.0949794e+08 | AI76: ESPAC 2022, tabla 6 | AJ76: 250626.56 | AK76: =D76*AJ76*1000 -> 1.1278195e+08
C77: Papa Tierno Asociado | D77: 0.45 | G77: =D77*F77*1000 -> 0 | H77: CNA 2000, tabla 20_00 | I77: 2649 | J77: =D77*I77*1000 -> 1192050 | K77: ESPAC 2006, tabla 6_06 | L77: 2493 | M77: =D77*L77*1000 -> 1121850 | N77: ESPAC 2010, tabla 6_10 | O77: 2564 | P77: =D77*O77*1000 -> 1153800 | Q77: ESPAC 2012, tabla 6 | R77: 471.40138 | S77: =D77*R77*1000 -> 212130.62 | T77: ESPAC 2014, tabla 6 | U77: 3882.6638 | V77: =D77*U77*1000 -> 1747198.7 | W77: ESPAC 2016, tabla 6 | X77: 4042.3073 | Y77: =D77*X77*1000 -> 1819038.3 | Z77: ESPAC 2018, tabla 6 | AA77: 1457.4927 | AB77: =D77*AA77*1000 -> 655871.73 | AC77: ESPAC 2020, tabla 6 | AD77: 799.0024 | AE77: =D77*AD77*1000 -> 359551.08 | AF77: ESPAC 2021, tabla 6 | AG77: 1419.7912 | AH77: =D77*AG77*1000 -> 638906.02 | AI77: ESPAC 2022, tabla 6 | AJ77: 806.82904 | AK77: =D77*AJ77*1000 -> 363073.07
C78: Tomate Riñón Tierno Solo | D78: 0.1 | E78: ESPAC 1995 | F78: 64034.55 | G78: =D78*F78*1000 -> 6403455 | H78: CNA 2000, tabla 20_00 | I78: 60859 | J78: =D78*I78*1000 -> 6085900 | K78: ESPAC 2006, tabla 6_06 | L78: 60030 | M78: =D78*L78*1000 -> 6003000 | N78: ESPAC 2010, tabla 6_10 | O78: 53369 | P78: =D78*O78*1000 -> 5336900 | Q78: ESPAC 2012, tabla 6 | R78: 62716.345 | S78: =D78*R78*1000 -> 6271634.5 | T78: ESPAC 2014, tabla 6 | U78: 67718.078 | V78: =D78*U78*1000 -> 6771807.8 | W78: ESPAC 2016, tabla 6 | X78: 55334.815 | Y78: =D78*X78*1000 -> 5533481.5 | Z78: ESPAC 2018, tabla 6 | AA78: 31461.991 | AB78: =D78*AA78*1000 -> 3146199.1 | AC78: ESPAC 2020, tabla 6 | AD78: 38438.381 | AE78: =D78*AD78*1000 -> 3843838.1 | AF78: ESPAC 2021, tabla 6 | AG78: 55277.204 | AH78: =D78*AG78*1000 -> 5527720.4 | AI78: ESPAC 2022, tabla 6 | AJ78: 52228.949 | AK78: =D78*AJ78*1000 -> 5222894.9
C79: Tomate Riñón Tierno Asociado | D79: 0.1 | G79: =D79*F79*1000 -> 0 | H79: CNA 2000, tabla 20_00 | I79: 567 | J79: =D79*I79*1000 -> 56700 | K79: ESPAC 2006, tabla 6_06 | L79: 1899 | M79: =D79*L79*1000 -> 189900 | N79: ESPAC 2010, tabla 6_10 | O79: 149 | P79: =D79*O79*1000 -> 14900 | Q79: ESPAC 2012, tabla 6 | R79: 239.53365 | S79: =D79*R79*1000 -> 23953.365 | T79: ESPAC 2014, tabla 6 | U79: 4112.4783 | V79: =D79*U79*1000 -> 411247.83 | W79: ESPAC 2016, tabla 6 | X79: 215.59593 | Y79: =D79*X79*1000 -> 21559.593 | Z79: ESPAC 2018, tabla 6 | AA79: 429.50393 | AB79: =D79*AA79*1000 -> 42950.393 | AC79: ESPAC 2020, tabla 6 | AE79: =D79*AD79*1000 -> 0 | AF79: ESPAC 2021, tabla 6 | AH79: =D79*AG79*1000 -> 0 | AI79: ESPAC 2022, tabla 6 | AK79: =D79*AJ79*1000 -> 0
C80: Trigo Seco Solo | D80: 0.83 | E80: ESPAC 1995 | F80: 19762.86 | G80: =D80*F80*1000 -> 16403174 | H80: CNA 2000, tabla 20_00 | I80: 12822 | J80: =D80*I80*1000 -> 10642260 | K80: ESPAC 2006, tabla 6_06 | L80: 7577 | M80: =D80*L80*1000 -> 6288910 | N80: ESPAC 2010, tabla 6_10 | O80: 7605 | P80: =D80*O80*1000 -> 6312150 | Q80: ESPAC 2012, tabla 6 | R80: 7450 | S80: =D80*R80*1000 -> 6183500 | T80: ESPAC 2014, tabla 6 | U80: 6814.237 | V80: =D80*U80*1000 -> 5655816.7 | W80: ESPAC 2016, tabla 6 | X80: 6745.7733 | Y80: =D80*X80*1000 -> 5598991.8 | Z80: ESPAC 2018, tabla 6 | AA80: 5397.7721 | AB80: =D80*AA80*1000 -> 4480150.8 | AC80: ESPAC 2020, tabla 6 | AD80: 14646.735 | AE80: =D80*AD80*1000 -> 12156790 | AF80: ESPAC 2021, tabla 6 | AG80: 10898.384 | AH80: =D80*AG80*1000 -> 9045658.5 | AI80: ESPAC 2022, tabla 6 | AJ80: 7431.1932 | AK80: =D80*AJ80*1000 -> 6167890.4
C81: Trigo Seco Asociado | D81: 0.83 | G81: =D81*F81*1000 -> 0 | H81: CNA 2000, tabla 20_00 | I81: 136 | J81: =D81*I81*1000 -> 112880 | K81: ESPAC 2006, tabla 6_06 | L81: 0 | M81: =D81*L81*1000 -> 0 | N81: ESPAC 2010, tabla 6_10 | O81: 0 | P81: =D81*O81*1000 -> 0 | Q81: ESPAC 2012, tabla 6 | T81: ESPAC 2014, tabla 6 | W81: ESPAC 2016, tabla 6 | Z81: ESPAC 2018, tabla 6 | AB81: =D81*AA81*1000 -> 0 | AC81: ESPAC 2020, tabla 6 | AE81: =D81*AD81*1000 -> 0 | AF81: ESPAC 2021, tabla 6 | AH81: =D81*AG81*1000 -> 0 | AI81: ESPAC 2022, tabla 6 | AK81: =D81*AJ81*1000 -> 0
C82: Yuca Tierno Solo | D82: 0.37 | E82: ESPAC 1995 | F82: 75682.83 | G82: =D82*F82*1000 -> 28002647 | H82: CNA 2000, tabla 20_00 | I82: 66844 | J82: =D82*I82*1000 -> 24732280 | K82: ESPAC 2006, tabla 6_06 | L82: 53704 | M82: =D82*L82*1000 -> 19870480 | N82: ESPAC 2010, tabla 6_10 | O82: 46976 | P82: =D82*O82*1000 -> 17381120 | Q82: ESPAC 2012, tabla 6 | R82: 52696.837 | S82: =D82*R82*1000 -> 19497830 | T82: ESPAC 2014, tabla 6 | U82: 91573.78 | V82: =D82*U82*1000 -> 33882299 | W82: ESPAC 2016, tabla 6 | X82: 64899.349 | Y82: =D82*X82*1000 -> 24012759 | Z82: ESPAC 2018, tabla 6 | AA82: 71518.873 | AB82: =D82*AA82*1000 -> 26461983 | AC82: ESPAC 2020, tabla 6 | AD82: 60909.759 | AE82: =D82*AD82*1000 -> 22536611 | AF82: ESPAC 2021, tabla 6 | AG82: 84223.965 | AH82: =D82*AG82*1000 -> 31162867 | AI82: ESPAC 2022, tabla 6 | AJ82: 141133.45 | AK82: =D82*AJ82*1000 -> 52219378
C83: Yuca Tierno Asociado | D83: 0.37 | G83: =D83*F83*1000 -> 0 | H83: CNA 2000, tabla 20_00 | I83: 18127 | J83: =D83*I83*1000 -> 6706990 | K83: ESPAC 2006, tabla 6_06 | L83: 15693 | M83: =D83*L83*1000 -> 5806410 | N83: ESPAC 2010, tabla 6_10 | O83: 6881 | P83: =D83*O83*1000 -> 2545970 | Q83: ESPAC 2012, tabla 6 | R83: 18248.326 | S83: =D83*R83*1000 -> 6751880.5 | T83: ESPAC 2014, tabla 6 | U83: 19719.793 | V83: =D83*U83*1000 -> 7296323.3 | W83: ESPAC 2016, tabla 6 | X83: 25827.06 | Y83: =D83*X83*1000 -> 9556012.1 | Z83: ESPAC 2018, tabla 6 | AA83: 5373.6121 | AB83: =D83*AA83*1000 -> 1988236.5 | AC83: ESPAC 2020, tabla 6 | AD83: 3363.2386 | AE83: =D83*AD83*1000 -> 1244398.3 | AF83: ESPAC 2021, tabla 6 | AG83: 11986.53 | AH83: =D83*AG83*1000 -> 4435016.2 | AI83: ESPAC 2022, tabla 6 | AJ83: 5166.3209 | AK83: =D83*AJ83*1000 -> 1911538.7
C84: TOTALES | F84: =SUM(F64:F83) -> 2567789.7 | G84: =SUM(G64:G83) -> 1.8683126e+09 | I84: =SUM(I64:I83) -> 2306800 | J84: =SUM(J64:J83) -> 1742287930 | L84: =SUM(L64:L83) -> 2859413 | M84: =SUM(M64:M83) -> 2144817720 | O84: =SUM(O64:O83) -> 3210801 | P84: =SUM(P64:P83) -> 2456597350 | R84: =SUM(R64:R83) -> 3332480.8 | S84: =SUM(S64:S83) -> 2.5848524e+09 | U84: =SUM(U64:U83) -> 3673146.6 | V84: =SUM(V64:V83) -> 2.7992501e+09 | X84: =SUM(X64:X83) -> 3334638.1 | Y84: =SUM(Y64:Y83) -> 2.526192e+09 | AA84: =SUM(AA64:AA83) -> 3196414.6 | AB84: =SUM(AB64:AB83) -> 2.4947558e+09 | AD84: =SUM(AD64:AD83) -> 3339559.6 | AE84: =SUM(AE64:AE83) -> 2.5506833e+09 | AG84: =SUM(AG64:AG83) -> 3775434.2 | AH84: =SUM(AH64:AH83) -> 2.9699862e+09 | AJ84: =SUM(AJ64:AJ83) -> 3766216.7 | AK84: =SUM(AK64:AK83) -> 2.9550358e+09
C86: Fuentes y Categorías | E86: Cultivos Fijadores de Nitrógeno (Total nacional por año de inventario)
C87: Suelos Agrícolas | D87: Fracción materia seca (%) | E87: 1994 | I87: 2000 | M87: 2006 | Q87: 2010 | U87: 2012 | Y87: 2014 | AB87: 2016 | AE87: 2018 | AH87: 2020 | AK87: 2021 | AN87: 2022
E88: Fuente | F88: Producción (t) | G88: Producción Kg. Materia Seca (C*E*1000) | H88: Aporte de N cultivos fijadores (FBN) kg N/año | I88: Fuente | J88: Producción (t) | K88: Producción Kg. Materia Seca (C*I*1000) | L88: Aporte de N cultivos fijadores (FBN) kg N/año | M88: Fuente | N88: Producción (t) | O88: Producción Kg. Materia Seca (C*M*1000) | P88: Aporte de N cultivos fijadores (FBN) kg N/año | Q88: Fuente | R88: Producción (t) | S88: Producción Kg. Materia Seca (C*Q*1000) | T88: Aporte de N cultivos fijadores (FBN) kg N/año | U88: Fuente | V88: Producción (t) | W88: Producción Kg. Materia Seca (C*U*1000) | X88: Aporte de N cultivos fijadores (FBN) kg N/año | Y88: Fuente | Z88: Producción (t) | AA88: Producción Kg. Materia Seca (C*Y*1000) | AB88: Fuente | AC88: Producción (t) | AD88: Producción Kg. Materia Seca (C*Y*1000) | AE88: Fuente | AF88: Producción (t) | AG88: Producción Kg. Materia Seca (C*Y*1000) | AH88: Fuente | AI88: Producción (t) | AJ88: Producción Kg. Materia Seca (C*Y*1000) | AK88: Fuente | AL88: Producción (t) | AM88: Producción Kg. Materia Seca (C*Y*1000) | AN88: Fuente | AO88: Producción (t) | AP88: Producción Kg. Materia Seca (C*Y*1000)
C89: Arveja Seco Solo | D89: 0.83 | E89: ESPAC 1995 | F89: 3020.77 | G89: =D89*F89*1000 -> 2507239.1 | H89: 150434.35 | I89: CNA 2000, tabla 20_00 | J89: 1683 | K89: =D89*J89*1000 -> 1396890 | L89: 83813.4 | M89: ESPAC 2006, tabla 6_06 | N89: 1668 | O89: =D89*N89*1000 -> 1384440 | P89: 83066.4 | Q89: ESPAC 2010, tabla 6_10 | R89: 1026 | S89: =D89*R89*1000 -> 851580 | T89: 51094.8 | U89: ESPAC 2012, tabla 6 | V89: 365.89292 | W89: =D89*V89*1000 -> 303691.12 | X89: 18221.467 | Y89: ESPAC 2014, tabla 6 | Z89: 890 | AA89: =D89*Z89*1000 -> 738700 | AB89: ESPAC 2016, tabla 6 | AC89: 824.82937 | AD89: =D89*AC89*1000 -> 684608.38 | AE89: ESPAC 2018, tabla 6 | AF89: 509.88869 | AG89: =D89*AF89*1000 -> 423207.61 | AH89: ESPAC 2020, tabla 6 | AI89: 836.65413 | AJ89: =$D89*AI89*1000 -> 694422.93 | AK89: ESPAC 2021, tabla 6 | AL89: 415.41526 | AM89: =$D89*AL89*1000 -> 344794.67 | AN89: ESPAC 2022, tabla 6 | AO89: 772.04925 | AP89: =$D89*AO89*1000 -> 640800.88
C90: Arveja Seco Asociado | D90: 0.83 | E90: ESPAC 1995 | G90: =D90*F90*1000 -> 0 | H90: 0 | I90: CNA 2000, tabla 20_00 | J90: 128 | K90: =D90*J90*1000 -> 106240 | L90: 3187.2 | M90: ESPAC 2006, tabla 6_06 | N90: 63 | O90: =D90*N90*1000 -> 52290 | P90: 3137.4 | Q90: ESPAC 2010, tabla 6_10 | R90: 263 | S90: =D90*R90*1000 -> 218290 | T90: 13097.4 | U90: ESPAC 2012, tabla 6 | V90: 142.76693 | W90: =D90*V90*1000 -> 118496.55 | X90: 7109.793 | Y90: ESPAC 2014, tabla 6 | AA90: =D90*Z90*1000 -> 0 | AB90: ESPAC 2016, tabla 6 | AC90: 211.17808 | AD90: =D90*AC90*1000 -> 175277.8 | AE90: ESPAC 2018, tabla 6 | AF90: 82.145717 | AG90: =D90*AF90*1000 -> 68180.945 | AH90: ESPAC 2020, tabla 6 | AI90: 44.319172 | AJ90: =$D90*AI90*1000 -> 36784.913 | AK90: ESPAC 2021, tabla 6 | AL90: 8.1504418 | AM90: =$D90*AL90*1000 -> 6764.8667 | AN90: ESPAC 2022, tabla 6 | AO90: 15.372905 | AP90: =$D90*AO90*1000 -> 12759.511
C91: Arveja Tierno Solo | D91: 0.4 | E91: ESPAC 1995 | F91: 12897.73 | G91: =D91*F91*1000 -> 5159092 | H91: 309545.52 | I91: CNA 2000, tabla 20_00 | J91: 5991 | K91: =D91*J91*1000 -> 2396400 | L91: 71892 | M91: ESPAC 2006, tabla 6_06 | N91: 13254 | O91: =D91*N91*1000 -> 5301600 | P91: 318096 | Q91: ESPAC 2010, tabla 6_10 | R91: 9295 | S91: =D91*R91*1000 -> 3718000 | T91: 223080 | U91: ESPAC 2012, tabla 6 | V91: 4708.7061 | W91: =D91*V91*1000 -> 1883482.4 | X91: 113008.95 | Y91: ESPAC 2014, tabla 6 | Z91: 10945 | AA91: =D91*Z91*1000 -> 4378000 | AB91: ESPAC 2016, tabla 6 | AC91: 8954.5213 | AD91: =D91*AC91*1000 -> 3581808.5 | AE91: ESPAC 2018, tabla 6 | AF91: 13168.115 | AG91: =D91*AF91*1000 -> 5267246.1 | AH91: ESPAC 2020, tabla 6 | AI91: 18860.285 | AJ91: =$D91*AI91*1000 -> 7544113.9 | AK91: ESPAC 2021, tabla 6 | AL91: 16837.039 | AM91: =$D91*AL91*1000 -> 6734815.6 | AN91: ESPAC 2022, tabla 6 | AO91: 6810.6807 | AP91: =$D91*AO91*1000 -> 2724272.3
C92: Arveja Tierno Asociado | D92: 0.4 | E92: ESPAC 1995 | G92: =D92*F92*1000 -> 0 | H92: 0 | I92: CNA 2000, tabla 20_00 | J92: 524 | K92: =D92*J92*1000 -> 209600 | L92: 6288 | M92: ESPAC 2006, tabla 6_06 | N92: 295 | O92: =D92*N92*1000 -> 118000 | P92: 7080 | Q92: ESPAC 2010, tabla 6_10 | R92: 196 | S92: =D92*R92*1000 -> 78400 | T92: 4704 | U92: ESPAC 2012, tabla 6 | V92: 172.18166 | W92: =D92*V92*1000 -> 68872.664 | X92: 4132.3598 | Y92: ESPAC 2014, tabla 6 | AA92: =D92*Z92*1000 -> 0 | AB92: ESPAC 2016, tabla 6 | AC92: 586.36496 | AD92: =D92*AC92*1000 -> 234545.98 | AE92: ESPAC 2018, tabla 6 | AF92: 818.17949 | AG92: =D92*AF92*1000 -> 327271.79 | AH92: ESPAC 2020, tabla 6 | AI92: 1281.6546 | AJ92: =$D92*AI92*1000 -> 512661.83 | AK92: ESPAC 2021, tabla 6 | AL92: 419.65001 | AM92: =$D92*AL92*1000 -> 167860 | AN92: ESPAC 2022, tabla 6 | AO92: 135.78005 | AP92: =$D92*AO92*1000 -> 54312.022
C93: Fréjol Seco Solo | D93: 0.83 | E93: ESPAC 1995 | F93: 33382.98 | G93: =D93*F93*1000 -> 27707873 | H93: 1662472.4 | I93: CNA 2000, tabla 20_00 | J93: 8509 | K93: =D93*J93*1000 -> 7062470 | L93: 211874.1 | M93: ESPAC 2006, tabla 6_06 | N93: 10853 | O93: =D93*N93*1000 -> 9007990 | P93: 540479.4 | Q93: ESPAC 2010, tabla 6_10 | R93: 5639 | S93: =D93*R93*1000 -> 4680370 | T93: 280822.2 | U93: ESPAC 2012, tabla 6 | V93: 5211.2247 | W93: =D93*V93*1000 -> 4325316.5 | X93: 259518.99 | Y93: ESPAC 2014, tabla 6 | Z93: 12550 | AA93: =D93*Z93*1000 -> 10416500 | AB93: ESPAC 2016, tabla 6 | AC93: 5326.2515 | AD93: =D93*AC93*1000 -> 4420788.7 | AE93: ESPAC 2018, tabla 6 | AF93: 5184.4424 | AG93: =D93*AF93*1000 -> 4303087.2 | AH93: ESPAC 2020, tabla 6 | AI93: 9053.3713 | AJ93: =$D93*AI93*1000 -> 7514298.1 | AK93: ESPAC 2021, tabla 6 | AL93: 12943.762 | AM93: =$D93*AL93*1000 -> 10743323 | AN93: ESPAC 2022, tabla 6 | AO93: 10419.181 | AP93: =$D93*AO93*1000 -> 8647920.4
C94: Fréjol Seco Asociado | D94: 0.83 | E94: ESPAC 1995 | G94: =D94*F94*1000 -> 0 | H94: 0 | I94: CNA 2000, tabla 20_00 | J94: 9541 | K94: =D94*J94*1000 -> 7919030 | L94: 237570.9 | M94: ESPAC 2006, tabla 6_06 | N94: 7077 | O94: =D94*N94*1000 -> 5873910 | P94: 352434.6 | Q94: ESPAC 2010, tabla 6_10 | R94: 9005 | S94: =D94*R94*1000 -> 7474150 | T94: 448449 | U94: ESPAC 2012, tabla 6 | V94: 4779.26 | W94: =D94*V94*1000 -> 3966785.8 | X94: 238007.15 | Y94: ESPAC 2014, tabla 6 | AA94: =D94*Z94*1000 -> 0 | AB94: ESPAC 2016, tabla 6 | AC94: 5346.1937 | AD94: =D94*AC94*1000 -> 4437340.8 | AE94: ESPAC 2018, tabla 6 | AF94: 5910.9988 | AG94: =D94*AF94*1000 -> 4906129 | AH94: ESPAC 2020, tabla 6 | AI94: 2820.1231 | AJ94: =$D94*AI94*1000 -> 2340702.1 | AK94: ESPAC 2021, tabla 6 | AL94: 4773.446 | AM94: =$D94*AL94*1000 -> 3961960.2 | AN94: ESPAC 2022, tabla 6 | AO94: 4253.2493 | AP94: =$D94*AO94*1000 -> 3530196.9
C95: Fréjol Tierno Solo | D95: 0.4 | E95: ESPAC 1995 | F95: 18047.49 | G95: =D95*F95*1000 -> 7218996 | H95: 433139.76 | I95: CNA 2000, tabla 20_00 | J95: 5296 | K95: =D95*J95*1000 -> 2118400 | L95: 63552 | M95: ESPAC 2006, tabla 6_06 | N95: 15053 | O95: =D95*N95*1000 -> 6021200 | P95: 361272 | Q95: ESPAC 2010, tabla 6_10 | R95: 7344 | S95: =D95*R95*1000 -> 2937600 | T95: 176256 | U95: ESPAC 2012, tabla 6 | V95: 6833.4677 | W95: =D95*V95*1000 -> 2733387.1 | X95: 164003.22 | Y95: ESPAC 2014, tabla 6 | Z95: 17856 | AA95: =D95*Z95*1000 -> 7142400 | AB95: ESPAC 2016, tabla 6 | AC95: 12916.434 | AD95: =D95*AC95*1000 -> 5166573.6 | AE95: ESPAC 2018, tabla 6 | AF95: 17527.627 | AG95: =D95*AF95*1000 -> 7011050.8 | AH95: ESPAC 2020, tabla 6 | AI95: 8041.5331 | AJ95: =$D95*AI95*1000 -> 3216613.2 | AK95: ESPAC 2021, tabla 6 | AL95: 11859.484 | AM95: =$D95*AL95*1000 -> 4743793.7 | AN95: ESPAC 2022, tabla 6 | AO95: 19815.084 | AP95: =$D95*AO95*1000 -> 7926033.7
C96: Fréjol Tierno Asociado | D96: 0.4 | E96: ESPAC 1995 | G96: =D96*F96*1000 -> 0 | H96: 0 | I96: CNA 2000, tabla 20_00 | J96: 3152 | K96: =D96*J96*1000 -> 1260800 | L96: 37824 | M96: ESPAC 2006, tabla 6_06 | N96: 11103 | O96: =D96*N96*1000 -> 4441200 | P96: 266472 | Q96: ESPAC 2010, tabla 6_10 | R96: 10668 | S96: =D96*R96*1000 -> 4267200 | T96: 256032 | U96: ESPAC 2012, tabla 6 | V96: 9082.4913 | W96: =D96*V96*1000 -> 3632996.5 | X96: 217979.79 | Y96: ESPAC 2014, tabla 6 | AA96: =D96*Z96*1000 -> 0 | AB96: ESPAC 2016, tabla 6 | AC96: 13632.877 | AD96: =D96*AC96*1000 -> 5453150.8 | AE96: ESPAC 2018, tabla 6 | AF96: 4082.1914 | AG96: =D96*AF96*1000 -> 1632876.5 | AH96: ESPAC 2020, tabla 6 | AI96: 4110.4097 | AJ96: =$D96*AI96*1000 -> 1644163.9 | AK96: ESPAC 2021, tabla 6 | AL96: 5817.8477 | AM96: =$D96*AL96*1000 -> 2327139.1 | AN96: ESPAC 2022, tabla 6 | AO96: 4458.263 | AP96: =$D96*AO96*1000 -> 1783305.2
C97: Haba Seco Solo | D97: 0.83 | E97: ESPAC 1995 | F97: 3791.98 | G97: =D97*F97*1000 -> 3147343.4 | H97: 188840.6 | I97: CNA 2000, tabla 20_00 | J97: 4101 | K97: =D97*J97*1000 -> 3403830 | L97: 102114.9 | M97: ESPAC 2006, tabla 6_06 | N97: 2616 | O97: =D97*N97*1000 -> 2171280 | P97: 130276.8 | Q97: ESPAC 2010, tabla 6_10 | R97: 969 | S97: =D97*R97*1000 -> 804270 | T97: 48256.2 | U97: ESPAC 2012, tabla 6 | V97: 1084.6543 | W97: =D97*V97*1000 -> 900263.11 | X97: 54015.786 | Y97: ESPAC 2014, tabla 6 | Z97: 3957 | AA97: =D97*Z97*1000 -> 3284310 | AB97: ESPAC 2016, tabla 6 | AC97: 746.11559 | AD97: =D97*AC97*1000 -> 619275.94 | AE97: ESPAC 2018, tabla 6 | AF97: 1216.1255 | AG97: =D97*AF97*1000 -> 1009384.2 | AH97: ESPAC 2020, tabla 6 | AI97: 678.44893 | AJ97: =$D97*AI97*1000 -> 563112.61 | AK97: ESPAC 2021, tabla 6 | AL97: 2957.41 | AM97: =$D97*AL97*1000 -> 2454650.3 | AN97: ESPAC 2022, tabla 6 | AO97: 1435.8251 | AP97: =$D97*AO97*1000 -> 1191734.9
C98: Haba Seco Asociado | D98: 0.83 | E98: ESPAC 1995 | G98: =D98*F98*1000 -> 0 | H98: 0 | I98: CNA 2000, tabla 20_00 | J98: 1298 | K98: =D98*J98*1000 -> 1077340 | L98: 32320.2 | M98: ESPAC 2006, tabla 6_06 | N98: 1186 | O98: =D98*N98*1000 -> 984380 | P98: 59062.8 | Q98: ESPAC 2010, tabla 6_10 | R98: 1521 | S98: =D98*R98*1000 -> 1262430 | T98: 75745.8 | U98: ESPAC 2012, tabla 6 | V98: 1152.9308 | W98: =D98*V98*1000 -> 956932.58 | X98: 57415.955 | Y98: ESPAC 2014, tabla 6 | AA98: =D98*Z98*1000 -> 0 | AB98: ESPAC 2016, tabla 6 | AC98: 538.52562 | AD98: =D98*AC98*1000 -> 446976.26 | AE98: ESPAC 2018, tabla 6 | AF98: 473.86819 | AG98: =D98*AF98*1000 -> 393310.6 | AH98: ESPAC 2020, tabla 6 | AI98: 380.8955 | AJ98: =$D98*AI98*1000 -> 316143.26 | AK98: ESPAC 2021, tabla 6 | AL98: 352.73805 | AM98: =$D98*AL98*1000 -> 292772.58 | AN98: ESPAC 2022, tabla 6 | AO98: 706.67392 | AP98: =$D98*AO98*1000 -> 586539.35
C99: Haba Tierno Solo | D99: 0.4 | E99: ESPAC 1995 | F99: 17589.92 | G99: =D99*F99*1000 -> 7035968 | H99: 422158.08 | I99: CNA 2000, tabla 20_00 | J99: 12822 | K99: =D99*J99*1000 -> 5128800 | L99: 153864 | M99: ESPAC 2006, tabla 6_06 | N99: 12410 | O99: =D99*N99*1000 -> 4964000 | P99: 297840 | Q99: ESPAC 2010, tabla 6_10 | R99: 9214 | S99: =D99*R99*1000 -> 3685600 | T99: 221136 | U99: ESPAC 2012, tabla 6 | V99: 9649.6747 | W99: =D99*V99*1000 -> 3859869.9 | X99: 231592.19 | Y99: ESPAC 2014, tabla 6 | Z99: 26297 | AA99: =D99*Z99*1000 -> 10518800 | AB99: ESPAC 2016, tabla 6 | AC99: 18885.233 | AD99: =D99*AC99*1000 -> 7554093.2 | AE99: ESPAC 2018, tabla 6 | AF99: 14191.988 | AG99: =D99*AF99*1000 -> 5676795.4 | AH99: ESPAC 2020, tabla 6 | AI99: 27263.212 | AJ99: =$D99*AI99*1000 -> 10905285 | AK99: ESPAC 2021, tabla 6 | AL99: 24080.954 | AM99: =$D99*AL99*1000 -> 9632381.7 | AN99: ESPAC 2022, tabla 6 | AO99: 18797.453 | AP99: =$D99*AO99*1000 -> 7518981.2
C100: Haba Tierno Asociado | D100: 0.4 | E100: ESPAC 1995 | G100: =D100*F100*1000 -> 0 | H100: 0 | I100: CNA 2000, tabla 20_00 | J100: 951 | K100: =D100*J100*1000 -> 380400 | L100: 11412 | M100: ESPAC 2006, tabla 6_06 | N100: 1754 | O100: =D100*N100*1000 -> 701600 | P100: 42096 | Q100: ESPAC 2010, tabla 6_10 | R100: 2994 | S100: =D100*R100*1000 -> 1197600 | T100: 71856 | U100: ESPAC 2012, tabla 6 | V100: 2791.5553 | W100: =D100*V100*1000 -> 1116622.1 | X100: 66997.328 | Y100: ESPAC 2014, tabla 6 | AA100: =D100*Z100*1000 -> 0 | AB100: ESPAC 2016, tabla 6 | AC100: 759.76647 | AD100: =D100*AC100*1000 -> 303906.59 | AE100: ESPAC 2018, tabla 6 | AF100: 892.84489 | AG100: =D100*AF100*1000 -> 357137.96 | AH100: ESPAC 2020, tabla 6 | AI100: 609.04966 | AJ100: =$D100*AI100*1000 -> 243619.86 | AK100: ESPAC 2021, tabla 6 | AL100: 564.43989 | AM100: =$D100*AL100*1000 -> 225775.96 | AN100: ESPAC 2022, tabla 6 | AO100: 738.76136 | AP100: =$D100*AO100*1000 -> 295504.54
C101: TOTALES | F101: =SUM(F89:F100) -> 88730.87 | G101: =SUM(G89:G100) -> 52776512 | H101: =SUM(H89:H100) -> 3166590.7 | J101: =SUM(J89:J100) -> 53996 | K101: =SUM(K89:K100) -> 32460200 | L101: =SUM(L89:L100) -> 1015712.7 | N101: =SUM(N89:N100) -> 77332 | O101: =SUM(O89:O100) -> 41021890 | P101: =SUM(P89:P100) -> 2461313.4 | R101: =SUM(R89:R100) -> 58134 | S101: =SUM(S89:S100) -> 31175490 | T101: =SUM(T89:T100) -> 1870529.4 | V101: =SUM(V89:V100) -> 45974.807 | W101: =SUM(W89:W100) -> 23866716 | X101: =SUM(X89:X100) -> 1432003 | Z101: =SUM(Z89:Z100) -> 72495 | AC101: =SUM(AC89:AC100) -> 68728.291 | AF101: =SUM(AF89:AF100) -> 64058.416 | AI101: =SUM(AI89:AI100) -> 73979.956 | AL101: =SUM(AL89:AL100) -> 81030.337 | AO101: =SUM(AO89:AO100) -> 68358.374
C103: Fuentes y Categorías | D103: Principales Cultivos
C104: Quema en el campo de residuos agrícolas | D104: 1994 | G104: 2000 | J104: 2006 | M104: 2010 | P104: 2012 | S104: 2014 | V104: 2016 | Y104: 2018 | AB104: 2020 | AE104: 2021 | AH104: 2022
D105: Fuente | E105: Total (t) | F105: Total (Gg) | G105: Fuente | H105: Total (t) | I105: Total (Gg) | J105: Fuente | K105: Total (t) | L105: Total (Gg) | M105: Fuente | N105: Total (t) | O105: Total (Gg) | P105: Fuente | Q105: Total (t) | R105: Total (Gg) | S105: Fuente | T105: Total (t) | U105: Total (Gg) | V105: Fuente | W105: Total (t) | X105: Total (Gg) | Y105: Fuente | Z105: Total (t) | AA105: Total (Gg) | AB105: Fuente | AC105: Total (t) | AD105: Total (Gg) | AE105: Fuente | AF105: Total (t) | AG105: Total (Gg) | AH105: Fuente | AI105: Total (t) | AJ105: Total (Gg)
C106: 1 Cereales
C107: Trigo | D107: ESPAC 1995 | E107: =F80+F81 -> 19762.86 | F107: =E107/1000 -> 19.76286 | H107: =I80+I81 -> 12958 | I107: =H107/1000 -> 12.958 | K107: =L80+L81 -> 7577 | L107: =K107/1000 -> 7.577 | N107: =O80+O81 -> 7605 | O107: =N107/1000 -> 7.605 | Q107: =R80+R81 -> 7450 | R107: =Q107/1000 -> 7.45 | S107: ESPAC 2014, tabla 6 | T107: =U80+U81 -> 6814.237 | U107: =T107/1000 -> 6.814237 | V107: ESPAC 2016, tabla 6 | W107: =X80+X81 -> 6745.7733 | X107: =W107/1000 -> 6.7457733 | Y107: ESPAC 2018, tabla 6 | Z107: =AA80+AA81 -> 5397.7721 | AA107: =Z107/1000 -> 5.3977721 | AB107: ESPAC 2020, tabla 6 | AC107: =AD80+AD81 -> 14646.735 | AD107: =AC107/1000 -> 14.646735 | AE107: ESPAC 2021, tabla 6 | AF107: =AG80+AG81 -> 10898.384 | AG107: =AF107/1000 -> 10.898384 | AH107: ESPAC 2022, tabla 6 | AI107: =AJ80+AJ81 -> 7431.1932 | AJ107: =AI107/1000 -> 7.4311932
C108: Maíz | D108: ESPAC 1995 | E108: {=F68:F75} -> 489692.26 | F108: =E108/1000 -> 489.69226 | H108: {=I68:I75} -> 487825 | I108: =H108/1000 -> 487.825 | K108: {=L68:L75} -> 647184 | L108: =K108/1000 -> 647.184 | N108: {=O68:O75} -> 412021 | O108: =N108/1000 -> 412.021 | Q108: {=R68:R75} -> 1130552.5 | R108: =Q108/1000 -> 1130.5525 | S108: ESPAC 2014, tabla 6 | T108: {=U68:U75} -> 1468801.7 | U108: =T108/1000 -> 1468.8017 | V108: ESPAC 2016, tabla 6 | W108: {=X68:X75} -> 1028521.6 | X108: =W108/1000 -> 1028.5216 | Y108: ESPAC 2018, tabla 6 | Z108: {=AA68:AA75} -> 1306660.7 | AA108: =Z108/1000 -> 1306.6607 | AB108: ESPAC 2020, tabla 6 | AC108: {=AD68:AD75} -> 1286416.5 | AD108: =AC108/1000 -> 1286.4165 | AE108: ESPAC 2021, tabla 6 | AF108: {=AG68:AG75} -> 1657355.4 | AG108: =AF108/1000 -> 1657.3554 | AH108: ESPAC 2022, tabla 6 | AI108: {=AJ68:AJ75} -> 1613368.7 | AJ108: =AI108/1000 -> 1613.3687
C109: Maíz duro choclo (en choclo, solo) | E109: 0 | H109: 27478 | J109: ESPAC 2006, tabla 6_06 | K109: 35854 | M109: ESPAC 2010, tabla 6_10 | N109: 456006 | P109: ESPAC 2012, tabla 6 | Q109: 84640.052 | T109: 64417.014 | W109: 62586.483 | Y109: ESPAC 2018, tabla 6 | Z109: 17486.237 | AB109: ESPAC 2020, tabla 6 | AC109: 18467.853 | AE109: ESPAC 2021, tabla 6 | AF109: 42014.183 | AH109: ESPAC 2022, tabla 6 | AI109: 27762.535
C110: Maíz duro choclo (en choclo, asociado) | E110: 0 | H110: 4603 | J110: ESPAC 2006, tabla 6_06 | K110: 30738 | M110: ESPAC 2010, tabla 6_10 | N110: 11420 | Q110: 8773.585 | T110: 22780.467 | W110: 22699.186 | Y110: ESPAC 2018, tabla 6 | Z110: 42296.134 | AB110: ESPAC 2020, tabla 6 | AC110: 83119.531 | AE110: ESPAC 2021, tabla 6 | AF110: 35898.189 | AH110: ESPAC 2022, tabla 6 | AI110: 33832.959
C111: Maíz duro seco (grano seco, solo) | E111: 0 | H111: 687 | J111: ESPAC 2006, tabla 6_06 | K111: 3898 | M111: ESPAC 2010, tabla 6_10 | N111: 13377 | P111: ESPAC 2012, tabla 6 | Q111: 19362.06 | T111: 13937.691 | W111: 7551.3165 | Y111: ESPAC 2018, tabla 6 | Z111: 7556.4412 | AB111: ESPAC 2020, tabla 6 | AC111: 5474.6167 | AE111: ESPAC 2021, tabla 6 | AF111: 6915.117 | AH111: ESPAC 2022, tabla 6 | AI111: 5618.7013
C112: Maíz duro seco (grano seco, asociado) | E112: 67696.15 | H112: 46068 | J112: ESPAC 2006, tabla 6_06 | K112: 34839 | M112: ESPAC 2010, tabla 6_10 | N112: 17125 | P112: ESPAC 2012, tabla 6 | Q112: 8682.6684 | T112: 17057.903 | W112: 7912.0672 | Y112: ESPAC 2018, tabla 6 | Z112: 7355.1166 | AB112: ESPAC 2020, tabla 6 | AC112: 15911.221 | AE112: ESPAC 2021, tabla 6 | AF112: 22034.519 | AH112: ESPAC 2022, tabla 6 | AI112: 10290.954
C113: Maíz suave choclo (en choclo, solo) | E113: 0 | H113: 26145 | J113: ESPAC 2006, tabla 6_06 | K113: 15750 | M113: ESPAC 2010, tabla 6_10 | N113: 20422 | P113: ESPAC 2012, tabla 6 | Q113: 4896.7511 | T113: 5649.9836 | W113: 797.86347 | Y113: ESPAC 2018, tabla 6 | Z113: 122.76859 | AB113: ESPAC 2020, tabla 6 | AC113: 147.71108 | AE113: ESPAC 2021, tabla 6 | AF113: 369.62463 | AH113: ESPAC 2022, tabla 6 | AI113: 1123.1756
C114: Maíz suave choclo (en choclo, asociado) | E114: 55514.74 | H114: 32543 | J114: ESPAC 2006, tabla 6_06 | K114: 50320 | M114: ESPAC 2010, tabla 6_10 | N114: 34557 | P114: ESPAC 2012, tabla 6 | Q114: 50270.321 | T114: 55358.328 | W114: 61955.656 | Y114: ESPAC 2018, tabla 6 | Z114: 65948.036 | AB114: ESPAC 2020, tabla 6 | AC114: 52169.961 | AE114: ESPAC 2021, tabla 6 | AF114: 81666.918 | AH114: ESPAC 2022, tabla 6 | AI114: 40052.848
C115: Maíz suave seco (grano seco, solo) | E115: 0 | H115: 10626 | J115: ESPAC 2006, tabla 6_06 | K115: 16458 | M115: ESPAC 2010, tabla 6_10 | N115: 19168 | P115: ESPAC 2012, tabla 6 | Q115: 22354.113 | T115: 19700.831 | W115: 7050.7049 | Z115: 1840.4696 | AC115: 1571.4791 | AF115: 3151.1677 | AI115: 4347.1244
C116: Maíz suave seco (grano seco, asociado) | J116: ESPAC 2006, tabla 6_06 | M116: ESPAC 2010, tabla 6_10 | P116: ESPAC 2012, tabla 6
C117: Arroz | D117: ESPAC 1995 | E117: =F64+F65 -> 1290518.3 | F117: =E117/1000 -> 1290.5183 | H117: =I64+I65 -> 1246634 | I117: =H117/1000 -> 1246.634 | K117: =L64+L65 -> 1501238 | L117: =K117/1000 -> 1501.238 | N117: =O64+O65 -> 1706193 | O117: =N117/1000 -> 1706.193 | Q117: =R64+R65 -> 1565535.3 | R117: =Q117/1000 -> 1565.5353 | S117: ESPAC 2014, tabla 6 | T117: =U64+U65 -> 1379953.6 | U117: =T117/1000 -> 1379.9536 | V117: ESPAC 2016, tabla 6 | W117: =X64+X65 -> 1534537.1 | X117: =W117/1000 -> 1534.5371 | Y117: ESPAC 2018, tabla 6 | Z117: =AA64+AA65 -> 1350092.7 | AA117: =Z117/1000 -> 1350.0927 | AB117: ESPAC 2020, tabla 6 | AC117: =AD64+AD65 -> 1336501.8 | AD117: =AC117/1000 -> 1336.5018 | AE117: ESPAC 2021, tabla 6 | AF117: =AG64+AG65 -> 1504213.6 | AG117: =AF117/1000 -> 1504.2136 | AH117: ESPAC 2022, tabla 6 | AI117: =AJ64+AJ65 -> 1561271.3 | AJ117: =AI117/1000 -> 1561.2713
...

Sheet 3A1 Fermentación E.
B2: EMISIONES POR FERMENTACIÓN ENTÉRICA Y GESTIÓN DE ESTIÉRCOL | G2: INDICE
B4: Sector | C4: Agricultura
B5: Categoria | C5: Emisiones de Metano por Fermentación Entérica y Gestión de Estiércol
B6: Código de Categoría | C6: 3A1 y 3A2
B7: Hoja | C7: 1 de 1
B8: Ecuación | D8: Ecuación 10.19 | F8: Ec. 10.19 y 10.20
B9: Categoria de Ganado | D9: Número de Animales | E9: Factor de Emisión para Fermentación Entérica | F9: CH4 Emisiones para Fermentación Entérica
D10: (cabezas) | E10: (kg cabeza-1 año-1) | F10: (Gg CH4 año-1)
E11: Tablas 10.10 y 10.11 | F11: CH4 Enterica = N(T) * EF(T) * 10-6
B12: T | D12: N (T) | E12: EF(T) | F12: CH4 Enteric
B13: Ganado Lechero | C13: Sierra | D13: ='Datos de Actividad'!T14 -> 522643.97 | E13: 86.403932 | F13: =D13*E13*(10^-6) -> 45.158494
C14: Costa | D14: ='Datos de Actividad'!T15 -> 262262.61 | E14: 107.26406 | F14: =D14*E14*(10^-6) -> 28.131352
C15: Amazonia | D15: ='Datos de Actividad'!T16 -> 47621.019 | E15: 104.30794 | F15: =D15*E15*(10^-6) -> 4.9672503
B16: No LecheroToros | C16: Sierra | D16: ='Datos de Actividad'!T17 -> 153765.65 | E16: 72.771229 | F16: =D16*E16*(10^-6) -> 11.189715
C17: Costa | D17: ='Datos de Actividad'!T18 -> 73566.158 | E17: 101.72988 | F17: =D17*E17*(10^-6) -> 7.4838761
C18: Amazonia | D18: ='Datos de Actividad'!T19 -> 28493.155 | E18: 83.486331 | F18: =D18*E18*(10^-6) -> 2.378789
B19: No Lechero Vacas | C19: Sierra | D19: ='Datos de Actividad'!T20 -> 250720.67 | E19: 68.638417 | F19: =D19*E19*(10^-6) -> 17.20907
C20: Costa | D20: ='Datos de Actividad'!T21 -> 401964.14 | E20: 95.165192 | F20: =D20*E20*(10^-6) -> 38.252995
C21: Amazonia | D21: ='Datos de Actividad'!T22 -> 74474.301 | E21: 91.432747 | F21: =D21*E21*(10^-6) -> 6.8093899
B22: No Lechero En crecimiento | C22: Sierra | D22: ='Datos de Actividad'!T23 -> 1036600.5 | E22: 40.729428 | F22: =D22*E22*(10^-6) -> 42.220144
C23: Costa | D23: ='Datos de Actividad'!T24 -> 984149.28 | E23: 54.996918 | F23: =D23*E23*(10^-6) -> 54.125177
C24: Amazonia | D24: ='Datos de Actividad'!T25 -> 220534.27 | E24: 59.13981 | F24: =D24*E24*(10^-6) -> 13.042355
B25: Búfalos | D25: ='Datos de Actividad'!T26 -> 3839 | E25: 68 | F25: =D25*E25*(10^-6) -> 0.261052
B26: Ovejas | D26: ='Datos de Actividad'!T27 -> 498952.01 | E26: 5 | F26: =D26*E26*(10^-6) -> 2.4947601
B27: Cabras | D27: ='Datos de Actividad'!T28 -> 21745.307 | E27: 5 | F27: =D27*E27*(10^-6) -> 0.10872653
B28: Camélidos sudamericanos | D28: ='Datos de Actividad'!T29 -> 20949.783 | E28: 8 | F28: =D28*E28*(10^-6) -> 0.16759827
B29: Caballos | D29: ='Datos de Actividad'!T30 -> 260479.02 | E29: 18 | F29: =D29*E29*(10^-6) -> 4.6886223
B30: Mulas & Asnos | D30: ='Datos de Actividad'!T31 -> 147168.66 | E30: 10 | F30: =D30*E30*(10^-6) -> 1.4716866
B31: Cerdos | D31: ='Datos de Actividad'!T32 -> 1682662 | E31: 1 | F31: =D31*E31*(10^-6) -> 1.682662
B32: Aves de engorde | D32: ='Datos de Actividad'!T33 -> 30205479 | E32: NA | F32: NA
B33: Ponedoras | D33: ='Datos de Actividad'!T34 -> 13510000 | E33: NA | F33: NA
B34: Patos | D34: ='Datos de Actividad'!T35 -> 70291.656 | E34: NA | F34: NA
B35: Pavos | D35: ='Datos de Actividad'!T36 -> 198716.81 | E35: NA | F35: NA
B36: Total | F36: =SUM(F13:F35) -> 281.84372
B39: NOTA EXPLICATIVA CATEGORIA FERMENTACIÓN ENTÉRICA
B40: Dato | C40: Tipo | D40: Fuente | E40: Observaciones
B41: Factor de emisión propio para bovinos | C41: FE | D41: Elaboración país | E41: El factor propio es calculado en base a los datos del proyecto GCI del periodo 2014-2018, incluye todas las variables requeridas para el cálculo del mismo de forma regional y por categoría, el Ym es usado por defecto del IPCC | G41: .
B42: Ganado Lechero | C42: Datos de Actividad | D42: ESPAC 2018 (datos ajustados y suavizados, se usan las tasas de variación interanual del registro de agrocalidad de vacunación por fiebre aftosa), tabla 66, | E42: Dato de actividad desagregado por región, dato de existencias población adulta de mas de dos años | G42: .
B43: Ganado Lechero | C43: FE para Fermentación Entérica | D43: FE propio para Ecuador calculado en base a los parametros levantados en campo por el Proyecto Ganadería Climáticamente Inteligente-- NAMA de FAO, cálculos realizados por el equipo INGEI Agricultura, el factor de conversión Ym es tomado de los recomendados por el IPCC | E43: El cálculo del factor de emisión propio utiliza las variables del proyecto GCI levantadas en un muestreo de fincas representivo a nivel nacional | G43: .
B44: No Lechero Toros | C44: Datos de Actividad | D44: ESPAC 2018, tabla 50 | E44: Corresponde al número de toros de 2 o más años de edad | G44: .
B45: No LecheroToros | C45: FE para Fermentación Entérica | D45: FE propio para Ecuador calculado en base a los parametros levantados en campo por el Proyecto Ganadería Climáticamente Inteligente-- NAMA de FAO, cálculos realizados por el equipo INGEI Agricultura, Ym tomado de los valores por defecto para la región del IPCC | E45: El cálculo del factor de emisión propio utiliza las variables del proyecto GCI levantadas en un muestreo de fincas representivo a nivel nacional | G45: .
B46: No Lechero Vacas | C46: Datos de Actividad | D46: ESPAC 2018, tabla 50. Este dato considera (Vacas madre, vacas vientre, otras hembras) menos el número de vacas lecheras | E46: Corresponde al número de vacas de 2 o más años de edad menos el número de vacas ordeñadas | G46: .
B47: No Lechero Vacas | C47: FE para Fermentación Entérica | D47: FE propio para Ecuador calculado en base a los parametros levantados en campo por el Proyecto Ganadería Climáticamente Inteligente-- NAMA de FAO, cálculos realizados por el equipo INGEI Agricultura, Ym tomado de los valores por defecto para la región del IPCC | E47: El cálculo del factor de emisión propio utiliza las variables del proyecto GCI levantadas en un muestreo de fincas representivo a nivel nacional | G47: .
B48: No Lechero En crecimiento | C48: Datos de Actividad | D48: ESPAC 2018, tabla 50 | E48: Corresponde a la suma de terneros, toretes, terneras y vaconas, se confirma que el dato puede ser usado como dato final (dias vivo) considerando que el formulario del INEC pregunta por las existencias al momento de la encuesta, y no existe estadistica nacional para discretizar aquella población que vive menos de un año. | G48: .
B49: No Lechero En crecimiento | C49: FE para Fermentación Entérica | D49: FE propio para Ecuador calculado en base a los parametros levantados en campo por el Proyecto Ganadería Climáticamente Inteligente-- NAMA de FAO, cálculos realizados por el equipo INGEI Agricultura, Ym tomado de los valores por defecto para la región del IPCC | E49: El cálculo del factor de emisión propio utiliza las variables del proyecto GCI levantadas en un muestreo de fincas representivo a nivel nacional | G49: .
B50: Búfalos | C50: Datos de Actividad | D50: Registro de vacunación por fiebre aftosa de agrocalidad | G50: .
B51: Búfalos | C51: FE para Fermentación Entérica | D51: Directrices del IPCC para los inventarios de gases de efecto invernadero 2006, Vol 4, Cap 10 (Cuadro 10A.2, p. 10.74) | G51: .
B52: Ovejas | C52: Datos de Actividad | D52: ESPAC 2018 (datos ajustados y suavizados), tabla 57 | E52: se confirma que el dato puede ser usado como dato final (dias vivo) considerando que el formulario del INEC pregunta por las existencias al momento de la encuesta, y no existe estadistica nacional para discretizar aquella población que vive menos de un año. | G52: .
B53: Ovejas | C53: FE para Fermentación Entérica | D53: Directrices del IPCC de 2006 para los inventarios nacionales de gases de efecto invernadero, Vol 4, Cap 10 (Cuadro 10.10, p. 10.30) | G53: .
B54: Cabras | C54: Datos de Actividad | D54: ESPAC 2018 (datos ajustados y suavizados), tabla 58 | E54: se confirma que el dato puede ser usado como dato final (dias vivo) considerando que el formulario del INEC pregunta por las existencias al momento de la encuesta, y no existe estadistica nacional para discretizar aquella población que vive menos de un año. | G54: .
B55: Cabras | C55: FE para Fermentación Entérica | D55: Directrices del IPCC de 2006 para los inventarios nacionales de gases de efecto invernadero, Vol 4, Cap 10 (Cuadro 10.10, p. 10.30) | G55: .
B56: Camélidos sudamericanos | C56: Datos de Actividad | D56: Ministerio de Agricultura, Agrocalidad, Regional Chimborazo. Para este dato se consideran alpacas, llamas, vicuñas, huarisos. | E56: Se confirman estadisticas similares y poblaciones estacionales para la categoría, las tasas de crecimiento se proyectan desde los datos de 2016 y 2018 para los siguientes años | G56: .
B57: Camélidos sudamericanos | C57: FE para Fermentación Entérica | D57: Directrices del IPCC de 2006 para los inventarios nacionales de gases de efecto invernadero, Vol 4, Cap 10 (Cuadro 10.10, p. 10.30) | E57: Corresponde al EF por defecto para alpacas, atendiendo al peso en pie detallado en el cuadro 10.10 capitulo 10. De acuerdo al informe "Situación de los camélidos sudamericanos en Ecuador (FAO, 2005 p.10)", éstos presentan un peso moderado (60 a 80 kg). Se asume que el EF de alpacas aplica a todas las especies de camélidos sudamericanos. | G57: .
B58: Caballos | C58: Datos de Actividad | D58: ESPAC 2018 (datos ajustados y suavizados), tabla 58 | E58: se confirma que el dato puede ser usado como dato final (dias vivo) considerando que el formulario del INEC pregunta por las existencias al momento de la encuesta, y no existe estadistica nacional para discretizar aquella población que vive menos de un año. | G58: .
B59: Caballos | C59: FE para Fermentación Entérica | D59: Directrices del IPCC de 2006 para los inventarios nacionales de gases de efecto invernadero, Vol 4, Cap 10 (Cuadro 10.10, p. 10.30) | G59: .
B60: Mulas & Asnos | C60: Datos de Actividad | D60: ESPAC 2018 (datos ajustados y suavizados), tabla 58 | E60: se confirma que el dato puede ser usado como dato final (dias vivo) considerando que el formulario del INEC pregunta por las existencias al momento de la encuesta, y no existe estadistica nacional para discretizar aquella población que vive menos de un año. | G60: .
B61: Mulas & Asnos | C61: FE para Fermentación Entérica | D61: Directrices del IPCC de 2006 para los inventarios nacionales de gases de efecto invernadero, Vol 4, Cap 10 (Cuadro 10.10, p. 10.30) | G61: .
B62: Cerdos | C62: Datos de Actividad | D62: ESPAC 2018 (datos ajustados y suavizados), tabla 56 | E62: Se usa el dato de existencias, para afinar la estadistica de "dias vivo", el periodo de dias vivo se consideran 27 semanas | G62: .
B63: Cerdos | C63: FE para Fermentación Entérica | D63: Directrices del IPCC de 2006 para los inventarios nacionales de gases de efecto invernadero, Vol 4, Cap 10 (Cuadro 10.10, p. 10.30) | G63: .
B64: Aves de engorde | C64: Datos de Actividad | D64: Datos de CONAVE, bajo la consideración de ciclos productivos o dias vivo del animal (45) | E64: Corresponde a la suma de aves criadas en campo (pollitos, pollitas, pollos, pollas + gallos, gallinas) + aves criadas en planteles avícolas (pollitos, pollitas, pollos, pollas + gallinas ), El dato de aves de corral que reporta el INEC a través de la ESPAC corresponde a un solo ciclo de producción en el año, se toma el dato de CONAVE como real. | G64: .
B65: Aves de engorde | C65: FE para Fermentación Entérica | D65: NA | G65: .
B66: Patos | C66: Datos de Actividad | D66: CONAVE | E66: Corresponde al dato de número de cabezas de patos criados en campo | G66: .
B67: Patos | C67: FE para Fermentación Entérica | D67: NA | G67: .
B68: Pavos | C68: Datos de Actividad | D68: ESPAC 2018 (datos ajustados y suavizados), tablas 59-60, CONAVE, MAG, Ajuste de suavizamiento realizado a la categoria debido a su importancia en Gestión de estiercol. La tasa de crecimiento es producto de la comparación con el crecimiento promedio de los últimos 6 años del censo del MAG a 2015, y de la variable macroeconómica del PIB x actividad (producción de carne incluido pollos) del Banco Central del Ecuador además de la variable crianza de aves del registro del SRI para 2018 y 2018. Los saltos bruscos de crecimiento se deben a ajustes metodológicos realizador por la fuente. | E68: Corresponde a la suma de aves criadas en campo (pavos) + aves criadas en planteles avícolas (pavos) | G68: .
B69: Pavos | C69: FE para Fermentación Entérica | D69: NA | G69: .
B70: Ponedoras | C70: Datos de Actividad | D70: Datos de CONAVE, bajo la consideración de ciclos productivos o dias vivo del animal (45) | E70: Corresponde al dato de número de cabezas de ponedoras en planteles avícolas | G70: .
B71: Ponedoras | C71: FE para Fermentación Entérica | D71: NA | G71: .

Sheet 3B Manejo de Estiércol CH4
B2: EMISIONES POR FERMENTACIÓN ENTÉRICA Y GESTIÓN DE ESTIÉRCOL
U3: INDICE
B4: Sector | C4: Agricultura
B5: Categoria | C5: Emisiones de Metano por Gestión de Estiércol
B6: Código de Categoría | C6: 3A2
B7: Hoja | C7: 1 de 1
B8: Ecuación | E8: Ecuación 10.22A | H8: Ecuación 10.22
B9: Categoria de Ganado | D9: Número de Animales | E9: Excresión anual por cabeza VS ratio | F9: Masa tipica del animal por categoría | G9: Excresión anual por cabeza VS | H9: Fracción del total anual de manejo de estiercol por tipo de sistema y tipo de ganado; ANIMAL WASTE MANAGEMENT SYSTEM (AWMS) | N9: Factor de Emisión de Metano por tipo de sistema de manejo y tipo de ganado (FE) | T9: CH4 Emisiones por Gestión del Estiércol
D10: (cabezas) | E10: (kg cabeza-1 año-1) (KG VS (1000 KG ANIMAL MASS) -1 DAY -1 ) | F10: Kg | G10: (kg cabeza-1 año-1) | H10: Sistema manejo estiércol: Almacenaje de sólidos | I10: Sistema manejo estiércol: Compostaje | J10: Sistema manejo estiércol: Distribución diaria en pasturas | K10: Sistema manejo estiércol: Líquido/fango | L10: Otros Sistemas de Manejo | M10: Sistema manejo estiércol: Pasturas, sin manejo | N10: Sistema manejo estiércol: Almacenaje de sólidos | O10: Sistema manejo estiércol: Compostaje | P10: Sistema manejo estiércol: Distribución diaria en pasturas | Q10: Sistema manejo estiércol: Líquido/fango | R10: Otros | S10: Sistema manejo estiércol: Pasturas, sin manejo | T10: (Kg CH4 año-1)
E11: Tabla 10.13 | F11: Tabla 10A.5 | H11: Tablas 10A.6 a 10A.9 | N11: Tabla 10.14 - 10.15 | T11: CH4 Estiércol = (N(T) *Vs*AWMS* EF(T))/(10^3)
B12: T | D12: N (T) | E12: VS(T,p) ratio | F12: TAM(T,p) | G12: VS(T,p) | H12: % | I12: % | J12: % | K12: % | L12: % | M12: % | N12: EF(T) | O12: EF(T) | P12: EF(T) | Q12: EF(T) | R12: EF(T) | S12: EF(T) | T12: CH4 Manure
B13: Ganado Lechero | C13: Sierra | D13: ='3A1 Fermentación E.'!D13 -> 522643.97 | E13: 7.9 | F13: 419.01067 | G13: =(E13*(F13/1000))*365 -> 1208.2173 | H13: 0.63456633 | I13: 7.8409864 | J13: 12.651786 | K13: 0.025510204 | L13: 4.4451531 | M13: 74.401998 | N13: 1.7 | O13: 1.7 | P13: 0.1 | Q13: 22.6 | R13: 0.9 | S13: 0.6 | T13: =((D13*G13*H13%*N13)/(10^3))+((D13*G13*I13%*O13)/(10^3))+((D13*G13*J13%*P13)/(10^3))+((D13*G13*K13%*Q13)/(10^3))+((D13*G13*L13%*R13)/(10^3))+((D13*G13*M13%*S13)/(10^3)) -> 409771.78
C14: Costa | D14: ='3A1 Fermentación E.'!D14 -> 262262.61 | E14: 7.1 | F14: 605.43489 | G14: =(E14*(F14/1000))*365 -> 1568.9845 | H14: 0.032467532 | I14: 0.038961039 | J14: 6.2077922 | K14: 0.64935065 | L14: 0.3125 | M14: 92.758929 | N14: 4.4 | O14: 4.4 | P14: 0.9 | Q14: 63.6 | R14: 1.7 | S14: 0.6 | T14: =((D14*G14*H14%*N14)/(10^3))+((D14*G14*I14%*O14)/(10^3))+((D14*G14*J14%*P14)/(10^3))+((D14*G14*K14%*Q14)/(10^3))+((D14*G14*L14%*R14)/(10^3))+((D14*G14*M14%*S14)/(10^3)) -> 425421.38
C15: Amazonia | D15: ='3A1 Fermentación E.'!D15 -> 47621.019 | E15: 8.6 | F15: 425.22942 | G15: =(E15*(F15/1000))*365 -> 1334.7951 | H15: 0.096153846 | I15: 0.038461538 | J15: 0 | K15: 0 | L15: 0 | M15: 99.865385 | N15: 4.4 | O15: 4.4 | P15: 0.9 | Q15: 66.2 | R15: 1.7 | S15: 0.6 | T15: =((D15*G15*H15%*N15)/(10^3))+((D15*G15*I15%*O15)/(10^3))+((D15*G15*J15%*P15)/(10^3))+((D15*G15*K15%*Q15)/(10^3))+((D15*G15*L15%*R15)/(10^3))+((D15*G15*M15%*S15)/(10^3)) -> 38463.739
B16: No LecheroToros | C16: Sierra | D16: ='3A1 Fermentación E.'!D16 -> 153765.65 | E16: 7.9 | F16: 513.2818 | G16: =(E16*(F16/1000))*365 -> 1480.0481 | H16: 0 | I16: 4.8148148 | J16: 0.12222222 | K16: 0 | L16: 0 | M16: 95.062963 | N16: 1.7 | O16: 1.7 | P16: 0.1 | Q16: 22.6 | R16: 0.9 | S16: 0.6 | T16: =((D16*G16*H16%*N16)/(10^3))+((D16*G16*I16%*O16)/(10^3))+((D16*G16*J16%*P16)/(10^3))+((D16*G16*K16%*Q16)/(10^3))+((D16*G16*L16%*R16)/(10^3))+((D16*G16*M16%*S16)/(10^3)) -> 148462.6
C17: Costa | D17: ='3A1 Fermentación E.'!D17 -> 73566.158 | E17: 7.1 | F17: 535.61652 | G17: =(E17*(F17/1000))*365 -> 1388.0502 | H17: 0 | I17: 0.035714286 | J17: 0.57142857 | K17: 8.3333333 | L17: 0 | M17: 91.059524 | N17: 4.4 | O17: 4.4 | P17: 0.9 | Q17: 66.2 | R17: 1.7 | S17: 0.6 | T17: =((D17*G17*H17%*N17)/(10^3))+((D17*G17*I17%*O17)/(10^3))+((D17*G17*J17%*P17)/(10^3))+((D17*G17*K17%*Q17)/(10^3))+((D17*G17*L17%*R17)/(10^3))+((D17*G17*M17%*S17)/(10^3)) -> 619802.33
C18: Amazonia | D18: ='3A1 Fermentación E.'!D18 -> 28493.155 | E18: 8.6 | F18: 460.03682 | G18: =(E18*(F18/1000))*365 -> 1444.0556 | H18: 0 | I18: 0 | J18: 2.173913 | K18: 0 | L18: 0 | M18: 97.826087 | N18: 4.4 | O18: 4.4 | P18: 0.9 | Q18: 66.2 | R18: 1.7 | S18: 0.6 | T18: =((D18*G18*H18%*N18)/(10^3))+((D18*G18*I18%*O18)/(10^3))+((D18*G18*J18%*P18)/(10^3))+((D18*G18*K18%*Q18)/(10^3))+((D18*G18*L18%*R18)/(10^3))+((D18*G18*M18%*S18)/(10^3)) -> 24955.761
B19: No Lechero Vacas | C19: Sierra | D19: ='3A1 Fermentación E.'!D19 -> 250720.67 | E19: 7.9 | F19: 375.7196 | G19: =(E19*(F19/1000))*365 -> 1083.3875 | H19: 0 | I19: 4.8148148 | J19: 0.12222222 | K19: 0 | L19: 0 | M19: 95.062963 | N19: 1.7 | O19: 1.7 | P19: 0.1 | Q19: 22.6 | R19: 0.9 | S19: 0.6 | T19: =((D19*G19*H19%*N19)/(10^3))+((D19*G19*I19%*O19)/(10^3))+((D19*G19*J19%*P19)/(10^3))+((D19*G19*K19%*Q19)/(10^3))+((D19*G19*L19%*R19)/(10^3))+((D19*G19*M19%*S19)/(10^3)) -> 177196.79
C20: Costa | D20: ='3A1 Fermentación E.'!D20 -> 401964.14 | E20: 7.1 | F20: 430.60864 | G20: =(E20*(F20/1000))*365 -> 1115.9223 | H20: 0 | I20: 0.035714286 | J20: 0.57142857 | K20: 8.3333333 | L20: 0 | M20: 91.059524 | N20: 4.4 | O20: 4.4 | P20: 0.9 | Q20: 66.2 | R20: 1.7 | S20: 0.6 | T20: =((D20*G20*H20%*N20)/(10^3))+((D20*G20*I20%*O20)/(10^3))+((D20*G20*J20%*P20)/(10^3))+((D20*G20*K20%*Q20)/(10^3))+((D20*G20*L20%*R20)/(10^3))+((D20*G20*M20%*S20)/(10^3)) -> 2722646.2
C21: Amazonia | D21: ='3A1 Fermentación E.'!D21 -> 74474.301 | E21: 8.6 | F21: 427.92286 | G21: =(E21*(F21/1000))*365 -> 1343.2499 | H21: 0 | I21: 0 | J21: 2.173913 | K21: 0 | L21: 0 | M21: 97.826087 | N21: 4.4 | O21: 4.4 | P21: 0.9 | Q21: 66.2 | R21: 1.7 | S21: 0.6 | T21: =((D21*G21*H21%*N21)/(10^3))+((D21*G21*I21%*O21)/(10^3))+((D21*G21*J21%*P21)/(10^3))+((D21*G21*K21%*Q21)/(10^3))+((D21*G21*L21%*R21)/(10^3))+((D21*G21*M21%*S21)/(10^3)) -> 60674.975
B22: No Lechero En crecimiento | C22: Sierra | D22: ='3A1 Fermentación E.'!D22 -> 1036600.5 | E22: 7.9 | F22: 165.49943 | G22: =(E22*(F22/1000))*365 -> 477.21761 | H22: 0 | I22: 4.8148148 | J22: 0.12222222 | K22: 0 | L22: 0 | M22: 95.062963 | N22: 1.7 | O22: 1.7 | P22: 0.1 | Q22: 22.6 | R22: 0.9 | S22: 0.6 | T22: =((D22*G22*H22%*N22)/(10^3))+((D22*G22*I22%*O22)/(10^3))+((D22*G22*J22%*P22)/(10^3))+((D22*G22*K22%*Q22)/(10^3))+((D22*G22*L22%*R22)/(10^3))+((D22*G22*M22%*S22)/(10^3)) -> 322708.02
C23: Costa | D23: ='3A1 Fermentación E.'!D23 -> 984149.28 | E23: 7.1 | F23: 174.42759 | G23: =(E23*(F23/1000))*365 -> 452.0291 | H23: 0 | I23: 0.035714286 | J23: 0.57142857 | K23: 8.3333333 | L23: 0 | M23: 91.059524 | N23: 4.4 | O23: 4.4 | P23: 0.9 | Q23: 66.2 | R23: 1.7 | S23: 0.6 | T23: =((D23*G23*H23%*N23)/(10^3))+((D23*G23*I23%*O23)/(10^3))+((D23*G23*J23%*P23)/(10^3))+((D23*G23*K23%*Q23)/(10^3))+((D23*G23*L23%*R23)/(10^3))+((D23*G23*M23%*S23)/(10^3)) -> 2700208.6
C24: Amazonia | D24: ='3A1 Fermentación E.'!D24 -> 220534.27 | E24: 8.6 | F24: 174.58749 | G24: =(E24*(F24/1000))*365 -> 548.03012 | H24: 0 | I24: 0 | J24: 2.173913 | K24: 0 | L24: 0 | M24: 97.826087 | N24: 4.4 | O24: 4.4 | P24: 0.9 | Q24: 66.2 | R24: 1.7 | S24: 0.6 | T24: =((D24*G24*H24%*N24)/(10^3))+((D24*G24*I24%*O24)/(10^3))+((D24*G24*J24%*P24)/(10^3))+((D24*G24*K24%*Q24)/(10^3))+((D24*G24*L24%*R24)/(10^3))+((D24*G24*M24%*S24)/(10^3)) -> 73303.868
B25: Búfalos | D25: ='3A1 Fermentación E.'!D25 -> 3839 | E25: 11.2 | F25: 315 | G25: =(E25*(F25/1000))*365 -> 1287.72 | H25: 2 | I25: 0 | J25: 0 | K25: 0 | L25: 5 | M25: 93 | N25: 4.4 | O25: 4.4 | P25: 0.9 | Q25: 66.2 | R25: 1.7 | S25: 0.6 | T25: =((D25*G25*H25%*N25)/(10^3))+((D25*G25*I25%*O25)/(10^3))+((D25*G25*J25%*P25)/(10^3))+((D25*G25*K25%*Q25)/(10^3))+((D25*G25*L25%*R25)/(10^3))+((D25*G25*M25%*S25)/(10^3)) -> 3613.7402
B26: Ovejas | D26: ='3A1 Fermentación E.'!D26 -> 498952.01 | E26: 8.3 | F26: 31 | G26: =(E26*(F26/1000))*365 -> 93.9145 | H26: 17 | I26: 3 | J26: 0 | K26: 0 | L26: 0 | M26: 80 | N26: 1.7 | O26: 1.7 | P26: 1.7 | Q26: 1.7 | R26: 0.9 | S26: 0.6 | T26: =((D26*G26*H26%*N26)/(10^3))+((D26*G26*I26%*O26)/(10^3))+((D26*G26*J26%*P26)/(10^3))+((D26*G26*K26%*Q26)/(10^3))+((D26*G26*L26%*R26)/(10^3))+((D26*G26*M26%*S26)/(10^3)) -> 38424.24
B27: Cabras | D27: ='3A1 Fermentación E.'!D27 -> 21745.307 | E27: 10.4 | F27: 24 | G27: =(E27*(F27/1000))*365 -> 91.104 | H27: 17 | I27: 3 | J27: 0 | K27: 0 | L27: 0 | M27: 80 | N27: 1.7 | O27: 1.7 | P27: 1.7 | Q27: 1.7 | R27: 0.9 | S27: 0.6 | T27: =((D27*G27*H27%*N27)/(10^3))+((D27*G27*I27%*O27)/(10^3))+((D27*G27*J27%*P27)/(10^3))+((D27*G27*K27%*Q27)/(10^3))+((D27*G27*L27%*R27)/(10^3))+((D27*G27*M27%*S27)/(10^3)) -> 1624.4892
B28: Camélidos sudamericanos | D28: ='3A1 Fermentación E.'!D28 -> 20949.783 | E28: 8.3 | F28: 65 | G28: =(E28*(F28/1000))*365 -> 196.9175 | H28: 17 | I28: 3 | J28: 0 | K28: 0 | L28: 0 | M28: 80 | N28: 1.7 | O28: 1.7 | P28: 1.7 | Q28: 1.7 | R28: 0.9 | S28: 0.6 | T28: =((D28*G28*H28%*N28)/(10^3))+((D28*G28*I28%*O28)/(10^3))+((D28*G28*J28%*P28)/(10^3))+((D28*G28*K28%*Q28)/(10^3))+((D28*G28*L28%*R28)/(10^3))+((D28*G28*M28%*S28)/(10^3)) -> 3382.8107
B29: Caballos | D29: ='3A1 Fermentación E.'!D29 -> 260479.02 | E29: 7.2 | F29: 238 | G29: =(E29*(F29/1000))*365 -> 625.464 | H29: 17 | I29: 3 | J29: 0 | K29: 0 | L29: 0 | M29: 80 | N29: 7 | O29: 7 | P29: 7 | Q29: 7 | R29: 2.6 | S29: 0.6 | T29: =((D29*G29*H29%*N29)/(10^3))+((D29*G29*I29%*O29)/(10^3))+((D29*G29*J29%*P29)/(10^3))+((D29*G29*K29%*Q29)/(10^3))+((D29*G29*L29%*R29)/(10^3))+((D29*G29*M29%*S29)/(10^3)) -> 306290.07
B30: Mulas & Asnos | D30: ='3A1 Fermentación E.'!D30 -> 147168.66 | E30: 7.2 | F30: 130 | G30: =(E30*(F30/1000))*365 -> 341.64 | H30: 17 | I30: 3 | J30: 0 | K30: 0 | L30: 0 | M30: 80 | N30: 7 | O30: 7 | P30: 7 | Q30: 7 | R30: 2.6 | S30: 0.6 | T30: =((D30*G30*H30%*N30)/(10^3))+((D30*G30*I30%*O30)/(10^3))+((D30*G30*J30%*P30)/(10^3))+((D30*G30*K30%*Q30)/(10^3))+((D30*G30*L30%*R30)/(10^3))+((D30*G30*M30%*S30)/(10^3)) -> 94523.961
B31: Cerdos | D31: ='3A1 Fermentación E.'!D31 -> 1682662 | E31: 8.3 | F31: 59 | G31: =(E31*(F31/1000))*365 -> 178.7405 | H31: 15 | I31: 5 | J31: 5 | K31: 30 | L31: 40 | M31: 5 | N31: 7.8 | O31: 7.8 | P31: 1 | Q31: 71.9 | R31: 1 | S31: 0.6 | T31: =((D31*G31*H31%*N31)/(10^3))+((D31*G31*I31%*O31)/(10^3))+((D31*G31*J31%*P31)/(10^3))+((D31*G31*K31%*Q31)/(10^3))+((D31*G31*L31%*R31)/(10^3))+((D31*G31*M31%*S31)/(10^3)) -> 7100940.2
B32: Aves de engorde | D32: ='3A1 Fermentación E.'!D32 -> 30205479 | E32: 15.6 | F32: 0.9 | G32: =(E32*(F32/1000))*365 -> 5.1246 | H32: 0 | I32: 0 | J32: 0 | K32: 0 | L32: 100 | M32: 0 | N32: 2.4 | O32: 2.4 | P32: 2.4 | Q32: 2.4 | R32: 2.4 | S32: 0.6 | T32: =((D32*G32*H32%*N32)/(10^3))+((D32*G32*I32%*O32)/(10^3))+((D32*G32*J32%*P32)/(10^3))+((D32*G32*K32%*Q32)/(10^3))+((D32*G32*L32%*R32)/(10^3))+((D32*G32*M32%*S32)/(10^3)) -> 371498.4
B33: Ponedoras | D33: ='3A1 Fermentación E.'!D33 -> 13510000 | E33: 10.1 | F33: 1.4 | G33: =(E33*(F33/1000))*365 -> 5.1611 | H33: 42 | I33: 0 | J33: 0 | K33: 58 | L33: 0 | M33: 0 | N33: 2.4 | O33: 2.4 | P33: 2.4 | Q33: 2.4 | R33: 2.4 | S33: 0.6 | T33: =((D33*G33*H33%*N33)/(10^3))+((D33*G33*I33%*O33)/(10^3))+((D33*G33*J33%*P33)/(10^3))+((D33*G33*K33%*Q33)/(10^3))+((D33*G33*L33%*R33)/(10^3))+((D33*G33*M33%*S33)/(10^3)) -> 167343.51
B34: Patos | D34: ='3A1 Fermentación E.'!D34 -> 70291.656 | E34: 7.4 | F34: 2.7 | G34: =(E34*(F34/1000))*365 -> 7.2927 | H34: 0 | I34: 0 | J34: 0 | K34: 0 | L34: 100 | M34: 0 | N34: 2.4 | O34: 2.4 | P34: 2.4 | Q34: 2.4 | R34: 2.4 | S34: 0.6 | T34: =((D34*G34*H34%*N34)/(10^3))+((D34*G34*I34%*O34)/(10^3))+((D34*G34*J34%*P34)/(10^3))+((D34*G34*K34%*Q34)/(10^3))+((D34*G34*L34%*R34)/(10^3))+((D34*G34*M34%*S34)/(10^3)) -> 1230.2783
B35: Pavos | D35: ='3A1 Fermentación E.'!D35 -> 198716.81 | E35: 10.3 | F35: 6.8 | G35: =(E35*(F35/1000))*365 -> 25.5646 | H35: 0 | I35: 0 | J35: 0 | K35: 0 | L35: 100 | M35: 0 | N35: 2.4 | O35: 2.4 | P35: 2.4 | Q35: 2.4 | R35: 2.4 | S35: 0.6 | T35: =((D35*G35*H35%*N35)/(10^3))+((D35*G35*I35%*O35)/(10^3))+((D35*G35*J35%*P35)/(10^3))+((D35*G35*K35%*Q35)/(10^3))+((D35*G35*L35%*R35)/(10^3))+((D35*G35*M35%*S35)/(10^3)) -> 12192.278
B36: Total | T36: =SUM(T13:T35) -> 15824680
B39: NOTA EXPLICATIVA DE FUENTES Y OTRAS CONSIDERACIONES DE LOS DATOS
B40: TIPO DE GANADO | D40: DATO DE ACTIVIDAD | E40: Observaciones | F40: VS ratio | G40: TAM | H40: Fracción AWMS | I40: FACTOR DE EMISIÓN
B41: Ganado Lechero | D41: ESPAC 2018 , tabla 67 | E41: Dato de actividad desagregado por región, dato de existencias población adulta de mas de dos años | F41: Se obtiene por defecto de la tabla 10.13 directrices IPCC V4, para ganado de la sierra se considera productividad media, en tanto para las otras regiones se considera productividad baja | G41: Dato propio del país según registros de proyecto GCI por región | H41: Valor propio del país según registros proyecto GCI por región, se promedian modos de producción | I41: Factor de emisión por defecto tablas 10.14 y 10.15 directrices IPCC V4, en algunos casos se asemejan factores según similitud de sistemas de manejo y tipo de clima por región | J41: .
B42: No LecheroToros | D42: ESPAC 2018, tabla 50 | E42: Corresponde al número de toros de 2 o más años de edad | F42: Se obtiene por defecto de la tabla 10.13 directrices IPCC V4, para ganado de la sierra se considera productividad media, en tanto para las otras regiones se considera productividad baja | G42: Dato propio del país según registros de proyecto GCI por región | H42: Valor propio del país según registros proyecto GCI por región, se promedian modos de producción | I42: Factor de emisión por defecto tablas 10.14 y 10.15 directrices IPCC V4, en algunos casos se asemejan factores según similitud de sistemas de manejo y tipo de clima por región | J42: .
B43: No Lechero Vacas | D43: ESPAC 2018, tabla 50 | E43: Corresponde al número de vacas de 2 o más años de edad menos el número de vacas ordeñadas | F43: Se obtiene por defecto de la tabla 10.13 directrices IPCC V4, para ganado de la sierra se considera productividad media, en tanto para las otras regiones se considera productividad baja | G43: Dato propio del país según registros de proyecto GCI por región | H43: Valor propio del país según registros proyecto GCI por región, se promedian modos de producción | I43: Factor de emisión por defecto tablas 10.14 y 10.15 directrices IPCC V4, en algunos casos se asemejan factores según similitud de sistemas de manejo y tipo de clima por región | J43: .
B44: No Lechero En crecimiento | D44: ESPAC 2018, tabla 50 | E44: Corresponde a la suma de terneros, toretes, terneras y vaconas, se confirma que el dato puede ser usado como dato final (dias vivo) considerando que el formulario del INEC pregunta por las existencias al momento de la encuesta, y no existe estadistica nacional para discretizar aquella población que vive menos de un año. | F44: Se obtiene por defecto de la tabla 10.13 directrices IPCC V4, para ganado de la sierra se considera productividad media, en tanto para las otras regiones se considera productividad baja | G44: Dato propio del país según registros de proyecto GCI por región, suma grupos de bovinos menores a 2 años machos y hembras | H44: Valor propio del país según registros proyecto GCI por región, se promedian modos de producción | I44: Factor de emisión por defecto tablas 10.14 y 10.15 directrices IPCC V4, en algunos casos se asemejan factores según similitud de sistemas de manejo y tipo de clima por región | J44: .
B45: Búfalos | D45: Datos Agrocalidad, registro vacunación por fiebre aftosa. | F45: Se obtiene por defecto de la tabla 10.13 directrices IPCC V4, para todas las regiones se considera productividad baja (relacionando pesos vivo) | G45: Valor por defecto directrices IPCC tabla 10A.5 | H45: Valor por defecto Tablas 10A.6 a 10A.9 directrices IPCC V4, Otros al no ser relevante suma los demás sistemas no considerados individualmente | I45: Factor de emisión por defecto tablas 10.14 y 10.15 directrices IPCC V4, en algunos casos se asemejan factores según similitud de sistemas de manejo y tipo de clima por región | J45: .
B46: Ovejas | D46: ESPAC 2018 , tabla 60 | E46: se confirma que el dato puede ser usado como dato final (dias vivo) considerando que el formulario del INEC pregunta por las existencias al momento de la encuesta, y no existe estadistica nacional para discretizar aquella población que vive menos de un año. | F46: Se obtiene por defecto de la tabla 10.13 directrices IPCC V4, para todas las regiones se considera productividad baja (relacionando pesos vivo) | G46: Valor por defecto directrices IPCC tabla 10A.6 | H46: Valor por defecto Tablas 10A.6 a 10A.9 directrices IPCC V4, Otros al no ser relevante suma los demás sistemas no considerados individualmente | I46: Factor de emisión por defecto tablas 10.14 y 10.15 directrices IPCC V4, en algunos casos se asemejan factores según similitud de sistemas de manejo y tipo de clima por región | J46: .
B47: Cabras | D47: ESPAC 2018 , tabla 61 | E47: se confirma que el dato puede ser usado como dato final (dias vivo) considerando que el formulario del INEC pregunta por las existencias al momento de la encuesta, y no existe estadistica nacional para discretizar aquella población que vive menos de un año. | F47: Se obtiene por defecto de la tabla 10.13 directrices IPCC V4, para todas las regiones se considera productividad baja (relacionando pesos vivo) | G47: Valor por defecto directrices IPCC tabla 10A.7 | H47: Valor por defecto Tablas 10A.6 a 10A.9 directrices IPCC V4, Otros al no ser relevante suma los demás sistemas no considerados individualmente | I47: Factor de emisión por defecto tablas 10.14 y 10.15 directrices IPCC V4, en algunos casos se asemejan factores según similitud de sistemas de manejo y tipo de clima por región | J47: .
B48: Camélidos sudamericanos | D48: Ministerio de Agricultura, Agrocalidad, Regional Chimborazo | E48: Se confirman estadisticas similares y poblaciones estacionales para la categoría, las tasas de crecimiento se proyectan desde los datos de 2016 y 2018 para los siguientes años | F48: Se obtiene por defecto de la tabla 10.13 directrices IPCC V4, para todas las regiones se considera productividad baja (relacionando pesos vivo) | G48: Valor por defecto directrices IPCC tabla 10A.8 | H48: Valor por defecto Tablas 10A.6 a 10A.9 directrices IPCC V4, Otros al no ser relevante suma los demás sistemas no considerados individualmente | I48: Factor de emisión por defecto tablas 10.14 y 10.15 directrices IPCC V4, en algunos casos se asemejan factores según similitud de sistemas de manejo y tipo de clima por región | J48: .
B49: Caballos | D49: ESPAC 2018 , tabla 61 | E49: se confirma que el dato puede ser usado como dato final (dias vivo) considerando que el formulario del INEC pregunta por las existencias al momento de la encuesta, y no existe estadistica nacional para discretizar aquella población que vive menos de un año. | F49: Se obtiene por defecto de la tabla 10.13 directrices IPCC V4, para todas las regiones se considera productividad baja (relacionando pesos vivo) | G49: Valor por defecto directrices IPCC tabla 10A.9 | H49: Valor por defecto Tablas 10A.6 a 10A.9 directrices IPCC V4, Otros al no ser relevante suma los demás sistemas no considerados individualmente | I49: Factor de emisión por defecto tablas 10.14 y 10.15 directrices IPCC V4, en algunos casos se asemejan factores según similitud de sistemas de manejo y tipo de clima por región | J49: .
B50: Mulas & Asnos | D50: ESPAC 2018 , tabla 61 | E50: se confirma que el dato puede ser usado como dato final (dias vivo) considerando que el formulario del INEC pregunta por las existencias al momento de la encuesta, y no existe estadistica nacional para discretizar aquella población que vive menos de un año. | F50: Se obtiene por defecto de la tabla 10.13 directrices IPCC V4, para todas las regiones se considera productividad baja (relacionando pesos vivo) | G50: Valor por defecto directrices IPCC tabla 10A.10 | H50: Valor por defecto Tablas 10A.6 a 10A.9 directrices IPCC V4, Otros al no ser relevante suma los demás sistemas no considerados individualmente | I50: Factor de emisión por defecto tablas 10.14 y 10.15 directrices IPCC V4, en algunos casos se asemejan factores según similitud de sistemas de manejo y tipo de clima por región | J50: .
B51: Cerdos | D51: ESPAC 2018 , tabla 57 | E51: Se usa el dato de existencias, para afinar la estadistica de "dias vivo", el periodo de dias vivo se consideran 27 semanas | F51: Se obtiene por defecto de la tabla 10.13 directrices IPCC V4, para todas las regiones se considera productividad baja (relacionando pesos vivo) | G51: Valor por defecto directrices IPCC tabla 10A.11 | H51: Valor por defecto Tablas 10A.6 a 10A.9 directrices IPCC V4, Otros al no ser relevante suma los demás sistemas no considerados individualmente | I51: Factor de emisión por defecto tablas 10.14 y 10.15 directrices IPCC V4, en algunos casos se asemejan factores según similitud de sistemas de manejo y tipo de clima por región | J51: .
B52: Aves de engorde | D52: Datos de CONAVE considerando los dias vivo del animal al año | E52: Corresponde a la suma de aves criadas en campo (pollitos, pollitas, pollos, pollas + gallos, gallinas) + aves criadas en planteles avícolas (pollitos, pollitas, pollos, pollas + gallinas ), El dato de aves de corral que reporta el INEC a través de la ESPAC corresponde a un solo ciclo de producción en el año, se toma el dato de CONAVE como real. | F52: Se obtiene por defecto de la tabla 10.13 directrices IPCC V4, para todas las regiones se considera productividad media (relacionando sistemas de producción referenciados en las directrices IPCC) | G52: Valor por defecto directrices IPCC tabla 10A.12 | H52: Valor por defecto Tablas 10A.6 a 10A.9 directrices IPCC V4, Otros al no ser relevante suma los demás sistemas no considerados individualmente | I52: Factor de emisión por defecto tablas 10.14 y 10.15 directrices IPCC V4, en algunos casos se asemejan factores según similitud de sistemas de manejo y tipo de clima por región | J52: .
B53: Ponedoras | D53: Datos de CONAVE considerando los dias vivo del animal al año | E53: Corresponde al dato de número de cabezas de patos criados en campo | F53: Se obtiene por defecto de la tabla 10.13 directrices IPCC V4, para todas las regiones se considera productividad media (relacionando sistemas de producción referenciados en las directrices IPCC) | G53: Valor por defecto directrices IPCC tabla 10A.13 | H53: Valor por defecto Tablas 10A.6 a 10A.9 directrices IPCC V4, Otros al no ser relevante suma los demás sistemas no considerados individualmente | I53: Factor de emisión por defecto tablas 10.14 y 10.15 directrices IPCC V4, en algunos casos se asemejan factores según similitud de sistemas de manejo y tipo de clima por región | J53: .
B54: Patos | D54: ESPAC 2018 , tabla 62,63 | E54: Corresponde a la suma de aves criadas en campo (pavos) + aves criadas en planteles avícolas (pavos) | F54: Se obtiene por defecto de la tabla 10.13 directrices IPCC V4, para todas las regiones se considera productividad baja (relacionando sistemas de producción referenciados en las directrices IPCC) | G54: Valor por defecto directrices IPCC tabla 10A.14 | H54: Valor por defecto Tablas 10A.6 a 10A.9 directrices IPCC V4, Otros al no ser relevante suma los demás sistemas no considerados individualmente | I54: Factor de emisión por defecto tablas 10.14 y 10.15 directrices IPCC V4, en algunos casos se asemejan factores según similitud de sistemas de manejo y tipo de clima por región | J54: .
B55: Pavos | D55: ESPAC 2018 , tabla 62,63 | E55: Corresponde al dato de número de cabezas de ponedoras en planteles avícolas | F55: Se obtiene por defecto de la tabla 10.13 directrices IPCC V4, para todas las regiones se considera productividad baja (relacionando sistemas de producción referenciados en las directrices IPCC) | G55: Valor por defecto directrices IPCC tabla 10A.15 | H55: Valor por defecto Tablas 10A.6 a 10A.9 directrices IPCC V4, Otros al no ser relevante suma los demás sistemas no considerados individualmente | I55: Factor de emisión por defecto tablas 10.14 y 10.15 directrices IPCC V4, en algunos casos se asemejan factores según similitud de sistemas de manejo y tipo de clima por región | J55: .

Sheet 3B Gestión Estiércol N2O Dir
B2: GESTIÓN DE ESTIÉRCOL : EMISIONES DIRECTAS DE N2O
B4: Sector | F4: Agricultura
B5: Categoría | F5: Gestión de Estiércol: Emisiones Directas de N2O del Gestión de Estiércol
B6: Código de Categoría | F6: 3A2
B7: Hoja | F7: 1 of 1 | W7: suelos agricolas
B8: Ecuación | E8: Eq. 10.25 | F8: Ecuación 10.30 | I8: Ecuación 10.25 | W8: Ecuación 11.15
B9: Sistema de Gestión de Estiércol (MMS)1 (se desagrega a continuación de manera horizontal) | E9: Número de animales | F9: Ratio de excreción de N (default) | G9: Masa tipica del animal por categoría | H9: Excreción anual de N por cabeza de especie / categoría ganadera3 | I9: Fracción del total anual de manejo de estiercol por tipo de sistema y tipo de ganado; ANIMAL WASTE MANAGEMENT SYSTEM (AWMS) | O9: Factor de emisión para emisiones directas de N2O-N por MMS | U9: Emisiones anuales directas de N2O | W9: N EN LA ORINA Y EL ESTIÉRICO DEPOSITADOS POR LOS ANIMALES QUE PASTAN | Z9: N excretado por sistema | AG9: emisiones por sistema
C10: Categoria de Ganado | E10: (Cabezas) | F10: [kg N | G10: (kg) | H10: (kg N animal-1 | I10: (-) | U10: kg N2O yr-1 | W10: kg N2O yr-1 | Z10: (-) | AG10: (-)
F11: (1000 kg animal)-1 día-1] | H11: año-1) | I11: ='3B Manejo de Estiércol CH4'!H10 -> Sistema manejo estiércol: Almacenaje de sólidos | J11: ='3B Manejo de Estiércol CH4'!I10 -> Sistema manejo estiércol: Compostaje | K11: ='3B Manejo de Estiércol CH4'!J10 -> Sistema manejo estiércol: Distribución diaria en pasturas | L11: ='3B Manejo de Estiércol CH4'!K10 -> Sistema manejo estiércol: Líquido/fango | M11: ='3B Manejo de Estiércol CH4'!L10 -> Otros Sistemas de Manejo | N11: ='3B Manejo de Estiércol CH4'!M10 -> Sistema manejo estiércol: Pasturas, sin manejo | O11: =I11 -> Sistema manejo estiércol: Almacenaje de sólidos | P11: =J11 -> Sistema manejo estiércol: Compostaje | Q11: =K11 -> Sistema manejo estiércol: Distribución diaria en pasturas | R11: =L11 -> Sistema manejo estiércol: Líquido/fango | S11: =M11 -> Otros Sistemas de Manejo | T11: =N11 -> Sistema manejo estiércol: Pasturas, sin manejo | U11: Emisiones anuales directas de N2O por Gestión de estiércol | W11: Cantidad anual de N en orina y estiércol depositado en pastos, pastizales y potreros por pastoreo. animales, kg N año | Z11: Sistema manejo estiércol: Almacenaje de sólidos | AA11: Sistema manejo estiércol: Compostaje | AB11: Sistema manejo estiércol: Distribución diaria en pasturas | AC11: Sistema manejo estiércol: Líquido/fango | AD11: Otros Sistemas de Manejo | AE11: Sistema manejo estiércol: Pasturas, sin manejo | AG11: Sistema manejo estiércol: Almacenaje de sólidos | AH11: Sistema manejo estiércol: Compostaje | AI11: Sistema manejo estiércol: Distribución diaria en pasturas | AJ11: Sistema manejo estiércol: Líquido/fango | AK11: Otros Sistemas de Manejo | AL11: Sistema manejo estiércol: Pasturas, sin manejo
F12: Tabla 10.19 | G12: Tablas 10A-4 to 10A-9 | H12: Nex(T) = Nrate(T) * TAM * 10-3 * 365 | I12: Tablas 10A.6 a 10A.9 | U12: N2O(mm) = | Z12: Tablas 10A.6 a 10A.9 | AG12: Tablas 10A.6 a 10A.9
O13: Tabla 10.21 | U13: NEMMS * EF3(S) * 44/28
B14: S | C14: T | E14: N(T) | F14: Nrate(T) | G14: TAM | H14: Nex(T) | I14: AWMS (%) | O14: EF3(S) | U14: N2OD(mm) | W14: Fprp | Z14: KG | AG14: KG
C15: Ganado Lechero | D15: Sierra | E15: ='3A1 Fermentación E.'!D13 -> 522643.97 | F15: 0.39 | G15: ='3B Manejo de Estiércol CH4'!F13 -> 419.01067 | H15: =F15*G15*(10^-3)*365 -> 59.646169 | I15: ='3B Manejo de Estiércol CH4'!H13 -> 0.63456633 | J15: ='3B Manejo de Estiércol CH4'!I13 -> 7.8409864 | K15: ='3B Manejo de Estiércol CH4'!J13 -> 12.651786 | L15: ='3B Manejo de Estiércol CH4'!K13 -> 0.025510204 | M15: ='3B Manejo de Estiércol CH4'!L13 -> 4.4451531 | N15: ='3B Manejo de Estiércol CH4'!M13 -> 74.401998 | O15: 0.01 | P15: 0.01 | Q15: 0 | R15: 0 | S15: 0.02 | T15: 0 | U15: =(E15*H15*J15%*P15*(44/28))+(E15*H15*I15%*O15*(44/28))+(E15*H15*K15%*Q15*(44/28))+(E15*H15*L15%*R15*(44/28))+(E15*H15*M15%*S15*(44/28))+(E15*H15*N15%*T15*(44/28)) -> 85070.583 | W15: =E15*H15*N15% -> 23193864 | Z15: =$E15*$H15*I15% -> 197817.87 | AA15: =$E15*$H15*J15% -> 2444326.4 | AB15: =$E15*$H15*K15% -> 3944031.1 | AC15: =$E15*$H15*L15% -> 7952.4772 | AD15: =$E15*$H15*M15% -> 1385719.2 | AE15: =$E15*$H15*N15% -> 23193864 | AG15: =$E15*$H15*I15%*O15*(44/28) -> 3108.5665 | AH15: =$E15*$H15*J15%*P15*(44/28) -> 38410.844 | AI15: =$E15*$H15*K15%*Q15*(44/28) -> 0 | AJ15: =$E15*$H15*L15%*R15*(44/28) -> 0 | AK15: =$E15*$H15*M15%*S15*(44/28) -> 43551.173 | AL15: =$E15*$H15*N15%*T15*(44/28) -> 0
D16: Costa | E16: ='3A1 Fermentación E.'!D14 -> 262262.61 | F16: 0.39 | G16: ='3B Manejo de Estiércol CH4'!F14 -> 605.43489 | H16: =F16*G16*(10^-3)*365 -> 86.183656 | I16: ='3B Manejo de Estiércol CH4'!H14 -> 0.032467532 | J16: ='3B Manejo de Estiércol CH4'!I14 -> 0.038961039 | K16: ='3B Manejo de Estiércol CH4'!J14 -> 6.2077922 | L16: ='3B Manejo de Estiércol CH4'!K14 -> 0.64935065 | M16: ='3B Manejo de Estiércol CH4'!L14 -> 0.3125 | N16: ='3B Manejo de Estiércol CH4'!M14 -> 92.758929 | O16: 0.01 | P16: 0.01 | Q16: 0 | R16: 0 | S16: 0.02 | T16: 0 | U16: =(E16*H16*J16%*P16*(44/28))+(E16*H16*I16%*O16*(44/28))+(E16*H16*K16%*Q16*(44/28))+(E16*H16*L16%*R16*(44/28))+(E16*H16*M16%*S16*(44/28))+(E16*H16*N16%*T16*(44/28)) -> 2473.6173 | W16: =E16*H16*N16% -> 20966069 | Z16: =$E16*$H16*I16% -> 7338.5553 | AA16: =$E16*$H16*J16% -> 8806.2664 | AB16: =$E16*$H16*K16% -> 1403131.8 | AC16: =$E16*$H16*L16% -> 146771.11 | AD16: =$E16*$H16*M16% -> 70633.595 | AE16: =$E16*$H16*N16% -> 20966069 | AG16: =$E16*$H16*I16%*O16*(44/28) -> 115.32016 | AH16: =$E16*$H16*J16%*P16*(44/28) -> 138.38419 | AI16: =$E16*$H16*K16%*Q16*(44/28) -> 0 | AJ16: =$E16*$H16*L16%*R16*(44/28) -> 0 | AK16: =$E16*$H16*M16%*S16*(44/28) -> 2219.913 | AL16: =$E16*$H16*N16%*T16*(44/28) -> 0
D17: Amazonia | E17: ='3A1 Fermentación E.'!D15 -> 47621.019 | F17: 0.39 | G17: ='3B Manejo de Estiércol CH4'!F15 -> 425.22942 | H17: =F17*G17*(10^-3)*365 -> 60.531408 | I17: ='3B Manejo de Estiércol CH4'!H15 -> 0.096153846 | J17: ='3B Manejo de Estiércol CH4'!I15 -> 0.038461538 | K17: ='3B Manejo de Estiércol CH4'!J15 -> 0 | L17: ='3B Manejo de Estiércol CH4'!K15 -> 0 | M17: ='3B Manejo de Estiércol CH4'!L15 -> 0 | N17: ='3B Manejo de Estiércol CH4'!M15 -> 99.865385 | O17: 0.01 | P17: 0.01 | Q17: 0 | R17: 0 | S17: 0.02 | T17: 0 | U17: =(E17*H17*J17%*P17*(44/28))+(E17*H17*I17%*O17*(44/28))+(E17*H17*K17%*Q17*(44/28))+(E17*H17*L17%*R17*(44/28))+(E17*H17*M17%*S17*(44/28))+(E17*H17*N17%*T17*(44/28)) -> 60.977385 | W17: =E17*H17*N17% -> 2878686.9 | Z17: =$E17*$H17*I17% -> 2771.6993 | AA17: =$E17*$H17*J17% -> 1108.6797 | AB17: =$E17*$H17*K17% -> 0 | AC17: =$E17*$H17*L17% -> 0 | AD17: =$E17*$H17*M17% -> 0 | AE17: =$E17*$H17*N17% -> 2878686.9 | AG17: =$E17*$H17*I17%*O17*(44/28) -> 43.555275 | AH17: =$E17*$H17*J17%*P17*(44/28) -> 17.42211 | AI17: =$E17*$H17*K17%*Q17*(44/28) -> 0 | AJ17: =$E17*$H17*L17%*R17*(44/28) -> 0 | AK17: =$E17*$H17*M17%*S17*(44/28) -> 0 | AL17: =$E17*$H17*N17%*T17*(44/28) -> 0
C18: No LecheroToros | D18: Sierra | E18: ='3A1 Fermentación E.'!D16 -> 153765.65 | F18: 0.29 | G18: ='3B Manejo de Estiércol CH4'!F16 -> 513.2818 | H18: =F18*G18*(10^-3)*365 -> 54.330878 | I18: ='3B Manejo de Estiércol CH4'!H16 -> 0 | J18: ='3B Manejo de Estiércol CH4'!I16 -> 4.8148148 | K18: ='3B Manejo de Estiércol CH4'!J16 -> 0.12222222 | L18: ='3B Manejo de Estiércol CH4'!K16 -> 0 | M18: ='3B Manejo de Estiércol CH4'!L16 -> 0 | N18: ='3B Manejo de Estiércol CH4'!M16 -> 95.062963 | O18: 0.01 | P18: 0.01 | Q18: 0 | R18: 0 | S18: 0.02 | T18: 0 | U18: =(E18*H18*J18%*P18*(44/28))+(E18*H18*I18%*O18*(44/28))+(E18*H18*K18%*Q18*(44/28))+(E18*H18*L18%*R18*(44/28))+(E18*H18*M18%*S18*(44/28))+(E18*H18*N18%*T18*(44/28)) -> 6320.9199 | W18: =E18*H18*N18% -> 7941771.8 | Z18: =$E18*$H18*I18% -> 0 | AA18: =$E18*$H18*J18% -> 402240.36 | AB18: =$E18*$H18*K18% -> 10210.717 | AC18: =$E18*$H18*L18% -> 0 | AD18: =$E18*$H18*M18% -> 0 | AE18: =$E18*$H18*N18% -> 7941771.8 | AG18: =$E18*$H18*I18%*O18*(44/28) -> 0 | AH18: =$E18*$H18*J18%*P18*(44/28) -> 6320.9199 | AI18: =$E18*$H18*K18%*Q18*(44/28) -> 0 | AJ18: =$E18*$H18*L18%*R18*(44/28) -> 0 | AK18: =$E18*$H18*M18%*S18*(44/28) -> 0 | AL18: =$E18*$H18*N18%*T18*(44/28) -> 0
D19: Costa | E19: ='3A1 Fermentación E.'!D17 -> 73566.158 | F19: 0.29 | G19: ='3B Manejo de Estiércol CH4'!F17 -> 535.61652 | H19: =F19*G19*(10^-3)*365 -> 56.695009 | I19: ='3B Manejo de Estiércol CH4'!H17 -> 0 | J19: ='3B Manejo de Estiércol CH4'!I17 -> 0.035714286 | K19: ='3B Manejo de Estiércol CH4'!J17 -> 0.57142857 | L19: ='3B Manejo de Estiércol CH4'!K17 -> 8.3333333 | M19: ='3B Manejo de Estiércol CH4'!L17 -> 0 | N19: ='3B Manejo de Estiércol CH4'!M17 -> 91.059524 | O19: 0.01 | P19: 0.01 | Q19: 0 | R19: 0 | S19: 0.02 | T19: 0 | U19: =(E19*H19*J19%*P19*(44/28))+(E19*H19*I19%*O19*(44/28))+(E19*H19*K19%*Q19*(44/28))+(E19*H19*L19%*R19*(44/28))+(E19*H19*M19%*S19*(44/28))+(E19*H19*N19%*T19*(44/28)) -> 23.407742 | W19: =E19*H19*N19% -> 3797941.6 | Z19: =$E19*$H19*I19% -> 0 | AA19: =$E19*$H19*J19% -> 1489.5836 | AB19: =$E19*$H19*K19% -> 23833.337 | AC19: =$E19*$H19*L19% -> 347569.5 | AD19: =$E19*$H19*M19% -> 0 | AE19: =$E19*$H19*N19% -> 3797941.6 | AG19: =$E19*$H19*I19%*O19*(44/28) -> 0 | AH19: =$E19*$H19*J19%*P19*(44/28) -> 23.407742 | AI19: =$E19*$H19*K19%*Q19*(44/28) -> 0 | AJ19: =$E19*$H19*L19%*R19*(44/28) -> 0 | AK19: =$E19*$H19*M19%*S19*(44/28) -> 0 | AL19: =$E19*$H19*N19%*T19*(44/28) -> 0
D20: Amazonia | E20: ='3A1 Fermentación E.'!D18 -> 28493.155 | F20: 0.29 | G20: ='3B Manejo de Estiércol CH4'!F18 -> 460.03682 | H20: =F20*G20*(10^-3)*365 -> 48.694897 | I20: ='3B Manejo de Estiércol CH4'!H18 -> 0 | J20: ='3B Manejo de Estiércol CH4'!I18 -> 0 | K20: ='3B Manejo de Estiércol CH4'!J18 -> 2.173913 | L20: ='3B Manejo de Estiércol CH4'!K18 -> 0 | M20: ='3B Manejo de Estiércol CH4'!L18 -> 0 | N20: ='3B Manejo de Estiércol CH4'!M18 -> 97.826087 | O20: 0.01 | P20: 0.01 | Q20: 0 | R20: 0 | S20: 0.02 | T20: 0 | U20: =(E20*H20*J20%*P20*(44/28))+(E20*H20*I20%*O20*(44/28))+(E20*H20*K20%*Q20*(44/28))+(E20*H20*L20%*R20*(44/28))+(E20*H20*M20%*S20*(44/28))+(E20*H20*N20%*T20*(44/28)) -> 0 | W20: =E20*H20*N20% -> 1357308.8 | Z20: =$E20*$H20*I20% -> 0 | AA20: =$E20*$H20*J20% -> 0 | AB20: =$E20*$H20*K20% -> 30162.419 | AC20: =$E20*$H20*L20% -> 0 | AD20: =$E20*$H20*M20% -> 0 | AE20: =$E20*$H20*N20% -> 1357308.8 | AG20: =$E20*$H20*I20%*O20*(44/28) -> 0 | AH20: =$E20*$H20*J20%*P20*(44/28) -> 0 | AI20: =$E20*$H20*K20%*Q20*(44/28) -> 0 | AJ20: =$E20*$H20*L20%*R20*(44/28) -> 0 | AK20: =$E20*$H20*M20%*S20*(44/28) -> 0 | AL20: =$E20*$H20*N20%*T20*(44/28) -> 0
C21: No Lechero Vacas | D21: Sierra | E21: ='3A1 Fermentación E.'!D19 -> 250720.67 | F21: 0.29 | G21: ='3B Manejo de Estiércol CH4'!F19 -> 375.7196 | H21: =F21*G21*(10^-3)*365 -> 39.769919 | I21: ='3B Manejo de Estiércol CH4'!H19 -> 0 | J21: ='3B Manejo de Estiércol CH4'!I19 -> 4.8148148 | K21: ='3B Manejo de Estiércol CH4'!J19 -> 0.12222222 | L21: ='3B Manejo de Estiércol CH4'!K19 -> 0 | M21: ='3B Manejo de Estiércol CH4'!L19 -> 0 | N21: ='3B Manejo de Estiércol CH4'!M19 -> 95.062963 | O21: 0.01 | P21: 0.01 | Q21: 0 | R21: 0 | S21: 0.02 | T21: 0 | U21: =(E21*H21*J21%*P21*(44/28))+(E21*H21*I21%*O21*(44/28))+(E21*H21*K21%*Q21*(44/28))+(E21*H21*L21%*R21*(44/28))+(E21*H21*M21%*S21*(44/28))+(E21*H21*N21%*T21*(44/28)) -> 7544.3023 | W21: =E21*H21*N21% -> 9478861.8 | Z21: =$E21*$H21*I21% -> 0 | AA21: =$E21*$H21*J21% -> 480091.96 | AB21: =$E21*$H21*K21% -> 12186.95 | AC21: =$E21*$H21*L21% -> 0 | AD21: =$E21*$H21*M21% -> 0 | AE21: =$E21*$H21*N21% -> 9478861.8 | AG21: =$E21*$H21*I21%*O21*(44/28) -> 0 | AH21: =$E21*$H21*J21%*P21*(44/28) -> 7544.3023 | AI21: =$E21*$H21*K21%*Q21*(44/28) -> 0 | AJ21: =$E21*$H21*L21%*R21*(44/28) -> 0 | AK21: =$E21*$H21*M21%*S21*(44/28) -> 0 | AL21: =$E21*$H21*N21%*T21*(44/28) -> 0
D22: Costa | E22: ='3A1 Fermentación E.'!D20 -> 401964.14 | F22: 0.29 | G22: ='3B Manejo de Estiércol CH4'!F20 -> 430.60864 | H22: =F22*G22*(10^-3)*365 -> 45.579924 | I22: ='3B Manejo de Estiércol CH4'!H20 -> 0 | J22: ='3B Manejo de Estiércol CH4'!I20 -> 0.035714286 | K22: ='3B Manejo de Estiércol CH4'!J20 -> 0.57142857 | L22: ='3B Manejo de Estiércol CH4'!K20 -> 8.3333333 | M22: ='3B Manejo de Estiércol CH4'!L20 -> 0 | N22: ='3B Manejo de Estiércol CH4'!M20 -> 91.059524 | O22: 0.01 | P22: 0.01 | Q22: 0 | R22: 0 | S22: 0.02 | T22: 0 | U22: =(E22*H22*J22%*P22*(44/28))+(E22*H22*I22%*O22*(44/28))+(E22*H22*K22%*Q22*(44/28))+(E22*H22*L22%*R22*(44/28))+(E22*H22*M22%*S22*(44/28))+(E22*H22*N22%*T22*(44/28)) -> 102.82472 | W22: =E22*H22*N22% -> 16683466 | Z22: =$E22*$H22*I22% -> 0 | AA22: =$E22*$H22*J22% -> 6543.3911 | AB22: =$E22*$H22*K22% -> 104694.26 | AC22: =$E22*$H22*L22% -> 1526791.3 | AD22: =$E22*$H22*M22% -> 0 | AE22: =$E22*$H22*N22% -> 16683466 | AG22: =$E22*$H22*I22%*O22*(44/28) -> 0 | AH22: =$E22*$H22*J22%*P22*(44/28) -> 102.82472 | AI22: =$E22*$H22*K22%*Q22*(44/28) -> 0 | AJ22: =$E22*$H22*L22%*R22*(44/28) -> 0 | AK22: =$E22*$H22*M22%*S22*(44/28) -> 0 | AL22: =$E22*$H22*N22%*T22*(44/28) -> 0
D23: Amazonia | E23: ='3A1 Fermentación E.'!D21 -> 74474.301 | F23: 0.29 | G23: ='3B Manejo de Estiércol CH4'!F21 -> 427.92286 | H23: =F23*G23*(10^-3)*365 -> 45.295635 | I23: ='3B Manejo de Estiércol CH4'!H21 -> 0 | J23: ='3B Manejo de Estiércol CH4'!I21 -> 0 | K23: ='3B Manejo de Estiércol CH4'!J21 -> 2.173913 | L23: ='3B Manejo de Estiércol CH4'!K21 -> 0 | M23: ='3B Manejo de Estiércol CH4'!L21 -> 0 | N23: ='3B Manejo de Estiércol CH4'!M21 -> 97.826087 | O23: 0.01 | P23: 0.01 | Q23: 0 | R23: 0 | S23: 0.02 | T23: 0 | U23: =(E23*H23*J23%*P23*(44/28))+(E23*H23*I23%*O23*(44/28))+(E23*H23*K23%*Q23*(44/28))+(E23*H23*L23%*R23*(44/28))+(E23*H23*M23%*S23*(44/28))+(E23*H23*N23%*T23*(44/28)) -> 0 | W23: =E23*H23*N23% -> 3300026.8 | Z23: =$E23*$H23*I23% -> 0 | AA23: =$E23*$H23*J23% -> 0 | AB23: =$E23*$H23*K23% -> 73333.929 | AC23: =$E23*$H23*L23% -> 0 | AD23: =$E23*$H23*M23% -> 0 | AE23: =$E23*$H23*N23% -> 3300026.8 | AG23: =$E23*$H23*I23%*O23*(44/28) -> 0 | AH23: =$E23*$H23*J23%*P23*(44/28) -> 0 | AI23: =$E23*$H23*K23%*Q23*(44/28) -> 0 | AJ23: =$E23*$H23*L23%*R23*(44/28) -> 0 | AK23: =$E23*$H23*M23%*S23*(44/28) -> 0 | AL23: =$E23*$H23*N23%*T23*(44/28) -> 0
C24: No Lechero En crecimiento | D24: Sierra | E24: ='3A1 Fermentación E.'!D22 -> 1036600.5 | F24: 0.29 | G24: ='3B Manejo de Estiércol CH4'!F22 -> 165.49943 | H24: =F24*G24*(10^-3)*365 -> 17.518115 | I24: ='3B Manejo de Estiércol CH4'!H22 -> 0 | J24: ='3B Manejo de Estiércol CH4'!I22 -> 4.8148148 | K24: ='3B Manejo de Estiércol CH4'!J22 -> 0.12222222 | L24: ='3B Manejo de Estiércol CH4'!K22 -> 0 | M24: ='3B Manejo de Estiércol CH4'!L22 -> 0 | N24: ='3B Manejo de Estiércol CH4'!M22 -> 95.062963 | O24: 0.01 | P24: 0.01 | Q24: 0 | R24: 0 | S24: 0.02 | T24: 0 | U24: =(E24*H24*J24%*P24*(44/28))+(E24*H24*I24%*O24*(44/28))+(E24*H24*K24%*Q24*(44/28))+(E24*H24*L24%*R24*(44/28))+(E24*H24*M24%*S24*(44/28))+(E24*H24*N24%*T24*(44/28)) -> 13739.566 | W24: =E24*H24*N24% -> 17262755 | Z24: =$E24*$H24*I24% -> 0 | AA24: =$E24*$H24*J24% -> 874335.99 | AB24: =$E24*$H24*K24% -> 22194.683 | AC24: =$E24*$H24*L24% -> 0 | AD24: =$E24*$H24*M24% -> 0 | AE24: =$E24*$H24*N24% -> 17262755 | AG24: =$E24*$H24*I24%*O24*(44/28) -> 0 | AH24: =$E24*$H24*J24%*P24*(44/28) -> 13739.566 | AI24: =$E24*$H24*K24%*Q24*(44/28) -> 0 | AJ24: =$E24*$H24*L24%*R24*(44/28) -> 0 | AK24: =$E24*$H24*M24%*S24*(44/28) -> 0 | AL24: =$E24*$H24*N24%*T24*(44/28) -> 0
D25: Costa | E25: ='3A1 Fermentación E.'!D23 -> 984149.28 | F25: 0.29 | G25: ='3B Manejo de Estiércol CH4'!F23 -> 174.42759 | H25: =F25*G25*(10^-3)*365 -> 18.46316 | I25: ='3B Manejo de Estiércol CH4'!H23 -> 0 | J25: ='3B Manejo de Estiércol CH4'!I23 -> 0.035714286 | K25: ='3B Manejo de Estiércol CH4'!J23 -> 0.57142857 | L25: ='3B Manejo de Estiércol CH4'!K23 -> 8.3333333 | M25: ='3B Manejo de Estiércol CH4'!L23 -> 0 | N25: ='3B Manejo de Estiércol CH4'!M23 -> 91.059524 | O25: 0.01 | P25: 0.01 | Q25: 0 | R25: 0 | S25: 0.02 | T25: 0 | U25: =(E25*H25*J25%*P25*(44/28))+(E25*H25*I25%*O25*(44/28))+(E25*H25*K25%*Q25*(44/28))+(E25*H25*L25%*R25*(44/28))+(E25*H25*M25%*S25*(44/28))+(E25*H25*N25%*T25*(44/28)) -> 101.97733 | W25: =E25*H25*N25% -> 16545976 | Z25: =$E25*$H25*I25% -> 0 | AA25: =$E25*$H25*J25% -> 6489.4664 | AB25: =$E25*$H25*K25% -> 103831.46 | AC25: =$E25*$H25*L25% -> 1514208.8 | AD25: =$E25*$H25*M25% -> 0 | AE25: =$E25*$H25*N25% -> 16545976 | AG25: =$E25*$H25*I25%*O25*(44/28) -> 0 | AH25: =$E25*$H25*J25%*P25*(44/28) -> 101.97733 | AI25: =$E25*$H25*K25%*Q25*(44/28) -> 0 | AJ25: =$E25*$H25*L25%*R25*(44/28) -> 0 | AK25: =$E25*$H25*M25%*S25*(44/28) -> 0 | AL25: =$E25*$H25*N25%*T25*(44/28) -> 0
D26: Amazonia | E26: ='3A1 Fermentación E.'!D24 -> 220534.27 | F26: 0.29 | G26: ='3B Manejo de Estiércol CH4'!F24 -> 174.58749 | H26: =F26*G26*(10^-3)*365 -> 18.480085 | I26: ='3B Manejo de Estiércol CH4'!H24 -> 0 | J26: ='3B Manejo de Estiércol CH4'!I24 -> 0 | K26: ='3B Manejo de Estiércol CH4'!J24 -> 2.173913 | L26: ='3B Manejo de Estiércol CH4'!K24 -> 0 | M26: ='3B Manejo de Estiércol CH4'!L24 -> 0 | N26: ='3B Manejo de Estiércol CH4'!M24 -> 97.826087 | O26: 0.01 | P26: 0.01 | Q26: 0 | R26: 0 | S26: 0.02 | T26: 0 | U26: =(E26*H26*J26%*P26*(44/28))+(E26*H26*I26%*O26*(44/28))+(E26*H26*K26%*Q26*(44/28))+(E26*H26*L26%*R26*(44/28))+(E26*H26*M26%*S26*(44/28))+(E26*H26*N26%*T26*(44/28)) -> 0 | W26: =E26*H26*N26% -> 3986894.6 | Z26: =$E26*$H26*I26% -> 0 | AA26: =$E26*$H26*J26% -> 0 | AB26: =$E26*$H26*K26% -> 88597.657 | AC26: =$E26*$H26*L26% -> 0 | AD26: =$E26*$H26*M26% -> 0 | AE26: =$E26*$H26*N26% -> 3986894.6 | AG26: =$E26*$H26*I26%*O26*(44/28) -> 0 | AH26: =$E26*$H26*J26%*P26*(44/28) -> 0 | AI26: =$E26*$H26*K26%*Q26*(44/28) -> 0 | AJ26: =$E26*$H26*L26%*R26*(44/28) -> 0 | AK26: =$E26*$H26*M26%*S26*(44/28) -> 0 | AL26: =$E26*$H26*N26%*T26*(44/28) -> 0
C27: Búfalos | E27: ='3A1 Fermentación E.'!D25 -> 3839 | F27: 0.41 | G27: ='3B Manejo de Estiércol CH4'!F25 -> 315 | H27: =F27*G27*(10^-3)*365 -> 47.13975 | I27: ='3B Manejo de Estiércol CH4'!H25 -> 2 | J27: ='3B Manejo de Estiércol CH4'!I25 -> 0 | K27: ='3B Manejo de Estiércol CH4'!J25 -> 0 | L27: ='3B Manejo de Estiércol CH4'!K25 -> 0 | M27: ='3B Manejo de Estiércol CH4'!L25 -> 5 | N27: ='3B Manejo de Estiércol CH4'!M25 -> 93 | O27: 0.01 | P27: 0.01 | Q27: 0 | R27: 0 | S27: 0.02 | T27: 0 | U27: =(E27*H27*J27%*P27*(44/28))+(E27*H27*I27%*O27*(44/28))+(E27*H27*K27%*Q27*(44/28))+(E27*H27*L27%*R27*(44/28))+(E27*H27*M27%*S27*(44/28))+(E27*H27*N27%*T27*(44/28)) -> 341.25677 | W27: =E27*H27*N27% -> 168301.64 | Z27: =$E27*$H27*I27% -> 3619.39 | AA27: =$E27*$H27*J27% -> 0 | AB27: =$E27*$H27*K27% -> 0 | AC27: =$E27*$H27*L27% -> 0 | AD27: =$E27*$H27*M27% -> 9048.475 | AE27: =$E27*$H27*N27% -> 168301.64 | AG27: =$E27*$H27*I27%*O27*(44/28) -> 56.876129 | AH27: =$E27*$H27*J27%*P27*(44/28) -> 0 | AI27: =$E27*$H27*K27%*Q27*(44/28) -> 0 | AJ27: =$E27*$H27*L27%*R27*(44/28) -> 0 | AK27: =$E27*$H27*M27%*S27*(44/28) -> 284.38064 | AL27: =$E27*$H27*N27%*T27*(44/28) -> 0
C28: Ovejas | E28: ='3A1 Fermentación E.'!D26 -> 498952.01 | F28: 0.32 | G28: ='3B Manejo de Estiércol CH4'!F26 -> 31 | H28: =F28*G28*(10^-3)*365 -> 3.6208 | I28: ='3B Manejo de Estiércol CH4'!H26 -> 17 | J28: ='3B Manejo de Estiércol CH4'!I26 -> 3 | K28: ='3B Manejo de Estiércol CH4'!J26 -> 0 | L28: ='3B Manejo de Estiércol CH4'!K26 -> 0 | M28: ='3B Manejo de Estiércol CH4'!L26 -> 0 | N28: ='3B Manejo de Estiércol CH4'!M26 -> 80 | O28: 0.01 | P28: 0.01 | Q28: 0 | R28: 0 | S28: 0.02 | T28: 0 | U28: =(E28*H28*J28%*P28*(44/28))+(E28*H28*I28%*O28*(44/28))+(E28*H28*K28%*Q28*(44/28))+(E28*H28*L28%*R28*(44/28))+(E28*H28*M28%*S28*(44/28))+(E28*H28*N28%*T28*(44/28)) -> 5677.9028 | W28: =E28*H28*N28% -> 1445284.4 | Z28: =$E28*$H28*I28% -> 307122.93 | AA28: =$E28*$H28*J28% -> 54198.163 | AB28: =$E28*$H28*K28% -> 0 | AC28: =$E28*$H28*L28% -> 0 | AD28: =$E28*$H28*M28% -> 0 | AE28: =$E28*$H28*N28% -> 1445284.4 | AG28: =$E28*$H28*I28%*O28*(44/28) -> 4826.2174 | AH28: =$E28*$H28*J28%*P28*(44/28) -> 851.68543 | AI28: =$E28*$H28*K28%*Q28*(44/28) -> 0 | AJ28: =$E28*$H28*L28%*R28*(44/28) -> 0 | AK28: =$E28*$H28*M28%*S28*(44/28) -> 0 | AL28: =$E28*$H28*N28%*T28*(44/28) -> 0
C29: Cabras | E29: ='3A1 Fermentación E.'!D27 -> 21745.307 | F29: 0.34 | G29: ='3B Manejo de Estiércol CH4'!F27 -> 24 | H29: =F29*G29*(10^-3)*365 -> 2.9784 | I29: ='3B Manejo de Estiércol CH4'!H27 -> 17 | J29: ='3B Manejo de Estiércol CH4'!I27 -> 3 | K29: ='3B Manejo de Estiércol CH4'!J27 -> 0 | L29: ='3B Manejo de Estiércol CH4'!K27 -> 0 | M29: ='3B Manejo de Estiércol CH4'!L27 -> 0 | N29: ='3B Manejo de Estiércol CH4'!M27 -> 80 | O29: 0.01 | P29: 0.01 | Q29: 0 | R29: 0 | S29: 0.02 | T29: 0 | U29: =(E29*H29*J29%*P29*(44/28))+(E29*H29*I29%*O29*(44/28))+(E29*H29*K29%*Q29*(44/28))+(E29*H29*L29%*R29*(44/28))+(E29*H29*M29%*S29*(44/28))+(E29*H29*N29%*T29*(44/28)) -> 203.55098 | W29: =E29*H29*N29% -> 51812.978 | Z29: =$E29*$H29*I29% -> 11010.258 | AA29: =$E29*$H29*J29% -> 1942.9867 | AB29: =$E29*$H29*K29% -> 0 | AC29: =$E29*$H29*L29% -> 0 | AD29: =$E29*$H29*M29% -> 0 | AE29: =$E29*$H29*N29% -> 51812.978 | AG29: =$E29*$H29*I29%*O29*(44/28) -> 173.01834 | AH29: =$E29*$H29*J29%*P29*(44/28) -> 30.532648 | AI29: =$E29*$H29*K29%*Q29*(44/28) -> 0 | AJ29: =$E29*$H29*L29%*R29*(44/28) -> 0 | AK29: =$E29*$H29*M29%*S29*(44/28) -> 0 | AL29: =$E29*$H29*N29%*T29*(44/28) -> 0
C30: Camélidos sudamericanos | E30: ='3A1 Fermentación E.'!D28 -> 20949.783 | F30: 0.46 | G30: ='3B Manejo de Estiércol CH4'!F28 -> 65 | H30: =F30*G30*(10^-3)*365 -> 10.9135 | I30: ='3B Manejo de Estiércol CH4'!H28 -> 17 | J30: ='3B Manejo de Estiércol CH4'!I28 -> 3 | K30: ='3B Manejo de Estiércol CH4'!J28 -> 0 | L30: ='3B Manejo de Estiércol CH4'!K28 -> 0 | M30: ='3B Manejo de Estiércol CH4'!L28 -> 0 | N30: ='3B Manejo de Estiércol CH4'!M28 -> 80 | O30: 0.01 | P30: 0.01 | Q30: 0 | R30: 0 | S30: 0.02 | T30: 0 | U30: =(E30*H30*J30%*P30*(44/28))+(E30*H30*I30%*O30*(44/28))+(E30*H30*K30%*Q30*(44/28))+(E30*H30*L30%*R30*(44/28))+(E30*H30*M30%*S30*(44/28))+(E30*H30*N30%*T30*(44/28)) -> 718.56859 | W30: =E30*H30*N30% -> 182908.37 | Z30: =$E30*$H30*I30% -> 38868.028 | AA30: =$E30*$H30*J30% -> 6859.0638 | AB30: =$E30*$H30*K30% -> 0 | AC30: =$E30*$H30*L30% -> 0 | AD30: =$E30*$H30*M30% -> 0 | AE30: =$E30*$H30*N30% -> 182908.37 | AG30: =$E30*$H30*I30%*O30*(44/28) -> 610.7833 | AH30: =$E30*$H30*J30%*P30*(44/28) -> 107.78529 | AI30: =$E30*$H30*K30%*Q30*(44/28) -> 0 | AJ30: =$E30*$H30*L30%*R30*(44/28) -> 0 | AK30: =$E30*$H30*M30%*S30*(44/28) -> 0 | AL30: =$E30*$H30*N30%*T30*(44/28) -> 0
C31: Caballos | E31: ='3A1 Fermentación E.'!D29 -> 260479.02 | F31: 0.46 | G31: ='3B Manejo de Estiércol CH4'!F29 -> 238 | H31: =F31*G31*(10^-3)*365 -> 39.9602 | I31: ='3B Manejo de Estiércol CH4'!H29 -> 17 | J31: ='3B Manejo de Estiércol CH4'!I29 -> 3 | K31: ='3B Manejo de Estiércol CH4'!J29 -> 0 | L31: ='3B Manejo de Estiércol CH4'!K29 -> 0 | M31: ='3B Manejo de Estiércol CH4'!L29 -> 0 | N31: ='3B Manejo de Estiércol CH4'!M29 -> 80 | O31: 0.01 | P31: 0.01 | Q31: 0 | R31: 0 | S31: 0.02 | T31: 0 | U31: =(E31*H31*J31%*P31*(44/28))+(E31*H31*I31%*O31*(44/28))+(E31*H31*K31%*Q31*(44/28))+(E31*H31*L31%*R31*(44/28))+(E31*H31*M31%*S31*(44/28))+(E31*H31*N31%*T31*(44/28)) -> 32713.351 | W31: =E31*H31*N31% -> 8327034.9 | Z31: =$E31*$H31*I31% -> 1769494.9 | AA31: =$E31*$H31*J31% -> 312263.81 | AB31: =$E31*$H31*K31% -> 0 | AC31: =$E31*$H31*L31% -> 0 | AD31: =$E31*$H31*M31% -> 0 | AE31: =$E31*$H31*N31% -> 8327034.9 | AG31: =$E31*$H31*I31%*O31*(44/28) -> 27806.349 | AH31: =$E31*$H31*J31%*P31*(44/28) -> 4907.0027 | AI31: =$E31*$H31*K31%*Q31*(44/28) -> 0 | AJ31: =$E31*$H31*L31%*R31*(44/28) -> 0 | AK31: =$E31*$H31*M31%*S31*(44/28) -> 0 | AL31: =$E31*$H31*N31%*T31*(44/28) -> 0
C32: Mulas & Asnos | E32: ='3A1 Fermentación E.'!D30 -> 147168.66 | F32: 0.46 | G32: ='3B Manejo de Estiércol CH4'!F30 -> 130 | H32: =F32*G32*(10^-3)*365 -> 21.827 | I32: ='3B Manejo de Estiércol CH4'!H30 -> 17 | J32: ='3B Manejo de Estiércol CH4'!I30 -> 3 | K32: ='3B Manejo de Estiércol CH4'!J30 -> 0 | L32: ='3B Manejo de Estiércol CH4'!K30 -> 0 | M32: ='3B Manejo de Estiércol CH4'!L30 -> 0 | N32: ='3B Manejo de Estiércol CH4'!M30 -> 80 | O32: 0.01 | P32: 0.01 | Q32: 0 | R32: 0 | S32: 0.02 | T32: 0 | U32: =(E32*H32*J32%*P32*(44/28))+(E32*H32*I32%*O32*(44/28))+(E32*H32*K32%*Q32*(44/28))+(E32*H32*L32%*R32*(44/28))+(E32*H32*M32%*S32*(44/28))+(E32*H32*N32%*T32*(44/28)) -> 10095.644 | W32: =E32*H32*N32% -> 2569800.4 | Z32: =$E32*$H32*I32% -> 546082.57 | AA32: =$E32*$H32*J32% -> 96367.513 | AB32: =$E32*$H32*K32% -> 0 | AC32: =$E32*$H32*L32% -> 0 | AD32: =$E32*$H32*M32% -> 0 | AE32: =$E32*$H32*N32% -> 2569800.4 | AG32: =$E32*$H32*I32%*O32*(44/28) -> 8581.2976 | AH32: =$E32*$H32*J32%*P32*(44/28) -> 1514.3466 | AI32: =$E32*$H32*K32%*Q32*(44/28) -> 0 | AJ32: =$E32*$H32*L32%*R32*(44/28) -> 0 | AK32: =$E32*$H32*M32%*S32*(44/28) -> 0 | AL32: =$E32*$H32*N32%*T32*(44/28) -> 0
C33: Cerdos | E33: ='3A1 Fermentación E.'!D31 -> 1682662 | F33: 0.67 | G33: ='3B Manejo de Estiércol CH4'!F31 -> 59 | H33: =F33*G33*(10^-3)*365 -> 14.42845 | I33: ='3B Manejo de Estiércol CH4'!H31 -> 15 | J33: ='3B Manejo de Estiércol CH4'!I31 -> 5 | K33: ='3B Manejo de Estiércol CH4'!J31 -> 5 | L33: ='3B Manejo de Estiércol CH4'!K31 -> 30 | M33: ='3B Manejo de Estiércol CH4'!L31 -> 40 | N33: ='3B Manejo de Estiércol CH4'!M31 -> 5 | O33: 0.01 | P33: 0.01 | Q33: 0 | R33: 0 | S33: 0.02 | T33: 0 | U33: =(E33*H33*J33%*P33*(44/28))+(E33*H33*I33%*O33*(44/28))+(E33*H33*K33%*Q33*(44/28))+(E33*H33*L33%*R33*(44/28))+(E33*H33*M33%*S33*(44/28))+(E33*H33*N33%*T33*(44/28)) -> 381514.65 | W33: =E33*H33*N33% -> 1213910.3 | Z33: =$E33*$H33*I33% -> 3641730.8 | AA33: =$E33*$H33*J33% -> 1213910.3 | AB33: =$E33*$H33*K33% -> 1213910.3 | AC33: =$E33*$H33*L33% -> 7283461.5 | AD33: =$E33*$H33*M33% -> 9711282 | AE33: =$E33*$H33*N33% -> 1213910.3 | AG33: =$E33*$H33*I33%*O33*(44/28) -> 57227.198 | AH33: =$E33*$H33*J33%*P33*(44/28) -> 19075.733 | AI33: =$E33*$H33*K33%*Q33*(44/28) -> 0 | AJ33: =$E33*$H33*L33%*R33*(44/28) -> 0 | AK33: =$E33*$H33*M33%*S33*(44/28) -> 305211.72 | AL33: =$E33*$H33*N33%*T33*(44/28) -> 0
C34: Aves de engorde | E34: ='3A1 Fermentación E.'!D32 -> 30205479 | F34: 1.2 | G34: ='3B Manejo de Estiércol CH4'!F32 -> 0.9 | H34: =F34*G34*(10^-3)*365 -> 0.3942 | I34: ='3B Manejo de Estiércol CH4'!H32 -> 0 | J34: ='3B Manejo de Estiércol CH4'!I32 -> 0 | K34: ='3B Manejo de Estiércol CH4'!J32 -> 0 | L34: ='3B Manejo de Estiércol CH4'!K32 -> 0 | M34: ='3B Manejo de Estiércol CH4'!L32 -> 100 | N34: ='3B Manejo de Estiércol CH4'!M32 -> 0 | O34: 0.01 | P34: 0.01 | Q34: 0 | R34: 0 | S34: 0.02 | T34: 0 | U34: =(E34*H34*J34%*P34*(44/28))+(E34*H34*I34%*O34*(44/28))+(E34*H34*K34%*Q34*(44/28))+(E34*H34*L34%*R34*(44/28))+(E34*H34*M34%*S34*(44/28))+(E34*H34*N34%*T34*(44/28)) -> 374220 | W34: =E34*H34*N34% -> 0 | Z34: =$E34*$H34*I34% -> 0 | AA34: =$E34*$H34*J34% -> 0 | AB34: =$E34*$H34*K34% -> 0 | AC34: =$E34*$H34*L34% -> 0 | AD34: =$E34*$H34*M34% -> 11907000 | AE34: =$E34*$H34*N34% -> 0 | AG34: =$E34*$H34*I34%*O34*(44/28) -> 0 | AH34: =$E34*$H34*J34%*P34*(44/28) -> 0 | AI34: =$E34*$H34*K34%*Q34*(44/28) -> 0 | AJ34: =$E34*$H34*L34%*R34*(44/28) -> 0 | AK34: =$E34*$H34*M34%*S34*(44/28) -> 374220 | AL34: =$E34*$H34*N34%*T34*(44/28) -> 0
C35: Ponedoras | E35: ='3A1 Fermentación E.'!D33 -> 13510000 | F35: 2.01 | G35: ='3B Manejo de Estiércol CH4'!F33 -> 1.4 | H35: =F35*G35*(10^-3)*365 -> 1.02711 | I35: ='3B Manejo de Estiércol CH4'!H33 -> 42 | J35: ='3B Manejo de Estiércol CH4'!I33 -> 0 | K35: ='3B Manejo de Estiércol CH4'!J33 -> 0 | L35: ='3B Manejo de Estiércol CH4'!K33 -> 58 | M35: ='3B Manejo de Estiércol CH4'!L33 -> 0 | N35: ='3B Manejo de Estiércol CH4'!M33 -> 0 | O35: 0.01 | P35: 0.01 | Q35: 0 | R35: 0 | S35: 0.02 | T35: 0 | U35: =(E35*H35*J35%*P35*(44/28))+(E35*H35*I35%*O35*(44/28))+(E35*H35*K35%*Q35*(44/28))+(E35*H35*L35%*R35*(44/28))+(E35*H35*M35%*S35*(44/28))+(E35*H35*N35%*T35*(44/28)) -> 91583.29 | W35: =E35*H35*N35% -> 0 | Z35: =$E35*$H35*I35% -> 5828027.6 | AA35: =$E35*$H35*J35% -> 0 | AB35: =$E35*$H35*K35% -> 0 | AC35: =$E35*$H35*L35% -> 8048228.5 | AD35: =$E35*$H35*M35% -> 0 | AE35: =$E35*$H35*N35% -> 0 | AG35: =$E35*$H35*I35%*O35*(44/28) -> 91583.29 | AH35: =$E35*$H35*J35%*P35*(44/28) -> 0 | AI35: =$E35*$H35*K35%*Q35*(44/28) -> 0 | AJ35: =$E35*$H35*L35%*R35*(44/28) -> 0 | AK35: =$E35*$H35*M35%*S35*(44/28) -> 0 | AL35: =$E35*$H35*N35%*T35*(44/28) -> 0
C36: Patos | E36: ='3A1 Fermentación E.'!D34 -> 70291.656 | F36: 0.83 | G36: ='3B Manejo de Estiércol CH4'!F34 -> 2.7 | H36: =F36*G36*(10^-3)*365 -> 0.817965 | I36: ='3B Manejo de Estiércol CH4'!H34 -> 0 | J36: ='3B Manejo de Estiércol CH4'!I34 -> 0 | K36: ='3B Manejo de Estiércol CH4'!J34 -> 0 | L36: ='3B Manejo de Estiércol CH4'!K34 -> 0 | M36: ='3B Manejo de Estiércol CH4'!L34 -> 100 | N36: ='3B Manejo de Estiércol CH4'!M34 -> 0 | O36: 0.01 | P36: 0.01 | Q36: 0 | R36: 0 | S36: 0.02 | T36: 0 | U36: =(E36*H36*J36%*P36*(44/28))+(E36*H36*I36%*O36*(44/28))+(E36*H36*K36%*Q36*(44/28))+(E36*H36*L36%*R36*(44/28))+(E36*H36*M36%*S36*(44/28))+(E36*H36*N36%*T36*(44/28)) -> 1807.0207 | W36: =E36*H36*N36% -> 0 | Z36: =$E36*$H36*I36% -> 0 | AA36: =$E36*$H36*J36% -> 0 | AB36: =$E36*$H36*K36% -> 0 | AC36: =$E36*$H36*L36% -> 0 | AD36: =$E36*$H36*M36% -> 57496.114 | AE36: =$E36*$H36*N36% -> 0 | AG36: =$E36*$H36*I36%*O36*(44/28) -> 0 | AH36: =$E36*$H36*J36%*P36*(44/28) -> 0 | AI36: =$E36*$H36*K36%*Q36*(44/28) -> 0 | AJ36: =$E36*$H36*L36%*R36*(44/28) -> 0 | AK36: =$E36*$H36*M36%*S36*(44/28) -> 1807.0207 | AL36: =$E36*$H36*N36%*T36*(44/28) -> 0
C37: Pavos | E37: ='3A1 Fermentación E.'!D35 -> 198716.81 | F37: 0.74 | G37: ='3B Manejo de Estiércol CH4'!F35 -> 6.8 | H37: =F37*G37*(10^-3)*365 -> 1.83668 | I37: ='3B Manejo de Estiércol CH4'!H35 -> 0 | J37: ='3B Manejo de Estiércol CH4'!I35 -> 0 | K37: ='3B Manejo de Estiércol CH4'!J35 -> 0 | L37: ='3B Manejo de Estiércol CH4'!K35 -> 0 | M37: ='3B Manejo de Estiércol CH4'!L35 -> 100 | N37: ='3B Manejo de Estiércol CH4'!M35 -> 0 | O37: 0.01 | P37: 0.01 | Q37: 0 | R37: 0 | S37: 0.02 | T37: 0 | U37: =(E37*H37*J37%*P37*(44/28))+(E37*H37*I37%*O37*(44/28))+(E37*H37*K37%*Q37*(44/28))+(E37*H37*L37%*R37*(44/28))+(E37*H37*M37%*S37*(44/28))+(E37*H37*N37%*T37*(44/28)) -> 11470.775 | W37: =E37*H37*N37% -> 0 | Z37: =$E37*$H37*I37% -> 0 | AA37: =$E37*$H37*J37% -> 0 | AB37: =$E37*$H37*K37% -> 0 | AC37: =$E37*$H37*L37% -> 0 | AD37: =$E37*$H37*M37% -> 364979.19 | AE37: =$E37*$H37*N37% -> 0 | AG37: =$E37*$H37*I37%*O37*(44/28) -> 0 | AH37: =$E37*$H37*J37%*P37*(44/28) -> 0 | AI37: =$E37*$H37*K37%*Q37*(44/28) -> 0 | AJ37: =$E37*$H37*L37%*R37*(44/28) -> 0 | AK37: =$E37*$H37*M37%*S37*(44/28) -> 11470.775 | AL37: =$E37*$H37*N37%*T37*(44/28) -> 0
B38: Total | E38: =SUM(E15:E37) -> 50677079 | U38: =SUM(U15:U37) -> 1025784.2 | W38: =SUM(W15:W37) -> 1.4135268e+08 | Z38: =SUM(Z15:Z37) -> 12353885 | AA38: =SUM(AA15:AA37) -> 5910973.9 | AB38: =SUM(AB15:AB37) -> 7030118.5 | AC38: =SUM(AC15:AC37) -> 18874983 | AD38: =SUM(AD15:AD37) -> 23506159 | AE38: =SUM(AE15:AE37) -> 1.4135268e+08 | AG38: =SUM(AG15:AG37) -> 194132.47 | AH38: =SUM(AH15:AH37) -> 92886.733 | AI38: =SUM(AI15:AI37) -> 0 | AJ38: =SUM(AJ15:AJ37) -> 0 | AK38: =SUM(AK15:AK37) -> 738764.98 | AL38: =SUM(AL15:AL37) -> 0
C39: (*) Para la variable de nitrogeno agregado vía co-digestión en sistemas de digestión anaeróbica no se cuentan con datos anuales nacionales, y aun cuando el Proyecto GCI detalla un % minimo de gestión de estiércol en estos sistemas para bovinos, el mismo es irrelevante respecto del total, por lo que se omite en la fórmula de cálculo
W40: =SUM(W15:W26)+W33+SUM(W34:W37) -> 1.2860753e+08 | X40: CPP
W41: =W38-W40 -> 12745143 | X41: SO
C42: NOTA EXPLICATIVA DE FUENTES Y OTRAS CONSIDERACIONES DE LOS DATOS
C43: TIPO DE GANADO | D43: DATO DE ACTIVIDAD | E43: Observaciones | F43: N ratio | G43: TAM | H43: Fracción AWMS | I43: FACTOR DE EMISIÓN
C44: Ganado Lechero | D44: ESPAC 2018 , tabla 67 | E44: Dato de actividad desagregado por región, dato de existencias población adulta de mas de dos años | F44: Se obtiene por defecto de la tabla 10.19 directrices IPCC V4 CH 10, para ganado de la sierra se considera productividad media, en tanto para las otras regiones se considera productividad baja | G44: Dato propio del país según registros de proyecto GCI por región | H44: Valor propio del país según registros proyecto GCI por región, se promedian modos de producción | I44: Factor de emisión por defecto tablas 10.21 directrices IPCC V4, en algunos casos se asemejan factores según similitud de sistemas de manejo y tipo de clima por región | J44: . | AH44: .
C45: No LecheroToros | D45: ESPAC 2018, tabla 50 | E45: Corresponde al número de toros de 2 o más años de edad | F45: Se obtiene por defecto de la tabla 10.19 directrices IPCC V4 CH 10, para ganado de la sierra se considera productividad media, en tanto para las otras regiones se considera productividad baja | G45: Dato propio del país según registros de proyecto GCI por región | H45: Valor propio del país según registros proyecto GCI por región, se promedian modos de producción | I45: Factor de emisión por defecto tablas 10.21 directrices IPCC V4, en algunos casos se asemejan factores según similitud de sistemas de manejo y tipo de clima por región | J45: . | AH45: .
C46: No Lechero Vacas | D46: ESPAC 2018, tabla 50 | E46: Corresponde al número de vacas de 2 o más años de edad menos el número de vacas ordeñadas | F46: Se obtiene por defecto de la tabla 10.19 directrices IPCC V4 CH 10, para ganado de la sierra se considera productividad media, en tanto para las otras regiones se considera productividad baja | G46: Dato propio del país según registros de proyecto GCI por región | H46: Valor propio del país según registros proyecto GCI por región, se promedian modos de producción | I46: Factor de emisión por defecto tablas 10.21 directrices IPCC V4, en algunos casos se asemejan factores según similitud de sistemas de manejo y tipo de clima por región | J46: . | AH46: .
C47: No Lechero En crecimiento | D47: ESPAC 2018, tabla 50 | E47: Corresponde a la suma de terneros, toretes, terneras y vaconas, se confirma que el dato puede ser usado como dato final (dias vivo) considerando que el formulario del INEC pregunta por las existencias al momento de la encuesta, y no existe estadistica nacional para discretizar aquella población que vive menos de un año. | F47: Se obtiene por defecto de la tabla 10.19 directrices IPCC V4 CH 10, para ganado de la sierra se considera productividad media, en tanto para las otras regiones se considera productividad baja | G47: Dato propio del país según registros de proyecto GCI por región, suma grupos de bovinos menores a 2 años machos y hembras | H47: Valor propio del país según registros proyecto GCI por región, se promedian modos de producción | I47: Factor de emisión por defecto tablas 10.21 directrices IPCC V4, en algunos casos se asemejan factores según similitud de sistemas de manejo y tipo de clima por región | J47: . | M47: . | AH47: . | AK47: .
C48: Búfalos | D48: Datos Agrocalidad, registro vacunación por fiebre aftosa. | F48: Se obtiene por defecto de la tabla 10.19 directrices IPCC V4 CH 10, para ganado de la sierra se considera productividad media, en tanto para las otras regiones se considera productividad baja | G48: Valor por defecto directrices IPCC tabla 10A.5 | H48: Valor por defecto Tablas 10A.6 a 10A.9 directrices IPCC V4, Otros al no ser relevante suma los demás sistemas no considerados individualmente | I48: Factor de emisión por defecto tablas 10.21 directrices IPCC V4, en algunos casos se asemejan factores según similitud de sistemas de manejo y tipo de clima por región | J48: . | M48: . | AH48: . | AK48: .
C49: Ovejas | D49: ESPAC 2018 , tabla 60 | E49: se confirma que el dato puede ser usado como dato final (dias vivo) considerando que el formulario del INEC pregunta por las existencias al momento de la encuesta, y no existe estadistica nacional para discretizar aquella población que vive menos de un año. | F49: Se obtiene por defecto de la tabla 10.19 directrices IPCC V4 CH 10, para ganado de la sierra se considera productividad media, en tanto para las otras regiones se considera productividad baja | G49: Valor por defecto directrices IPCC tabla 10A.6 | H49: Valor por defecto Tablas 10A.6 a 10A.9 directrices IPCC V4, Otros al no ser relevante suma los demás sistemas no considerados individualmente | I49: Factor de emisión por defecto tablas 10.21 directrices IPCC V4, en algunos casos se asemejan factores según similitud de sistemas de manejo y tipo de clima por región | J49: . | M49: . | AH49: . | AK49: .
C50: Cabras | D50: ESPAC 2018 , tabla 61 | E50: se confirma que el dato puede ser usado como dato final (dias vivo) considerando que el formulario del INEC pregunta por las existencias al momento de la encuesta, y no existe estadistica nacional para discretizar aquella población que vive menos de un año. | F50: Se obtiene por defecto de la tabla 10.19 directrices IPCC V4 CH 10, para ganado de la sierra se considera productividad media, en tanto para las otras regiones se considera productividad baja | G50: Valor por defecto directrices IPCC tabla 10A.7 | H50: Valor por defecto Tablas 10A.6 a 10A.9 directrices IPCC V4, Otros al no ser relevante suma los demás sistemas no considerados individualmente | I50: Factor de emisión por defecto tablas 10.21 directrices IPCC V4, en algunos casos se asemejan factores según similitud de sistemas de manejo y tipo de clima por región | J50: . | M50: . | AH50: . | AK50: .
C51: Camélidos sudamericanos | D51: Ministerio de Agricultura, Agrocalidad, Regional Chimborazo | E51: Se confirman estadisticas similares y poblaciones estacionales para la categoría, las tasas de crecimiento se proyectan desde los datos de 2016 y 2018 para los siguientes años | F51: Se obtiene por defecto de la tabla 10.19 directrices IPCC V4 CH 10, para ganado de la sierra se considera productividad media, en tanto para las otras regiones se considera productividad baja | G51: Valor por defecto directrices IPCC tabla 10A.8 | H51: Valor por defecto Tablas 10A.6 a 10A.9 directrices IPCC V4, Otros al no ser relevante suma los demás sistemas no considerados individualmente | I51: Factor de emisión por defecto tablas 10.21 directrices IPCC V4, en algunos casos se asemejan factores según similitud de sistemas de manejo y tipo de clima por región | J51: . | M51: . | AH51: . | AK51: .
C52: Caballos | D52: ESPAC 2018 , tabla 61 | E52: se confirma que el dato puede ser usado como dato final (dias vivo) considerando que el formulario del INEC pregunta por las existencias al momento de la encuesta, y no existe estadistica nacional para discretizar aquella población que vive menos de un año. | F52: Se obtiene por defecto de la tabla 10.19 directrices IPCC V4 CH 10, para ganado de la sierra se considera productividad media, en tanto para las otras regiones se considera productividad baja | G52: Valor por defecto directrices IPCC tabla 10A.9 | H52: Valor por defecto Tablas 10A.6 a 10A.9 directrices IPCC V4, Otros al no ser relevante suma los demás sistemas no considerados individualmente | I52: Factor de emisión por defecto tablas 10.21 directrices IPCC V4, en algunos casos se asemejan factores según similitud de sistemas de manejo y tipo de clima por región | J52: . | M52: . | AH52: . | AK52: .
C53: Mulas & Asnos | D53: ESPAC 2018 , tabla 61 | E53: se confirma que el dato puede ser usado como dato final (dias vivo) considerando que el formulario del INEC pregunta por las existencias al momento de la encuesta, y no existe estadistica nacional para discretizar aquella población que vive menos de un año. | F53: Se obtiene por defecto de la tabla 10.19 directrices IPCC V4 CH 10, para ganado de la sierra se considera productividad media, en tanto para las otras regiones se considera productividad baja | G53: Valor por defecto directrices IPCC tabla 10A.10 | H53: Valor por defecto Tablas 10A.6 a 10A.9 directrices IPCC V4, Otros al no ser relevante suma los demás sistemas no considerados individualmente | I53: Factor de emisión por defecto tablas 10.21 directrices IPCC V4, en algunos casos se asemejan factores según similitud de sistemas de manejo y tipo de clima por región | J53: . | M53: . | AH53: . | AK53: .
C54: Cerdos | D54: ESPAC 2018 , tabla 57 | E54: Se usa el dato de existencias, para afinar la estadistica de "dias vivo", el periodo de dias vivo se consideran 27 semanas | F54: Se obtiene por defecto de la tabla 10.19 directrices IPCC V4 CH 10, para ganado de la sierra se considera productividad media, en tanto para las otras regiones se considera productividad baja | G54: Valor por defecto directrices IPCC tabla 10A.11 | H54: Valor por defecto Tablas 10A.6 a 10A.9 directrices IPCC V4, Otros al no ser relevante suma los demás sistemas no considerados individualmente | I54: Factor de emisión por defecto tablas 10.21 directrices IPCC V4, en algunos casos se asemejan factores según similitud de sistemas de manejo y tipo de clima por región | J54: . | M54: . | AH54: . | AK54: .
C55: Aves de engorde | D55: Datos de CONAVE | E55: Corresponde a la suma de aves criadas en campo (pollitos, pollitas, pollos, pollas + gallos, gallinas) + aves criadas en planteles avícolas (pollitos, pollitas, pollos, pollas + gallinas ), El dato de aves de corral que reporta el INEC a través de la ESPAC corresponde a un solo ciclo de producción en el año, se toma el dato de CONAVE como real. | F55: Se obtiene por defecto de la tabla 10.19 directrices IPCC V4, para todas las regiones se considera productividad media (relacionando sistemas de producción referenciados en las directrices IPCC) | G55: Valor por defecto directrices IPCC tabla 10A.12 | H55: Valor por defecto Tablas 10A.6 a 10A.9 directrices IPCC V4, Otros al no ser relevante suma los demás sistemas no considerados individualmente | I55: Factor de emisión por defecto tablas 10.21 directrices IPCC V4, en algunos casos se asemejan factores según similitud de sistemas de manejo y tipo de clima por región | J55: . | M55: . | AH55: . | AK55: .
C56: Ponedoras | D56: Datos de CONAVE | E56: Corresponde al dato de número de cabezas de patos criados en campo | F56: Se obtiene por defecto de la tabla 10.19 directrices IPCC V4, para todas las regiones se considera productividad media (relacionando sistemas de producción referenciados en las directrices IPCC) | G56: Valor por defecto directrices IPCC tabla 10A.13 | H56: Valor por defecto Tablas 10A.6 a 10A.9 directrices IPCC V4, Otros al no ser relevante suma los demás sistemas no considerados individualmente | I56: Factor de emisión por defecto tablas 10.21 directrices IPCC V4, en algunos casos se asemejan factores según similitud de sistemas de manejo y tipo de clima por región | J56: . | M56: . | AH56: . | AK56: .
C57: Patos | D57: ESPAC 2018 , tabla 62,63 | E57: Corresponde a la suma de aves criadas en campo (pavos) + aves criadas en planteles avícolas (pavos) | F57: Se obtiene por defecto de la tabla 10.19 directrices IPCC V4, para todas las regiones se considera productividad baja (relacionando sistemas de producción referenciados en las directrices IPCC) | G57: Valor por defecto directrices IPCC tabla 10A.14 | H57: Valor por defecto Tablas 10A.6 a 10A.9 directrices IPCC V4, Otros al no ser relevante suma los demás sistemas no considerados individualmente | I57: Factor de emisión por defecto tablas 10.21 directrices IPCC V4, en algunos casos se asemejan factores según similitud de sistemas de manejo y tipo de clima por región | J57: . | AH57: .
C58: Pavos | D58: ESPAC 2018 , tabla 62,63 | E58: Corresponde al dato de número de cabezas de ponedoras en planteles avícolas | F58: Se obtiene por defecto de la tabla 10.19 directrices IPCC V4, para todas las regiones se considera productividad baja (relacionando sistemas de producción referenciados en las directrices IPCC) | G58: Valor por defecto directrices IPCC tabla 10A.15 | H58: Valor por defecto Tablas 10A.6 a 10A.9 directrices IPCC V4, Otros al no ser relevante suma los demás sistemas no considerados individualmente | I58: Factor de emisión por defecto tablas 10.21 directrices IPCC V4, en algunos casos se asemejan factores según similitud de sistemas de manejo y tipo de clima por región | J58: . | AH58: .

Sheet 3B Gestión Estiércol N2O Ind
B2: GESTIÓN DE ESTIÉRCOL : EMISIONES DIRECTAS DE N2O
B4: Sector | F4: Agricultura
B5: Categoría | F5: Gestión de Estiércol: Emisiones Directas de N2O del Gestión de Estiércol
B6: Código de Categoría | F6: 3A2
B7: Hoja | F7: 1 of 1
B8: Ecuación | E8: Eq. 10.25 | F8: Ecuación 10.30 | AC8: Ecuación 10.26 | AD8: Ecuación 10.27 | AE8: V | AF8: L
B9: Sistema de Gestión de Estiércol (MMS)1 (se desagrega a continuación de manera horizontal) | E9: Número de animales | F9: Ratio de excreción de N (default) | G9: Masa tipica del animal por categoría | H9: Excreción anual de N por cabeza de especie / categoría ganadera3 | I9: Fracción del total anual de manejo de estiercol por tipo de sistema y tipo de ganado; ANIMAL WASTE MANAGEMENT SYSTEM (AWMS) | O9: Cantidad de nitrógeno del estiércol que se pierde debido a la volatilización de NH3 y Nox Frac Gas_MS | U9: Cantidad de nitrógeno del estiércol que se pierde debido a la lixiviación Frac leach_MS | AA9: Factor de emisión para emisiones indirectas de N2O-N por MMS | AE9: Emisiones anuales indirectas de N2O | AF9: Emisiones anuales indirectas de N2O | AG9: Emisiones anuales indirectas de N2O | AK9: Cantidad de nitrógeno del estiércol que se pierde debido a la lixiviación Frac leach_MS
C10: Categoria de Ganado | E10: (Cabezas) | F10: [kg N | G10: (kg) | H10: (kg N animal-1 | I10: (-) | AE10: kg N2O yr-1 | AF10: kg N2O yr-1 | AG10: kg N2O yr-2
F11: (1000 kg animal)-1 día-1] | H11: año-1) | I11: ='3B Manejo de Estiércol CH4'!H10 -> Sistema manejo estiércol: Almacenaje de sólidos | J11: ='3B Manejo de Estiércol CH4'!I10 -> Sistema manejo estiércol: Compostaje | K11: ='3B Manejo de Estiércol CH4'!J10 -> Sistema manejo estiércol: Distribución diaria en pasturas | L11: ='3B Manejo de Estiércol CH4'!K10 -> Sistema manejo estiércol: Líquido/fango | M11: ='3B Manejo de Estiércol CH4'!L10 -> Otros Sistemas de Manejo | N11: ='3B Manejo de Estiércol CH4'!M10 -> Sistema manejo estiércol: Pasturas, sin manejo | O11: Sistema manejo estiércol: Almacenaje de sólidos | P11: Sistema manejo estiércol: Compostaje | Q11: Sistema manejo estiércol: Distribución diaria en pasturas | R11: Sistema manejo estiércol: Líquido/fango | S11: Otros Sistemas de Manejo | T11: Sistema manejo estiércol: Pasturas, sin manejo | U11: Sistema manejo estiércol: Almacenaje de sólidos | V11: Sistema manejo estiércol: Compostaje | W11: Sistema manejo estiércol: Distribución diaria en pasturas | X11: Sistema manejo estiércol: Líquido/fango | Y11: Otros Sistemas de Manejo | Z11: Sistema manejo estiércol: Pasturas, sin manejo | AA11: Factor por volatilización | AB11: Factor por lixiviación | AC11: Pérdidas de nitrógeno por volatilización | AD11: Pérdidas de nitrógeno por lixiviación | AE11: Emisiones anuales indirectas de N2O por volatilización | AF11: Emisiones anuales indirectas de N2O por lixiviación | AG11: Emisiones anuales indirectas de N2O TOTALES | AK11: Sistema manejo estiércol: Almacenaje de sólidos | AL11: Sistema manejo estiércol: Compostaje | AM11: Sistema manejo estiércol: Distribución diaria en pasturas | AN11: Sistema manejo estiércol: Líquido/fango | AO11: Otros Sistemas de Manejo | AP11: Sistema manejo estiércol: Pasturas, sin manejo
F12: Tabla 10.19 | G12: Tablas 10A-4 to 10A-9 | H12: Nex(T) = Nrate(T) * TAM * 10-3 * 365 | I12: Tablas 10A.6 a 10A.9 | AE12: N2O(mm) = | AF12: N2O(mm) = | AG12: N2O(mm) =
P13: Tabla 10.22 | V13: Tabla 10.22 | AA13: Tabla 11.3 | AE13: NEMMS * EF4(S) * 44/28 | AF13: NEMMS * EF5(S) * 44/28 | AG13: V+L | AL13: Tabla 10.22
B14: S | C14: T | E14: N(T) | F14: Nrate(T) | G14: TAM | H14: Nex(T) | I14: AWMS (%) | O14: Frac Gas_MS | U14: Frac leach_MS | AA14: EF4(S) | AB14: EF5(S) | AC14: kg N yr-1 | AD14: kg N yr-1 | AE14: N2Og(mm) | AF14: N2Ol(mm) | AG14: N2Ol(mm) | AK14: Frac leach_MS
C15: Ganado Lechero | D15: Sierra | E15: ='3A1 Fermentación E.'!D13 -> 522643.97 | F15: ='3B Gestión Estiércol N2O Dir'!F15 -> 0.39 | G15: ='3B Manejo de Estiércol CH4'!F13 -> 419.01067 | H15: =F15*G15*(10^-3)*365 -> 59.646169 | I15: ='3B Manejo de Estiércol CH4'!H13 -> 0.63456633 | J15: ='3B Manejo de Estiércol CH4'!I13 -> 7.8409864 | K15: ='3B Manejo de Estiércol CH4'!J13 -> 12.651786 | L15: ='3B Manejo de Estiércol CH4'!K13 -> 0.025510204 | M15: ='3B Manejo de Estiércol CH4'!L13 -> 4.4451531 | N15: ='3B Manejo de Estiércol CH4'!M13 -> 74.401998 | O15: 0.3 | P15: 0.45 | Q15: 0.07 | R15: 0.48 | S15: 0.25 | T15: 0 | U15: 0.02 | V15: 0.04 | W15: 0 | X15: 0 | Y15: 0.035 | Z15: 0 | AA15: 0.005 | AB15: 0.011 | AC15: =(E15*H15*I15%*O15)+(E15*H15*J15%*P15)+(E15*H15*K15%*Q15)+(E15*H15*L15%*R15)+(E15*H15*M15%*S15)+(E15*H15*N15%*T15) -> 1785621.4 | AD15: =(E15*H15*I15%*U15)+(E15*H15*J15%*V15)+(E15*H15*K15%*W15)+(E15*H15*L15%*X15)+(E15*H15*M15%*Y15)+(E15*H15*N15%*Z15) -> 150229.58 | AE15: =AC15*AA15*(44/28) -> 14029.882 | AF15: =AD15*AB15*(44/28) -> 2596.8257 | AG15: =AE15+AF15 -> 16626.708 | AK15: 0.02 | AL15: 0.04 | AM15: 0 | AN15: 0 | AO15: 0.035 | AP15: 0
D16: Costa | E16: ='3A1 Fermentación E.'!D14 -> 262262.61 | F16: ='3B Gestión Estiércol N2O Dir'!F16 -> 0.39 | G16: ='3B Manejo de Estiércol CH4'!F14 -> 605.43489 | H16: =F16*G16*(10^-3)*365 -> 86.183656 | I16: ='3B Manejo de Estiércol CH4'!H14 -> 0.032467532 | J16: ='3B Manejo de Estiércol CH4'!I14 -> 0.038961039 | K16: ='3B Manejo de Estiércol CH4'!J14 -> 6.2077922 | L16: ='3B Manejo de Estiércol CH4'!K14 -> 0.64935065 | M16: ='3B Manejo de Estiércol CH4'!L14 -> 0.3125 | N16: ='3B Manejo de Estiércol CH4'!M14 -> 92.758929 | O16: 0.3 | P16: 0.45 | Q16: 0.07 | R16: 0.48 | S16: 0.25 | T16: 0 | U16: 0.02 | V16: 0.04 | W16: 0 | X16: 0 | Y16: 0.035 | Z16: 0 | AA16: 0.014 | AB16: 0.011 | AC16: =(E16*H16*I16%*O16)+(E16*H16*J16%*P16)+(E16*H16*K16%*Q16)+(E16*H16*L16%*R16)+(E16*H16*M16%*S16)+(E16*H16*N16%*T16) -> 192492.14 | AD16: =(E16*H16*I16%*U16)+(E16*H16*J16%*V16)+(E16*H16*K16%*W16)+(E16*H16*L16%*X16)+(E16*H16*M16%*Y16)+(E16*H16*N16%*Z16) -> 2971.1976 | AE16: =AC16*AA16*(44/28) -> 4234.8271 | AF16: =AD16*AB16*(44/28) -> 51.359273 | AG16: =AE16+AF16 -> 4286.1864 | AK16: 0.02 | AL16: 0.04 | AM16: 0 | AN16: 0 | AO16: 0.035 | AP16: 0
D17: Amazonia | E17: ='3A1 Fermentación E.'!D15 -> 47621.019 | F17: ='3B Gestión Estiércol N2O Dir'!F17 -> 0.39 | G17: ='3B Manejo de Estiércol CH4'!F15 -> 425.22942 | H17: =F17*G17*(10^-3)*365 -> 60.531408 | I17: ='3B Manejo de Estiércol CH4'!H15 -> 0.096153846 | J17: ='3B Manejo de Estiércol CH4'!I15 -> 0.038461538 | K17: ='3B Manejo de Estiércol CH4'!J15 -> 0 | L17: ='3B Manejo de Estiércol CH4'!K15 -> 0 | M17: ='3B Manejo de Estiércol CH4'!L15 -> 0 | N17: ='3B Manejo de Estiércol CH4'!M15 -> 99.865385 | O17: 0.3 | P17: 0.45 | Q17: 0.07 | R17: 0.48 | S17: 0.25 | T17: 0 | U17: 0.02 | V17: 0.04 | W17: 0 | X17: 0 | Y17: 0.035 | Z17: 0 | AA17: 0.014 | AB17: 0.011 | AC17: =(E17*H17*I17%*O17)+(E17*H17*J17%*P17)+(E17*H17*K17%*Q17)+(E17*H17*L17%*R17)+(E17*H17*M17%*S17)+(E17*H17*N17%*T17) -> 1330.4157 | AD17: =(E17*H17*I17%*U17)+(E17*H17*J17%*V17)+(E17*H17*K17%*W17)+(E17*H17*L17%*X17)+(E17*H17*M17%*Y17)+(E17*H17*N17%*Z17) -> 99.781176 | AE17: =AC17*AA17*(44/28) -> 29.269145 | AF17: =AD17*AB17*(44/28) -> 1.7247889 | AG17: =AE17+AF17 -> 30.993934 | AK17: 0.02 | AL17: 0.04 | AM17: 0 | AN17: 0 | AO17: 0.035 | AP17: 0
C18: No LecheroToros | D18: Sierra | E18: ='3A1 Fermentación E.'!D16 -> 153765.65 | F18: ='3B Gestión Estiércol N2O Dir'!F18 -> 0.29 | G18: ='3B Manejo de Estiércol CH4'!F16 -> 513.2818 | H18: =F18*G18*(10^-3)*365 -> 54.330878 | I18: ='3B Manejo de Estiércol CH4'!H16 -> 0 | J18: ='3B Manejo de Estiércol CH4'!I16 -> 4.8148148 | K18: ='3B Manejo de Estiércol CH4'!J16 -> 0.12222222 | L18: ='3B Manejo de Estiércol CH4'!K16 -> 0 | M18: ='3B Manejo de Estiércol CH4'!L16 -> 0 | N18: ='3B Manejo de Estiércol CH4'!M16 -> 95.062963 | O18: 0.45 | P18: 0.6 | Q18: 0.07 | R18: 0.48 | S18: 0.25 | T18: 0 | U18: 0.02 | V18: 0.04 | W18: 0 | X18: 0 | Y18: 0.035 | Z18: 0 | AA18: 0.005 | AB18: 0.011 | AC18: =(E18*H18*I18%*O18)+(E18*H18*J18%*P18)+(E18*H18*K18%*Q18)+(E18*H18*L18%*R18)+(E18*H18*M18%*S18)+(E18*H18*N18%*T18) -> 242058.97 | AD18: =(E18*H18*I18%*U18)+(E18*H18*J18%*V18)+(E18*H18*K18%*W18)+(E18*H18*L18%*X18)+(E18*H18*M18%*Y18)+(E18*H18*N18%*Z18) -> 16089.614 | AE18: =AC18*AA18*(44/28) -> 1901.8919 | AF18: =AD18*AB18*(44/28) -> 278.12048 | AG18: =AE18+AF18 -> 2180.0123 | AK18: 0.02 | AL18: 0.04 | AM18: 0 | AN18: 0 | AO18: 0.035 | AP18: 0
D19: Costa | E19: ='3A1 Fermentación E.'!D17 -> 73566.158 | F19: ='3B Gestión Estiércol N2O Dir'!F19 -> 0.29 | G19: ='3B Manejo de Estiércol CH4'!F17 -> 535.61652 | H19: =F19*G19*(10^-3)*365 -> 56.695009 | I19: ='3B Manejo de Estiércol CH4'!H17 -> 0 | J19: ='3B Manejo de Estiércol CH4'!I17 -> 0.035714286 | K19: ='3B Manejo de Estiércol CH4'!J17 -> 0.57142857 | L19: ='3B Manejo de Estiércol CH4'!K17 -> 8.3333333 | M19: ='3B Manejo de Estiércol CH4'!L17 -> 0 | N19: ='3B Manejo de Estiércol CH4'!M17 -> 91.059524 | O19: 0.45 | P19: 0.6 | Q19: 0.07 | R19: 0.48 | S19: 0.25 | T19: 0 | U19: 0.02 | V19: 0.04 | W19: 0 | X19: 0 | Y19: 0.035 | Z19: 0 | AA19: 0.014 | AB19: 0.011 | AC19: =(E19*H19*I19%*O19)+(E19*H19*J19%*P19)+(E19*H19*K19%*Q19)+(E19*H19*L19%*R19)+(E19*H19*M19%*S19)+(E19*H19*N19%*T19) -> 169395.44 | AD19: =(E19*H19*I19%*U19)+(E19*H19*J19%*V19)+(E19*H19*K19%*W19)+(E19*H19*L19%*X19)+(E19*H19*M19%*Y19)+(E19*H19*N19%*Z19) -> 59.583342 | AE19: =AC19*AA19*(44/28) -> 3726.6997 | AF19: =AD19*AB19*(44/28) -> 1.0299406 | AG19: =AE19+AF19 -> 3727.7297 | AK19: 0.02 | AL19: 0.04 | AM19: 0 | AN19: 0 | AO19: 0.035 | AP19: 0
D20: Amazonia | E20: ='3A1 Fermentación E.'!D18 -> 28493.155 | F20: ='3B Gestión Estiércol N2O Dir'!F20 -> 0.29 | G20: ='3B Manejo de Estiércol CH4'!F18 -> 460.03682 | H20: =F20*G20*(10^-3)*365 -> 48.694897 | I20: ='3B Manejo de Estiércol CH4'!H18 -> 0 | J20: ='3B Manejo de Estiércol CH4'!I18 -> 0 | K20: ='3B Manejo de Estiércol CH4'!J18 -> 2.173913 | L20: ='3B Manejo de Estiércol CH4'!K18 -> 0 | M20: ='3B Manejo de Estiércol CH4'!L18 -> 0 | N20: ='3B Manejo de Estiércol CH4'!M18 -> 97.826087 | O20: 0.45 | P20: 0.6 | Q20: 0.07 | R20: 0.48 | S20: 0.25 | T20: 0 | U20: 0.02 | V20: 0.04 | W20: 0 | X20: 0 | Y20: 0.035 | Z20: 0 | AA20: 0.014 | AB20: 0.011 | AC20: =(E20*H20*I20%*O20)+(E20*H20*J20%*P20)+(E20*H20*K20%*Q20)+(E20*H20*L20%*R20)+(E20*H20*M20%*S20)+(E20*H20*N20%*T20) -> 2111.3693 | AD20: =(E20*H20*I20%*U20)+(E20*H20*J20%*V20)+(E20*H20*K20%*W20)+(E20*H20*L20%*X20)+(E20*H20*M20%*Y20)+(E20*H20*N20%*Z20) -> 0 | AE20: =AC20*AA20*(44/28) -> 46.450125 | AF20: =AD20*AB20*(44/28) -> 0 | AG20: =AE20+AF20 -> 46.450125 | AK20: 0.02 | AL20: 0.04 | AM20: 0 | AN20: 0 | AO20: 0.035 | AP20: 0
C21: No Lechero Vacas | D21: Sierra | E21: ='3A1 Fermentación E.'!D19 -> 250720.67 | F21: ='3B Gestión Estiércol N2O Dir'!F21 -> 0.29 | G21: ='3B Manejo de Estiércol CH4'!F19 -> 375.7196 | H21: =F21*G21*(10^-3)*365 -> 39.769919 | I21: ='3B Manejo de Estiércol CH4'!H19 -> 0 | J21: ='3B Manejo de Estiércol CH4'!I19 -> 4.8148148 | K21: ='3B Manejo de Estiércol CH4'!J19 -> 0.12222222 | L21: ='3B Manejo de Estiércol CH4'!K19 -> 0 | M21: ='3B Manejo de Estiércol CH4'!L19 -> 0 | N21: ='3B Manejo de Estiércol CH4'!M19 -> 95.062963 | O21: 0.45 | P21: 0.6 | Q21: 0.07 | R21: 0.48 | S21: 0.25 | T21: 0 | U21: 0.02 | V21: 0.04 | W21: 0 | X21: 0 | Y21: 0.035 | Z21: 0 | AA21: 0.005 | AB21: 0.011 | AC21: =(E21*H21*I21%*O21)+(E21*H21*J21%*P21)+(E21*H21*K21%*Q21)+(E21*H21*L21%*R21)+(E21*H21*M21%*S21)+(E21*H21*N21%*T21) -> 288908.26 | AD21: =(E21*H21*I21%*U21)+(E21*H21*J21%*V21)+(E21*H21*K21%*W21)+(E21*H21*L21%*X21)+(E21*H21*M21%*Y21)+(E21*H21*N21%*Z21) -> 19203.678 | AE21: =AC21*AA21*(44/28) -> 2269.9935 | AF21: =AD21*AB21*(44/28) -> 331.9493 | AG21: =AE21+AF21 -> 2601.9428 | AK21: 0.02 | AL21: 0.04 | AM21: 0 | AN21: 0 | AO21: 0.035 | AP21: 0
D22: Costa | E22: ='3A1 Fermentación E.'!D20 -> 401964.14 | F22: ='3B Gestión Estiércol N2O Dir'!F22 -> 0.29 | G22: ='3B Manejo de Estiércol CH4'!F20 -> 430.60864 | H22: =F22*G22*(10^-3)*365 -> 45.579924 | I22: ='3B Manejo de Estiércol CH4'!H20 -> 0 | J22: ='3B Manejo de Estiércol CH4'!I20 -> 0.035714286 | K22: ='3B Manejo de Estiércol CH4'!J20 -> 0.57142857 | L22: ='3B Manejo de Estiércol CH4'!K20 -> 8.3333333 | M22: ='3B Manejo de Estiércol CH4'!L20 -> 0 | N22: ='3B Manejo de Estiércol CH4'!M20 -> 91.059524 | O22: 0.45 | P22: 0.6 | Q22: 0.07 | R22: 0.48 | S22: 0.25 | T22: 0 | U22: 0.02 | V22: 0.04 | W22: 0 | X22: 0 | Y22: 0.035 | Z22: 0 | AA22: 0.014 | AB22: 0.011 | AC22: =(E22*H22*I22%*O22)+(E22*H22*J22%*P22)+(E22*H22*K22%*Q22)+(E22*H22*L22%*R22)+(E22*H22*M22%*S22)+(E22*H22*N22%*T22) -> 744114.43 | AD22: =(E22*H22*I22%*U22)+(E22*H22*J22%*V22)+(E22*H22*K22%*W22)+(E22*H22*L22%*X22)+(E22*H22*M22%*Y22)+(E22*H22*N22%*Z22) -> 261.73564 | AE22: =AC22*AA22*(44/28) -> 16370.518 | AF22: =AD22*AB22*(44/28) -> 4.5242875 | AG22: =AE22+AF22 -> 16375.042 | AK22: 0.02 | AL22: 0.04 | AM22: 0 | AN22: 0 | AO22: 0.035 | AP22: 0
D23: Amazonia | E23: ='3A1 Fermentación E.'!D21 -> 74474.301 | F23: ='3B Gestión Estiércol N2O Dir'!F23 -> 0.29 | G23: ='3B Manejo de Estiércol CH4'!F21 -> 427.92286 | H23: =F23*G23*(10^-3)*365 -> 45.295635 | I23: ='3B Manejo de Estiércol CH4'!H21 -> 0 | J23: ='3B Manejo de Estiércol CH4'!I21 -> 0 | K23: ='3B Manejo de Estiércol CH4'!J21 -> 2.173913 | L23: ='3B Manejo de Estiércol CH4'!K21 -> 0 | M23: ='3B Manejo de Estiércol CH4'!L21 -> 0 | N23: ='3B Manejo de Estiércol CH4'!M21 -> 97.826087 | O23: 0.45 | P23: 0.6 | Q23: 0.07 | R23: 0.48 | S23: 0.25 | T23: 0 | U23: 0.02 | V23: 0.04 | W23: 0 | X23: 0 | Y23: 0.035 | Z23: 0 | AA23: 0.014 | AB23: 0.011 | AC23: =(E23*H23*I23%*O23)+(E23*H23*J23%*P23)+(E23*H23*K23%*Q23)+(E23*H23*L23%*R23)+(E23*H23*M23%*S23)+(E23*H23*N23%*T23) -> 5133.375 | AD23: =(E23*H23*I23%*U23)+(E23*H23*J23%*V23)+(E23*H23*K23%*W23)+(E23*H23*L23%*X23)+(E23*H23*M23%*Y23)+(E23*H23*N23%*Z23) -> 0 | AE23: =AC23*AA23*(44/28) -> 112.93425 | AF23: =AD23*AB23*(44/28) -> 0 | AG23: =AE23+AF23 -> 112.93425 | AK23: 0.02 | AL23: 0.04 | AM23: 0 | AN23: 0 | AO23: 0.035 | AP23: 0
C24: No Lechero En crecimiento | D24: Sierra | E24: ='3A1 Fermentación E.'!D22 -> 1036600.5 | F24: ='3B Gestión Estiércol N2O Dir'!F24 -> 0.29 | G24: ='3B Manejo de Estiércol CH4'!F22 -> 165.49943 | H24: =F24*G24*(10^-3)*365 -> 17.518115 | I24: ='3B Manejo de Estiércol CH4'!H22 -> 0 | J24: ='3B Manejo de Estiércol CH4'!I22 -> 4.8148148 | K24: ='3B Manejo de Estiércol CH4'!J22 -> 0.12222222 | L24: ='3B Manejo de Estiércol CH4'!K22 -> 0 | M24: ='3B Manejo de Estiércol CH4'!L22 -> 0 | N24: ='3B Manejo de Estiércol CH4'!M22 -> 95.062963 | O24: 0.45 | P24: 0.6 | Q24: 0.07 | R24: 0.48 | S24: 0.25 | T24: 0 | U24: 0.02 | V24: 0.04 | W24: 0 | X24: 0 | Y24: 0.035 | Z24: 0 | AA24: 0.005 | AB24: 0.011 | AC24: =(E24*H24*I24%*O24)+(E24*H24*J24%*P24)+(E24*H24*K24%*Q24)+(E24*H24*L24%*R24)+(E24*H24*M24%*S24)+(E24*H24*N24%*T24) -> 526155.22 | AD24: =(E24*H24*I24%*U24)+(E24*H24*J24%*V24)+(E24*H24*K24%*W24)+(E24*H24*L24%*X24)+(E24*H24*M24%*Y24)+(E24*H24*N24%*Z24) -> 34973.439 | AE24: =AC24*AA24*(44/28) -> 4134.0767 | AF24: =AD24*AB24*(44/28) -> 604.54088 | AG24: =AE24+AF24 -> 4738.6176 | AK24: 0.02 | AL24: 0.04 | AM24: 0 | AN24: 0 | AO24: 0.035 | AP24: 0
D25: Costa | E25: ='3A1 Fermentación E.'!D23 -> 984149.28 | F25: ='3B Gestión Estiércol N2O Dir'!F25 -> 0.29 | G25: ='3B Manejo de Estiércol CH4'!F23 -> 174.42759 | H25: =F25*G25*(10^-3)*365 -> 18.46316 | I25: ='3B Manejo de Estiércol CH4'!H23 -> 0 | J25: ='3B Manejo de Estiércol CH4'!I23 -> 0.035714286 | K25: ='3B Manejo de Estiércol CH4'!J23 -> 0.57142857 | L25: ='3B Manejo de Estiércol CH4'!K23 -> 8.3333333 | M25: ='3B Manejo de Estiércol CH4'!L23 -> 0 | N25: ='3B Manejo de Estiércol CH4'!M23 -> 91.059524 | O25: 0.45 | P25: 0.6 | Q25: 0.07 | R25: 0.48 | S25: 0.25 | T25: 0 | U25: 0.02 | V25: 0.04 | W25: 0 | X25: 0 | Y25: 0.035 | Z25: 0 | AA25: 0.014 | AB25: 0.011 | AC25: =(E25*H25*I25%*O25)+(E25*H25*J25%*P25)+(E25*H25*K25%*Q25)+(E25*H25*L25%*R25)+(E25*H25*M25%*S25)+(E25*H25*N25%*T25) -> 737982.12 | AD25: =(E25*H25*I25%*U25)+(E25*H25*J25%*V25)+(E25*H25*K25%*W25)+(E25*H25*L25%*X25)+(E25*H25*M25%*Y25)+(E25*H25*N25%*Z25) -> 259.57866 | AE25: =AC25*AA25*(44/28) -> 16235.607 | AF25: =AD25*AB25*(44/28) -> 4.4870025 | AG25: =AE25+AF25 -> 16240.094 | AK25: 0.02 | AL25: 0.04 | AM25: 0 | AN25: 0 | AO25: 0.035 | AP25: 0
D26: Amazonia | E26: ='3A1 Fermentación E.'!D24 -> 220534.27 | F26: ='3B Gestión Estiércol N2O Dir'!F26 -> 0.29 | G26: ='3B Manejo de Estiércol CH4'!F24 -> 174.58749 | H26: =F26*G26*(10^-3)*365 -> 18.480085 | I26: ='3B Manejo de Estiércol CH4'!H24 -> 0 | J26: ='3B Manejo de Estiércol CH4'!I24 -> 0 | K26: ='3B Manejo de Estiércol CH4'!J24 -> 2.173913 | L26: ='3B Manejo de Estiércol CH4'!K24 -> 0 | M26: ='3B Manejo de Estiércol CH4'!L24 -> 0 | N26: ='3B Manejo de Estiércol CH4'!M24 -> 97.826087 | O26: 0.45 | P26: 0.6 | Q26: 0.07 | R26: 0.48 | S26: 0.3 | T26: 0 | U26: 0.02 | V26: 0.04 | W26: 0 | X26: 0 | Y26: 0.035 | Z26: 0 | AA26: 0.014 | AB26: 0.011 | AC26: =(E26*H26*I26%*O26)+(E26*H26*J26%*P26)+(E26*H26*K26%*Q26)+(E26*H26*L26%*R26)+(E26*H26*M26%*S26)+(E26*H26*N26%*T26) -> 6201.836 | AD26: =(E26*H26*I26%*U26)+(E26*H26*J26%*V26)+(E26*H26*K26%*W26)+(E26*H26*L26%*X26)+(E26*H26*M26%*Y26)+(E26*H26*N26%*Z26) -> 0 | AE26: =AC26*AA26*(44/28) -> 136.44039 | AF26: =AD26*AB26*(44/28) -> 0 | AG26: =AE26+AF26 -> 136.44039 | AK26: 0.02 | AL26: 0.04 | AM26: 0 | AN26: 0 | AO26: 0.035 | AP26: 0
C27: Búfalos | E27: ='3A1 Fermentación E.'!D25 -> 3839 | F27: ='3B Gestión Estiércol N2O Dir'!F27 -> 0.41 | G27: ='3B Manejo de Estiércol CH4'!F25 -> 315 | H27: =F27*G27*(10^-3)*365 -> 47.13975 | I27: ='3B Manejo de Estiércol CH4'!H25 -> 2 | J27: ='3B Manejo de Estiércol CH4'!I25 -> 0 | K27: ='3B Manejo de Estiércol CH4'!J25 -> 0 | L27: ='3B Manejo de Estiércol CH4'!K25 -> 0 | M27: ='3B Manejo de Estiércol CH4'!L25 -> 5 | N27: ='3B Manejo de Estiércol CH4'!M25 -> 93 | O27: 0.12 | P27: 0.18 | Q27: 0.07 | R27: 0.15 | S27: 0.3 | T27: 0 | U27: 0.02 | V27: 0.04 | W27: 0 | X27: 0 | Y27: 0.035 | Z27: 0 | AA27: 0.01 | AB27: 0.011 | AC27: =(E27*H27*I27%*O27)+(E27*H27*J27%*P27)+(E27*H27*K27%*Q27)+(E27*H27*L27%*R27)+(E27*H27*M27%*S27)+(E27*H27*N27%*T27) -> 3148.8693 | AD27: =(E27*H27*I27%*U27)+(E27*H27*J27%*V27)+(E27*H27*K27%*W27)+(E27*H27*L27%*X27)+(E27*H27*M27%*Y27)+(E27*H27*N27%*Z27) -> 389.08443 | AE27: =AC27*AA27*(44/28) -> 49.482232 | AF27: =AD27*AB27*(44/28) -> 6.7256022 | AG27: =AE27+AF27 -> 56.207834 | AK27: 0.02 | AL27: 0.04 | AM27: 0 | AN27: 0 | AO27: 0.035 | AP27: 0
C28: Ovejas | E28: ='3A1 Fermentación E.'!D26 -> 498952.01 | F28: ='3B Gestión Estiércol N2O Dir'!F28 -> 0.32 | G28: ='3B Manejo de Estiércol CH4'!F26 -> 31 | H28: =F28*G28*(10^-3)*365 -> 3.6208 | I28: ='3B Manejo de Estiércol CH4'!H26 -> 17 | J28: ='3B Manejo de Estiércol CH4'!I26 -> 3 | K28: ='3B Manejo de Estiércol CH4'!J26 -> 0 | L28: ='3B Manejo de Estiércol CH4'!K26 -> 0 | M28: ='3B Manejo de Estiércol CH4'!L26 -> 0 | N28: ='3B Manejo de Estiércol CH4'!M26 -> 80 | O28: 0.12 | P28: 0.18 | Q28: 0.07 | R28: 0.15 | S28: 0.3 | T28: 0 | U28: 0.02 | V28: 0.04 | W28: 0 | X28: 0 | Y28: 0.035 | Z28: 0 | AA28: 0.01 | AB28: 0.011 | AC28: =(E28*H28*I28%*O28)+(E28*H28*J28%*P28)+(E28*H28*K28%*Q28)+(E28*H28*L28%*R28)+(E28*H28*M28%*S28)+(E28*H28*N28%*T28) -> 46610.421 | AD28: =(E28*H28*I28%*U28)+(E28*H28*J28%*V28)+(E28*H28*K28%*W28)+(E28*H28*L28%*X28)+(E28*H28*M28%*Y28)+(E28*H28*N28%*Z28) -> 8310.3851 | AE28: =AC28*AA28*(44/28) -> 732.44947 | AF28: =AD28*AB28*(44/28) -> 143.65094 | AG28: =AE28+AF28 -> 876.10041 | AK28: 0.02 | AL28: 0.04 | AM28: 0 | AN28: 0 | AO28: 0.035 | AP28: 0
C29: Cabras | E29: ='3A1 Fermentación E.'!D27 -> 21745.307 | F29: ='3B Gestión Estiércol N2O Dir'!F29 -> 0.34 | G29: ='3B Manejo de Estiércol CH4'!F27 -> 24 | H29: =F29*G29*(10^-3)*365 -> 2.9784 | I29: ='3B Manejo de Estiércol CH4'!H27 -> 17 | J29: ='3B Manejo de Estiércol CH4'!I27 -> 3 | K29: ='3B Manejo de Estiércol CH4'!J27 -> 0 | L29: ='3B Manejo de Estiércol CH4'!K27 -> 0 | M29: ='3B Manejo de Estiércol CH4'!L27 -> 0 | N29: ='3B Manejo de Estiércol CH4'!M27 -> 80 | O29: 0.12 | P29: 0.18 | Q29: 0.07 | R29: 0.15 | S29: 0.3 | T29: 0 | U29: 0.02 | V29: 0.04 | W29: 0 | X29: 0 | Y29: 0.035 | Z29: 0 | AA29: 0.01 | AB29: 0.011 | AC29: =(E29*H29*I29%*O29)+(E29*H29*J29%*P29)+(E29*H29*K29%*Q29)+(E29*H29*L29%*R29)+(E29*H29*M29%*S29)+(E29*H29*N29%*T29) -> 1670.9685 | AD29: =(E29*H29*I29%*U29)+(E29*H29*J29%*V29)+(E29*H29*K29%*W29)+(E29*H29*L29%*X29)+(E29*H29*M29%*Y29)+(E29*H29*N29%*Z29) -> 297.92462 | AE29: =AC29*AA29*(44/28) -> 26.258077 | AF29: =AD29*AB29*(44/28) -> 5.1498399 | AG29: =AE29+AF29 -> 31.407917 | AK29: 0.02 | AL29: 0.04 | AM29: 0 | AN29: 0 | AO29: 0.035 | AP29: 0
C30: Camélidos sudamericanos | E30: ='3A1 Fermentación E.'!D28 -> 20949.783 | F30: ='3B Gestión Estiércol N2O Dir'!F30 -> 0.46 | G30: ='3B Manejo de Estiércol CH4'!F28 -> 65 | H30: =F30*G30*(10^-3)*365 -> 10.9135 | I30: ='3B Manejo de Estiércol CH4'!H28 -> 17 | J30: ='3B Manejo de Estiércol CH4'!I28 -> 3 | K30: ='3B Manejo de Estiércol CH4'!J28 -> 0 | L30: ='3B Manejo de Estiércol CH4'!K28 -> 0 | M30: ='3B Manejo de Estiércol CH4'!L28 -> 0 | N30: ='3B Manejo de Estiércol CH4'!M28 -> 80 | O30: 0.12 | P30: 0.18 | Q30: 0.07 | R30: 0.15 | S30: 0.3 | T30: 0 | U30: 0.02 | V30: 0.04 | W30: 0 | X30: 0 | Y30: 0.035 | Z30: 0 | AA30: 0.01 | AB30: 0.011 | AC30: =(E30*H30*I30%*O30)+(E30*H30*J30%*P30)+(E30*H30*K30%*Q30)+(E30*H30*L30%*R30)+(E30*H30*M30%*S30)+(E30*H30*N30%*T30) -> 5898.7949 | AD30: =(E30*H30*I30%*U30)+(E30*H30*J30%*V30)+(E30*H30*K30%*W30)+(E30*H30*L30%*X30)+(E30*H30*M30%*Y30)+(E30*H30*N30%*Z30) -> 1051.7231 | AE30: =AC30*AA30*(44/28) -> 92.695348 | AF30: =AD30*AB30*(44/28) -> 18.179785 | AG30: =AE30+AF30 -> 110.87513 | AK30: 0.02 | AL30: 0.04 | AM30: 0 | AN30: 0 | AO30: 0.035 | AP30: 0
C31: Caballos | E31: ='3A1 Fermentación E.'!D29 -> 260479.02 | F31: ='3B Gestión Estiércol N2O Dir'!F31 -> 0.46 | G31: ='3B Manejo de Estiércol CH4'!F29 -> 238 | H31: =F31*G31*(10^-3)*365 -> 39.9602 | I31: ='3B Manejo de Estiércol CH4'!H29 -> 17 | J31: ='3B Manejo de Estiércol CH4'!I29 -> 3 | K31: ='3B Manejo de Estiércol CH4'!J29 -> 0 | L31: ='3B Manejo de Estiércol CH4'!K29 -> 0 | M31: ='3B Manejo de Estiércol CH4'!L29 -> 0 | N31: ='3B Manejo de Estiércol CH4'!M29 -> 80 | O31: 0.12 | P31: 0.18 | Q31: 0.07 | R31: 0.15 | S31: 0.3 | T31: 0 | U31: 0.02 | V31: 0.04 | W31: 0 | X31: 0 | Y31: 0.035 | Z31: 0 | AA31: 0.01 | AB31: 0.011 | AC31: =(E31*H31*I31%*O31)+(E31*H31*J31%*P31)+(E31*H31*K31%*Q31)+(E31*H31*L31%*R31)+(E31*H31*M31%*S31)+(E31*H31*N31%*T31) -> 268546.88 | AD31: =(E31*H31*I31%*U31)+(E31*H31*J31%*V31)+(E31*H31*K31%*W31)+(E31*H31*L31%*X31)+(E31*H31*M31%*Y31)+(E31*H31*N31%*Z31) -> 47880.451 | AE31: =AC31*AA31*(44/28) -> 4220.0223 | AF31: =AD31*AB31*(44/28) -> 827.64779 | AG31: =AE31+AF31 -> 5047.6701 | AK31: 0.02 | AL31: 0.04 | AM31: 0 | AN31: 0 | AO31: 0.035 | AP31: 0
C32: Mulas & Asnos | E32: ='3A1 Fermentación E.'!D30 -> 147168.66 | F32: ='3B Gestión Estiércol N2O Dir'!F32 -> 0.46 | G32: ='3B Manejo de Estiércol CH4'!F30 -> 130 | H32: =F32*G32*(10^-3)*365 -> 21.827 | I32: ='3B Manejo de Estiércol CH4'!H30 -> 17 | J32: ='3B Manejo de Estiércol CH4'!I30 -> 3 | K32: ='3B Manejo de Estiércol CH4'!J30 -> 0 | L32: ='3B Manejo de Estiércol CH4'!K30 -> 0 | M32: ='3B Manejo de Estiércol CH4'!L30 -> 0 | N32: ='3B Manejo de Estiércol CH4'!M30 -> 80 | O32: 0.12 | P32: 0.18 | Q32: 0.07 | R32: 0.15 | S32: 0.3 | T32: 0 | U32: 0.02 | V32: 0.04 | W32: 0 | X32: 0 | Y32: 0.035 | Z32: 0 | AA32: 0.01 | AB32: 0.011 | AC32: =(E32*H32*I32%*O32)+(E32*H32*J32%*P32)+(E32*H32*K32%*Q32)+(E32*H32*L32%*R32)+(E32*H32*M32%*S32)+(E32*H32*N32%*T32) -> 82876.061 | AD32: =(E32*H32*I32%*U32)+(E32*H32*J32%*V32)+(E32*H32*K32%*W32)+(E32*H32*L32%*X32)+(E32*H32*M32%*Y32)+(E32*H32*N32%*Z32) -> 14776.352 | AE32: =AC32*AA32*(44/28) -> 1302.3381 | AF32: =AD32*AB32*(44/28) -> 255.4198 | AG32: =AE32+AF32 -> 1557.7579 | AK32: 0.02 | AL32: 0.04 | AM32: 0 | AN32: 0 | AO32: 0.035 | AP32: 0
C33: Cerdos | E33: ='3A1 Fermentación E.'!D31 -> 1682662 | F33: ='3B Gestión Estiércol N2O Dir'!F33 -> 0.67 | G33: ='3B Manejo de Estiércol CH4'!F31 -> 59 | H33: =F33*G33*(10^-3)*365 -> 14.42845 | I33: ='3B Manejo de Estiércol CH4'!H31 -> 15 | J33: ='3B Manejo de Estiércol CH4'!I31 -> 5 | K33: ='3B Manejo de Estiércol CH4'!J31 -> 5 | L33: ='3B Manejo de Estiércol CH4'!K31 -> 30 | M33: ='3B Manejo de Estiércol CH4'!L31 -> 40 | N33: ='3B Manejo de Estiércol CH4'!M31 -> 5 | O33: 0.45 | P33: 0.6 | Q33: 0.07 | R33: 0.2 | S33: 0.45 | T33: 0 | U33: 0.02 | V33: 0.04 | W33: 0 | X33: 0 | Y33: 0.035 | Z33: 0 | AA33: 0.01 | AB33: 0.011 | AC33: =(E33*H33*I33%*O33)+(E33*H33*J33%*P33)+(E33*H33*K33%*Q33)+(E33*H33*L33%*R33)+(E33*H33*M33%*S33)+(E33*H33*N33%*T33) -> 8278867.9 | AD33: =(E33*H33*I33%*U33)+(E33*H33*J33%*V33)+(E33*H33*K33%*W33)+(E33*H33*L33%*X33)+(E33*H33*M33%*Y33)+(E33*H33*N33%*Z33) -> 461285.9 | AE33: =AC33*AA33*(44/28) -> 130096.5 | AF33: =AD33*AB33*(44/28) -> 7973.6562 | AG33: =AE33+AF33 -> 138070.15 | AK33: 0.02 | AL33: 0.04 | AM33: 0 | AN33: 0 | AO33: 0.035 | AP33: 0
C34: Aves de engorde | E34: ='3A1 Fermentación E.'!D32 -> 30205479 | F34: ='3B Gestión Estiércol N2O Dir'!F34 -> 1.2 | G34: ='3B Manejo de Estiércol CH4'!F32 -> 0.9 | H34: =F34*G34*(10^-3)*365 -> 0.3942 | I34: ='3B Manejo de Estiércol CH4'!H32 -> 0 | J34: ='3B Manejo de Estiércol CH4'!I32 -> 0 | K34: ='3B Manejo de Estiércol CH4'!J32 -> 0 | L34: ='3B Manejo de Estiércol CH4'!K32 -> 0 | M34: ='3B Manejo de Estiércol CH4'!L32 -> 100 | N34: ='3B Manejo de Estiércol CH4'!M32 -> 0 | O34: 0.4 | P34: 0.6 | Q34: 0.07 | R34: 0.18 | S34: 0.4 | T34: 0 | U34: 0.02 | V34: 0.04 | W34: 0 | X34: 0 | Y34: 0 | Z34: 0 | AA34: 0.01 | AB34: 0.011 | AC34: =(E34*H34*I34%*O34)+(E34*H34*J34%*P34)+(E34*H34*K34%*Q34)+(E34*H34*L34%*R34)+(E34*H34*M34%*S34)+(E34*H34*N34%*T34) -> 4762800 | AD34: =(E34*H34*I34%*U34)+(E34*H34*J34%*V34)+(E34*H34*K34%*W34)+(E34*H34*L34%*X34)+(E34*H34*M34%*Y34)+(E34*H34*N34%*Z34) -> 0 | AE34: =AC34*AA34*(44/28) -> 74844 | AF34: =AD34*AB34*(44/28) -> 0 | AG34: =AE34+AF34 -> 74844 | AK34: 0.02 | AL34: 0.04 | AM34: 0 | AN34: 0 | AO34: 0 | AP34: 0
C35: Ponedoras | E35: ='3A1 Fermentación E.'!D33 -> 13510000 | F35: ='3B Gestión Estiércol N2O Dir'!F35 -> 2.01 | G35: ='3B Manejo de Estiércol CH4'!F33 -> 1.4 | H35: =F35*G35*(10^-3)*365 -> 1.02711 | I35: ='3B Manejo de Estiércol CH4'!H33 -> 42 | J35: ='3B Manejo de Estiércol CH4'!I33 -> 0 | K35: ='3B Manejo de Estiércol CH4'!J33 -> 0 | L35: ='3B Manejo de Estiércol CH4'!K33 -> 58 | M35: ='3B Manejo de Estiércol CH4'!L33 -> 0 | N35: ='3B Manejo de Estiércol CH4'!M33 -> 0 | O35: 0.4 | P35: 0.6 | Q35: 0.07 | R35: 0.18 | S35: 0.4 | T35: 0 | U35: 0.02 | V35: 0.04 | W35: 0 | X35: 0 | Y35: 0 | Z35: 0 | AA35: 0.01 | AB35: 0.011 | AC35: =(E35*H35*I35%*O35)+(E35*H35*J35%*P35)+(E35*H35*K35%*Q35)+(E35*H35*L35%*R35)+(E35*H35*M35%*S35)+(E35*H35*N35%*T35) -> 3779892.2 | AD35: =(E35*H35*I35%*U35)+(E35*H35*J35%*V35)+(E35*H35*K35%*W35)+(E35*H35*L35%*X35)+(E35*H35*M35%*Y35)+(E35*H35*N35%*Z35) -> 116560.55 | AE35: =AC35*AA35*(44/28) -> 59398.305 | AF35: =AD35*AB35*(44/28) -> 2014.8324 | AG35: =AE35+AF35 -> 61413.138 | AK35: 0.02 | AL35: 0.04 | AM35: 0 | AN35: 0 | AO35: 0 | AP35: 0
C36: Patos | E36: ='3A1 Fermentación E.'!D34 -> 70291.656 | F36: ='3B Gestión Estiércol N2O Dir'!F36 -> 0.83 | G36: ='3B Manejo de Estiércol CH4'!F34 -> 2.7 | H36: =F36*G36*(10^-3)*365 -> 0.817965 | I36: ='3B Manejo de Estiércol CH4'!H34 -> 0 | J36: ='3B Manejo de Estiércol CH4'!I34 -> 0 | K36: ='3B Manejo de Estiércol CH4'!J34 -> 0 | L36: ='3B Manejo de Estiércol CH4'!K34 -> 0 | M36: ='3B Manejo de Estiércol CH4'!L34 -> 100 | N36: ='3B Manejo de Estiércol CH4'!M34 -> 0 | O36: 0.4 | P36: 0.6 | Q36: 0.07 | R36: 0.18 | S36: 0.4 | T36: 0 | U36: 0.02 | V36: 0.04 | W36: 0 | X36: 0 | Y36: 0 | Z36: 0 | AA36: 0.01 | AB36: 0.011 | AC36: =(E36*H36*I36%*O36)+(E36*H36*J36%*P36)+(E36*H36*K36%*Q36)+(E36*H36*L36%*R36)+(E36*H36*M36%*S36)+(E36*H36*N36%*T36) -> 22998.446 | AD36: =(E36*H36*I36%*U36)+(E36*H36*J36%*V36)+(E36*H36*K36%*W36)+(E36*H36*L36%*X36)+(E36*H36*M36%*Y36)+(E36*H36*N36%*Z36) -> 0 | AE36: =AC36*AA36*(44/28) -> 361.40415 | AF36: =AD36*AB36*(44/28) -> 0 | AG36: =AE36+AF36 -> 361.40415 | AK36: 0.02 | AL36: 0.04 | AM36: 0 | AN36: 0 | AO36: 0 | AP36: 0
C37: Pavos | E37: ='3A1 Fermentación E.'!D35 -> 198716.81 | F37: ='3B Gestión Estiércol N2O Dir'!F37 -> 0.74 | G37: ='3B Manejo de Estiércol CH4'!F35 -> 6.8 | H37: =F37*G37*(10^-3)*365 -> 1.83668 | I37: ='3B Manejo de Estiércol CH4'!H35 -> 0 | J37: ='3B Manejo de Estiércol CH4'!I35 -> 0 | K37: ='3B Manejo de Estiércol CH4'!J35 -> 0 | L37: ='3B Manejo de Estiércol CH4'!K35 -> 0 | M37: ='3B Manejo de Estiércol CH4'!L35 -> 100 | N37: ='3B Manejo de Estiércol CH4'!M35 -> 0 | O37: 0.4 | P37: 0.6 | Q37: 0.07 | R37: 0.18 | S37: 0.4 | T37: 0 | U37: 0.02 | V37: 0.04 | W37: 0 | X37: 0 | Y37: 0 | Z37: 0 | AA37: 0.01 | AB37: 0.011 | AC37: =(E37*H37*I37%*O37)+(E37*H37*J37%*P37)+(E37*H37*K37%*Q37)+(E37*H37*L37%*R37)+(E37*H37*M37%*S37)+(E37*H37*N37%*T37) -> 145991.68 | AD37: =(E37*H37*I37%*U37)+(E37*H37*J37%*V37)+(E37*H37*K37%*W37)+(E37*H37*L37%*X37)+(E37*H37*M37%*Y37)+(E37*H37*N37%*Z37) -> 0 | AE37: =AC37*AA37*(44/28) -> 2294.1549 | AF37: =AD37*AB37*(44/28) -> 0 | AG37: =AE37+AF37 -> 2294.1549 | AK37: 0.02 | AL37: 0.04 | AM37: 0 | AN37: 0 | AO37: 0 | AP37: 0
B38: Total | E38: =SUM(E15:E37) -> 50677079 | AE38: =SUM(AE15:AE37) -> 336646.2 | AF38: =SUM(AF15:AF37) -> 15119.824 | AG38: =AE38+AF38 -> 351766.02
C39: (*) Para la variable de nitrogeno agregado vía co-digestión en sistemas de digestión anaeróbica no se cuentan con datos anuales nacionales, y aun cuando el Proyecto GCI detalla un % minimo de gestión de estiércol en estos sistemas para bovinos, el mismo es irrelevante respecto del total, por lo que se omite en la fórmula de cálculo
C42: NOTA EXPLICATIVA DE FUENTES Y OTRAS CONSIDERACIONES DE LOS DATOS
C43: TIPO DE GANADO | E43: DATO DE ACTIVIDAD | F43: N ratio | G43: TAM | H43: Fracción AWMS | I43: Fracción volatilización | J43: Fracción lixiviación | K43: FACTOR DE EMISIÓN volatilización | L43: FACTOR DE EMISIÓN lixiviación
C44: Ganado Lechero | E44: ESPAC 2018 , tabla 67 | F44: Se obtiene por defecto de la tabla 10.19 directrices IPCC V4 CH 10, para ganado de la sierra se considera productividad media, en tanto para las otras regiones se considera productividad baja | G44: Dato propio del país según registros de proyecto GCI por región | H44: Valor propio del país según registros proyecto GCI por región, se promedian modos de producción | I44: Fracción correspondiente a cada sistema de gestión, considerando datos promedio según diferencias de las 3 regiones del país, datos por defecto tabla 10.22 V4 CH10 | J44: Fracción correspondiente a cada sistema de gestión, considerando datos promedio según diferencias de las 3 regiones del país, datos por defecto tabla 10.22 V4 CH10 | K44: Factor de emisión por defecto tablas 11.3 directrices IPCC V4 CH11, considera clima mojado para costa y amazonia y clima seco para sierra | L44: Factor de emisión por defecto tablas 11.3 directrices IPCC V4 CH11, considera valor agregado por default | M44: .
C45: No LecheroToros | E45: ESPAC 2018, tabla 50 | F45: Se obtiene por defecto de la tabla 10.19 directrices IPCC V4 CH 10, para ganado de la sierra se considera productividad media, en tanto para las otras regiones se considera productividad baja | G45: Dato propio del país según registros de proyecto GCI por región | H45: Valor propio del país según registros proyecto GCI por región, se promedian modos de producción | I45: Fracción correspondiente a cada sistema de gestión, considerando datos promedio según diferencias de las 3 regiones del país, datos por defecto tabla 10.22 V4 CH11 | J45: Fracción correspondiente a cada sistema de gestión, considerando datos promedio según diferencias de las 3 regiones del país, datos por defecto tabla 10.22 V4 CH11 | K45: Factor de emisión por defecto tablas 11.3 directrices IPCC V4 CH11, considera clima mojado para costa y amazonia y clima seco para sierra | L45: Factor de emisión por defecto tablas 11.3 directrices IPCC V4 CH11, considera valor agregado por default | M45: .
C46: No Lechero Vacas | E46: ESPAC 2018, tabla 50 | F46: Se obtiene por defecto de la tabla 10.19 directrices IPCC V4 CH 10, para ganado de la sierra se considera productividad media, en tanto para las otras regiones se considera productividad baja | G46: Dato propio del país según registros de proyecto GCI por región | H46: Valor propio del país según registros proyecto GCI por región, se promedian modos de producción | I46: Fracción correspondiente a cada sistema de gestión, considerando datos promedio según diferencias de las 3 regiones del país, datos por defecto tabla 10.22 V4 CH12 | J46: Fracción correspondiente a cada sistema de gestión, considerando datos promedio según diferencias de las 3 regiones del país, datos por defecto tabla 10.22 V4 CH12 | K46: Factor de emisión por defecto tablas 11.3 directrices IPCC V4 CH11, considera clima mojado para costa y amazonia y clima seco para sierra | L46: Factor de emisión por defecto tablas 11.3 directrices IPCC V4 CH11, considera valor agregado por default | M46: .
C47: No Lechero En crecimiento | E47: ESPAC 2018, tabla 50 | F47: Se obtiene por defecto de la tabla 10.19 directrices IPCC V4 CH 10, para ganado de la sierra se considera productividad media, en tanto para las otras regiones se considera productividad baja | G47: Dato propio del país según registros de proyecto GCI por región, suma grupos de bovinos menores a 2 años machos y hembras | H47: Valor propio del país según registros proyecto GCI por región, se promedian modos de producción | I47: Fracción correspondiente a cada sistema de gestión, considerando valores promedio, datos por defecto tabla 10.22 V4 CH13 | J47: Fracción correspondiente a cada sistema de gestión, considerando valores promedio, datos por defecto tabla 10.22 V4 CH13 | K47: Factor de emisión por defecto tablas 11.3 directrices IPCC V4 CH11, considera clima mojado para costa y amazonia y clima seco para sierra | L47: Factor de emisión por defecto tablas 11.3 directrices IPCC V4 CH11, considera valor agregado por default | M47: .
C48: Búfalos | E48: Datos Agrocalidad, registro vacunación por fiebre aftosa. | F48: Se obtiene por defecto de la tabla 10.19 directrices IPCC V4 CH 10, para ganado de la sierra se considera productividad media, en tanto para las otras regiones se considera productividad baja | G48: Valor por defecto directrices IPCC tabla 10A.5 | H48: Valor por defecto Tablas 10A.6 a 10A.9 directrices IPCC V4, Otros al no ser relevante suma los demás sistemas no considerados individualmente | I48: Fracción correspondiente a cada sistema de gestión, considerando valores promedio, datos por defecto tabla 10.22 V4 CH14 | J48: Fracción correspondiente a cada sistema de gestión, considerando valores promedio, datos por defecto tabla 10.22 V4 CH14 | K48: Factor de emisión por defecto tablas 11.3 directrices IPCC V4 CH11, considera valor agregado por default | L48: Factor de emisión por defecto tablas 11.3 directrices IPCC V4 CH11, considera valor agregado por default | M48: .
C49: Ovejas | E49: ESPAC 2018 , tabla 60 | F49: Se obtiene por defecto de la tabla 10.19 directrices IPCC V4 CH 10, para ganado de la sierra se considera productividad media, en tanto para las otras regiones se considera productividad baja | G49: Valor por defecto directrices IPCC tabla 10A.6 | H49: Valor por defecto Tablas 10A.6 a 10A.9 directrices IPCC V4, Otros al no ser relevante suma los demás sistemas no considerados individualmente | I49: Fracción correspondiente a cada sistema de gestión, considerando valores promedio, datos por defecto tabla 10.22 V4 CH15 | J49: Fracción correspondiente a cada sistema de gestión, considerando valores promedio, datos por defecto tabla 10.22 V4 CH15 | K49: Factor de emisión por defecto tablas 11.3 directrices IPCC V4 CH11, considera valor agregado por default | L49: Factor de emisión por defecto tablas 11.3 directrices IPCC V4 CH11, considera valor agregado por default | M49: .
C50: Cabras | E50: ESPAC 2018 , tabla 61 | F50: Se obtiene por defecto de la tabla 10.19 directrices IPCC V4 CH 10, para ganado de la sierra se considera productividad media, en tanto para las otras regiones se considera productividad baja | G50: Valor por defecto directrices IPCC tabla 10A.7 | H50: Valor por defecto Tablas 10A.6 a 10A.9 directrices IPCC V4, Otros al no ser relevante suma los demás sistemas no considerados individualmente | I50: Fracción correspondiente a cada sistema de gestión, considerando valores promedio, datos por defecto tabla 10.22 V4 CH16 | J50: Fracción correspondiente a cada sistema de gestión, considerando valores promedio, datos por defecto tabla 10.22 V4 CH16 | K50: Factor de emisión por defecto tablas 11.3 directrices IPCC V4 CH11, considera valor agregado por default | L50: Factor de emisión por defecto tablas 11.3 directrices IPCC V4 CH11, considera valor agregado por default | M50: .
C51: Camélidos sudamericanos | E51: Ministerio de Agricultura, Agrocalidad, Regional Chimborazo | F51: Se obtiene por defecto de la tabla 10.19 directrices IPCC V4 CH 10, para ganado de la sierra se considera productividad media, en tanto para las otras regiones se considera productividad baja | G51: Valor por defecto directrices IPCC tabla 10A.8 | H51: Valor por defecto Tablas 10A.6 a 10A.9 directrices IPCC V4, Otros al no ser relevante suma los demás sistemas no considerados individualmente | I51: Fracción correspondiente a cada sistema de gestión, considerando valores promedio, datos por defecto tabla 10.22 V4 CH17 | J51: Fracción correspondiente a cada sistema de gestión, considerando valores promedio, datos por defecto tabla 10.22 V4 CH17 | K51: Factor de emisión por defecto tablas 11.3 directrices IPCC V4 CH11, considera valor agregado por default | L51: Factor de emisión por defecto tablas 11.3 directrices IPCC V4 CH11, considera valor agregado por default | M51: .
C52: Caballos | E52: ESPAC 2018 , tabla 61 | F52: Se obtiene por defecto de la tabla 10.19 directrices IPCC V4 CH 10, para ganado de la sierra se considera productividad media, en tanto para las otras regiones se considera productividad baja | G52: Valor por defecto directrices IPCC tabla 10A.9 | H52: Valor por defecto Tablas 10A.6 a 10A.9 directrices IPCC V4, Otros al no ser relevante suma los demás sistemas no considerados individualmente | I52: Fracción correspondiente a cada sistema de gestión, considerando valores promedio, datos por defecto tabla 10.22 V4 CH18 | J52: Fracción correspondiente a cada sistema de gestión, considerando valores promedio, datos por defecto tabla 10.22 V4 CH18 | K52: Factor de emisión por defecto tablas 11.3 directrices IPCC V4 CH11, considera valor agregado por default | L52: Factor de emisión por defecto tablas 11.3 directrices IPCC V4 CH11, considera valor agregado por default | M52: .
C53: Mulas & Asnos | E53: ESPAC 2018 , tabla 61 | F53: Se obtiene por defecto de la tabla 10.19 directrices IPCC V4 CH 10, para ganado de la sierra se considera productividad media, en tanto para las otras regiones se considera productividad baja | G53: Valor por defecto directrices IPCC tabla 10A.10 | H53: Valor por defecto Tablas 10A.6 a 10A.9 directrices IPCC V4, Otros al no ser relevante suma los demás sistemas no considerados individualmente | I53: Fracción correspondiente a cada sistema de gestión, considerando valores promedio, datos por defecto tabla 10.22 V4 CH19 | J53: Fracción correspondiente a cada sistema de gestión, considerando valores promedio, datos por defecto tabla 10.22 V4 CH19 | K53: Factor de emisión por defecto tablas 11.3 directrices IPCC V4 CH11, considera valor agregado por default | L53: Factor de emisión por defecto tablas 11.3 directrices IPCC V4 CH11, considera valor agregado por default | M53: .
C54: Cerdos | E54: ESPAC 2018 , tabla 57 | F54: Se obtiene por defecto de la tabla 10.19 directrices IPCC V4 CH 10, para ganado de la sierra se considera productividad media, en tanto para las otras regiones se considera productividad baja | G54: Valor por defecto directrices IPCC tabla 10A.11 | H54: Valor por defecto Tablas 10A.6 a 10A.9 directrices IPCC V4, Otros al no ser relevante suma los demás sistemas no considerados individualmente | I54: Fracción correspondiente a cada sistema de gestión, considerando valores promedio, datos por defecto tabla 10.22 V4 CH20 | J54: Fracción correspondiente a cada sistema de gestión, considerando valores promedio, datos por defecto tabla 10.22 V4 CH20 | K54: Factor de emisión por defecto tablas 11.3 directrices IPCC V4 CH11, considera valor agregado por default | L54: Factor de emisión por defecto tablas 11.3 directrices IPCC V4 CH11, considera valor agregado por default | M54: .
C55: Aves de engorde | E55: Datos de CONAVE | F55: Se obtiene por defecto de la tabla 10.19 directrices IPCC V4, para todas las regiones se considera productividad media (relacionando sistemas de producción referenciados en las directrices IPCC) | G55: Valor por defecto directrices IPCC tabla 10A.12 | H55: Valor por defecto Tablas 10A.6 a 10A.9 directrices IPCC V4, Otros al no ser relevante suma los demás sistemas no considerados individualmente | I55: Fracción correspondiente a cada sistema de gestión, considerando valores promedio, datos por defecto tabla 10.22 V4 CH21 | J55: Fracción correspondiente a cada sistema de gestión, considerando valores promedio, datos por defecto tabla 10.22 V4 CH21 | K55: Factor de emisión por defecto tablas 11.3 directrices IPCC V4 CH11, considera valor agregado por default | L55: Factor de emisión por defecto tablas 11.3 directrices IPCC V4 CH11, considera valor agregado por default | M55: .
... C58: Pavos | E58: ESPAC 2018 , tabla 62,63 | F58: Se obtiene por defecto de la tabla 10.19 directrices IPCC V4, para todas las regiones se considera productividad baja (relacionando sistemas de producción referenciados en las directrices IPCC) | G58: Valor por defecto directrices IPCC tabla 10A.15 | H58: Valor por defecto Tablas 10A.6 a 10A.9 directrices IPCC V4, Otros al no ser relevante suma los demás sistemas no considerados individualmente | I58: Fracción correspondiente a cada sistema de gestión, considerando valores promedio, datos por defecto tabla 10.22 V4 CH24 | J58: Fracción correspondiente a cada sistema de gestión, considerando valores promedio, datos por defecto tabla 10.22 V4 CH24 | K58: Factor de emisión por defecto tablas 11.3 directrices IPCC V4 CH11, considera valor agregado por default | L58: Factor de emisión por defecto tablas 11.3 directrices IPCC V4 CH11, considera valor agregado por default | M58: .

Sheet 3C7 Arroz
C3: EMISIONES DE METANO POR CULTIVO DE ARROZ | I3: INDICE
V4: Las mejoras en la estimación de las emisiones de CH4 del cultivo de arroz incluyen actualizaciones sobre lo siguiente: (i) línea de base
C5: Sector | D5: Agricultura | N5: Sector | O5: Agricultura | V5: factor de emisión (EFc) a escala global (con nuevos valores predeterminados a escala regional); (ii) factores de escala para el agua
C6: Categoría | D6: Cultivo de Arroz: Emisiones anuales de Metano CH4 | N6: Categoría | O6: Cultivo de Arroz: Emisiones anuales de Metano CH4 | V6: regímenes antes y durante los períodos de cultivo; y (iii) factores de conversión predeterminados para diferentes tipos de
C7: Código de Categoría | D7: 3C7 | N7: Código de Categoría | O7: 3C7 | V7: enmiendas orgánicas. Se proporciona una nueva tabla sobre los períodos de cultivo predeterminados, a escala global y regional, y una
C8: Tabla | D8: 1 de 2 | N8: Tabla | O8: 2 de 2 | V8: Nueva sección que muestra un ejemplo de cómo implementar el método de Nivel 1. También se incluye una caja nueva en buen estado.
C9: Ecuación | D9: Eq. 2.2 | E9: Ecuación 5.1 | G9: Ecuación 5.2 | J9: Ecuación 5.3 | L9: Ecuación 5.3 | N9: Ecuación | O9: Ecuación 2.2 | Q9: Ecuación 5.1 | V9: Guía práctica para desarrollar EFc.
C10: Ecosistema de arroz | D10: Subcategorías para el año del informe1 (porcentaje de superficie por cada ecosistema) | E10: Area Cosechada Anual | F10: Periodo de cultivo del arroz | G10: Factor de emisión de línea de base para campos continuamente inundados sin enmiendas orgánicas | H10: Factor de escala para tener en cuenta las diferencias en el régimen del agua durante el período de cultivo | I10: Factor de escala para tener en cuenta las diferencias en el régimen hídrico en la pretemporada antes del período de cultivo | J10: Ratio de aplicación de enmienda orgánica en el cultivo | K10: Factor de conversión de enmienda orgánica | L10: Factor de escala para ambos tipos y cantidad de enmienda orgánica aplicada | N10: Ecosistema de arroz | O10: Subcategorías para el año del informe1 | P10: Factor de emisión diario ajustado para un área cosechada en particular | Q10: Emisión Anual de Metano CH4 del cultivo de arroz
E11: (ha yr-1) | F11: (day) | G11: kg CH4 ha-1 day-1 | H11: (-) | I11: (-) | J11: (tonnes ha-1) | L11: (tonnes ha-1) | P11: (kg CH4 ha-1 day-1) | Q11: Gg CH4 yr-1
G12: tabla 5.11 | H12: tabla 5.12 | I12: tabla 5.13 | K12: tabla 5.14 | L12: SFo = | P12: EFi = EFc * SFw * SFp * SFo * SFs,r | Q12: CH4Rice = A * t * EFi * 10-6
L13: (1+ROAi * CFOAi)0.58
E14: A | F14: t | G14: EFc | H14: SFW | I14: SFp | J14: ROAi | K14: CFOAi | L14: SFo | P14: EFi | Q14: CH4Rice
C15: Irrigados - inundados intermitentemente -aireación multiple | E15: ='Datos de Actividad'!AA50 -> 84518.84 | F15: 124 | G15: 1.27 | H15: 0.55 | I15: 1.22 | J15: ='Datos de Actividad'!AJ170 -> 0.0053806392 | K15: 0.21 | L15: =(1+J15*K15)^0.59 -> 1.0006665 | N15: Irrigados - inundados intermitentemente -aireación multiple | P15: =G15*H15*I15*L15 -> 0.85273798 | Q15: =(E15)*F15*P15*(10^-6) -> 8.9369806
D17: Sub-total | O17: Sub-total
C18: Secano y aguas profundas -alimentación por lluvia | E18: ='Datos de Actividad'!AA51 -> 135833.85 | F18: 124 | G18: 1.27 | H18: 0.54 | I18: 2.41 | J18: =J15 -> 0.0053806392 | K18: 0.21 | L18: =(1+J18*K18)^0.59 -> 1.0006665 | N18: Secano y aguas profundas -alimentación por lluvia | P18: =G18*H18*I18*L18 -> 1.6538796 | Q18: =(E18)*F18*P18*(10^-6) -> 27.856951
D20: Sub-total | O20: Sub-total
C21: Secano y aguas profundas -aguas profundas | E21: ='Datos de Actividad'!AA53 -> 81500.31 | F21: 124 | G21: 1.27 | H21: 0.06 | I21: 1.22 | J21: =J18 -> 0.0053806392 | K21: 0.21 | L21: =(1+J21*K21)^0.59 -> 1.0006665 | N21: Secano y aguas profundas -aguas profundas | P21: =G21*H21*I21*L21 -> 0.093025961 | Q21: =(E21)*F21*P21*(10^-6) -> 0.94012393
D23: Sub-total | O23: Sub-total
C24: Total | E24: =E15+E18+E21 -> 301853 | N24: Total | Q24: =SUM(Q15:Q23) -> 37.734056
C25: 1 El ecosistema del arroz se puede estratificar según los regímenes hídricos, el tipo y la cantidad de enmiendas orgánicas y otras condiciones en las que las emisiones de CH4 del arroz pueden variar. | N25: 1 La tierra debe estratificarse según los ecosistemas, los regímenes de agua, el tipo y la cantidad de enmiendas orgánicas y otras condiciones en las que las emisiones de CH4 del arroz pueden variar. La desagregación del área de cosecha anual de arroz debe realizarse al menos para tres regímenes de agua de referencia, incluidos los de regadío, de secano y de tierras altas. Dentro de cada estrato, los subestratos deben separarse para cada tipo de enmienda orgánica (ver Ecuación 5.3)
C29: NOTA EXPLICATIVA CATEGORIA CULTIVO DE ARROZ
C30: Dato | E30: Tipo | F30: Fuente | G30: Observaciones
C31: Area Cosechada Anual -- Irrigado | E31: Dato de Actividad | F31: El dato base total se toma de la ESPAC 2018 (fuente mas consistente) y la desagregación por tipo de ecosistema se calcula según los reportes de estimaciones de producción de arroz en base a imágenes satelitales del MAG por cuatrimestre, aplcando los porcentajes de area cultivada respecto del total anual por cada periodo, al dato de la ESPAC | G31: La asignación de ecosistemas fue conversada y definida con especialistas del MAG según las caracteristicas de producción en cada cuatrimestre reportado, los % de area cultivada según el MAG son aplicados al total generado en la ESPAC. | J31: . | L31: . | U31: .
C32: Area Cosechada Anual -- Aguas profundas | E32: Dato de Actividad | F32: El dato base total se toma de la ESPAC 2018 (fuente mas consistente) y la desagregación por tipo de ecosistema se calcula según los reportes de estimaciones de producción de arroz en base a imágenes satelitales del MAG por cuatrimestre, aplcando los porcentajes de area cultivada respecto del total anual por cada periodo, al dato de la ESPAC | G32: La asignación de ecosistemas fue conversada y definida con especialistas del MAG según las caracteristicas de producción en cada cuatrimestre reportado, los % de area cultivada según el MAG son aplicados al total generado en la ESPAC. | J32: . | L32: . | U32: .
C33: Area Cosechada Anual -- Tierras Altas | E33: Dato de Actividad | F33: El dato base total se toma de la ESPAC 2018 (fuente mas consistente) y la desagregación por tipo de ecosistema se calcula según los reportes de estimaciones de producción de arroz en base a imágenes satelitales del MAG por cuatrimestre, aplcando los porcentajes de area cultivada respecto del total anual por cada periodo, al dato de la ESPAC | G33: La asignación de ecosistemas fue conversada y definida con especialistas del MAG según las caracteristicas de producción en cada cuatrimestre reportado, los % de area cultivada según el MAG son aplicados al total generado en la ESPAC. | J33: . | L33: . | U33: .
